Workbook
Name DATOS: #REF!
Name Print_Area: 'Gerencia de Infraestructura'!$A$1:$I$905
Name Print_Area: 'Gerencias y Oficinas'!$A$1:$I$314
Name Print_Area: PECSA!$A$1:$I$13
Name Print_Titles: DEPI!$1:$5
Name Print_Titles: DS!$1:$6
Name Print_Titles: 'Gerencia de Infraestructura'!$1:$6
Name Print_Titles: 'Gerencias y Oficinas'!$1:$5
Name Print_Titles: GRDE!$1:$6
Name Print_Titles: GRRNyDA!$1:$6
Name Print_Titles: PECSA!$1:$5
Name Print_Titles: PETT!$1:$5

Sheet Gerencia de Infraestructura
C1: ANEXO N° 01
A2: ="COMPORTAMIENTO DE EJECUCIÓN DE PROYECTOS DE INVERSIÓN PÚBLICA 2026 - U.E. 001 SEDE CENTRAL AL "&TEXT(SIAF!B3,"dd/mm/yyyy") -> COMPORTAMIENTO DE EJECUCIÓN DE PROYECTOS DE INVERSIÓN PÚBLICA 2026 - U.E. 001 SEDE CENTRAL AL 06/10/2026
A3: N° | B3: META | C3: PROYECTO | D3: PIM 2026 (A) | E3: CERTIFICACIÓN (B) | F3: SALDO (A-B) | G3: DEVENGADO ( C ) | H3: SALDO (A-C) | I3: AVANCE DEVEN % | J3: MODALIDAD DE EJECUCIÓN | K3: ESTADO SITUACIONAL DEL PROYECTO | L3: Monto Año 2026 (S/) | M3: Monto Año 2027 (S/) | N3: Monto Año 2028 (S/) | O3: Monto Año 2029 (S/)
A5: 001. REGION PUNO-SEDE CENTRAL | D5: ='Gerencias y Oficinas'!D314 -> 905026984 | E5: ='Gerencias y Oficinas'!E314 -> 8.4314313e+08 | F5: ='Gerencias y Oficinas'!F314 -> 61883857 | G5: ='Gerencias y Oficinas'!G314 -> 4.3357577e+08 | H5: ='Gerencias y Oficinas'!H314 -> 4.7145121e+08 | I5: ='Gerencias y Oficinas'!I314 -> 0.47907497
A6: GERENCIA DE INFRAESTRUCTURA | D6: =D10+D11+D13+D14+D15+D16+D17+D18+D19+D20+D21+D22+D23+D24+D25+D26+D27+D28+D29+D30+D31+D32+D33+D34+D35+D37+D38+D39+D41+D42+D43+D44+D45+D46+D47+D48+D49+D50+D51+D52+D53+D54+D55+D56+D57+D58+D59+D60+D61+D62+D63+D64+D66+D67+D68+D69+D70+D71+D72+D73+D74+D76+D79+D130+D131+D132+D133+D134+D135+D137+D138+D139+D140+D141+D142+D143+D144+D145+D146+D147+D148+D149+D150+D151+D152+D153+D154+D155+D156+D158+D159+D160+D161+D162+D163+D164+D165+D166+D167+D169+D170+D171+D177+D178+D179+D180+D181+D182+D183+D184+D185+D188+D189+D190+D191+D192+D193+D194+D195+D196+D197+D199+D201+D202+D204+D212+D216+D219+D222+D224+D227+D229+D231+D233+D235+D237+D241+D243+D245+D249+D251+D253+D255+D257+D259+D263+D265+D272+D275+D277+D279+D281+D283+D285+D287+D289+D291+D293+D295+D297+D300+D302+D305+D309+D312+D314+D316+D319+D322+D325+D558+D561+D566+D569+D574+D577+D580+D582+D585+D588+D591+D594+D597+D600+D603+D606+D609+D611+D620+D622+D625+D627+D630+D633+D636+D638+D641+D644+D647+D650+D653+D656+D661+D664+D667+D670+D673+D676+D680+D683+D686+D689+D692+D695+D698+D700+D702+D705+D708+D711+D714+D716+D719+D721+D724+D726+D728+D731+D734+D737+D740+D742+D745+D752+D754+D767+D770+D773+D776+D779+D781+D787+D790+D793+D796+D800+D803+D806+D809+D812+D815+D818+D821+D824+D827+D830+D833+D836+D839+D843+D846+D849+D852+D855+D858+D861+D864+D867+D870+D874+D877+D880+D883+D887+D889+D891+D894+D897+D900+D903 -> 770071302 | E6: =E10+E11+E13+E14+E15+E16+E17+E18+E19+E20+E21+E22+E23+E24+E25+E26+E27+E28+E29+E30+E31+E32+E33+E34+E35+E37+E38+E39+E41+E42+E43+E44+E45+E46+E47+E48+E49+E50+E51+E52+E53+E54+E55+E56+E57+E58+E59+E60+E61+E62+E63+E64+E66+E67+E68+E69+E70+E71+E72+E73+E74+E76+E79+E130+E131+E132+E133+E134+E135+E137+E138+E139+E140+E141+E142+E143+E144+E145+E146+E147+E148+E149+E150+E151+E152+E153+E154+E155+E156+E158+E159+E160+E161+E162+E163+E164+E165+E166+E167+E169+E170+E171+E177+E178+E179+E180+E181+E182+E183+E184+E185+E188+E189+E190+E191+E192+E193+E194+E195+E196+E197+E199+E201+E202+E204+E212+E216+E219+E222+E224+E227+E229+E231+E233+E235+E237+E241+E243+E245+E249+E251+E253+E255+E257+E259+E263+E265+E272+E275+E277+E279+E281+E283+E285+E287+E289+E291+E293+E295+E297+E300+E302+E305+E309+E312+E314+E316+E319+E322+E325+E558+E561+E566+E569+E574+E577+E580+E582+E585+E588+E591+E594+E597+E600+E603+E606+E609+E611+E620+E622+E625+E627+E630+E633+E636+E638+E641+E644+E647+E650+E653+E656+E661+E664+E667+E670+E673+E676+E680+E683+E686+E689+E692+E695+E698+E700+E702+E705+E708+E711+E714+E716+E719+E721+E724+E726+E728+E731+E734+E737+E740+E742+E745+E752+E754+E767+E770+E773+E776+E779+E781+E787+E790+E793+E796+E800+E803+E806+E809+E812+E815+E818+E821+E824+E827+E830+E833+E836+E839+E843+E846+E849+E852+E855+E858+E861+E864+E867+E870+E874+E877+E880+E883+E887+E889+E891+E894+E897+E900+E903 -> 7.2264955e+08 | F6: =D6-E6 -> 47421747 | G6: =G10+G11+G13+G14+G15+G16+G17+G18+G19+G20+G21+G22+G23+G24+G25+G26+G27+G28+G29+G30+G31+G32+G33+G34+G35+G37+G38+G39+G41+G42+G43+G44+G45+G46+G47+G48+G49+G50+G51+G52+G53+G54+G55+G56+G57+G58+G59+G60+G61+G62+G63+G64+G66+G67+G68+G69+G70+G71+G72+G73+G74+G76+G79+G130+G131+G132+G133+G134+G135+G137+G138+G139+G140+G141+G142+G143+G144+G145+G146+G147+G148+G149+G150+G151+G152+G153+G154+G155+G156+G158+G159+G160+G161+G162+G163+G164+G165+G166+G167+G169+G170+G171+G177+G178+G179+G180+G181+G182+G183+G184+G185+G188+G189+G190+G191+G192+G193+G194+G195+G196+G197+G199+G201+G202+G204+G212+G216+G219+G222+G224+G227+G229+G231+G233+G235+G237+G241+G243+G245+G249+G251+G253+G255+G257+G259+G263+G265+G272+G275+G277+G279+G281+G283+G285+G287+G289+G291+G293+G295+G297+G300+G302+G305+G309+G312+G314+G316+G319+G322+G325+G558+G561+G566+G569+G574+G577+G580+G582+G585+G588+G591+G594+G597+G600+G603+G606+G609+G611+G620+G622+G625+G627+G630+G633+G636+G638+G641+G644+G647+G650+G653+G656+G661+G664+G667+G670+G673+G676+G680+G683+G686+G689+G692+G695+G698+G700+G702+G705+G708+G711+G714+G716+G719+G721+G724+G726+G728+G731+G734+G737+G740+G742+G745+G752+G754+G767+G770+G773+G776+G779+G781+G787+G790+G793+G796+G800+G803+G806+G809+G812+G815+G818+G821+G824+G827+G830+G833+G836+G839+G843+G846+G849+G852+G855+G858+G861+G864+G867+G870+G874+G877+G880+G883+G887+G889+G891+G894+G897+G900+G903 -> 3.8172744e+08 | H6: =D6-G6 -> 3.8834387e+08 | I6: =IF(D6=0,0,G6/D6) -> 0.49570402
A7: EJECUCIÓN POR ADMINISTRACIÓN DIRECTA | D7: =D10+D11+D13+D14+D15+D16+D17+D18+D19+D20+D21+D22+D23+D24+D25+D26+D27+D28+D29+D30+D31+D32+D33+D34+D35+D37+D38+D39+D41+D42+D43+D44+D45+D46+D47+D48+D49+D50+D51+D52+D53+D54+D55+D56+D57+D58+D59+D60+D61+D62+D63+D64+D66+D67+D68+D69+D70+D71+D72+D73+D74+D76+D79+D130+D131+D132+D133+D134+D135+D137+D138+D139+D140+D141+D142+D143+D144+D145+D146+D147+D148+D149+D150+D151+D152+D153+D154+D155+D156+D158+D159+D160+D161+D162+D163+D164+D165+D166+D167+D169+D170+D171 -> 501723065 | E7: =E10+E11+E13+E14+E15+E16+E17+E18+E19+E20+E21+E22+E23+E24+E25+E26+E27+E28+E29+E30+E31+E32+E33+E34+E35+E37+E38+E39+E41+E42+E43+E44+E45+E46+E47+E48+E49+E50+E51+E52+E53+E54+E55+E56+E57+E58+E59+E60+E61+E62+E63+E64+E66+E67+E68+E69+E70+E71+E72+E73+E74+E76+E79+E130+E131+E132+E133+E134+E135+E137+E138+E139+E140+E141+E142+E143+E144+E145+E146+E147+E148+E149+E150+E151+E152+E153+E154+E155+E156+E158+E159+E160+E161+E162+E163+E164+E165+E166+E167+E169+E170+E171 -> 4.7258296e+08 | F7: =D7-E7 -> 29140105 | G7: =G10+G11+G13+G14+G15+G16+G17+G18+G19+G20+G21+G22+G23+G24+G25+G26+G27+G28+G29+G30+G31+G32+G33+G34+G35+G37+G38+G39+G41+G42+G43+G44+G45+G46+G47+G48+G49+G50+G51+G52+G53+G54+G55+G56+G57+G58+G59+G60+G61+G62+G63+G64+G66+G67+G68+G69+G70+G71+G72+G73+G74+G76+G79+G130+G131+G132+G133+G134+G135+G137+G138+G139+G140+G141+G142+G143+G144+G145+G146+G147+G148+G149+G150+G151+G152+G153+G154+G155+G156+G158+G159+G160+G161+G162+G163+G164+G165+G166+G167+G169+G170+G171 -> 2.5907445e+08 | H7: =D7-G7 -> 2.4264861e+08 | I7: =IF(D7=0,0,G7/D7) -> 0.51636943
A8: EJECUCIÓN POR ADMINISTRACIÓN DIRECTA - DIRECTIVA 10 | D8: =D10+D11+D13+D14+D15+D16+D17+D18+D19+D20+D21+D22+D23+D24+D25+D26+D27+D28+D29+D30+D31+D32+D33+D34+D35+D37+D38+D39+D41+D42+D43+D44+D45+D46+D47+D48+D49+D50+D51+D52+D53+D54+D55+D56+D57+D58+D59+D60+D61+D62+D63+D64+D66+D67+D68+D69+D70+D71+D72+D73+D74+D76+D79 -> 234326742 | E8: =E10+E11+E13+E14+E15+E16+E17+E18+E19+E20+E21+E22+E23+E24+E25+E26+E27+E28+E29+E30+E31+E32+E33+E34+E35+E37+E38+E39+E41+E42+E43+E44+E45+E46+E47+E48+E49+E50+E51+E52+E53+E54+E55+E56+E57+E58+E59+E60+E61+E62+E63+E64+E66+E67+E68+E69+E70+E71+E72+E73+E74+E76+E79 -> 2.2363717e+08 | F8: =D8-E8 -> 10689571 | G8: =G10+G11+G13+G14+G15+G16+G17+G18+G19+G20+G21+G22+G23+G24+G25+G26+G27+G28+G29+G30+G31+G32+G33+G34+G35+G37+G38+G39+G41+G42+G43+G44+G45+G46+G47+G48+G49+G50+G51+G52+G53+G54+G55+G56+G57+G58+G59+G60+G61+G62+G63+G64+G66+G67+G68+G69+G70+G71+G72+G73+G74+G76+G79 -> 99970240 | H8: =D8-G8 -> 1.343565e+08 | I8: =IF(D8=0,0,G8/D8) -> 0.42662753
A9: 20. SALUD | D9: =D10+D11 -> 53926751 | E9: =E10+E11 -> 53909348 | F9: =D9-E9 -> 17402.8 | G9: =G10+G11 -> 364124.26 | H9: =D9-G9 -> 53562627 | I9: =IF(D9=0,0,G9/D9) -> 0.006752201
A10: =SUBTOTAL(103,$B$10:B10) -> 1 | B10: 1 | C10: 2108576: CONSTRUCCION DEL HOSPITAL MATERNO INFANTIL DEL CONO SUR JULIACA | D10: =IF(COUNTIF(tSIAF[Clave],"2108576|1")=0,"",SUMIF(tSIAF[Clave],"2108576|1",tSIAF[PIM])) -> 167354 | E10: =IF(COUNTIF(tSIAF[Clave],"2108576|1")=0,"",SUMIF(tSIAF[Clave],"2108576|1",tSIAF[Certificacion])) -> 149951.3 | F10: =IF(D10="","",D10-E10) -> 17402.7 | G10: =IF(COUNTIF(tSIAF[Clave],"2108576|1")=0,"",SUMIF(tSIAF[Clave],"2108576|1",tSIAF[Devengado])) -> 102781.21 | H10: =IF(D10="","",D10-G10) -> 64572.79 | I10: =IF(D10="","",IF(D10=0,0,G10/D10)) -> 0.61415449 | J10: EJECUCIÓN POR ADMINISTRACIÓN DIRECTA - DIRECTIVA 10 | K10: Por completar | L10: =IF(COUNTIF(tCartera[CUI],"2108576")=0,"Sin PMI",IF(INDEX(tCartera[PMI2026],MATCH("2108576",tCartera[CUI],0))="","No informado",INDEX(tCartera[PMI2026],MATCH("2108576",tCartera[CUI],0)))) -> 12460540 | M10: =IF(COUNTIF(tCartera[CUI],"2108576")=0,"Sin PMI",IF(INDEX(tCartera[PMI2027],MATCH("2108576",tCartera[CUI],0))="","No informado",INDEX(tCartera[PMI2027],MATCH("2108576",tCartera[CUI],0)))) -> 5731000 | N10: =IF(COUNTIF(tCartera[CUI],"2108576")=0,"Sin PMI",IF(INDEX(tCartera[PMI2028],MATCH("2108576",tCartera[CUI],0))="","No informado",INDEX(tCartera[PMI2028],MATCH("2108576",tCartera[CUI],0)))) -> 5000000 | O10: =IF(COUNTIF(tCartera[CUI],"2108576")=0,"Sin PMI",IF(INDEX(tCartera[PMI2029],MATCH("2108576",tCartera[CUI],0))="","No informado",INDEX(tCartera[PMI2029],MATCH("2108576",tCartera[CUI],0)))) -> 5000000
A11: =SUBTOTAL(103,$B$10:B11) -> 2 | B11: 220 | C11: 2279375: MEJORAMIENTO DE LOS SERVICIOS DE SALUD DEL HOSPITAL DE APOYO ILAVE, PROVINCIA DE EL COLLAO - REGION PUNO | D11: =IF(COUNTIF(tSIAF[Clave],"2279375|220")=0,"",SUMIF(tSIAF[Clave],"2279375|220",tSIAF[PIM])) -> 53759397 | E11: =IF(COUNTIF(tSIAF[Clave],"2279375|220")=0,"",SUMIF(tSIAF[Clave],"2279375|220",tSIAF[Certificacion])) -> 53759397 | F11: =IF(D11="","",D11-E11) -> 0.1 | G11: =IF(COUNTIF(tSIAF[Clave],"2279375|220")=0,"",SUMIF(tSIAF[Clave],"2279375|220",tSIAF[Devengado])) -> 261343.05 | H11: =IF(D11="","",D11-G11) -> 53498054 | I11: =IF(D11="","",IF(D11=0,0,G11/D11)) -> 0.0048613464 | J11: EJECUCIÓN POR ADMINISTRACIÓN DIRECTA - DIRECTIVA 10 | K11: Por completar | L11: =IF(COUNTIF(tCartera[CUI],"2279375")=0,"Sin PMI",IF(INDEX(tCartera[PMI2026],MATCH("2279375",tCartera[CUI],0))="","No informado",INDEX(tCartera[PMI2026],MATCH("2279375",tCartera[CUI],0)))) -> Sin PMI | M11: =IF(COUNTIF(tCartera[CUI],"2279375")=0,"Sin PMI",IF(INDEX(tCartera[PMI2027],MATCH("2279375",tCartera[CUI],0))="","No informado",INDEX(tCartera[PMI2027],MATCH("2279375",tCartera[CUI],0)))) -> Sin PMI | N11: =IF(COUNTIF(tCartera[CUI],"2279375")=0,"Sin PMI",IF(INDEX(tCartera[PMI2028],MATCH("2279375",tCartera[CUI],0))="","No informado",INDEX(tCartera[PMI2028],MATCH("2279375",tCartera[CUI],0)))) -> Sin PMI | O11: =IF(COUNTIF(tCartera[CUI],"2279375")=0,"Sin PMI",IF(INDEX(tCartera[PMI2029],MATCH("2279375",tCartera[CUI],0))="","No informado",INDEX(tCartera[PMI2029],MATCH("2279375",tCartera[CUI],0)))) -> Sin PMI
A12: 22. EDUCACION | D12: =D13+D14+D15+D16+D17+D18+D19+D20+D21+D22+D23+D24+D25+D26+D27+D28+D29+D30+D31+D32+D33+D34+D35+D37+D38+D39 -> 60810433 | E12: =E13+E14+E15+E16+E17+E18+E19+E20+E21+E22+E23+E24+E25+E26+E27+E28+E29+E30+E31+E32+E33+E34+E35+E37+E38+E39 -> 57496092 | F12: =D12-E12 -> 3314341 | G12: =G13+G14+G15+G16+G17+G18+G19+G20+G21+G22+G23+G24+G25+G26+G27+G28+G29+G30+G31+G32+G33+G34+G35+G37+G38+G39 -> 35508320 | H12: =D12-G12 -> 25302113 | I12: =IF(D12=0,0,G12/D12) -> 0.58391822
A13: =SUBTOTAL(103,$B$10:B13) -> 3 | B13: 223 | C13: 2323700: MEJORAMIENTO DEL SERVICIO EDUCATIVO DE LAS CARRERAS DE PRODUCCION, AUTOMOTRIZ, MINERIA, CONTABILIDAD, COMPUTACION, SECRETARIADO, ENFERMERIA, LABORATORIO CLINICO Y PROTESIS DENTAL DEL IST MANUEL NUÑEZ BUTRON, JULIACA, SAN ROMAN - PUNO | D13: =IF(COUNTIF(tSIAF[Clave],"2323700|223")=0,"",SUMIF(tSIAF[Clave],"2323700|223",tSIAF[PIM])) -> 10519577 | E13: =IF(COUNTIF(tSIAF[Clave],"2323700|223")=0,"",SUMIF(tSIAF[Clave],"2323700|223",tSIAF[Certificacion])) -> 10386241 | F13: =IF(D13="","",D13-E13) -> 133335.78 | G13: =IF(COUNTIF(tSIAF[Clave],"2323700|223")=0,"",SUMIF(tSIAF[Clave],"2323700|223",tSIAF[Devengado])) -> 7596372.7 | H13: =IF(D13="","",D13-G13) -> 2923204.3 | I13: =IF(D13="","",IF(D13=0,0,G13/D13)) -> 0.72211769 | J13: EJECUCIÓN POR ADMINISTRACIÓN DIRECTA - DIRECTIVA 10 | K13: Por completar | L13: =IF(COUNTIF(tCartera[CUI],"2323700")=0,"Sin PMI",IF(INDEX(tCartera[PMI2026],MATCH("2323700",tCartera[CUI],0))="","No informado",INDEX(tCartera[PMI2026],MATCH("2323700",tCartera[CUI],0)))) -> 2546207 | M13: =IF(COUNTIF(tCartera[CUI],"2323700")=0,"Sin PMI",IF(INDEX(tCartera[PMI2027],MATCH("2323700",tCartera[CUI],0))="","No informado",INDEX(tCartera[PMI2027],MATCH("2323700",tCartera[CUI],0)))) -> 638376 | N13: =IF(COUNTIF(tCartera[CUI],"2323700")=0,"Sin PMI",IF(INDEX(tCartera[PMI2028],MATCH("2323700",tCartera[CUI],0))="","No informado",INDEX(tCartera[PMI2028],MATCH("2323700",tCartera[CUI],0)))) -> 2568939 | O13: =IF(COUNTIF(tCartera[CUI],"2323700")=0,"Sin PMI",IF(INDEX(tCartera[PMI2029],MATCH("2323700",tCartera[CUI],0))="","No informado",INDEX(tCartera[PMI2029],MATCH("2323700",tCartera[CUI],0)))) -> 0
A14: =SUBTOTAL(103,$B$10:B14) -> 4 | B14: 224 | C14: 2335880: MEJORAMIENTO DEL SERVICIO EDUCATIVO DE LAS CARRERAS DE CONTABILIDAD, ENFERMERIA TECNICA, COMPUTACION E INFORMATICA, INDUSTRIA ALIMENTARIA Y PRODUCCION AGROPECUARIA DEL ISEPA, PROVINCIA DE MELGAR - PUNO | D14: =IF(COUNTIF(tSIAF[Clave],"2335880|224")=0,"",SUMIF(tSIAF[Clave],"2335880|224",tSIAF[PIM])) -> 10208307 | E14: =IF(COUNTIF(tSIAF[Clave],"2335880|224")=0,"",SUMIF(tSIAF[Clave],"2335880|224",tSIAF[Certificacion])) -> 9968469.6 | F14: =IF(D14="","",D14-E14) -> 239837.38 | G14: =IF(COUNTIF(tSIAF[Clave],"2335880|224")=0,"",SUMIF(tSIAF[Clave],"2335880|224",tSIAF[Devengado])) -> 6440724.5 | H14: =IF(D14="","",D14-G14) -> 3767582.5 | I14: =IF(D14="","",IF(D14=0,0,G14/D14)) -> 0.63092974 | J14: EJECUCIÓN POR ADMINISTRACIÓN DIRECTA - DIRECTIVA 10 | K14: Por completar | L14: =IF(COUNTIF(tCartera[CUI],"2335880")=0,"Sin PMI",IF(INDEX(tCartera[PMI2026],MATCH("2335880",tCartera[CUI],0))="","No informado",INDEX(tCartera[PMI2026],MATCH("2335880",tCartera[CUI],0)))) -> 5597990 | M14: =IF(COUNTIF(tCartera[CUI],"2335880")=0,"Sin PMI",IF(INDEX(tCartera[PMI2027],MATCH("2335880",tCartera[CUI],0))="","No informado",INDEX(tCartera[PMI2027],MATCH("2335880",tCartera[CUI],0)))) -> 1254673 | N14: =IF(COUNTIF(tCartera[CUI],"2335880")=0,"Sin PMI",IF(INDEX(tCartera[PMI2028],MATCH("2335880",tCartera[CUI],0))="","No informado",INDEX(tCartera[PMI2028],MATCH("2335880",tCartera[CUI],0)))) -> 2493351 | O14: =IF(COUNTIF(tCartera[CUI],"2335880")=0,"Sin PMI",IF(INDEX(tCartera[PMI2029],MATCH("2335880",tCartera[CUI],0))="","No informado",INDEX(tCartera[PMI2029],MATCH("2335880",tCartera[CUI],0)))) -> 0
A15: =SUBTOTAL(103,$B$10:B15) -> 5 | B15: 245 | C15: 2521936: MEJORAMIENTO Y AMPLIACION DEL SERVICIO DE EDUCACION SUPERIOR TECNOLOGICA EN EL INSTITUTO SUPERIOR TECNOLOGICO PUBLICO DE MACUSANI DISTRITO DE MACUSANI - PROVINCIA DE CARABAYA - DEPARTAMENTO DE PUNO | D15: =IF(COUNTIF(tSIAF[Clave],"2521936|245")=0,"",SUMIF(tSIAF[Clave],"2521936|245",tSIAF[PIM])) -> 11203165 | E15: =IF(COUNTIF(tSIAF[Clave],"2521936|245")=0,"",SUMIF(tSIAF[Clave],"2521936|245",tSIAF[Certificacion])) -> 10889669 | F15: =IF(D15="","",D15-E15) -> 313496.41 | G15: =IF(COUNTIF(tSIAF[Clave],"2521936|245")=0,"",SUMIF(tSIAF[Clave],"2521936|245",tSIAF[Devengado])) -> 6395813.3 | H15: =IF(D15="","",D15-G15) -> 4807351.7 | I15: =IF(D15="","",IF(D15=0,0,G15/D15)) -> 0.57089343 | J15: EJECUCIÓN POR ADMINISTRACIÓN DIRECTA - DIRECTIVA 10 | K15: Por completar | L15: =IF(COUNTIF(tCartera[CUI],"2521936")=0,"Sin PMI",IF(INDEX(tCartera[PMI2026],MATCH("2521936",tCartera[CUI],0))="","No informado",INDEX(tCartera[PMI2026],MATCH("2521936",tCartera[CUI],0)))) -> 4902849 | M15: =IF(COUNTIF(tCartera[CUI],"2521936")=0,"Sin PMI",IF(INDEX(tCartera[PMI2027],MATCH("2521936",tCartera[CUI],0))="","No informado",INDEX(tCartera[PMI2027],MATCH("2521936",tCartera[CUI],0)))) -> 60001 | N15: =IF(COUNTIF(tCartera[CUI],"2521936")=0,"Sin PMI",IF(INDEX(tCartera[PMI2028],MATCH("2521936",tCartera[CUI],0))="","No informado",INDEX(tCartera[PMI2028],MATCH("2521936",tCartera[CUI],0)))) -> 2722594 | O15: =IF(COUNTIF(tCartera[CUI],"2521936")=0,"Sin PMI",IF(INDEX(tCartera[PMI2029],MATCH("2521936",tCartera[CUI],0))="","No informado",INDEX(tCartera[PMI2029],MATCH("2521936",tCartera[CUI],0)))) -> 0
A16: =SUBTOTAL(103,$B$10:B16) -> 6 | B16: 29 | C16: 2344324: MEJORAMIENTO DE LOS SERVICIOS EDUCATIVOS DE LA I.E.S. MANUEL GONZALES PRADA, CENTRO POBLADO DE ISANI - DISTRITO DE ZEPITA - PROVINCIA DE CHUCUITO - REGION PUNO | D16: =IF(COUNTIF(tSIAF[Clave],"2344324|29")=0,"",SUMIF(tSIAF[Clave],"2344324|29",tSIAF[PIM])) -> 2079431 | E16: =IF(COUNTIF(tSIAF[Clave],"2344324|29")=0,"",SUMIF(tSIAF[Clave],"2344324|29",tSIAF[Certificacion])) -> 1994037.5 | F16: =IF(D16="","",D16-E16) -> 85393.54 | G16: =IF(COUNTIF(tSIAF[Clave],"2344324|29")=0,"",SUMIF(tSIAF[Clave],"2344324|29",tSIAF[Devengado])) -> 1946470.9 | H16: =IF(D16="","",D16-G16) -> 132960.06 | I16: =IF(D16="","",IF(D16=0,0,G16/D16)) -> 0.9360594 | J16: EJECUCIÓN POR ADMINISTRACIÓN DIRECTA - DIRECTIVA 10 | K16: Por completar | L16: =IF(COUNTIF(tCartera[CUI],"2344324")=0,"Sin PMI",IF(INDEX(tCartera[PMI2026],MATCH("2344324",tCartera[CUI],0))="","No informado",INDEX(tCartera[PMI2026],MATCH("2344324",tCartera[CUI],0)))) -> 298669 | M16: =IF(COUNTIF(tCartera[CUI],"2344324")=0,"Sin PMI",IF(INDEX(tCartera[PMI2027],MATCH("2344324",tCartera[CUI],0))="","No informado",INDEX(tCartera[PMI2027],MATCH("2344324",tCartera[CUI],0)))) -> 349669 | N16: =IF(COUNTIF(tCartera[CUI],"2344324")=0,"Sin PMI",IF(INDEX(tCartera[PMI2028],MATCH("2344324",tCartera[CUI],0))="","No informado",INDEX(tCartera[PMI2028],MATCH("2344324",tCartera[CUI],0)))) -> 84977 | O16: =IF(COUNTIF(tCartera[CUI],"2344324")=0,"Sin PMI",IF(INDEX(tCartera[PMI2029],MATCH("2344324",tCartera[CUI],0))="","No informado",INDEX(tCartera[PMI2029],MATCH("2344324",tCartera[CUI],0)))) -> 0
A17: =SUBTOTAL(103,$B$10:B17) -> 7 | B17: 315 | C17: 2490075: MEJORAMIENTO DEL SERVICIO EDUCATIVO DEL NIVEL SECUNDARIA DE LA I.E. AGROPECUARIO SAN JUAN DEL ORO EN EL DISTRITO DE SAN JUAN DEL ORO - PROVINCIA DE SANDIA - DEPARTAMENTO DE PUNO | D17: =IF(COUNTIF(tSIAF[Clave],"2490075|315")=0,"",SUMIF(tSIAF[Clave],"2490075|315",tSIAF[PIM])) -> 1425006 | E17: =IF(COUNTIF(tSIAF[Clave],"2490075|315")=0,"",SUMIF(tSIAF[Clave],"2490075|315",tSIAF[Certificacion])) -> 1239788.9 | F17: =IF(D17="","",D17-E17) -> 185217.1 | G17: =IF(COUNTIF(tSIAF[Clave],"2490075|315")=0,"",SUMIF(tSIAF[Clave],"2490075|315",tSIAF[Devengado])) -> 1170437 | H17: =IF(D17="","",D17-G17) -> 254569.02 | I17: =IF(D17="","",IF(D17=0,0,G17/D17)) -> 0.82135583 | J17: EJECUCIÓN POR ADMINISTRACIÓN DIRECTA - DIRECTIVA 10 | K17: Por completar | L17: =IF(COUNTIF(tCartera[CUI],"2490075")=0,"Sin PMI",IF(INDEX(tCartera[PMI2026],MATCH("2490075",tCartera[CUI],0))="","No informado",INDEX(tCartera[PMI2026],MATCH("2490075",tCartera[CUI],0)))) -> 1122019 | M17: =IF(COUNTIF(tCartera[CUI],"2490075")=0,"Sin PMI",IF(INDEX(tCartera[PMI2027],MATCH("2490075",tCartera[CUI],0))="","No informado",INDEX(tCartera[PMI2027],MATCH("2490075",tCartera[CUI],0)))) -> 0 | N17: =IF(COUNTIF(tCartera[CUI],"2490075")=0,"Sin PMI",IF(INDEX(tCartera[PMI2028],MATCH("2490075",tCartera[CUI],0))="","No informado",INDEX(tCartera[PMI2028],MATCH("2490075",tCartera[CUI],0)))) -> 32869 | O17: =IF(COUNTIF(tCartera[CUI],"2490075")=0,"Sin PMI",IF(INDEX(tCartera[PMI2029],MATCH("2490075",tCartera[CUI],0))="","No informado",INDEX(tCartera[PMI2029],MATCH("2490075",tCartera[CUI],0)))) -> 0
A18: =SUBTOTAL(103,$B$10:B18) -> 8 | B18: 160 | C18: 2570978: MEJORAMIENTO DE LOS SERVICIOS DE EDUCACION SUPERIOR DEL INSTITUTO SUPERIOR TECNOLOGICO PUBLICA DE CABANILLAS DEL DISTRITO DE CABANILLAS - PROVINCIA DE SAN ROMAN - DEPARTAMENTO DE PUNO | D18: =IF(COUNTIF(tSIAF[Clave],"2570978|160")=0,"",SUMIF(tSIAF[Clave],"2570978|160",tSIAF[PIM])) -> 9222405 | E18: =IF(COUNTIF(tSIAF[Clave],"2570978|160")=0,"",SUMIF(tSIAF[Clave],"2570978|160",tSIAF[Certificacion])) -> 9003232.5 | F18: =IF(D18="","",D18-E18) -> 219172.47 | G18: =IF(COUNTIF(tSIAF[Clave],"2570978|160")=0,"",SUMIF(tSIAF[Clave],"2570978|160",tSIAF[Devengado])) -> 5421356.6 | H18: =IF(D18="","",D18-G18) -> 3801048.4 | I18: =IF(D18="","",IF(D18=0,0,G18/D18)) -> 0.58784629 | J18: EJECUCIÓN POR ADMINISTRACIÓN DIRECTA - DIRECTIVA 10 | K18: Por completar | L18: =IF(COUNTIF(tCartera[CUI],"2570978")=0,"Sin PMI",IF(INDEX(tCartera[PMI2026],MATCH("2570978",tCartera[CUI],0))="","No informado",INDEX(tCartera[PMI2026],MATCH("2570978",tCartera[CUI],0)))) -> 2595053 | M18: =IF(COUNTIF(tCartera[CUI],"2570978")=0,"Sin PMI",IF(INDEX(tCartera[PMI2027],MATCH("2570978",tCartera[CUI],0))="","No informado",INDEX(tCartera[PMI2027],MATCH("2570978",tCartera[CUI],0)))) -> 255676 | N18: =IF(COUNTIF(tCartera[CUI],"2570978")=0,"Sin PMI",IF(INDEX(tCartera[PMI2028],MATCH("2570978",tCartera[CUI],0))="","No informado",INDEX(tCartera[PMI2028],MATCH("2570978",tCartera[CUI],0)))) -> 1817178 | O18: =IF(COUNTIF(tCartera[CUI],"2570978")=0,"Sin PMI",IF(INDEX(tCartera[PMI2029],MATCH("2570978",tCartera[CUI],0))="","No informado",INDEX(tCartera[PMI2029],MATCH("2570978",tCartera[CUI],0)))) -> 0
A19: =SUBTOTAL(103,$B$10:B19) -> 9 | B19: 162 | C19: 2591926: MEJORAMIENTO SERVICIO DE EDUCACION SUPERIOR TECNOLOGICA EN EL INSTITUTO SUPERIOR TECNOLOGICO PUBLICO JOSE DOMINGO CHOQUEHUANCA DEL DISTRITO DE JOSE DOMINGO CHOQUEHUANCA DE LA PROVINCIA DE AZANGARO DEL DEPARTAMENTO DE PUNO | D19: =IF(COUNTIF(tSIAF[Clave],"2591926|162")=0,"",SUMIF(tSIAF[Clave],"2591926|162",tSIAF[PIM])) -> 5194033 | E19: =IF(COUNTIF(tSIAF[Clave],"2591926|162")=0,"",SUMIF(tSIAF[Clave],"2591926|162",tSIAF[Certificacion])) -> 5106124.8 | F19: =IF(D19="","",D19-E19) -> 87908.23 | G19: =IF(COUNTIF(tSIAF[Clave],"2591926|162")=0,"",SUMIF(tSIAF[Clave],"2591926|162",tSIAF[Devengado])) -> 1941765.3 | H19: =IF(D19="","",D19-G19) -> 3252267.7 | I19: =IF(D19="","",IF(D19=0,0,G19/D19)) -> 0.37384539 | J19: EJECUCIÓN POR ADMINISTRACIÓN DIRECTA - DIRECTIVA 10 | K19: Por completar | L19: =IF(COUNTIF(tCartera[CUI],"2591926")=0,"Sin PMI",IF(INDEX(tCartera[PMI2026],MATCH("2591926",tCartera[CUI],0))="","No informado",INDEX(tCartera[PMI2026],MATCH("2591926",tCartera[CUI],0)))) -> 5194033 | M19: =IF(COUNTIF(tCartera[CUI],"2591926")=0,"Sin PMI",IF(INDEX(tCartera[PMI2027],MATCH("2591926",tCartera[CUI],0))="","No informado",INDEX(tCartera[PMI2027],MATCH("2591926",tCartera[CUI],0)))) -> 6569076 | N19: =IF(COUNTIF(tCartera[CUI],"2591926")=0,"Sin PMI",IF(INDEX(tCartera[PMI2028],MATCH("2591926",tCartera[CUI],0))="","No informado",INDEX(tCartera[PMI2028],MATCH("2591926",tCartera[CUI],0)))) -> 1 | O19: =IF(COUNTIF(tCartera[CUI],"2591926")=0,"Sin PMI",IF(INDEX(tCartera[PMI2029],MATCH("2591926",tCartera[CUI],0))="","No informado",INDEX(tCartera[PMI2029],MATCH("2591926",tCartera[CUI],0)))) -> 0
A20: =SUBTOTAL(103,$B$10:B20) -> 10 | B20: 44 | C20: 2629119.MEJORAMIENTO DEL SERVICIO DE EDUCACION SECUNDARIA EN I.E. ROSASPATA DE CENTRO POBLADO ROSASPATA DISTRITO DE ROSASPATA DE LA PROVINCIA DE HUANCANE DEL DEPARTAMENTO DE PUNO | D20: =IF(COUNTIF(tSIAF[Clave],"2629119|44")=0,"",SUMIF(tSIAF[Clave],"2629119|44",tSIAF[PIM])) -> 3656326 | E20: =IF(COUNTIF(tSIAF[Clave],"2629119|44")=0,"",SUMIF(tSIAF[Clave],"2629119|44",tSIAF[Certificacion])) -> 3383177.1 | F20: =IF(D20="","",D20-E20) -> 273148.9 | G20: =IF(COUNTIF(tSIAF[Clave],"2629119|44")=0,"",SUMIF(tSIAF[Clave],"2629119|44",tSIAF[Devengado])) -> 2126125.4 | H20: =IF(D20="","",D20-G20) -> 1530200.6 | I20: =IF(D20="","",IF(D20=0,0,G20/D20)) -> 0.58149229 | J20: EJECUCIÓN POR ADMINISTRACIÓN DIRECTA - DIRECTIVA 10 | K20: Por completar | L20: =IF(COUNTIF(tCartera[CUI],"2629119")=0,"Sin PMI",IF(INDEX(tCartera[PMI2026],MATCH("2629119",tCartera[CUI],0))="","No informado",INDEX(tCartera[PMI2026],MATCH("2629119",tCartera[CUI],0)))) -> 2278000 | M20: =IF(COUNTIF(tCartera[CUI],"2629119")=0,"Sin PMI",IF(INDEX(tCartera[PMI2027],MATCH("2629119",tCartera[CUI],0))="","No informado",INDEX(tCartera[PMI2027],MATCH("2629119",tCartera[CUI],0)))) -> 1683936 | N20: =IF(COUNTIF(tCartera[CUI],"2629119")=0,"Sin PMI",IF(INDEX(tCartera[PMI2028],MATCH("2629119",tCartera[CUI],0))="","No informado",INDEX(tCartera[PMI2028],MATCH("2629119",tCartera[CUI],0)))) -> 1459275 | O20: =IF(COUNTIF(tCartera[CUI],"2629119")=0,"Sin PMI",IF(INDEX(tCartera[PMI2029],MATCH("2629119",tCartera[CUI],0))="","No informado",INDEX(tCartera[PMI2029],MATCH("2629119",tCartera[CUI],0)))) -> 0
A21: =SUBTOTAL(103,$B$10:B21) -> 11 | B21: 248 | C21: 2539673: MEJORAMIENTO Y AMPLIACION DEL SERVICIO DE EDUCACION SUPERIOR TECNOLOGICA EN EL INSTITUTO SUPERIOR TECNOLOGICO PUBLICO DE JULI, DISTRITO DE JULI - PROVINCIA DE CHUCUITO - DEPARTAMENTO DE PUNO | D21: =IF(COUNTIF(tSIAF[Clave],"2539673|248")=0,"",SUMIF(tSIAF[Clave],"2539673|248",tSIAF[PIM])) -> 2000000 | E21: =IF(COUNTIF(tSIAF[Clave],"2539673|248")=0,"",SUMIF(tSIAF[Clave],"2539673|248",tSIAF[Certificacion])) -> 2000000 | F21: =IF(D21="","",D21-E21) -> 0 | G21: =IF(COUNTIF(tSIAF[Clave],"2539673|248")=0,"",SUMIF(tSIAF[Clave],"2539673|248",tSIAF[Devengado])) -> 0 | H21: =IF(D21="","",D21-G21) -> 2000000 | I21: =IF(D21="","",IF(D21=0,0,G21/D21)) -> 0 | J21: EJECUCIÓN POR ADMINISTRACIÓN DIRECTA - DIRECTIVA 10 | K21: Por completar | L21: =IF(COUNTIF(tCartera[CUI],"2539673")=0,"Sin PMI",IF(INDEX(tCartera[PMI2026],MATCH("2539673",tCartera[CUI],0))="","No informado",INDEX(tCartera[PMI2026],MATCH("2539673",tCartera[CUI],0)))) -> 12000000 | M21: =IF(COUNTIF(tCartera[CUI],"2539673")=0,"Sin PMI",IF(INDEX(tCartera[PMI2027],MATCH("2539673",tCartera[CUI],0))="","No informado",INDEX(tCartera[PMI2027],MATCH("2539673",tCartera[CUI],0)))) -> 14558623 | N21: =IF(COUNTIF(tCartera[CUI],"2539673")=0,"Sin PMI",IF(INDEX(tCartera[PMI2028],MATCH("2539673",tCartera[CUI],0))="","No informado",INDEX(tCartera[PMI2028],MATCH("2539673",tCartera[CUI],0)))) -> 14894208 | O21: =IF(COUNTIF(tCartera[CUI],"2539673")=0,"Sin PMI",IF(INDEX(tCartera[PMI2029],MATCH("2539673",tCartera[CUI],0))="","No informado",INDEX(tCartera[PMI2029],MATCH("2539673",tCartera[CUI],0)))) -> 10928387
A22: =SUBTOTAL(103,$B$10:B22) -> 12 | B22: 45 | C22: 2637985: MEJORAMIENTO DEL SERVICIO DE EDUCACION SECUNDARIA EN I.E. LLAULLI DE CENTRO POBLADO LLAULLI DISTRITO DE MOHO DE LA PROVINCIA DE MOHO DEL DEPARTAMENTO DE PUNO | D22: =IF(COUNTIF(tSIAF[Clave],"2637985|45")=0,"",SUMIF(tSIAF[Clave],"2637985|45",tSIAF[PIM])) -> 0 | E22: =IF(COUNTIF(tSIAF[Clave],"2637985|45")=0,"",SUMIF(tSIAF[Clave],"2637985|45",tSIAF[Certificacion])) -> 0 | F22: =IF(D22="","",D22-E22) -> 0 | G22: =IF(COUNTIF(tSIAF[Clave],"2637985|45")=0,"",SUMIF(tSIAF[Clave],"2637985|45",tSIAF[Devengado])) -> 0 | H22: =IF(D22="","",D22-G22) -> 0 | I22: =IF(D22="","",IF(D22=0,0,G22/D22)) -> 0 | J22: EJECUCIÓN POR ADMINISTRACIÓN DIRECTA - DIRECTIVA 10 | K22: Por completar | L22: =IF(COUNTIF(tCartera[CUI],"2637985")=0,"Sin PMI",IF(INDEX(tCartera[PMI2026],MATCH("2637985",tCartera[CUI],0))="","No informado",INDEX(tCartera[PMI2026],MATCH("2637985",tCartera[CUI],0)))) -> 100000 | M22: =IF(COUNTIF(tCartera[CUI],"2637985")=0,"Sin PMI",IF(INDEX(tCartera[PMI2027],MATCH("2637985",tCartera[CUI],0))="","No informado",INDEX(tCartera[PMI2027],MATCH("2637985",tCartera[CUI],0)))) -> 1234564 | N22: =IF(COUNTIF(tCartera[CUI],"2637985")=0,"Sin PMI",IF(INDEX(tCartera[PMI2028],MATCH("2637985",tCartera[CUI],0))="","No informado",INDEX(tCartera[PMI2028],MATCH("2637985",tCartera[CUI],0)))) -> 0 | O22: =IF(COUNTIF(tCartera[CUI],"2637985")=0,"Sin PMI",IF(INDEX(tCartera[PMI2029],MATCH("2637985",tCartera[CUI],0))="","No informado",INDEX(tCartera[PMI2029],MATCH("2637985",tCartera[CUI],0)))) -> 3335545
A23: =SUBTOTAL(103,$B$10:B23) -> 13 | B23: 193 | C23: 2664940: MEJORAMIENTO DEL SERVICIO DE EDUCACION INICIAL EN I.E. 1099 INMACULADA DISTRITO DE PUTINA DE LA PROVINCIA DE SAN ANTONIO DE PUTINA DEL DEPARTAMENTO DE PUNO | D23: =IF(COUNTIF(tSIAF[Clave],"2664940|193")=0,"",SUMIF(tSIAF[Clave],"2664940|193",tSIAF[PIM])) -> 1861270 | E23: =IF(COUNTIF(tSIAF[Clave],"2664940|193")=0,"",SUMIF(tSIAF[Clave],"2664940|193",tSIAF[Certificacion])) -> 1466941.4 | F23: =IF(D23="","",D23-E23) -> 394328.59 | G23: =IF(COUNTIF(tSIAF[Clave],"2664940|193")=0,"",SUMIF(tSIAF[Clave],"2664940|193",tSIAF[Devengado])) -> 1164545.4 | H23: =IF(D23="","",D23-G23) -> 696724.63 | I23: =IF(D23="","",IF(D23=0,0,G23/D23)) -> 0.62567245 | J23: EJECUCIÓN POR ADMINISTRACIÓN DIRECTA - DIRECTIVA 10 | K23: Por completar | L23: =IF(COUNTIF(tCartera[CUI],"2664940")=0,"Sin PMI",IF(INDEX(tCartera[PMI2026],MATCH("2664940",tCartera[CUI],0))="","No informado",INDEX(tCartera[PMI2026],MATCH("2664940",tCartera[CUI],0)))) -> 1410000 | M23: =IF(COUNTIF(tCartera[CUI],"2664940")=0,"Sin PMI",IF(INDEX(tCartera[PMI2027],MATCH("2664940",tCartera[CUI],0))="","No informado",INDEX(tCartera[PMI2027],MATCH("2664940",tCartera[CUI],0)))) -> 833474 | N23: =IF(COUNTIF(tCartera[CUI],"2664940")=0,"Sin PMI",IF(INDEX(tCartera[PMI2028],MATCH("2664940",tCartera[CUI],0))="","No informado",INDEX(tCartera[PMI2028],MATCH("2664940",tCartera[CUI],0)))) -> 0 | O23: =IF(COUNTIF(tCartera[CUI],"2664940")=0,"Sin PMI",IF(INDEX(tCartera[PMI2029],MATCH("2664940",tCartera[CUI],0))="","No informado",INDEX(tCartera[PMI2029],MATCH("2664940",tCartera[CUI],0)))) -> 0
A24: =SUBTOTAL(103,$B$10:B24) -> 14 | B24: 46 | C24: 2637997: MEJORAMIENTO DEL SERVICIO DE EDUCACION SECUNDARIA EN I.E. UMUCHI DISTRITO DE MOHO DE LA PROVINCIA DE MOHO DEL DEPARTAMENTO DE PUNO | D24: =IF(COUNTIF(tSIAF[Clave],"2637997|46")=0,"",SUMIF(tSIAF[Clave],"2637997|46",tSIAF[PIM])) -> 304829 | E24: =IF(COUNTIF(tSIAF[Clave],"2637997|46")=0,"",SUMIF(tSIAF[Clave],"2637997|46",tSIAF[Certificacion])) -> 0 | F24: =IF(D24="","",D24-E24) -> 304829 | G24: =IF(COUNTIF(tSIAF[Clave],"2637997|46")=0,"",SUMIF(tSIAF[Clave],"2637997|46",tSIAF[Devengado])) -> 0 | H24: =IF(D24="","",D24-G24) -> 304829 | I24: =IF(D24="","",IF(D24=0,0,G24/D24)) -> 0 | J24: EJECUCIÓN POR ADMINISTRACIÓN DIRECTA - DIRECTIVA 10 | K24: Por completar | L24: =IF(COUNTIF(tCartera[CUI],"2637997")=0,"Sin PMI",IF(INDEX(tCartera[PMI2026],MATCH("2637997",tCartera[CUI],0))="","No informado",INDEX(tCartera[PMI2026],MATCH("2637997",tCartera[CUI],0)))) -> 100000 | M24: =IF(COUNTIF(tCartera[CUI],"2637997")=0,"Sin PMI",IF(INDEX(tCartera[PMI2027],MATCH("2637997",tCartera[CUI],0))="","No informado",INDEX(tCartera[PMI2027],MATCH("2637997",tCartera[CUI],0)))) -> 0 | N24: =IF(COUNTIF(tCartera[CUI],"2637997")=0,"Sin PMI",IF(INDEX(tCartera[PMI2028],MATCH("2637997",tCartera[CUI],0))="","No informado",INDEX(tCartera[PMI2028],MATCH("2637997",tCartera[CUI],0)))) -> 0 | O24: =IF(COUNTIF(tCartera[CUI],"2637997")=0,"Sin PMI",IF(INDEX(tCartera[PMI2029],MATCH("2637997",tCartera[CUI],0))="","No informado",INDEX(tCartera[PMI2029],MATCH("2637997",tCartera[CUI],0)))) -> 4317457
A25: =SUBTOTAL(103,$B$10:B25) -> 15 | B25: 480 | C25: 2650476.ADQUISICION DE EQUIPAMIENTO DE AMBIENTES COMPLEMENTARIOS Y MOBILIARIO DE AULA; EN EL(LA) I.E. EL CENTENARIO DISTRITO DE PUTINA, PROVINCIA SAN ANTONIO DE PUTINA, DEPARTAMENTO PUNO | D25: =IF(COUNTIF(tSIAF[Clave],"2650476|480")=0,"",SUMIF(tSIAF[Clave],"2650476|480",tSIAF[PIM])) -> 677644 | E25: =IF(COUNTIF(tSIAF[Clave],"2650476|480")=0,"",SUMIF(tSIAF[Clave],"2650476|480",tSIAF[Certificacion])) -> 607692.88 | F25: =IF(D25="","",D25-E25) -> 69951.12 | G25: =IF(COUNTIF(tSIAF[Clave],"2650476|480")=0,"",SUMIF(tSIAF[Clave],"2650476|480",tSIAF[Devengado])) -> 131223.38 | H25: =IF(D25="","",D25-G25) -> 546420.62 | I25: =IF(D25="","",IF(D25=0,0,G25/D25)) -> 0.19364649 | J25: EJECUCIÓN POR ADMINISTRACIÓN DIRECTA - DIRECTIVA 10 | K25: Por completar | L25: =IF(COUNTIF(tCartera[CUI],"2650476")=0,"Sin PMI",IF(INDEX(tCartera[PMI2026],MATCH("2650476",tCartera[CUI],0))="","No informado",INDEX(tCartera[PMI2026],MATCH("2650476",tCartera[CUI],0)))) -> Sin PMI | M25: =IF(COUNTIF(tCartera[CUI],"2650476")=0,"Sin PMI",IF(INDEX(tCartera[PMI2027],MATCH("2650476",tCartera[CUI],0))="","No informado",INDEX(tCartera[PMI2027],MATCH("2650476",tCartera[CUI],0)))) -> Sin PMI | N25: =IF(COUNTIF(tCartera[CUI],"2650476")=0,"Sin PMI",IF(INDEX(tCartera[PMI2028],MATCH("2650476",tCartera[CUI],0))="","No informado",INDEX(tCartera[PMI2028],MATCH("2650476",tCartera[CUI],0)))) -> Sin PMI | O25: =IF(COUNTIF(tCartera[CUI],"2650476")=0,"Sin PMI",IF(INDEX(tCartera[PMI2029],MATCH("2650476",tCartera[CUI],0))="","No informado",INDEX(tCartera[PMI2029],MATCH("2650476",tCartera[CUI],0)))) -> Sin PMI
A26: =SUBTOTAL(103,$B$10:B26) -> 16 | B26: 479 | C26: 2695845.MEJORAMIENTO DEL SERVICIO DE EDUCACION SECUNDARIA EN I.E. SAN FRANCISCO DE BORJA DISTRITO DE TARACO DE LA PROVINCIA DE HUANCANE DEL DEPARTAMENTO DE PUNO | D26: =IF(COUNTIF(tSIAF[Clave],"2695845|479")=0,"",SUMIF(tSIAF[Clave],"2695845|479",tSIAF[PIM])) -> 492669 | E26: =IF(COUNTIF(tSIAF[Clave],"2695845|479")=0,"",SUMIF(tSIAF[Clave],"2695845|479",tSIAF[Certificacion])) -> 464894 | F26: =IF(D26="","",D26-E26) -> 27775 | G26: =IF(COUNTIF(tSIAF[Clave],"2695845|479")=0,"",SUMIF(tSIAF[Clave],"2695845|479",tSIAF[Devengado])) -> 211662.5 | H26: =IF(D26="","",D26-G26) -> 281006.5 | I26: =IF(D26="","",IF(D26=0,0,G26/D26)) -> 0.42962415 | J26: EJECUCIÓN POR ADMINISTRACIÓN DIRECTA - DIRECTIVA 10 | K26: Por completar | L26: =IF(COUNTIF(tCartera[CUI],"2695845")=0,"Sin PMI",IF(INDEX(tCartera[PMI2026],MATCH("2695845",tCartera[CUI],0))="","No informado",INDEX(tCartera[PMI2026],MATCH("2695845",tCartera[CUI],0)))) -> Sin PMI | M26: =IF(COUNTIF(tCartera[CUI],"2695845")=0,"Sin PMI",IF(INDEX(tCartera[PMI2027],MATCH("2695845",tCartera[CUI],0))="","No informado",INDEX(tCartera[PMI2027],MATCH("2695845",tCartera[CUI],0)))) -> Sin PMI | N26: =IF(COUNTIF(tCartera[CUI],"2695845")=0,"Sin PMI",IF(INDEX(tCartera[PMI2028],MATCH("2695845",tCartera[CUI],0))="","No informado",INDEX(tCartera[PMI2028],MATCH("2695845",tCartera[CUI],0)))) -> Sin PMI | O26: =IF(COUNTIF(tCartera[CUI],"2695845")=0,"Sin PMI",IF(INDEX(tCartera[PMI2029],MATCH("2695845",tCartera[CUI],0))="","No informado",INDEX(tCartera[PMI2029],MATCH("2695845",tCartera[CUI],0)))) -> Sin PMI
A27: =SUBTOTAL(103,$B$10:B27) -> 17 | B27: 170 | C27: 2196865: MEJORAMIENTO DEL SERVICIO EDUCATIVO DE NIVEL INICIAL ESCOLARIZADO EN LA I.E.I. LLUNGO, DISTRITO DE ATUNCOLLA, PROVINCIA DE PUNO - PUNO. | D27: =IF(COUNTIF(tSIAF[Clave],"2196865|170")=0,"",SUMIF(tSIAF[Clave],"2196865|170",tSIAF[PIM])) -> 118539 | E27: =IF(COUNTIF(tSIAF[Clave],"2196865|170")=0,"",SUMIF(tSIAF[Clave],"2196865|170",tSIAF[Certificacion])) -> 70562.13 | F27: =IF(D27="","",D27-E27) -> 47976.87 | G27: =IF(COUNTIF(tSIAF[Clave],"2196865|170")=0,"",SUMIF(tSIAF[Clave],"2196865|170",tSIAF[Devengado])) -> 70562.13 | H27: =IF(D27="","",D27-G27) -> 47976.87 | I27: =IF(D27="","",IF(D27=0,0,G27/D27)) -> 0.5952651 | J27: EJECUCIÓN POR ADMINISTRACIÓN DIRECTA - DIRECTIVA 10 | K27: Por completar | L27: =IF(COUNTIF(tCartera[CUI],"2196865")=0,"Sin PMI",IF(INDEX(tCartera[PMI2026],MATCH("2196865",tCartera[CUI],0))="","No informado",INDEX(tCartera[PMI2026],MATCH("2196865",tCartera[CUI],0)))) -> 159740 | M27: =IF(COUNTIF(tCartera[CUI],"2196865")=0,"Sin PMI",IF(INDEX(tCartera[PMI2027],MATCH("2196865",tCartera[CUI],0))="","No informado",INDEX(tCartera[PMI2027],MATCH("2196865",tCartera[CUI],0)))) -> 0 | N27: =IF(COUNTIF(tCartera[CUI],"2196865")=0,"Sin PMI",IF(INDEX(tCartera[PMI2028],MATCH("2196865",tCartera[CUI],0))="","No informado",INDEX(tCartera[PMI2028],MATCH("2196865",tCartera[CUI],0)))) -> 0 | O27: =IF(COUNTIF(tCartera[CUI],"2196865")=0,"Sin PMI",IF(INDEX(tCartera[PMI2029],MATCH("2196865",tCartera[CUI],0))="","No informado",INDEX(tCartera[PMI2029],MATCH("2196865",tCartera[CUI],0)))) -> 0
A28: =SUBTOTAL(103,$B$10:B28) -> 18 | B28: 490 | C28: 2301117: MEJORAMIENTO DEL SERVICIO EDUCATIVO EN LAS INSTITUCIONES EDUCATIVAS PRIMARIAS N 70511, N 70815 Y N 72637, DISTRITO DE ORURILLO - MELGAR - PUNO | D28: =IF(COUNTIF(tSIAF[Clave],"2301117|490")=0,"",SUMIF(tSIAF[Clave],"2301117|490",tSIAF[PIM])) -> 28700 | E28: =IF(COUNTIF(tSIAF[Clave],"2301117|490")=0,"",SUMIF(tSIAF[Clave],"2301117|490",tSIAF[Certificacion])) -> 0 | F28: =IF(D28="","",D28-E28) -> 28700 | G28: =IF(COUNTIF(tSIAF[Clave],"2301117|490")=0,"",SUMIF(tSIAF[Clave],"2301117|490",tSIAF[Devengado])) -> 0 | H28: =IF(D28="","",D28-G28) -> 28700 | I28: =IF(D28="","",IF(D28=0,0,G28/D28)) -> 0 | J28: EJECUCIÓN POR ADMINISTRACIÓN DIRECTA - DIRECTIVA 10 | K28: Por completar | L28: =IF(COUNTIF(tCartera[CUI],"2301117")=0,"Sin PMI",IF(INDEX(tCartera[PMI2026],MATCH("2301117",tCartera[CUI],0))="","No informado",INDEX(tCartera[PMI2026],MATCH("2301117",tCartera[CUI],0)))) -> 539829 | M28: =IF(COUNTIF(tCartera[CUI],"2301117")=0,"Sin PMI",IF(INDEX(tCartera[PMI2027],MATCH("2301117",tCartera[CUI],0))="","No informado",INDEX(tCartera[PMI2027],MATCH("2301117",tCartera[CUI],0)))) -> 504509 | N28: =IF(COUNTIF(tCartera[CUI],"2301117")=0,"Sin PMI",IF(INDEX(tCartera[PMI2028],MATCH("2301117",tCartera[CUI],0))="","No informado",INDEX(tCartera[PMI2028],MATCH("2301117",tCartera[CUI],0)))) -> 0 | O28: =IF(COUNTIF(tCartera[CUI],"2301117")=0,"Sin PMI",IF(INDEX(tCartera[PMI2029],MATCH("2301117",tCartera[CUI],0))="","No informado",INDEX(tCartera[PMI2029],MATCH("2301117",tCartera[CUI],0)))) -> 0
A29: =SUBTOTAL(103,$B$10:B29) -> 19 | B29: 489 | C29: 2301117: MEJORAMIENTO DEL SERVICIO EDUCATIVO EN LAS INSTITUCIONES EDUCATIVAS PRIMARIAS N 70511, N 70815 Y N 72637, DISTRITO DE ORURILLO - MELGAR - PUNO | D29: =IF(COUNTIF(tSIAF[Clave],"2301117|489")=0,"",SUMIF(tSIAF[Clave],"2301117|489",tSIAF[PIM])) -> 25000 | E29: =IF(COUNTIF(tSIAF[Clave],"2301117|489")=0,"",SUMIF(tSIAF[Clave],"2301117|489",tSIAF[Certificacion])) -> 0 | F29: =IF(D29="","",D29-E29) -> 25000 | G29: =IF(COUNTIF(tSIAF[Clave],"2301117|489")=0,"",SUMIF(tSIAF[Clave],"2301117|489",tSIAF[Devengado])) -> 0 | H29: =IF(D29="","",D29-G29) -> 25000 | I29: =IF(D29="","",IF(D29=0,0,G29/D29)) -> 0 | J29: EJECUCIÓN POR ADMINISTRACIÓN DIRECTA - DIRECTIVA 10 | K29: Por completar | L29: =IF(COUNTIF(tCartera[CUI],"2301117")=0,"Sin PMI",IF(INDEX(tCartera[PMI2026],MATCH("2301117",tCartera[CUI],0))="","No informado",INDEX(tCartera[PMI2026],MATCH("2301117",tCartera[CUI],0)))) -> 539829 | M29: =IF(COUNTIF(tCartera[CUI],"2301117")=0,"Sin PMI",IF(INDEX(tCartera[PMI2027],MATCH("2301117",tCartera[CUI],0))="","No informado",INDEX(tCartera[PMI2027],MATCH("2301117",tCartera[CUI],0)))) -> 504509 | N29: =IF(COUNTIF(tCartera[CUI],"2301117")=0,"Sin PMI",IF(INDEX(tCartera[PMI2028],MATCH("2301117",tCartera[CUI],0))="","No informado",INDEX(tCartera[PMI2028],MATCH("2301117",tCartera[CUI],0)))) -> 0 | O29: =IF(COUNTIF(tCartera[CUI],"2301117")=0,"Sin PMI",IF(INDEX(tCartera[PMI2029],MATCH("2301117",tCartera[CUI],0))="","No informado",INDEX(tCartera[PMI2029],MATCH("2301117",tCartera[CUI],0)))) -> 0
A30: =SUBTOTAL(103,$B$10:B30) -> 20 | B30: 484 | C30: 2623682: RENOVACION DE AULA DE EDUCACION SUPERIOR PEDAGOGICA, LABORATORIO Y/O TALLER Y AMBIENTE COMPLEMENTARIO; REPARACION DE CERCO Y/O PORTADA; ADEMAS DE OTROS ACTIVOS EN EL(LA) INSTITUTO DE EDUCACION SUPERIOR PEDAGOGICO HUANCANE DEL DISTRITO DE HUANCANE, PROVINCIA HUANCANE, DEPARTAMENTO PUNO | D30: =IF(COUNTIF(tSIAF[Clave],"2623682|484")=0,"",SUMIF(tSIAF[Clave],"2623682|484",tSIAF[PIM])) -> 23560 | E30: =IF(COUNTIF(tSIAF[Clave],"2623682|484")=0,"",SUMIF(tSIAF[Clave],"2623682|484",tSIAF[Certificacion])) -> 22650 | F30: =IF(D30="","",D30-E30) -> 910 | G30: =IF(COUNTIF(tSIAF[Clave],"2623682|484")=0,"",SUMIF(tSIAF[Clave],"2623682|484",tSIAF[Devengado])) -> 14282.09 | H30: =IF(D30="","",D30-G30) -> 9277.91 | I30: =IF(D30="","",IF(D30=0,0,G30/D30)) -> 0.60620076 | J30: EJECUCIÓN POR ADMINISTRACIÓN DIRECTA - DIRECTIVA 10 | K30: Por completar | L30: =IF(COUNTIF(tCartera[CUI],"2623682")=0,"Sin PMI",IF(INDEX(tCartera[PMI2026],MATCH("2623682",tCartera[CUI],0))="","No informado",INDEX(tCartera[PMI2026],MATCH("2623682",tCartera[CUI],0)))) -> 23560 | M30: =IF(COUNTIF(tCartera[CUI],"2623682")=0,"Sin PMI",IF(INDEX(tCartera[PMI2027],MATCH("2623682",tCartera[CUI],0))="","No informado",INDEX(tCartera[PMI2027],MATCH("2623682",tCartera[CUI],0)))) -> 27080 | N30: =IF(COUNTIF(tCartera[CUI],"2623682")=0,"Sin PMI",IF(INDEX(tCartera[PMI2028],MATCH("2623682",tCartera[CUI],0))="","No informado",INDEX(tCartera[PMI2028],MATCH("2623682",tCartera[CUI],0)))) -> 0 | O30: =IF(COUNTIF(tCartera[CUI],"2623682")=0,"Sin PMI",IF(INDEX(tCartera[PMI2029],MATCH("2623682",tCartera[CUI],0))="","No informado",INDEX(tCartera[PMI2029],MATCH("2623682",tCartera[CUI],0)))) -> 0
A31: =SUBTOTAL(103,$B$10:B31) -> 21 | B31: 453 | C31: 2196822: INSTALACION DEL SERVICIO DE EDUCACION INICIAL DE LA I.E.I. NRO. 94 DEL CENTRO POBLADO DE UMUCHI, DISTRITO DE MOHO, PROVINCIA DE MOHO, DEPARTAMENTO DE PUNO. | D31: =IF(COUNTIF(tSIAF[Clave],"2196822|453")=0,"",SUMIF(tSIAF[Clave],"2196822|453",tSIAF[PIM])) -> 17714 | E31: =IF(COUNTIF(tSIAF[Clave],"2196822|453")=0,"",SUMIF(tSIAF[Clave],"2196822|453",tSIAF[Certificacion])) -> 14228.68 | F31: =IF(D31="","",D31-E31) -> 3485.32 | G31: =IF(COUNTIF(tSIAF[Clave],"2196822|453")=0,"",SUMIF(tSIAF[Clave],"2196822|453",tSIAF[Devengado])) -> 9749.8 | H31: =IF(D31="","",D31-G31) -> 7964.2 | I31: =IF(D31="","",IF(D31=0,0,G31/D31)) -> 0.55040081 | J31: EJECUCIÓN POR ADMINISTRACIÓN DIRECTA - DIRECTIVA 10 | K31: Por completar | L31: =IF(COUNTIF(tCartera[CUI],"2196822")=0,"Sin PMI",IF(INDEX(tCartera[PMI2026],MATCH("2196822",tCartera[CUI],0))="","No informado",INDEX(tCartera[PMI2026],MATCH("2196822",tCartera[CUI],0)))) -> 13915 | M31: =IF(COUNTIF(tCartera[CUI],"2196822")=0,"Sin PMI",IF(INDEX(tCartera[PMI2027],MATCH("2196822",tCartera[CUI],0))="","No informado",INDEX(tCartera[PMI2027],MATCH("2196822",tCartera[CUI],0)))) -> 0 | N31: =IF(COUNTIF(tCartera[CUI],"2196822")=0,"Sin PMI",IF(INDEX(tCartera[PMI2028],MATCH("2196822",tCartera[CUI],0))="","No informado",INDEX(tCartera[PMI2028],MATCH("2196822",tCartera[CUI],0)))) -> 0 | O31: =IF(COUNTIF(tCartera[CUI],"2196822")=0,"Sin PMI",IF(INDEX(tCartera[PMI2029],MATCH("2196822",tCartera[CUI],0))="","No informado",INDEX(tCartera[PMI2029],MATCH("2196822",tCartera[CUI],0)))) -> 0
A32: =SUBTOTAL(103,$B$10:B32) -> 22 | B32: 24 | C32: 2194504: INSTALACION DEL SERVICIO EDUCATIVO DEL NIVEL SECUNDARIO EN LA I.E.S. RODOLFO DIESEL, DISTRITO DE JULIACA, PROVINCIA SAN ROMAN - PUNO. | D32: =IF(COUNTIF(tSIAF[Clave],"2194504|24")=0,"",SUMIF(tSIAF[Clave],"2194504|24",tSIAF[PIM])) -> 0 | E32: =IF(COUNTIF(tSIAF[Clave],"2194504|24")=0,"",SUMIF(tSIAF[Clave],"2194504|24",tSIAF[Certificacion])) -> 0 | F32: =IF(D32="","",D32-E32) -> 0 | G32: =IF(COUNTIF(tSIAF[Clave],"2194504|24")=0,"",SUMIF(tSIAF[Clave],"2194504|24",tSIAF[Devengado])) -> 0 | H32: =IF(D32="","",D32-G32) -> 0 | I32: =IF(D32="","",IF(D32=0,0,G32/D32)) -> 0 | J32: EJECUCIÓN POR ADMINISTRACIÓN DIRECTA - DIRECTIVA 10 | K32: Por completar | L32: =IF(COUNTIF(tCartera[CUI],"2194504")=0,"Sin PMI",IF(INDEX(tCartera[PMI2026],MATCH("2194504",tCartera[CUI],0))="","No informado",INDEX(tCartera[PMI2026],MATCH("2194504",tCartera[CUI],0)))) -> Sin PMI | M32: =IF(COUNTIF(tCartera[CUI],"2194504")=0,"Sin PMI",IF(INDEX(tCartera[PMI2027],MATCH("2194504",tCartera[CUI],0))="","No informado",INDEX(tCartera[PMI2027],MATCH("2194504",tCartera[CUI],0)))) -> Sin PMI | N32: =IF(COUNTIF(tCartera[CUI],"2194504")=0,"Sin PMI",IF(INDEX(tCartera[PMI2028],MATCH("2194504",tCartera[CUI],0))="","No informado",INDEX(tCartera[PMI2028],MATCH("2194504",tCartera[CUI],0)))) -> Sin PMI | O32: =IF(COUNTIF(tCartera[CUI],"2194504")=0,"Sin PMI",IF(INDEX(tCartera[PMI2029],MATCH("2194504",tCartera[CUI],0))="","No informado",INDEX(tCartera[PMI2029],MATCH("2194504",tCartera[CUI],0)))) -> Sin PMI
A33: =SUBTOTAL(103,$B$10:B33) -> 23 | B33: 168 | C33: 2196834: MEJORAMIENTO DE LOS SERVICIOS DE EDUCACION INICIAL EN LA I.E.I. CUCURAYA DE LA COMUNIDAD DE CUCURAYA, DISTRITO DE TILALI, PROVINCIA DE MOHO - PUNO. | D33: =IF(COUNTIF(tSIAF[Clave],"2196834|168")=0,"",SUMIF(tSIAF[Clave],"2196834|168",tSIAF[PIM])) -> 728529 | E33: =IF(COUNTIF(tSIAF[Clave],"2196834|168")=0,"",SUMIF(tSIAF[Clave],"2196834|168",tSIAF[Certificacion])) -> 0 | F33: =IF(D33="","",D33-E33) -> 728529 | G33: =IF(COUNTIF(tSIAF[Clave],"2196834|168")=0,"",SUMIF(tSIAF[Clave],"2196834|168",tSIAF[Devengado])) -> 0 | H33: =IF(D33="","",D33-G33) -> 728529 | I33: =IF(D33="","",IF(D33=0,0,G33/D33)) -> 0 | J33: EJECUCIÓN POR ADMINISTRACIÓN DIRECTA - DIRECTIVA 10 | K33: Por completar | L33: =IF(COUNTIF(tCartera[CUI],"2196834")=0,"Sin PMI",IF(INDEX(tCartera[PMI2026],MATCH("2196834",tCartera[CUI],0))="","No informado",INDEX(tCartera[PMI2026],MATCH("2196834",tCartera[CUI],0)))) -> 699403 | M33: =IF(COUNTIF(tCartera[CUI],"2196834")=0,"Sin PMI",IF(INDEX(tCartera[PMI2027],MATCH("2196834",tCartera[CUI],0))="","No informado",INDEX(tCartera[PMI2027],MATCH("2196834",tCartera[CUI],0)))) -> 0 | N33: =IF(COUNTIF(tCartera[CUI],"2196834")=0,"Sin PMI",IF(INDEX(tCartera[PMI2028],MATCH("2196834",tCartera[CUI],0))="","No informado",INDEX(tCartera[PMI2028],MATCH("2196834",tCartera[CUI],0)))) -> 0 | O33: =IF(COUNTIF(tCartera[CUI],"2196834")=0,"Sin PMI",IF(INDEX(tCartera[PMI2029],MATCH("2196834",tCartera[CUI],0))="","No informado",INDEX(tCartera[PMI2029],MATCH("2196834",tCartera[CUI],0)))) -> 0
A34: =SUBTOTAL(103,$B$10:B34) -> 24 | B34: 464 | C34: 2490131: MEJORAMIENTO DEL SERVICIO DE EDUCACION SECUNDARIA DE LA IES CABANILLAS, DISTRITO DE CABANILLAS - PROVINCIA DE SAN ROMAN - DEPARTAMENTO DE PUNO | D34: =IF(COUNTIF(tSIAF[Clave],"2490131|464")=0,"",SUMIF(tSIAF[Clave],"2490131|464",tSIAF[PIM])) -> 40621 | E34: =IF(COUNTIF(tSIAF[Clave],"2490131|464")=0,"",SUMIF(tSIAF[Clave],"2490131|464",tSIAF[Certificacion])) -> 28914.4 | F34: =IF(D34="","",D34-E34) -> 11706.6 | G34: =IF(COUNTIF(tSIAF[Clave],"2490131|464")=0,"",SUMIF(tSIAF[Clave],"2490131|464",tSIAF[Devengado])) -> 27953.93 | H34: =IF(D34="","",D34-G34) -> 12667.07 | I34: =IF(D34="","",IF(D34=0,0,G34/D34)) -> 0.6881645 | J34: EJECUCIÓN POR ADMINISTRACIÓN DIRECTA - DIRECTIVA 10 | K34: Por completar | L34: =IF(COUNTIF(tCartera[CUI],"2490131")=0,"Sin PMI",IF(INDEX(tCartera[PMI2026],MATCH("2490131",tCartera[CUI],0))="","No informado",INDEX(tCartera[PMI2026],MATCH("2490131",tCartera[CUI],0)))) -> 2455 | M34: =IF(COUNTIF(tCartera[CUI],"2490131")=0,"Sin PMI",IF(INDEX(tCartera[PMI2027],MATCH("2490131",tCartera[CUI],0))="","No informado",INDEX(tCartera[PMI2027],MATCH("2490131",tCartera[CUI],0)))) -> 0 | N34: =IF(COUNTIF(tCartera[CUI],"2490131")=0,"Sin PMI",IF(INDEX(tCartera[PMI2028],MATCH("2490131",tCartera[CUI],0))="","No informado",INDEX(tCartera[PMI2028],MATCH("2490131",tCartera[CUI],0)))) -> 0 | O34: =IF(COUNTIF(tCartera[CUI],"2490131")=0,"Sin PMI",IF(INDEX(tCartera[PMI2029],MATCH("2490131",tCartera[CUI],0))="","No informado",INDEX(tCartera[PMI2029],MATCH("2490131",tCartera[CUI],0)))) -> 0
A35: =SUBTOTAL(103,$B$10:B35) -> 25 | B35: 169 | C35: 2196857: INSTALACION DEL SERVICIO EDUCATIVO EN LA INSTITUCION EDUCATIVA INICIAL N 986 SAN JUAN BAUTISTA DEL DISTRITO DE JULIACA, PROVINCIA DE SAN ROMAN - PUNO | D35: =IF(COUNTIF(tSIAF[Clave],"2196857|169")=0,"",SUMIF(tSIAF[Clave],"2196857|169",tSIAF[PIM])) -> 0 | E35: =IF(COUNTIF(tSIAF[Clave],"2196857|169")=0,"",SUMIF(tSIAF[Clave],"2196857|169",tSIAF[Certificacion])) -> 0 | F35: =IF(D35="","",D35-E35) -> 0 | G35: =IF(COUNTIF(tSIAF[Clave],"2196857|169")=0,"",SUMIF(tSIAF[Clave],"2196857|169",tSIAF[Devengado])) -> 0 | H35: =IF(D35="","",D35-G35) -> 0 | I35: =IF(D35="","",IF(D35=0,0,G35/D35)) -> 0 | J35: EJECUCIÓN POR ADMINISTRACIÓN DIRECTA - DIRECTIVA 10 | K35: Por completar | L35: =IF(COUNTIF(tCartera[CUI],"2196857")=0,"Sin PMI",IF(INDEX(tCartera[PMI2026],MATCH("2196857",tCartera[CUI],0))="","No informado",INDEX(tCartera[PMI2026],MATCH("2196857",tCartera[CUI],0)))) -> 2878733 | M35: =IF(COUNTIF(tCartera[CUI],"2196857")=0,"Sin PMI",IF(INDEX(tCartera[PMI2027],MATCH("2196857",tCartera[CUI],0))="","No informado",INDEX(tCartera[PMI2027],MATCH("2196857",tCartera[CUI],0)))) -> 0 | N35: =IF(COUNTIF(tCartera[CUI],"2196857")=0,"Sin PMI",IF(INDEX(tCartera[PMI2028],MATCH("2196857",tCartera[CUI],0))="","No informado",INDEX(tCartera[PMI2028],MATCH("2196857",tCartera[CUI],0)))) -> 0 | O35: =IF(COUNTIF(tCartera[CUI],"2196857")=0,"Sin PMI",IF(INDEX(tCartera[PMI2029],MATCH("2196857",tCartera[CUI],0))="","No informado",INDEX(tCartera[PMI2029],MATCH("2196857",tCartera[CUI],0)))) -> 0
A36: =SUBTOTAL(103,$B$10:B36) -> 25 | B36: 499 | C36: MEJORAMIENTO DE LOS SERVICIOS EDUCATIVOS EN LA I.E.I. N 596 MUNAYPATA DEL CENTRO POBLADO DE MUNAYPATA, DISTRITO DE OLLACHEA PROVINCIA DE CARABAYA PUNO
A37: =SUBTOTAL(103,$B$10:B37) -> 26 | B37: 27 | C37: 2301117: MEJORAMIENTO DEL SERVICIO EDUCATIVO EN LAS INSTITUCIONES EDUCATIVAS PRIMARIAS N 70511, N 70815 Y N 72637, DISTRITO DE ORURILLO - MELGAR - PUNO | D37: =IF(COUNTIF(tSIAF[Clave],"2301117|27")=0,"",SUMIF(tSIAF[Clave],"2301117|27",tSIAF[PIM])) -> 855386 | E37: =IF(COUNTIF(tSIAF[Clave],"2301117|27")=0,"",SUMIF(tSIAF[Clave],"2301117|27",tSIAF[Certificacion])) -> 725859.11 | F37: =IF(D37="","",D37-E37) -> 129526.89 | G37: =IF(COUNTIF(tSIAF[Clave],"2301117|27")=0,"",SUMIF(tSIAF[Clave],"2301117|27",tSIAF[Devengado])) -> 715665.61 | H37: =IF(D37="","",D37-G37) -> 139720.39 | I37: =IF(D37="","",IF(D37=0,0,G37/D37)) -> 0.83665808 | J37: EJECUCIÓN POR ADMINISTRACIÓN DIRECTA - DIRECTIVA 10 | K37: Por completar | L37: =IF(COUNTIF(tCartera[CUI],"2301117")=0,"Sin PMI",IF(INDEX(tCartera[PMI2026],MATCH("2301117",tCartera[CUI],0))="","No informado",INDEX(tCartera[PMI2026],MATCH("2301117",tCartera[CUI],0)))) -> 539829 | M37: =IF(COUNTIF(tCartera[CUI],"2301117")=0,"Sin PMI",IF(INDEX(tCartera[PMI2027],MATCH("2301117",tCartera[CUI],0))="","No informado",INDEX(tCartera[PMI2027],MATCH("2301117",tCartera[CUI],0)))) -> 504509 | N37: =IF(COUNTIF(tCartera[CUI],"2301117")=0,"Sin PMI",IF(INDEX(tCartera[PMI2028],MATCH("2301117",tCartera[CUI],0))="","No informado",INDEX(tCartera[PMI2028],MATCH("2301117",tCartera[CUI],0)))) -> 0 | O37: =IF(COUNTIF(tCartera[CUI],"2301117")=0,"Sin PMI",IF(INDEX(tCartera[PMI2029],MATCH("2301117",tCartera[CUI],0))="","No informado",INDEX(tCartera[PMI2029],MATCH("2301117",tCartera[CUI],0)))) -> 0
A38: =SUBTOTAL(103,$B$10:B38) -> 27 | B38: 22 | C38: 2194462: INSTALACION DEL SERVICIO DE EDUCACION SECUNDARIA THOMAS ALVA EDISON EN LA URBANIZACION CHILLA - LOS ROSALES EN EL DISTRITO DE JULIACA, PROVINCIA DE SAN ROMAN. | D38: =IF(COUNTIF(tSIAF[Clave],"2194462|22")=0,"",SUMIF(tSIAF[Clave],"2194462|22",tSIAF[PIM])) -> 77590 | E38: =IF(COUNTIF(tSIAF[Clave],"2194462|22")=0,"",SUMIF(tSIAF[Clave],"2194462|22",tSIAF[Certificacion])) -> 76159.18 | F38: =IF(D38="","",D38-E38) -> 1430.82 | G38: =IF(COUNTIF(tSIAF[Clave],"2194462|22")=0,"",SUMIF(tSIAF[Clave],"2194462|22",tSIAF[Devengado])) -> 76159.18 | H38: =IF(D38="","",D38-G38) -> 1430.82 | I38: =IF(D38="","",IF(D38=0,0,G38/D38)) -> 0.98155922 | J38: EJECUCIÓN POR ADMINISTRACIÓN DIRECTA - DIRECTIVA 10 | K38: Por completar | L38: =IF(COUNTIF(tCartera[CUI],"2194462")=0,"Sin PMI",IF(INDEX(tCartera[PMI2026],MATCH("2194462",tCartera[CUI],0))="","No informado",INDEX(tCartera[PMI2026],MATCH("2194462",tCartera[CUI],0)))) -> 357505 | M38: =IF(COUNTIF(tCartera[CUI],"2194462")=0,"Sin PMI",IF(INDEX(tCartera[PMI2027],MATCH("2194462",tCartera[CUI],0))="","No informado",INDEX(tCartera[PMI2027],MATCH("2194462",tCartera[CUI],0)))) -> 0 | N38: =IF(COUNTIF(tCartera[CUI],"2194462")=0,"Sin PMI",IF(INDEX(tCartera[PMI2028],MATCH("2194462",tCartera[CUI],0))="","No informado",INDEX(tCartera[PMI2028],MATCH("2194462",tCartera[CUI],0)))) -> 0 | O38: =IF(COUNTIF(tCartera[CUI],"2194462")=0,"Sin PMI",IF(INDEX(tCartera[PMI2029],MATCH("2194462",tCartera[CUI],0))="","No informado",INDEX(tCartera[PMI2029],MATCH("2194462",tCartera[CUI],0)))) -> 344884
A39: =SUBTOTAL(103,$B$10:B39) -> 28 | B39: 37 | C39: 2467893: MEJORAMIENTO DEL SERVICIO EDUCATIVO DEL NIVEL SECUNDARIA DE LA I.E.S. TARACO DEL DISTRITO DE TARACO - PROVINCIA DE HUANCANE - DEPARTAMENTO DE PUNO | D39: =IF(COUNTIF(tSIAF[Clave],"2467893|37")=0,"",SUMIF(tSIAF[Clave],"2467893|37",tSIAF[PIM])) -> 50132 | E39: =IF(COUNTIF(tSIAF[Clave],"2467893|37")=0,"",SUMIF(tSIAF[Clave],"2467893|37",tSIAF[Certificacion])) -> 47450.05 | F39: =IF(D39="","",D39-E39) -> 2681.95 | G39: =IF(COUNTIF(tSIAF[Clave],"2467893|37")=0,"",SUMIF(tSIAF[Clave],"2467893|37",tSIAF[Devengado])) -> 47450.05 | H39: =IF(D39="","",D39-G39) -> 2681.95 | I39: =IF(D39="","",IF(D39=0,0,G39/D39)) -> 0.94650223 | J39: EJECUCIÓN POR ADMINISTRACIÓN DIRECTA - DIRECTIVA 10 | K39: Por completar | L39: =IF(COUNTIF(tCartera[CUI],"2467893")=0,"Sin PMI",IF(INDEX(tCartera[PMI2026],MATCH("2467893",tCartera[CUI],0))="","No informado",INDEX(tCartera[PMI2026],MATCH("2467893",tCartera[CUI],0)))) -> 175369 | M39: =IF(COUNTIF(tCartera[CUI],"2467893")=0,"Sin PMI",IF(INDEX(tCartera[PMI2027],MATCH("2467893",tCartera[CUI],0))="","No informado",INDEX(tCartera[PMI2027],MATCH("2467893",tCartera[CUI],0)))) -> 79091 | N39: =IF(COUNTIF(tCartera[CUI],"2467893")=0,"Sin PMI",IF(INDEX(tCartera[PMI2028],MATCH("2467893",tCartera[CUI],0))="","No informado",INDEX(tCartera[PMI2028],MATCH("2467893",tCartera[CUI],0)))) -> 583672 | O39: =IF(COUNTIF(tCartera[CUI],"2467893")=0,"Sin PMI",IF(INDEX(tCartera[PMI2029],MATCH("2467893",tCartera[CUI],0))="","No informado",INDEX(tCartera[PMI2029],MATCH("2467893",tCartera[CUI],0)))) -> 0
A40: 15. TRANSPORTE | D40: =D41+D42+D43+D44+D45+D46+D47+D48+D49+D50+D51+D52+D53+D54+D55+D56+D57+D58+D59+D60+D61+D62+D63+D64 -> 87794613 | E40: =E41+E42+E43+E44+E45+E46+E47+E48+E49+E50+E51+E52+E53+E54+E55+E56+E57+E58+E59+E60+E61+E62+E63+E64 -> 83882331 | F40: =D40-E40 -> 3912282.3 | G40: =G41+G42+G43+G44+G45+G46+G47+G48+G49+G50+G51+G52+G53+G54+G55+G56+G57+G58+G59+G60+G61+G62+G63+G64 -> 50834366 | H40: =D40-G40 -> 36960247 | I40: =IF(D40=0,0,G40/D40) -> 0.57901463
A41: =SUBTOTAL(103,$B$10:B41) -> 29 | B41: 95 | C41: 2194702: MEJORAMIENTO DE LA CARRETERA (PU 675) POMATA - YOROHOCO, PROVINCIA DE CHUCUITO - PUNO | D41: =IF(COUNTIF(tSIAF[Clave],"2194702|95")=0,"",SUMIF(tSIAF[Clave],"2194702|95",tSIAF[PIM])) -> 18401182 | E41: =IF(COUNTIF(tSIAF[Clave],"2194702|95")=0,"",SUMIF(tSIAF[Clave],"2194702|95",tSIAF[Certificacion])) -> 17764558 | F41: =IF(D41="","",D41-E41) -> 636624.07 | G41: =IF(COUNTIF(tSIAF[Clave],"2194702|95")=0,"",SUMIF(tSIAF[Clave],"2194702|95",tSIAF[Devengado])) -> 15484260 | H41: =IF(D41="","",D41-G41) -> 2916922.1 | I41: =IF(D41="","",IF(D41=0,0,G41/D41)) -> 0.84148181 | J41: EJECUCIÓN POR ADMINISTRACIÓN DIRECTA - DIRECTIVA 10 | K41: Por completar | L41: =IF(COUNTIF(tCartera[CUI],"2194702")=0,"Sin PMI",IF(INDEX(tCartera[PMI2026],MATCH("2194702",tCartera[CUI],0))="","No informado",INDEX(tCartera[PMI2026],MATCH("2194702",tCartera[CUI],0)))) -> 9922902 | M41: =IF(COUNTIF(tCartera[CUI],"2194702")=0,"Sin PMI",IF(INDEX(tCartera[PMI2027],MATCH("2194702",tCartera[CUI],0))="","No informado",INDEX(tCartera[PMI2027],MATCH("2194702",tCartera[CUI],0)))) -> 180000 | N41: =IF(COUNTIF(tCartera[CUI],"2194702")=0,"Sin PMI",IF(INDEX(tCartera[PMI2028],MATCH("2194702",tCartera[CUI],0))="","No informado",INDEX(tCartera[PMI2028],MATCH("2194702",tCartera[CUI],0)))) -> 0 | O41: =IF(COUNTIF(tCartera[CUI],"2194702")=0,"Sin PMI",IF(INDEX(tCartera[PMI2029],MATCH("2194702",tCartera[CUI],0))="","No informado",INDEX(tCartera[PMI2029],MATCH("2194702",tCartera[CUI],0)))) -> 0
A42: =SUBTOTAL(103,$B$10:B42) -> 30 | B42: 98 | C42: 2287700: MEJORAMIENTO DE LA CARRETERA PU N-110: EMP. PE-34I ASIRUNI - ROSASPATA - HUAYRAPATA - EMP. PE-34I NINANTAYA, DISTRITOS DE VILQUECHICO-ROSASPATA-MOHO-HUAYRAPATA, PROVINCIA DE HUANCANE Y MOHO - PUNO | D42: =IF(COUNTIF(tSIAF[Clave],"2287700|98")=0,"",SUMIF(tSIAF[Clave],"2287700|98",tSIAF[PIM])) -> 10002053 | E42: =IF(COUNTIF(tSIAF[Clave],"2287700|98")=0,"",SUMIF(tSIAF[Clave],"2287700|98",tSIAF[Certificacion])) -> 9636351.5 | F42: =IF(D42="","",D42-E42) -> 365701.52 | G42: =IF(COUNTIF(tSIAF[Clave],"2287700|98")=0,"",SUMIF(tSIAF[Clave],"2287700|98",tSIAF[Devengado])) -> 5473965.1 | H42: =IF(D42="","",D42-G42) -> 4528087.9 | I42: =IF(D42="","",IF(D42=0,0,G42/D42)) -> 0.54728415 | J42: EJECUCIÓN POR ADMINISTRACIÓN DIRECTA - DIRECTIVA 10 | K42: Por completar | L42: =IF(COUNTIF(tCartera[CUI],"2287700")=0,"Sin PMI",IF(INDEX(tCartera[PMI2026],MATCH("2287700",tCartera[CUI],0))="","No informado",INDEX(tCartera[PMI2026],MATCH("2287700",tCartera[CUI],0)))) -> 4289351 | M42: =IF(COUNTIF(tCartera[CUI],"2287700")=0,"Sin PMI",IF(INDEX(tCartera[PMI2027],MATCH("2287700",tCartera[CUI],0))="","No informado",INDEX(tCartera[PMI2027],MATCH("2287700",tCartera[CUI],0)))) -> 500000 | N42: =IF(COUNTIF(tCartera[CUI],"2287700")=0,"Sin PMI",IF(INDEX(tCartera[PMI2028],MATCH("2287700",tCartera[CUI],0))="","No informado",INDEX(tCartera[PMI2028],MATCH("2287700",tCartera[CUI],0)))) -> 109570 | O42: =IF(COUNTIF(tCartera[CUI],"2287700")=0,"Sin PMI",IF(INDEX(tCartera[PMI2029],MATCH("2287700",tCartera[CUI],0))="","No informado",INDEX(tCartera[PMI2029],MATCH("2287700",tCartera[CUI],0)))) -> 0
A43: =SUBTOTAL(103,$B$10:B43) -> 31 | B43: 112 | C43: 2480499: MEJORAMIENTO DE LA CARRETERA PU 146; EMP PE - 34 I (HUANCANE) - HUERTAPATA - VISCACHANI - QUELLAHUYO - EMP PE - 34 (CACUÑA), DISTRITO DE HUANCANE - PROVINCIA DE HUANCANE - DEPARTAMENTO DE PUNO | D43: =IF(COUNTIF(tSIAF[Clave],"2480499|112")=0,"",SUMIF(tSIAF[Clave],"2480499|112",tSIAF[PIM])) -> 3297813 | E43: =IF(COUNTIF(tSIAF[Clave],"2480499|112")=0,"",SUMIF(tSIAF[Clave],"2480499|112",tSIAF[Certificacion])) -> 3286650.5 | F43: =IF(D43="","",D43-E43) -> 11162.55 | G43: =IF(COUNTIF(tSIAF[Clave],"2480499|112")=0,"",SUMIF(tSIAF[Clave],"2480499|112",tSIAF[Devengado])) -> 3269277.3 | H43: =IF(D43="","",D43-G43) -> 28535.72 | I43: =IF(D43="","",IF(D43=0,0,G43/D43)) -> 0.99134708 | J43: EJECUCIÓN POR ADMINISTRACIÓN DIRECTA - DIRECTIVA 10 | K43: Por completar | L43: =IF(COUNTIF(tCartera[CUI],"2480499")=0,"Sin PMI",IF(INDEX(tCartera[PMI2026],MATCH("2480499",tCartera[CUI],0))="","No informado",INDEX(tCartera[PMI2026],MATCH("2480499",tCartera[CUI],0)))) -> 5406629 | M43: =IF(COUNTIF(tCartera[CUI],"2480499")=0,"Sin PMI",IF(INDEX(tCartera[PMI2027],MATCH("2480499",tCartera[CUI],0))="","No informado",INDEX(tCartera[PMI2027],MATCH("2480499",tCartera[CUI],0)))) -> 0 | N43: =IF(COUNTIF(tCartera[CUI],"2480499")=0,"Sin PMI",IF(INDEX(tCartera[PMI2028],MATCH("2480499",tCartera[CUI],0))="","No informado",INDEX(tCartera[PMI2028],MATCH("2480499",tCartera[CUI],0)))) -> 304959 | O43: =IF(COUNTIF(tCartera[CUI],"2480499")=0,"Sin PMI",IF(INDEX(tCartera[PMI2029],MATCH("2480499",tCartera[CUI],0))="","No informado",INDEX(tCartera[PMI2029],MATCH("2480499",tCartera[CUI],0)))) -> 0
A44: =SUBTOTAL(103,$B$10:B44) -> 32 | B44: 99 | C44: 2300575: MEJORAMIENTO DE LA AVENIDA CIRCUNVALACION II (EMP. PE- 3S-AV. HUANCANE-CIRCUNVALACION ESTE-EMP PE-3S) DE LA CIUDAD DE JULIACA- EMPALME PU-3S INICIO CON CIRCUNVALACION II - DISTRITO DE SAN MIGUEL - EMPALME PU-3S FINAL CON CIRCUNVALACION II - DISTRITO DE CARACOTO - PROVINCIA DE SAN ROMAN - REGION PUNO | D44: =IF(COUNTIF(tSIAF[Clave],"2300575|99")=0,"",SUMIF(tSIAF[Clave],"2300575|99",tSIAF[PIM])) -> 2394023 | E44: =IF(COUNTIF(tSIAF[Clave],"2300575|99")=0,"",SUMIF(tSIAF[Clave],"2300575|99",tSIAF[Certificacion])) -> 2316938.8 | F44: =IF(D44="","",D44-E44) -> 77084.21 | G44: =IF(COUNTIF(tSIAF[Clave],"2300575|99")=0,"",SUMIF(tSIAF[Clave],"2300575|99",tSIAF[Devengado])) -> 1138698.8 | H44: =IF(D44="","",D44-G44) -> 1255324.2 | I44: =IF(D44="","",IF(D44=0,0,G44/D44)) -> 0.4756424 | J44: EJECUCIÓN POR ADMINISTRACIÓN DIRECTA - DIRECTIVA 10 | K44: Por completar | L44: =IF(COUNTIF(tCartera[CUI],"2300575")=0,"Sin PMI",IF(INDEX(tCartera[PMI2026],MATCH("2300575",tCartera[CUI],0))="","No informado",INDEX(tCartera[PMI2026],MATCH("2300575",tCartera[CUI],0)))) -> 3545977 | M44: =IF(COUNTIF(tCartera[CUI],"2300575")=0,"Sin PMI",IF(INDEX(tCartera[PMI2027],MATCH("2300575",tCartera[CUI],0))="","No informado",INDEX(tCartera[PMI2027],MATCH("2300575",tCartera[CUI],0)))) -> 1000000 | N44: =IF(COUNTIF(tCartera[CUI],"2300575")=0,"Sin PMI",IF(INDEX(tCartera[PMI2028],MATCH("2300575",tCartera[CUI],0))="","No informado",INDEX(tCartera[PMI2028],MATCH("2300575",tCartera[CUI],0)))) -> 3651450 | O44: =IF(COUNTIF(tCartera[CUI],"2300575")=0,"Sin PMI",IF(INDEX(tCartera[PMI2029],MATCH("2300575",tCartera[CUI],0))="","No informado",INDEX(tCartera[PMI2029],MATCH("2300575",tCartera[CUI],0)))) -> 1489826
A45: =SUBTOTAL(103,$B$10:B45) -> 33 | B45: 87 | C45: 2031310: CONSTRUCCION Y MEJORAMIENTO DE LA CARRETERA SAN JOSE (EMP. R 100) VALLE GRANDE -ISILLUMA DEL DISTRITO DE ALTO INAMBARI | D45: =IF(COUNTIF(tSIAF[Clave],"2031310|87")=0,"",SUMIF(tSIAF[Clave],"2031310|87",tSIAF[PIM])) -> 1122559 | E45: =IF(COUNTIF(tSIAF[Clave],"2031310|87")=0,"",SUMIF(tSIAF[Clave],"2031310|87",tSIAF[Certificacion])) -> 1117871.1 | F45: =IF(D45="","",D45-E45) -> 4687.95 | G45: =IF(COUNTIF(tSIAF[Clave],"2031310|87")=0,"",SUMIF(tSIAF[Clave],"2031310|87",tSIAF[Devengado])) -> 1042098.6 | H45: =IF(D45="","",D45-G45) -> 80460.44 | I45: =IF(D45="","",IF(D45=0,0,G45/D45)) -> 0.92832409 | J45: EJECUCIÓN POR ADMINISTRACIÓN DIRECTA - DIRECTIVA 10 | K45: Por completar | L45: =IF(COUNTIF(tCartera[CUI],"2031310")=0,"Sin PMI",IF(INDEX(tCartera[PMI2026],MATCH("2031310",tCartera[CUI],0))="","No informado",INDEX(tCartera[PMI2026],MATCH("2031310",tCartera[CUI],0)))) -> 1404195 | M45: =IF(COUNTIF(tCartera[CUI],"2031310")=0,"Sin PMI",IF(INDEX(tCartera[PMI2027],MATCH("2031310",tCartera[CUI],0))="","No informado",INDEX(tCartera[PMI2027],MATCH("2031310",tCartera[CUI],0)))) -> 324567 | N45: =IF(COUNTIF(tCartera[CUI],"2031310")=0,"Sin PMI",IF(INDEX(tCartera[PMI2028],MATCH("2031310",tCartera[CUI],0))="","No informado",INDEX(tCartera[PMI2028],MATCH("2031310",tCartera[CUI],0)))) -> 0 | O45: =IF(COUNTIF(tCartera[CUI],"2031310")=0,"Sin PMI",IF(INDEX(tCartera[PMI2029],MATCH("2031310",tCartera[CUI],0))="","No informado",INDEX(tCartera[PMI2029],MATCH("2031310",tCartera[CUI],0)))) -> 936265
A46: =SUBTOTAL(103,$B$10:B46) -> 34 | B46: 92 | C46: 2163760: MEJORAMIENTO DE LA INFRAESTRUCTURA VIAL TURISTICO, TRAMO PHUTINI - JAYU JAYU, DISTRITO DE ACORA - PUNO - PUNO | D46: =IF(COUNTIF(tSIAF[Clave],"2163760|92")=0,"",SUMIF(tSIAF[Clave],"2163760|92",tSIAF[PIM])) -> 1202934 | E46: =IF(COUNTIF(tSIAF[Clave],"2163760|92")=0,"",SUMIF(tSIAF[Clave],"2163760|92",tSIAF[Certificacion])) -> 1151623.8 | F46: =IF(D46="","",D46-E46) -> 51310.21 | G46: =IF(COUNTIF(tSIAF[Clave],"2163760|92")=0,"",SUMIF(tSIAF[Clave],"2163760|92",tSIAF[Devengado])) -> 1105100.4 | H46: =IF(D46="","",D46-G46) -> 97833.58 | I46: =IF(D46="","",IF(D46=0,0,G46/D46)) -> 0.91867087 | J46: EJECUCIÓN POR ADMINISTRACIÓN DIRECTA - DIRECTIVA 10 | K46: Por completar | L46: =IF(COUNTIF(tCartera[CUI],"2163760")=0,"Sin PMI",IF(INDEX(tCartera[PMI2026],MATCH("2163760",tCartera[CUI],0))="","No informado",INDEX(tCartera[PMI2026],MATCH("2163760",tCartera[CUI],0)))) -> 2596051 | M46: =IF(COUNTIF(tCartera[CUI],"2163760")=0,"Sin PMI",IF(INDEX(tCartera[PMI2027],MATCH("2163760",tCartera[CUI],0))="","No informado",INDEX(tCartera[PMI2027],MATCH("2163760",tCartera[CUI],0)))) -> 120000 | N46: =IF(COUNTIF(tCartera[CUI],"2163760")=0,"Sin PMI",IF(INDEX(tCartera[PMI2028],MATCH("2163760",tCartera[CUI],0))="","No informado",INDEX(tCartera[PMI2028],MATCH("2163760",tCartera[CUI],0)))) -> 2215461 | O46: =IF(COUNTIF(tCartera[CUI],"2163760")=0,"Sin PMI",IF(INDEX(tCartera[PMI2029],MATCH("2163760",tCartera[CUI],0))="","No informado",INDEX(tCartera[PMI2029],MATCH("2163760",tCartera[CUI],0)))) -> 3675255
A47: =SUBTOTAL(103,$B$10:B47) -> 35 | B47: 104 | C47: 2375549: CREACION DE LA INFRAESTRUCTURA DE INTEGRACION VIAL ENTRE SANDIA (CP. QUENEQUE) Y PATAMBUCO (C.P. TIRACA), DISTRITO DE SANDIA Y PATAMBUCO, PROVINCIA DE SANDIA - PUNO | D47: =IF(COUNTIF(tSIAF[Clave],"2375549|104")=0,"",SUMIF(tSIAF[Clave],"2375549|104",tSIAF[PIM])) -> 167638 | E47: =IF(COUNTIF(tSIAF[Clave],"2375549|104")=0,"",SUMIF(tSIAF[Clave],"2375549|104",tSIAF[Certificacion])) -> 167637.03 | F47: =IF(D47="","",D47-E47) -> 0.97 | G47: =IF(COUNTIF(tSIAF[Clave],"2375549|104")=0,"",SUMIF(tSIAF[Clave],"2375549|104",tSIAF[Devengado])) -> 124800.07 | H47: =IF(D47="","",D47-G47) -> 42837.93 | I47: =IF(D47="","",IF(D47=0,0,G47/D47)) -> 0.7444617 | J47: EJECUCIÓN POR ADMINISTRACIÓN DIRECTA - DIRECTIVA 10 | K47: Por completar | L47: =IF(COUNTIF(tCartera[CUI],"2375549")=0,"Sin PMI",IF(INDEX(tCartera[PMI2026],MATCH("2375549",tCartera[CUI],0))="","No informado",INDEX(tCartera[PMI2026],MATCH("2375549",tCartera[CUI],0)))) -> 1200000 | M47: =IF(COUNTIF(tCartera[CUI],"2375549")=0,"Sin PMI",IF(INDEX(tCartera[PMI2027],MATCH("2375549",tCartera[CUI],0))="","No informado",INDEX(tCartera[PMI2027],MATCH("2375549",tCartera[CUI],0)))) -> 2500000 | N47: =IF(COUNTIF(tCartera[CUI],"2375549")=0,"Sin PMI",IF(INDEX(tCartera[PMI2028],MATCH("2375549",tCartera[CUI],0))="","No informado",INDEX(tCartera[PMI2028],MATCH("2375549",tCartera[CUI],0)))) -> 2882362 | O47: =IF(COUNTIF(tCartera[CUI],"2375549")=0,"Sin PMI",IF(INDEX(tCartera[PMI2029],MATCH("2375549",tCartera[CUI],0))="","No informado",INDEX(tCartera[PMI2029],MATCH("2375549",tCartera[CUI],0)))) -> 1526602
A48: =SUBTOTAL(103,$B$10:B48) -> 36 | B48: 101 | C48: 2321290: MEJORAMIENTO DE LOS SERVICIOS DE TRANSITABILIDAD DE LA VIA VECINAL PU-595: DV. PAMPA BLANCA - RINCONADA - CERRO LUNAR, DISTRITO DE ANANEA, PROVINCIA DE SAN ANTONIO DE PUTINA - PUNO | D48: =IF(COUNTIF(tSIAF[Clave],"2321290|101")=0,"",SUMIF(tSIAF[Clave],"2321290|101",tSIAF[PIM])) -> 844818 | E48: =IF(COUNTIF(tSIAF[Clave],"2321290|101")=0,"",SUMIF(tSIAF[Clave],"2321290|101",tSIAF[Certificacion])) -> 75387.03 | F48: =IF(D48="","",D48-E48) -> 769430.97 | G48: =IF(COUNTIF(tSIAF[Clave],"2321290|101")=0,"",SUMIF(tSIAF[Clave],"2321290|101",tSIAF[Devengado])) -> 75387.03 | H48: =IF(D48="","",D48-G48) -> 769430.97 | I48: =IF(D48="","",IF(D48=0,0,G48/D48)) -> 0.08923464 | J48: EJECUCIÓN POR ADMINISTRACIÓN DIRECTA - DIRECTIVA 10 | K48: Por completar | L48: =IF(COUNTIF(tCartera[CUI],"2321290")=0,"Sin PMI",IF(INDEX(tCartera[PMI2026],MATCH("2321290",tCartera[CUI],0))="","No informado",INDEX(tCartera[PMI2026],MATCH("2321290",tCartera[CUI],0)))) -> 1050000 | M48: =IF(COUNTIF(tCartera[CUI],"2321290")=0,"Sin PMI",IF(INDEX(tCartera[PMI2027],MATCH("2321290",tCartera[CUI],0))="","No informado",INDEX(tCartera[PMI2027],MATCH("2321290",tCartera[CUI],0)))) -> 50000 | N48: =IF(COUNTIF(tCartera[CUI],"2321290")=0,"Sin PMI",IF(INDEX(tCartera[PMI2028],MATCH("2321290",tCartera[CUI],0))="","No informado",INDEX(tCartera[PMI2028],MATCH("2321290",tCartera[CUI],0)))) -> 1054806 | O48: =IF(COUNTIF(tCartera[CUI],"2321290")=0,"Sin PMI",IF(INDEX(tCartera[PMI2029],MATCH("2321290",tCartera[CUI],0))="","No informado",INDEX(tCartera[PMI2029],MATCH("2321290",tCartera[CUI],0)))) -> 0
A49: =SUBTOTAL(103,$B$10:B49) -> 37 | B49: 166 | C49: 2475053: MEJORAMIENTO DEL SERVICIO DE MOVILIDAD URBANA DE LA AV. ANDRES AVELINO CACERES (TRAMO: AV. TUPAC YUPANQUI - AV. AVIACION), AV. LOS GERANIOS DEL DISTRITO DE JULIACA - PROVINCIA DE SAN ROMAN - DEPARTAMENTO DE PUNO | D49: =IF(COUNTIF(tSIAF[Clave],"2475053|166")=0,"",SUMIF(tSIAF[Clave],"2475053|166",tSIAF[PIM])) -> 0 | E49: =IF(COUNTIF(tSIAF[Clave],"2475053|166")=0,"",SUMIF(tSIAF[Clave],"2475053|166",tSIAF[Certificacion])) -> 0 | F49: =IF(D49="","",D49-E49) -> 0 | G49: =IF(COUNTIF(tSIAF[Clave],"2475053|166")=0,"",SUMIF(tSIAF[Clave],"2475053|166",tSIAF[Devengado])) -> 0 | H49: =IF(D49="","",D49-G49) -> 0 | I49: =IF(D49="","",IF(D49=0,0,G49/D49)) -> 0 | J49: EJECUCIÓN POR ADMINISTRACIÓN DIRECTA - DIRECTIVA 10 | K49: Por completar | L49: =IF(COUNTIF(tCartera[CUI],"2475053")=0,"Sin PMI",IF(INDEX(tCartera[PMI2026],MATCH("2475053",tCartera[CUI],0))="","No informado",INDEX(tCartera[PMI2026],MATCH("2475053",tCartera[CUI],0)))) -> 675842 | M49: =IF(COUNTIF(tCartera[CUI],"2475053")=0,"Sin PMI",IF(INDEX(tCartera[PMI2027],MATCH("2475053",tCartera[CUI],0))="","No informado",INDEX(tCartera[PMI2027],MATCH("2475053",tCartera[CUI],0)))) -> 110000 | N49: =IF(COUNTIF(tCartera[CUI],"2475053")=0,"Sin PMI",IF(INDEX(tCartera[PMI2028],MATCH("2475053",tCartera[CUI],0))="","No informado",INDEX(tCartera[PMI2028],MATCH("2475053",tCartera[CUI],0)))) -> 0 | O49: =IF(COUNTIF(tCartera[CUI],"2475053")=0,"Sin PMI",IF(INDEX(tCartera[PMI2029],MATCH("2475053",tCartera[CUI],0))="","No informado",INDEX(tCartera[PMI2029],MATCH("2475053",tCartera[CUI],0)))) -> 0
A50: =SUBTOTAL(103,$B$10:B50) -> 38 | B50: 90 | C50: 2131661: CONSTRUCCION Y MEJORAMIENTO DE LA CARRETERA DESVIO VILQUECHICO-COJATA-SINA-YANAHUAYA | D50: =IF(COUNTIF(tSIAF[Clave],"2131661|90")=0,"",SUMIF(tSIAF[Clave],"2131661|90",tSIAF[PIM])) -> 459851 | E50: =IF(COUNTIF(tSIAF[Clave],"2131661|90")=0,"",SUMIF(tSIAF[Clave],"2131661|90",tSIAF[Certificacion])) -> 344060.18 | F50: =IF(D50="","",D50-E50) -> 115790.82 | G50: =IF(COUNTIF(tSIAF[Clave],"2131661|90")=0,"",SUMIF(tSIAF[Clave],"2131661|90",tSIAF[Devengado])) -> 300345.76 | H50: =IF(D50="","",D50-G50) -> 159505.24 | I50: =IF(D50="","",IF(D50=0,0,G50/D50)) -> 0.65313712 | J50: EJECUCIÓN POR ADMINISTRACIÓN DIRECTA - DIRECTIVA 10 | K50: Por completar | L50: =IF(COUNTIF(tCartera[CUI],"2131661")=0,"Sin PMI",IF(INDEX(tCartera[PMI2026],MATCH("2131661",tCartera[CUI],0))="","No informado",INDEX(tCartera[PMI2026],MATCH("2131661",tCartera[CUI],0)))) -> 4800690 | M50: =IF(COUNTIF(tCartera[CUI],"2131661")=0,"Sin PMI",IF(INDEX(tCartera[PMI2027],MATCH("2131661",tCartera[CUI],0))="","No informado",INDEX(tCartera[PMI2027],MATCH("2131661",tCartera[CUI],0)))) -> 4000000 | N50: =IF(COUNTIF(tCartera[CUI],"2131661")=0,"Sin PMI",IF(INDEX(tCartera[PMI2028],MATCH("2131661",tCartera[CUI],0))="","No informado",INDEX(tCartera[PMI2028],MATCH("2131661",tCartera[CUI],0)))) -> 14883202 | O50: =IF(COUNTIF(tCartera[CUI],"2131661")=0,"Sin PMI",IF(INDEX(tCartera[PMI2029],MATCH("2131661",tCartera[CUI],0))="","No informado",INDEX(tCartera[PMI2029],MATCH("2131661",tCartera[CUI],0)))) -> 19038629
A51: =SUBTOTAL(103,$B$10:B51) -> 39 | B51: 96 | C51: 2195487: MEJORAMIENTO DEL CAMINO VECINAL (EMP. PE 3S) HUAQUINA ZAPIJICANE - PTO JULI - CHUCASUYO DEL DISTRITO DE JULI - PROVINCIA DE CHUCUITO - DEPARTAMENTO DE PUNO | D51: =IF(COUNTIF(tSIAF[Clave],"2195487|96")=0,"",SUMIF(tSIAF[Clave],"2195487|96",tSIAF[PIM])) -> 91759 | E51: =IF(COUNTIF(tSIAF[Clave],"2195487|96")=0,"",SUMIF(tSIAF[Clave],"2195487|96",tSIAF[Certificacion])) -> 91758.5 | F51: =IF(D51="","",D51-E51) -> 0.5 | G51: =IF(COUNTIF(tSIAF[Clave],"2195487|96")=0,"",SUMIF(tSIAF[Clave],"2195487|96",tSIAF[Devengado])) -> 82094.58 | H51: =IF(D51="","",D51-G51) -> 9664.42 | I51: =IF(D51="","",IF(D51=0,0,G51/D51)) -> 0.89467605 | J51: EJECUCIÓN POR ADMINISTRACIÓN DIRECTA - DIRECTIVA 10 | K51: Por completar | L51: =IF(COUNTIF(tCartera[CUI],"2195487")=0,"Sin PMI",IF(INDEX(tCartera[PMI2026],MATCH("2195487",tCartera[CUI],0))="","No informado",INDEX(tCartera[PMI2026],MATCH("2195487",tCartera[CUI],0)))) -> 774665 | M51: =IF(COUNTIF(tCartera[CUI],"2195487")=0,"Sin PMI",IF(INDEX(tCartera[PMI2027],MATCH("2195487",tCartera[CUI],0))="","No informado",INDEX(tCartera[PMI2027],MATCH("2195487",tCartera[CUI],0)))) -> 0 | N51: =IF(COUNTIF(tCartera[CUI],"2195487")=0,"Sin PMI",IF(INDEX(tCartera[PMI2028],MATCH("2195487",tCartera[CUI],0))="","No informado",INDEX(tCartera[PMI2028],MATCH("2195487",tCartera[CUI],0)))) -> 707599 | O51: =IF(COUNTIF(tCartera[CUI],"2195487")=0,"Sin PMI",IF(INDEX(tCartera[PMI2029],MATCH("2195487",tCartera[CUI],0))="","No informado",INDEX(tCartera[PMI2029],MATCH("2195487",tCartera[CUI],0)))) -> 0
A52: =SUBTOTAL(103,$B$10:B52) -> 40 | B52: 113 | C52: 2514428: CREACION DEL SERVICIO DE INTERCONEXION DE MOVILIDAD URBANA EN LA VIA TRONCAL DEL PUENTE YARAJA DISTRITO DE AZANGARO - PROVINCIA DE AZANGARO - DEPARTAMENTO DE PUNO | D52: =IF(COUNTIF(tSIAF[Clave],"2514428|113")=0,"",SUMIF(tSIAF[Clave],"2514428|113",tSIAF[PIM])) -> 104124 | E52: =IF(COUNTIF(tSIAF[Clave],"2514428|113")=0,"",SUMIF(tSIAF[Clave],"2514428|113",tSIAF[Certificacion])) -> 48234.88 | F52: =IF(D52="","",D52-E52) -> 55889.12 | G52: =IF(COUNTIF(tSIAF[Clave],"2514428|113")=0,"",SUMIF(tSIAF[Clave],"2514428|113",tSIAF[Devengado])) -> 48234.88 | H52: =IF(D52="","",D52-G52) -> 55889.12 | I52: =IF(D52="","",IF(D52=0,0,G52/D52)) -> 0.46324459 | J52: EJECUCIÓN POR ADMINISTRACIÓN DIRECTA - DIRECTIVA 10 | K52: Por completar | L52: =IF(COUNTIF(tCartera[CUI],"2514428")=0,"Sin PMI",IF(INDEX(tCartera[PMI2026],MATCH("2514428",tCartera[CUI],0))="","No informado",INDEX(tCartera[PMI2026],MATCH("2514428",tCartera[CUI],0)))) -> 228677 | M52: =IF(COUNTIF(tCartera[CUI],"2514428")=0,"Sin PMI",IF(INDEX(tCartera[PMI2027],MATCH("2514428",tCartera[CUI],0))="","No informado",INDEX(tCartera[PMI2027],MATCH("2514428",tCartera[CUI],0)))) -> 0 | N52: =IF(COUNTIF(tCartera[CUI],"2514428")=0,"Sin PMI",IF(INDEX(tCartera[PMI2028],MATCH("2514428",tCartera[CUI],0))="","No informado",INDEX(tCartera[PMI2028],MATCH("2514428",tCartera[CUI],0)))) -> 0 | O52: =IF(COUNTIF(tCartera[CUI],"2514428")=0,"Sin PMI",IF(INDEX(tCartera[PMI2029],MATCH("2514428",tCartera[CUI],0))="","No informado",INDEX(tCartera[PMI2029],MATCH("2514428",tCartera[CUI],0)))) -> 865181
A53: =SUBTOTAL(103,$B$10:B53) -> 41 | B53: 107 | C53: 2436247.MEJORAMIENTO DEL CAMINO VECINAL RUTA PU-713, EMP. PE 3S (AYAVIRI - DESV. CALUYO - TINAJANI - L. PROV. LAMPA), DISTRITO DE AYAVIRI - PROVINCIA DE MELGAR - DEPARTAMENTO DE PUNO | D53: =IF(COUNTIF(tSIAF[Clave],"2436247|107")=0,"",SUMIF(tSIAF[Clave],"2436247|107",tSIAF[PIM])) -> 22224878 | E53: =IF(COUNTIF(tSIAF[Clave],"2436247|107")=0,"",SUMIF(tSIAF[Clave],"2436247|107",tSIAF[Certificacion])) -> 21946068 | F53: =IF(D53="","",D53-E53) -> 278809.8 | G53: =IF(COUNTIF(tSIAF[Clave],"2436247|107")=0,"",SUMIF(tSIAF[Clave],"2436247|107",tSIAF[Devengado])) -> 7073509.6 | H53: =IF(D53="","",D53-G53) -> 15151368 | I53: =IF(D53="","",IF(D53=0,0,G53/D53)) -> 0.31826989 | J53: EJECUCIÓN POR ADMINISTRACIÓN DIRECTA - DIRECTIVA 10 | K53: Por completar | L53: =IF(COUNTIF(tCartera[CUI],"2436247")=0,"Sin PMI",IF(INDEX(tCartera[PMI2026],MATCH("2436247",tCartera[CUI],0))="","No informado",INDEX(tCartera[PMI2026],MATCH("2436247",tCartera[CUI],0)))) -> Sin PMI | M53: =IF(COUNTIF(tCartera[CUI],"2436247")=0,"Sin PMI",IF(INDEX(tCartera[PMI2027],MATCH("2436247",tCartera[CUI],0))="","No informado",INDEX(tCartera[PMI2027],MATCH("2436247",tCartera[CUI],0)))) -> Sin PMI | N53: =IF(COUNTIF(tCartera[CUI],"2436247")=0,"Sin PMI",IF(INDEX(tCartera[PMI2028],MATCH("2436247",tCartera[CUI],0))="","No informado",INDEX(tCartera[PMI2028],MATCH("2436247",tCartera[CUI],0)))) -> Sin PMI | O53: =IF(COUNTIF(tCartera[CUI],"2436247")=0,"Sin PMI",IF(INDEX(tCartera[PMI2029],MATCH("2436247",tCartera[CUI],0))="","No informado",INDEX(tCartera[PMI2029],MATCH("2436247",tCartera[CUI],0)))) -> Sin PMI
A54: =SUBTOTAL(103,$B$10:B54) -> 42 | B54: 124 | C54: 2603167.MEJORAMIENTO DEL SERVICIO DE TRANSITABILIDAD VIAL INTERURBANA EN LA CARRETERA PU - 1233 (ILAVE) - ANOKARIRI (EMP. - 1234), ANOKARIRI - SACUYO - SECTOR NUEVA ALIANZA, PU 1103 (SECTOR NUEVA ALIANZA) - EMP. PE 36P (LARAQUERI PICHACANI) DISTRITOS DE I | D54: =IF(COUNTIF(tSIAF[Clave],"2603167|124")=0,"",SUMIF(tSIAF[Clave],"2603167|124",tSIAF[PIM])) -> 11412366 | E54: =IF(COUNTIF(tSIAF[Clave],"2603167|124")=0,"",SUMIF(tSIAF[Clave],"2603167|124",tSIAF[Certificacion])) -> 10878205 | F54: =IF(D54="","",D54-E54) -> 534160.77 | G54: =IF(COUNTIF(tSIAF[Clave],"2603167|124")=0,"",SUMIF(tSIAF[Clave],"2603167|124",tSIAF[Devengado])) -> 6860678.4 | H54: =IF(D54="","",D54-G54) -> 4551687.6 | I54: =IF(D54="","",IF(D54=0,0,G54/D54)) -> 0.60116179 | J54: EJECUCIÓN POR ADMINISTRACIÓN DIRECTA - DIRECTIVA 10 | K54: Por completar | L54: =IF(COUNTIF(tCartera[CUI],"2603167")=0,"Sin PMI",IF(INDEX(tCartera[PMI2026],MATCH("2603167",tCartera[CUI],0))="","No informado",INDEX(tCartera[PMI2026],MATCH("2603167",tCartera[CUI],0)))) -> 2800000 | M54: =IF(COUNTIF(tCartera[CUI],"2603167")=0,"Sin PMI",IF(INDEX(tCartera[PMI2027],MATCH("2603167",tCartera[CUI],0))="","No informado",INDEX(tCartera[PMI2027],MATCH("2603167",tCartera[CUI],0)))) -> 10234564 | N54: =IF(COUNTIF(tCartera[CUI],"2603167")=0,"Sin PMI",IF(INDEX(tCartera[PMI2028],MATCH("2603167",tCartera[CUI],0))="","No informado",INDEX(tCartera[PMI2028],MATCH("2603167",tCartera[CUI],0)))) -> 6182303 | O54: =IF(COUNTIF(tCartera[CUI],"2603167")=0,"Sin PMI",IF(INDEX(tCartera[PMI2029],MATCH("2603167",tCartera[CUI],0))="","No informado",INDEX(tCartera[PMI2029],MATCH("2603167",tCartera[CUI],0)))) -> 9563936
A55: =SUBTOTAL(103,$B$10:B55) -> 43 | B55: 116 | C55: 2585540: MEJORAMIENTO DEL SERVICIO DE TRANSITABILIDAD VIAL INTERURBANA EN LA CARRETERA PU-139 (HDA. POTONI) - SAN JOSE, - COLLANA - EMP. PU-111 - PUENTE YARAJA (AZANGARO) DISTRITOS DE POTONI, SAN JOSE DE LA PROVINCIA DE AZANGARO DEL DEPARTAMENTO DE PUNO | D55: =IF(COUNTIF(tSIAF[Clave],"2585540|116")=0,"",SUMIF(tSIAF[Clave],"2585540|116",tSIAF[PIM])) -> 6736048 | E55: =IF(COUNTIF(tSIAF[Clave],"2585540|116")=0,"",SUMIF(tSIAF[Clave],"2585540|116",tSIAF[Certificacion])) -> 6652871.2 | F55: =IF(D55="","",D55-E55) -> 83176.79 | G55: =IF(COUNTIF(tSIAF[Clave],"2585540|116")=0,"",SUMIF(tSIAF[Clave],"2585540|116",tSIAF[Devengado])) -> 3336854.4 | H55: =IF(D55="","",D55-G55) -> 3399193.6 | I55: =IF(D55="","",IF(D55=0,0,G55/D55)) -> 0.49537271 | J55: EJECUCIÓN POR ADMINISTRACIÓN DIRECTA - DIRECTIVA 10 | K55: Por completar | L55: =IF(COUNTIF(tCartera[CUI],"2585540")=0,"Sin PMI",IF(INDEX(tCartera[PMI2026],MATCH("2585540",tCartera[CUI],0))="","No informado",INDEX(tCartera[PMI2026],MATCH("2585540",tCartera[CUI],0)))) -> 800000 | M55: =IF(COUNTIF(tCartera[CUI],"2585540")=0,"Sin PMI",IF(INDEX(tCartera[PMI2027],MATCH("2585540",tCartera[CUI],0))="","No informado",INDEX(tCartera[PMI2027],MATCH("2585540",tCartera[CUI],0)))) -> 12057170 | N55: =IF(COUNTIF(tCartera[CUI],"2585540")=0,"Sin PMI",IF(INDEX(tCartera[PMI2028],MATCH("2585540",tCartera[CUI],0))="","No informado",INDEX(tCartera[PMI2028],MATCH("2585540",tCartera[CUI],0)))) -> 6000000 | O55: =IF(COUNTIF(tCartera[CUI],"2585540")=0,"Sin PMI",IF(INDEX(tCartera[PMI2029],MATCH("2585540",tCartera[CUI],0))="","No informado",INDEX(tCartera[PMI2029],MATCH("2585540",tCartera[CUI],0)))) -> 7375100
A56: =SUBTOTAL(103,$B$10:B56) -> 44 | B56: 123 | C56: 2603165: MEJORAMIENTO DEL SERVICIO DE TRANSITABILIDAD VIAL INTERURBANA EN LA CARRETERA TRAMO ACHAYA - EMP. PU 113(ARAPA), DE LOS DISTRITOS DE ACHAYA, ARAPA DE LA PROVINCIA DE AZANGARO DEL DEPARTAMENTO DE PUNO | D56: =IF(COUNTIF(tSIAF[Clave],"2603165|123")=0,"",SUMIF(tSIAF[Clave],"2603165|123",tSIAF[PIM])) -> 9037622 | E56: =IF(COUNTIF(tSIAF[Clave],"2603165|123")=0,"",SUMIF(tSIAF[Clave],"2603165|123",tSIAF[Certificacion])) -> 8236997.1 | F56: =IF(D56="","",D56-E56) -> 800624.91 | G56: =IF(COUNTIF(tSIAF[Clave],"2603165|123")=0,"",SUMIF(tSIAF[Clave],"2603165|123",tSIAF[Devengado])) -> 5290297.7 | H56: =IF(D56="","",D56-G56) -> 3747324.3 | I56: =IF(D56="","",IF(D56=0,0,G56/D56)) -> 0.5853639 | J56: EJECUCIÓN POR ADMINISTRACIÓN DIRECTA - DIRECTIVA 10 | K56: Por completar | L56: =IF(COUNTIF(tCartera[CUI],"2603165")=0,"Sin PMI",IF(INDEX(tCartera[PMI2026],MATCH("2603165",tCartera[CUI],0))="","No informado",INDEX(tCartera[PMI2026],MATCH("2603165",tCartera[CUI],0)))) -> 2500000 | M56: =IF(COUNTIF(tCartera[CUI],"2603165")=0,"Sin PMI",IF(INDEX(tCartera[PMI2027],MATCH("2603165",tCartera[CUI],0))="","No informado",INDEX(tCartera[PMI2027],MATCH("2603165",tCartera[CUI],0)))) -> 6578987 | N56: =IF(COUNTIF(tCartera[CUI],"2603165")=0,"Sin PMI",IF(INDEX(tCartera[PMI2028],MATCH("2603165",tCartera[CUI],0))="","No informado",INDEX(tCartera[PMI2028],MATCH("2603165",tCartera[CUI],0)))) -> 6552040 | O56: =IF(COUNTIF(tCartera[CUI],"2603165")=0,"Sin PMI",IF(INDEX(tCartera[PMI2029],MATCH("2603165",tCartera[CUI],0))="","No informado",INDEX(tCartera[PMI2029],MATCH("2603165",tCartera[CUI],0)))) -> 2921013
A57: =SUBTOTAL(103,$B$10:B57) -> 45 | B57: 94 | C57: 2185578: MEJORAMIENTO DE LA CARRETERA DV. DESAGUADERO (EMP PE 36A) - KELLUYO - PISACOMA, PROVINCIA DE CHUCUITO - PUNO | D57: =IF(COUNTIF(tSIAF[Clave],"2185578|94")=0,"",SUMIF(tSIAF[Clave],"2185578|94",tSIAF[PIM])) -> 67139 | E57: =IF(COUNTIF(tSIAF[Clave],"2185578|94")=0,"",SUMIF(tSIAF[Clave],"2185578|94",tSIAF[Certificacion])) -> 0 | F57: =IF(D57="","",D57-E57) -> 67139 | G57: =IF(COUNTIF(tSIAF[Clave],"2185578|94")=0,"",SUMIF(tSIAF[Clave],"2185578|94",tSIAF[Devengado])) -> 0 | H57: =IF(D57="","",D57-G57) -> 67139 | I57: =IF(D57="","",IF(D57=0,0,G57/D57)) -> 0 | J57: EJECUCIÓN POR ADMINISTRACIÓN DIRECTA - DIRECTIVA 10 | K57: Por completar | L57: =IF(COUNTIF(tCartera[CUI],"2185578")=0,"Sin PMI",IF(INDEX(tCartera[PMI2026],MATCH("2185578",tCartera[CUI],0))="","No informado",INDEX(tCartera[PMI2026],MATCH("2185578",tCartera[CUI],0)))) -> 1732548 | M57: =IF(COUNTIF(tCartera[CUI],"2185578")=0,"Sin PMI",IF(INDEX(tCartera[PMI2027],MATCH("2185578",tCartera[CUI],0))="","No informado",INDEX(tCartera[PMI2027],MATCH("2185578",tCartera[CUI],0)))) -> 0 | N57: =IF(COUNTIF(tCartera[CUI],"2185578")=0,"Sin PMI",IF(INDEX(tCartera[PMI2028],MATCH("2185578",tCartera[CUI],0))="","No informado",INDEX(tCartera[PMI2028],MATCH("2185578",tCartera[CUI],0)))) -> 2325267 | O57: =IF(COUNTIF(tCartera[CUI],"2185578")=0,"Sin PMI",IF(INDEX(tCartera[PMI2029],MATCH("2185578",tCartera[CUI],0))="","No informado",INDEX(tCartera[PMI2029],MATCH("2185578",tCartera[CUI],0)))) -> 0
A58: =SUBTOTAL(103,$B$10:B58) -> 46 | B58: 433 | C58: 2515272: RECUPERACION DEL PUENTE COLGANTE PEATONAL SOBRE EL RIO INAMBARI EN LA LOCALIDAD SANTA ROSA YANAMAYO DEL DISTRITO DE ALTO INAMBARI - PROVINCIA DE SANDIA - DEPARTAMENTO DE PUNO | D58: =IF(COUNTIF(tSIAF[Clave],"2515272|433")=0,"",SUMIF(tSIAF[Clave],"2515272|433",tSIAF[PIM])) -> 105000 | E58: =IF(COUNTIF(tSIAF[Clave],"2515272|433")=0,"",SUMIF(tSIAF[Clave],"2515272|433",tSIAF[Certificacion])) -> 44312.3 | F58: =IF(D58="","",D58-E58) -> 60687.7 | G58: =IF(COUNTIF(tSIAF[Clave],"2515272|433")=0,"",SUMIF(tSIAF[Clave],"2515272|433",tSIAF[Devengado])) -> 39935.87 | H58: =IF(D58="","",D58-G58) -> 65064.13 | I58: =IF(D58="","",IF(D58=0,0,G58/D58)) -> 0.38034162 | J58: EJECUCIÓN POR ADMINISTRACIÓN DIRECTA - DIRECTIVA 10 | K58: Por completar | L58: =IF(COUNTIF(tCartera[CUI],"2515272")=0,"Sin PMI",IF(INDEX(tCartera[PMI2026],MATCH("2515272",tCartera[CUI],0))="","No informado",INDEX(tCartera[PMI2026],MATCH("2515272",tCartera[CUI],0)))) -> 105000 | M58: =IF(COUNTIF(tCartera[CUI],"2515272")=0,"Sin PMI",IF(INDEX(tCartera[PMI2027],MATCH("2515272",tCartera[CUI],0))="","No informado",INDEX(tCartera[PMI2027],MATCH("2515272",tCartera[CUI],0)))) -> 0 | N58: =IF(COUNTIF(tCartera[CUI],"2515272")=0,"Sin PMI",IF(INDEX(tCartera[PMI2028],MATCH("2515272",tCartera[CUI],0))="","No informado",INDEX(tCartera[PMI2028],MATCH("2515272",tCartera[CUI],0)))) -> 0 | O58: =IF(COUNTIF(tCartera[CUI],"2515272")=0,"Sin PMI",IF(INDEX(tCartera[PMI2029],MATCH("2515272",tCartera[CUI],0))="","No informado",INDEX(tCartera[PMI2029],MATCH("2515272",tCartera[CUI],0)))) -> 0
A59: =SUBTOTAL(103,$B$10:B59) -> 47 | B59: 508 | C59: 2585540.MEJORAMIENTO DEL SERVICIO DE TRANSITABILIDAD VIAL INTERURBANA EN LA CARRETERA PU-139 (HDA. POTONI) - SAN JOSE, - COLLANA - EMP. PU-111 - PUENTE YARAJA (AZANGARO) DISTRITOS DE POTONI, SAN JOSE DE LA PROVINCIA DE AZANGARO DEL DEPARTAMENTO DE PUNO | D59: =IF(COUNTIF(tSIAF[Clave],"2585540|508")=0,"",SUMIF(tSIAF[Clave],"2585540|508",tSIAF[PIM])) -> 94054 | E59: =IF(COUNTIF(tSIAF[Clave],"2585540|508")=0,"",SUMIF(tSIAF[Clave],"2585540|508",tSIAF[Certificacion])) -> 94054 | F59: =IF(D59="","",D59-E59) -> 0 | G59: =IF(COUNTIF(tSIAF[Clave],"2585540|508")=0,"",SUMIF(tSIAF[Clave],"2585540|508",tSIAF[Devengado])) -> 60075.86 | H59: =IF(D59="","",D59-G59) -> 33978.14 | I59: =IF(D59="","",IF(D59=0,0,G59/D59)) -> 0.63873796 | J59: EJECUCIÓN POR ADMINISTRACIÓN DIRECTA - DIRECTIVA 10 | K59: Por completar | L59: =IF(COUNTIF(tCartera[CUI],"2585540")=0,"Sin PMI",IF(INDEX(tCartera[PMI2026],MATCH("2585540",tCartera[CUI],0))="","No informado",INDEX(tCartera[PMI2026],MATCH("2585540",tCartera[CUI],0)))) -> 800000 | M59: =IF(COUNTIF(tCartera[CUI],"2585540")=0,"Sin PMI",IF(INDEX(tCartera[PMI2027],MATCH("2585540",tCartera[CUI],0))="","No informado",INDEX(tCartera[PMI2027],MATCH("2585540",tCartera[CUI],0)))) -> 12057170 | N59: =IF(COUNTIF(tCartera[CUI],"2585540")=0,"Sin PMI",IF(INDEX(tCartera[PMI2028],MATCH("2585540",tCartera[CUI],0))="","No informado",INDEX(tCartera[PMI2028],MATCH("2585540",tCartera[CUI],0)))) -> 6000000 | O59: =IF(COUNTIF(tCartera[CUI],"2585540")=0,"Sin PMI",IF(INDEX(tCartera[PMI2029],MATCH("2585540",tCartera[CUI],0))="","No informado",INDEX(tCartera[PMI2029],MATCH("2585540",tCartera[CUI],0)))) -> 7375100
A60: =SUBTOTAL(103,$B$10:B60) -> 48 | B60: 457 | C60: 2440946.MEJORAMIENTO DEL SERVICIO DE TRANSITABILIDAD VEHICULAR DE LA CARRETERA TRAMO ACHAYA (PU-140) - ESTRELLA (EMP. PE- 3S) DEL DISTRITO DE ACHAYA - PROVINCIA DE AZANGARO - DEPARTAMENTO DE PUNO | D60: =IF(COUNTIF(tSIAF[Clave],"2440946|457")=0,"",SUMIF(tSIAF[Clave],"2440946|457",tSIAF[PIM])) -> 28752 | E60: =IF(COUNTIF(tSIAF[Clave],"2440946|457")=0,"",SUMIF(tSIAF[Clave],"2440946|457",tSIAF[Certificacion])) -> 28751.6 | F60: =IF(D60="","",D60-E60) -> 0.4 | G60: =IF(COUNTIF(tSIAF[Clave],"2440946|457")=0,"",SUMIF(tSIAF[Clave],"2440946|457",tSIAF[Devengado])) -> 28751.6 | H60: =IF(D60="","",D60-G60) -> 0.4 | I60: =IF(D60="","",IF(D60=0,0,G60/D60)) -> 0.99998609 | J60: EJECUCIÓN POR ADMINISTRACIÓN DIRECTA - DIRECTIVA 10 | K60: Por completar | L60: =IF(COUNTIF(tCartera[CUI],"2440946")=0,"Sin PMI",IF(INDEX(tCartera[PMI2026],MATCH("2440946",tCartera[CUI],0))="","No informado",INDEX(tCartera[PMI2026],MATCH("2440946",tCartera[CUI],0)))) -> 28752 | M60: =IF(COUNTIF(tCartera[CUI],"2440946")=0,"Sin PMI",IF(INDEX(tCartera[PMI2027],MATCH("2440946",tCartera[CUI],0))="","No informado",INDEX(tCartera[PMI2027],MATCH("2440946",tCartera[CUI],0)))) -> 50000 | N60: =IF(COUNTIF(tCartera[CUI],"2440946")=0,"Sin PMI",IF(INDEX(tCartera[PMI2028],MATCH("2440946",tCartera[CUI],0))="","No informado",INDEX(tCartera[PMI2028],MATCH("2440946",tCartera[CUI],0)))) -> 0 | O60: =IF(COUNTIF(tCartera[CUI],"2440946")=0,"Sin PMI",IF(INDEX(tCartera[PMI2029],MATCH("2440946",tCartera[CUI],0))="","No informado",INDEX(tCartera[PMI2029],MATCH("2440946",tCartera[CUI],0)))) -> 0
A61: =SUBTOTAL(103,$B$10:B61) -> 49 | B61: 88 | C61: 2055915: MEJORAMIENTO DE LA CARRETERA AZANGARO - SAYTOCOCHA - SANDIA - SAN JUAN DEL ORO | D61: =IF(COUNTIF(tSIAF[Clave],"2055915|88")=0,"",SUMIF(tSIAF[Clave],"2055915|88",tSIAF[PIM])) -> 0 | E61: =IF(COUNTIF(tSIAF[Clave],"2055915|88")=0,"",SUMIF(tSIAF[Clave],"2055915|88",tSIAF[Certificacion])) -> 0 | F61: =IF(D61="","",D61-E61) -> 0 | G61: =IF(COUNTIF(tSIAF[Clave],"2055915|88")=0,"",SUMIF(tSIAF[Clave],"2055915|88",tSIAF[Devengado])) -> 0 | H61: =IF(D61="","",D61-G61) -> 0 | I61: =IF(D61="","",IF(D61=0,0,G61/D61)) -> 0 | J61: EJECUCIÓN POR ADMINISTRACIÓN DIRECTA - DIRECTIVA 10 | K61: Por completar | L61: =IF(COUNTIF(tCartera[CUI],"2055915")=0,"Sin PMI",IF(INDEX(tCartera[PMI2026],MATCH("2055915",tCartera[CUI],0))="","No informado",INDEX(tCartera[PMI2026],MATCH("2055915",tCartera[CUI],0)))) -> 7600000 | M61: =IF(COUNTIF(tCartera[CUI],"2055915")=0,"Sin PMI",IF(INDEX(tCartera[PMI2027],MATCH("2055915",tCartera[CUI],0))="","No informado",INDEX(tCartera[PMI2027],MATCH("2055915",tCartera[CUI],0)))) -> 413080 | N61: =IF(COUNTIF(tCartera[CUI],"2055915")=0,"Sin PMI",IF(INDEX(tCartera[PMI2028],MATCH("2055915",tCartera[CUI],0))="","No informado",INDEX(tCartera[PMI2028],MATCH("2055915",tCartera[CUI],0)))) -> 1413086 | O61: =IF(COUNTIF(tCartera[CUI],"2055915")=0,"Sin PMI",IF(INDEX(tCartera[PMI2029],MATCH("2055915",tCartera[CUI],0))="","No informado",INDEX(tCartera[PMI2029],MATCH("2055915",tCartera[CUI],0)))) -> 5797708
A62: =SUBTOTAL(103,$B$10:B62) -> 50 | B62: 89 | C62: 2131389: MEJORAMIENTO DE LA INFRAESTRUCTURA VIAL DEL CIRCUITO TURISTICO LAGO SAGRADO DE LOS INCAS - DISTRITOS CAPACHICA, CHUCUITO, PLATERIA, ACORA, ILAVE | D62: =IF(COUNTIF(tSIAF[Clave],"2131389|89")=0,"",SUMIF(tSIAF[Clave],"2131389|89",tSIAF[PIM])) -> 0 | E62: =IF(COUNTIF(tSIAF[Clave],"2131389|89")=0,"",SUMIF(tSIAF[Clave],"2131389|89",tSIAF[Certificacion])) -> 0 | F62: =IF(D62="","",D62-E62) -> 0 | G62: =IF(COUNTIF(tSIAF[Clave],"2131389|89")=0,"",SUMIF(tSIAF[Clave],"2131389|89",tSIAF[Devengado])) -> 0 | H62: =IF(D62="","",D62-G62) -> 0 | I62: =IF(D62="","",IF(D62=0,0,G62/D62)) -> 0 | J62: EJECUCIÓN POR ADMINISTRACIÓN DIRECTA - DIRECTIVA 10 | K62: Por completar | L62: =IF(COUNTIF(tCartera[CUI],"2131389")=0,"Sin PMI",IF(INDEX(tCartera[PMI2026],MATCH("2131389",tCartera[CUI],0))="","No informado",INDEX(tCartera[PMI2026],MATCH("2131389",tCartera[CUI],0)))) -> 3778561 | M62: =IF(COUNTIF(tCartera[CUI],"2131389")=0,"Sin PMI",IF(INDEX(tCartera[PMI2027],MATCH("2131389",tCartera[CUI],0))="","No informado",INDEX(tCartera[PMI2027],MATCH("2131389",tCartera[CUI],0)))) -> 0 | N62: =IF(COUNTIF(tCartera[CUI],"2131389")=0,"Sin PMI",IF(INDEX(tCartera[PMI2028],MATCH("2131389",tCartera[CUI],0))="","No informado",INDEX(tCartera[PMI2028],MATCH("2131389",tCartera[CUI],0)))) -> 0 | O62: =IF(COUNTIF(tCartera[CUI],"2131389")=0,"Sin PMI",IF(INDEX(tCartera[PMI2029],MATCH("2131389",tCartera[CUI],0))="","No informado",INDEX(tCartera[PMI2029],MATCH("2131389",tCartera[CUI],0)))) -> 1047863
A63: =SUBTOTAL(103,$B$10:B63) -> 51 | B63: 97 | C63: 2232371: MEJORAMIENTO Y CONSTRUCCION DE LA CARRETERA PICHACANI - YURACMAYO DISTRITO DE PICHACANI Y SAN ANTONIO, PROVINCIA DE PUNO - PUNO | D63: =IF(COUNTIF(tSIAF[Clave],"2232371|97")=0,"",SUMIF(tSIAF[Clave],"2232371|97",tSIAF[PIM])) -> 0 | E63: =IF(COUNTIF(tSIAF[Clave],"2232371|97")=0,"",SUMIF(tSIAF[Clave],"2232371|97",tSIAF[Certificacion])) -> 0 | F63: =IF(D63="","",D63-E63) -> 0 | G63: =IF(COUNTIF(tSIAF[Clave],"2232371|97")=0,"",SUMIF(tSIAF[Clave],"2232371|97",tSIAF[Devengado])) -> 0 | H63: =IF(D63="","",D63-G63) -> 0 | I63: =IF(D63="","",IF(D63=0,0,G63/D63)) -> 0 | J63: EJECUCIÓN POR ADMINISTRACIÓN DIRECTA - DIRECTIVA 10 | K63: Por completar | L63: =IF(COUNTIF(tCartera[CUI],"2232371")=0,"Sin PMI",IF(INDEX(tCartera[PMI2026],MATCH("2232371",tCartera[CUI],0))="","No informado",INDEX(tCartera[PMI2026],MATCH("2232371",tCartera[CUI],0)))) -> 1023926 | M63: =IF(COUNTIF(tCartera[CUI],"2232371")=0,"Sin PMI",IF(INDEX(tCartera[PMI2027],MATCH("2232371",tCartera[CUI],0))="","No informado",INDEX(tCartera[PMI2027],MATCH("2232371",tCartera[CUI],0)))) -> 0 | N63: =IF(COUNTIF(tCartera[CUI],"2232371")=0,"Sin PMI",IF(INDEX(tCartera[PMI2028],MATCH("2232371",tCartera[CUI],0))="","No informado",INDEX(tCartera[PMI2028],MATCH("2232371",tCartera[CUI],0)))) -> 0 | O63: =IF(COUNTIF(tCartera[CUI],"2232371")=0,"Sin PMI",IF(INDEX(tCartera[PMI2029],MATCH("2232371",tCartera[CUI],0))="","No informado",INDEX(tCartera[PMI2029],MATCH("2232371",tCartera[CUI],0)))) -> 0
A64: =SUBTOTAL(103,$B$10:B64) -> 52 | B64: 108 | C64: 2443679: MEJORAMIENTO DEL SERVICIO DE TRANSITABILIDAD VEHICULAR DE LA CARRETERA TRAMO I: EMP- 34L (COJATA) - HUANCASAYA, TRAMO II: HUANCASAYA - TARUCANI-EMP-PU-115 (INCHUPALLA), DEL DISTRITO DE COJATA - PROVINCIA DE HUANCANE - DEPARTAMENTO DE PUNO | D64: =IF(COUNTIF(tSIAF[Clave],"2443679|108")=0,"",SUMIF(tSIAF[Clave],"2443679|108",tSIAF[PIM])) -> 0 | E64: =IF(COUNTIF(tSIAF[Clave],"2443679|108")=0,"",SUMIF(tSIAF[Clave],"2443679|108",tSIAF[Certificacion])) -> 0 | F64: =IF(D64="","",D64-E64) -> 0 | G64: =IF(COUNTIF(tSIAF[Clave],"2443679|108")=0,"",SUMIF(tSIAF[Clave],"2443679|108",tSIAF[Devengado])) -> 0 | H64: =IF(D64="","",D64-G64) -> 0 | I64: =IF(D64="","",IF(D64=0,0,G64/D64)) -> 0 | J64: EJECUCIÓN POR ADMINISTRACIÓN DIRECTA - DIRECTIVA 10 | K64: Por completar | L64: =IF(COUNTIF(tCartera[CUI],"2443679")=0,"Sin PMI",IF(INDEX(tCartera[PMI2026],MATCH("2443679",tCartera[CUI],0))="","No informado",INDEX(tCartera[PMI2026],MATCH("2443679",tCartera[CUI],0)))) -> 800000 | M64: =IF(COUNTIF(tCartera[CUI],"2443679")=0,"Sin PMI",IF(INDEX(tCartera[PMI2027],MATCH("2443679",tCartera[CUI],0))="","No informado",INDEX(tCartera[PMI2027],MATCH("2443679",tCartera[CUI],0)))) -> 2345478 | N64: =IF(COUNTIF(tCartera[CUI],"2443679")=0,"Sin PMI",IF(INDEX(tCartera[PMI2028],MATCH("2443679",tCartera[CUI],0))="","No informado",INDEX(tCartera[PMI2028],MATCH("2443679",tCartera[CUI],0)))) -> 9005306 | O64: =IF(COUNTIF(tCartera[CUI],"2443679")=0,"Sin PMI",IF(INDEX(tCartera[PMI2029],MATCH("2443679",tCartera[CUI],0))="","No informado",INDEX(tCartera[PMI2029],MATCH("2443679",tCartera[CUI],0)))) -> 19493721
A65: 21. CULTURA Y DEPORTE | D65: =D66+D67+D68+D69+D70+D71+D72+D73+D74 -> 24086616 | E65: =E66+E67+E68+E69+E70+E71+E72+E73+E74 -> 20655001 | F65: =D65-E65 -> 3431614.6 | G65: =G66+G67+G68+G69+G70+G71+G72+G73+G74 -> 5596985.4 | H65: =D65-G65 -> 18489631 | I65: =IF(D65=0,0,G65/D65) -> 0.2323691
A66: =SUBTOTAL(103,$B$10:B66) -> 53 | B66: 217 | C66: 2163853: MEJORAMIENTO DEL ESTADIO MUNICIPAL CESAR RAUL CARRERA DEL DISTRITO DE AZANGARO, PROVINCIA DE AZANGARO - PUNO | D66: =IF(COUNTIF(tSIAF[Clave],"2163853|217")=0,"",SUMIF(tSIAF[Clave],"2163853|217",tSIAF[PIM])) -> 5810277 | E66: =IF(COUNTIF(tSIAF[Clave],"2163853|217")=0,"",SUMIF(tSIAF[Clave],"2163853|217",tSIAF[Certificacion])) -> 5204423.6 | F66: =IF(D66="","",D66-E66) -> 605853.4 | G66: =IF(COUNTIF(tSIAF[Clave],"2163853|217")=0,"",SUMIF(tSIAF[Clave],"2163853|217",tSIAF[Devengado])) -> 1157372.6 | H66: =IF(D66="","",D66-G66) -> 4652904.4 | I66: =IF(D66="","",IF(D66=0,0,G66/D66)) -> 0.19919405 | J66: EJECUCIÓN POR ADMINISTRACIÓN DIRECTA - DIRECTIVA 10 | K66: Por completar | L66: =IF(COUNTIF(tCartera[CUI],"2163853")=0,"Sin PMI",IF(INDEX(tCartera[PMI2026],MATCH("2163853",tCartera[CUI],0))="","No informado",INDEX(tCartera[PMI2026],MATCH("2163853",tCartera[CUI],0)))) -> 6269000 | M66: =IF(COUNTIF(tCartera[CUI],"2163853")=0,"Sin PMI",IF(INDEX(tCartera[PMI2027],MATCH("2163853",tCartera[CUI],0))="","No informado",INDEX(tCartera[PMI2027],MATCH("2163853",tCartera[CUI],0)))) -> 1345765 | N66: =IF(COUNTIF(tCartera[CUI],"2163853")=0,"Sin PMI",IF(INDEX(tCartera[PMI2028],MATCH("2163853",tCartera[CUI],0))="","No informado",INDEX(tCartera[PMI2028],MATCH("2163853",tCartera[CUI],0)))) -> 5566267 | O66: =IF(COUNTIF(tCartera[CUI],"2163853")=0,"Sin PMI",IF(INDEX(tCartera[PMI2029],MATCH("2163853",tCartera[CUI],0))="","No informado",INDEX(tCartera[PMI2029],MATCH("2163853",tCartera[CUI],0)))) -> 0
A67: =SUBTOTAL(103,$B$10:B67) -> 54 | B67: 63 | C67: 2188542: MEJORAMIENTO DE LA CAPACIDAD DE PRESTACION DE SERVICIOS DEPORTIVOS EN EL ESTADIO GUILLERMO BRICEÑO ROSAMEDINA DE LA CIUDAD DE JULIACA, PROVINCIA DE SAN ROMAN - PUNO | D67: =IF(COUNTIF(tSIAF[Clave],"2188542|63")=0,"",SUMIF(tSIAF[Clave],"2188542|63",tSIAF[PIM])) -> 5921783 | E67: =IF(COUNTIF(tSIAF[Clave],"2188542|63")=0,"",SUMIF(tSIAF[Clave],"2188542|63",tSIAF[Certificacion])) -> 5612635.5 | F67: =IF(D67="","",D67-E67) -> 309147.48 | G67: =IF(COUNTIF(tSIAF[Clave],"2188542|63")=0,"",SUMIF(tSIAF[Clave],"2188542|63",tSIAF[Devengado])) -> 1271806.7 | H67: =IF(D67="","",D67-G67) -> 4649976.3 | I67: =IF(D67="","",IF(D67=0,0,G67/D67)) -> 0.21476753 | J67: EJECUCIÓN POR ADMINISTRACIÓN DIRECTA - DIRECTIVA 10 | K67: Por completar | L67: =IF(COUNTIF(tCartera[CUI],"2188542")=0,"Sin PMI",IF(INDEX(tCartera[PMI2026],MATCH("2188542",tCartera[CUI],0))="","No informado",INDEX(tCartera[PMI2026],MATCH("2188542",tCartera[CUI],0)))) -> 1139986 | M67: =IF(COUNTIF(tCartera[CUI],"2188542")=0,"Sin PMI",IF(INDEX(tCartera[PMI2027],MATCH("2188542",tCartera[CUI],0))="","No informado",INDEX(tCartera[PMI2027],MATCH("2188542",tCartera[CUI],0)))) -> 500000 | N67: =IF(COUNTIF(tCartera[CUI],"2188542")=0,"Sin PMI",IF(INDEX(tCartera[PMI2028],MATCH("2188542",tCartera[CUI],0))="","No informado",INDEX(tCartera[PMI2028],MATCH("2188542",tCartera[CUI],0)))) -> 3220643 | O67: =IF(COUNTIF(tCartera[CUI],"2188542")=0,"Sin PMI",IF(INDEX(tCartera[PMI2029],MATCH("2188542",tCartera[CUI],0))="","No informado",INDEX(tCartera[PMI2029],MATCH("2188542",tCartera[CUI],0)))) -> 0
A68: =SUBTOTAL(103,$B$10:B68) -> 55 | B68: 62 | C68: 2186641: MEJORAMIENTO DEL SERVICIO DEPORTIVO, CULTURAL Y RECREACIONAL EN LA CAPITAL DE LA REGION PUNO | D68: =IF(COUNTIF(tSIAF[Clave],"2186641|62")=0,"",SUMIF(tSIAF[Clave],"2186641|62",tSIAF[PIM])) -> 1180793 | E68: =IF(COUNTIF(tSIAF[Clave],"2186641|62")=0,"",SUMIF(tSIAF[Clave],"2186641|62",tSIAF[Certificacion])) -> 1110291.7 | F68: =IF(D68="","",D68-E68) -> 70501.27 | G68: =IF(COUNTIF(tSIAF[Clave],"2186641|62")=0,"",SUMIF(tSIAF[Clave],"2186641|62",tSIAF[Devengado])) -> 1081390.3 | H68: =IF(D68="","",D68-G68) -> 99402.73 | I68: =IF(D68="","",IF(D68=0,0,G68/D68)) -> 0.91581697 | J68: EJECUCIÓN POR ADMINISTRACIÓN DIRECTA - DIRECTIVA 10 | K68: Por completar | L68: =IF(COUNTIF(tCartera[CUI],"2186641")=0,"Sin PMI",IF(INDEX(tCartera[PMI2026],MATCH("2186641",tCartera[CUI],0))="","No informado",INDEX(tCartera[PMI2026],MATCH("2186641",tCartera[CUI],0)))) -> 11675669 | M68: =IF(COUNTIF(tCartera[CUI],"2186641")=0,"Sin PMI",IF(INDEX(tCartera[PMI2027],MATCH("2186641",tCartera[CUI],0))="","No informado",INDEX(tCartera[PMI2027],MATCH("2186641",tCartera[CUI],0)))) -> 6000000 | N68: =IF(COUNTIF(tCartera[CUI],"2186641")=0,"Sin PMI",IF(INDEX(tCartera[PMI2028],MATCH("2186641",tCartera[CUI],0))="","No informado",INDEX(tCartera[PMI2028],MATCH("2186641",tCartera[CUI],0)))) -> 6503691 | O68: =IF(COUNTIF(tCartera[CUI],"2186641")=0,"Sin PMI",IF(INDEX(tCartera[PMI2029],MATCH("2186641",tCartera[CUI],0))="","No informado",INDEX(tCartera[PMI2029],MATCH("2186641",tCartera[CUI],0)))) -> 7526858
A69: =SUBTOTAL(103,$B$10:B69) -> 56 | B69: 72 | C69: 2646100: CONSTRUCCION DE CAMPO DEPORTIVO Y SERVICIOS HIGIENICOS Y/O VESTIDORES PARA PERSONAL; REPARACION DE TRIBUNA Y/O PALCO; EN EL(LA) ESTADIO MUNICIPAL DE SAN PEDRO DE PUTINA PUNCO DISTRITO DE SAN PEDRO DE PUTINA PUNCO, PROVINCIA SANDIA, DEPARTAMENTO PUNO | D69: =IF(COUNTIF(tSIAF[Clave],"2646100|72")=0,"",SUMIF(tSIAF[Clave],"2646100|72",tSIAF[PIM])) -> 2167000 | E69: =IF(COUNTIF(tSIAF[Clave],"2646100|72")=0,"",SUMIF(tSIAF[Clave],"2646100|72",tSIAF[Certificacion])) -> 1860545 | F69: =IF(D69="","",D69-E69) -> 306455 | G69: =IF(COUNTIF(tSIAF[Clave],"2646100|72")=0,"",SUMIF(tSIAF[Clave],"2646100|72",tSIAF[Devengado])) -> 33059.94 | H69: =IF(D69="","",D69-G69) -> 2133940.1 | I69: =IF(D69="","",IF(D69=0,0,G69/D69)) -> 0.015256087 | J69: EJECUCIÓN POR ADMINISTRACIÓN DIRECTA - DIRECTIVA 10 | K69: Por completar | L69: =IF(COUNTIF(tCartera[CUI],"2646100")=0,"Sin PMI",IF(INDEX(tCartera[PMI2026],MATCH("2646100",tCartera[CUI],0))="","No informado",INDEX(tCartera[PMI2026],MATCH("2646100",tCartera[CUI],0)))) -> 2000000 | M69: =IF(COUNTIF(tCartera[CUI],"2646100")=0,"Sin PMI",IF(INDEX(tCartera[PMI2027],MATCH("2646100",tCartera[CUI],0))="","No informado",INDEX(tCartera[PMI2027],MATCH("2646100",tCartera[CUI],0)))) -> 1547463 | N69: =IF(COUNTIF(tCartera[CUI],"2646100")=0,"Sin PMI",IF(INDEX(tCartera[PMI2028],MATCH("2646100",tCartera[CUI],0))="","No informado",INDEX(tCartera[PMI2028],MATCH("2646100",tCartera[CUI],0)))) -> 0 | O69: =IF(COUNTIF(tCartera[CUI],"2646100")=0,"Sin PMI",IF(INDEX(tCartera[PMI2029],MATCH("2646100",tCartera[CUI],0))="","No informado",INDEX(tCartera[PMI2029],MATCH("2646100",tCartera[CUI],0)))) -> 0
A70: =SUBTOTAL(103,$B$10:B70) -> 57 | B70: 67 | C70: 2645380: CONSTRUCCION DE TRIBUNA Y/O PALCO, CAMPO DEPORTIVO Y PISTA DE ATLETISMO (DEPORTE RECREATIVO); REPARACION DE SERVICIOS HIGIENICOS Y/O VESTIDORES; ADEMAS DE OTROS ACTIVOS EN EL(LA) ESTADIO MUNICIPAL FERNANDO ROMERO CARREON DISTRITO DE LAMPA, PROVINCIA LAMPA, DEPARTAMENTO PUNO | D70: =IF(COUNTIF(tSIAF[Clave],"2645380|67")=0,"",SUMIF(tSIAF[Clave],"2645380|67",tSIAF[PIM])) -> 2575916 | E70: =IF(COUNTIF(tSIAF[Clave],"2645380|67")=0,"",SUMIF(tSIAF[Clave],"2645380|67",tSIAF[Certificacion])) -> 2503779 | F70: =IF(D70="","",D70-E70) -> 72137 | G70: =IF(COUNTIF(tSIAF[Clave],"2645380|67")=0,"",SUMIF(tSIAF[Clave],"2645380|67",tSIAF[Devengado])) -> 23527.19 | H70: =IF(D70="","",D70-G70) -> 2552388.8 | I70: =IF(D70="","",IF(D70=0,0,G70/D70)) -> 0.0091335238 | J70: EJECUCIÓN POR ADMINISTRACIÓN DIRECTA - DIRECTIVA 10 | K70: Por completar | L70: =IF(COUNTIF(tCartera[CUI],"2645380")=0,"Sin PMI",IF(INDEX(tCartera[PMI2026],MATCH("2645380",tCartera[CUI],0))="","No informado",INDEX(tCartera[PMI2026],MATCH("2645380",tCartera[CUI],0)))) -> 2575916 | M70: =IF(COUNTIF(tCartera[CUI],"2645380")=0,"Sin PMI",IF(INDEX(tCartera[PMI2027],MATCH("2645380",tCartera[CUI],0))="","No informado",INDEX(tCartera[PMI2027],MATCH("2645380",tCartera[CUI],0)))) -> 2345678 | N70: =IF(COUNTIF(tCartera[CUI],"2645380")=0,"Sin PMI",IF(INDEX(tCartera[PMI2028],MATCH("2645380",tCartera[CUI],0))="","No informado",INDEX(tCartera[PMI2028],MATCH("2645380",tCartera[CUI],0)))) -> 1558799 | O70: =IF(COUNTIF(tCartera[CUI],"2645380")=0,"Sin PMI",IF(INDEX(tCartera[PMI2029],MATCH("2645380",tCartera[CUI],0))="","No informado",INDEX(tCartera[PMI2029],MATCH("2645380",tCartera[CUI],0)))) -> 0
A71: =SUBTOTAL(103,$B$10:B71) -> 58 | B71: 71 | C71: 2646096: CONSTRUCCION DE TRIBUNA Y/O PALCO; REPARACION DE TRIBUNA Y/O PALCO Y CAMPO DEPORTIVO; EN EL(LA) ESTADIO JOSE CARLOS MARIATEGUI DISTRITO DE YUNGUYO, PROVINCIA YUNGUYO, DEPARTAMENTO PUNO | D71: =IF(COUNTIF(tSIAF[Clave],"2646096|71")=0,"",SUMIF(tSIAF[Clave],"2646096|71",tSIAF[PIM])) -> 2054253 | E71: =IF(COUNTIF(tSIAF[Clave],"2646096|71")=0,"",SUMIF(tSIAF[Clave],"2646096|71",tSIAF[Certificacion])) -> 1854253 | F71: =IF(D71="","",D71-E71) -> 200000 | G71: =IF(COUNTIF(tSIAF[Clave],"2646096|71")=0,"",SUMIF(tSIAF[Clave],"2646096|71",tSIAF[Devengado])) -> 0 | H71: =IF(D71="","",D71-G71) -> 2054253 | I71: =IF(D71="","",IF(D71=0,0,G71/D71)) -> 0 | J71: EJECUCIÓN POR ADMINISTRACIÓN DIRECTA - DIRECTIVA 10 | K71: Por completar | L71: =IF(COUNTIF(tCartera[CUI],"2646096")=0,"Sin PMI",IF(INDEX(tCartera[PMI2026],MATCH("2646096",tCartera[CUI],0))="","No informado",INDEX(tCartera[PMI2026],MATCH("2646096",tCartera[CUI],0)))) -> 2054253 | M71: =IF(COUNTIF(tCartera[CUI],"2646096")=0,"Sin PMI",IF(INDEX(tCartera[PMI2027],MATCH("2646096",tCartera[CUI],0))="","No informado",INDEX(tCartera[PMI2027],MATCH("2646096",tCartera[CUI],0)))) -> 2546789 | N71: =IF(COUNTIF(tCartera[CUI],"2646096")=0,"Sin PMI",IF(INDEX(tCartera[PMI2028],MATCH("2646096",tCartera[CUI],0))="","No informado",INDEX(tCartera[PMI2028],MATCH("2646096",tCartera[CUI],0)))) -> 0 | O71: =IF(COUNTIF(tCartera[CUI],"2646096")=0,"Sin PMI",IF(INDEX(tCartera[PMI2029],MATCH("2646096",tCartera[CUI],0))="","No informado",INDEX(tCartera[PMI2029],MATCH("2646096",tCartera[CUI],0)))) -> 0
A72: =SUBTOTAL(103,$B$10:B72) -> 59 | B72: 65 | C72: 2645340: REPARACION DE TRIBUNA Y/O PALCO Y SERVICIOS HIGIENICOS Y/O VESTIDORES; CONSTRUCCION DE CAMPO DEPORTIVO; EN EL(LA) ESTADIO MUNICIPAL CRUCERO DISTRITO DE CRUCERO, PROVINCIA CARABAYA, DEPARTAMENTO PUNO | D72: =IF(COUNTIF(tSIAF[Clave],"2645340|65")=0,"",SUMIF(tSIAF[Clave],"2645340|65",tSIAF[PIM])) -> 2038388 | E72: =IF(COUNTIF(tSIAF[Clave],"2645340|65")=0,"",SUMIF(tSIAF[Clave],"2645340|65",tSIAF[Certificacion])) -> 2031210.5 | F72: =IF(D72="","",D72-E72) -> 7177.5 | G72: =IF(COUNTIF(tSIAF[Clave],"2645340|65")=0,"",SUMIF(tSIAF[Clave],"2645340|65",tSIAF[Devengado])) -> 1711781.1 | H72: =IF(D72="","",D72-G72) -> 326606.88 | I72: =IF(D72="","",IF(D72=0,0,G72/D72)) -> 0.83977198 | J72: EJECUCIÓN POR ADMINISTRACIÓN DIRECTA - DIRECTIVA 10 | K72: Por completar | L72: =IF(COUNTIF(tCartera[CUI],"2645340")=0,"Sin PMI",IF(INDEX(tCartera[PMI2026],MATCH("2645340",tCartera[CUI],0))="","No informado",INDEX(tCartera[PMI2026],MATCH("2645340",tCartera[CUI],0)))) -> 2028388 | M72: =IF(COUNTIF(tCartera[CUI],"2645340")=0,"Sin PMI",IF(INDEX(tCartera[PMI2027],MATCH("2645340",tCartera[CUI],0))="","No informado",INDEX(tCartera[PMI2027],MATCH("2645340",tCartera[CUI],0)))) -> 2258011 | N72: =IF(COUNTIF(tCartera[CUI],"2645340")=0,"Sin PMI",IF(INDEX(tCartera[PMI2028],MATCH("2645340",tCartera[CUI],0))="","No informado",INDEX(tCartera[PMI2028],MATCH("2645340",tCartera[CUI],0)))) -> 0 | O72: =IF(COUNTIF(tCartera[CUI],"2645340")=0,"Sin PMI",IF(INDEX(tCartera[PMI2029],MATCH("2645340",tCartera[CUI],0))="","No informado",INDEX(tCartera[PMI2029],MATCH("2645340",tCartera[CUI],0)))) -> 0
A73: =SUBTOTAL(103,$B$10:B73) -> 60 | B73: 252 | C73: 2555837: REPARACION DE CAMPO DEPORTIVO; ADQUISICION DE EQUIPO NO DEPORTIVO PARA INSTALACIONES DEPORTIVAS; EN EL(LA) ESTADIO ENRIQUE TORRES BELON DISTRITO DE PUNO, PROVINCIA PUNO, DEPARTAMENTO PUNO | D73: =IF(COUNTIF(tSIAF[Clave],"2555837|252")=0,"",SUMIF(tSIAF[Clave],"2555837|252",tSIAF[PIM])) -> 2047936 | E73: =IF(COUNTIF(tSIAF[Clave],"2555837|252")=0,"",SUMIF(tSIAF[Clave],"2555837|252",tSIAF[Certificacion])) -> 377863 | F73: =IF(D73="","",D73-E73) -> 1670073 | G73: =IF(COUNTIF(tSIAF[Clave],"2555837|252")=0,"",SUMIF(tSIAF[Clave],"2555837|252",tSIAF[Devengado])) -> 318047.53 | H73: =IF(D73="","",D73-G73) -> 1729888.5 | I73: =IF(D73="","",IF(D73=0,0,G73/D73)) -> 0.1553015 | J73: EJECUCIÓN POR ADMINISTRACIÓN DIRECTA - DIRECTIVA 10 | K73: Por completar | L73: =IF(COUNTIF(tCartera[CUI],"2555837")=0,"Sin PMI",IF(INDEX(tCartera[PMI2026],MATCH("2555837",tCartera[CUI],0))="","No informado",INDEX(tCartera[PMI2026],MATCH("2555837",tCartera[CUI],0)))) -> 327863 | M73: =IF(COUNTIF(tCartera[CUI],"2555837")=0,"Sin PMI",IF(INDEX(tCartera[PMI2027],MATCH("2555837",tCartera[CUI],0))="","No informado",INDEX(tCartera[PMI2027],MATCH("2555837",tCartera[CUI],0)))) -> 1876545 | N73: =IF(COUNTIF(tCartera[CUI],"2555837")=0,"Sin PMI",IF(INDEX(tCartera[PMI2028],MATCH("2555837",tCartera[CUI],0))="","No informado",INDEX(tCartera[PMI2028],MATCH("2555837",tCartera[CUI],0)))) -> 0 | O73: =IF(COUNTIF(tCartera[CUI],"2555837")=0,"Sin PMI",IF(INDEX(tCartera[PMI2029],MATCH("2555837",tCartera[CUI],0))="","No informado",INDEX(tCartera[PMI2029],MATCH("2555837",tCartera[CUI],0)))) -> 0
A74: =SUBTOTAL(103,$B$10:B74) -> 61 | B74: 260 | C74: 2593683: REPARACION DE PISTA DE ATLETISMO (COMPETENCIA); ADQUISICION DE TORRE DE ILUMINACION; EN EL(LA) ESTADIO ENRIQUE TORRES BELON DEL DISTRITO DE PUNO, PROVINCIA PUNO, DEPARTAMENTO PUNO | D74: =IF(COUNTIF(tSIAF[Clave],"2593683|260")=0,"",SUMIF(tSIAF[Clave],"2593683|260",tSIAF[PIM])) -> 290270 | E74: =IF(COUNTIF(tSIAF[Clave],"2593683|260")=0,"",SUMIF(tSIAF[Clave],"2593683|260",tSIAF[Certificacion])) -> 100000 | F74: =IF(D74="","",D74-E74) -> 190270 | G74: =IF(COUNTIF(tSIAF[Clave],"2593683|260")=0,"",SUMIF(tSIAF[Clave],"2593683|260",tSIAF[Devengado])) -> 0 | H74: =IF(D74="","",D74-G74) -> 290270 | I74: =IF(D74="","",IF(D74=0,0,G74/D74)) -> 0 | J74: EJECUCIÓN POR ADMINISTRACIÓN DIRECTA - DIRECTIVA 10 | K74: Por completar | L74: =IF(COUNTIF(tCartera[CUI],"2593683")=0,"Sin PMI",IF(INDEX(tCartera[PMI2026],MATCH("2593683",tCartera[CUI],0))="","No informado",INDEX(tCartera[PMI2026],MATCH("2593683",tCartera[CUI],0)))) -> 100000 | M74: =IF(COUNTIF(tCartera[CUI],"2593683")=0,"Sin PMI",IF(INDEX(tCartera[PMI2027],MATCH("2593683",tCartera[CUI],0))="","No informado",INDEX(tCartera[PMI2027],MATCH("2593683",tCartera[CUI],0)))) -> 2089685 | N74: =IF(COUNTIF(tCartera[CUI],"2593683")=0,"Sin PMI",IF(INDEX(tCartera[PMI2028],MATCH("2593683",tCartera[CUI],0))="","No informado",INDEX(tCartera[PMI2028],MATCH("2593683",tCartera[CUI],0)))) -> 3000000 | O74: =IF(COUNTIF(tCartera[CUI],"2593683")=0,"Sin PMI",IF(INDEX(tCartera[PMI2029],MATCH("2593683",tCartera[CUI],0))="","No informado",INDEX(tCartera[PMI2029],MATCH("2593683",tCartera[CUI],0)))) -> 11639950
A75: 03. PLANEAMIENTO, GESTION Y RESERVA DE CONTINGENCIA | D75: =D76 -> 7609099 | E75: =E76 -> 7595390.9 | F75: =D75-E75 -> 13708.12 | G75: =G76 -> 7570246.4 | H75: =D75-G75 -> 38852.61 | I75: =IF(D75=0,0,G75/D75) -> 0.99489393
A76: =SUBTOTAL(103,$B$10:B76) -> 62 | B76: 259 | C76: 2592407: MEJORAMIENTO DE LOS SERVICIOS OPERATIVOS O MISIONALES INSTITUCIONALES EN LA OFICINA DE EQUIPO MECANICO DEL GOBIERNO REGIONAL PUNO DISTRITO DE PUNO DE LA PROVINCIA DE PUNO DEL DEPARTAMENTO DE PUNO | D76: =IF(COUNTIF(tSIAF[Clave],"2592407|259")=0,"",SUMIF(tSIAF[Clave],"2592407|259",tSIAF[PIM])) -> 7609099 | E76: =IF(COUNTIF(tSIAF[Clave],"2592407|259")=0,"",SUMIF(tSIAF[Clave],"2592407|259",tSIAF[Certificacion])) -> 7595390.9 | F76: =IF(D76="","",D76-E76) -> 13708.12 | G76: =IF(COUNTIF(tSIAF[Clave],"2592407|259")=0,"",SUMIF(tSIAF[Clave],"2592407|259",tSIAF[Devengado])) -> 7570246.4 | H76: =IF(D76="","",D76-G76) -> 38852.61 | I76: =IF(D76="","",IF(D76=0,0,G76/D76)) -> 0.99489393 | J76: EJECUCIÓN POR ADMINISTRACIÓN DIRECTA - DIRECTIVA 10 | K76: Por completar | L76: =IF(COUNTIF(tCartera[CUI],"2592407")=0,"Sin PMI",IF(INDEX(tCartera[PMI2026],MATCH("2592407",tCartera[CUI],0))="","No informado",INDEX(tCartera[PMI2026],MATCH("2592407",tCartera[CUI],0)))) -> 6185000 | M76: =IF(COUNTIF(tCartera[CUI],"2592407")=0,"Sin PMI",IF(INDEX(tCartera[PMI2027],MATCH("2592407",tCartera[CUI],0))="","No informado",INDEX(tCartera[PMI2027],MATCH("2592407",tCartera[CUI],0)))) -> 1000000 | N76: =IF(COUNTIF(tCartera[CUI],"2592407")=0,"Sin PMI",IF(INDEX(tCartera[PMI2028],MATCH("2592407",tCartera[CUI],0))="","No informado",INDEX(tCartera[PMI2028],MATCH("2592407",tCartera[CUI],0)))) -> 0 | O76: =IF(COUNTIF(tCartera[CUI],"2592407")=0,"Sin PMI",IF(INDEX(tCartera[PMI2029],MATCH("2592407",tCartera[CUI],0))="","No informado",INDEX(tCartera[PMI2029],MATCH("2592407",tCartera[CUI],0)))) -> 1000000
C77: 2027881: OPTIMIZAR LA CAPACIDAD DE RESPUESTA EN EL HOSPITAL SAN JUAN DE DIOS DE AYAVIRI PUNO, CABECERA DE RED
A78: 23. PROTECCION SOCIAL | D78: =D79 -> 99230 | E78: =E79 -> 99007.59 | F78: =D78-E78 -> 222.41 | G78: =G79 -> 96198.77 | H78: =D78-G78 -> 3031.23 | I78: =IF(D78=0,0,G78/D78) -> 0.96945248
A79: =SUBTOTAL(103,$B$10:B79) -> 63 | B79: 456 | C79: 2230752: MEJORAMIENTO DE LOS SERVICIOS ASISTENCIALES DE LA ALDEA INFANTIL VIRGEN DE LA CANDELARIA EN EL BARRIO LA RINCONADA DEL CENTRO POBLADO DE SALCEDO, DISTRITO DE PUNO, PROVINCIA DE PUNO, REGION DE PUNO | D79: =IF(COUNTIF(tSIAF[Clave],"2230752|456")=0,"",SUMIF(tSIAF[Clave],"2230752|456",tSIAF[PIM])) -> 99230 | E79: =IF(COUNTIF(tSIAF[Clave],"2230752|456")=0,"",SUMIF(tSIAF[Clave],"2230752|456",tSIAF[Certificacion])) -> 99007.59 | F79: =IF(D79="","",D79-E79) -> 222.41 | G79: =IF(COUNTIF(tSIAF[Clave],"2230752|456")=0,"",SUMIF(tSIAF[Clave],"2230752|456",tSIAF[Devengado])) -> 96198.77 | H79: =IF(D79="","",D79-G79) -> 3031.23 | I79: =IF(D79="","",IF(D79=0,0,G79/D79)) -> 0.96945248 | J79: EJECUCIÓN POR ADMINISTRACIÓN DIRECTA - DIRECTIVA 10 | K79: Por completar | L79: =IF(COUNTIF(tCartera[CUI],"2230752")=0,"Sin PMI",IF(INDEX(tCartera[PMI2026],MATCH("2230752",tCartera[CUI],0))="","No informado",INDEX(tCartera[PMI2026],MATCH("2230752",tCartera[CUI],0)))) -> 99230 | M79: =IF(COUNTIF(tCartera[CUI],"2230752")=0,"Sin PMI",IF(INDEX(tCartera[PMI2027],MATCH("2230752",tCartera[CUI],0))="","No informado",INDEX(tCartera[PMI2027],MATCH("2230752",tCartera[CUI],0)))) -> 0 | N79: =IF(COUNTIF(tCartera[CUI],"2230752")=0,"Sin PMI",IF(INDEX(tCartera[PMI2028],MATCH("2230752",tCartera[CUI],0))="","No informado",INDEX(tCartera[PMI2028],MATCH("2230752",tCartera[CUI],0)))) -> 0 | O79: =IF(COUNTIF(tCartera[CUI],"2230752")=0,"Sin PMI",IF(INDEX(tCartera[PMI2029],MATCH("2230752",tCartera[CUI],0))="","No informado",INDEX(tCartera[PMI2029],MATCH("2230752",tCartera[CUI],0)))) -> 0
C80: 2188379 MEJORAMIENTO DEL SERVICIO EDUCATIVO DE LA INSTITUCION EDUCATIVA PRIMARIA Nº 70605 DOMINGO SAVIO, DISTRITO DE JULIACA - SAN ROMAN - PUNO
C81: 2165276: MEJORAMIENTO DEL SERVICIO DE EDUCACION SECUNDARIA EN LA IE JULIO GABANCHO ENRIQUEZ DE LA CIUDAD DE MACUSANI, DISTRITO DE MACUSANI, PROVINCIA DE CARABAYA - PUNO
C82: 2244071: MEJORAMIENTO DEL SERVICIO DE EDUCACION PRIMARIA EN LA I.E. N 72596 CESAR VALLEJO DE LA CIUDAD DE PUTINA, DISTRITO DE PUTINA, PROVINCIA DE SAN ANTONIO DE PUTINA - PUNO
C83: 2250558: MEJORAMIENTO DE LOS SERVICIOS EDUCATIVOS DE LA INSTITUCION EDUCATIVA PRIMARIA N 72659 DE AYAVIRI, DISTRITO DE AYAVIRI, PROVINCIA DE MELGAR - PUNO
C84: 2282351 MEJORAMIENTO DE SERVICIO TRANSITABILIDAD VEHICULAR Y PEATONAL DE LA AV. TAMBOPATA TRAMO AV. SAN MARTIN - AV. CIRCUNVALACION II DE LA CIUDAD DE DE JULIACA (SEGUNDA ETAPA : TRAMO AV. SANTA ROSA - AV. CIRCUNVALACION II), DISTRITO JULIACA - SAN ROMAN - PUNO
C85: 2161480: MEJORAMIENTO DE LA CARRETERA MACUSANI - ABRA SUSUYA, DISTRITO DE MACUSANI, PROVINCIA DE CARABAYA - PUNO
C86: 2178716: MEJORAMIENTO DE LA CARRETERA CALACOTA - SANTA ROSA DE HUAYLLATA (RUTA R-11) DISTRITO DE ILAVE PROVINCIA DE EL COLLAO - PUNO
C87: 2267525: MEJORAMIENTO DE LA CARRETERA AZANGARO (EMP. PU-113) - SAN JUAN DE SALINAS - CHUPA, DISTRITOS DE AZANGARO, SAN JUAN DE SALINAS Y CHUPA, PROVINCIA DE AZANGARO -PUNO
C88: 2307608: MEJORAMIENTO DE LOS SERVICIOS DE TRANSITABILIDAD VEHICULAR Y PEATONAL DE LA VIA DE ACCESO A LA LOCALIDAD DE COATA, DISTRITO DE COATA - PROVINCIA DE PUNO - DEPARTAMENTO DE PUNO
C89: 2300092 MEJORAMIENTO Y CREACION DE LA AVENIDA COSTANERA SUR Y SURESTE EN EL TRAMO JIRON LUIS BANCHERO ROSSI - JIRON ESPINAR - PANAMERICANA SUR INTERSECCION VIAL AVENIDA DEL ESTUDIANTE, DISTRITO DE PUNO, PROVINCIA DE PUNO - PUNO
C90: 2454312: CREACION DEL PUENTE CARROZABLE DE INTERCONEXION ENTRE LOS C.P. QUEQUERANA Y C.P. NINANTAYA DEL DISTRITO DE MOHO - PROVINCIA DE MOHO - DEPARTAMENTO DE PUNO
C91: 2357090 MEJORAMIENTO DE LA CAPACIDAD RESOLUTIVA DEL CENTRO DE SALUD VALLECITO I-3 DE LA MICRO RED METROPOLITANO, RED DE SALUD PUNO, DIRESA PUNO,
... C127: 2131661: CONSTRUCCION Y MEJORAMIENTO DE LA CARRETERA DESVIO VILQUECHICO-COJATA-SINA-YANAHUAYA
A128: EJECUCIÓN POR ADMINISTRACIÓN DIRECTA - DIRECTIVA 17 | D128: =D130+D131+D132+D133+D134+D135+D137+D138+D139+D140+D141+D142+D143+D144+D145+D146+D147+D148+D149+D150+D151+D152+D153+D154+D155+D156+D158+D159+D160+D161+D162+D163+D164+D165+D166+D167+D169+D170+D171 -> 267396323 | E128: =E130+E131+E132+E133+E134+E135+E137+E138+E139+E140+E141+E142+E143+E144+E145+E146+E147+E148+E149+E150+E151+E152+E153+E154+E155+E156+E158+E159+E160+E161+E162+E163+E164+E165+E166+E167+E169+E170+E171 -> 2.4894579e+08 | F128: =D128-E128 -> 18450534 | G128: =G130+G131+G132+G133+G134+G135+G137+G138+G139+G140+G141+G142+G143+G144+G145+G146+G147+G148+G149+G150+G151+G152+G153+G154+G155+G156+G158+G159+G160+G161+G162+G163+G164+G165+G166+G167+G169+G170+G171 -> 1.5910421e+08 | H128: =D128-G128 -> 1.0829211e+08 | I128: =IF(D128=0,0,G128/D128) -> 0.59501271
A129: 20. SALUD | D129: =D130+D131+D132+D133+D134+D135 -> 32634907 | E129: =E130+E131+E132+E133+E134+E135 -> 31001164 | F129: =D129-E129 -> 1633743.5 | G129: =G130+G131+G132+G133+G134+G135 -> 13051954 | H129: =D129-G129 -> 19582953 | I129: =IF(D129=0,0,G129/D129) -> 0.39993844
A130: =SUBTOTAL(103,$B$10:B130) -> 64 | B130: 242 | C130: 2504553: MEJORAMIENTO DEL SERVICIO DE SALUD EN EL CENTRO DE SALUD YANAPATA DE LA MICRO RED COPANI, RED DE SALUD YUNGUYO, DISTRITO DE YUNGUYO - PROVINCIA DE YUNGUYO - DEPARTAMENTO DE PUNO | D130: =IF(COUNTIF(tSIAF[Clave],"2504553|242")=0,"",SUMIF(tSIAF[Clave],"2504553|242",tSIAF[PIM])) -> 8256172 | E130: =IF(COUNTIF(tSIAF[Clave],"2504553|242")=0,"",SUMIF(tSIAF[Clave],"2504553|242",tSIAF[Certificacion])) -> 7527846.9 | F130: =IF(D130="","",D130-E130) -> 728325.09 | G130: =IF(COUNTIF(tSIAF[Clave],"2504553|242")=0,"",SUMIF(tSIAF[Clave],"2504553|242",tSIAF[Devengado])) -> 4485721.8 | H130: =IF(D130="","",D130-G130) -> 3770450.2 | I130: =IF(D130="","",IF(D130=0,0,G130/D130)) -> 0.54331739 | J130: EJECUCIÓN POR ADMINISTRACIÓN DIRECTA - DIRECTIVA 17 | K130: Por completar | L130: =IF(COUNTIF(tCartera[CUI],"2504553")=0,"Sin PMI",IF(INDEX(tCartera[PMI2026],MATCH("2504553",tCartera[CUI],0))="","No informado",INDEX(tCartera[PMI2026],MATCH("2504553",tCartera[CUI],0)))) -> 9468125 | M130: =IF(COUNTIF(tCartera[CUI],"2504553")=0,"Sin PMI",IF(INDEX(tCartera[PMI2027],MATCH("2504553",tCartera[CUI],0))="","No informado",INDEX(tCartera[PMI2027],MATCH("2504553",tCartera[CUI],0)))) -> 933429 | N130: =IF(COUNTIF(tCartera[CUI],"2504553")=0,"Sin PMI",IF(INDEX(tCartera[PMI2028],MATCH("2504553",tCartera[CUI],0))="","No informado",INDEX(tCartera[PMI2028],MATCH("2504553",tCartera[CUI],0)))) -> 6042788 | O130: =IF(COUNTIF(tCartera[CUI],"2504553")=0,"Sin PMI",IF(INDEX(tCartera[PMI2029],MATCH("2504553",tCartera[CUI],0))="","No informado",INDEX(tCartera[PMI2029],MATCH("2504553",tCartera[CUI],0)))) -> 2500000
A131: =SUBTOTAL(103,$B$10:B131) -> 65 | B131: 237 | C131: 2470517: MEJORAMIENTO DE LOS SERVICIOS DE SALUD DEL CENTRO DE SALUD COPANI DE LA MICRO RED COPANI, RED DE SALUD YUNGUYO, DISTRITO DE COPANI - PROVINCIA DE YUNGUYO - DEPARTAMENTO DE PUNO | D131: =IF(COUNTIF(tSIAF[Clave],"2470517|237")=0,"",SUMIF(tSIAF[Clave],"2470517|237",tSIAF[PIM])) -> 7374992 | E131: =IF(COUNTIF(tSIAF[Clave],"2470517|237")=0,"",SUMIF(tSIAF[Clave],"2470517|237",tSIAF[Certificacion])) -> 7374802 | F131: =IF(D131="","",D131-E131) -> 190 | G131: =IF(COUNTIF(tSIAF[Clave],"2470517|237")=0,"",SUMIF(tSIAF[Clave],"2470517|237",tSIAF[Devengado])) -> 0 | H131: =IF(D131="","",D131-G131) -> 7374992 | I131: =IF(D131="","",IF(D131=0,0,G131/D131)) -> 0 | J131: EJECUCIÓN POR ADMINISTRACIÓN DIRECTA - DIRECTIVA 17 | K131: Por completar | L131: =IF(COUNTIF(tCartera[CUI],"2470517")=0,"Sin PMI",IF(INDEX(tCartera[PMI2026],MATCH("2470517",tCartera[CUI],0))="","No informado",INDEX(tCartera[PMI2026],MATCH("2470517",tCartera[CUI],0)))) -> 8000000 | M131: =IF(COUNTIF(tCartera[CUI],"2470517")=0,"Sin PMI",IF(INDEX(tCartera[PMI2027],MATCH("2470517",tCartera[CUI],0))="","No informado",INDEX(tCartera[PMI2027],MATCH("2470517",tCartera[CUI],0)))) -> 8258658 | N131: =IF(COUNTIF(tCartera[CUI],"2470517")=0,"Sin PMI",IF(INDEX(tCartera[PMI2028],MATCH("2470517",tCartera[CUI],0))="","No informado",INDEX(tCartera[PMI2028],MATCH("2470517",tCartera[CUI],0)))) -> 10741348 | O131: =IF(COUNTIF(tCartera[CUI],"2470517")=0,"Sin PMI",IF(INDEX(tCartera[PMI2029],MATCH("2470517",tCartera[CUI],0))="","No informado",INDEX(tCartera[PMI2029],MATCH("2470517",tCartera[CUI],0)))) -> 1075057
A132: =SUBTOTAL(103,$B$10:B132) -> 66 | B132: 228 | C132: 2357092: MEJORAMIENTO DE LA CAPACIDAD RESOLUTIVA DEL CENTRO DE SALUD COJATA I-4, DE LA MICRO RED COJATA, RED DE SALUD HUANCANE, DIRESA PUNO, DISTRITO DE COJATA - PROVINCIA DE HUANCANE - DEPARTAMENTO DE PUNO | D132: =IF(COUNTIF(tSIAF[Clave],"2357092|228")=0,"",SUMIF(tSIAF[Clave],"2357092|228",tSIAF[PIM])) -> 6997430 | E132: =IF(COUNTIF(tSIAF[Clave],"2357092|228")=0,"",SUMIF(tSIAF[Clave],"2357092|228",tSIAF[Certificacion])) -> 6787158.8 | F132: =IF(D132="","",D132-E132) -> 210271.19 | G132: =IF(COUNTIF(tSIAF[Clave],"2357092|228")=0,"",SUMIF(tSIAF[Clave],"2357092|228",tSIAF[Devengado])) -> 2630352.4 | H132: =IF(D132="","",D132-G132) -> 4367077.6 | I132: =IF(D132="","",IF(D132=0,0,G132/D132)) -> 0.37590264 | J132: EJECUCIÓN POR ADMINISTRACIÓN DIRECTA - DIRECTIVA 17 | K132: Por completar | L132: =IF(COUNTIF(tCartera[CUI],"2357092")=0,"Sin PMI",IF(INDEX(tCartera[PMI2026],MATCH("2357092",tCartera[CUI],0))="","No informado",INDEX(tCartera[PMI2026],MATCH("2357092",tCartera[CUI],0)))) -> 8000000 | M132: =IF(COUNTIF(tCartera[CUI],"2357092")=0,"Sin PMI",IF(INDEX(tCartera[PMI2027],MATCH("2357092",tCartera[CUI],0))="","No informado",INDEX(tCartera[PMI2027],MATCH("2357092",tCartera[CUI],0)))) -> 10256256 | N132: =IF(COUNTIF(tCartera[CUI],"2357092")=0,"Sin PMI",IF(INDEX(tCartera[PMI2028],MATCH("2357092",tCartera[CUI],0))="","No informado",INDEX(tCartera[PMI2028],MATCH("2357092",tCartera[CUI],0)))) -> 15069544 | O132: =IF(COUNTIF(tCartera[CUI],"2357092")=0,"Sin PMI",IF(INDEX(tCartera[PMI2029],MATCH("2357092",tCartera[CUI],0))="","No informado",INDEX(tCartera[PMI2029],MATCH("2357092",tCartera[CUI],0)))) -> 4478827
A133: =SUBTOTAL(103,$B$10:B133) -> 67 | B133: 241 | C133: 2494039: MEJORAMIENTO Y AMPLIACION DE LOS SERVICIOS DE SALUD EN EL ESTABLECIMIENTO DE SALUD UMACHIRI CATEGORIA I-2 DEL DISTRITO DE UMACHIRI - PROVINCIA DE MELGAR - DEPARTAMENTO DE PUNO | D133: =IF(COUNTIF(tSIAF[Clave],"2494039|241")=0,"",SUMIF(tSIAF[Clave],"2494039|241",tSIAF[PIM])) -> 6688287 | E133: =IF(COUNTIF(tSIAF[Clave],"2494039|241")=0,"",SUMIF(tSIAF[Clave],"2494039|241",tSIAF[Certificacion])) -> 6156914.2 | F133: =IF(D133="","",D133-E133) -> 531372.77 | G133: =IF(COUNTIF(tSIAF[Clave],"2494039|241")=0,"",SUMIF(tSIAF[Clave],"2494039|241",tSIAF[Devengado])) -> 3692512.7 | H133: =IF(D133="","",D133-G133) -> 2995774.3 | I133: =IF(D133="","",IF(D133=0,0,G133/D133)) -> 0.55208646 | J133: EJECUCIÓN POR ADMINISTRACIÓN DIRECTA - DIRECTIVA 17 | K133: Por completar | L133: =IF(COUNTIF(tCartera[CUI],"2494039")=0,"Sin PMI",IF(INDEX(tCartera[PMI2026],MATCH("2494039",tCartera[CUI],0))="","No informado",INDEX(tCartera[PMI2026],MATCH("2494039",tCartera[CUI],0)))) -> 2822702 | M133: =IF(COUNTIF(tCartera[CUI],"2494039")=0,"Sin PMI",IF(INDEX(tCartera[PMI2027],MATCH("2494039",tCartera[CUI],0))="","No informado",INDEX(tCartera[PMI2027],MATCH("2494039",tCartera[CUI],0)))) -> 65844 | N133: =IF(COUNTIF(tCartera[CUI],"2494039")=0,"Sin PMI",IF(INDEX(tCartera[PMI2028],MATCH("2494039",tCartera[CUI],0))="","No informado",INDEX(tCartera[PMI2028],MATCH("2494039",tCartera[CUI],0)))) -> 0 | O133: =IF(COUNTIF(tCartera[CUI],"2494039")=0,"Sin PMI",IF(INDEX(tCartera[PMI2029],MATCH("2494039",tCartera[CUI],0))="","No informado",INDEX(tCartera[PMI2029],MATCH("2494039",tCartera[CUI],0)))) -> 0
A134: =SUBTOTAL(103,$B$10:B134) -> 68 | B134: 221 | C134: 2290342: MEJORAMIENTO DE LA CAPACIDAD RESOLUTIVA DE LOS SERVICIOS DEL PUESTO DE SALUD I - 1 DEL CENTRO POBLADO DE CARI CARI DEL DISTRITO DE MAÑAZO - PROVINCIA DE PUNO - DEPARTAMENTO DE PUNO | D134: =IF(COUNTIF(tSIAF[Clave],"2290342|221")=0,"",SUMIF(tSIAF[Clave],"2290342|221",tSIAF[PIM])) -> 3318026 | E134: =IF(COUNTIF(tSIAF[Clave],"2290342|221")=0,"",SUMIF(tSIAF[Clave],"2290342|221",tSIAF[Certificacion])) -> 3154441.6 | F134: =IF(D134="","",D134-E134) -> 163584.43 | G134: =IF(COUNTIF(tSIAF[Clave],"2290342|221")=0,"",SUMIF(tSIAF[Clave],"2290342|221",tSIAF[Devengado])) -> 2243366.7 | H134: =IF(D134="","",D134-G134) -> 1074659.3 | I134: =IF(D134="","",IF(D134=0,0,G134/D134)) -> 0.67611487 | J134: EJECUCIÓN POR ADMINISTRACIÓN DIRECTA - DIRECTIVA 17 | K134: Por completar | L134: =IF(COUNTIF(tCartera[CUI],"2290342")=0,"Sin PMI",IF(INDEX(tCartera[PMI2026],MATCH("2290342",tCartera[CUI],0))="","No informado",INDEX(tCartera[PMI2026],MATCH("2290342",tCartera[CUI],0)))) -> 821892 | M134: =IF(COUNTIF(tCartera[CUI],"2290342")=0,"Sin PMI",IF(INDEX(tCartera[PMI2027],MATCH("2290342",tCartera[CUI],0))="","No informado",INDEX(tCartera[PMI2027],MATCH("2290342",tCartera[CUI],0)))) -> 47336 | N134: =IF(COUNTIF(tCartera[CUI],"2290342")=0,"Sin PMI",IF(INDEX(tCartera[PMI2028],MATCH("2290342",tCartera[CUI],0))="","No informado",INDEX(tCartera[PMI2028],MATCH("2290342",tCartera[CUI],0)))) -> 0 | O134: =IF(COUNTIF(tCartera[CUI],"2290342")=0,"Sin PMI",IF(INDEX(tCartera[PMI2029],MATCH("2290342",tCartera[CUI],0))="","No informado",INDEX(tCartera[PMI2029],MATCH("2290342",tCartera[CUI],0)))) -> 0
A135: =SUBTOTAL(103,$B$10:B135) -> 69 | B135: 235 | C135: 2451529: MEJORAMIENTO DEL SERVICIO DE SALUD EN EL CENTRO DE SALUD PILCUYO DE LA MICRORED PILCUYO, RED DE SALUD EL COLLAO, DEL DISTRITO DE PILCUYO - PROVINCIA DE EL COLLAO - DEPARTAMENTO DE PUNO | D135: =IF(COUNTIF(tSIAF[Clave],"2451529|235")=0,"",SUMIF(tSIAF[Clave],"2451529|235",tSIAF[PIM])) -> 0 | E135: =IF(COUNTIF(tSIAF[Clave],"2451529|235")=0,"",SUMIF(tSIAF[Clave],"2451529|235",tSIAF[Certificacion])) -> 0 | F135: =IF(D135="","",D135-E135) -> 0 | G135: =IF(COUNTIF(tSIAF[Clave],"2451529|235")=0,"",SUMIF(tSIAF[Clave],"2451529|235",tSIAF[Devengado])) -> 0 | H135: =IF(D135="","",D135-G135) -> 0 | I135: =IF(D135="","",IF(D135=0,0,G135/D135)) -> 0 | J135: EJECUCIÓN POR ADMINISTRACIÓN DIRECTA - DIRECTIVA 17 | K135: Por completar | L135: =IF(COUNTIF(tCartera[CUI],"2451529")=0,"Sin PMI",IF(INDEX(tCartera[PMI2026],MATCH("2451529",tCartera[CUI],0))="","No informado",INDEX(tCartera[PMI2026],MATCH("2451529",tCartera[CUI],0)))) -> 12571000 | M135: =IF(COUNTIF(tCartera[CUI],"2451529")=0,"Sin PMI",IF(INDEX(tCartera[PMI2027],MATCH("2451529",tCartera[CUI],0))="","No informado",INDEX(tCartera[PMI2027],MATCH("2451529",tCartera[CUI],0)))) -> 5987564 | N135: =IF(COUNTIF(tCartera[CUI],"2451529")=0,"Sin PMI",IF(INDEX(tCartera[PMI2028],MATCH("2451529",tCartera[CUI],0))="","No informado",INDEX(tCartera[PMI2028],MATCH("2451529",tCartera[CUI],0)))) -> 16094501 | O135: =IF(COUNTIF(tCartera[CUI],"2451529")=0,"Sin PMI",IF(INDEX(tCartera[PMI2029],MATCH("2451529",tCartera[CUI],0))="","No informado",INDEX(tCartera[PMI2029],MATCH("2451529",tCartera[CUI],0)))) -> 22576094
A136: 22. EDUCACION | D136: =D137+D138+D139+D140+D141+D142+D143+D144+D145+D146+D147+D148+D149+D150+D151+D152+D153+D154+D155+D156 -> 160639248 | E136: =E137+E138+E139+E140+E141+E142+E143+E144+E145+E146+E147+E148+E149+E150+E151+E152+E153+E154+E155+E156 -> 1.5009595e+08 | F136: =D136-E136 -> 10543296 | G136: =G137+G138+G139+G140+G141+G142+G143+G144+G145+G146+G147+G148+G149+G150+G151+G152+G153+G154+G155+G156 -> 1.0464849e+08 | H136: =D136-G136 -> 55990754 | I136: =IF(D136=0,0,G136/D136) -> 0.65145035
...

Sheet Gerencias y Oficinas
C1: ANEXO N° 02
A2: ="COMPORTAMIENTO DE EJECUCIÓN DE PROYECTOS DE INVERSIÓN PÚBLICA 2026 - U.E. 001 SEDE CENTRAL AL "&TEXT(SIAF!B3,"dd/mm/yyyy") -> COMPORTAMIENTO DE EJECUCIÓN DE PROYECTOS DE INVERSIÓN PÚBLICA 2026 - U.E. 001 SEDE CENTRAL AL 06/10/2026
A4: N° | B4: UE/META | C4: PROYECTO | D4: PIM 2026 (A) | E4: CERTIFICACION (B) | F4: SALDO (A-B) | G4: DEVENGADO ( C ) | H4: SALDO (A-C) | I4: DEVEN % | J4: MODALIDAD DE EJECUCIÓN | K4: ESTADO SITUACIONAL DEL PROYECTO | L4: Monto Año 2026 (S/) | M4: Monto Año 2027 (S/) | N4: Monto Año 2028 (S/) | O4: Monto Año 2029 (S/)
A6: GERENCIA REGIONAL DE DESARROLLO ECONOMICO | D6: =D8+D9+D10+D11+D13+D14+D16+D17+D19+D20+D21+D22+D23+D24+D25+D26+D27+D28+D29+D30+D31+D32+D33+D34+D35+D36+D37+D38+D39+D40+D41+D42+D43+D44+D45+D46+D47+D48+D49+D50+D51+D52+D53+D54+D55+D56+D57+D58+D59+D60+D61+D62+D63+D64+D65+D66+D67+D68+D69+D70+D71+D72+D73+D74+D75+D76+D77+D78+D79+D80+D81+D82+D84+D85+D86+D87+D89+D90+D91+D92+D93+D94+D95 -> 15438088 | E6: =E8+E9+E10+E11+E13+E14+E16+E17+E19+E20+E21+E22+E23+E24+E25+E26+E27+E28+E29+E30+E31+E32+E33+E34+E35+E36+E37+E38+E39+E40+E41+E42+E43+E44+E45+E46+E47+E48+E49+E50+E51+E52+E53+E54+E55+E56+E57+E58+E59+E60+E61+E62+E63+E64+E65+E66+E67+E68+E69+E70+E71+E72+E73+E74+E75+E76+E77+E78+E79+E80+E81+E82+E84+E85+E86+E87+E89+E90+E91+E92+E93+E94+E95 -> 13246424 | F6: =D6-E6 -> 2191664.1 | G6: =G8+G9+G10+G11+G13+G14+G16+G17+G19+G20+G21+G22+G23+G24+G25+G26+G27+G28+G29+G30+G31+G32+G33+G34+G35+G36+G37+G38+G39+G40+G41+G42+G43+G44+G45+G46+G47+G48+G49+G50+G51+G52+G53+G54+G55+G56+G57+G58+G59+G60+G61+G62+G63+G64+G65+G66+G67+G68+G69+G70+G71+G72+G73+G74+G75+G76+G77+G78+G79+G80+G81+G82+G84+G85+G86+G87+G89+G90+G91+G92+G93+G94+G95 -> 6937956.8 | H6: =D6-G6 -> 8500131.2 | I6: =IF(D6=0,0,G6/D6) -> 0.44940518
A7: 09. TURISMO | D7: =D8+D9+D10+D11 -> 3137774 | E7: =E8+E9+E10+E11 -> 2421934 | F7: =D7-E7 -> 715839.98 | G7: =G8+G9+G10+G11 -> 1602346.4 | H7: =D7-G7 -> 1535427.6 | I7: =IF(D7=0,0,G7/D7) -> 0.51066342
A8: =SUBTOTAL(103,$B$8:B8)+287 -> 288 | B8: 20 | C8: 2526527: MEJORAMIENTO DE LAS CAPACIDADES PARA LA PRODUCTIVIDAD Y LA COMPETITIVIDAD DE ARTESANIAS EN 13 PROVINCIAS DEL DEPARTAMENTO DE PUNO | D8: =IF(COUNTIF(tSIAF[Clave],"2526527|20")=0,"",SUMIF(tSIAF[Clave],"2526527|20",tSIAF[PIM])) -> 2659376 | E8: =IF(COUNTIF(tSIAF[Clave],"2526527|20")=0,"",SUMIF(tSIAF[Clave],"2526527|20",tSIAF[Certificacion])) -> 1980094.5 | F8: =IF(D8="","",D8-E8) -> 679281.48 | G8: =IF(COUNTIF(tSIAF[Clave],"2526527|20")=0,"",SUMIF(tSIAF[Clave],"2526527|20",tSIAF[Devengado])) -> 1386716.9 | H8: =IF(D8="","",D8-G8) -> 1272659.1 | I8: =IF(D8="","",IF(D8=0,0,G8/D8)) -> 0.52144446 | K8: Por completar | L8: =IF(COUNTIF(tCartera[CUI],"2526527")=0,"Sin PMI",IF(INDEX(tCartera[PMI2026],MATCH("2526527",tCartera[CUI],0))="","No informado",INDEX(tCartera[PMI2026],MATCH("2526527",tCartera[CUI],0)))) -> 3659376 | M8: =IF(COUNTIF(tCartera[CUI],"2526527")=0,"Sin PMI",IF(INDEX(tCartera[PMI2027],MATCH("2526527",tCartera[CUI],0))="","No informado",INDEX(tCartera[PMI2027],MATCH("2526527",tCartera[CUI],0)))) -> 55933 | N8: =IF(COUNTIF(tCartera[CUI],"2526527")=0,"Sin PMI",IF(INDEX(tCartera[PMI2028],MATCH("2526527",tCartera[CUI],0))="","No informado",INDEX(tCartera[PMI2028],MATCH("2526527",tCartera[CUI],0)))) -> 0 | O8: =IF(COUNTIF(tCartera[CUI],"2526527")=0,"Sin PMI",IF(INDEX(tCartera[PMI2029],MATCH("2526527",tCartera[CUI],0))="","No informado",INDEX(tCartera[PMI2029],MATCH("2526527",tCartera[CUI],0)))) -> 1953448
A9: =SUBTOTAL(103,$B$8:B9)+287 -> 289 | B9: 383 | C9: 2717147.MEJORAMIENTO DE LOS SERVICIOS TURISTICOS DE AVENTURA Y ALOJAMIENTO RURAL EN LA ASOCIACION DE TURISMO VIVENCIAL COMUNITARIO LUQUINA CHICO, DISTRITO CHUCUITO, PROVINCIA PUNO, REGION PUNO. | D9: =IF(COUNTIF(tSIAF[Clave],"2717147|383")=0,"",SUMIF(tSIAF[Clave],"2717147|383",tSIAF[PIM])) -> 159946 | E9: =IF(COUNTIF(tSIAF[Clave],"2717147|383")=0,"",SUMIF(tSIAF[Clave],"2717147|383",tSIAF[Certificacion])) -> 154011 | F9: =IF(D9="","",D9-E9) -> 5935 | G9: =IF(COUNTIF(tSIAF[Clave],"2717147|383")=0,"",SUMIF(tSIAF[Clave],"2717147|383",tSIAF[Devengado])) -> 60441 | H9: =IF(D9="","",D9-G9) -> 99505 | I9: =IF(D9="","",IF(D9=0,0,G9/D9)) -> 0.37788379 | K9: Por completar | L9: =IF(COUNTIF(tCartera[CUI],"2717147")=0,"Sin PMI",IF(INDEX(tCartera[PMI2026],MATCH("2717147",tCartera[CUI],0))="","No informado",INDEX(tCartera[PMI2026],MATCH("2717147",tCartera[CUI],0)))) -> Sin PMI | M9: =IF(COUNTIF(tCartera[CUI],"2717147")=0,"Sin PMI",IF(INDEX(tCartera[PMI2027],MATCH("2717147",tCartera[CUI],0))="","No informado",INDEX(tCartera[PMI2027],MATCH("2717147",tCartera[CUI],0)))) -> Sin PMI | N9: =IF(COUNTIF(tCartera[CUI],"2717147")=0,"Sin PMI",IF(INDEX(tCartera[PMI2028],MATCH("2717147",tCartera[CUI],0))="","No informado",INDEX(tCartera[PMI2028],MATCH("2717147",tCartera[CUI],0)))) -> Sin PMI | O9: =IF(COUNTIF(tCartera[CUI],"2717147")=0,"Sin PMI",IF(INDEX(tCartera[PMI2029],MATCH("2717147",tCartera[CUI],0))="","No informado",INDEX(tCartera[PMI2029],MATCH("2717147",tCartera[CUI],0)))) -> Sin PMI
A10: =SUBTOTAL(103,$B$8:B10)+287 -> 290 | B10: 475 | C10: 2723296.MEJORAMIENTO DE LA PRODUCCION Y COMERCIALIZACION DE ARTESANIA DE FIBRA DE ALPACA Y LANA DE OVINO EN LA ASOCIACION DE ARTESANOS EMPRENDEDORES EN TEXTILERIA SAN JUAN BAUTISTA DE NAPA ROSASPATA, DISTRITO DE ROSASPATA, PROVINCIA DE HUANCANE, REGION PU | D10: =IF(COUNTIF(tSIAF[Clave],"2723296|475")=0,"",SUMIF(tSIAF[Clave],"2723296|475",tSIAF[PIM])) -> 159560 | E10: =IF(COUNTIF(tSIAF[Clave],"2723296|475")=0,"",SUMIF(tSIAF[Clave],"2723296|475",tSIAF[Certificacion])) -> 141270 | F10: =IF(D10="","",D10-E10) -> 18290 | G10: =IF(COUNTIF(tSIAF[Clave],"2723296|475")=0,"",SUMIF(tSIAF[Clave],"2723296|475",tSIAF[Devengado])) -> 57830 | H10: =IF(D10="","",D10-G10) -> 101730 | I10: =IF(D10="","",IF(D10=0,0,G10/D10)) -> 0.36243419 | K10: Por completar | L10: =IF(COUNTIF(tCartera[CUI],"2723296")=0,"Sin PMI",IF(INDEX(tCartera[PMI2026],MATCH("2723296",tCartera[CUI],0))="","No informado",INDEX(tCartera[PMI2026],MATCH("2723296",tCartera[CUI],0)))) -> Sin PMI | M10: =IF(COUNTIF(tCartera[CUI],"2723296")=0,"Sin PMI",IF(INDEX(tCartera[PMI2027],MATCH("2723296",tCartera[CUI],0))="","No informado",INDEX(tCartera[PMI2027],MATCH("2723296",tCartera[CUI],0)))) -> Sin PMI | N10: =IF(COUNTIF(tCartera[CUI],"2723296")=0,"Sin PMI",IF(INDEX(tCartera[PMI2028],MATCH("2723296",tCartera[CUI],0))="","No informado",INDEX(tCartera[PMI2028],MATCH("2723296",tCartera[CUI],0)))) -> Sin PMI | O10: =IF(COUNTIF(tCartera[CUI],"2723296")=0,"Sin PMI",IF(INDEX(tCartera[PMI2029],MATCH("2723296",tCartera[CUI],0))="","No informado",INDEX(tCartera[PMI2029],MATCH("2723296",tCartera[CUI],0)))) -> Sin PMI
A11: =SUBTOTAL(103,$B$8:B11)+287 -> 291 | B11: 410 | C11: 2717175.MEJORAMIENTO DE LOS SERVICIOS DE ALOJAMIENTO TURISTICO Y DEL TURISMO VIVENCIAL DE OBSERVACION ASTRONOMICA EN LA ASOCIACION DE TURISMO COMUNITARIO TIKA WASI LLACHON, DISTRITO DE CAPACHICA, PROVINCIA DE PUNO Y DEPARTAMENTO DE PUNO. | D11: =IF(COUNTIF(tSIAF[Clave],"2717175|410")=0,"",SUMIF(tSIAF[Clave],"2717175|410",tSIAF[PIM])) -> 158892 | E11: =IF(COUNTIF(tSIAF[Clave],"2717175|410")=0,"",SUMIF(tSIAF[Clave],"2717175|410",tSIAF[Certificacion])) -> 146558.5 | F11: =IF(D11="","",D11-E11) -> 12333.5 | G11: =IF(COUNTIF(tSIAF[Clave],"2717175|410")=0,"",SUMIF(tSIAF[Clave],"2717175|410",tSIAF[Devengado])) -> 97358.5 | H11: =IF(D11="","",D11-G11) -> 61533.5 | I11: =IF(D11="","",IF(D11=0,0,G11/D11)) -> 0.61273381 | K11: Por completar | L11: =IF(COUNTIF(tCartera[CUI],"2717175")=0,"Sin PMI",IF(INDEX(tCartera[PMI2026],MATCH("2717175",tCartera[CUI],0))="","No informado",INDEX(tCartera[PMI2026],MATCH("2717175",tCartera[CUI],0)))) -> Sin PMI | M11: =IF(COUNTIF(tCartera[CUI],"2717175")=0,"Sin PMI",IF(INDEX(tCartera[PMI2027],MATCH("2717175",tCartera[CUI],0))="","No informado",INDEX(tCartera[PMI2027],MATCH("2717175",tCartera[CUI],0)))) -> Sin PMI | N11: =IF(COUNTIF(tCartera[CUI],"2717175")=0,"Sin PMI",IF(INDEX(tCartera[PMI2028],MATCH("2717175",tCartera[CUI],0))="","No informado",INDEX(tCartera[PMI2028],MATCH("2717175",tCartera[CUI],0)))) -> Sin PMI | O11: =IF(COUNTIF(tCartera[CUI],"2717175")=0,"Sin PMI",IF(INDEX(tCartera[PMI2029],MATCH("2717175",tCartera[CUI],0))="","No informado",INDEX(tCartera[PMI2029],MATCH("2717175",tCartera[CUI],0)))) -> Sin PMI
A12: 03. PLANEAMIENTO, GESTION Y RESERVA DE CONTINGENCIA | D12: =D13+D14 -> 243160 | E12: =E13+E14 -> 83160 | F12: =D12-E12 -> 160000 | G12: =G13+G14 -> 83100.4 | H12: =D12-G12 -> 160059.6 | I12: =IF(D12=0,0,G12/D12) -> 0.34175193
A13: =SUBTOTAL(103,$B$8:B13)+287 -> 292 | B13: 399 | C13: 2717164.MEJORAMIENTO DE LA CAPACIDAD PRODUCTIVA Y DE COMERCIALIZACION DE MIEL MEDIANTE EL FORTALECIMIENTO DE PROCESOS PRODUCTIVOS APICOLAS EN LA ASOCIACION DE PRODUCTORES AGROPECUARIOS MONTE SILOE KOLLA MISKI DISTRITO PLATERIA, PROVINCIA DE PUNO, REGION P | D13: =IF(COUNTIF(tSIAF[Clave],"2717164|399")=0,"",SUMIF(tSIAF[Clave],"2717164|399",tSIAF[PIM])) -> 160000 | E13: =IF(COUNTIF(tSIAF[Clave],"2717164|399")=0,"",SUMIF(tSIAF[Clave],"2717164|399",tSIAF[Certificacion])) -> 0 | F13: =IF(D13="","",D13-E13) -> 160000 | G13: =IF(COUNTIF(tSIAF[Clave],"2717164|399")=0,"",SUMIF(tSIAF[Clave],"2717164|399",tSIAF[Devengado])) -> 0 | H13: =IF(D13="","",D13-G13) -> 160000 | I13: =IF(D13="","",IF(D13=0,0,G13/D13)) -> 0 | K13: Por completar | L13: =IF(COUNTIF(tCartera[CUI],"2717164")=0,"Sin PMI",IF(INDEX(tCartera[PMI2026],MATCH("2717164",tCartera[CUI],0))="","No informado",INDEX(tCartera[PMI2026],MATCH("2717164",tCartera[CUI],0)))) -> Sin PMI | M13: =IF(COUNTIF(tCartera[CUI],"2717164")=0,"Sin PMI",IF(INDEX(tCartera[PMI2027],MATCH("2717164",tCartera[CUI],0))="","No informado",INDEX(tCartera[PMI2027],MATCH("2717164",tCartera[CUI],0)))) -> Sin PMI | N13: =IF(COUNTIF(tCartera[CUI],"2717164")=0,"Sin PMI",IF(INDEX(tCartera[PMI2028],MATCH("2717164",tCartera[CUI],0))="","No informado",INDEX(tCartera[PMI2028],MATCH("2717164",tCartera[CUI],0)))) -> Sin PMI | O13: =IF(COUNTIF(tCartera[CUI],"2717164")=0,"Sin PMI",IF(INDEX(tCartera[PMI2029],MATCH("2717164",tCartera[CUI],0))="","No informado",INDEX(tCartera[PMI2029],MATCH("2717164",tCartera[CUI],0)))) -> Sin PMI
A14: =SUBTOTAL(103,$B$8:B14)+287 -> 293 | B14: 373 | C14: 2676438: MEJORAMIENTO DE LA PRODUCCION DE MIEL DE ABEJA DE LA ASOCIACION DE APICULTORES Y PRODUCTORES AGROPECUARIOS DEL VALLE YANAHUAYA, DEL DISTRITO DE YANAHUARA PROVINCIA DE SANDIA DEPARTAMENTO DE PUNO | D14: =IF(COUNTIF(tSIAF[Clave],"2676438|373")=0,"",SUMIF(tSIAF[Clave],"2676438|373",tSIAF[PIM])) -> 83160 | E14: =IF(COUNTIF(tSIAF[Clave],"2676438|373")=0,"",SUMIF(tSIAF[Clave],"2676438|373",tSIAF[Certificacion])) -> 83160 | F14: =IF(D14="","",D14-E14) -> 0 | G14: =IF(COUNTIF(tSIAF[Clave],"2676438|373")=0,"",SUMIF(tSIAF[Clave],"2676438|373",tSIAF[Devengado])) -> 83100.4 | H14: =IF(D14="","",D14-G14) -> 59.6 | I14: =IF(D14="","",IF(D14=0,0,G14/D14)) -> 0.99928331 | K14: Por completar | L14: =IF(COUNTIF(tCartera[CUI],"2676438")=0,"Sin PMI",IF(INDEX(tCartera[PMI2026],MATCH("2676438",tCartera[CUI],0))="","No informado",INDEX(tCartera[PMI2026],MATCH("2676438",tCartera[CUI],0)))) -> Sin PMI | M14: =IF(COUNTIF(tCartera[CUI],"2676438")=0,"Sin PMI",IF(INDEX(tCartera[PMI2027],MATCH("2676438",tCartera[CUI],0))="","No informado",INDEX(tCartera[PMI2027],MATCH("2676438",tCartera[CUI],0)))) -> Sin PMI | N14: =IF(COUNTIF(tCartera[CUI],"2676438")=0,"Sin PMI",IF(INDEX(tCartera[PMI2028],MATCH("2676438",tCartera[CUI],0))="","No informado",INDEX(tCartera[PMI2028],MATCH("2676438",tCartera[CUI],0)))) -> Sin PMI | O14: =IF(COUNTIF(tCartera[CUI],"2676438")=0,"Sin PMI",IF(INDEX(tCartera[PMI2029],MATCH("2676438",tCartera[CUI],0))="","No informado",INDEX(tCartera[PMI2029],MATCH("2676438",tCartera[CUI],0)))) -> Sin PMI
A15: 08. COMERCIO | D15: =D16+D17 -> 1098209 | E15: =E16+E17 -> 995606.03 | F15: =D15-E15 -> 102602.97 | G15: =G16+G17 -> 677101.76 | H15: =D15-G15 -> 421107.24 | I15: =IF(D15=0,0,G15/D15) -> 0.61655091
A16: =SUBTOTAL(103,$B$8:B16)+287 -> 294 | B16: 216 | C16: 2016766: INICIATIVA A LA COMPETITIVIDAD | D16: =IF(COUNTIF(tSIAF[Clave],"2016766|216")=0,"",SUMIF(tSIAF[Clave],"2016766|216",tSIAF[PIM])) -> 928209 | E16: =IF(COUNTIF(tSIAF[Clave],"2016766|216")=0,"",SUMIF(tSIAF[Clave],"2016766|216",tSIAF[Certificacion])) -> 900951.03 | F16: =IF(D16="","",D16-E16) -> 27257.97 | G16: =IF(COUNTIF(tSIAF[Clave],"2016766|216")=0,"",SUMIF(tSIAF[Clave],"2016766|216",tSIAF[Devengado])) -> 633092.52 | H16: =IF(D16="","",D16-G16) -> 295116.48 | I16: =IF(D16="","",IF(D16=0,0,G16/D16)) -> 0.68205816 | K16: Por completar | L16: =IF(COUNTIF(tCartera[CUI],"2016766")=0,"Sin PMI",IF(INDEX(tCartera[PMI2026],MATCH("2016766",tCartera[CUI],0))="","No informado",INDEX(tCartera[PMI2026],MATCH("2016766",tCartera[CUI],0)))) -> Sin PMI | M16: =IF(COUNTIF(tCartera[CUI],"2016766")=0,"Sin PMI",IF(INDEX(tCartera[PMI2027],MATCH("2016766",tCartera[CUI],0))="","No informado",INDEX(tCartera[PMI2027],MATCH("2016766",tCartera[CUI],0)))) -> Sin PMI | N16: =IF(COUNTIF(tCartera[CUI],"2016766")=0,"Sin PMI",IF(INDEX(tCartera[PMI2028],MATCH("2016766",tCartera[CUI],0))="","No informado",INDEX(tCartera[PMI2028],MATCH("2016766",tCartera[CUI],0)))) -> Sin PMI | O16: =IF(COUNTIF(tCartera[CUI],"2016766")=0,"Sin PMI",IF(INDEX(tCartera[PMI2029],MATCH("2016766",tCartera[CUI],0))="","No informado",INDEX(tCartera[PMI2029],MATCH("2016766",tCartera[CUI],0)))) -> Sin PMI
A17: =SUBTOTAL(103,$B$8:B17)+287 -> 295 | B17: 493 | C17: 2016766: INICIATIVA A LA COMPETITIVIDAD | D17: =IF(COUNTIF(tSIAF[Clave],"2016766|493")=0,"",SUMIF(tSIAF[Clave],"2016766|493",tSIAF[PIM])) -> 170000 | E17: =IF(COUNTIF(tSIAF[Clave],"2016766|493")=0,"",SUMIF(tSIAF[Clave],"2016766|493",tSIAF[Certificacion])) -> 94655 | F17: =IF(D17="","",D17-E17) -> 75345 | G17: =IF(COUNTIF(tSIAF[Clave],"2016766|493")=0,"",SUMIF(tSIAF[Clave],"2016766|493",tSIAF[Devengado])) -> 44009.24 | H17: =IF(D17="","",D17-G17) -> 125990.76 | I17: =IF(D17="","",IF(D17=0,0,G17/D17)) -> 0.25887788 | K17: Por completar | L17: =IF(COUNTIF(tCartera[CUI],"2016766")=0,"Sin PMI",IF(INDEX(tCartera[PMI2026],MATCH("2016766",tCartera[CUI],0))="","No informado",INDEX(tCartera[PMI2026],MATCH("2016766",tCartera[CUI],0)))) -> Sin PMI | M17: =IF(COUNTIF(tCartera[CUI],"2016766")=0,"Sin PMI",IF(INDEX(tCartera[PMI2027],MATCH("2016766",tCartera[CUI],0))="","No informado",INDEX(tCartera[PMI2027],MATCH("2016766",tCartera[CUI],0)))) -> Sin PMI | N17: =IF(COUNTIF(tCartera[CUI],"2016766")=0,"Sin PMI",IF(INDEX(tCartera[PMI2028],MATCH("2016766",tCartera[CUI],0))="","No informado",INDEX(tCartera[PMI2028],MATCH("2016766",tCartera[CUI],0)))) -> Sin PMI | O17: =IF(COUNTIF(tCartera[CUI],"2016766")=0,"Sin PMI",IF(INDEX(tCartera[PMI2029],MATCH("2016766",tCartera[CUI],0))="","No informado",INDEX(tCartera[PMI2029],MATCH("2016766",tCartera[CUI],0)))) -> Sin PMI
A18: 10. AGROPECUARIA | D18: =D19+D20+D21+D22+D23+D24+D25+D26+D27+D28+D29+D30+D31+D32+D33+D34+D35+D36+D37+D38+D39+D40+D41+D42+D43+D44+D45+D46+D47+D48+D49+D50+D51+D52+D53+D54+D55+D56+D57+D58+D59+D60+D61+D62+D63+D64+D65+D66+D67+D68+D69+D70+D71+D72+D73+D74+D75+D76+D77+D78+D79+D80+D81+D82 -> 8596003 | E18: =E19+E20+E21+E22+E23+E24+E25+E26+E27+E28+E29+E30+E31+E32+E33+E34+E35+E36+E37+E38+E39+E40+E41+E42+E43+E44+E45+E46+E47+E48+E49+E50+E51+E52+E53+E54+E55+E56+E57+E58+E59+E60+E61+E62+E63+E64+E65+E66+E67+E68+E69+E70+E71+E72+E73+E74+E75+E76+E77+E78+E79+E80+E81+E82 -> 7643005.1 | F18: =D18-E18 -> 952997.85 | G18: =G19+G20+G21+G22+G23+G24+G25+G26+G27+G28+G29+G30+G31+G32+G33+G34+G35+G36+G37+G38+G39+G40+G41+G42+G43+G44+G45+G46+G47+G48+G49+G50+G51+G52+G53+G54+G55+G56+G57+G58+G59+G60+G61+G62+G63+G64+G65+G66+G67+G68+G69+G70+G71+G72+G73+G74+G75+G76+G77+G78+G79+G80+G81+G82 -> 4006476.2 | H18: =D18-G18 -> 4589526.8 | I18: =IF(D18=0,0,G18/D18) -> 0.46608595
A19: =SUBTOTAL(103,$B$8:B19)+287 -> 296 | B19: 418 | C19: 2717186.MEJORAMIENTO DE LA PLANTA DE TRANSFORMACION DE GRANOS ANDINOS DEL GRUPO TURISTICO GASTRONOMICO SAMKA S.A.C., DISTRITO PUNO, PROVINCIA PUNO, REGION PUNO. | D19: =IF(COUNTIF(tSIAF[Clave],"2717186|418")=0,"",SUMIF(tSIAF[Clave],"2717186|418",tSIAF[PIM])) -> 350000 | E19: =IF(COUNTIF(tSIAF[Clave],"2717186|418")=0,"",SUMIF(tSIAF[Clave],"2717186|418",tSIAF[Certificacion])) -> 334060 | F19: =IF(D19="","",D19-E19) -> 15940 | G19: =IF(COUNTIF(tSIAF[Clave],"2717186|418")=0,"",SUMIF(tSIAF[Clave],"2717186|418",tSIAF[Devengado])) -> 65360 | H19: =IF(D19="","",D19-G19) -> 284640 | I19: =IF(D19="","",IF(D19=0,0,G19/D19)) -> 0.18674286 | K19: Por completar | L19: =IF(COUNTIF(tCartera[CUI],"2717186")=0,"Sin PMI",IF(INDEX(tCartera[PMI2026],MATCH("2717186",tCartera[CUI],0))="","No informado",INDEX(tCartera[PMI2026],MATCH("2717186",tCartera[CUI],0)))) -> Sin PMI | M19: =IF(COUNTIF(tCartera[CUI],"2717186")=0,"Sin PMI",IF(INDEX(tCartera[PMI2027],MATCH("2717186",tCartera[CUI],0))="","No informado",INDEX(tCartera[PMI2027],MATCH("2717186",tCartera[CUI],0)))) -> Sin PMI | N19: =IF(COUNTIF(tCartera[CUI],"2717186")=0,"Sin PMI",IF(INDEX(tCartera[PMI2028],MATCH("2717186",tCartera[CUI],0))="","No informado",INDEX(tCartera[PMI2028],MATCH("2717186",tCartera[CUI],0)))) -> Sin PMI | O19: =IF(COUNTIF(tCartera[CUI],"2717186")=0,"Sin PMI",IF(INDEX(tCartera[PMI2029],MATCH("2717186",tCartera[CUI],0))="","No informado",INDEX(tCartera[PMI2029],MATCH("2717186",tCartera[CUI],0)))) -> Sin PMI
A20: =SUBTOTAL(103,$B$8:B20)+287 -> 297 | B20: 424 | C20: 2717193.AMPLIACION DE LA CAPACIDAD PRODUCCION DE QUESO PARIA EN GRUPO NEBRASKA S.A.C. EN DISTRITO DE JULIACA PROVINCIA DE SAN ROMAN REGION PUNO | D20: =IF(COUNTIF(tSIAF[Clave],"2717193|424")=0,"",SUMIF(tSIAF[Clave],"2717193|424",tSIAF[PIM])) -> 349950 | E20: =IF(COUNTIF(tSIAF[Clave],"2717193|424")=0,"",SUMIF(tSIAF[Clave],"2717193|424",tSIAF[Certificacion])) -> 287705 | F20: =IF(D20="","",D20-E20) -> 62245 | G20: =IF(COUNTIF(tSIAF[Clave],"2717193|424")=0,"",SUMIF(tSIAF[Clave],"2717193|424",tSIAF[Devengado])) -> 136062 | H20: =IF(D20="","",D20-G20) -> 213888 | I20: =IF(D20="","",IF(D20=0,0,G20/D20)) -> 0.38880411 | K20: Por completar | L20: =IF(COUNTIF(tCartera[CUI],"2717193")=0,"Sin PMI",IF(INDEX(tCartera[PMI2026],MATCH("2717193",tCartera[CUI],0))="","No informado",INDEX(tCartera[PMI2026],MATCH("2717193",tCartera[CUI],0)))) -> Sin PMI | M20: =IF(COUNTIF(tCartera[CUI],"2717193")=0,"Sin PMI",IF(INDEX(tCartera[PMI2027],MATCH("2717193",tCartera[CUI],0))="","No informado",INDEX(tCartera[PMI2027],MATCH("2717193",tCartera[CUI],0)))) -> Sin PMI | N20: =IF(COUNTIF(tCartera[CUI],"2717193")=0,"Sin PMI",IF(INDEX(tCartera[PMI2028],MATCH("2717193",tCartera[CUI],0))="","No informado",INDEX(tCartera[PMI2028],MATCH("2717193",tCartera[CUI],0)))) -> Sin PMI | O20: =IF(COUNTIF(tCartera[CUI],"2717193")=0,"Sin PMI",IF(INDEX(tCartera[PMI2029],MATCH("2717193",tCartera[CUI],0))="","No informado",INDEX(tCartera[PMI2029],MATCH("2717193",tCartera[CUI],0)))) -> Sin PMI
A21: =SUBTOTAL(103,$B$8:B21)+287 -> 298 | B21: 413 | C21: 2717178.MEJORAMIENTO DEL CULTIVO DE HABAS EN CORPORACION PECUARIO AGRICOLA EMMANUEL S.A.C., DISTRITO DE ZEPITA, PROVINCIA DE CHUCUITO Y DEPARTAMENTO DE PUNO | D21: =IF(COUNTIF(tSIAF[Clave],"2717178|413")=0,"",SUMIF(tSIAF[Clave],"2717178|413",tSIAF[PIM])) -> 349899 | E21: =IF(COUNTIF(tSIAF[Clave],"2717178|413")=0,"",SUMIF(tSIAF[Clave],"2717178|413",tSIAF[Certificacion])) -> 307070 | F21: =IF(D21="","",D21-E21) -> 42829 | G21: =IF(COUNTIF(tSIAF[Clave],"2717178|413")=0,"",SUMIF(tSIAF[Clave],"2717178|413",tSIAF[Devengado])) -> 10500 | H21: =IF(D21="","",D21-G21) -> 339399 | I21: =IF(D21="","",IF(D21=0,0,G21/D21)) -> 0.03000866 | K21: Por completar | L21: =IF(COUNTIF(tCartera[CUI],"2717178")=0,"Sin PMI",IF(INDEX(tCartera[PMI2026],MATCH("2717178",tCartera[CUI],0))="","No informado",INDEX(tCartera[PMI2026],MATCH("2717178",tCartera[CUI],0)))) -> Sin PMI | M21: =IF(COUNTIF(tCartera[CUI],"2717178")=0,"Sin PMI",IF(INDEX(tCartera[PMI2027],MATCH("2717178",tCartera[CUI],0))="","No informado",INDEX(tCartera[PMI2027],MATCH("2717178",tCartera[CUI],0)))) -> Sin PMI | N21: =IF(COUNTIF(tCartera[CUI],"2717178")=0,"Sin PMI",IF(INDEX(tCartera[PMI2028],MATCH("2717178",tCartera[CUI],0))="","No informado",INDEX(tCartera[PMI2028],MATCH("2717178",tCartera[CUI],0)))) -> Sin PMI | O21: =IF(COUNTIF(tCartera[CUI],"2717178")=0,"Sin PMI",IF(INDEX(tCartera[PMI2029],MATCH("2717178",tCartera[CUI],0))="","No informado",INDEX(tCartera[PMI2029],MATCH("2717178",tCartera[CUI],0)))) -> Sin PMI
A22: =SUBTOTAL(103,$B$8:B22)+287 -> 299 | B22: 394 | C22: 2717158.MEJORAMIENTO DE LA PRODUCCION DE PACAS EN LA ASOCIACION DE PRODUCTORES AGROPECUARIOS Y FORESTALES SAN PEDRO DE FRAYLIMA, DISTRITO DE AZANGARO, PROVINCIA AZANGARO Y DEPARTAMENTO DE PUNO | D22: =IF(COUNTIF(tSIAF[Clave],"2717158|394")=0,"",SUMIF(tSIAF[Clave],"2717158|394",tSIAF[PIM])) -> 349792 | E22: =IF(COUNTIF(tSIAF[Clave],"2717158|394")=0,"",SUMIF(tSIAF[Clave],"2717158|394",tSIAF[Certificacion])) -> 321500 | F22: =IF(D22="","",D22-E22) -> 28292 | G22: =IF(COUNTIF(tSIAF[Clave],"2717158|394")=0,"",SUMIF(tSIAF[Clave],"2717158|394",tSIAF[Devengado])) -> 0 | H22: =IF(D22="","",D22-G22) -> 349792 | I22: =IF(D22="","",IF(D22=0,0,G22/D22)) -> 0 | K22: Por completar | L22: =IF(COUNTIF(tCartera[CUI],"2717158")=0,"Sin PMI",IF(INDEX(tCartera[PMI2026],MATCH("2717158",tCartera[CUI],0))="","No informado",INDEX(tCartera[PMI2026],MATCH("2717158",tCartera[CUI],0)))) -> Sin PMI | M22: =IF(COUNTIF(tCartera[CUI],"2717158")=0,"Sin PMI",IF(INDEX(tCartera[PMI2027],MATCH("2717158",tCartera[CUI],0))="","No informado",INDEX(tCartera[PMI2027],MATCH("2717158",tCartera[CUI],0)))) -> Sin PMI | N22: =IF(COUNTIF(tCartera[CUI],"2717158")=0,"Sin PMI",IF(INDEX(tCartera[PMI2028],MATCH("2717158",tCartera[CUI],0))="","No informado",INDEX(tCartera[PMI2028],MATCH("2717158",tCartera[CUI],0)))) -> Sin PMI | O22: =IF(COUNTIF(tCartera[CUI],"2717158")=0,"Sin PMI",IF(INDEX(tCartera[PMI2029],MATCH("2717158",tCartera[CUI],0))="","No informado",INDEX(tCartera[PMI2029],MATCH("2717158",tCartera[CUI],0)))) -> Sin PMI
A23: =SUBTOTAL(103,$B$8:B23)+287 -> 300 | B23: 408 | C23: 2717173.MEJORAMIENTO DE LA PRODUCCION DE DERIVADOS DE QUINUA EN HARINA EXTRUIDA Y POP EXTRUIDO DE LA EMPRESA CORPORACION DALSAR SOCIEDAD ANONIMA CERRADA DEL DISTRITO DE PUNO, PROVINCIA PUNO, DEPARTAMENTO PUNO. | D23: =IF(COUNTIF(tSIAF[Clave],"2717173|408")=0,"",SUMIF(tSIAF[Clave],"2717173|408",tSIAF[PIM])) -> 349792 | E23: =IF(COUNTIF(tSIAF[Clave],"2717173|408")=0,"",SUMIF(tSIAF[Clave],"2717173|408",tSIAF[Certificacion])) -> 329100 | F23: =IF(D23="","",D23-E23) -> 20692 | G23: =IF(COUNTIF(tSIAF[Clave],"2717173|408")=0,"",SUMIF(tSIAF[Clave],"2717173|408",tSIAF[Devengado])) -> 0 | H23: =IF(D23="","",D23-G23) -> 349792 | I23: =IF(D23="","",IF(D23=0,0,G23/D23)) -> 0 | K23: Por completar | L23: =IF(COUNTIF(tCartera[CUI],"2717173")=0,"Sin PMI",IF(INDEX(tCartera[PMI2026],MATCH("2717173",tCartera[CUI],0))="","No informado",INDEX(tCartera[PMI2026],MATCH("2717173",tCartera[CUI],0)))) -> Sin PMI | M23: =IF(COUNTIF(tCartera[CUI],"2717173")=0,"Sin PMI",IF(INDEX(tCartera[PMI2027],MATCH("2717173",tCartera[CUI],0))="","No informado",INDEX(tCartera[PMI2027],MATCH("2717173",tCartera[CUI],0)))) -> Sin PMI | N23: =IF(COUNTIF(tCartera[CUI],"2717173")=0,"Sin PMI",IF(INDEX(tCartera[PMI2028],MATCH("2717173",tCartera[CUI],0))="","No informado",INDEX(tCartera[PMI2028],MATCH("2717173",tCartera[CUI],0)))) -> Sin PMI | O23: =IF(COUNTIF(tCartera[CUI],"2717173")=0,"Sin PMI",IF(INDEX(tCartera[PMI2029],MATCH("2717173",tCartera[CUI],0))="","No informado",INDEX(tCartera[PMI2029],MATCH("2717173",tCartera[CUI],0)))) -> Sin PMI
A24: =SUBTOTAL(103,$B$8:B24)+287 -> 301 | B24: 421 | C24: 2717189.MEJORAMIENTO DE LA PRODUCCION DE YOGURT EN EL AEO AGROINDUSTRIA YOGULE S.A.C., DISTRITO DE CABANA, PROVINCIA SAN ROMAN, REGION PUNO | D24: =IF(COUNTIF(tSIAF[Clave],"2717189|421")=0,"",SUMIF(tSIAF[Clave],"2717189|421",tSIAF[PIM])) -> 346711 | E24: =IF(COUNTIF(tSIAF[Clave],"2717189|421")=0,"",SUMIF(tSIAF[Clave],"2717189|421",tSIAF[Certificacion])) -> 318955 | F24: =IF(D24="","",D24-E24) -> 27756 | G24: =IF(COUNTIF(tSIAF[Clave],"2717189|421")=0,"",SUMIF(tSIAF[Clave],"2717189|421",tSIAF[Devengado])) -> 112190 | H24: =IF(D24="","",D24-G24) -> 234521 | I24: =IF(D24="","",IF(D24=0,0,G24/D24)) -> 0.32358362 | K24: Por completar | L24: =IF(COUNTIF(tCartera[CUI],"2717189")=0,"Sin PMI",IF(INDEX(tCartera[PMI2026],MATCH("2717189",tCartera[CUI],0))="","No informado",INDEX(tCartera[PMI2026],MATCH("2717189",tCartera[CUI],0)))) -> Sin PMI | M24: =IF(COUNTIF(tCartera[CUI],"2717189")=0,"Sin PMI",IF(INDEX(tCartera[PMI2027],MATCH("2717189",tCartera[CUI],0))="","No informado",INDEX(tCartera[PMI2027],MATCH("2717189",tCartera[CUI],0)))) -> Sin PMI | N24: =IF(COUNTIF(tCartera[CUI],"2717189")=0,"Sin PMI",IF(INDEX(tCartera[PMI2028],MATCH("2717189",tCartera[CUI],0))="","No informado",INDEX(tCartera[PMI2028],MATCH("2717189",tCartera[CUI],0)))) -> Sin PMI | O24: =IF(COUNTIF(tCartera[CUI],"2717189")=0,"Sin PMI",IF(INDEX(tCartera[PMI2029],MATCH("2717189",tCartera[CUI],0))="","No informado",INDEX(tCartera[PMI2029],MATCH("2717189",tCartera[CUI],0)))) -> Sin PMI
A25: =SUBTOTAL(103,$B$8:B25)+287 -> 302 | B25: 387 | C25: 2717151.MEJORAMIENTO DE LA PRODUCCION DE LECHE FRESCA EN LA ASOCIACION DE PRODUCTORES AGROPECUARIOS SUMAC KANCHAY DE LA LIBERTAD NUNOA MELGAR PUNO, DISTRITO DE NUNOA, PROVINCIA DE MELGAR Y REGION PUNO | D25: =IF(COUNTIF(tSIAF[Clave],"2717151|387")=0,"",SUMIF(tSIAF[Clave],"2717151|387",tSIAF[PIM])) -> 269980 | E25: =IF(COUNTIF(tSIAF[Clave],"2717151|387")=0,"",SUMIF(tSIAF[Clave],"2717151|387",tSIAF[Certificacion])) -> 259749 | F25: =IF(D25="","",D25-E25) -> 10231 | G25: =IF(COUNTIF(tSIAF[Clave],"2717151|387")=0,"",SUMIF(tSIAF[Clave],"2717151|387",tSIAF[Devengado])) -> 255066 | H25: =IF(D25="","",D25-G25) -> 14914 | I25: =IF(D25="","",IF(D25=0,0,G25/D25)) -> 0.94475887 | K25: Por completar | L25: =IF(COUNTIF(tCartera[CUI],"2717151")=0,"Sin PMI",IF(INDEX(tCartera[PMI2026],MATCH("2717151",tCartera[CUI],0))="","No informado",INDEX(tCartera[PMI2026],MATCH("2717151",tCartera[CUI],0)))) -> Sin PMI | M25: =IF(COUNTIF(tCartera[CUI],"2717151")=0,"Sin PMI",IF(INDEX(tCartera[PMI2027],MATCH("2717151",tCartera[CUI],0))="","No informado",INDEX(tCartera[PMI2027],MATCH("2717151",tCartera[CUI],0)))) -> Sin PMI | N25: =IF(COUNTIF(tCartera[CUI],"2717151")=0,"Sin PMI",IF(INDEX(tCartera[PMI2028],MATCH("2717151",tCartera[CUI],0))="","No informado",INDEX(tCartera[PMI2028],MATCH("2717151",tCartera[CUI],0)))) -> Sin PMI | O25: =IF(COUNTIF(tCartera[CUI],"2717151")=0,"Sin PMI",IF(INDEX(tCartera[PMI2029],MATCH("2717151",tCartera[CUI],0))="","No informado",INDEX(tCartera[PMI2029],MATCH("2717151",tCartera[CUI],0)))) -> Sin PMI
A26: =SUBTOTAL(103,$B$8:B26)+287 -> 303 | B26: 378 | C26: 2676440: MEJORAMIENTO DE LA PRODUCCION Y LA PRODUCTIVIDAD DE QUESO TIPO PARIA PASTEURIZADO DE LA EMPRESA DE PRODUCCION AGROPECUARIA MICA ASUNCION SAC DEL, DISTRITO DE AZANGARO, PROVINCIA AZANGARO, DEPARTAMENTO PUNO. | D26: =IF(COUNTIF(tSIAF[Clave],"2676440|378")=0,"",SUMIF(tSIAF[Clave],"2676440|378",tSIAF[PIM])) -> 209400 | E26: =IF(COUNTIF(tSIAF[Clave],"2676440|378")=0,"",SUMIF(tSIAF[Clave],"2676440|378",tSIAF[Certificacion])) -> 176550 | F26: =IF(D26="","",D26-E26) -> 32850 | G26: =IF(COUNTIF(tSIAF[Clave],"2676440|378")=0,"",SUMIF(tSIAF[Clave],"2676440|378",tSIAF[Devengado])) -> 136550 | H26: =IF(D26="","",D26-G26) -> 72850 | I26: =IF(D26="","",IF(D26=0,0,G26/D26)) -> 0.65210124 | K26: Por completar | L26: =IF(COUNTIF(tCartera[CUI],"2676440")=0,"Sin PMI",IF(INDEX(tCartera[PMI2026],MATCH("2676440",tCartera[CUI],0))="","No informado",INDEX(tCartera[PMI2026],MATCH("2676440",tCartera[CUI],0)))) -> Sin PMI | M26: =IF(COUNTIF(tCartera[CUI],"2676440")=0,"Sin PMI",IF(INDEX(tCartera[PMI2027],MATCH("2676440",tCartera[CUI],0))="","No informado",INDEX(tCartera[PMI2027],MATCH("2676440",tCartera[CUI],0)))) -> Sin PMI | N26: =IF(COUNTIF(tCartera[CUI],"2676440")=0,"Sin PMI",IF(INDEX(tCartera[PMI2028],MATCH("2676440",tCartera[CUI],0))="","No informado",INDEX(tCartera[PMI2028],MATCH("2676440",tCartera[CUI],0)))) -> Sin PMI | O26: =IF(COUNTIF(tCartera[CUI],"2676440")=0,"Sin PMI",IF(INDEX(tCartera[PMI2029],MATCH("2676440",tCartera[CUI],0))="","No informado",INDEX(tCartera[PMI2029],MATCH("2676440",tCartera[CUI],0)))) -> Sin PMI
A27: =SUBTOTAL(103,$B$8:B27)+287 -> 304 | B27: 392 | C27: 2717156.MEJORAMIENTO DE LA PRODUCCION Y LA COMERCIALIZACION DE LECHE FRESCA EN LA ORGANIZACION DE PRODUCTORES SAN JUAN DE FAON DEL DISTRITO DE HUATA, PROVINCIA DE PUNO, DEPARTAMENTO DE PUNO. | D27: =IF(COUNTIF(tSIAF[Clave],"2717156|392")=0,"",SUMIF(tSIAF[Clave],"2717156|392",tSIAF[PIM])) -> 160000 | E27: =IF(COUNTIF(tSIAF[Clave],"2717156|392")=0,"",SUMIF(tSIAF[Clave],"2717156|392",tSIAF[Certificacion])) -> 143401 | F27: =IF(D27="","",D27-E27) -> 16599 | G27: =IF(COUNTIF(tSIAF[Clave],"2717156|392")=0,"",SUMIF(tSIAF[Clave],"2717156|392",tSIAF[Devengado])) -> 143401 | H27: =IF(D27="","",D27-G27) -> 16599 | I27: =IF(D27="","",IF(D27=0,0,G27/D27)) -> 0.89625625 | K27: Por completar | L27: =IF(COUNTIF(tCartera[CUI],"2717156")=0,"Sin PMI",IF(INDEX(tCartera[PMI2026],MATCH("2717156",tCartera[CUI],0))="","No informado",INDEX(tCartera[PMI2026],MATCH("2717156",tCartera[CUI],0)))) -> Sin PMI | M27: =IF(COUNTIF(tCartera[CUI],"2717156")=0,"Sin PMI",IF(INDEX(tCartera[PMI2027],MATCH("2717156",tCartera[CUI],0))="","No informado",INDEX(tCartera[PMI2027],MATCH("2717156",tCartera[CUI],0)))) -> Sin PMI | N27: =IF(COUNTIF(tCartera[CUI],"2717156")=0,"Sin PMI",IF(INDEX(tCartera[PMI2028],MATCH("2717156",tCartera[CUI],0))="","No informado",INDEX(tCartera[PMI2028],MATCH("2717156",tCartera[CUI],0)))) -> Sin PMI | O27: =IF(COUNTIF(tCartera[CUI],"2717156")=0,"Sin PMI",IF(INDEX(tCartera[PMI2029],MATCH("2717156",tCartera[CUI],0))="","No informado",INDEX(tCartera[PMI2029],MATCH("2717156",tCartera[CUI],0)))) -> Sin PMI
A28: =SUBTOTAL(103,$B$8:B28)+287 -> 305 | B28: 393 | C28: 2717157.MEJORAMIENTO DE LA PRODUCCION Y ENGORDE DE GANADO VACUNO A TRAVES DE LA OPTIMIZACION DE LA ALIMENTACION EN LA ASOCIACION DE PRODUCTORES AGROPECUARIOS EL TORITO BRAVO DEL DISTRITO DE QUILCAPUNCO, PROVINCIA DE SAN ANTONIO DE PUTINA, REGION PUNO. | D28: =IF(COUNTIF(tSIAF[Clave],"2717157|393")=0,"",SUMIF(tSIAF[Clave],"2717157|393",tSIAF[PIM])) -> 160000 | E28: =IF(COUNTIF(tSIAF[Clave],"2717157|393")=0,"",SUMIF(tSIAF[Clave],"2717157|393",tSIAF[Certificacion])) -> 149840 | F28: =IF(D28="","",D28-E28) -> 10160 | G28: =IF(COUNTIF(tSIAF[Clave],"2717157|393")=0,"",SUMIF(tSIAF[Clave],"2717157|393",tSIAF[Devengado])) -> 18740 | H28: =IF(D28="","",D28-G28) -> 141260 | I28: =IF(D28="","",IF(D28=0,0,G28/D28)) -> 0.117125 | K28: Por completar | L28: =IF(COUNTIF(tCartera[CUI],"2717157")=0,"Sin PMI",IF(INDEX(tCartera[PMI2026],MATCH("2717157",tCartera[CUI],0))="","No informado",INDEX(tCartera[PMI2026],MATCH("2717157",tCartera[CUI],0)))) -> Sin PMI | M28: =IF(COUNTIF(tCartera[CUI],"2717157")=0,"Sin PMI",IF(INDEX(tCartera[PMI2027],MATCH("2717157",tCartera[CUI],0))="","No informado",INDEX(tCartera[PMI2027],MATCH("2717157",tCartera[CUI],0)))) -> Sin PMI | N28: =IF(COUNTIF(tCartera[CUI],"2717157")=0,"Sin PMI",IF(INDEX(tCartera[PMI2028],MATCH("2717157",tCartera[CUI],0))="","No informado",INDEX(tCartera[PMI2028],MATCH("2717157",tCartera[CUI],0)))) -> Sin PMI | O28: =IF(COUNTIF(tCartera[CUI],"2717157")=0,"Sin PMI",IF(INDEX(tCartera[PMI2029],MATCH("2717157",tCartera[CUI],0))="","No informado",INDEX(tCartera[PMI2029],MATCH("2717157",tCartera[CUI],0)))) -> Sin PMI
A29: =SUBTOTAL(103,$B$8:B29)+287 -> 306 | B29: 397 | C29: 2717161.MEJORAMIENTO DE LA CAPACIDAD DE TRANSFORMACION DE CHIPS DE PAPA NATIVA, EN LA AEO ASOCIACION DE PRODUCTORES MULTIPLES SAN ISIDRO DE TANTAMACO DEL DISTRITO DE MACUSANI, PROVINCIA DE CARABAYA, REGION DE PUNO | D29: =IF(COUNTIF(tSIAF[Clave],"2717161|397")=0,"",SUMIF(tSIAF[Clave],"2717161|397",tSIAF[PIM])) -> 160000 | E29: =IF(COUNTIF(tSIAF[Clave],"2717161|397")=0,"",SUMIF(tSIAF[Clave],"2717161|397",tSIAF[Certificacion])) -> 148990 | F29: =IF(D29="","",D29-E29) -> 11010 | G29: =IF(COUNTIF(tSIAF[Clave],"2717161|397")=0,"",SUMIF(tSIAF[Clave],"2717161|397",tSIAF[Devengado])) -> 26000 | H29: =IF(D29="","",D29-G29) -> 134000 | I29: =IF(D29="","",IF(D29=0,0,G29/D29)) -> 0.1625 | K29: Por completar | L29: =IF(COUNTIF(tCartera[CUI],"2717161")=0,"Sin PMI",IF(INDEX(tCartera[PMI2026],MATCH("2717161",tCartera[CUI],0))="","No informado",INDEX(tCartera[PMI2026],MATCH("2717161",tCartera[CUI],0)))) -> Sin PMI | M29: =IF(COUNTIF(tCartera[CUI],"2717161")=0,"Sin PMI",IF(INDEX(tCartera[PMI2027],MATCH("2717161",tCartera[CUI],0))="","No informado",INDEX(tCartera[PMI2027],MATCH("2717161",tCartera[CUI],0)))) -> Sin PMI | N29: =IF(COUNTIF(tCartera[CUI],"2717161")=0,"Sin PMI",IF(INDEX(tCartera[PMI2028],MATCH("2717161",tCartera[CUI],0))="","No informado",INDEX(tCartera[PMI2028],MATCH("2717161",tCartera[CUI],0)))) -> Sin PMI | O29: =IF(COUNTIF(tCartera[CUI],"2717161")=0,"Sin PMI",IF(INDEX(tCartera[PMI2029],MATCH("2717161",tCartera[CUI],0))="","No informado",INDEX(tCartera[PMI2029],MATCH("2717161",tCartera[CUI],0)))) -> Sin PMI
A30: =SUBTOTAL(103,$B$8:B30)+287 -> 307 | B30: 404 | C30: 2717169.CREACION DE UNA PLANTA PROCESADORA DE QUINUA EN LA AEO ASOCIACION DE PRODUCTORES AGROPECUARIOS ROQUE APAZA PAMPA DEL DISTRITO DE PAUCARCOLLA, PROVINCIA DE PUNO, DEPARTAMENTO DE PUNO | D30: =IF(COUNTIF(tSIAF[Clave],"2717169|404")=0,"",SUMIF(tSIAF[Clave],"2717169|404",tSIAF[PIM])) -> 160000 | E30: =IF(COUNTIF(tSIAF[Clave],"2717169|404")=0,"",SUMIF(tSIAF[Clave],"2717169|404",tSIAF[Certificacion])) -> 150870 | F30: =IF(D30="","",D30-E30) -> 9130 | G30: =IF(COUNTIF(tSIAF[Clave],"2717169|404")=0,"",SUMIF(tSIAF[Clave],"2717169|404",tSIAF[Devengado])) -> 45270 | H30: =IF(D30="","",D30-G30) -> 114730 | I30: =IF(D30="","",IF(D30=0,0,G30/D30)) -> 0.2829375 | K30: Por completar | L30: =IF(COUNTIF(tCartera[CUI],"2717169")=0,"Sin PMI",IF(INDEX(tCartera[PMI2026],MATCH("2717169",tCartera[CUI],0))="","No informado",INDEX(tCartera[PMI2026],MATCH("2717169",tCartera[CUI],0)))) -> Sin PMI | M30: =IF(COUNTIF(tCartera[CUI],"2717169")=0,"Sin PMI",IF(INDEX(tCartera[PMI2027],MATCH("2717169",tCartera[CUI],0))="","No informado",INDEX(tCartera[PMI2027],MATCH("2717169",tCartera[CUI],0)))) -> Sin PMI | N30: =IF(COUNTIF(tCartera[CUI],"2717169")=0,"Sin PMI",IF(INDEX(tCartera[PMI2028],MATCH("2717169",tCartera[CUI],0))="","No informado",INDEX(tCartera[PMI2028],MATCH("2717169",tCartera[CUI],0)))) -> Sin PMI | O30: =IF(COUNTIF(tCartera[CUI],"2717169")=0,"Sin PMI",IF(INDEX(tCartera[PMI2029],MATCH("2717169",tCartera[CUI],0))="","No informado",INDEX(tCartera[PMI2029],MATCH("2717169",tCartera[CUI],0)))) -> Sin PMI
A31: =SUBTOTAL(103,$B$8:B31)+287 -> 308 | B31: 407 | C31: 2717172.MEJORAMIENTO DEL PROCESO DE PRODUCCION DE QUESO EN LA ASOCIACION DE PEQUENOS PRODUCTORES AGROPECUARIOS DE DERIVADOS LACTEOS SAN JOSE TATASQA, DISTRITO DE LAMPA, PROVINCIA DE LAMPA Y DEPARTAMENTO DE PUNO | D31: =IF(COUNTIF(tSIAF[Clave],"2717172|407")=0,"",SUMIF(tSIAF[Clave],"2717172|407",tSIAF[PIM])) -> 160000 | E31: =IF(COUNTIF(tSIAF[Clave],"2717172|407")=0,"",SUMIF(tSIAF[Clave],"2717172|407",tSIAF[Certificacion])) -> 151322 | F31: =IF(D31="","",D31-E31) -> 8678 | G31: =IF(COUNTIF(tSIAF[Clave],"2717172|407")=0,"",SUMIF(tSIAF[Clave],"2717172|407",tSIAF[Devengado])) -> 96322 | H31: =IF(D31="","",D31-G31) -> 63678 | I31: =IF(D31="","",IF(D31=0,0,G31/D31)) -> 0.6020125 | K31: Por completar | L31: =IF(COUNTIF(tCartera[CUI],"2717172")=0,"Sin PMI",IF(INDEX(tCartera[PMI2026],MATCH("2717172",tCartera[CUI],0))="","No informado",INDEX(tCartera[PMI2026],MATCH("2717172",tCartera[CUI],0)))) -> Sin PMI | M31: =IF(COUNTIF(tCartera[CUI],"2717172")=0,"Sin PMI",IF(INDEX(tCartera[PMI2027],MATCH("2717172",tCartera[CUI],0))="","No informado",INDEX(tCartera[PMI2027],MATCH("2717172",tCartera[CUI],0)))) -> Sin PMI | N31: =IF(COUNTIF(tCartera[CUI],"2717172")=0,"Sin PMI",IF(INDEX(tCartera[PMI2028],MATCH("2717172",tCartera[CUI],0))="","No informado",INDEX(tCartera[PMI2028],MATCH("2717172",tCartera[CUI],0)))) -> Sin PMI | O31: =IF(COUNTIF(tCartera[CUI],"2717172")=0,"Sin PMI",IF(INDEX(tCartera[PMI2029],MATCH("2717172",tCartera[CUI],0))="","No informado",INDEX(tCartera[PMI2029],MATCH("2717172",tCartera[CUI],0)))) -> Sin PMI
A32: =SUBTOTAL(103,$B$8:B32)+287 -> 309 | B32: 412 | C32: 2717177.MEJORAMIENTO TECNOLOGICO DE LA PRODUCCION Y COMPETITIVIDAD EN EL ENGORDE DE VACUNOS DE CARNE DE LA ASOCIACION DE PRODUCTORES AGROPECUARIOS Y OTROS GENERACION ACTIVA DE LA COMUNIDAD DE CHALLACOLLO, DISTRITO HUACULLANI, PROVINCIA CHUCUITO,REGION PUN | D32: =IF(COUNTIF(tSIAF[Clave],"2717177|412")=0,"",SUMIF(tSIAF[Clave],"2717177|412",tSIAF[PIM])) -> 160000 | E32: =IF(COUNTIF(tSIAF[Clave],"2717177|412")=0,"",SUMIF(tSIAF[Clave],"2717177|412",tSIAF[Certificacion])) -> 145570.62 | F32: =IF(D32="","",D32-E32) -> 14429.38 | G32: =IF(COUNTIF(tSIAF[Clave],"2717177|412")=0,"",SUMIF(tSIAF[Clave],"2717177|412",tSIAF[Devengado])) -> 10545 | H32: =IF(D32="","",D32-G32) -> 149455 | I32: =IF(D32="","",IF(D32=0,0,G32/D32)) -> 0.06590625 | K32: Por completar | L32: =IF(COUNTIF(tCartera[CUI],"2717177")=0,"Sin PMI",IF(INDEX(tCartera[PMI2026],MATCH("2717177",tCartera[CUI],0))="","No informado",INDEX(tCartera[PMI2026],MATCH("2717177",tCartera[CUI],0)))) -> Sin PMI | M32: =IF(COUNTIF(tCartera[CUI],"2717177")=0,"Sin PMI",IF(INDEX(tCartera[PMI2027],MATCH("2717177",tCartera[CUI],0))="","No informado",INDEX(tCartera[PMI2027],MATCH("2717177",tCartera[CUI],0)))) -> Sin PMI | N32: =IF(COUNTIF(tCartera[CUI],"2717177")=0,"Sin PMI",IF(INDEX(tCartera[PMI2028],MATCH("2717177",tCartera[CUI],0))="","No informado",INDEX(tCartera[PMI2028],MATCH("2717177",tCartera[CUI],0)))) -> Sin PMI | O32: =IF(COUNTIF(tCartera[CUI],"2717177")=0,"Sin PMI",IF(INDEX(tCartera[PMI2029],MATCH("2717177",tCartera[CUI],0))="","No informado",INDEX(tCartera[PMI2029],MATCH("2717177",tCartera[CUI],0)))) -> Sin PMI
A33: =SUBTOTAL(103,$B$8:B33)+287 -> 310 | B33: 420 | C33: 2717188.MEJORAMIENTO DE LA COMPETITIVIDAD DE LA PRODUCCION DE LECHE FRESCA EN LA COOPERATIVA AGROINDUSTRIAL SAGRADO CORAZON DE JESUS DE CCOTA DISTRITO DE PLATERIA PROVINCIA DE PUNO DEPARTAMENTO DE PUNO | D33: =IF(COUNTIF(tSIAF[Clave],"2717188|420")=0,"",SUMIF(tSIAF[Clave],"2717188|420",tSIAF[PIM])) -> 160000 | E33: =IF(COUNTIF(tSIAF[Clave],"2717188|420")=0,"",SUMIF(tSIAF[Clave],"2717188|420",tSIAF[Certificacion])) -> 154450 | F33: =IF(D33="","",D33-E33) -> 5550 | G33: =IF(COUNTIF(tSIAF[Clave],"2717188|420")=0,"",SUMIF(tSIAF[Clave],"2717188|420",tSIAF[Devengado])) -> 129270 | H33: =IF(D33="","",D33-G33) -> 30730 | I33: =IF(D33="","",IF(D33=0,0,G33/D33)) -> 0.8079375 | K33: Por completar | L33: =IF(COUNTIF(tCartera[CUI],"2717188")=0,"Sin PMI",IF(INDEX(tCartera[PMI2026],MATCH("2717188",tCartera[CUI],0))="","No informado",INDEX(tCartera[PMI2026],MATCH("2717188",tCartera[CUI],0)))) -> Sin PMI | M33: =IF(COUNTIF(tCartera[CUI],"2717188")=0,"Sin PMI",IF(INDEX(tCartera[PMI2027],MATCH("2717188",tCartera[CUI],0))="","No informado",INDEX(tCartera[PMI2027],MATCH("2717188",tCartera[CUI],0)))) -> Sin PMI | N33: =IF(COUNTIF(tCartera[CUI],"2717188")=0,"Sin PMI",IF(INDEX(tCartera[PMI2028],MATCH("2717188",tCartera[CUI],0))="","No informado",INDEX(tCartera[PMI2028],MATCH("2717188",tCartera[CUI],0)))) -> Sin PMI | O33: =IF(COUNTIF(tCartera[CUI],"2717188")=0,"Sin PMI",IF(INDEX(tCartera[PMI2029],MATCH("2717188",tCartera[CUI],0))="","No informado",INDEX(tCartera[PMI2029],MATCH("2717188",tCartera[CUI],0)))) -> Sin PMI
A34: =SUBTOTAL(103,$B$8:B34)+287 -> 311 | B34: 423 | C34: 2717192.MEJORAMIENTO DE LA PRODUCCION Y PROCESAMIENTO DE CULTIVOS FORRAJEROS EN LA ASOCIACION DE PRODUCTORES AGROPECUARIOS ALIANZA RENOVADO CALLANCA, DISTRITO DE PLATERIA, PROVINCIA DE PUNO, DEPARTAMENTO DE PUNO | D34: =IF(COUNTIF(tSIAF[Clave],"2717192|423")=0,"",SUMIF(tSIAF[Clave],"2717192|423",tSIAF[PIM])) -> 160000 | E34: =IF(COUNTIF(tSIAF[Clave],"2717192|423")=0,"",SUMIF(tSIAF[Clave],"2717192|423",tSIAF[Certificacion])) -> 146000 | F34: =IF(D34="","",D34-E34) -> 14000 | G34: =IF(COUNTIF(tSIAF[Clave],"2717192|423")=0,"",SUMIF(tSIAF[Clave],"2717192|423",tSIAF[Devengado])) -> 2000 | H34: =IF(D34="","",D34-G34) -> 158000 | I34: =IF(D34="","",IF(D34=0,0,G34/D34)) -> 0.0125 | K34: Por completar | L34: =IF(COUNTIF(tCartera[CUI],"2717192")=0,"Sin PMI",IF(INDEX(tCartera[PMI2026],MATCH("2717192",tCartera[CUI],0))="","No informado",INDEX(tCartera[PMI2026],MATCH("2717192",tCartera[CUI],0)))) -> Sin PMI | M34: =IF(COUNTIF(tCartera[CUI],"2717192")=0,"Sin PMI",IF(INDEX(tCartera[PMI2027],MATCH("2717192",tCartera[CUI],0))="","No informado",INDEX(tCartera[PMI2027],MATCH("2717192",tCartera[CUI],0)))) -> Sin PMI | N34: =IF(COUNTIF(tCartera[CUI],"2717192")=0,"Sin PMI",IF(INDEX(tCartera[PMI2028],MATCH("2717192",tCartera[CUI],0))="","No informado",INDEX(tCartera[PMI2028],MATCH("2717192",tCartera[CUI],0)))) -> Sin PMI | O34: =IF(COUNTIF(tCartera[CUI],"2717192")=0,"Sin PMI",IF(INDEX(tCartera[PMI2029],MATCH("2717192",tCartera[CUI],0))="","No informado",INDEX(tCartera[PMI2029],MATCH("2717192",tCartera[CUI],0)))) -> Sin PMI
A35: =SUBTOTAL(103,$B$8:B35)+287 -> 312 | B35: 425 | C35: 2717194.MEJORAMIENTO DEL CENTRO DE ENGORDE Y COMERCIALIZACION DE GANADO VACUNO EN LA ASOCIACION DE PRODUCTORES GANADERIA LA CANTUTA, DISTRITO DE VILQUE, PROVINCIA PUNO Y REGION PUNO | D35: =IF(COUNTIF(tSIAF[Clave],"2717194|425")=0,"",SUMIF(tSIAF[Clave],"2717194|425",tSIAF[PIM])) -> 160000 | E35: =IF(COUNTIF(tSIAF[Clave],"2717194|425")=0,"",SUMIF(tSIAF[Clave],"2717194|425",tSIAF[Certificacion])) -> 92650 | F35: =IF(D35="","",D35-E35) -> 67350 | G35: =IF(COUNTIF(tSIAF[Clave],"2717194|425")=0,"",SUMIF(tSIAF[Clave],"2717194|425",tSIAF[Devengado])) -> 89300 | H35: =IF(D35="","",D35-G35) -> 70700 | I35: =IF(D35="","",IF(D35=0,0,G35/D35)) -> 0.558125 | K35: Por completar | L35: =IF(COUNTIF(tCartera[CUI],"2717194")=0,"Sin PMI",IF(INDEX(tCartera[PMI2026],MATCH("2717194",tCartera[CUI],0))="","No informado",INDEX(tCartera[PMI2026],MATCH("2717194",tCartera[CUI],0)))) -> Sin PMI | M35: =IF(COUNTIF(tCartera[CUI],"2717194")=0,"Sin PMI",IF(INDEX(tCartera[PMI2027],MATCH("2717194",tCartera[CUI],0))="","No informado",INDEX(tCartera[PMI2027],MATCH("2717194",tCartera[CUI],0)))) -> Sin PMI | N35: =IF(COUNTIF(tCartera[CUI],"2717194")=0,"Sin PMI",IF(INDEX(tCartera[PMI2028],MATCH("2717194",tCartera[CUI],0))="","No informado",INDEX(tCartera[PMI2028],MATCH("2717194",tCartera[CUI],0)))) -> Sin PMI | O35: =IF(COUNTIF(tCartera[CUI],"2717194")=0,"Sin PMI",IF(INDEX(tCartera[PMI2029],MATCH("2717194",tCartera[CUI],0))="","No informado",INDEX(tCartera[PMI2029],MATCH("2717194",tCartera[CUI],0)))) -> Sin PMI
A36: =SUBTOTAL(103,$B$8:B36)+287 -> 313 | B36: 351 | C36: 2612522: MEJORAMIENTO DE LA PRODUCCION Y TRANSFORMACION DE QUESOS EN LA ASOCIACION DE PRODUCTORES LACTI SUR DE HUAPACA SANTIAGO DEL DISTRITO DE POMATA, PROVINCIA DE CHUCUITO Y DEPARTAMENTO DE PUN | D36: =IF(COUNTIF(tSIAF[Clave],"2612522|351")=0,"",SUMIF(tSIAF[Clave],"2612522|351",tSIAF[PIM])) -> 61500 | E36: =IF(COUNTIF(tSIAF[Clave],"2612522|351")=0,"",SUMIF(tSIAF[Clave],"2612522|351",tSIAF[Certificacion])) -> 59000 | F36: =IF(D36="","",D36-E36) -> 2500 | G36: =IF(COUNTIF(tSIAF[Clave],"2612522|351")=0,"",SUMIF(tSIAF[Clave],"2612522|351",tSIAF[Devengado])) -> 0 | H36: =IF(D36="","",D36-G36) -> 61500 | I36: =IF(D36="","",IF(D36=0,0,G36/D36)) -> 0 | K36: Por completar | L36: =IF(COUNTIF(tCartera[CUI],"2612522")=0,"Sin PMI",IF(INDEX(tCartera[PMI2026],MATCH("2612522",tCartera[CUI],0))="","No informado",INDEX(tCartera[PMI2026],MATCH("2612522",tCartera[CUI],0)))) -> Sin PMI | M36: =IF(COUNTIF(tCartera[CUI],"2612522")=0,"Sin PMI",IF(INDEX(tCartera[PMI2027],MATCH("2612522",tCartera[CUI],0))="","No informado",INDEX(tCartera[PMI2027],MATCH("2612522",tCartera[CUI],0)))) -> Sin PMI | N36: =IF(COUNTIF(tCartera[CUI],"2612522")=0,"Sin PMI",IF(INDEX(tCartera[PMI2028],MATCH("2612522",tCartera[CUI],0))="","No informado",INDEX(tCartera[PMI2028],MATCH("2612522",tCartera[CUI],0)))) -> Sin PMI | O36: =IF(COUNTIF(tCartera[CUI],"2612522")=0,"Sin PMI",IF(INDEX(tCartera[PMI2029],MATCH("2612522",tCartera[CUI],0))="","No informado",INDEX(tCartera[PMI2029],MATCH("2612522",tCartera[CUI],0)))) -> Sin PMI
A37: =SUBTOTAL(103,$B$8:B37)+287 -> 314 | B37: 352 | C37: 2612541: MEJORAMIENTO DE LA PRODUCCION Y COMERCIALIZACION DE DERIVADOS LACTEOS EN LA ASOCIACION DE PRODUCTORES AGROPECUARIOS EMPRENDEDORES LOS CLAVELES DE SAN SALVADOR HUATASANI, DEL DISTRITO DE HUATASANI, PROVINCIA DE HUANCANE Y REGION DE PUNO | D37: =IF(COUNTIF(tSIAF[Clave],"2612541|352")=0,"",SUMIF(tSIAF[Clave],"2612541|352",tSIAF[PIM])) -> 62000 | E37: =IF(COUNTIF(tSIAF[Clave],"2612541|352")=0,"",SUMIF(tSIAF[Clave],"2612541|352",tSIAF[Certificacion])) -> 61766.67 | F37: =IF(D37="","",D37-E37) -> 233.33 | G37: =IF(COUNTIF(tSIAF[Clave],"2612541|352")=0,"",SUMIF(tSIAF[Clave],"2612541|352",tSIAF[Devengado])) -> 0 | H37: =IF(D37="","",D37-G37) -> 62000 | I37: =IF(D37="","",IF(D37=0,0,G37/D37)) -> 0 | K37: Por completar | L37: =IF(COUNTIF(tCartera[CUI],"2612541")=0,"Sin PMI",IF(INDEX(tCartera[PMI2026],MATCH("2612541",tCartera[CUI],0))="","No informado",INDEX(tCartera[PMI2026],MATCH("2612541",tCartera[CUI],0)))) -> Sin PMI | M37: =IF(COUNTIF(tCartera[CUI],"2612541")=0,"Sin PMI",IF(INDEX(tCartera[PMI2027],MATCH("2612541",tCartera[CUI],0))="","No informado",INDEX(tCartera[PMI2027],MATCH("2612541",tCartera[CUI],0)))) -> Sin PMI | N37: =IF(COUNTIF(tCartera[CUI],"2612541")=0,"Sin PMI",IF(INDEX(tCartera[PMI2028],MATCH("2612541",tCartera[CUI],0))="","No informado",INDEX(tCartera[PMI2028],MATCH("2612541",tCartera[CUI],0)))) -> Sin PMI | O37: =IF(COUNTIF(tCartera[CUI],"2612541")=0,"Sin PMI",IF(INDEX(tCartera[PMI2029],MATCH("2612541",tCartera[CUI],0))="","No informado",INDEX(tCartera[PMI2029],MATCH("2612541",tCartera[CUI],0)))) -> Sin PMI
A38: =SUBTOTAL(103,$B$8:B38)+287 -> 315 | B38: 353 | C38: 2680578: MEJORAMIENTO DEL PROCESO Y CALIDAD DEL QUESO TIPO PARIA DE LA ASOCIACION LACTEOS LIKHA QUINSACHATA SOCIEDAD COMERCIAL DE RESPONSABILIDAD LIMITADA, DISTRITO CABANILLA, PROVINCIA LAMPA, REGION PUNO. | D38: =IF(COUNTIF(tSIAF[Clave],"2680578|353")=0,"",SUMIF(tSIAF[Clave],"2680578|353",tSIAF[PIM])) -> 63755 | E38: =IF(COUNTIF(tSIAF[Clave],"2680578|353")=0,"",SUMIF(tSIAF[Clave],"2680578|353",tSIAF[Certificacion])) -> 60139.48 | F38: =IF(D38="","",D38-E38) -> 3615.52 | G38: =IF(COUNTIF(tSIAF[Clave],"2680578|353")=0,"",SUMIF(tSIAF[Clave],"2680578|353",tSIAF[Devengado])) -> 2139.48 | H38: =IF(D38="","",D38-G38) -> 61615.52 | I38: =IF(D38="","",IF(D38=0,0,G38/D38)) -> 0.033557839 | K38: Por completar | L38: =IF(COUNTIF(tCartera[CUI],"2680578")=0,"Sin PMI",IF(INDEX(tCartera[PMI2026],MATCH("2680578",tCartera[CUI],0))="","No informado",INDEX(tCartera[PMI2026],MATCH("2680578",tCartera[CUI],0)))) -> Sin PMI | M38: =IF(COUNTIF(tCartera[CUI],"2680578")=0,"Sin PMI",IF(INDEX(tCartera[PMI2027],MATCH("2680578",tCartera[CUI],0))="","No informado",INDEX(tCartera[PMI2027],MATCH("2680578",tCartera[CUI],0)))) -> Sin PMI | N38: =IF(COUNTIF(tCartera[CUI],"2680578")=0,"Sin PMI",IF(INDEX(tCartera[PMI2028],MATCH("2680578",tCartera[CUI],0))="","No informado",INDEX(tCartera[PMI2028],MATCH("2680578",tCartera[CUI],0)))) -> Sin PMI | O38: =IF(COUNTIF(tCartera[CUI],"2680578")=0,"Sin PMI",IF(INDEX(tCartera[PMI2029],MATCH("2680578",tCartera[CUI],0))="","No informado",INDEX(tCartera[PMI2029],MATCH("2680578",tCartera[CUI],0)))) -> Sin PMI
A39: =SUBTOTAL(103,$B$8:B39)+287 -> 316 | B39: 354 | C39: 2676418: MEJORAMIENTO DE UNA PLANTA PROCESADORA DE LECHE PARA LA ELABORACION DE QUESOS FRESCOS TIPO PARIA DE LA ASOCIACION DE PRODUCTORES AGROPECUARIOS VILLA ACASSO APROAVA, DISTRITO DE PILCUYO, PROVINCIA DE EL COLLAO, REGION DE PUNO | D39: =IF(COUNTIF(tSIAF[Clave],"2676418|354")=0,"",SUMIF(tSIAF[Clave],"2676418|354",tSIAF[PIM])) -> 65438 | E39: =IF(COUNTIF(tSIAF[Clave],"2676418|354")=0,"",SUMIF(tSIAF[Clave],"2676418|354",tSIAF[Certificacion])) -> 59650 | F39: =IF(D39="","",D39-E39) -> 5788 | G39: =IF(COUNTIF(tSIAF[Clave],"2676418|354")=0,"",SUMIF(tSIAF[Clave],"2676418|354",tSIAF[Devengado])) -> 0 | H39: =IF(D39="","",D39-G39) -> 65438 | I39: =IF(D39="","",IF(D39=0,0,G39/D39)) -> 0 | K39: Por completar | L39: =IF(COUNTIF(tCartera[CUI],"2676418")=0,"Sin PMI",IF(INDEX(tCartera[PMI2026],MATCH("2676418",tCartera[CUI],0))="","No informado",INDEX(tCartera[PMI2026],MATCH("2676418",tCartera[CUI],0)))) -> Sin PMI | M39: =IF(COUNTIF(tCartera[CUI],"2676418")=0,"Sin PMI",IF(INDEX(tCartera[PMI2027],MATCH("2676418",tCartera[CUI],0))="","No informado",INDEX(tCartera[PMI2027],MATCH("2676418",tCartera[CUI],0)))) -> Sin PMI | N39: =IF(COUNTIF(tCartera[CUI],"2676418")=0,"Sin PMI",IF(INDEX(tCartera[PMI2028],MATCH("2676418",tCartera[CUI],0))="","No informado",INDEX(tCartera[PMI2028],MATCH("2676418",tCartera[CUI],0)))) -> Sin PMI | O39: =IF(COUNTIF(tCartera[CUI],"2676418")=0,"Sin PMI",IF(INDEX(tCartera[PMI2029],MATCH("2676418",tCartera[CUI],0))="","No informado",INDEX(tCartera[PMI2029],MATCH("2676418",tCartera[CUI],0)))) -> Sin PMI
A40: =SUBTOTAL(103,$B$8:B40)+287 -> 317 | B40: 355 | C40: 2681120: MEJORAMIENTO TECNOLOGICO DEL VALOR AGREGADO DE HABAS EN LA ASOCIACION DE PRODUCTORES AGRARIOS Y PECUARIOS NUEVO PROGRESO TAUCAMAYA, DISTRITO DE COPANI, PROVINCIA DE YUNGUYO, REGION PUNO. | D40: =IF(COUNTIF(tSIAF[Clave],"2681120|355")=0,"",SUMIF(tSIAF[Clave],"2681120|355",tSIAF[PIM])) -> 61200 | E40: =IF(COUNTIF(tSIAF[Clave],"2681120|355")=0,"",SUMIF(tSIAF[Clave],"2681120|355",tSIAF[Certificacion])) -> 59150 | F40: =IF(D40="","",D40-E40) -> 2050 | G40: =IF(COUNTIF(tSIAF[Clave],"2681120|355")=0,"",SUMIF(tSIAF[Clave],"2681120|355",tSIAF[Devengado])) -> 59150 | H40: =IF(D40="","",D40-G40) -> 2050 | I40: =IF(D40="","",IF(D40=0,0,G40/D40)) -> 0.96650327 | K40: Por completar | L40: =IF(COUNTIF(tCartera[CUI],"2681120")=0,"Sin PMI",IF(INDEX(tCartera[PMI2026],MATCH("2681120",tCartera[CUI],0))="","No informado",INDEX(tCartera[PMI2026],MATCH("2681120",tCartera[CUI],0)))) -> Sin PMI | M40: =IF(COUNTIF(tCartera[CUI],"2681120")=0,"Sin PMI",IF(INDEX(tCartera[PMI2027],MATCH("2681120",tCartera[CUI],0))="","No informado",INDEX(tCartera[PMI2027],MATCH("2681120",tCartera[CUI],0)))) -> Sin PMI | N40: =IF(COUNTIF(tCartera[CUI],"2681120")=0,"Sin PMI",IF(INDEX(tCartera[PMI2028],MATCH("2681120",tCartera[CUI],0))="","No informado",INDEX(tCartera[PMI2028],MATCH("2681120",tCartera[CUI],0)))) -> Sin PMI | O40: =IF(COUNTIF(tCartera[CUI],"2681120")=0,"Sin PMI",IF(INDEX(tCartera[PMI2029],MATCH("2681120",tCartera[CUI],0))="","No informado",INDEX(tCartera[PMI2029],MATCH("2681120",tCartera[CUI],0)))) -> Sin PMI
A41: =SUBTOTAL(103,$B$8:B41)+287 -> 318 | B41: 357 | C41: 2676423: MEJORAMIENTO EN LA PRODUCCION DE QUESOS TIPO PARIA EN LA ASOCIACION DE PRODUCTORES DE LECHE Y SUS DERIVADOS PIAS MILAN DE LA COMUNIDAD DE HUAYTA, DISTRITO DE LAMPA, PROVINCIA DE LAMPA DEL DEPARTAMENTO DE PUNO. | D41: =IF(COUNTIF(tSIAF[Clave],"2676423|357")=0,"",SUMIF(tSIAF[Clave],"2676423|357",tSIAF[PIM])) -> 2936 | E41: =IF(COUNTIF(tSIAF[Clave],"2676423|357")=0,"",SUMIF(tSIAF[Clave],"2676423|357",tSIAF[Certificacion])) -> 2936 | F41: =IF(D41="","",D41-E41) -> 0 | G41: =IF(COUNTIF(tSIAF[Clave],"2676423|357")=0,"",SUMIF(tSIAF[Clave],"2676423|357",tSIAF[Devengado])) -> 2936 | H41: =IF(D41="","",D41-G41) -> 0 | I41: =IF(D41="","",IF(D41=0,0,G41/D41)) -> 1 | K41: Por completar | L41: =IF(COUNTIF(tCartera[CUI],"2676423")=0,"Sin PMI",IF(INDEX(tCartera[PMI2026],MATCH("2676423",tCartera[CUI],0))="","No informado",INDEX(tCartera[PMI2026],MATCH("2676423",tCartera[CUI],0)))) -> Sin PMI | M41: =IF(COUNTIF(tCartera[CUI],"2676423")=0,"Sin PMI",IF(INDEX(tCartera[PMI2027],MATCH("2676423",tCartera[CUI],0))="","No informado",INDEX(tCartera[PMI2027],MATCH("2676423",tCartera[CUI],0)))) -> Sin PMI | N41: =IF(COUNTIF(tCartera[CUI],"2676423")=0,"Sin PMI",IF(INDEX(tCartera[PMI2028],MATCH("2676423",tCartera[CUI],0))="","No informado",INDEX(tCartera[PMI2028],MATCH("2676423",tCartera[CUI],0)))) -> Sin PMI | O41: =IF(COUNTIF(tCartera[CUI],"2676423")=0,"Sin PMI",IF(INDEX(tCartera[PMI2029],MATCH("2676423",tCartera[CUI],0))="","No informado",INDEX(tCartera[PMI2029],MATCH("2676423",tCartera[CUI],0)))) -> Sin PMI
A42: =SUBTOTAL(103,$B$8:B42)+287 -> 319 | B42: 358 | C42: 2676424: MEJORAMIENTO DE LA PLANTA PROCESADORA DE CAFE PARA LA ELABORACION DE CAFE TOSTADO MOLIDO DE LA COOPERATIVA AGRARIA CAFETALERA SAN IGNACIO LTDA., DISTRITO DE SAN PEDRO DE PUTINA PUNCO, PROVINCIA DE SANDIA, REGION DE PUNO | D42: =IF(COUNTIF(tSIAF[Clave],"2676424|358")=0,"",SUMIF(tSIAF[Clave],"2676424|358",tSIAF[PIM])) -> 10692 | E42: =IF(COUNTIF(tSIAF[Clave],"2676424|358")=0,"",SUMIF(tSIAF[Clave],"2676424|358",tSIAF[Certificacion])) -> 10691.76 | F42: =IF(D42="","",D42-E42) -> 0.24 | G42: =IF(COUNTIF(tSIAF[Clave],"2676424|358")=0,"",SUMIF(tSIAF[Clave],"2676424|358",tSIAF[Devengado])) -> 10691.76 | H42: =IF(D42="","",D42-G42) -> 0.24 | I42: =IF(D42="","",IF(D42=0,0,G42/D42)) -> 0.99997755 | K42: Por completar | L42: =IF(COUNTIF(tCartera[CUI],"2676424")=0,"Sin PMI",IF(INDEX(tCartera[PMI2026],MATCH("2676424",tCartera[CUI],0))="","No informado",INDEX(tCartera[PMI2026],MATCH("2676424",tCartera[CUI],0)))) -> Sin PMI | M42: =IF(COUNTIF(tCartera[CUI],"2676424")=0,"Sin PMI",IF(INDEX(tCartera[PMI2027],MATCH("2676424",tCartera[CUI],0))="","No informado",INDEX(tCartera[PMI2027],MATCH("2676424",tCartera[CUI],0)))) -> Sin PMI | N42: =IF(COUNTIF(tCartera[CUI],"2676424")=0,"Sin PMI",IF(INDEX(tCartera[PMI2028],MATCH("2676424",tCartera[CUI],0))="","No informado",INDEX(tCartera[PMI2028],MATCH("2676424",tCartera[CUI],0)))) -> Sin PMI | O42: =IF(COUNTIF(tCartera[CUI],"2676424")=0,"Sin PMI",IF(INDEX(tCartera[PMI2029],MATCH("2676424",tCartera[CUI],0))="","No informado",INDEX(tCartera[PMI2029],MATCH("2676424",tCartera[CUI],0)))) -> Sin PMI
A43: =SUBTOTAL(103,$B$8:B43)+287 -> 320 | B43: 359 | C43: 2681121: MEJORAMIENTO DE LA PRODUCCION DE PRENDAS DE ARTESANIA TEXTIL EN LA ASOCIACION DE PRODUCTORES RITA POMA DEL TAWANTINSUYO PUNO, DISTRITO PUNO, PROVINCIA PUNO Y REGION PUNO | D43: =IF(COUNTIF(tSIAF[Clave],"2681121|359")=0,"",SUMIF(tSIAF[Clave],"2681121|359",tSIAF[PIM])) -> 7816 | E43: =IF(COUNTIF(tSIAF[Clave],"2681121|359")=0,"",SUMIF(tSIAF[Clave],"2681121|359",tSIAF[Certificacion])) -> 4500 | F43: =IF(D43="","",D43-E43) -> 3316 | G43: =IF(COUNTIF(tSIAF[Clave],"2681121|359")=0,"",SUMIF(tSIAF[Clave],"2681121|359",tSIAF[Devengado])) -> 3000 | H43: =IF(D43="","",D43-G43) -> 4816 | I43: =IF(D43="","",IF(D43=0,0,G43/D43)) -> 0.38382805 | K43: Por completar | L43: =IF(COUNTIF(tCartera[CUI],"2681121")=0,"Sin PMI",IF(INDEX(tCartera[PMI2026],MATCH("2681121",tCartera[CUI],0))="","No informado",INDEX(tCartera[PMI2026],MATCH("2681121",tCartera[CUI],0)))) -> Sin PMI | M43: =IF(COUNTIF(tCartera[CUI],"2681121")=0,"Sin PMI",IF(INDEX(tCartera[PMI2027],MATCH("2681121",tCartera[CUI],0))="","No informado",INDEX(tCartera[PMI2027],MATCH("2681121",tCartera[CUI],0)))) -> Sin PMI | N43: =IF(COUNTIF(tCartera[CUI],"2681121")=0,"Sin PMI",IF(INDEX(tCartera[PMI2028],MATCH("2681121",tCartera[CUI],0))="","No informado",INDEX(tCartera[PMI2028],MATCH("2681121",tCartera[CUI],0)))) -> Sin PMI | O43: =IF(COUNTIF(tCartera[CUI],"2681121")=0,"Sin PMI",IF(INDEX(tCartera[PMI2029],MATCH("2681121",tCartera[CUI],0))="","No informado",INDEX(tCartera[PMI2029],MATCH("2681121",tCartera[CUI],0)))) -> Sin PMI
A44: =SUBTOTAL(103,$B$8:B44)+287 -> 321 | B44: 360 | C44: 2676426: MEJORAMIENTO DE LA PRODUCTIVIDAD Y GENERACION DE VALOR AGREGADO DEL GRANO DE QUINUA PARA SU COMERCIALIZACION EN LA ASOCIACION DE PRODUCTORES AGROPECUARIOS AGROINDUSTRIALES KAPIA DEL DISTRITO DE YUNGUYO, PROVINCIA DE YUNGUYO, DEPARTAMENTO DE PUNO. | D44: =IF(COUNTIF(tSIAF[Clave],"2676426|360")=0,"",SUMIF(tSIAF[Clave],"2676426|360",tSIAF[PIM])) -> 3546 | E44: =IF(COUNTIF(tSIAF[Clave],"2676426|360")=0,"",SUMIF(tSIAF[Clave],"2676426|360",tSIAF[Certificacion])) -> 3546 | F44: =IF(D44="","",D44-E44) -> 0 | G44: =IF(COUNTIF(tSIAF[Clave],"2676426|360")=0,"",SUMIF(tSIAF[Clave],"2676426|360",tSIAF[Devengado])) -> 3546 | H44: =IF(D44="","",D44-G44) -> 0 | I44: =IF(D44="","",IF(D44=0,0,G44/D44)) -> 1 | K44: Por completar | L44: =IF(COUNTIF(tCartera[CUI],"2676426")=0,"Sin PMI",IF(INDEX(tCartera[PMI2026],MATCH("2676426",tCartera[CUI],0))="","No informado",INDEX(tCartera[PMI2026],MATCH("2676426",tCartera[CUI],0)))) -> Sin PMI | M44: =IF(COUNTIF(tCartera[CUI],"2676426")=0,"Sin PMI",IF(INDEX(tCartera[PMI2027],MATCH("2676426",tCartera[CUI],0))="","No informado",INDEX(tCartera[PMI2027],MATCH("2676426",tCartera[CUI],0)))) -> Sin PMI | N44: =IF(COUNTIF(tCartera[CUI],"2676426")=0,"Sin PMI",IF(INDEX(tCartera[PMI2028],MATCH("2676426",tCartera[CUI],0))="","No informado",INDEX(tCartera[PMI2028],MATCH("2676426",tCartera[CUI],0)))) -> Sin PMI | O44: =IF(COUNTIF(tCartera[CUI],"2676426")=0,"Sin PMI",IF(INDEX(tCartera[PMI2029],MATCH("2676426",tCartera[CUI],0))="","No informado",INDEX(tCartera[PMI2029],MATCH("2676426",tCartera[CUI],0)))) -> Sin PMI
A45: =SUBTOTAL(103,$B$8:B45)+287 -> 322 | B45: 361 | C45: 2676427: MEJORAMIENTO DE LA PRODUCCION DE LECHE FRESCA EN LA ASOCIACION DE PRODUCTORES AGROPECUARIOS, AGROINDUSTRIALES, ARTESANALES CCACCALLACTA AMPATUIRE ORURILLO, DISTRITO ORURILLO, PROVINCIA MELGAR, REGION PUNO | D45: =IF(COUNTIF(tSIAF[Clave],"2676427|361")=0,"",SUMIF(tSIAF[Clave],"2676427|361",tSIAF[PIM])) -> 2555 | E45: =IF(COUNTIF(tSIAF[Clave],"2676427|361")=0,"",SUMIF(tSIAF[Clave],"2676427|361",tSIAF[Certificacion])) -> 2550 | F45: =IF(D45="","",D45-E45) -> 5 | G45: =IF(COUNTIF(tSIAF[Clave],"2676427|361")=0,"",SUMIF(tSIAF[Clave],"2676427|361",tSIAF[Devengado])) -> 2550 | H45: =IF(D45="","",D45-G45) -> 5 | I45: =IF(D45="","",IF(D45=0,0,G45/D45)) -> 0.99804305 | K45: Por completar | L45: =IF(COUNTIF(tCartera[CUI],"2676427")=0,"Sin PMI",IF(INDEX(tCartera[PMI2026],MATCH("2676427",tCartera[CUI],0))="","No informado",INDEX(tCartera[PMI2026],MATCH("2676427",tCartera[CUI],0)))) -> Sin PMI | M45: =IF(COUNTIF(tCartera[CUI],"2676427")=0,"Sin PMI",IF(INDEX(tCartera[PMI2027],MATCH("2676427",tCartera[CUI],0))="","No informado",INDEX(tCartera[PMI2027],MATCH("2676427",tCartera[CUI],0)))) -> Sin PMI | N45: =IF(COUNTIF(tCartera[CUI],"2676427")=0,"Sin PMI",IF(INDEX(tCartera[PMI2028],MATCH("2676427",tCartera[CUI],0))="","No informado",INDEX(tCartera[PMI2028],MATCH("2676427",tCartera[CUI],0)))) -> Sin PMI | O45: =IF(COUNTIF(tCartera[CUI],"2676427")=0,"Sin PMI",IF(INDEX(tCartera[PMI2029],MATCH("2676427",tCartera[CUI],0))="","No informado",INDEX(tCartera[PMI2029],MATCH("2676427",tCartera[CUI],0)))) -> Sin PMI
A46: =SUBTOTAL(103,$B$8:B46)+287 -> 323 | B46: 362 | C46: 2676430: MEJORAMIENTO DEL PROCESO DE PANIFICACION DE GRANOS ANDINOS EN LA ASOCIACION DE PRODUCTORES AGROPECUARIOS AGROINDUSTRIALES Y SERVICIOS MULTIPLES JC3 APAASM JC3 EN EL DISTRITO DE ILAVE PROVINCIA EL COLLAO REGION PUNO | D46: =IF(COUNTIF(tSIAF[Clave],"2676430|362")=0,"",SUMIF(tSIAF[Clave],"2676430|362",tSIAF[PIM])) -> 73376 | E46: =IF(COUNTIF(tSIAF[Clave],"2676430|362")=0,"",SUMIF(tSIAF[Clave],"2676430|362",tSIAF[Certificacion])) -> 69875.75 | F46: =IF(D46="","",D46-E46) -> 3500.25 | G46: =IF(COUNTIF(tSIAF[Clave],"2676430|362")=0,"",SUMIF(tSIAF[Clave],"2676430|362",tSIAF[Devengado])) -> 69875.75 | H46: =IF(D46="","",D46-G46) -> 3500.25 | I46: =IF(D46="","",IF(D46=0,0,G46/D46)) -> 0.95229707 | K46: Por completar | L46: =IF(COUNTIF(tCartera[CUI],"2676430")=0,"Sin PMI",IF(INDEX(tCartera[PMI2026],MATCH("2676430",tCartera[CUI],0))="","No informado",INDEX(tCartera[PMI2026],MATCH("2676430",tCartera[CUI],0)))) -> Sin PMI | M46: =IF(COUNTIF(tCartera[CUI],"2676430")=0,"Sin PMI",IF(INDEX(tCartera[PMI2027],MATCH("2676430",tCartera[CUI],0))="","No informado",INDEX(tCartera[PMI2027],MATCH("2676430",tCartera[CUI],0)))) -> Sin PMI | N46: =IF(COUNTIF(tCartera[CUI],"2676430")=0,"Sin PMI",IF(INDEX(tCartera[PMI2028],MATCH("2676430",tCartera[CUI],0))="","No informado",INDEX(tCartera[PMI2028],MATCH("2676430",tCartera[CUI],0)))) -> Sin PMI | O46: =IF(COUNTIF(tCartera[CUI],"2676430")=0,"Sin PMI",IF(INDEX(tCartera[PMI2029],MATCH("2676430",tCartera[CUI],0))="","No informado",INDEX(tCartera[PMI2029],MATCH("2676430",tCartera[CUI],0)))) -> Sin PMI
A47: =SUBTOTAL(103,$B$8:B47)+287 -> 324 | B47: 363 | C47: 2676431: MEJORAMIENTO DE LA PRODUCCION TEXTIL DE FIBRA DE ALPACA EN LA ASOCIACION DE PRODUCTORES AGROPECUARIOS AGROINDUSTRIALES Y ARTESANOS HUAYLLAPUJO, DISTRITO DE SANTA ROSA, PROVINCIA DE EL COLLAO, REGION PUNO | D47: =IF(COUNTIF(tSIAF[Clave],"2676431|363")=0,"",SUMIF(tSIAF[Clave],"2676431|363",tSIAF[PIM])) -> 54964 | E47: =IF(COUNTIF(tSIAF[Clave],"2676431|363")=0,"",SUMIF(tSIAF[Clave],"2676431|363",tSIAF[Certificacion])) -> 1977.5 | F47: =IF(D47="","",D47-E47) -> 52986.5 | G47: =IF(COUNTIF(tSIAF[Clave],"2676431|363")=0,"",SUMIF(tSIAF[Clave],"2676431|363",tSIAF[Devengado])) -> 1977.5 | H47: =IF(D47="","",D47-G47) -> 52986.5 | I47: =IF(D47="","",IF(D47=0,0,G47/D47)) -> 0.035978095 | K47: Por completar | L47: =IF(COUNTIF(tCartera[CUI],"2676431")=0,"Sin PMI",IF(INDEX(tCartera[PMI2026],MATCH("2676431",tCartera[CUI],0))="","No informado",INDEX(tCartera[PMI2026],MATCH("2676431",tCartera[CUI],0)))) -> Sin PMI | M47: =IF(COUNTIF(tCartera[CUI],"2676431")=0,"Sin PMI",IF(INDEX(tCartera[PMI2027],MATCH("2676431",tCartera[CUI],0))="","No informado",INDEX(tCartera[PMI2027],MATCH("2676431",tCartera[CUI],0)))) -> Sin PMI | N47: =IF(COUNTIF(tCartera[CUI],"2676431")=0,"Sin PMI",IF(INDEX(tCartera[PMI2028],MATCH("2676431",tCartera[CUI],0))="","No informado",INDEX(tCartera[PMI2028],MATCH("2676431",tCartera[CUI],0)))) -> Sin PMI | O47: =IF(COUNTIF(tCartera[CUI],"2676431")=0,"Sin PMI",IF(INDEX(tCartera[PMI2029],MATCH("2676431",tCartera[CUI],0))="","No informado",INDEX(tCartera[PMI2029],MATCH("2676431",tCartera[CUI],0)))) -> Sin PMI
A48: =SUBTOTAL(103,$B$8:B48)+287 -> 325 | B48: 364 | C48: 2676432: CREACION DE LA PLANTA DE PROCESO DE ELABORACION DE PAN DE QUINUA DE LA ASOCIACION DE TRANSFORMADORES DE GRANOS ANDINOS EN PANADERIA Y PASTELERIA ARTESANAL EL SOL DE LAMPA, DEL DISTRITO DE LAMPA, PROVINCIA DE LAMPA, REGION PUNO. | D48: =IF(COUNTIF(tSIAF[Clave],"2676432|364")=0,"",SUMIF(tSIAF[Clave],"2676432|364",tSIAF[PIM])) -> 73915 | E48: =IF(COUNTIF(tSIAF[Clave],"2676432|364")=0,"",SUMIF(tSIAF[Clave],"2676432|364",tSIAF[Certificacion])) -> 71560 | F48: =IF(D48="","",D48-E48) -> 2355 | G48: =IF(COUNTIF(tSIAF[Clave],"2676432|364")=0,"",SUMIF(tSIAF[Clave],"2676432|364",tSIAF[Devengado])) -> 69710 | H48: =IF(D48="","",D48-G48) -> 4205 | I48: =IF(D48="","",IF(D48=0,0,G48/D48)) -> 0.94311033 | K48: Por completar | L48: =IF(COUNTIF(tCartera[CUI],"2676432")=0,"Sin PMI",IF(INDEX(tCartera[PMI2026],MATCH("2676432",tCartera[CUI],0))="","No informado",INDEX(tCartera[PMI2026],MATCH("2676432",tCartera[CUI],0)))) -> Sin PMI | M48: =IF(COUNTIF(tCartera[CUI],"2676432")=0,"Sin PMI",IF(INDEX(tCartera[PMI2027],MATCH("2676432",tCartera[CUI],0))="","No informado",INDEX(tCartera[PMI2027],MATCH("2676432",tCartera[CUI],0)))) -> Sin PMI | N48: =IF(COUNTIF(tCartera[CUI],"2676432")=0,"Sin PMI",IF(INDEX(tCartera[PMI2028],MATCH("2676432",tCartera[CUI],0))="","No informado",INDEX(tCartera[PMI2028],MATCH("2676432",tCartera[CUI],0)))) -> Sin PMI | O48: =IF(COUNTIF(tCartera[CUI],"2676432")=0,"Sin PMI",IF(INDEX(tCartera[PMI2029],MATCH("2676432",tCartera[CUI],0))="","No informado",INDEX(tCartera[PMI2029],MATCH("2676432",tCartera[CUI],0)))) -> Sin PMI
A49: =SUBTOTAL(103,$B$8:B49)+287 -> 326 | B49: 365 | C49: 2681125: MEJORAMIENTO DE LA PRODUCTIVIDAD Y CALIDAD DE LECHE FRESCA EN LA ASOCIACION DE PRODUCTORES AGROPECUARIOS DE GANADO VACUNO LECHERO ARTESANAL KANCHAQ WASI DE COMUNIDAD COLCA ATUNCOLLA, DISTRITO DE ATUNCOLLA, PROVINCIA DE PUNO, REGION PUNO | D49: =IF(COUNTIF(tSIAF[Clave],"2681125|365")=0,"",SUMIF(tSIAF[Clave],"2681125|365",tSIAF[PIM])) -> 5098 | E49: =IF(COUNTIF(tSIAF[Clave],"2681125|365")=0,"",SUMIF(tSIAF[Clave],"2681125|365",tSIAF[Certificacion])) -> 5097 | F49: =IF(D49="","",D49-E49) -> 1 | G49: =IF(COUNTIF(tSIAF[Clave],"2681125|365")=0,"",SUMIF(tSIAF[Clave],"2681125|365",tSIAF[Devengado])) -> 5097 | H49: =IF(D49="","",D49-G49) -> 1 | I49: =IF(D49="","",IF(D49=0,0,G49/D49)) -> 0.99980384 | K49: Por completar | L49: =IF(COUNTIF(tCartera[CUI],"2681125")=0,"Sin PMI",IF(INDEX(tCartera[PMI2026],MATCH("2681125",tCartera[CUI],0))="","No informado",INDEX(tCartera[PMI2026],MATCH("2681125",tCartera[CUI],0)))) -> Sin PMI | M49: =IF(COUNTIF(tCartera[CUI],"2681125")=0,"Sin PMI",IF(INDEX(tCartera[PMI2027],MATCH("2681125",tCartera[CUI],0))="","No informado",INDEX(tCartera[PMI2027],MATCH("2681125",tCartera[CUI],0)))) -> Sin PMI | N49: =IF(COUNTIF(tCartera[CUI],"2681125")=0,"Sin PMI",IF(INDEX(tCartera[PMI2028],MATCH("2681125",tCartera[CUI],0))="","No informado",INDEX(tCartera[PMI2028],MATCH("2681125",tCartera[CUI],0)))) -> Sin PMI | O49: =IF(COUNTIF(tCartera[CUI],"2681125")=0,"Sin PMI",IF(INDEX(tCartera[PMI2029],MATCH("2681125",tCartera[CUI],0))="","No informado",INDEX(tCartera[PMI2029],MATCH("2681125",tCartera[CUI],0)))) -> Sin PMI
A50: =SUBTOTAL(103,$B$8:B50)+287 -> 327 | B50: 366 | C50: 2681128: MEJORAMIENTO DE LA PRODUCCION DE QUESOS TIPO PARIA DE LA ASOCIACION DE PRODUCTORES ORGANICOS AGROPECUARIOS Y AGROINDUSTRIALES LA LIBERTAD NUNOA, DISTRITO DE NUNOA, PROVINCIA DE MELGAR, REGION PUNO | D50: =IF(COUNTIF(tSIAF[Clave],"2681128|366")=0,"",SUMIF(tSIAF[Clave],"2681128|366",tSIAF[PIM])) -> 4800 | E50: =IF(COUNTIF(tSIAF[Clave],"2681128|366")=0,"",SUMIF(tSIAF[Clave],"2681128|366",tSIAF[Certificacion])) -> 4800 | F50: =IF(D50="","",D50-E50) -> 0 | G50: =IF(COUNTIF(tSIAF[Clave],"2681128|366")=0,"",SUMIF(tSIAF[Clave],"2681128|366",tSIAF[Devengado])) -> 4800 | H50: =IF(D50="","",D50-G50) -> 0 | I50: =IF(D50="","",IF(D50=0,0,G50/D50)) -> 1 | K50: Por completar | L50: =IF(COUNTIF(tCartera[CUI],"2681128")=0,"Sin PMI",IF(INDEX(tCartera[PMI2026],MATCH("2681128",tCartera[CUI],0))="","No informado",INDEX(tCartera[PMI2026],MATCH("2681128",tCartera[CUI],0)))) -> Sin PMI | M50: =IF(COUNTIF(tCartera[CUI],"2681128")=0,"Sin PMI",IF(INDEX(tCartera[PMI2027],MATCH("2681128",tCartera[CUI],0))="","No informado",INDEX(tCartera[PMI2027],MATCH("2681128",tCartera[CUI],0)))) -> Sin PMI | N50: =IF(COUNTIF(tCartera[CUI],"2681128")=0,"Sin PMI",IF(INDEX(tCartera[PMI2028],MATCH("2681128",tCartera[CUI],0))="","No informado",INDEX(tCartera[PMI2028],MATCH("2681128",tCartera[CUI],0)))) -> Sin PMI | O50: =IF(COUNTIF(tCartera[CUI],"2681128")=0,"Sin PMI",IF(INDEX(tCartera[PMI2029],MATCH("2681128",tCartera[CUI],0))="","No informado",INDEX(tCartera[PMI2029],MATCH("2681128",tCartera[CUI],0)))) -> Sin PMI
A51: =SUBTOTAL(103,$B$8:B51)+287 -> 328 | B51: 367 | C51: 2681129: CREACION DE UN TALLER TEXTIL PARA LA ELABORACION DE PRENDAS DE VESTIR Y ARTICULOS DE FIBRA DE ALPACA, DE LA ASOCIACION 24 DE JUNIO CHAJANA EN EL DISTRITO DE COJATA, PROVINCIA DE HUANCANE, DEPARTAMENTO DE PUNO | D51: =IF(COUNTIF(tSIAF[Clave],"2681129|367")=0,"",SUMIF(tSIAF[Clave],"2681129|367",tSIAF[PIM])) -> 12800 | E51: =IF(COUNTIF(tSIAF[Clave],"2681129|367")=0,"",SUMIF(tSIAF[Clave],"2681129|367",tSIAF[Certificacion])) -> 12800 | F51: =IF(D51="","",D51-E51) -> 0 | G51: =IF(COUNTIF(tSIAF[Clave],"2681129|367")=0,"",SUMIF(tSIAF[Clave],"2681129|367",tSIAF[Devengado])) -> 12800 | H51: =IF(D51="","",D51-G51) -> 0 | I51: =IF(D51="","",IF(D51=0,0,G51/D51)) -> 1 | K51: Por completar | L51: =IF(COUNTIF(tCartera[CUI],"2681129")=0,"Sin PMI",IF(INDEX(tCartera[PMI2026],MATCH("2681129",tCartera[CUI],0))="","No informado",INDEX(tCartera[PMI2026],MATCH("2681129",tCartera[CUI],0)))) -> Sin PMI | M51: =IF(COUNTIF(tCartera[CUI],"2681129")=0,"Sin PMI",IF(INDEX(tCartera[PMI2027],MATCH("2681129",tCartera[CUI],0))="","No informado",INDEX(tCartera[PMI2027],MATCH("2681129",tCartera[CUI],0)))) -> Sin PMI | N51: =IF(COUNTIF(tCartera[CUI],"2681129")=0,"Sin PMI",IF(INDEX(tCartera[PMI2028],MATCH("2681129",tCartera[CUI],0))="","No informado",INDEX(tCartera[PMI2028],MATCH("2681129",tCartera[CUI],0)))) -> Sin PMI | O51: =IF(COUNTIF(tCartera[CUI],"2681129")=0,"Sin PMI",IF(INDEX(tCartera[PMI2029],MATCH("2681129",tCartera[CUI],0))="","No informado",INDEX(tCartera[PMI2029],MATCH("2681129",tCartera[CUI],0)))) -> Sin PMI
A52: =SUBTOTAL(103,$B$8:B52)+287 -> 329 | B52: 369 | C52: 2676435: MEJORAMIENTO DEL PROCESO DE ENGORDE Y COMERCIALIZACION DE GANADO VACUNO EN LA ASOCIACION DE PRODUCTORES AGROPECUARIOS STMA. TRINIDAD DE CCACCAPUNCO EN EL DISTRITO DE VILQUE, PROVINCIA PUNO Y REGION PUNO | D52: =IF(COUNTIF(tSIAF[Clave],"2676435|369")=0,"",SUMIF(tSIAF[Clave],"2676435|369",tSIAF[PIM])) -> 57400 | E52: =IF(COUNTIF(tSIAF[Clave],"2676435|369")=0,"",SUMIF(tSIAF[Clave],"2676435|369",tSIAF[Certificacion])) -> 57400 | F52: =IF(D52="","",D52-E52) -> 0 | G52: =IF(COUNTIF(tSIAF[Clave],"2676435|369")=0,"",SUMIF(tSIAF[Clave],"2676435|369",tSIAF[Devengado])) -> 57400 | H52: =IF(D52="","",D52-G52) -> 0 | I52: =IF(D52="","",IF(D52=0,0,G52/D52)) -> 1 | K52: Por completar | L52: =IF(COUNTIF(tCartera[CUI],"2676435")=0,"Sin PMI",IF(INDEX(tCartera[PMI2026],MATCH("2676435",tCartera[CUI],0))="","No informado",INDEX(tCartera[PMI2026],MATCH("2676435",tCartera[CUI],0)))) -> Sin PMI | M52: =IF(COUNTIF(tCartera[CUI],"2676435")=0,"Sin PMI",IF(INDEX(tCartera[PMI2027],MATCH("2676435",tCartera[CUI],0))="","No informado",INDEX(tCartera[PMI2027],MATCH("2676435",tCartera[CUI],0)))) -> Sin PMI | N52: =IF(COUNTIF(tCartera[CUI],"2676435")=0,"Sin PMI",IF(INDEX(tCartera[PMI2028],MATCH("2676435",tCartera[CUI],0))="","No informado",INDEX(tCartera[PMI2028],MATCH("2676435",tCartera[CUI],0)))) -> Sin PMI | O52: =IF(COUNTIF(tCartera[CUI],"2676435")=0,"Sin PMI",IF(INDEX(tCartera[PMI2029],MATCH("2676435",tCartera[CUI],0))="","No informado",INDEX(tCartera[PMI2029],MATCH("2676435",tCartera[CUI],0)))) -> Sin PMI
A53: =SUBTOTAL(103,$B$8:B53)+287 -> 330 | B53: 370 | C53: 2676436: AMPLIACION DE LA PLANTA PROCESADORA DE LECHE PARA LA ELABORACION DE QUESOS DE LA ASOCIACION DE PRODUCTORES DE LECHE Y DERIVADOS LACTEOS VIRGEN DE ASUNCION ROSASPATA, DISTRITO DE ROSASPATA, PROVINCIA DE HUANCANE, REGION PUNO | D53: =IF(COUNTIF(tSIAF[Clave],"2676436|370")=0,"",SUMIF(tSIAF[Clave],"2676436|370",tSIAF[PIM])) -> 5898 | E53: =IF(COUNTIF(tSIAF[Clave],"2676436|370")=0,"",SUMIF(tSIAF[Clave],"2676436|370",tSIAF[Certificacion])) -> 5898 | F53: =IF(D53="","",D53-E53) -> 0 | G53: =IF(COUNTIF(tSIAF[Clave],"2676436|370")=0,"",SUMIF(tSIAF[Clave],"2676436|370",tSIAF[Devengado])) -> 5898 | H53: =IF(D53="","",D53-G53) -> 0 | I53: =IF(D53="","",IF(D53=0,0,G53/D53)) -> 1 | K53: Por completar | L53: =IF(COUNTIF(tCartera[CUI],"2676436")=0,"Sin PMI",IF(INDEX(tCartera[PMI2026],MATCH("2676436",tCartera[CUI],0))="","No informado",INDEX(tCartera[PMI2026],MATCH("2676436",tCartera[CUI],0)))) -> Sin PMI | M53: =IF(COUNTIF(tCartera[CUI],"2676436")=0,"Sin PMI",IF(INDEX(tCartera[PMI2027],MATCH("2676436",tCartera[CUI],0))="","No informado",INDEX(tCartera[PMI2027],MATCH("2676436",tCartera[CUI],0)))) -> Sin PMI | N53: =IF(COUNTIF(tCartera[CUI],"2676436")=0,"Sin PMI",IF(INDEX(tCartera[PMI2028],MATCH("2676436",tCartera[CUI],0))="","No informado",INDEX(tCartera[PMI2028],MATCH("2676436",tCartera[CUI],0)))) -> Sin PMI | O53: =IF(COUNTIF(tCartera[CUI],"2676436")=0,"Sin PMI",IF(INDEX(tCartera[PMI2029],MATCH("2676436",tCartera[CUI],0))="","No informado",INDEX(tCartera[PMI2029],MATCH("2676436",tCartera[CUI],0)))) -> Sin PMI
A54: =SUBTOTAL(103,$B$8:B54)+287 -> 331 | B54: 371 | C54: 2681276: MEJORAMIENTO EN LA CAPACIDAD TECNICA DE PRODUCCION DE PRENDAS DE TEXTIL DE TEJIDO A MANO DE ALTO RELIEVE DE FIBRA DE ALPACA DE LA ASOCIACION DE MUJERES ARTESANAS VIRGEN DE CANDELARIA PICHACANI QUIRINE DISTRITO MACARI, PROVINCIA MELGAR, REGION PUNO | D54: =IF(COUNTIF(tSIAF[Clave],"2681276|371")=0,"",SUMIF(tSIAF[Clave],"2681276|371",tSIAF[PIM])) -> 3000 | E54: =IF(COUNTIF(tSIAF[Clave],"2681276|371")=0,"",SUMIF(tSIAF[Clave],"2681276|371",tSIAF[Certificacion])) -> 3000 | F54: =IF(D54="","",D54-E54) -> 0 | G54: =IF(COUNTIF(tSIAF[Clave],"2681276|371")=0,"",SUMIF(tSIAF[Clave],"2681276|371",tSIAF[Devengado])) -> 3000 | H54: =IF(D54="","",D54-G54) -> 0 | I54: =IF(D54="","",IF(D54=0,0,G54/D54)) -> 1 | K54: Por completar | L54: =IF(COUNTIF(tCartera[CUI],"2681276")=0,"Sin PMI",IF(INDEX(tCartera[PMI2026],MATCH("2681276",tCartera[CUI],0))="","No informado",INDEX(tCartera[PMI2026],MATCH("2681276",tCartera[CUI],0)))) -> Sin PMI | M54: =IF(COUNTIF(tCartera[CUI],"2681276")=0,"Sin PMI",IF(INDEX(tCartera[PMI2027],MATCH("2681276",tCartera[CUI],0))="","No informado",INDEX(tCartera[PMI2027],MATCH("2681276",tCartera[CUI],0)))) -> Sin PMI | N54: =IF(COUNTIF(tCartera[CUI],"2681276")=0,"Sin PMI",IF(INDEX(tCartera[PMI2028],MATCH("2681276",tCartera[CUI],0))="","No informado",INDEX(tCartera[PMI2028],MATCH("2681276",tCartera[CUI],0)))) -> Sin PMI | O54: =IF(COUNTIF(tCartera[CUI],"2681276")=0,"Sin PMI",IF(INDEX(tCartera[PMI2029],MATCH("2681276",tCartera[CUI],0))="","No informado",INDEX(tCartera[PMI2029],MATCH("2681276",tCartera[CUI],0)))) -> Sin PMI
A55: =SUBTOTAL(103,$B$8:B55)+287 -> 332 | B55: 372 | C55: 2681132: MEJORAMIENTO DE LA CAPACIDAD PRODUCTIVA DE CAFE TOSTADO Y MOLIDO EN LA COOPERATIVA AGRARIA EN INNOVACION TECNOLOGICA MONTANA AZUL LIMITADA, DISTRITO DE SAN PEDRO DE PUTINA PUNCO, PROVINCIA DE SANDIA, REGION PUNO. | D55: =IF(COUNTIF(tSIAF[Clave],"2681132|372")=0,"",SUMIF(tSIAF[Clave],"2681132|372",tSIAF[PIM])) -> 87790 | E55: =IF(COUNTIF(tSIAF[Clave],"2681132|372")=0,"",SUMIF(tSIAF[Clave],"2681132|372",tSIAF[Certificacion])) -> 87438 | F55: =IF(D55="","",D55-E55) -> 352 | G55: =IF(COUNTIF(tSIAF[Clave],"2681132|372")=0,"",SUMIF(tSIAF[Clave],"2681132|372",tSIAF[Devengado])) -> 77990 | H55: =IF(D55="","",D55-G55) -> 9800 | I55: =IF(D55="","",IF(D55=0,0,G55/D55)) -> 0.88836997 | K55: Por completar | L55: =IF(COUNTIF(tCartera[CUI],"2681132")=0,"Sin PMI",IF(INDEX(tCartera[PMI2026],MATCH("2681132",tCartera[CUI],0))="","No informado",INDEX(tCartera[PMI2026],MATCH("2681132",tCartera[CUI],0)))) -> Sin PMI | M55: =IF(COUNTIF(tCartera[CUI],"2681132")=0,"Sin PMI",IF(INDEX(tCartera[PMI2027],MATCH("2681132",tCartera[CUI],0))="","No informado",INDEX(tCartera[PMI2027],MATCH("2681132",tCartera[CUI],0)))) -> Sin PMI | N55: =IF(COUNTIF(tCartera[CUI],"2681132")=0,"Sin PMI",IF(INDEX(tCartera[PMI2028],MATCH("2681132",tCartera[CUI],0))="","No informado",INDEX(tCartera[PMI2028],MATCH("2681132",tCartera[CUI],0)))) -> Sin PMI | O55: =IF(COUNTIF(tCartera[CUI],"2681132")=0,"Sin PMI",IF(INDEX(tCartera[PMI2029],MATCH("2681132",tCartera[CUI],0))="","No informado",INDEX(tCartera[PMI2029],MATCH("2681132",tCartera[CUI],0)))) -> Sin PMI
