Workbook

Sheet Proyectos
A4: Consulta Amigable
A5: Consulta de Ejecución del Gasto
A7: Fecha de la Consulta: 06-octubre-2026
A9: Año de Ejecución: 2026
A10: Incluye: Sólo Proyectos
A12: Resultados 1 - 400 de 447, Página 1 de 2
A13: Pliego 458: GOBIERNO REGIONAL DEL DEPARTAMENTO DE PUNO | B13: 797237434 | C13: 987989928 | D13: 919370470 | E13: 687283682 | F13: 562422558 | G13: 495107472 | H13: 462867242 | I13: 50.1
A14: Proyecto | B14: PIA | C14: PIM | D14: Certificación | E14: Compromiso Anual | F14: Ejecución | I14: Avance % | J14: Saldo No Certificado | K14: Saldo No Comprometido | L14: Saldo Certificado No Comprometido | M14: Saldo No Devengado | N14: % Saldo No Comprometido | O14: % Devengado | P14: Registra en la PMI
F15: Atención de Compromiso Mensual | G15: Devengado | H15: Girado
A16: 2001621: ESTUDIOS DE PRE-INVERSION | B16: 34651774 | C16: 7962753 | D16: 6442206 | E16: 6317905 | F16: 6097967 | G16: 5860251 | H16: 5788002 | I16: 73.6 | J16: =C16-D16 -> 1520547 | K16: =C16-E16 -> 1644848 | L16: =D16-E16 -> 124301 | M16: =C16-G16 -> 2102502 | N16: =IFERROR(K16/C16, " ") -> 0.20656775 | O16: =IFERROR(G16/C16, "ERROR") -> 0.7359579
A17: 2016766: INICIATIVA A LA COMPETITIVIDAD | B17: 11000000 | C17: 1098209 | D17: 995606 | E17: 993027 | F17: 784755 | G17: 677102 | H17: 675102 | I17: 61.7 | J17: =C17-D17 -> 102603 | K17: =C17-E17 -> 105182 | L17: =D17-E17 -> 2579 | M17: =C17-G17 -> 421107 | N17: =IFERROR(K17/C17, " ") -> 0.095775941 | O17: =IFERROR(G17/C17, "ERROR") -> 0.61655113
A18: 2031310: CONSTRUCCION Y MEJORAMIENTO DE LA CARRETERA SAN JOSE (EMP. R 100) VALLE GRANDE -ISILLUMA DEL DISTRITO DE ALTO INAMBARI | B18: 1404195 | C18: 1122559 | D18: 1117871 | E18: 1117871 | F18: 1117453 | G18: 1042099 | H18: 1031699 | I18: 92.8 | J18: =C18-D18 -> 4688 | K18: =C18-E18 -> 4688 | L18: =D18-E18 -> 0 | M18: =C18-G18 -> 80460 | N18: =IFERROR(K18/C18, " ") -> 0.0041761725 | O18: =IFERROR(G18/C18, "ERROR") -> 0.92832448
A19: 2055915: MEJORAMIENTO DE LA CARRETERA AZANGARO - SAYTOCOCHA - SANDIA - SAN JUAN DEL ORO | B19: 7600000 | C19: 0 | D19: 0 | E19: 0 | F19: 0 | G19: 0 | H19: 0 | I19: 0.0 | J19: =C19-D19 -> 0 | K19: =C19-E19 -> 0 | L19: =D19-E19 -> 0 | M19: =C19-G19 -> 0 | N19: =IFERROR(K19/C19, " ") | O19: =IFERROR(G19/C19, "ERROR") -> ERROR
A20: 2108576: CONSTRUCCION DEL HOSPITAL MATERNO INFANTIL DEL CONO SUR JULIACA | B20: 12460540 | C20: 167354 | D20: 149951 | E20: 149951 | F20: 102781 | G20: 102781 | H20: 102781 | I20: 61.4 | J20: =C20-D20 -> 17403 | K20: =C20-E20 -> 17403 | L20: =D20-E20 -> 0 | M20: =C20-G20 -> 64573 | N20: =IFERROR(K20/C20, " ") -> 0.10398915 | O20: =IFERROR(G20/C20, "ERROR") -> 0.61415323
A21: 2131389: MEJORAMIENTO DE LA INFRAESTRUCTURA VIAL DEL CIRCUITO TURISTICO LAGO SAGRADO DE LOS INCAS - DISTRITOS CAPACHICA, CHUCUITO, PLATERIA, ACORA, ILAVE | B21: 3778561 | C21: 0 | D21: 0 | E21: 0 | F21: 0 | G21: 0 | H21: 0 | I21: 0.0 | J21: =C21-D21 -> 0 | K21: =C21-E21 -> 0 | L21: =D21-E21 -> 0 | M21: =C21-G21 -> 0 | N21: =IFERROR(K21/C21, " ") | O21: =IFERROR(G21/C21, "ERROR") -> ERROR
A22: 2131661: CONSTRUCCION Y MEJORAMIENTO DE LA CARRETERA DESVIO VILQUECHICO-COJATA-SINA-YANAHUAYA | B22: 4800690 | C22: 1868752 | D22: 1642733 | E22: 353547 | F22: 308433 | G22: 308433 | H22: 308433 | I22: 16.5 | J22: =C22-D22 -> 226019 | K22: =C22-E22 -> 1515205 | L22: =D22-E22 -> 1289186 | M22: =C22-G22 -> 1560319 | N22: =IFERROR(K22/C22, " ") -> 0.81081117 | O22: =IFERROR(G22/C22, "ERROR") -> 0.16504758
A23: 2154443: MEJORAMIENTO DEL ESTADO NUTRICIONAL DEL NIÑO MENOR DE TRES AÑOS Y LA MADRE GESTANTE EN LAS PROVINCIAS DE AZANGARO, LAMPA Y SAN ROMAN DE LA REGION PUNO | B23: 4098 | C23: 0 | D23: 0 | E23: 0 | F23: 0 | G23: 0 | H23: 0 | I23: 0.0 | J23: =C23-D23 -> 0 | K23: =C23-E23 -> 0 | L23: =D23-E23 -> 0 | M23: =C23-G23 -> 0 | N23: =IFERROR(K23/C23, " ") | O23: =IFERROR(G23/C23, "ERROR") -> ERROR
A24: 2159149: MEJORAMIENTO DE LAS CAPACIDADES PARA PREVENIR LA DESNUTRICION CRONICA, EN MENORES DE 3 AÑOS EN LAS PROVINCIAS DE CARABAYA, MELGAR Y SANDIA DE LA REGION PUNO | B24: 87917 | C24: 0 | D24: 0 | E24: 0 | F24: 0 | G24: 0 | H24: 0 | I24: 0.0 | J24: =C24-D24 -> 0 | K24: =C24-E24 -> 0 | L24: =D24-E24 -> 0 | M24: =C24-G24 -> 0 | N24: =IFERROR(K24/C24, " ") | O24: =IFERROR(G24/C24, "ERROR") -> ERROR
A25: 2159836: MEJORAMIENTO Y CREACION DEL CAMINO VECINAL SACO-HUANACURI, DISTRITO DE COASA - CARABAYA - PUNO | B25: 100000 | C25: 350198 | D25: 287570 | E25: 287570 | F25: 273287 | G25: 252137 | H25: 252137 | I25: 72.0 | J25: =C25-D25 -> 62628 | K25: =C25-E25 -> 62628 | L25: =D25-E25 -> 0 | M25: =C25-G25 -> 98061 | N25: =IFERROR(K25/C25, " ") -> 0.17883597 | O25: =IFERROR(G25/C25, "ERROR") -> 0.71998412
A26: 2163760: MEJORAMIENTO DE LA INFRAESTRUCTURA VIAL TURISTICO, TRAMO PHUTINI - JAYU JAYU, DISTRITO DE ACORA - PUNO - PUNO | B26: 2596051 | C26: 1202934 | D26: 1151624 | E26: 1151624 | F26: 1137287 | G26: 1105100 | H26: 1105100 | I26: 91.9 | J26: =C26-D26 -> 51310 | K26: =C26-E26 -> 51310 | L26: =D26-E26 -> 0 | M26: =C26-G26 -> 97834 | N26: =IFERROR(K26/C26, " ") -> 0.042654044 | O26: =IFERROR(G26/C26, "ERROR") -> 0.91867052
A27: 2163853: MEJORAMIENTO DEL ESTADIO MUNICIPAL CESAR RAUL CARRERA DEL DISTRITO DE AZANGARO, PROVINCIA DE AZANGARO - PUNO | B27: 6269000 | C27: 5810277 | D27: 5204424 | E27: 3160250 | F27: 2836806 | G27: 1157373 | H27: 1109853 | I27: 19.9 | J27: =C27-D27 -> 605853 | K27: =C27-E27 -> 2650027 | L27: =D27-E27 -> 2044174 | M27: =C27-G27 -> 4652904 | N27: =IFERROR(K27/C27, " ") -> 0.45609306 | O27: =IFERROR(G27/C27, "ERROR") -> 0.19919412
... A29: 2185111: MEJORAMIENTO DE LA CARRETERA (PU 112) PUTINA - MUÑANI, DISTRITOS DE PUTINA Y MUÑANI, PROVINCIAS DE SAN ANTONIO DE PUTINA Y AZANGARO - PUNO | B29: 100000 | C29: 0 | D29: 0 | E29: 0 | F29: 0 | G29: 0 | H29: 0 | I29: 0.0 | J29: =C29-D29 -> 0 | K29: =C29-E29 -> 0 | L29: =D29-E29 -> 0 | M29: =C29-G29 -> 0 | N29: =IFERROR(K29/C29, " ") | O29: =IFERROR(G29/C29, "ERROR") -> ERROR
A30: 2185578: MEJORAMIENTO DE LA CARRETERA DV. DESAGUADERO (EMP PE 36A) - KELLUYO - PISACOMA, PROVINCIA DE CHUCUITO - PUNO | B30: 1732548 | C30: 67139 | D30: 0 | E30: 0 | F30: 0 | G30: 0 | H30: 0 | I30: 0.0 | J30: =C30-D30 -> 67139 | K30: =C30-E30 -> 67139 | L30: =D30-E30 -> 0 | M30: =C30-G30 -> 67139 | N30: =IFERROR(K30/C30, " ") -> 1 | O30: =IFERROR(G30/C30, "ERROR") -> 0 | P30: SI-PMI
A31: 2186641: MEJORAMIENTO DEL SERVICIO DEPORTIVO, CULTURAL Y RECREACIONAL EN LA CAPITAL DE LA REGION PUNO | B31: 11675669 | C31: 1506514 | D31: 1436013 | E31: 1436013 | F31: 1240537 | G31: 1240537 | H31: 1240537 | I31: 82.3 | J31: =C31-D31 -> 70501 | K31: =C31-E31 -> 70501 | L31: =D31-E31 -> 0 | M31: =C31-G31 -> 265977 | N31: =IFERROR(K31/C31, " ") -> 0.046797441 | O31: =IFERROR(G31/C31, "ERROR") -> 0.8234487
A32: 2187217: MEJORAMIENTO DE LA CADENA DE VALOR DE LA FIBRA DE ALPACA EN LA REGION PUNO | B32: 630478 | C32: 1332387 | D32: 1332217 | E32: 1328895 | F32: 1275973 | G32: 1212326 | H32: 1197867 | I32: 91.0 | J32: =C32-D32 -> 170 | K32: =C32-E32 -> 3492 | L32: =D32-E32 -> 3322 | M32: =C32-G32 -> 120061 | N32: =IFERROR(K32/C32, " ") -> 0.0026208602 | O32: =IFERROR(G32/C32, "ERROR") -> 0.90989029
A33: 2188379: MEJORAMIENTO DEL SERVICIO EDUCATIVO DE LA INSTITUCION EDUCATIVA PRIMARIA N 70605 DOMINGO SAVIO DE JULIACA, DISTRITO DE JULIACA, PROVINCIA DE SAN ROMAN - PUNO | B33: 1792000 | C33: 0 | D33: 0 | E33: 0 | F33: 0 | G33: 0 | H33: 0 | I33: 0.0 | J33: =C33-D33 -> 0 | K33: =C33-E33 -> 0 | L33: =D33-E33 -> 0 | M33: =C33-G33 -> 0 | N33: =IFERROR(K33/C33, " ") | O33: =IFERROR(G33/C33, "ERROR") -> ERROR
A34: 2188542: MEJORAMIENTO DE LA CAPACIDAD DE PRESTACION DE SERVICIOS DEPORTIVOS EN EL ESTADIO GUILLERMO BRICEÑO ROSAMEDINA DE LA CIUDAD DE JULIACA, PROVINCIA DE SAN ROMAN - PUNO | B34: 1139986 | C34: 5921783 | D34: 5612636 | E34: 2263180 | F34: 2211564 | G34: 1271807 | H34: 1239120 | I34: 21.5 | J34: =C34-D34 -> 309147 | K34: =C34-E34 -> 3658603 | L34: =D34-E34 -> 3349456 | M34: =C34-G34 -> 4649976 | N34: =IFERROR(K34/C34, " ") -> 0.61782119 | O34: =IFERROR(G34/C34, "ERROR") -> 0.21476758
A35: 2194462: INSTALACION DEL SERVICIO DE EDUCACION SECUNDARIA THOMAS ALVA EDISON EN LA URBANIZACION CHILLA - LOS ROSALES EN EL DISTRITO DE JULIACA, PROVINCIA DE SAN ROMAN. | B35: 357505 | C35: 77590 | D35: 76159 | E35: 76159 | F35: 76159 | G35: 76159 | H35: 76159 | I35: 98.2 | J35: =C35-D35 -> 1431 | K35: =C35-E35 -> 1431 | L35: =D35-E35 -> 0 | M35: =C35-G35 -> 1431 | N35: =IFERROR(K35/C35, " ") -> 0.018443098 | O35: =IFERROR(G35/C35, "ERROR") -> 0.9815569
A36: 2194501: INSTALACION DEL SERVICIO EDUCATIVO DE LA INSTITUCION EDUCATIVA SECUNDARIA SANTA MONICA EN EL DISTRITO DE JULIACA, PROVINCIA DE SAN ROMAN - PUNO. | B36: 144908 | C36: 0 | D36: 0 | E36: 0 | F36: 0 | G36: 0 | H36: 0 | I36: 0.0 | J36: =C36-D36 -> 0 | K36: =C36-E36 -> 0 | L36: =D36-E36 -> 0 | M36: =C36-G36 -> 0 | N36: =IFERROR(K36/C36, " ") | O36: =IFERROR(G36/C36, "ERROR") -> ERROR
A37: 2194504: INSTALACION DEL SERVICIO EDUCATIVO DEL NIVEL SECUNDARIO EN LA I.E.S. RODOLFO DIESEL, DISTRITO DE JULIACA, PROVINCIA SAN ROMAN - PUNO. | B37: 17477 | C37: 0 | D37: 0 | E37: 0 | F37: 0 | G37: 0 | H37: 0 | I37: 0.0 | J37: =C37-D37 -> 0 | K37: =C37-E37 -> 0 | L37: =D37-E37 -> 0 | M37: =C37-G37 -> 0 | N37: =IFERROR(K37/C37, " ") | O37: =IFERROR(G37/C37, "ERROR") -> ERROR
A38: 2194702: MEJORAMIENTO DE LA CARRETERA (PU 675) POMATA - YOROHOCO, PROVINCIA DE CHUCUITO - PUNO | B38: 9922902 | C38: 18401182 | D38: 17764558 | E38: 17200007 | F38: 16692676 | G38: 15484260 | H38: 15232468 | I38: 84.1 | J38: =C38-D38 -> 636624 | K38: =C38-E38 -> 1201175 | L38: =D38-E38 -> 564551 | M38: =C38-G38 -> 2916922 | N38: =IFERROR(K38/C38, " ") -> 0.065277057 | O38: =IFERROR(G38/C38, "ERROR") -> 0.84148181
A39: 2194989: MEJORAMIENTO DE LOS SERVICIOS EDUCATIVOS EN LA INSTITUCION EDUCATIVA SECUNDARIA DANTE NAVA DEL CENTRO POBLADO SANTA CRUZ DE PUNA AYLLU, DISTRITO DE PATAMBUCO, PROVINCIA DE SANDIA, REGION PUNO | B39: 0 | C39: 133512 | D39: 0 | E39: 0 | F39: 0 | G39: 0 | H39: 0 | I39: 0.0 | J39: =C39-D39 -> 133512 | K39: =C39-E39 -> 133512 | L39: =D39-E39 -> 0 | M39: =C39-G39 -> 133512 | N39: =IFERROR(K39/C39, " ") -> 1 | O39: =IFERROR(G39/C39, "ERROR") -> 0 | P39: NO-PMI
A40: 2195487: MEJORAMIENTO DEL CAMINO VECINAL (EMP. PE 3S) HUAQUINA ZAPIJICANE - PTO JULI - CHUCASUYO DEL DISTRITO DE JULI - PROVINCIA DE CHUCUITO - DEPARTAMENTO DE PUNO | B40: 774665 | C40: 91759 | D40: 91759 | E40: 82309 | F40: 82095 | G40: 82095 | H40: 82095 | I40: 89.5 | J40: =C40-D40 -> 0 | K40: =C40-E40 -> 9450 | L40: =D40-E40 -> 9450 | M40: =C40-G40 -> 9664 | N40: =IFERROR(K40/C40, " ") -> 0.10298717 | O40: =IFERROR(G40/C40, "ERROR") -> 0.89468063
A41: 2196822: INSTALACION DEL SERVICIO DE EDUCACION INICIAL DE LA I.E.I. NRO. 94 DEL CENTRO POBLADO DE UMUCHI, DISTRITO DE MOHO, PROVINCIA DE MOHO, DEPARTAMENTO DE PUNO. | B41: 0 | C41: 17714 | D41: 14229 | E41: 14229 | F41: 13548 | G41: 9750 | H41: 9750 | I41: 55.0 | J41: =C41-D41 -> 3485 | K41: =C41-E41 -> 3485 | L41: =D41-E41 -> 0 | M41: =C41-G41 -> 7964 | N41: =IFERROR(K41/C41, " ") -> 0.19673704 | O41: =IFERROR(G41/C41, "ERROR") -> 0.5504121
A42: 2196834: MEJORAMIENTO DE LOS SERVICIOS DE EDUCACION INICIAL EN LA I.E.I. CUCURAYA DE LA COMUNIDAD DE CUCURAYA, DISTRITO DE TILALI, PROVINCIA DE MOHO - PUNO. | B42: 699403 | C42: 728529 | D42: 0 | E42: 0 | F42: 0 | G42: 0 | H42: 0 | I42: 0.0 | J42: =C42-D42 -> 728529 | K42: =C42-E42 -> 728529 | L42: =D42-E42 -> 0 | M42: =C42-G42 -> 728529 | N42: =IFERROR(K42/C42, " ") -> 1 | O42: =IFERROR(G42/C42, "ERROR") -> 0 | P42: SI-PMI
A43: 2196857: INSTALACION DEL SERVICIO EDUCATIVO EN LA INSTITUCION EDUCATIVA INICIAL N 986 SAN JUAN BAUTISTA DEL DISTRITO DE JULIACA, PROVINCIA DE SAN ROMAN - PUNO | B43: 2878733 | C43: 0 | D43: 0 | E43: 0 | F43: 0 | G43: 0 | H43: 0 | I43: 0.0 | J43: =C43-D43 -> 0 | K43: =C43-E43 -> 0 | L43: =D43-E43 -> 0 | M43: =C43-G43 -> 0 | N43: =IFERROR(K43/C43, " ") | O43: =IFERROR(G43/C43, "ERROR") -> ERROR
A44: 2196865: MEJORAMIENTO DEL SERVICIO EDUCATIVO DE NIVEL INICIAL ESCOLARIZADO EN LA I.E.I. LLUNGO, DISTRITO DE ATUNCOLLA, PROVINCIA DE PUNO - PUNO. | B44: 159740 | C44: 118539 | D44: 70562 | E44: 70562 | F44: 70562 | G44: 70562 | H44: 70562 | I44: 59.5 | J44: =C44-D44 -> 47977 | K44: =C44-E44 -> 47977 | L44: =D44-E44 -> 0 | M44: =C44-G44 -> 47977 | N44: =IFERROR(K44/C44, " ") -> 0.40473599 | O44: =IFERROR(G44/C44, "ERROR") -> 0.59526401
A45: 2227389: AMPLIACION Y MEJORAMIENTO DE LA CAPACIDAD RESOLUTIVA DEL HOSPITAL DE APOYO SAN MARTIN DE PORRES DE MACUSANI, PROVINCIA DE CARABAYA - PUNO | B45: 100000 | C45: 4068561 | D45: 4043454 | E45: 4043454 | F45: 4043454 | G45: 4043454 | H45: 0 | I45: 99.4 | J45: =C45-D45 -> 25107 | K45: =C45-E45 -> 25107 | L45: =D45-E45 -> 0 | M45: =C45-G45 -> 25107 | N45: =IFERROR(K45/C45, " ") -> 0.0061709779 | O45: =IFERROR(G45/C45, "ERROR") -> 0.99382902
A46: 2230619: MEJORAMIENTO DE LA PRODUCCION Y PRODUCTIVIDAD DE LAS MYPE DE LAS PRINCIPALES LINEAS DE PRODUCCION EN LAS PROVINCIAS DE PUNO, SAN ROMAN Y EL COLLAO DE LA REGION PUNO | B46: 287404 | C46: 119950 | D46: 114291 | E46: 114291 | F46: 114291 | G46: 70291 | H46: 70291 | I46: 58.6 | J46: =C46-D46 -> 5659 | K46: =C46-E46 -> 5659 | L46: =D46-E46 -> 0 | M46: =C46-G46 -> 49659 | N46: =IFERROR(K46/C46, " ") -> 0.047177991 | O46: =IFERROR(G46/C46, "ERROR") -> 0.5860025
A47: 2230752: MEJORAMIENTO DE LOS SERVICIOS ASISTENCIALES DE LA ALDEA INFANTIL VIRGEN DE LA CANDELARIA EN EL BARRIO LA RINCONADA DEL CENTRO POBLADO DE SALCEDO, DISTRITO DE PUNO, PROVINCIA DE PUNO, REGION DE PUNO | B47: 0 | C47: 99230 | D47: 99008 | E47: 96668 | F47: 96199 | G47: 96199 | H47: 96199 | I47: 96.9 | J47: =C47-D47 -> 222 | K47: =C47-E47 -> 2562 | L47: =D47-E47 -> 2340 | M47: =C47-G47 -> 3031 | N47: =IFERROR(K47/C47, " ") -> 0.025818805 | O47: =IFERROR(G47/C47, "ERROR") -> 0.9694548
A48: 2231037: MEJORAMIENTO DE LOS SERVICIOS EDUCATIVOS EN LA I.E.I. N 596 MUNAYPATA DEL CENTRO POBLADO DE MUNAYPATA, DISTRITO DE OLLACHEA PROVINCIA DE CARABAYA PUNO | B48: 0 | C48: 20166 | D48: 19362 | E48: 19362 | F48: 18148 | G48: 18148 | H48: 18148 | I48: 90.0 | J48: =C48-D48 -> 804 | K48: =C48-E48 -> 804 | L48: =D48-E48 -> 0 | M48: =C48-G48 -> 2018 | N48: =IFERROR(K48/C48, " ") -> 0.039869087 | O48: =IFERROR(G48/C48, "ERROR") -> 0.89993058
A49: 2232371: MEJORAMIENTO Y CONSTRUCCION DE LA CARRETERA PICHACANI - YURACMAYO DISTRITO DE PICHACANI Y SAN ANTONIO, PROVINCIA DE PUNO - PUNO | B49: 1023926 | C49: 0 | D49: 0 | E49: 0 | F49: 0 | G49: 0 | H49: 0 | I49: 0.0 | J49: =C49-D49 -> 0 | K49: =C49-E49 -> 0 | L49: =D49-E49 -> 0 | M49: =C49-G49 -> 0 | N49: =IFERROR(K49/C49, " ") | O49: =IFERROR(G49/C49, "ERROR") -> ERROR
A50: 2250307: INSTALACION DEL SERVICIO EDUCATIVO ESCOLARIZADO DEL NIVEL INICIAL DE 3 A 5 AÑOS EN LA I.E.I. PICHACANI QUIRINI, DISTRITO DE MACARI, PROVINCIA MELGAR PUNO | B50: 100000 | C50: 0 | D50: 0 | E50: 0 | F50: 0 | G50: 0 | H50: 0 | I50: 0.0 | J50: =C50-D50 -> 0 | K50: =C50-E50 -> 0 | L50: =D50-E50 -> 0 | M50: =C50-G50 -> 0 | N50: =IFERROR(K50/C50, " ") | O50: =IFERROR(G50/C50, "ERROR") -> ERROR
A51: 2250382: INSTALACION DE LOS SERVICIOS DE EDUCACION INICIAL EN LA I.E.I. CHIA, DEL C.P. DE CHIA, DEL DISTRITO DE OLLACHEA - PROVINCIA CARABAYA - REGION PUNO | B51: 800000 | C51: 2342684 | D51: 2159343 | E51: 1958588 | F51: 1715249 | G51: 1123789 | H51: 997142 | I51: 48.0 | J51: =C51-D51 -> 183341 | K51: =C51-E51 -> 384096 | L51: =D51-E51 -> 200755 | M51: =C51-G51 -> 1218895 | N51: =IFERROR(K51/C51, " ") -> 0.16395553 | O51: =IFERROR(G51/C51, "ERROR") -> 0.47970149
A52: 2250396: INSTALACION DEL SERVICIO EDUCATIVO DEL NIVEL INICIAL ESCOLARIZADO CICLO II EN LA I.E.I N 707 DEL CENTRO POBLADO DE JACHOCCO HUARACO, DISTRITO ILAVE, PROVINCIA DE EL COLLAO - DEPARTAMENTO PUNO. | B52: 120201 | C52: 41720 | D52: 31883 | E52: 31883 | F52: 31883 | G52: 31883 | H52: 31883 | I52: 76.4 | J52: =C52-D52 -> 9837 | K52: =C52-E52 -> 9837 | L52: =D52-E52 -> 0 | M52: =C52-G52 -> 9837 | N52: =IFERROR(K52/C52, " ") -> 0.23578619 | O52: =IFERROR(G52/C52, "ERROR") -> 0.76421381
A53: 2250460: INSTALACION DEL SERVICIO EDUCATIVO DE LA INSTITUCION EDUCATIVA INICIAL CICLO II NUEVA ESPERANZA, DISTRITO DE MACARI, PROVINCIA DE MELGAR - PUNO | B53: 60000 | C53: 0 | D53: 0 | E53: 0 | F53: 0 | G53: 0 | H53: 0 | I53: 0.0 | J53: =C53-D53 -> 0 | K53: =C53-E53 -> 0 | L53: =D53-E53 -> 0 | M53: =C53-G53 -> 0 | N53: =IFERROR(K53/C53, " ") | O53: =IFERROR(G53/C53, "ERROR") -> ERROR
A54: 2250970: MEJORAMIENTO DEL SERVICIO DE CONSERVACION DE LA DIVERSIDAD BIOLOGICA EN SELVA VERDE, SAN GABAN, PUNTA PERDIDA, COTACUCHO, PUNO, JUCUMARINI, CUSHINI, RIO CONDOR, RIO TAVARA, Y PACO PACUNI, DISTRITOS DE AYAPATA, SAN GABAN, SANTA ROSA, VILQUE CHICO-PUNO | B54: 2080646 | C54: 30000 | D54: 23434 | E54: 23434 | F54: 13106 | G54: 13106 | H54: 13106 | I54: 43.7 | J54: =C54-D54 -> 6566 | K54: =C54-E54 -> 6566 | L54: =D54-E54 -> 0 | M54: =C54-G54 -> 16894 | N54: =IFERROR(K54/C54, " ") -> 0.21886667 | O54: =IFERROR(G54/C54, "ERROR") -> 0.43686667
... A66: 2308220: MEJORAMIENTO DE LA CAPACIDAD RESOLUTIVA DEL PUESTO DE SALUD DE AYMAÑA DEL CENTRO POBLADO DE AYMAÑA DEL DISTRITO DE CORANI - PROVINCIA DE CARABAYA - DEPARTAMENTO DE PUNO | B66: 1199085 | C66: 407088 | D66: 327566 | E66: 323566 | F66: 316522 | G66: 287714 | H66: 287714 | I66: 70.7 | J66: =C66-D66 -> 79522 | K66: =C66-E66 -> 83522 | L66: =D66-E66 -> 4000 | M66: =C66-G66 -> 119374 | N66: =IFERROR(K66/C66, " ") -> 0.2051694 | O66: =IFERROR(G66/C66, "ERROR") -> 0.70676119
A67: 2313145: MEJORAMIENTO DEL MANEJO SOSTENIBLE DE VICUÑAS EN ZONAS ALTOANDINAS DE LA REGION PUNO | B67: 0 | C67: 40000 | D67: 0 | E67: 0 | F67: 0 | G67: 0 | H67: 0 | I67: 0.0 | J67: =C67-D67 -> 40000 | K67: =C67-E67 -> 40000 | L67: =D67-E67 -> 0 | M67: =C67-G67 -> 40000 | N67: =IFERROR(K67/C67, " ") -> 1 | O67: =IFERROR(G67/C67, "ERROR") -> 0 | P67: NO-PMI
A68: 2316291: MEJORAMIENTO Y AMPLIACION DEL CIRCUITO VIAL ECO TURISTICO, CAPACHICA - SIALE - CCOTOS - PARAMIS, DISTRITOS DE CAPACHICA, AMANTANI, PROVINCIA DE PUNO - PUNO | B68: 7946662 | C68: 0 | D68: 0 | E68: 0 | F68: 0 | G68: 0 | H68: 0 | I68: 0.0 | J68: =C68-D68 -> 0 | K68: =C68-E68 -> 0 | L68: =D68-E68 -> 0 | M68: =C68-G68 -> 0 | N68: =IFERROR(K68/C68, " ") | O68: =IFERROR(G68/C68, "ERROR") -> ERROR
A69: 2318520: MEJORAMIENTO DE LA CAPACIDAD AGROPRODUCTIVA DE GRANOS ANDINOS ORGANICOS DE QUINUA, CAÑIHUA, HABA Y TARWI EN LA REGION PUNO | B69: 0 | C69: 30892 | D69: 30000 | E69: 30000 | F69: 30000 | G69: 0 | H69: 0 | I69: 0.0 | J69: =C69-D69 -> 892 | K69: =C69-E69 -> 892 | L69: =D69-E69 -> 0 | M69: =C69-G69 -> 30892 | N69: =IFERROR(K69/C69, " ") -> 0.02887479 | O69: =IFERROR(G69/C69, "ERROR") -> 0 | P69: SI-PMI
A70: 2321290: MEJORAMIENTO DE LOS SERVICIOS DE TRANSITABILIDAD DE LA VIA VECINAL PU-595: DV. PAMPA BLANCA - RINCONADA - CERRO LUNAR, DISTRITO DE ANANEA, PROVINCIA DE SAN ANTONIO DE PUTINA - PUNO | B70: 1050000 | C70: 844818 | D70: 75387 | E70: 75387 | F70: 75387 | G70: 75387 | H70: 75387 | I70: 8.9 | J70: =C70-D70 -> 769431 | K70: =C70-E70 -> 769431 | L70: =D70-E70 -> 0 | M70: =C70-G70 -> 769431 | N70: =IFERROR(K70/C70, " ") -> 0.9107654 | O70: =IFERROR(G70/C70, "ERROR") -> 0.089234604
A71: 2323700: MEJORAMIENTO DEL SERVICIO EDUCATIVO DE LAS CARRERAS DE PRODUCCION, AUTOMOTRIZ, MINERIA, CONTABILIDAD, COMPUTACION, SECRETARIADO, ENFERMERIA, LABORATORIO CLINICO Y PROTESIS DENTAL DEL IST MANUEL NUÑEZ BUTRON, JULIACA, SAN ROMAN - PUNO | B71: 2546207 | C71: 10519577 | D71: 10386241 | E71: 8483089 | F71: 8382186 | G71: 7596373 | H71: 6861807 | I71: 72.2 | J71: =C71-D71 -> 133336 | K71: =C71-E71 -> 2036488 | L71: =D71-E71 -> 1903152 | M71: =C71-G71 -> 2923204 | N71: =IFERROR(K71/C71, " ") -> 0.19359029 | O71: =IFERROR(G71/C71, "ERROR") -> 0.72211772
A72: 2324613: MEJORAMIENTO DE LAS CAPACIDADES TECNOLOGICAS EN EL MANEJO DE CADENA PRODUCTIVA DE TRUCHA EN LA REGION PUNO | B72: 100560 | C72: 550560 | D72: 519500 | E72: 519159 | F72: 517920 | G72: 517920 | H72: 104420 | I72: 94.1 | J72: =C72-D72 -> 31060 | K72: =C72-E72 -> 31401 | L72: =D72-E72 -> 341 | M72: =C72-G72 -> 32640 | N72: =IFERROR(K72/C72, " ") -> 0.057034656 | O72: =IFERROR(G72/C72, "ERROR") -> 0.94071491
A73: 2325694: MEJORAMIENTO DE LA TECNIFICACION DE PROCESOS PARA LA CADENA PRODUCTIVA DE LA LECHE EN LA REGION PUNO | B73: 2215165 | C73: 30000 | D73: 0 | E73: 0 | F73: 0 | G73: 0 | H73: 0 | I73: 0.0 | J73: =C73-D73 -> 30000 | K73: =C73-E73 -> 30000 | L73: =D73-E73 -> 0 | M73: =C73-G73 -> 30000 | N73: =IFERROR(K73/C73, " ") -> 1 | O73: =IFERROR(G73/C73, "ERROR") -> 0 | P73: SI-PMI
A74: 2326588: MEJORAMIENTO DE LOS SERVICIOS DE APOYO A LA CADENA PRODUCTIVA DE CAFES ESPECIALES EN LOS DISTRITOS DE COASA, ITUATA, OLLACHEA, USICAYOS, LIMBANI, PATAMBUCO Y PHARA DE LAS PROVINCIAS DE CARABAYA Y SANDIA - REGION PUNO | B74: 0 | C74: 44000 | D74: 43500 | E74: 43500 | F74: 43500 | G74: 17400 | H74: 17400 | I74: 39.5 | J74: =C74-D74 -> 500 | K74: =C74-E74 -> 500 | L74: =D74-E74 -> 0 | M74: =C74-G74 -> 26600 | N74: =IFERROR(K74/C74, " ") -> 0.011363636 | O74: =IFERROR(G74/C74, "ERROR") -> 0.39545455
A75: 2335880: MEJORAMIENTO DEL SERVICIO EDUCATIVO DE LAS CARRERAS DE CONTABILIDAD, ENFERMERIA TECNICA, COMPUTACION E INFORMATICA, INDUSTRIA ALIMENTARIA Y PRODUCCION AGROPECUARIA DEL ISEPA, PROVINCIA DE MELGAR - PUNO | B75: 5597990 | C75: 10208307 | D75: 9968470 | E75: 9948238 | F75: 8344366 | G75: 6440724 | H75: 4826056 | I75: 63.1 | J75: =C75-D75 -> 239837 | K75: =C75-E75 -> 260069 | L75: =D75-E75 -> 20232 | M75: =C75-G75 -> 3767583 | N75: =IFERROR(K75/C75, " ") -> 0.025476213 | O75: =IFERROR(G75/C75, "ERROR") -> 0.63092969
A76: 2336682: RECUPERACION DE LA BIOMASA DEL CARACHI GRIS Y AMARILLO EN ZONAS DE DESOVE DE LA CUENCA DEL LAGO TITICACA DE LA REGION PUNO | B76: 1050000 | C76: 2417454 | D76: 1739635 | E76: 1715135 | F76: 1568544 | G76: 1492104 | H76: 1441585 | I76: 61.7 | J76: =C76-D76 -> 677819 | K76: =C76-E76 -> 702319 | L76: =D76-E76 -> 24500 | M76: =C76-G76 -> 925350 | N76: =IFERROR(K76/C76, " ") -> 0.29052011 | O76: =IFERROR(G76/C76, "ERROR") -> 0.61722126
A77: 2338085: CREACION DE LA CARRETERA PU-103 (EMP. PE-34B BOCA SANGABAN - DV. COASA), PU-108 (DV. COASA - ISILLUMA) EMP. PE-34P Y DV. PE-34P (SANTIAGO PAMPA) - EMP PE-34H (PUTINA PUNCO) DISTRITOS DE SAN GABAN, AYAPATA, ITUATA, COASA, LIMBANI, PHARA, ALTO INAMBARI, PUTINA PUNCO LAS PROVINCIAS DE SANDIA Y CARABAYA DEL DEPARTAMENTO DE PUNO | B77: 1000000 | C77: 0 | D77: 0 | E77: 0 | F77: 0 | G77: 0 | H77: 0 | I77: 0.0 | J77: =C77-D77 -> 0 | K77: =C77-E77 -> 0 | L77: =D77-E77 -> 0 | M77: =C77-G77 -> 0 | N77: =IFERROR(K77/C77, " ") | O77: =IFERROR(G77/C77, "ERROR") -> ERROR
A78: 2343199: MEJORAMIENTO DE LA CARRETERA (EMP 34B) AZANGARO - (EMP PU-102) JILA PURINA DE LOS DISTRITO DE AZANGARO - DISTRITO DE TIRAPATA - PROVINCIA DE AZANGARO - REGION PUNO | B78: 12491498 | C78: 14991498 | D78: 14685003 | E78: 13584705 | F78: 12187900 | G78: 11502167 | H78: 10437635 | I78: 76.7 | J78: =C78-D78 -> 306495 | K78: =C78-E78 -> 1406793 | L78: =D78-E78 -> 1100298 | M78: =C78-G78 -> 3489331 | N78: =IFERROR(K78/C78, " ") -> 0.093839388 | O78: =IFERROR(G78/C78, "ERROR") -> 0.76724601
A79: 2343538: CREACION DE LOS SERVICIOS DE PROMOCION DEL COMERCIO EXTERIOR EN LA ZEEDE PUNO - REGION DE PUNO | B79: 800000 | C79: 46429 | D79: 0 | E79: 0 | F79: 0 | G79: 0 | H79: 0 | I79: 0.0 | J79: =C79-D79 -> 46429 | K79: =C79-E79 -> 46429 | L79: =D79-E79 -> 0 | M79: =C79-G79 -> 46429 | N79: =IFERROR(K79/C79, " ") -> 1 | O79: =IFERROR(G79/C79, "ERROR") -> 0 | P79: SI-PMI
A80: 2344253: MEJORAMIENTO DEL SERVICIO EDUCATIVO EN LA I.E.S. JOSE ANTONIO ENCINAS FRANCO, CENTRO POBLADO DE LECHEMAYO DEL DISTRITO DE SAN GABAN - PROVINCIA DE CARABAYA - DEPARTAMENTO DE PUNO | B80: 2120577 | C80: 4026127 | D80: 3933835 | E80: 2228281 | F80: 1396384 | G80: 1387806 | H80: 1275287 | I80: 34.5 | J80: =C80-D80 -> 92292 | K80: =C80-E80 -> 1797846 | L80: =D80-E80 -> 1705554 | M80: =C80-G80 -> 2638321 | N80: =IFERROR(K80/C80, " ") -> 0.44654478 | O80: =IFERROR(G80/C80, "ERROR") -> 0.34470001
A81: 2344324: MEJORAMIENTO DE LOS SERVICIOS EDUCATIVOS DE LA I.E.S. MANUEL GONZALES PRADA, CENTRO POBLADO DE ISANI - DISTRITO DE ZEPITA - PROVINCIA DE CHUCUITO - REGION PUNO | B81: 298669 | C81: 2079431 | D81: 1994037 | E81: 1986740 | F81: 1982924 | G81: 1946471 | H81: 1933908 | I81: 93.6 | J81: =C81-D81 -> 85394 | K81: =C81-E81 -> 92691 | L81: =D81-E81 -> 7297 | M81: =C81-G81 -> 132960 | N81: =IFERROR(K81/C81, " ") -> 0.044575175 | O81: =IFERROR(G81/C81, "ERROR") -> 0.93605943
A82: 2357089: MEJORAMIENTO DE LOS SERVICIOS DEL CENTRO DE SALUD ESTRATEGICO SIMON BOLIVAR CATEGORIA I-4 RED DE SALUD PUNO, DISTRITO PUNO - PROVINCIA DE PUNO - REGION PUNO DISTRITO DE PUNO - PROVINCIA DE PUNO - DEPARTAMENTO DE PUNO | B82: 12200258 | C82: 18753537 | D82: 18471517 | E82: 17212318 | F82: 17212318 | G82: 17212318 | H82: 16212318 | I82: 91.8 | J82: =C82-D82 -> 282020 | K82: =C82-E82 -> 1541219 | L82: =D82-E82 -> 1259199 | M82: =C82-G82 -> 1541219 | N82: =IFERROR(K82/C82, " ") -> 0.082182844 | O82: =IFERROR(G82/C82, "ERROR") -> 0.91781716
A83: 2357091: MEJORAMIENTO DE LA CAPACIDAD RESOLUTIVA DEL CENTRO DE SALUD COATA I-3 DE LA MICRORED JAE, RED DE SALUD PUNO - DIRESA PUNO, - DISTRITO DE COATA - PROVINCIA DE PUNO - REGION PUNO | B83: 8282615 | C83: 10399190 | D83: 9609876 | E83: 9609876 | F83: 0 | G83: 0 | H83: 0 | I83: 0.0 | J83: =C83-D83 -> 789314 | K83: =C83-E83 -> 789314 | L83: =D83-E83 -> 0 | M83: =C83-G83 -> 10399190 | N83: =IFERROR(K83/C83, " ") -> 0.075901488 | O83: =IFERROR(G83/C83, "ERROR") -> 0 | P83: SI-PMI
A84: 2357092: MEJORAMIENTO DE LA CAPACIDAD RESOLUTIVA DEL CENTRO DE SALUD COJATA I-4, DE LA MICRO RED COJATA, RED DE SALUD HUANCANE, DIRESA PUNO, DISTRITO DE COJATA - PROVINCIA DE HUANCANE - DEPARTAMENTO DE PUNO | B84: 8000000 | C84: 6997430 | D84: 6787159 | E84: 5366065 | F84: 3559162 | G84: 2630352 | H84: 2455859 | I84: 37.6 | J84: =C84-D84 -> 210271 | K84: =C84-E84 -> 1631365 | L84: =D84-E84 -> 1421094 | M84: =C84-G84 -> 4367078 | N84: =IFERROR(K84/C84, " ") -> 0.23313774 | O84: =IFERROR(G84/C84, "ERROR") -> 0.37590258
A85: 2357322: MEJORAMIENTO SERVICIO EDUCATIVO EN LA IES. 32 MARIANO H. CORNEJO DE LA LOCALIDAD DE JULIACA - DISTRITO DE JULIACA - PROVINCIA DE SAN ROMAN - REGION PUNO | B85: 9609000 | C85: 19795501 | D85: 19793412 | E85: 18134195 | F85: 17203041 | G85: 14545766 | H85: 13998596 | I85: 73.5 | J85: =C85-D85 -> 2089 | K85: =C85-E85 -> 1661306 | L85: =D85-E85 -> 1659217 | M85: =C85-G85 -> 5249735 | N85: =IFERROR(K85/C85, " ") -> 0.083923413 | O85: =IFERROR(G85/C85, "ERROR") -> 0.73480161
A86: 2357330: MEJORAMIENTO DEL SERVICIO EDUCATIVO DE LAS CARRERAS DE PRODUCCION AGROPECUARIA, MECANICA DE PRODUCCION, COMPUTACION E INFORMATICA, ENFERMERIA TECNICA EN EL INSTITUTO SUPERIOR TECNOLOGICO PUBLICO DE HUANCANE DISTRITO DE HUANCANE - PROVINCIA DE HUANCANE - DEPARTAMENTO DE PUNO | B86: 12500000 | C86: 17354707 | D86: 17083718 | E86: 13375985 | F86: 10746841 | G86: 8610008 | H86: 8043611 | I86: 49.6 | J86: =C86-D86 -> 270989 | K86: =C86-E86 -> 3978722 | L86: =D86-E86 -> 3707733 | M86: =C86-G86 -> 8744699 | N86: =IFERROR(K86/C86, " ") -> 0.22925896 | O86: =IFERROR(G86/C86, "ERROR") -> 0.49611947
A87: 2357337: MEJORAMIENTO Y AMPLIACION DEL SERVICIO EDUCATIVO DE LA ESCUELA SUPERIOR DE FORMACION ARTISTICA PUBLICA (ESFAP - PUNO), DISTRITO DE PUNO - PROVINCIA DE PUNO - REGION PUNO | B87: 100000 | C87: 100000 | D87: 50000 | E87: 50000 | F87: 0 | G87: 0 | H87: 0 | I87: 0.0 | J87: =C87-D87 -> 50000 | K87: =C87-E87 -> 50000 | L87: =D87-E87 -> 0 | M87: =C87-G87 -> 100000 | N87: =IFERROR(K87/C87, " ") -> 0.5 | O87: =IFERROR(G87/C87, "ERROR") -> 0 | P87: SI-PMI
A88: 2375549: CREACION DE LA INFRAESTRUCTURA DE INTEGRACION VIAL ENTRE SANDIA (CP. QUENEQUE) Y PATAMBUCO (C.P. TIRACA), DISTRITO DE SANDIA Y PATAMBUCO, PROVINCIA DE SANDIA - PUNO | B88: 1200000 | C88: 167638 | D88: 167637 | E88: 167637 | F88: 143800 | G88: 124800 | H88: 124800 | I88: 74.4 | J88: =C88-D88 -> 1 | K88: =C88-E88 -> 1 | L88: =D88-E88 -> 0 | M88: =C88-G88 -> 42838 | N88: =IFERROR(K88/C88, " ") -> 5.9652346e-06 | O88: =IFERROR(G88/C88, "ERROR") -> 0.74446128
A89: 2380088: MEJORAMIENTO Y AMPLIACION DE LOS SERVICIOS DE SALUD DEL HOSPITAL CARLOS CORNEJO ROSELLO VIZCARDO DE LA CIUDAD DE AZANGARO, DISTRITO Y PROVINCIA DE AZANGARO, DEPARTAMENTO DE PUNO | B89: 1950000 | C89: 0 | D89: 0 | E89: 0 | F89: 0 | G89: 0 | H89: 0 | I89: 0.0 | J89: =C89-D89 -> 0 | K89: =C89-E89 -> 0 | L89: =D89-E89 -> 0 | M89: =C89-G89 -> 0 | N89: =IFERROR(K89/C89, " ") | O89: =IFERROR(G89/C89, "ERROR") -> ERROR
A90: 2384978: MEJORAMIENTO DE LOS SERVICIOS DE EDUCACION SECUNDARIA EN LA INSTITUCION EDUCATIVA PUBLICA MILITAR INCA MANCO CAPAC , CENTRO POBLADO DE TOTORANI - DISTRITO DE PUNO - PROVINCIA DE PUNO - REGION PUNO | B90: 100000 | C90: 100000 | D90: 85000 | E90: 60000 | F90: 58663 | G90: 58663 | H90: 54661 | I90: 58.7 | J90: =C90-D90 -> 15000 | K90: =C90-E90 -> 40000 | L90: =D90-E90 -> 25000 | M90: =C90-G90 -> 41337 | N90: =IFERROR(K90/C90, " ") -> 0.4 | O90: =IFERROR(G90/C90, "ERROR") -> 0.58663
A91: 2385051: MEJORAMIENTO DEL SERVICIO EDUCATIVO EN LA I.E.S. SAN JUAN BOSCO DE SALCEDO CON JORNADA ESCOLAR COMPLETA DISTRITO DE PUNO - PROVINCIA DE PUNO - REGION PUNO | B91: 2000000 | C91: 4927527 | D91: 4223261 | E91: 2264680 | F91: 2212773 | G91: 1725644 | H91: 1250146 | I91: 35.0 | J91: =C91-D91 -> 704266 | K91: =C91-E91 -> 2662847 | L91: =D91-E91 -> 1958581 | M91: =C91-G91 -> 3201883 | N91: =IFERROR(K91/C91, " ") -> 0.54040232 | O91: =IFERROR(G91/C91, "ERROR") -> 0.35020488
A92: 2385673: MEJORAMIENTO DEL SERVICIO EDUCATIVO DE LA I.E.S. LAS MERCEDES DE LA CIUDAD DE JULIACA - DISTRITO DE JULIACA - PROVINCIA DE SAN ROMAN - DEPARTAMENTO DE PUNO | B92: 8016014 | C92: 17241964 | D92: 17144705 | E92: 14900492 | F92: 14257900 | G92: 11639796 | H92: 11082518 | I92: 67.5 | J92: =C92-D92 -> 97259 | K92: =C92-E92 -> 2341472 | L92: =D92-E92 -> 2244213 | M92: =C92-G92 -> 5602168 | N92: =IFERROR(K92/C92, " ") -> 0.13580077 | O92: =IFERROR(G92/C92, "ERROR") -> 0.67508527
A93: 2387422: MEJORAMIENTO DE LA CARRETERA TRAMO II (PUENTE CULLCO) - PICHINCUTA - QUELCAHUECO - CORARACA DEL - DISTRITO DE ILAVE - PROVINCIA DE EL COLLAO - DEPARTAMENTO DE PUNO | B93: 2071511 | C93: 7751873 | D93: 7482027 | E93: 6468123 | F93: 6277782 | G93: 5292813 | H93: 4764959 | I93: 68.3 | J93: =C93-D93 -> 269846 | K93: =C93-E93 -> 1283750 | L93: =D93-E93 -> 1013904 | M93: =C93-G93 -> 2459060 | N93: =IFERROR(K93/C93, " ") -> 0.16560514 | O93: =IFERROR(G93/C93, "ERROR") -> 0.6827786
A94: 2393101: MEJORAMIENTO Y AMPLIACION DEL SERVICIO ADMINISTRATIVO DE LA UNIDAD DE GESTION EDUCATIVA LOCAL MELGAR EN EL DISTRITO DE AYAVIRI, PROVINCIA DE MELGAR, REGION PUNO | B94: 154969 | C94: 32592 | D94: 0 | E94: 0 | F94: 0 | G94: 0 | H94: 0 | I94: 0.0 | J94: =C94-D94 -> 32592 | K94: =C94-E94 -> 32592 | L94: =D94-E94 -> 0 | M94: =C94-G94 -> 32592 | N94: =IFERROR(K94/C94, " ") -> 1 | O94: =IFERROR(G94/C94, "ERROR") -> 0 | P94: SI-PMI
A95: 2393398: MEJORAMIENTO DEL SERVICIO EDUCATIVO DE NIVEL SECUNDARIO EN LA I.E. A - 28 PERU BIRF CENTRO POBLADO DE AZANGARO - DISTRITO DE AZANGARO - PROVINCIA DE AZANGARO - REGION PUNO | B95: 12431185 | C95: 18692228 | D95: 18634477 | E95: 18176428 | F95: 5026816 | G95: 4987668 | H95: 4425991 | I95: 26.7 | J95: =C95-D95 -> 57751 | K95: =C95-E95 -> 515800 | L95: =D95-E95 -> 458049 | M95: =C95-G95 -> 13704560 | N95: =IFERROR(K95/C95, " ") -> 0.027594356 | O95: =IFERROR(G95/C95, "ERROR") -> 0.26683111
A96: 2399543: MEJORAMIENTO DEL CAMINO VECINAL EMP. R01 (DV. LOANI) - CAMICACHI - EMP. R12 (ROSACANI) DISTRITO DE ILAVE - PROVINCIA DE EL COLLAO - REGION PUNO | B96: 2422294 | C96: 5270087 | D96: 5222084 | E96: 5222084 | F96: 5222084 | G96: 5220159 | H96: 5220159 | I96: 99.1 | J96: =C96-D96 -> 48003 | K96: =C96-E96 -> 48003 | L96: =D96-E96 -> 0 | M96: =C96-G96 -> 49928 | N96: =IFERROR(K96/C96, " ") -> 0.0091085783 | O96: =IFERROR(G96/C96, "ERROR") -> 0.99052615
A97: 2403888: MEJORAMIENTO DE LOS SERVICIOS DE EDUCACION SUPERIOR DEL INSTITUTO DE EDUCACION SUPERIOR TECNOLOGICO PUBLICA DESAGUADERO DEL DISTRITO DE DESAGUADERO - PROVINCIA DE CHUCUITO - DEPARTAMENTO DE PUNO | B97: 3500504 | C97: 261704 | D97: 261704 | E97: 261704 | F97: 134683 | G97: 134683 | H97: 91715 | I97: 51.5 | J97: =C97-D97 -> 0 | K97: =C97-E97 -> 0 | L97: =D97-E97 -> 0 | M97: =C97-G97 -> 127021 | N97: =IFERROR(K97/C97, " ") -> 0 | O97: =IFERROR(G97/C97, "ERROR") -> 0.51463868
A98: 2411317: MEJORAMIENTO DE LOS SERVICIOS PUBLICOS DEL GOBIERNO REGIONAL PUNO - SEDE CENTRAL, DEL DISTRITO DE PUNO - PROVINCIA DE PUNO - DEPARTAMENTO DE PUNO | B98: 10763553 | C98: 0 | D98: 0 | E98: 0 | F98: 0 | G98: 0 | H98: 0 | I98: 0.0 | J98: =C98-D98 -> 0 | K98: =C98-E98 -> 0 | L98: =D98-E98 -> 0 | M98: =C98-G98 -> 0 | N98: =IFERROR(K98/C98, " ") | O98: =IFERROR(G98/C98, "ERROR") -> ERROR
A99: 2411335: MEJORAMIENTO DEL SERVICIO EDUCATIVO EN LA I.E.S. SAN SALVADOR, - DISTRITO DE PUNO - PROVINCIA DE PUNO - DEPARTAMENTO DE PUNO | B99: 0 | C99: 1272735 | D99: 1253657 | E99: 1253657 | F99: 1229218 | G99: 1181486 | H99: 1181486 | I99: 92.8 | J99: =C99-D99 -> 19078 | K99: =C99-E99 -> 19078 | L99: =D99-E99 -> 0 | M99: =C99-G99 -> 91249 | N99: =IFERROR(K99/C99, " ") -> 0.014989766 | O99: =IFERROR(G99/C99, "ERROR") -> 0.92830479
A100: 2411336: MEJORAMIENTO SERVICIO INTEGRAL DE LA INSTITUCION EDUCATIVA SECUNDARIA INDUSTRIAL PERU BIRF DISTRITO DE SAN MIGUEL - PROVINCIA DE SAN ROMAN - DEPARTAMENTO DE PUNO | B100: 11955231 | C100: 21914154 | D100: 21776068 | E100: 20527324 | F100: 20073863 | G100: 15564867 | H100: 14020801 | I100: 71.0 | J100: =C100-D100 -> 138086 | K100: =C100-E100 -> 1386830 | L100: =D100-E100 -> 1248744 | M100: =C100-G100 -> 6349287 | N100: =IFERROR(K100/C100, " ") -> 0.06328467 | O100: =IFERROR(G100/C100, "ERROR") -> 0.71026547
A101: 2417765: MEJORAMIENTO Y AMPLIACION DEL SERVICIOS DE EDUCACION BASICA EN EL NIVEL PRIMARIO DE LA IEP Nº 72169 TAMBILLO, IEP Nº 72175 TAYACCUCHO, IEP Nº 72188 QUETY, IEP Nº 72642 MALLCUAPO, IEP Nº 72749 CALASUCA DEL DISTRITO DE ITUATA - PROVINCIA DE CARABAYA - DEPARTAMENTO DE PUNO DISTRITO DE ITUATA - PROVINCIA DE CARABAYA - DEPARTAMENTO DE PUNO | B101: 3770000 | C101: 9795205 | D101: 8653127 | E101: 8210931 | F101: 7642489 | G101: 6503506 | H101: 6197989 | I101: 66.4 | J101: =C101-D101 -> 1142078 | K101: =C101-E101 -> 1584274 | L101: =D101-E101 -> 442196 | M101: =C101-G101 -> 3291699 | N101: =IFERROR(K101/C101, " ") -> 0.16173975 | O101: =IFERROR(G101/C101, "ERROR") -> 0.66394792
A102: 2427364: MEJORAMIENTO DE LOS SERVICIOS DE SALUD DEL HOSPITAL ANTONIO BARRIONUEVO DISTRITO DE LAMPA - PROVINCIA DE LAMPA - DEPARTAMENTO DE PUNO | B102: 20000000 | C102: 966193 | D102: 746819 | E102: 6257 | F102: 6257 | G102: 6257 | H102: 6257 | I102: 0.6 | J102: =C102-D102 -> 219374 | K102: =C102-E102 -> 959936 | L102: =D102-E102 -> 740562 | M102: =C102-G102 -> 959936 | N102: =IFERROR(K102/C102, " ") -> 0.99352407 | O102: =IFERROR(G102/C102, "ERROR") -> 0.0064759318
A103: 2429723: MEJORAMIENTO Y AMPLIACION DEL SERVICIO DE AGUA PARA EL SISTEMA DE RIEGO PRESURIZADO EN LA MICROCUENCA YANAMAYO DEL DISTRITO DE AZANGARO - PROVINCIA DE AZANGARO - DEPARTAMENTO DE PUNO | B103: 20000 | C103: 34081 | D103: 33741 | E103: 33315 | F103: 33315 | G103: 33315 | H103: 33315 | I103: 97.8 | J103: =C103-D103 -> 340 | K103: =C103-E103 -> 766 | L103: =D103-E103 -> 426 | M103: =C103-G103 -> 766 | N103: =IFERROR(K103/C103, " ") -> 0.022475866 | O103: =IFERROR(G103/C103, "ERROR") -> 0.97752413
A104: 2435272: MEJORAMIENTO Y AMPLIACION DE LOS SERVICIOS DE SALUD DEL CENTRO DE SALUD LA REVOLUCION (NIVEL I-4) DISTRITO DE SAN MIGUEL - PROVINCIA DE SAN ROMAN - DEPARTAMENTO DE PUNO | B104: 12000000 | C104: 17484286 | D104: 17380463 | E104: 16260021 | F104: 15761867 | G104: 15761867 | H104: 15761867 | I104: 90.1 | J104: =C104-D104 -> 103823 | K104: =C104-E104 -> 1224265 | L104: =D104-E104 -> 1120442 | M104: =C104-G104 -> 1722419 | N104: =IFERROR(K104/C104, " ") -> 0.070020875 | O104: =IFERROR(G104/C104, "ERROR") -> 0.9014876
A105: 2436247: MEJORAMIENTO DEL CAMINO VECINAL RUTA PU-713, EMP. PE 3S (AYAVIRI - DESV. CALUYO - TINAJANI - L. PROV. LAMPA), DISTRITO DE AYAVIRI - PROVINCIA DE MELGAR - DEPARTAMENTO DE PUNO | B105: 10000000 | C105: 22224878 | D105: 21946068 | E105: 18817053 | F105: 7134863 | G105: 7073510 | H105: 7057069 | I105: 31.8 | J105: =C105-D105 -> 278810 | K105: =C105-E105 -> 3407825 | L105: =D105-E105 -> 3129015 | M105: =C105-G105 -> 15151368 | N105: =IFERROR(K105/C105, " ") -> 0.1533338 | O105: =IFERROR(G105/C105, "ERROR") -> 0.31826991
A106: 2440946: MEJORAMIENTO DEL SERVICIO DE TRANSITABILIDAD VEHICULAR DE LA CARRETERA TRAMO ACHAYA (PU-140) - ESTRELLA (EMP. PE- 3S) DEL DISTRITO DE ACHAYA - PROVINCIA DE AZANGARO - DEPARTAMENTO DE PUNO | B106: 0 | C106: 28752 | D106: 28752 | E106: 28752 | F106: 28752 | G106: 28752 | H106: 28752 | I106: 100.0 | J106: =C106-D106 -> 0 | K106: =C106-E106 -> 0 | L106: =D106-E106 -> 0 | M106: =C106-G106 -> 0 | N106: =IFERROR(K106/C106, " ") -> 0 | O106: =IFERROR(G106/C106, "ERROR") -> 1
A107: 2443679: MEJORAMIENTO DEL SERVICIO DE TRANSITABILIDAD VEHICULAR DE LA CARRETERA TRAMO I: EMP- 34L (COJATA) - HUANCASAYA, TRAMO II: HUANCASAYA - TARUCANI-EMP-PU-115 (INCHUPALLA), DEL DISTRITO DE COJATA - PROVINCIA DE HUANCANE - DEPARTAMENTO DE PUNO | B107: 800000 | C107: 0 | D107: 0 | E107: 0 | F107: 0 | G107: 0 | H107: 0 | I107: 0.0 | J107: =C107-D107 -> 0 | K107: =C107-E107 -> 0 | L107: =D107-E107 -> 0 | M107: =C107-G107 -> 0 | N107: =IFERROR(K107/C107, " ") | O107: =IFERROR(G107/C107, "ERROR") -> ERROR
A108: 2447465: MEJORAMIENTO DE LA INFRAESTRUCTURA VIAL EN LA AV. SACSAYHUAMAN TRAMO (JR. MIRAFLORES - AV. AVIACION), JR. AMANECER TRAMO (AV. INDEPENDENCIA - JR. MIRAFLORES) DE LA CIUDAD DE JULIACA, DISTRITO DE JULIACA - PROVINCIA DE SAN ROMAN - DEPARTAMENTO DE PUNO | B108: 4000000 | C108: 3978899 | D108: 3978899 | E108: 3978899 | F108: 0 | G108: 0 | H108: 0 | I108: 0.0 | J108: =C108-D108 -> 0 | K108: =C108-E108 -> 0 | L108: =D108-E108 -> 0 | M108: =C108-G108 -> 3978899 | N108: =IFERROR(K108/C108, " ") -> 0 | O108: =IFERROR(G108/C108, "ERROR") -> 0 | P108: SI-PMI
A109: 2450812: MEJORAMIENTO DE LOS SERVICIOS DE SALUD DEL CENTRO DE SALUD ZEPITA, MICRO RED ZEPITA, RED DE SALUD CHUCUITO, DEL DISTRITO DE ZEPITA - PROVINCIA DE CHUCUITO - DEPARTAMENTO DE PUNO | B109: 200000 | C109: 3866926 | D109: 2225809 | E109: 2101121 | F109: 2024160 | G109: 1961816 | H109: 1969860 | I109: 50.7 | J109: =C109-D109 -> 1641117 | K109: =C109-E109 -> 1765805 | L109: =D109-E109 -> 124688 | M109: =C109-G109 -> 1905110 | N109: =IFERROR(K109/C109, " ") -> 0.45664308 | O109: =IFERROR(G109/C109, "ERROR") -> 0.50733218
A110: 2451529: MEJORAMIENTO DEL SERVICIO DE SALUD EN EL CENTRO DE SALUD PILCUYO DE LA MICRORED PILCUYO, RED DE SALUD EL COLLAO, DEL DISTRITO DE PILCUYO - PROVINCIA DE EL COLLAO - DEPARTAMENTO DE PUNO | B110: 12571000 | C110: 0 | D110: 0 | E110: 0 | F110: 0 | G110: 0 | H110: 0 | I110: 0.0 | J110: =C110-D110 -> 0 | K110: =C110-E110 -> 0 | L110: =D110-E110 -> 0 | M110: =C110-G110 -> 0 | N110: =IFERROR(K110/C110, " ") | O110: =IFERROR(G110/C110, "ERROR") -> ERROR
A111: 2453224: MEJORAMIENTO DE LOS SERVICIOS DE EDUCACION SECUNDARIA DE LA INSTITUCION EDUCATIVA LIBERTADOR JOSE DE SAN MARTIN DE HUARISANI DEL DISTRITO DE HUANCANE - PROVINCIA DE HUANCANE - DEPARTAMENTO DE PUNO | B111: 0 | C111: 4265759 | D111: 3847053 | E111: 3704328 | F111: 3386045 | G111: 2741830 | H111: 2560623 | I111: 64.3 | J111: =C111-D111 -> 418706 | K111: =C111-E111 -> 561431 | L111: =D111-E111 -> 142725 | M111: =C111-G111 -> 1523929 | N111: =IFERROR(K111/C111, " ") -> 0.13161339 | O111: =IFERROR(G111/C111, "ERROR") -> 0.64275314
A112: 2454391: AMPLIACION DEL SERVICIO DE AGUA PARA RIEGO MEDIANTE LA CONSTRUCCION DE LA REPRESA SAPANCCOTA DEL DISTRITO DE PUCARA - PROVINCIA DE LAMPA - DEPARTAMENTO DE PUNO | B112: 2780000 | C112: 7891675 | D112: 7541696 | E112: 7384393 | F112: 6959893 | G112: 6428337 | H112: 6014554 | I112: 81.5 | J112: =C112-D112 -> 349979 | K112: =C112-E112 -> 507282 | L112: =D112-E112 -> 157303 | M112: =C112-G112 -> 1463338 | N112: =IFERROR(K112/C112, " ") -> 0.06428065 | O112: =IFERROR(G112/C112, "ERROR") -> 0.81457194
A113: 2456529: MEJORAMIENTO DE LA CARRETERA PU 147, EMP. PE-34I JIPATA - EMP. PE-34I MOHO, DISTRITO DE MOHO - PROVINCIA DE MOHO - DEPARTAMENTO DE PUNO | B113: 15500800 | C113: 23143575 | D113: 22275711 | E113: 19031849 | F113: 15277445 | G113: 12059018 | H113: 11569861 | I113: 52.1 | J113: =C113-D113 -> 867864 | K113: =C113-E113 -> 4111726 | L113: =D113-E113 -> 3243862 | M113: =C113-G113 -> 11084557 | N113: =IFERROR(K113/C113, " ") -> 0.17766166 | O113: =IFERROR(G113/C113, "ERROR") -> 0.52105252
A114: 2462296: CREACION DEL SERVICIO DE TRANSITABILIDAD A TRAVES DE LA INSTALACION DE PUENTES PEATONALES EN LAS PROVINCIAS DE CARABAYA Y SANDIA DEL DEPARTAMENTO DE PUNO | B114: 250000 | C114: 0 | D114: 0 | E114: 0 | F114: 0 | G114: 0 | H114: 0 | I114: 0.0 | J114: =C114-D114 -> 0 | K114: =C114-E114 -> 0 | L114: =D114-E114 -> 0 | M114: =C114-G114 -> 0 | N114: =IFERROR(K114/C114, " ") | O114: =IFERROR(G114/C114, "ERROR") -> ERROR
A115: 2467893: MEJORAMIENTO DEL SERVICIO EDUCATIVO DEL NIVEL SECUNDARIA DE LA I.E.S. TARACO DEL DISTRITO DE TARACO - PROVINCIA DE HUANCANE - DEPARTAMENTO DE PUNO | B115: 175369 | C115: 50132 | D115: 47450 | E115: 47450 | F115: 47450 | G115: 47450 | H115: 47450 | I115: 94.7 | J115: =C115-D115 -> 2682 | K115: =C115-E115 -> 2682 | L115: =D115-E115 -> 0 | M115: =C115-G115 -> 2682 | N115: =IFERROR(K115/C115, " ") -> 0.053498763 | O115: =IFERROR(G115/C115, "ERROR") -> 0.94650124
A116: 2470024: MEJORAMIENTO DEL SERVICIO DE TRANSITABILIDAD VEHICULAR A TRAVES DE PUENTES CARROZABLES EN LAS PROVINCIAS DE CARABAYA Y SANDIA DEL DEPARTAMENTO DE PUNO | B116: 2800000 | C116: 0 | D116: 0 | E116: 0 | F116: 0 | G116: 0 | H116: 0 | I116: 0.0 | J116: =C116-D116 -> 0 | K116: =C116-E116 -> 0 | L116: =D116-E116 -> 0 | M116: =C116-G116 -> 0 | N116: =IFERROR(K116/C116, " ") | O116: =IFERROR(G116/C116, "ERROR") -> ERROR
A117: 2470517: MEJORAMIENTO DE LOS SERVICIOS DE SALUD DEL CENTRO DE SALUD COPANI DE LA MICRO RED COPANI, RED DE SALUD YUNGUYO, DISTRITO DE COPANI - PROVINCIA DE YUNGUYO - DEPARTAMENTO DE PUNO | B117: 8000000 | C117: 7374992 | D117: 7374802 | E117: 0 | F117: 0 | G117: 0 | H117: 0 | I117: 0.0 | J117: =C117-D117 -> 190 | K117: =C117-E117 -> 7374992 | L117: =D117-E117 -> 7374802 | M117: =C117-G117 -> 7374992 | N117: =IFERROR(K117/C117, " ") -> 1 | O117: =IFERROR(G117/C117, "ERROR") -> 0 | P117: SI-PMI
A118: 2470845: MEJORAMIENTO Y AMPLIACION DEL SERVICIO DE AGUA PARA RIEGO TECNIFICADO EN LAS COMUNIDADES DE SAN JUAN DE TAHUACO Y MACHACMARCA DEL DISTRITO DE YUNGUYO - PROVINCIA DE YUNGUYO - DEPARTAMENTO DE PUNO | B118: 1850000 | C118: 2302588 | D118: 2195598 | E118: 2174756 | F118: 2173732 | G118: 2088606 | H118: 2088606 | I118: 90.7 | J118: =C118-D118 -> 106990 | K118: =C118-E118 -> 127832 | L118: =D118-E118 -> 20842 | M118: =C118-G118 -> 213982 | N118: =IFERROR(K118/C118, " ") -> 0.055516662 | O118: =IFERROR(G118/C118, "ERROR") -> 0.90706892
...

Sheet RESUMEN
A1: Proyectos que NO-PMI | B1: PIM | D1: Proyectos que NO-Cert-Comp | E1: PIM | G1: Proyectos que Solo Certificaron | H1: PIM
B2: =Proyectos!B422 -> PIM | E2: =Proyectos!E422 -> 0 | H2: =Proyectos!H422 -> 0
A3: =Proyectos!A424 -> 2194989: MEJORAMIENTO DE LOS SERVICIOS EDUCATIVOS EN LA INSTITUCION EDUCATIVA SECUNDARIA DANTE NAVA DEL CENTRO POBLADO SANTA CRUZ DE PUNA AYLLU, DISTRITO DE PATAMBUCO, PROVINCIA DE SANDIA, REGION PUNO | B3: =Proyectos!B424 -> 133512 | D3: =Proyectos!A450 -> 2185578: MEJORAMIENTO DE LA CARRETERA DV. DESAGUADERO (EMP PE 36A) - KELLUYO - PISACOMA, PROVINCIA DE CHUCUITO - PUNO | E3: =Proyectos!B450 -> 67139 | G3: =Proyectos!A474 -> 2470517: MEJORAMIENTO DE LOS SERVICIOS DE SALUD DEL CENTRO DE SALUD COPANI DE LA MICRO RED COPANI, RED DE SALUD YUNGUYO, DISTRITO DE COPANI - PROVINCIA DE YUNGUYO - DEPARTAMENTO DE PUNO | H3: =Proyectos!B474 -> 7374992
A4: =Proyectos!A425 -> 2313145: MEJORAMIENTO DEL MANEJO SOSTENIBLE DE VICUÑAS EN ZONAS ALTOANDINAS DE LA REGION PUNO | B4: =Proyectos!B425 -> 40000 | D4: =Proyectos!A451 -> 2196834: MEJORAMIENTO DE LOS SERVICIOS DE EDUCACION INICIAL EN LA I.E.I. CUCURAYA DE LA COMUNIDAD DE CUCURAYA, DISTRITO DE TILALI, PROVINCIA DE MOHO - PUNO. | E4: =Proyectos!B451 -> 728529 | G4: =Proyectos!A475 -> 2476464: MEJORAMIENTO Y AMPLIACION DE LOS SERVICIOS DE SALUD DEL CENTRO DE SALUD KELLUYO DEL DISTRITO DE KELLUYO - PROVINCIA DE CHUCUITO - DEPARTAMENTO DE PUNO | H4: =Proyectos!B475 -> 184669
A5: =Proyectos!A426 -> 2575299: MEJORAMIENTO DEL SERVICIO DE TRANSITABILIDAD VIAL INTERURBANA EN EL TRAMO TIQUILLACA - CONDORIRI DEL DISTRITO DE TIQUILLACA DE LA PROVINCIA DE PUNO DEL DEPARTAMENTO DE PUNO | B5: =Proyectos!B426 -> 18371 | D5: =Proyectos!A452 -> 2325694: MEJORAMIENTO DE LA TECNIFICACION DE PROCESOS PARA LA CADENA PRODUCTIVA DE LA LECHE EN LA REGION PUNO | E5: =Proyectos!B452 -> 30000 | G5: =Proyectos!A476 -> 2492442: MEJORAMIENTO Y AMPLIACION DE LOS SERVICIOS DE AGUA POTABLE Y ALCANTARILLADO SANITARIO EN LA LOCALIDAD DE CARACOTO DEL DISTRITO DE CARACOTO - PROVINCIA DE SAN ROMAN - DEPARTAMENTO DE PUNO | H5: =Proyectos!B476 -> 11000
A6: =Proyectos!A427 -> 2612522: MEJORAMIENTO DE LA PRODUCCION Y TRANSFORMACION DE QUESOS EN LA ASOCIACION DE PRODUCTORES LACTI SUR DE HUAPACA SANTIAGO DEL DISTRITO DE POMATA, PROVINCIA DE CHUCUITO Y DEPARTAMENTO DE PUN | B6: =Proyectos!B427 -> 61500 | D6: =Proyectos!A453 -> 2343538: CREACION DE LOS SERVICIOS DE PROMOCION DEL COMERCIO EXTERIOR EN LA ZEEDE PUNO - REGION DE PUNO | E6: =Proyectos!B453 -> 46429 | G6: =Proyectos!A477 -> 2501244: MEJORAMIENTO DEL SERVICIO EDUCATIVO DEL NIVEL SECUNDARIA DE LA I.E. AGROPECUARIO PAMPA YANAMAYO DEL DISTRITO DE ALTO INAMBARI - PROVINCIA DE SANDIA - DEPARTAMENTO DE PUNO | H6: =Proyectos!B477 -> 1038097
A7: =Proyectos!A428 -> 2612541: MEJORAMIENTO DE LA PRODUCCION Y COMERCIALIZACION DE DERIVADOS LACTEOS EN LA ASOCIACION DE PRODUCTORES AGROPECUARIOS EMPRENDEDORES LOS CLAVELES DE SAN SALVADOR HUATASANI, DEL DISTRITO DE HUATASANI, PROVINCIA DE HUANCANE Y REGION DE PUNO | B7: =Proyectos!B428 -> 62000 | D7: =Proyectos!A454 -> 2393101: MEJORAMIENTO Y AMPLIACION DEL SERVICIO ADMINISTRATIVO DE LA UNIDAD DE GESTION EDUCATIVA LOCAL MELGAR EN EL DISTRITO DE AYAVIRI, PROVINCIA DE MELGAR, REGION PUNO | E7: =Proyectos!B454 -> 32592 | G7: =Proyectos!A478 -> 2517448: MEJORAMIENTO DEL SERVICIO DE SALUD EN EL CENTRO DE SALUD SAN GABAN, DISTRITO DE SAN GABAN - PROVINCIA DE CARABAYA - DEPARTAMENTO DE PUNO | H7: =Proyectos!B478 -> 200000
A8: =Proyectos!A429 -> 2624292: MEJORAMIENTO DE LOS SERVICIOS EDUCACION SUPERIOR PEDAGOGICA EN EL INSTITUTO DE EDUCACION SUPERIOR PEDAGOGICO PUBLICO DE AYAVIRI DEL DISTRITO DE AYAVIRI DE LA PROVINCIA DE MELGAR DEL DEPARTAMENTO DE PUNO | B8: =Proyectos!B429 -> 58627 | D8: =Proyectos!A455 -> 2518131: AMPLIACION Y MEJORAMIENTO DE LOS SERVICIOS DE ADMINISTRACION DE JUSTICIA DE LOS ORGANOS JURISDICCIONALES DE LA SEDE CENTRAL DEL DISTRITO JUDICIAL DE PUNO, DISTRITO DE PUNO - PROVINCIA DE PUNO - DEPARTAMENTO DE PUNO | E8: =Proyectos!B455 -> 500000 | G8: =Proyectos!A479 -> 2532916: CREACION DEL SERVICIO DE PROTECCION EN RIBERAS DEL RIO LORIPONGO Y MOLLA AMBOS MARGENES VULNERABLES ANTE EL PELIGRO DE INUNDACION EN LA LOCALIDAD DE LARAQUERI Y CENTRO POBLADO DE HUARIJUYO DEL DISTRITO DE PICHACANI - PROVINCIA DE PUNO - DEPARTAMENTO DE PUNO | H8: =Proyectos!B479 -> 19658
A9: =Proyectos!A430 -> 2625216: MEJORAMIENTO DE LOS SERVICIOS ECOSISTEMICOS EN EL RIO TOROCOCHA DE LA LOCALIDAD DE JULIACA DISTRITO DE JULIACA DE LA PROVINCIA DE SAN ROMAN DEL DEPARTAMENTO DE PUNO | B9: =Proyectos!B430 -> 100000 | D9: =Proyectos!A456 -> 2533866: RECUPERACION DE ECOSISTEMAS DEGRADADOS POR VERTIMIENTO DE AGUAS RESIDUALES Y RESIDUOS SOLIDOS EN LA DESEMBOCADURA DEL RIO COATA, EN LOS DISTRITOS DE HUATA, COATA, CAPACHICA, JULIACA Y SAN MIGUEL EN LAS PROVINCIAS DE PUNO Y SAN ROMAN DEL DEPARTAMENTO DE PUNO | E9: =Proyectos!B456 -> 32099 | G9: =Proyectos!A480 -> 2539673: MEJORAMIENTO Y AMPLIACION DEL SERVICIO DE EDUCACION SUPERIOR TECNOLOGICA EN EL INSTITUTO SUPERIOR TECNOLOGICO PUBLICO DE JULI, DISTRITO DE JULI - PROVINCIA DE CHUCUITO - DEPARTAMENTO DE PUNO | H9: =Proyectos!B480 -> 2000000
A10: =Proyectos!A431 -> 2658446: PROYECTOS PARA EL DESARROLLO LOCAL | B10: =Proyectos!B431 -> 1376515 | D10: =Proyectos!A457 -> 2602163: MEJORAMIENTO DEL SERVICIO DE TRANSITABILIDAD VIAL INTERURBANA EN LA CARRETERA PU 866 (EMP PE 34 I) - EMP PU 110 (SULLCA), PU 870 (DV TOTORANI: EMP PU 866) - EMP PU 872 (OCCOPAMPA), PU 872: EMP. PU - 866 (HUAYRAPATA) - OCCOPAMPA - EMP. PU - 870 DISTRITOS DE MOHO, HUAYRAPATA DE LA PROVINCIA DE MOHO DEL DEPARTAMENTO DE PUNO | E10: =Proyectos!B457 -> 2308286 | G10: =Proyectos!A481 -> 2570365: MEJORAMIENTO DEL INSTITUTO DE EDUCACION SUPERIOR TECNOLOGICO PUBLICO SANTA LUCIA DEL DISTRITO DE SANTA LUCIA - PROVINCIA DE LAMPA - DEPARTAMENTO DE PUNO | H10: =Proyectos!B481 -> 4863
A11: =Proyectos!A432 -> 2659573: MEJORAMIENTO DEL SERVICIO DE EDUCACION PRIMARIA EN I.E. 73003 DISTRITO DE HUANCANE DE LA PROVINCIA DE HUANCANE DEL DEPARTAMENTO DE PUNO | B11: =Proyectos!B432 -> 81646 | D11: =Proyectos!A458 -> 2603160: MEJORAMIENTO DE LOS SERVICIOS DE APOYO AL DESARROLLO PRODUCTIVO EN 4 UNIDADES PRODUCTORAS 4 DISTRITOS DE LAS PROVINCIAS DE SANDIA, CARABAYA DEL DEPARTAMENTO DE PUNO | E11: =Proyectos!B458 -> 100000 | G11: =Proyectos!A482 -> 2585541: CREACION DEL SERVICIO DE TRANSITABILIDAD VIAL INTERURBANA EN EL PUENTE CARROZABLE SANTA ROSA DE HUAYLLATA ENTRE LOS DISTRITOS DE ILAVE Y PILCUYO DEL DISTRITO DE ILAVE DE LA PROVINCIA DE EL COLLAO DEL DEPARTAMENTO DE PUNO | H11: =Proyectos!B482 -> 391951
A12: =Proyectos!A433 -> 2663002: MEJORAMIENTO DEL SERVICIO DE EDUCACION SECUNDARIA EN I.E. HUAPACA SAN MIGUEL DE CENTRO POBLADO HUAPACA SAN MIGUEL DISTRITO DE POMATA DE LA PROVINCIA DE CHUCUITO DEL DEPARTAMENTO DE PUNO | B12: =Proyectos!B433 -> 292573 | D12: =Proyectos!A459 -> 2617364: MEJORAMIENTO Y AMPLIACION DEL SERVICIO DE EDUCACION INICIAL, SERVICIO DE EDUCACION PRIMARIA Y SERVICIO DE EDUCACION SECUNDARIA EN I.E. 27 SANTA LUCIA FE Y ALEGRIA DISTRITO DE MACARI DE LA PROVINCIA DE MELGAR DEL DEPARTAMENTO DE PUNO | E12: =Proyectos!B459 -> 218556 | G12: =Proyectos!A483 -> 2593683: REPARACION DE PISTA DE ATLETISMO (COMPETENCIA); ADQUISICION DE TORRE DE ILUMINACION; EN EL(LA) ESTADIO ENRIQUE TORRES BELON DEL DISTRITO DE PUNO, PROVINCIA PUNO, DEPARTAMENTO PUNO | H12: =Proyectos!B483 -> 290270
A13: =Proyectos!A434 -> 2676418: MEJORAMIENTO DE UNA PLANTA PROCESADORA DE LECHE PARA LA ELABORACION DE QUESOS FRESCOS TIPO PARIA DE LA ASOCIACION DE PRODUCTORES AGROPECUARIOS VILLA ACASSO APROAVA, DISTRITO DE PILCUYO, PROVINCIA DE EL COLLAO, REGION DE PUNO | B13: =Proyectos!B434 -> 65438 | D13: =Proyectos!A460 -> 2627406: RENOVACION DE AMBIENTE COMPLEMENTARIO, AULA DE EDUCACION SUPERIOR PEDAGOGICA Y CERCO PERIMETRICO; ADQUISICION DE MOBILIARIO DE AULA DE EDUCACION SUPERIOR PEDAGOGICA; ADEMAS DE OTROS ACTIVOS EN EL(LA) INSTITUTO DE EDUCACION SUPERIOR PEDAGOGICA PUBLICO JULI DEL DISTRITO DE JULI, PROVINCIA CHUCUITO, DEPARTAMENTO PUNO | E13: =Proyectos!B460 -> 61203 | G13: =Proyectos!A484 -> 2599489: CONSTRUCCION DE CONSULTORIO; ADQUISICION DE EQUIPOS BIOMEDICOS Y MOBILIARIO CLINICO; EN EL(LA) HOSPITAL SANDIA DISTRITO DE SANDIA, PROVINCIA SANDIA, DEPARTAMENTO PUNO | H13: =Proyectos!B484 -> 1750696
A14: =Proyectos!A435 -> 2681133: MEJORAMIENTO DE LA PRODUCCION DE QUESOS TIPO PARIA PASTEURIZADO DE LA CENTRAL DE ASOCIACIONES GANADEROS LECHEROS Y AGRARIOS DEL DISTRITO DE VILQUE, DISTRITO DE VILQUE, PROVINCIA DE PUNO, REGION PUNO | B14: =Proyectos!B435 -> 2795 | D14: =Proyectos!A461 -> 2637997: MEJORAMIENTO DEL SERVICIO DE EDUCACION SECUNDARIA EN I.E. UMUCHI DISTRITO DE MOHO DE LA PROVINCIA DE MOHO DEL DEPARTAMENTO DE PUNO | E14: =Proyectos!B461 -> 304829 | G14: =Proyectos!A485 -> 2623878: MEJORAMIENTO DEL SERVICIO DE ATENCION DE SALUD BASICOS EN CABANILLA DISTRITO DE CABANILLA DE LA PROVINCIA DE LAMPA DEL DEPARTAMENTO DE PUNO | H14: =Proyectos!B485 -> 656461
... A21: =Proyectos!A442 -> 2717149: MEJORAMIENTO EN LA PRODUCCION DE HILOS ARTESANALES DE LA ASOCIACION DE PRODUCTORES DE CAMELIDOS SUDAMERICANOS, ARTESANAL Y AGRICOLA TIKARIY PAMPA DEL DIST, DISTRITO MACUSANI, PROVINCIA CARABAYA, REGION PUNO | B21: =Proyectos!B442 -> 158642 | D21: =Proyectos!A468 -> 2684028: ADQUISICION DE AMBULANCIA URBANA; EN ONCE ESTABLECIMIENTOS DE SALUD II.1, ESTABLECIMIENTOS DE SALUD II.2 A NIVEL DEPARTAMENTAL (PUNO) | E21: =Proyectos!B468 -> 31336 | G21: =Proyectos!A492 -> TOTAL | H21: =Proyectos!B492 -> 21146555
A22: =Proyectos!A443 -> 2717158: MEJORAMIENTO DE LA PRODUCCION DE PACAS EN LA ASOCIACION DE PRODUCTORES AGROPECUARIOS Y FORESTALES SAN PEDRO DE FRAYLIMA, DISTRITO DE AZANGARO, PROVINCIA AZANGARO Y DEPARTAMENTO DE PUNO | B22: =Proyectos!B443 -> 349792 | D22: =Proyectos!A469 -> TOTAL | E22: =Proyectos!B469 -> 9230249
A23: =Proyectos!A444 -> TOTAL | B23: =Proyectos!B444 -> 3453224

Sheet Ordenado Segun No Comprometido
A1: Proyecto | B1: PIA | C1: PIM | D1: Certificación | E1: Compromiso Anual | F1: Ejecución | I1: Avance % | J1: Saldo No Certificado | K1: Saldo No Comprometido
F2: Atención de Compromiso Mensual | G2: Devengado | H2: Girado
A3: 2279375: MEJORAMIENTO DE LOS SERVICIOS DE SALUD DEL HOSPITAL DE APOYO ILAVE, PROVINCIA DE EL COLLAO - REGION PUNO | B3: 54666680 | C3: 53759397 | D3: 53759397 | E3: 262914 | F3: 261343 | G3: 261343 | H3: 261343 | I3: 0.5 | J3: =C3-D3 -> 0 | K3: =C3-E3 -> 53496483
A4: 2278822: MEJORAMIENTO DE LOS SERVICIOS DE SALUD DEL HOSPITAL RAFAEL ORTIZ RAVINES DE JULI, PROVINCIA DE CHUCUITO - REGION PUNO | B4: 0 | C4: 41519761 | D4: 39201249 | E4: 10839279 | F4: 10652960 | G4: 10652960 | H4: 10642217 | I4: 25.7 | J4: =C4-D4 -> 2318512 | K4: =C4-E4 -> 30680482
A5: 2692290: ADQUISICION DE EQUIPO DE ANESTESIA, VENTILADOR MECANICO, SISTEMA DE CIRUGIA LAPAROSCOPICA Y SISTEMA DE VIDEO GASTROENDOSCOPIA; ADEMAS DE OTROS ACTIVOS EN EL(LA) HOSPITAL SAN MARTIN DE PORRES DISTRITO DE MACUSANI, PROVINCIA CARABAYA, DEPARTAMENTO PUNO | B5: 0 | C5: 13926334 | D5: 13763618 | E5: 242796 | F5: 209025 | G5: 182925 | H5: 182925 | I5: 1.3 | J5: =C5-D5 -> 162716 | K5: =C5-E5 -> 13683538
A6: 2470517: MEJORAMIENTO DE LOS SERVICIOS DE SALUD DEL CENTRO DE SALUD COPANI DE LA MICRO RED COPANI, RED DE SALUD YUNGUYO, DISTRITO DE COPANI - PROVINCIA DE YUNGUYO - DEPARTAMENTO DE PUNO | B6: 8000000 | C6: 7374992 | D6: 7374802 | E6: 0 | F6: 0 | G6: 0 | H6: 0 | I6: 0.0 | J6: =C6-D6 -> 190 | K6: =C6-E6 -> 7374992
A7: 2603148: MEJORAMIENTO DE LOS SERVICIOS DE APOYO AL DESARROLLO PRODUCTIVO EN 19 UNIDADES PRODUCTORAS 19 DISTRITOS DE 7 PROVINCIAS DEL DEPARTAMENTO DE PUNO | B7: 1000000 | C7: 12532522 | D7: 12187041 | E7: 5981488 | F7: 5042093 | G7: 3196291 | H7: 3117313 | I7: 25.5 | J7: =C7-D7 -> 345481 | K7: =C7-E7 -> 6551034
A8: 2685431: ADQUISICION DE AMBULANCIA URBANA, CAMIONETA, CAMION PLATAFORMA Y CAMION CISTERNA; ADEMAS DE OTROS ACTIVOS EN CINCO COMPAÑIA DE BOMBEROS A NIVEL DEPARTAMENTAL (PUNO) | B8: 5358341 | C8: 5281360 | D8: 4436688 | E8: 176910 | F8: 152395 | G8: 140517 | H8: 140517 | I8: 2.7 | J8: =C8-D8 -> 844672 | K8: =C8-E8 -> 5104450
A9: 2650340: ADQUISICION DE MESA DE OPERACIONES HIDRAULICA/ELECTRICA, ESTERILIZADOR CON GENERADOR ELECTRICO DE VAPOR (INS), EQUIPOS BIOMEDICOS Y COCHE DE PARO; ADEMAS DE OTROS ACTIVOS EN EL(LA) PUTINA DISTRITO DE PUTINA, PROVINCIA SAN ANTONIO DE PUTINA, DEPARTAMENTO PUNO | B9: 2421000 | C9: 8043406 | D9: 5895077 | E9: 3321108 | F9: 2959752 | G9: 2705628 | H9: 2121400 | I9: 33.6 | J9: =C9-D9 -> 2148329 | K9: =C9-E9 -> 4722298
A10: 2490087: MEJORAMIENTO Y AMPLIACION DE LOS SERVICIOS DE SALUD DEL ESTABLECIMIENTO DE SALUD NIVEL I- 4 DE LA LOCALIDAD DE TARACO, DISTRITO DE TARACO - PROVINCIA DE HUANCANE - DEPARTAMENTO DE PUNO | B10: 22181694 | C10: 8766661 | D10: 8493624 | E10: 4063268 | F10: 3880775 | G10: 3843826 | H10: 3810986 | I10: 43.8 | J10: =C10-D10 -> 273037 | K10: =C10-E10 -> 4703393
A11: 2284935: MEJORAMIENTO DEL SERVICIO EDUCATIVO EN LA IES POLITECNICO REGIONAL LOS ANDES, DISTRITO DE JULIACA, PROVINCIA DE SAN ROMAN - PUNO | B11: 15800000 | C11: 22276780 | D11: 17912911 | E11: 17717779 | F11: 16334346 | G11: 15417466 | H11: 14634837 | I11: 69.2 | J11: =C11-D11 -> 4363869 | K11: =C11-E11 -> 4559001
A12: 2646109: REPARACION DE TRIBUNA Y/O PALCO; CONSTRUCCION DE CAMPO DEPORTIVO Y TRIBUNA Y/O PALCO; EN EL(LA) ESTADIO MUNICIPAL DE JULI DISTRITO DE JULI, PROVINCIA CHUCUITO, DEPARTAMENTO PUNO | B12: 1556258 | C12: 4474004 | D12: 4473905 | E12: 0 | F12: 0 | G12: 0 | H12: 0 | I12: 0.0 | J12: =C12-D12 -> 99 | K12: =C12-E12 -> 4474004
A13: 2585543: MEJORAMIENTO Y AMPLIACION DEL SERVICIO DE EDUCACION SUPERIOR TECNOLOGICA EN EL INSTITUTO DE EDUCACION SUPERIOR TECNOLOGICO PUBLICO ACORA DEL DISTRITO DE ACORA DE LA PROVINCIA DE PUNO DEL DEPARTAMENTO DE PUNO | B13: 6000000 | C13: 15380884 | D13: 14270657 | E13: 11262957 | F13: 10694417 | G13: 9463521 | H13: 8712169 | I13: 61.5 | J13: =C13-D13 -> 1110227 | K13: =C13-E13 -> 4117927
A14: 2456529: MEJORAMIENTO DE LA CARRETERA PU 147, EMP. PE-34I JIPATA - EMP. PE-34I MOHO, DISTRITO DE MOHO - PROVINCIA DE MOHO - DEPARTAMENTO DE PUNO | B14: 15500800 | C14: 23143575 | D14: 22275711 | E14: 19031849 | F14: 15277445 | G14: 12059018 | H14: 11569861 | I14: 52.1 | J14: =C14-D14 -> 867864 | K14: =C14-E14 -> 4111726
... A402: 2700348: MEJORAMIENTO DEL SERVICIO DE EDUCACION PRIMARIA EN I.E. 70288 DISTRITO DE DESAGUADERO DE LA PROVINCIA DE CHUCUITO DEL DEPARTAMENTO DE PUNO | B402: 0 | C402: 140000 | D402: 140000 | E402: 140000 | F402: 131428 | G402: 131428 | H402: 131428 | I402: 93.9 | J402: =C402-D402 -> 0 | K402: =C402-E402 -> 0
