Workbook

Sheet Resumen
A1: Gasto corriente · UE 001 · mapeo de disponibilidad · al 08/10/2026
A2: Montos en soles. Calculado desde la hoja Base GC. Umbrales en Config.
A4: Gerencia / Oficina | B4: Metas | C4: PIM 2026 | D4: Certificación | E4: Compromiso anual | F4: Devengado | G4: Disponible (PIM − comprom.) | H4: PIM 2.1 Personal | I4: PIM 2.3 Bienes y serv. | J4: PIM 2.5 Otros gastos | K4: PIM · Sin certificar | L4: PIM · Solo certificado | M4: PIM · Parcialmente comprometido | N4: PIM · Mayormente comprometido | O4: PIM · Ejecutado | P4: PIM · Sin PIM
A5: SIN CLASIFICAR (completar en maestro.xlsx, hoja ClasifGC) | B5: =COUNTIFS('Base GC'!$B$5:$B$84,$A5) -> 80 | C5: =SUMIFS('Base GC'!$H$5:$H$84,'Base GC'!$B$5:$B$84,$A5) -> 99795382 | D5: =SUMIFS('Base GC'!$I$5:$I$84,'Base GC'!$B$5:$B$84,$A5) -> 81255206 | E5: =SUMIFS('Base GC'!$J$5:$J$84,'Base GC'!$B$5:$B$84,$A5) -> 72637604 | F5: =SUMIFS('Base GC'!$K$5:$K$84,'Base GC'!$B$5:$B$84,$A5) -> 56814243 | G5: =SUMIFS('Base GC'!$S$5:$S$84,'Base GC'!$B$5:$B$84,$A5) -> 27100845 | H5: =SUMIFS('Base GC'!$T$5:$T$84,'Base GC'!$B$5:$B$84,$A5) -> 20504461 | I5: =SUMIFS('Base GC'!$U$5:$U$84,'Base GC'!$B$5:$B$84,$A5) -> 40283830 | J5: =SUMIFS('Base GC'!$V$5:$V$84,'Base GC'!$B$5:$B$84,$A5) -> 136213 | K5: =SUMIFS('Base GC'!$H$5:$H$84,'Base GC'!$B$5:$B$84,$A5,'Base GC'!$Q$5:$Q$84,"Sin certificar") -> 7063833 | L5: =SUMIFS('Base GC'!$H$5:$H$84,'Base GC'!$B$5:$B$84,$A5,'Base GC'!$Q$5:$Q$84,"Solo certificado") -> 295200 | M5: =SUMIFS('Base GC'!$H$5:$H$84,'Base GC'!$B$5:$B$84,$A5,'Base GC'!$Q$5:$Q$84,"Parcialmente comprometido") -> 17902644 | N5: =SUMIFS('Base GC'!$H$5:$H$84,'Base GC'!$B$5:$B$84,$A5,'Base GC'!$Q$5:$Q$84,"Mayormente comprometido") -> 50557591 | O5: =SUMIFS('Base GC'!$H$5:$H$84,'Base GC'!$B$5:$B$84,$A5,'Base GC'!$Q$5:$Q$84,"Ejecutado") -> 23976114 | P5: =SUMIFS('Base GC'!$H$5:$H$84,'Base GC'!$B$5:$B$84,$A5,'Base GC'!$Q$5:$Q$84,"Sin PIM") -> 0
A6: TOTAL | B6: =SUM(B5:B5) -> 80 | C6: =SUM(C5:C5) -> 99795382 | D6: =SUM(D5:D5) -> 81255206 | E6: =SUM(E5:E5) -> 72637604 | F6: =SUM(F5:F5) -> 56814243 | G6: =SUM(G5:G5) -> 27100845 | H6: =SUM(H5:H5) -> 20504461 | I6: =SUM(I5:I5) -> 40283830 | ... P6: =SUM(P5:P5) -> 0

Sheet Gasto corriente
C1: ANEXO · GASTO CORRIENTE
B2: COMPORTAMIENTO DE EJECUCIÓN DE GASTO CORRIENTE (ACTIVIDADES) · UE 001 · AÑO FISCAL 2026 · AL 08/10/2026
A4: N° | B4: META | C4: ACTIVIDAD / META | D4: PIM 2026 (A) | E4: CERTIFICACIÓN (B) | F4: SALDO (A-B) | G4: COMPROMISO ANUAL | H4: DEVENGADO ( C ) | I4: SALDO (A-C) | J4: DEVEN % | K4: ESTADO SITUACIONAL | L4: DISPONIBILIDAD | M4: CERTIFICADO NO COMPROMETIDO | N4: DISPONIBLE (PIM − COMPROM.) | O4: PIM 2.1 Personal | P4: PIM 2.3 Bienes y servicios | Q4: PIM 2.5 Otros gastos | R4: PIM otras genéricas | S4: RO (00) | T4: RDR (09) | U4: DyT (13) | V4: FONCOR (15) | W4: CANON (18) | X4: Otros rubros | Y4: EJECUTORA (SILUCIA)
A5: SIN CLASIFICAR (completar en maestro.xlsx, hoja ClasifGC) | D5: =D6+D35+D44+D69+D72+D74+D76+D78+D80+D85+D90+D95+D97 -> 99795382 | E5: =E6+E35+E44+E69+E72+E74+E76+E78+E80+E85+E90+E95+E97 -> 81255206 | F5: =D5-E5 -> 18540176 | G5: =G6+G35+G44+G69+G72+G74+G76+G78+G80+G85+G90+G95+G97 -> 72637604 | H5: =H6+H35+H44+H69+H72+H74+H76+H78+H80+H85+H90+H95+H97 -> 56814243 | I5: =D5-H5 -> 42981139 | J5: =IF(D5=0,0,H5/D5) -> 0.56930733 | M5: =M6+M35+M44+M69+M72+M74+M76+M78+M80+M85+M90+M95+M97 -> 8617601.6 | N5: =N6+N35+N44+N69+N72+N74+N76+N78+N80+N85+N90+N95+N97 -> 27100845 | O5: =O6+O35+O44+O69+O72+O74+O76+O78+O80+O85+O90+O95+O97 -> 20504461 | P5: =P6+P35+P44+P69+P72+P74+P76+P78+P80+P85+P90+P95+P97 -> 40283830 | Q5: =Q6+Q35+Q44+Q69+Q72+Q74+Q76+Q78+Q80+Q85+Q90+Q95+Q97 -> 136213 | R5: =R6+R35+R44+R69+R72+R74+R76+R78+R80+R85+R90+R95+R97 -> 38870878 | S5: =S6+S35+S44+S69+S72+S74+S76+S78+S80+S85+S90+S95+S97 -> 0 | T5: =T6+T35+T44+T69+T72+T74+T76+T78+T80+T85+T90+T95+T97 -> 0 | ... X5: =X6+X35+X44+X69+X72+X74+X76+X78+X80+X85+X90+X95+X97 -> 0
A6: 03. PLANEAMIENTO, GESTION Y RESERVA DE CONTINGENCIA | D6: =SUM(D7:D34) -> 79496450 | E6: =SUM(E7:E34) -> 66080769 | F6: =D6-E6 -> 13415681 | G6: =SUM(G7:G34) -> 59157030 | H6: =SUM(H7:H34) -> 47648236 | I6: =D6-H6 -> 31848214 | J6: =IF(D6=0,0,H6/D6) -> 0.59937565 | M6: =SUM(M7:M34) -> 6923738.9 | N6: =SUM(N7:N34) -> 20285737 | O6: =SUM(O7:O34) -> 16486195 | P6: =SUM(P7:P34) -> 31052131 | Q6: =SUM(Q7:Q34) -> 135543 | R6: =SUM(R7:R34) -> 31822581 | S6: =SUM(S7:S34) -> 0 | T6: =SUM(T7:T34) -> 0 | ... X6: =SUM(X7:X34) -> 0
A7: =SUBTOTAL(103,$B$6:B7) -> 1 | B7: 486 | C7: TRANSFERENCIA DE RECURSOS PARA LA EJECUCION DE PROYECTOS DE INVERSION · TRANSFERENCIA FINANCIERA PARA PROYECTOS DE INVERSION | D7: ='Base GC'!H5 -> 21854668 | E7: ='Base GC'!I5 -> 21854668 | F7: =D7-E7 -> 0 | G7: ='Base GC'!J5 -> 21800985 | H7: ='Base GC'!K5 -> 21800985 | I7: =D7-H7 -> 53683 | J7: =IF(D7=0,0,H7/D7) -> 0.99754364 | K7: ='Base GC'!Q5 -> Ejecutado | L7: ='Base GC'!R5 -> No usar | M7: ='Base GC'!M5 -> 53683 | N7: ='Base GC'!S5 -> 0 | O7: ='Base GC'!T5 -> 0 | P7: ='Base GC'!U5 -> 0 | Q7: ='Base GC'!V5 -> 0 | R7: ='Base GC'!W5 -> 21854668 | S7: ='Base GC'!X5 -> s/d | T7: ='Base GC'!Y5 -> s/d | U7: ='Base GC'!Z5 -> s/d | ... Y7: ='Base GC'!AD5
A8: =SUBTOTAL(103,$B$6:B8) -> 2 | B8: 199 | C8: PLANEAMIENTO Y PRESUPUESTO · ACCIONES DE PLANEAMIENTO Y PRESUPUESTO | D8: ='Base GC'!H6 -> 14397156 | E8: ='Base GC'!I6 -> 8698687.6 | F8: =D8-E8 -> 5698468.4 | G8: ='Base GC'!J6 -> 6321785.8 | H8: ='Base GC'!K6 -> 1694723 | I8: =D8-H8 -> 12702433 | J8: =IF(D8=0,0,H8/D8) -> 0.11771235 | K8: ='Base GC'!Q6 -> Parcialmente comprometido | L8: ='Base GC'!R6 -> Parcial | M8: ='Base GC'!M6 -> 2376901.8 | N8: ='Base GC'!S6 -> 8075370.2 | O8: ='Base GC'!T6 -> 5491591 | P8: ='Base GC'!U6 -> 6984992 | Q8: ='Base GC'!V6 -> 0 | R8: ='Base GC'!W6 -> 1920573 | S8: ='Base GC'!X6 -> s/d | T8: ='Base GC'!Y6 -> s/d | U8: ='Base GC'!Z6 -> s/d | ... Y8: ='Base GC'!AD6 -> GASTO CORRIENTE
A9: =SUBTOTAL(103,$B$6:B9) -> 3 | B9: 203 | C9: GESTION ADMINISTRATIVA · MANTENIMIENTO Y REPARACION DE EQUIPO MECANICO | D9: ='Base GC'!H7 -> 11561677 | E9: ='Base GC'!I7 -> 10764477 | F9: =D9-E9 -> 797200.27 | G9: ='Base GC'!J7 -> 6753457.1 | H9: ='Base GC'!K7 -> 5863914.2 | I9: =D9-H9 -> 5697762.8 | J9: =IF(D9=0,0,H9/D9) -> 0.50718543 | K9: ='Base GC'!Q7 -> Mayormente comprometido | L9: ='Base GC'!R7 -> Difícil | M9: ='Base GC'!M7 -> 4011019.6 | N9: ='Base GC'!S7 -> 4808219.9 | O9: ='Base GC'!T7 -> 0 | P9: ='Base GC'!U7 -> 11442377 | Q9: ='Base GC'!V7 -> 0 | R9: ='Base GC'!W7 -> 119300 | S9: ='Base GC'!X7 -> s/d | T9: ='Base GC'!Y7 -> s/d | U9: ='Base GC'!Z7 -> s/d | ... Y9: ='Base GC'!AD7 -> GASTO CORRIENTE
A10: =SUBTOTAL(103,$B$6:B10) -> 4 | B10: 202 | C10: GESTION ADMINISTRATIVA | D10: ='Base GC'!H8 -> 8960842 | E10: ='Base GC'!I8 -> 8663999 | F10: =D10-E10 -> 296843.03 | G10: ='Base GC'!J8 -> 8547567.6 | H10: ='Base GC'!K8 -> 6519476.6 | I10: =D10-H10 -> 2441365.4 | J10: =IF(D10=0,0,H10/D10) -> 0.72755178 | K10: ='Base GC'!Q8 -> Mayormente comprometido | L10: ='Base GC'!R8 -> Difícil | M10: ='Base GC'!M8 -> 116431.38 | N10: ='Base GC'!S8 -> 413274.41 | O10: ='Base GC'!T8 -> 3202893 | P10: ='Base GC'!U8 -> 4644868 | Q10: ='Base GC'!V8 -> 58501 | R10: ='Base GC'!W8 -> 1054580 | S10: ='Base GC'!X8 -> s/d | T10: ='Base GC'!Y8 -> s/d | U10: ='Base GC'!Z8 -> s/d | ... Y10: ='Base GC'!AD8 -> GASTO CORRIENTE
A11: =SUBTOTAL(103,$B$6:B11) -> 5 | B11: 531 | C11: TRANSFERENCIA DE RECURSOS PARA LA EJECUCION DE ACTIVIDADES · TRANSFERENCIA FINANCIERA PARA ACTIVIDADES | D11: ='Base GC'!H9 -> 4661250 | E11: ='Base GC'!I9 -> 0 | F11: =D11-E11 -> 4661250 | G11: ='Base GC'!J9 -> 0 | H11: ='Base GC'!K9 -> 0 | I11: =D11-H11 -> 4661250 | J11: =IF(D11=0,0,H11/D11) -> 0 | K11: ='Base GC'!Q9 -> Sin certificar | L11: ='Base GC'!R9 -> Disponible | M11: ='Base GC'!M9 -> 0 | N11: ='Base GC'!S9 -> 4661250 | O11: ='Base GC'!T9 -> 0 | P11: ='Base GC'!U9 -> 0 | Q11: ='Base GC'!V9 -> 0 | R11: ='Base GC'!W9 -> 4661250 | S11: ='Base GC'!X9 -> s/d | T11: ='Base GC'!Y9 -> s/d | U11: ='Base GC'!Z9 -> s/d | ... Y11: ='Base GC'!AD9
A12: =SUBTOTAL(103,$B$6:B12) -> 6 | B12: 300 | C12: SUPERVISION Y CONTROL · SEGUIMIENTO DE FISCALIZACION DE LOS CONSEJOS REGIONALES Y CONCEJOS MUNICIPALES A NIVEL NACIONAL | D12: ='Base GC'!H10 -> 3003455 | E12: ='Base GC'!I10 -> 2361957.3 | F12: =D12-E12 -> 641497.68 | G12: ='Base GC'!J10 -> 2312089.7 | H12: ='Base GC'!K10 -> 1164173.1 | I12: =D12-H12 -> 1839281.9 | J12: =IF(D12=0,0,H12/D12) -> 0.38761131 | K12: ='Base GC'!Q10 -> Mayormente comprometido | L12: ='Base GC'!R10 -> Difícil | M12: ='Base GC'!M10 -> 49867.66 | N12: ='Base GC'!S10 -> 691365.34 | O12: ='Base GC'!T10 -> 1074678 | P12: ='Base GC'!U10 -> 1928777 | Q12: ='Base GC'!V10 -> 0 | R12: ='Base GC'!W10 -> 0 | S12: ='Base GC'!X10 -> s/d | T12: ='Base GC'!Y10 -> s/d | U12: ='Base GC'!Z10 -> s/d | ... Y12: ='Base GC'!AD10 -> GASTO CORRIENTE
A13: =SUBTOTAL(103,$B$6:B13) -> 7 | B13: 291 | C13: DESARROLLO SOCIAL REGIONAL · PROMOCION Y CONCERTACION DE INICIATIVAS SOCIALES | D13: ='Base GC'!H11 -> 2564683 | E13: ='Base GC'!I11 -> 2101980.8 | F13: =D13-E13 -> 462702.25 | G13: ='Base GC'!J11 -> 2022558.7 | H13: ='Base GC'!K11 -> 1443358.5 | I13: =D13-H13 -> 1121324.5 | J13: =IF(D13=0,0,H13/D13) -> 0.56278243 | K13: ='Base GC'!Q11 -> Mayormente comprometido | L13: ='Base GC'!R11 -> Difícil | M13: ='Base GC'!M11 -> 79422 | N13: ='Base GC'!S11 -> 542124.25 | O13: ='Base GC'!T11 -> 502598 | P13: ='Base GC'!U11 -> 2037085 | Q13: ='Base GC'!V11 -> 0 | R13: ='Base GC'!W11 -> 25000 | S13: ='Base GC'!X11 -> s/d | T13: ='Base GC'!Y11 -> s/d | U13: ='Base GC'!Z11 -> s/d | ... Y13: ='Base GC'!AD11 -> GASTO CORRIENTE
A14: =SUBTOTAL(103,$B$6:B14) -> 8 | B14: 298 | C14: PRESERVACION Y DIFUSION DE ACERVOS BIBLIOGRAFICOS, DOCUMENTALES Y ARCHIVISTICOS · CONSERVACION Y CATALOGACION DE ARCHIVOS Y DOCUMENTOS | D14: ='Base GC'!H12 -> 1623842 | E14: ='Base GC'!I12 -> 1611611.3 | F14: =D14-E14 -> 12230.72 | G14: ='Base GC'!J12 -> 1583926.5 | H14: ='Base GC'!K12 -> 1213592.8 | I14: =D14-H14 -> 410249.25 | J14: =IF(D14=0,0,H14/D14) -> 0.74735889 | K14: ='Base GC'!Q12 -> Mayormente comprometido | L14: ='Base GC'!R12 -> Difícil | M14: ='Base GC'!M12 -> 27684.74 | N14: ='Base GC'!S12 -> 39915.46 | O14: ='Base GC'!T12 -> 1076197 | P14: ='Base GC'!U12 -> 540945 | Q14: ='Base GC'!V12 -> 0 | R14: ='Base GC'!W12 -> 6700 | S14: ='Base GC'!X12 -> s/d | T14: ='Base GC'!Y12 -> s/d | U14: ='Base GC'!Z12 -> s/d | ... Y14: ='Base GC'!AD12 -> GASTO CORRIENTE
A15: =SUBTOTAL(103,$B$6:B15) -> 9 | B15: 301 | C15: DIRECCION Y GESTION REGIONAL | D15: ='Base GC'!H13 -> 1255771 | E15: ='Base GC'!I13 -> 1182688.9 | F15: =D15-E15 -> 73082.14 | G15: ='Base GC'!J13 -> 1102819 | H15: ='Base GC'!K13 -> 800666.11 | I15: =D15-H15 -> 455104.89 | J15: =IF(D15=0,0,H15/D15) -> 0.63758927 | K15: ='Base GC'!Q13 -> Mayormente comprometido | L15: ='Base GC'!R13 -> Difícil | M15: ='Base GC'!M13 -> 79869.88 | N15: ='Base GC'!S13 -> 152952.02 | O15: ='Base GC'!T13 -> 493713 | P15: ='Base GC'!U13 -> 692246 | Q15: ='Base GC'!V13 -> 0 | R15: ='Base GC'!W13 -> 69812 | S15: ='Base GC'!X13 -> s/d | T15: ='Base GC'!Y13 -> s/d | U15: ='Base GC'!Z13 -> s/d | ... Y15: ='Base GC'!AD13 -> GASTO CORRIENTE
A16: =SUBTOTAL(103,$B$6:B16) -> 10 | B16: 503 | C16: TRANSFERENCIA DE RECURSOS PARA LA EJECUCION DE PROYECTOS DE INVERSION · TRANSFERENCIA FINANCIERA PARA PROYECTOS DE INVERSION | D16: ='Base GC'!H14 -> 1210000 | E16: ='Base GC'!I14 -> 1210000 | F16: =D16-E16 -> 0 | G16: ='Base GC'!J14 -> 1210000 | H16: ='Base GC'!K14 -> 1210000 | I16: =D16-H16 -> 0 | J16: =IF(D16=0,0,H16/D16) -> 1 | K16: ='Base GC'!Q14 -> Ejecutado | L16: ='Base GC'!R14 -> No usar | M16: ='Base GC'!M14 -> 0 | N16: ='Base GC'!S14 -> 0 | O16: ='Base GC'!T14 -> 0 | P16: ='Base GC'!U14 -> 0 | Q16: ='Base GC'!V14 -> 0 | R16: ='Base GC'!W14 -> 1210000 | S16: ='Base GC'!X14 -> s/d | T16: ='Base GC'!Y14 -> s/d | U16: ='Base GC'!Z14 -> s/d | ... Y16: ='Base GC'!AD14
A17: =SUBTOTAL(103,$B$6:B17) -> 11 | B17: 293 | C17: GESTION DE LA INFRAESTRUCTURA · APOYO PARA EL DESARROLLO DE LOS PROYECTOS DE INVERSION | D17: ='Base GC'!H15 -> 1103261 | E17: ='Base GC'!I15 -> 1059124.8 | F17: =D17-E17 -> 44136.2 | G17: ='Base GC'!J15 -> 1024183.3 | H17: ='Base GC'!K15 -> 825567.54 | I17: =D17-H17 -> 277693.46 | J17: =IF(D17=0,0,H17/D17) -> 0.74829758 | K17: ='Base GC'!Q15 -> Mayormente comprometido | L17: ='Base GC'!R15 -> Difícil | M17: ='Base GC'!M15 -> 34941.51 | N17: ='Base GC'!S15 -> 79077.71 | O17: ='Base GC'!T15 -> 881261 | P17: ='Base GC'!U15 -> 222000 | Q17: ='Base GC'!V15 -> 0 | R17: ='Base GC'!W15 -> 0 | S17: ='Base GC'!X15 -> s/d | T17: ='Base GC'!Y15 -> s/d | U17: ='Base GC'!Z15 -> s/d | ... Y17: ='Base GC'!AD15 -> GASTO CORRIENTE
A18: =SUBTOTAL(103,$B$6:B18) -> 12 | B18: 289 | C18: ASESORAMIENTO Y GESTION DEL MEDIO AMBIENTE · PRESERVACION DEL MEDIO AMBIENTE Y AREAS NATURALES | D18: ='Base GC'!H16 -> 993332 | E18: ='Base GC'!I16 -> 906092.54 | F18: =D18-E18 -> 87239.46 | G18: ='Base GC'!J16 -> 901270.68 | H18: ='Base GC'!K16 -> 644188.62 | I18: =D18-H18 -> 349143.38 | J18: =IF(D18=0,0,H18/D18) -> 0.6485129 | K18: ='Base GC'!Q16 -> Mayormente comprometido | L18: ='Base GC'!R16 -> Difícil | M18: ='Base GC'!M16 -> 4821.86 | N18: ='Base GC'!S16 -> 92061.32 | O18: ='Base GC'!T16 -> 643691 | P18: ='Base GC'!U16 -> 349641 | Q18: ='Base GC'!V16 -> 0 | R18: ='Base GC'!W16 -> 0 | S18: ='Base GC'!X16 -> s/d | T18: ='Base GC'!Y16 -> s/d | U18: ='Base GC'!Z16 -> s/d | ... Y18: ='Base GC'!AD16 -> GASTO CORRIENTE
... A34: =SUBTOTAL(103,$B$6:B34) -> 28 | B34: 198 | C34: PLANEAMIENTO Y PRESUPUESTO · CONDUCCION, SUPERVISION Y EVALUACION DE LOS PLANES Y PROGRAMAS, PRESUPUESTO Y COOPERACION TECNICA | D34: ='Base GC'!H32 -> 0 | E34: ='Base GC'!I32 -> 0 | F34: =D34-E34 -> 0 | G34: ='Base GC'!J32 -> 0 | H34: ='Base GC'!K32 -> 0 | I34: =D34-H34 -> 0 | J34: =IF(D34=0,0,H34/D34) -> 0 | K34: ='Base GC'!Q32 -> Sin PIM | L34: ='Base GC'!R32 -> Sin PIM | M34: ='Base GC'!M32 -> 0 | N34: ='Base GC'!S32 -> 0 | O34: ='Base GC'!T32 -> 0 | P34: ='Base GC'!U32 -> 0 | Q34: ='Base GC'!V32 -> 0 | R34: ='Base GC'!W32 -> 0 | S34: ='Base GC'!X32 -> s/d | T34: ='Base GC'!Y32 -> s/d | U34: ='Base GC'!Z32 -> s/d | ... Y34: ='Base GC'!AD32 -> GASTO CORRIENTE
A35: 05. ORDEN PUBLICO Y SEGURIDAD | D35: =SUM(D36:D43) -> 3066466 | E35: =SUM(E36:E43) -> 2624320.9 | F35: =D35-E35 -> 442145.1 | G35: =SUM(G36:G43) -> 1890446.7 | H35: =SUM(H36:H43) -> 1404527.2 | I35: =D35-H35 -> 1661938.8 | J35: =IF(D35=0,0,H35/D35) -> 0.45802796 | M35: =SUM(M36:M43) -> 733874.22 | N35: =SUM(N36:N43) -> 1172769.3 | O35: =SUM(O36:O43) -> 393085 | P35: =SUM(P36:P43) -> 1390227 | Q35: =SUM(Q36:Q43) -> 0 | R35: =SUM(R36:R43) -> 1283154 | S35: =SUM(S36:S43) -> 0 | T35: =SUM(T36:T43) -> 0 | ... X35: =SUM(X36:X43) -> 0
A36: =SUBTOTAL(103,$B$6:B36) -> 29 | B36: 11 | C36: ADMINISTRACION Y ALMACENAMIENTO DE KITS PARA LA ASISTENCIA FRENTE A EMERGENCIAS Y DESASTRES | D36: ='Base GC'!H33 -> 1428319 | E36: ='Base GC'!I33 -> 1363163.7 | F36: =D36-E36 -> 65155.28 | G36: ='Base GC'!J33 -> 645131.4 | H36: ='Base GC'!K33 -> 522691.81 | I36: =D36-H36 -> 905627.19 | J36: =IF(D36=0,0,H36/D36) -> 0.36594893 | K36: ='Base GC'!Q33 -> Parcialmente comprometido | L36: ='Base GC'!R33 -> Parcial | M36: ='Base GC'!M33 -> 718032.32 | N36: ='Base GC'!S33 -> 783187.6 | O36: ='Base GC'!T33 -> 0 | P36: ='Base GC'!U33 -> 148165 | Q36: ='Base GC'!V33 -> 0 | R36: ='Base GC'!W33 -> 1280154 | S36: ='Base GC'!X33 -> s/d | T36: ='Base GC'!Y33 -> s/d | U36: ='Base GC'!Z33 -> s/d | ... Y36: ='Base GC'!AD33 -> GASTO CORRIENTE
A37: =SUBTOTAL(103,$B$6:B37) -> 30 | B37: 12 | C37: DESARROLLO DE LOS CENTROS Y ESPACIOS DE MONITOREO DE EMERGENCIAS Y DESASTRES | D37: ='Base GC'!H34 -> 1171471 | E37: ='Base GC'!I34 -> 912826.18 | F37: =D37-E37 -> 258644.82 | G37: ='Base GC'!J34 -> 896984.28 | H37: ='Base GC'!K34 -> 632174.37 | I37: =D37-H37 -> 539296.63 | J37: =IF(D37=0,0,H37/D37) -> 0.5396415 | K37: ='Base GC'!Q34 -> Mayormente comprometido | L37: ='Base GC'!R34 -> Difícil | M37: ='Base GC'!M34 -> 15841.9 | N37: ='Base GC'!S34 -> 274486.72 | O37: ='Base GC'!T34 -> 393085 | P37: ='Base GC'!U34 -> 775386 | Q37: ='Base GC'!V34 -> 0 | R37: ='Base GC'!W34 -> 3000 | S37: ='Base GC'!X34 -> s/d | T37: ='Base GC'!Y34 -> s/d | U37: ='Base GC'!Z34 -> s/d | ... Y37: ='Base GC'!AD34 -> GASTO CORRIENTE
A38: =SUBTOTAL(103,$B$6:B38) -> 31 | B38: 15 | C38: FORMACION Y CAPACITACION EN MATERIA DE GESTION DE RIESGO DE DESASTRES Y ADAPTACION AL CAMBIO CLIMATICO · FORMACION Y CAPACITACION EN MATERIA DE GESTION DE RIESGO DE DESASTRES | D38: ='Base GC'!H35 -> 373040 | E38: ='Base GC'!I35 -> 287567 | F38: =D38-E38 -> 85473 | G38: ='Base GC'!J35 -> 287567 | H38: ='Base GC'!K35 -> 193397 | I38: =D38-H38 -> 179643 | J38: =IF(D38=0,0,H38/D38) -> 0.51843502 | K38: ='Base GC'!Q35 -> Mayormente comprometido | L38: ='Base GC'!R35 -> Difícil | M38: ='Base GC'!M35 -> 0 | N38: ='Base GC'!S35 -> 85473 | O38: ='Base GC'!T35 -> 0 | P38: ='Base GC'!U35 -> 373040 | Q38: ='Base GC'!V35 -> 0 | R38: ='Base GC'!W35 -> 0 | S38: ='Base GC'!X35 -> s/d | T38: ='Base GC'!Y35 -> s/d | U38: ='Base GC'!Z35 -> s/d | ... Y38: ='Base GC'!AD35 -> GASTO CORRIENTE
A39: =SUBTOTAL(103,$B$6:B39) -> 32 | B39: 9 | C39: DESARROLLO DE SIMULACROS EN GESTION REACTIVA | D39: ='Base GC'!H36 -> 25600 | E39: ='Base GC'!I36 -> 12638 | F39: =D39-E39 -> 12962 | G39: ='Base GC'!J36 -> 12638 | H39: ='Base GC'!K36 -> 8138 | I39: =D39-H39 -> 17462 | J39: =IF(D39=0,0,H39/D39) -> 0.31789062 | K39: ='Base GC'!Q36 -> Parcialmente comprometido | L39: ='Base GC'!R36 -> Parcial | M39: ='Base GC'!M36 -> 0 | N39: ='Base GC'!S36 -> 12962 | O39: ='Base GC'!T36 -> 0 | P39: ='Base GC'!U36 -> 25600 | Q39: ='Base GC'!V36 -> 0 | R39: ='Base GC'!W36 -> 0 | S39: ='Base GC'!X36 -> s/d | T39: ='Base GC'!Y36 -> s/d | U39: ='Base GC'!Z36 -> s/d | ... Y39: ='Base GC'!AD36 -> GASTO CORRIENTE
A40: =SUBTOTAL(103,$B$6:B40) -> 33 | B40: 10 | C40: IMPLEMENTACION DE BRIGADAS PARA LA ATENCION FRENTE A EMERGENCIAS Y DESASTRES | D40: ='Base GC'!H37 -> 25600 | E40: ='Base GC'!I37 -> 8940 | F40: =D40-E40 -> 16660 | G40: ='Base GC'!J37 -> 8940 | H40: ='Base GC'!K37 -> 8940 | I40: =D40-H40 -> 16660 | J40: =IF(D40=0,0,H40/D40) -> 0.34921875 | K40: ='Base GC'!Q37 -> Parcialmente comprometido | L40: ='Base GC'!R37 -> Parcial | M40: ='Base GC'!M37 -> 0 | N40: ='Base GC'!S37 -> 16660 | O40: ='Base GC'!T37 -> 0 | P40: ='Base GC'!U37 -> 25600 | Q40: ='Base GC'!V37 -> 0 | R40: ='Base GC'!W37 -> 0 | S40: ='Base GC'!X37 -> s/d | T40: ='Base GC'!Y37 -> s/d | U40: ='Base GC'!Z37 -> s/d | ... Y40: ='Base GC'!AD37 -> GASTO CORRIENTE
A41: =SUBTOTAL(103,$B$6:B41) -> 34 | B41: 16 | C41: DESARROLLO DE CAMPAÑAS COMUNICACIONALES PARA LA GESTION DEL RIESGO DE DESASTRES | D41: ='Base GC'!H38 -> 22528 | E41: ='Base GC'!I38 -> 20570 | F41: =D41-E41 -> 1958 | G41: ='Base GC'!J38 -> 20570 | H41: ='Base GC'!K38 -> 20570 | I41: =D41-H41 -> 1958 | J41: =IF(D41=0,0,H41/D41) -> 0.91308594 | K41: ='Base GC'!Q38 -> Ejecutado | L41: ='Base GC'!R38 -> No usar | M41: ='Base GC'!M38 -> 0 | N41: ='Base GC'!S38 -> 0 | O41: ='Base GC'!T38 -> 0 | P41: ='Base GC'!U38 -> 22528 | Q41: ='Base GC'!V38 -> 0 | R41: ='Base GC'!W38 -> 0 | S41: ='Base GC'!X38 -> s/d | T41: ='Base GC'!Y38 -> s/d | U41: ='Base GC'!Z38 -> s/d | ... Y41: ='Base GC'!AD38 -> GASTO CORRIENTE
A42: =SUBTOTAL(103,$B$6:B42) -> 35 | B42: 8 | C42: DESARROLLO DE INSTRUMENTOS ESTRATEGICOS PARA LA GESTION DEL RIESGO DE DESASTRES | D42: ='Base GC'!H39 -> 13047 | E42: ='Base GC'!I39 -> 11755 | F42: =D42-E42 -> 1292 | G42: ='Base GC'!J39 -> 11755 | H42: ='Base GC'!K39 -> 11755 | I42: =D42-H42 -> 1292 | J42: =IF(D42=0,0,H42/D42) -> 0.9009734 | K42: ='Base GC'!Q39 -> Ejecutado | L42: ='Base GC'!R39 -> No usar | M42: ='Base GC'!M39 -> 0 | N42: ='Base GC'!S39 -> 0 | O42: ='Base GC'!T39 -> 0 | P42: ='Base GC'!U39 -> 13047 | Q42: ='Base GC'!V39 -> 0 | R42: ='Base GC'!W39 -> 0 | S42: ='Base GC'!X39 -> s/d | T42: ='Base GC'!Y39 -> s/d | U42: ='Base GC'!Z39 -> s/d | ... Y42: ='Base GC'!AD39 -> GASTO CORRIENTE
A43: =SUBTOTAL(103,$B$6:B43) -> 36 | B43: 14 | C43: ACCESO A LA INFORMACION Y OPERATIVIDAD DEL SISTEMA DE INFORMACION EN GESTION DEL RIESGO DE DESASTRES | D43: ='Base GC'!H40 -> 6861 | E43: ='Base GC'!I40 -> 6861 | F43: =D43-E43 -> 0 | G43: ='Base GC'!J40 -> 6861 | H43: ='Base GC'!K40 -> 6861 | I43: =D43-H43 -> 0 | J43: =IF(D43=0,0,H43/D43) -> 1 | K43: ='Base GC'!Q40 -> Ejecutado | L43: ='Base GC'!R40 -> No usar | M43: ='Base GC'!M40 -> 0 | N43: ='Base GC'!S40 -> 0 | O43: ='Base GC'!T40 -> 0 | P43: ='Base GC'!U40 -> 6861 | Q43: ='Base GC'!V40 -> 0 | R43: ='Base GC'!W40 -> 0 | S43: ='Base GC'!X40 -> s/d | T43: ='Base GC'!Y40 -> s/d | U43: ='Base GC'!Z40 -> s/d | ... Y43: ='Base GC'!AD40 -> GASTO CORRIENTE
A44: 07. (sin nombre) | D44: =SUM(D45:D68) -> 3494452 | E44: =SUM(E45:E68) -> 2261872.3 | F44: =D44-E44 -> 1232579.7 | G44: =SUM(G45:G68) -> 2039455.2 | H44: =SUM(H45:H68) -> 1440842.2 | I44: =D44-H44 -> 2053609.8 | J44: =IF(D44=0,0,H44/D44) -> 0.41232279 | M44: =SUM(M45:M68) -> 222417.12 | N44: =SUM(N45:N68) -> 1454996.8 | O44: =SUM(O45:O68) -> 1496631 | P44: =SUM(P45:P68) -> 1667131 | Q44: =SUM(Q45:Q68) -> 670 | R44: =SUM(R45:R68) -> 330020 | S44: =SUM(S45:S68) -> 0 | T44: =SUM(T45:T68) -> 0 | ... X44: =SUM(X45:X68) -> 0
A45: =SUBTOTAL(103,$B$6:B45) -> 37 | B45: 75 | C45: GESTION DEL PROGRAMA | D45: ='Base GC'!H41 -> 1380688 | E45: ='Base GC'!I41 -> 1355769.9 | F45: =D45-E45 -> 24918.08 | G45: ='Base GC'!J41 -> 1154820.3 | H45: ='Base GC'!K41 -> 928988.41 | I45: =D45-H45 -> 451699.59 | J45: =IF(D45=0,0,H45/D45) -> 0.67284456 | K45: ='Base GC'!Q41 -> Mayormente comprometido | L45: ='Base GC'!R41 -> Difícil | M45: ='Base GC'!M41 -> 200949.6 | N45: ='Base GC'!S41 -> 225867.68 | O45: ='Base GC'!T41 -> 964264 | P45: ='Base GC'!U41 -> 415754 | Q45: ='Base GC'!V41 -> 670 | R45: ='Base GC'!W41 -> 0 | S45: ='Base GC'!X41 -> s/d | T45: ='Base GC'!Y41 -> s/d | U45: ='Base GC'!Z41 -> s/d | ... Y45: ='Base GC'!AD41 -> GASTO CORRIENTE
A46: =SUBTOTAL(103,$B$6:B46) -> 38 | B46: 451 | C46: GESTION DEL PROGRAMA | D46: ='Base GC'!H42 -> 375920 | E46: ='Base GC'!I42 -> 164385.96 | F46: =D46-E46 -> 211534.04 | G46: ='Base GC'!J42 -> 150224.39 | H46: ='Base GC'!K42 -> 82704.39 | I46: =D46-H46 -> 293215.61 | J46: =IF(D46=0,0,H46/D46) -> 0.22000529 | K46: ='Base GC'!Q42 -> Parcialmente comprometido | L46: ='Base GC'!R42 -> Parcial | M46: ='Base GC'!M42 -> 14161.57 | N46: ='Base GC'!S42 -> 225695.61 | O46: ='Base GC'!T42 -> 154800 | P46: ='Base GC'!U42 -> 206120 | Q46: ='Base GC'!V42 -> 0 | R46: ='Base GC'!W42 -> 15000 | S46: ='Base GC'!X42 -> s/d | T46: ='Base GC'!Y42 -> s/d | U46: ='Base GC'!Z42 -> s/d | ... Y46: ='Base GC'!AD42 -> GASTO CORRIENTE
A47: =SUBTOTAL(103,$B$6:B47) -> 39 | B47: 450 | C47: GESTION DEL PROGRAMA | D47: ='Base GC'!H43 -> 342413 | E47: ='Base GC'!I43 -> 37700 | F47: =D47-E47 -> 304713 | G47: ='Base GC'!J43 -> 37700 | H47: ='Base GC'!K43 -> 11600 | I47: =D47-H47 -> 330813 | J47: =IF(D47=0,0,H47/D47) -> 0.033877218 | K47: ='Base GC'!Q43 -> Parcialmente comprometido | L47: ='Base GC'!R43 -> Parcial | M47: ='Base GC'!M43 -> 0 | N47: ='Base GC'!S43 -> 304713 | O47: ='Base GC'!T43 -> 0 | P47: ='Base GC'!U43 -> 71413 | Q47: ='Base GC'!V43 -> 0 | R47: ='Base GC'!W43 -> 271000 | S47: ='Base GC'!X43 -> s/d | T47: ='Base GC'!Y43 -> s/d | U47: ='Base GC'!Z43 -> s/d | ... Y47: ='Base GC'!AD43 -> GASTO CORRIENTE
A48: =SUBTOTAL(103,$B$6:B48) -> 40 | B48: 435 | C48: FORMALIZACION DE LA FUERZA LABORAL | D48: ='Base GC'!H44 -> 214500 | E48: ='Base GC'!I44 -> 141630 | F48: =D48-E48 -> 72870 | G48: ='Base GC'!J44 -> 141630 | H48: ='Base GC'!K44 -> 85710 | I48: =D48-H48 -> 128790 | J48: =IF(D48=0,0,H48/D48) -> 0.39958042 | K48: ='Base GC'!Q44 -> Mayormente comprometido | L48: ='Base GC'!R44 -> Difícil | M48: ='Base GC'!M44 -> 0 | N48: ='Base GC'!S44 -> 72870 | O48: ='Base GC'!T44 -> 0 | P48: ='Base GC'!U44 -> 214500 | Q48: ='Base GC'!V44 -> 0 | R48: ='Base GC'!W44 -> 0 | S48: ='Base GC'!X44 -> s/d | T48: ='Base GC'!Y44 -> s/d | U48: ='Base GC'!Z44 -> s/d | ... Y48: ='Base GC'!AD44 -> GASTO CORRIENTE
A49: =SUBTOTAL(103,$B$6:B49) -> 41 | B49: 438 | C49: ABSOLUCION DE CONSULTAS EN MATERIAS LABORALES | D49: ='Base GC'!H45 -> 181963 | E49: ='Base GC'!I45 -> 37586 | F49: =D49-E49 -> 144377 | G49: ='Base GC'!J45 -> 37586 | H49: ='Base GC'!K45 -> 27386 | I49: =D49-H49 -> 154577 | J49: =IF(D49=0,0,H49/D49) -> 0.15050312 | K49: ='Base GC'!Q45 -> Parcialmente comprometido | L49: ='Base GC'!R45 -> Parcial | M49: ='Base GC'!M45 -> 0 | N49: ='Base GC'!S45 -> 144377 | O49: ='Base GC'!T45 -> 71191 | P49: ='Base GC'!U45 -> 84372 | Q49: ='Base GC'!V45 -> 0 | R49: ='Base GC'!W45 -> 26400 | S49: ='Base GC'!X45 -> s/d | T49: ='Base GC'!Y45 -> s/d | U49: ='Base GC'!Z45 -> s/d | ... Y49: ='Base GC'!AD45 -> GASTO CORRIENTE
A50: =SUBTOTAL(103,$B$6:B50) -> 42 | B50: 452 | C50: ATENCION DE SERVICIOS DE INTERMEDIACION LABORAL | D50: ='Base GC'!H46 -> 168357 | E50: ='Base GC'!I46 -> 56500 | F50: =D50-E50 -> 111857 | G50: ='Base GC'!J46 -> 56500 | H50: ='Base GC'!K46 -> 56500 | I50: =D50-H50 -> 111857 | J50: =IF(D50=0,0,H50/D50) -> 0.33559638 | K50: ='Base GC'!Q46 -> Parcialmente comprometido | L50: ='Base GC'!R46 -> Parcial | M50: ='Base GC'!M46 -> 0 | N50: ='Base GC'!S46 -> 111857 | O50: ='Base GC'!T46 -> 0 | P50: ='Base GC'!U46 -> 168357 | Q50: ='Base GC'!V46 -> 0 | R50: ='Base GC'!W46 -> 0 | S50: ='Base GC'!X46 -> s/d | T50: ='Base GC'!Y46 -> s/d | U50: ='Base GC'!Z46 -> s/d | ... Y50: ='Base GC'!AD46 -> GASTO CORRIENTE
A51: =SUBTOTAL(103,$B$6:B51) -> 43 | B51: 84 | C51: ATENCION DE SERVICIOS DE INTERMEDIACION LABORAL | D51: ='Base GC'!H47 -> 103873 | E51: ='Base GC'!I47 -> 98503 | F51: =D51-E51 -> 5370 | G51: ='Base GC'!J47 -> 98503 | H51: ='Base GC'!K47 -> 65331.27 | I51: =D51-H51 -> 38541.73 | J51: =IF(D51=0,0,H51/D51) -> 0.62895334 | K51: ='Base GC'!Q47 -> Mayormente comprometido | L51: ='Base GC'!R47 -> Difícil | M51: ='Base GC'!M47 -> 0 | N51: ='Base GC'!S47 -> 5370 | O51: ='Base GC'!T47 -> 85873 | P51: ='Base GC'!U47 -> 18000 | Q51: ='Base GC'!V47 -> 0 | R51: ='Base GC'!W47 -> 0 | S51: ='Base GC'!X47 -> s/d | T51: ='Base GC'!Y47 -> s/d | U51: ='Base GC'!Z47 -> s/d | ... Y51: ='Base GC'!AD47 -> GASTO CORRIENTE
A52: =SUBTOTAL(103,$B$6:B52) -> 44 | B52: 78 | C52: ABSOLUCION DE CONSULTAS EN MATERIAS LABORALES | D52: ='Base GC'!H48 -> 96920 | E52: ='Base GC'!I48 -> 93005.68 | F52: =D52-E52 -> 3914.32 | G52: ='Base GC'!J48 -> 92684.07 | H52: ='Base GC'!K48 -> 28863.58 | I52: =D52-H52 -> 68056.42 | J52: =IF(D52=0,0,H52/D52) -> 0.2978083 | K52: ='Base GC'!Q48 -> Mayormente comprometido | L52: ='Base GC'!R48 -> Difícil | M52: ='Base GC'!M48 -> 321.61 | N52: ='Base GC'!S48 -> 4235.93 | O52: ='Base GC'!T48 -> 90840 | P52: ='Base GC'!U48 -> 6080 | Q52: ='Base GC'!V48 -> 0 | R52: ='Base GC'!W48 -> 0 | S52: ='Base GC'!X48 -> s/d | T52: ='Base GC'!Y48 -> s/d | U52: ='Base GC'!Z48 -> s/d | ... Y52: ='Base GC'!AD48 -> GASTO CORRIENTE
A53: =SUBTOTAL(103,$B$6:B53) -> 45 | B53: 442 | C53: ABSOLUCION DE CONSULTAS EN MATERIAS LABORALES | D53: ='Base GC'!H49 -> 85775 | E53: ='Base GC'!I49 -> 26733.45 | F53: =D53-E53 -> 59041.55 | G53: ='Base GC'!J49 -> 26733.45 | H53: ='Base GC'!K49 -> 14233.45 | I53: =D53-H53 -> 71541.55 | J53: =IF(D53=0,0,H53/D53) -> 0.16593938 | K53: ='Base GC'!Q49 -> Parcialmente comprometido | L53: ='Base GC'!R49 -> Parcial | M53: ='Base GC'!M49 -> 0 | N53: ='Base GC'!S49 -> 59041.55 | O53: ='Base GC'!T49 -> 39568 | P53: ='Base GC'!U49 -> 46207 | Q53: ='Base GC'!V49 -> 0 | R53: ='Base GC'!W49 -> 0 | S53: ='Base GC'!X49 -> s/d | T53: ='Base GC'!Y49 -> s/d | U53: ='Base GC'!Z49 -> s/d | ... Y53: ='Base GC'!AD49 -> GASTO CORRIENTE
A54: =SUBTOTAL(103,$B$6:B54) -> 46 | B54: 79 | C54: CAPACITACION Y DIFUSION DE LA NORMATIVA LABORAL A TRAVES DE MEDIOS DE DIFUSION MASIVA | D54: ='Base GC'!H50 -> 83852 | E54: ='Base GC'!I50 -> 67041 | F54: =D54-E54 -> 16811 | G54: ='Base GC'!J50 -> 65651.53 | H54: ='Base GC'!K50 -> 54395.66 | I54: =D54-H54 -> 29456.34 | J54: =IF(D54=0,0,H54/D54) -> 0.64871035 | K54: ='Base GC'!Q50 -> Mayormente comprometido | L54: ='Base GC'!R50 -> Difícil | M54: ='Base GC'!M50 -> 1389.47 | N54: ='Base GC'!S50 -> 18200.47 | O54: ='Base GC'!T50 -> 28908 | P54: ='Base GC'!U50 -> 54944 | Q54: ='Base GC'!V50 -> 0 | R54: ='Base GC'!W50 -> 0 | S54: ='Base GC'!X50 -> s/d | T54: ='Base GC'!Y50 -> s/d | U54: ='Base GC'!Z50 -> s/d | ... Y54: ='Base GC'!AD50 -> GASTO CORRIENTE
A55: =SUBTOTAL(103,$B$6:B55) -> 47 | B55: 444 | C55: CAPACITACION Y DIFUSION DE LA NORMATIVA LABORAL A TRAVES DE MEDIOS DE DIFUSION MASIVA | D55: ='Base GC'!H51 -> 66358 | E55: ='Base GC'!I51 -> 53720.8 | F55: =D55-E55 -> 12637.2 | G55: ='Base GC'!J51 -> 50720.8 | H55: ='Base GC'!K51 -> 25002.8 | I55: =D55-H55 -> 41355.2 | J55: =IF(D55=0,0,H55/D55) -> 0.37678652 | K55: ='Base GC'!Q51 -> Mayormente comprometido | L55: ='Base GC'!R51 -> Difícil | M55: ='Base GC'!M51 -> 3000 | N55: ='Base GC'!S51 -> 15637.2 | O55: ='Base GC'!T51 -> 0 | P55: ='Base GC'!U51 -> 65958 | Q55: ='Base GC'!V51 -> 0 | R55: ='Base GC'!W51 -> 400 | S55: ='Base GC'!X51 -> s/d | T55: ='Base GC'!Y51 -> s/d | U55: ='Base GC'!Z51 -> s/d | ... Y55: ='Base GC'!AD51 -> GASTO CORRIENTE
A56: =SUBTOTAL(103,$B$6:B56) -> 48 | B56: 206 | C56: GESTION ADMINISTRATIVA · GARANTIZAR LA APLICACION DE NORMAS LABORALES | D56: ='Base GC'!H52 -> 65000 | E56: ='Base GC'!I52 -> 12930 | F56: =D56-E56 -> 52070 | G56: ='Base GC'!J52 -> 12930 | H56: ='Base GC'!K52 -> 1450 | I56: =D56-H56 -> 63550 | J56: =IF(D56=0,0,H56/D56) -> 0.022307692 | K56: ='Base GC'!Q52 -> Parcialmente comprometido | L56: ='Base GC'!R52 -> Parcial | M56: ='Base GC'!M52 -> 0 | N56: ='Base GC'!S52 -> 52070 | O56: ='Base GC'!T52 -> 0 | P56: ='Base GC'!U52 -> 65000 | Q56: ='Base GC'!V52 -> 0 | R56: ='Base GC'!W52 -> 0 | S56: ='Base GC'!X52 -> s/d | T56: ='Base GC'!Y52 -> s/d | U56: ='Base GC'!Z52 -> s/d | ... Y56: ='Base GC'!AD52 -> GASTO CORRIENTE
... A68: =SUBTOTAL(103,$B$6:B68) -> 60 | B68: 439 | C68: ABSOLUCION DE CONSULTAS EN MATERIAS LABORALES | D68: ='Base GC'!H64 -> 1058 | E68: ='Base GC'!I64 -> 0 | F68: =D68-E68 -> 1058 | G68: ='Base GC'!J64 -> 0 | H68: ='Base GC'!K64 -> 0 | I68: =D68-H68 -> 1058 | J68: =IF(D68=0,0,H68/D68) -> 0 | K68: ='Base GC'!Q64 -> Sin certificar | L68: ='Base GC'!R64 -> Disponible | M68: ='Base GC'!M64 -> 0 | N68: ='Base GC'!S64 -> 1058 | O68: ='Base GC'!T64 -> 0 | P68: ='Base GC'!U64 -> 1058 | Q68: ='Base GC'!V64 -> 0 | R68: ='Base GC'!W64 -> 0 | S68: ='Base GC'!X64 -> s/d | T68: ='Base GC'!Y64 -> s/d | U68: ='Base GC'!Z64 -> s/d | ... Y68: ='Base GC'!AD64 -> GASTO CORRIENTE
A69: 09. TURISMO | D69: =SUM(D70:D71) -> 1562035 | E69: =SUM(E70:E71) -> 1439017 | F69: =D69-E69 -> 123018.02 | G69: =SUM(G70:G71) -> 1423536.3 | H69: =SUM(H70:H71) -> 1104843.3 | I69: =D69-H69 -> 457191.75 | J69: =IF(D69=0,0,H69/D69) -> 0.70731018 | M69: =SUM(M70:M71) -> 15480.69 | N69: =SUM(N70:N71) -> 138498.71 | O69: =SUM(O70:O71) -> 1069594 | P69: =SUM(P70:P71) -> 489441 | Q69: =SUM(Q70:Q71) -> 0 | R69: =SUM(R70:R71) -> 3000 | S69: =SUM(S70:S71) -> 0 | T69: =SUM(T70:T71) -> 0 | ... X69: =SUM(X70:X71) -> 0
A70: =SUBTOTAL(103,$B$6:B70) -> 61 | B70: 207 | C70: GESTION ADMINISTRATIVA | D70: ='Base GC'!H65 -> 1324126 | E70: ='Base GC'!I65 -> 1238109.2 | F70: =D70-E70 -> 86016.82 | G70: ='Base GC'!J65 -> 1231164.5 | H70: ='Base GC'!K65 -> 971047.25 | I70: =D70-H70 -> 353078.75 | J70: =IF(D70=0,0,H70/D70) -> 0.73334958 | K70: ='Base GC'!Q65 -> Mayormente comprometido | L70: ='Base GC'!R65 -> Difícil | M70: ='Base GC'!M65 -> 6944.69 | N70: ='Base GC'!S65 -> 92961.51 | O70: ='Base GC'!T65 -> 1069594 | P70: ='Base GC'!U65 -> 251532 | Q70: ='Base GC'!V65 -> 0 | R70: ='Base GC'!W65 -> 3000 | S70: ='Base GC'!X65 -> s/d | T70: ='Base GC'!Y65 -> s/d | U70: ='Base GC'!Z65 -> s/d | ... Y70: ='Base GC'!AD65 -> GASTO CORRIENTE
A71: =SUBTOTAL(103,$B$6:B71) -> 62 | B71: 427 | C71: PLANEAMIENTO Y PRESUPUESTO · DEMARCACION Y ORDENAMIENTO TERRITORIAL | D71: ='Base GC'!H66 -> 237909 | E71: ='Base GC'!I66 -> 200907.8 | F71: =D71-E71 -> 37001.2 | G71: ='Base GC'!J66 -> 192371.8 | H71: ='Base GC'!K66 -> 133796 | I71: =D71-H71 -> 104113 | J71: =IF(D71=0,0,H71/D71) -> 0.5623831 | K71: ='Base GC'!Q66 -> Mayormente comprometido | L71: ='Base GC'!R66 -> Difícil | M71: ='Base GC'!M66 -> 8536 | N71: ='Base GC'!S66 -> 45537.2 | O71: ='Base GC'!T66 -> 0 | P71: ='Base GC'!U66 -> 237909 | Q71: ='Base GC'!V66 -> 0 | R71: ='Base GC'!W66 -> 0 | S71: ='Base GC'!X66 -> s/d | T71: ='Base GC'!Y66 -> s/d | U71: ='Base GC'!Z66 -> s/d | ... Y71: ='Base GC'!AD66 -> GASTO CORRIENTE
A72: 10. AGROPECUARIA | D72: =SUM(D73:D73) -> 493043 | E72: =SUM(E73:E73) -> 436035.75 | F72: =D72-E72 -> 57007.25 | G72: =SUM(G73:G73) -> 44160 | H72: =SUM(H73:H73) -> 23700 | I72: =D72-H72 -> 469343 | J72: =IF(D72=0,0,H72/D72) -> 0.04806883 | M72: =SUM(M73:M73) -> 391875.75 | N72: =SUM(N73:N73) -> 448883 | O72: =SUM(O73:O73) -> 0 | P72: =SUM(P73:P73) -> 493043 | Q72: =SUM(Q73:Q73) -> 0 | R72: =SUM(R73:R73) -> 0 | S72: =SUM(S73:S73) -> 0 | T72: =SUM(T73:T73) -> 0 | ... X72: =SUM(X73:X73) -> 0
A73: =SUBTOTAL(103,$B$6:B73) -> 63 | B73: 13 | C73: CONTROL DE ZONAS CRITICAS Y FAJAS MARGINALES EN CAUCES DE RIOS | D73: ='Base GC'!H67 -> 493043 | E73: ='Base GC'!I67 -> 436035.75 | F73: =D73-E73 -> 57007.25 | G73: ='Base GC'!J67 -> 44160 | H73: ='Base GC'!K67 -> 23700 | I73: =D73-H73 -> 469343 | J73: =IF(D73=0,0,H73/D73) -> 0.04806883 | K73: ='Base GC'!Q67 -> Parcialmente comprometido | L73: ='Base GC'!R67 -> Parcial | M73: ='Base GC'!M67 -> 391875.75 | N73: ='Base GC'!S67 -> 448883 | O73: ='Base GC'!T67 -> 0 | P73: ='Base GC'!U67 -> 493043 | Q73: ='Base GC'!V67 -> 0 | R73: ='Base GC'!W67 -> 0 | S73: ='Base GC'!X67 -> s/d | T73: ='Base GC'!Y67 -> s/d | U73: ='Base GC'!Z67 -> s/d | ... Y73: ='Base GC'!AD67 -> GASTO CORRIENTE
A74: 13. (sin nombre) | D74: =SUM(D75:D75) -> 2489068 | E74: =SUM(E75:E75) -> 1912904.4 | F74: =D74-E74 -> 576163.59 | G74: =SUM(G75:G75) -> 1902482.4 | H74: =SUM(H75:H75) -> 1352375.3 | I74: =D74-H74 -> 1136692.7 | J74: =IF(D74=0,0,H74/D74) -> 0.54332599 | M74: =SUM(M75:M75) -> 10421.97 | N74: =SUM(N75:N75) -> 586585.56 | O74: =SUM(O75:O75) -> 239760 | P74: =SUM(P75:P75) -> 2219308 | Q74: =SUM(Q75:Q75) -> 0 | R74: =SUM(R75:R75) -> 30000 | S74: =SUM(S75:S75) -> 0 | T74: =SUM(T75:T75) -> 0 | ... X74: =SUM(X75:X75) -> 0
A75: =SUBTOTAL(103,$B$6:B75) -> 64 | B75: 208 | C75: GESTION ADMINISTRATIVA | D75: ='Base GC'!H68 -> 2489068 | E75: ='Base GC'!I68 -> 1912904.4 | F75: =D75-E75 -> 576163.59 | G75: ='Base GC'!J68 -> 1902482.4 | H75: ='Base GC'!K68 -> 1352375.3 | I75: =D75-H75 -> 1136692.7 | J75: =IF(D75=0,0,H75/D75) -> 0.54332599 | K75: ='Base GC'!Q68 -> Mayormente comprometido | L75: ='Base GC'!R68 -> Difícil | M75: ='Base GC'!M68 -> 10421.97 | N75: ='Base GC'!S68 -> 586585.56 | O75: ='Base GC'!T68 -> 239760 | P75: ='Base GC'!U68 -> 2219308 | Q75: ='Base GC'!V68 -> 0 | R75: ='Base GC'!W68 -> 30000 | S75: ='Base GC'!X68 -> s/d | T75: ='Base GC'!Y68 -> s/d | U75: ='Base GC'!Z68 -> s/d | ... Y75: ='Base GC'!AD68 -> GASTO CORRIENTE
A76: 15. TRANSPORTE | D76: =SUM(D77:D77) -> 435935 | E76: =SUM(E77:E77) -> 0 | F76: =D76-E76 -> 435935 | G76: =SUM(G77:G77) -> 0 | H76: =SUM(H77:H77) -> 0 | I76: =D76-H76 -> 435935 | J76: =IF(D76=0,0,H76/D76) -> 0 | M76: =SUM(M77:M77) -> 0 | N76: =SUM(N77:N77) -> 435935 | O76: =SUM(O77:O77) -> 0 | P76: =SUM(P77:P77) -> 435935 | Q76: =SUM(Q77:Q77) -> 0 | R76: =SUM(R77:R77) -> 0 | S76: =SUM(S77:S77) -> 0 | T76: =SUM(T77:T77) -> 0 | ... X76: =SUM(X77:X77) -> 0
A77: =SUBTOTAL(103,$B$6:B77) -> 65 | B77: 295 | C77: MANTENIMIENTO DE INFRAESTRUCTURA PUBLICA · MEJORAMIENTO DE INFRAESTRUCTURA SOCIAL | D77: ='Base GC'!H69 -> 435935 | E77: ='Base GC'!I69 -> 0 | F77: =D77-E77 -> 435935 | G77: ='Base GC'!J69 -> 0 | H77: ='Base GC'!K69 -> 0 | I77: =D77-H77 -> 435935 | J77: =IF(D77=0,0,H77/D77) -> 0 | K77: ='Base GC'!Q69 -> Sin certificar | L77: ='Base GC'!R69 -> Disponible | M77: ='Base GC'!M69 -> 0 | N77: ='Base GC'!S69 -> 435935 | O77: ='Base GC'!T69 -> 0 | P77: ='Base GC'!U69 -> 435935 | Q77: ='Base GC'!V69 -> 0 | R77: ='Base GC'!W69 -> 0 | S77: ='Base GC'!X69 -> s/d | T77: ='Base GC'!Y69 -> s/d | U77: ='Base GC'!Z69 -> s/d | ... Y77: ='Base GC'!AD69 -> GASTO CORRIENTE
A78: 17. AMBIENTE | D78: =SUM(D79:D79) -> 17500 | E78: =SUM(E79:E79) -> 0 | F78: =D78-E78 -> 17500 | G78: =SUM(G79:G79) -> 0 | H78: =SUM(H79:H79) -> 0 | I78: =D78-H78 -> 17500 | J78: =IF(D78=0,0,H78/D78) -> 0 | M78: =SUM(M79:M79) -> 0 | N78: =SUM(N79:N79) -> 17500 | O78: =SUM(O79:O79) -> 0 | P78: =SUM(P79:P79) -> 17500 | Q78: =SUM(Q79:Q79) -> 0 | R78: =SUM(R79:R79) -> 0 | S78: =SUM(S79:S79) -> 0 | T78: =SUM(T79:T79) -> 0 | ... X78: =SUM(X79:X79) -> 0
A79: =SUBTOTAL(103,$B$6:B79) -> 66 | B79: 527 | C79: PROPUESTAS DE CREACION Y/O CATEGORIZACION DE AREAS NATURALES PROTEGIDAS ELABORADAS | D79: ='Base GC'!H70 -> 17500 | E79: ='Base GC'!I70 -> 0 | F79: =D79-E79 -> 17500 | G79: ='Base GC'!J70 -> 0 | H79: ='Base GC'!K70 -> 0 | I79: =D79-H79 -> 17500 | J79: =IF(D79=0,0,H79/D79) -> 0 | K79: ='Base GC'!Q70 -> Sin certificar | L79: ='Base GC'!R70 -> Disponible | M79: ='Base GC'!M70 -> 0 | N79: ='Base GC'!S70 -> 17500 | O79: ='Base GC'!T70 -> 0 | P79: ='Base GC'!U70 -> 17500 | Q79: ='Base GC'!V70 -> 0 | R79: ='Base GC'!W70 -> 0 | S79: ='Base GC'!X70 -> s/d | T79: ='Base GC'!Y70 -> s/d | U79: ='Base GC'!Z70 -> s/d | ... Y79: ='Base GC'!AD70
A80: 18. SANEAMIENTO | D80: =SUM(D81:D84) -> 1516146 | E80: =SUM(E81:E84) -> 1392267.4 | F80: =D80-E80 -> 123878.6 | G80: =SUM(G81:G84) -> 1398267.4 | H80: =SUM(H81:H84) -> 347898.28 | I80: =D80-H80 -> 1168247.7 | J80: =IF(D80=0,0,H80/D80) -> 0.22946225 | M80: =SUM(M81:M84) -> -6000 | N80: =SUM(N81:N84) -> 117878.6 | O80: =SUM(O81:O84) -> 0 | P80: =SUM(P81:P84) -> 1035274 | Q80: =SUM(Q81:Q84) -> 0 | R80: =SUM(R81:R84) -> 480872 | S80: =SUM(S81:S84) -> 0 | T80: =SUM(T81:T84) -> 0 | ... X80: =SUM(X81:X84) -> 0
A81: =SUBTOTAL(103,$B$6:B81) -> 67 | B81: 17 | C81: POTABILIZACION Y OTRAS FORMAS DE DESINFECCION Y TRATAMIENTO · POTABILIZACION Y OTRAS FORMAS DE DESINFECCION Y TRATAMIENTO | D81: ='Base GC'!H71 -> 685373 | E81: ='Base GC'!I71 -> 621850 | F81: =D81-E81 -> 63523 | G81: ='Base GC'!J71 -> 627850 | H81: ='Base GC'!K71 -> 108850 | I81: =D81-H81 -> 576523 | J81: =IF(D81=0,0,H81/D81) -> 0.15881863 | K81: ='Base GC'!Q71 -> Mayormente comprometido | L81: ='Base GC'!R71 -> Difícil | M81: ='Base GC'!M71 -> -6000 | N81: ='Base GC'!S71 -> 57523 | O81: ='Base GC'!T71 -> 0 | P81: ='Base GC'!U71 -> 204501 | Q81: ='Base GC'!V71 -> 0 | R81: ='Base GC'!W71 -> 480872 | S81: ='Base GC'!X71 -> s/d | T81: ='Base GC'!Y71 -> s/d | U81: ='Base GC'!Z71 -> s/d | ... Y81: ='Base GC'!AD71 -> GASTO CORRIENTE
A82: =SUBTOTAL(103,$B$6:B82) -> 68 | B82: 18 | C82: FORTALECIMIENTO DE CAPACIDADES A PRESTADORES, GL - ATM y GR - D/GRVCS · FORTALECIMIENTO DE CAPACIDADES A PRESTADORES DE LOS SERVICIOS DE AGUA Y DISPOSICION SANITARIA DE EXCRETAS | D82: ='Base GC'!H72 -> 483570 | E82: ='Base GC'!I72 -> 446040 | F82: =D82-E82 -> 37530 | G82: ='Base GC'!J72 -> 446040 | H82: ='Base GC'!K72 -> 89208 | I82: =D82-H82 -> 394362 | J82: =IF(D82=0,0,H82/D82) -> 0.18447795 | K82: ='Base GC'!Q72 -> Mayormente comprometido | L82: ='Base GC'!R72 -> Difícil | M82: ='Base GC'!M72 -> 0 | N82: ='Base GC'!S72 -> 37530 | O82: ='Base GC'!T72 -> 0 | P82: ='Base GC'!U72 -> 483570 | Q82: ='Base GC'!V72 -> 0 | R82: ='Base GC'!W72 -> 0 | S82: ='Base GC'!X72 -> s/d | T82: ='Base GC'!Y72 -> s/d | U82: ='Base GC'!Z72 -> s/d | ... Y82: ='Base GC'!AD72 -> GASTO CORRIENTE
A83: =SUBTOTAL(103,$B$6:B83) -> 69 | B83: 466 | C83: MONITOREO DE LA PRESTACION DE LOS SERVICIOS DE AGUA POTABLE Y DISPOSICION SANITARIA DE EXCRETAS PARA HOGARES CONCENTRADOS | D83: ='Base GC'!H73 -> 198613 | E83: ='Base GC'!I73 -> 190176 | F83: =D83-E83 -> 8437 | G83: ='Base GC'!J73 -> 190176 | H83: ='Base GC'!K73 -> 123000 | I83: =D83-H83 -> 75613 | J83: =IF(D83=0,0,H83/D83) -> 0.61929481 | K83: ='Base GC'!Q73 -> Mayormente comprometido | L83: ='Base GC'!R73 -> Difícil | M83: ='Base GC'!M73 -> 0 | N83: ='Base GC'!S73 -> 8437 | O83: ='Base GC'!T73 -> 0 | P83: ='Base GC'!U73 -> 198613 | Q83: ='Base GC'!V73 -> 0 | R83: ='Base GC'!W73 -> 0 | S83: ='Base GC'!X73 -> s/d | T83: ='Base GC'!Y73 -> s/d | U83: ='Base GC'!Z73 -> s/d | ... Y83: ='Base GC'!AD73 -> GASTO CORRIENTE
A84: =SUBTOTAL(103,$B$6:B84) -> 70 | B84: 19 | C84: FORTALECIMIENTO DE CAPACIDADES A PRESTADORES, GL - ATM y GR - D/GRVCS · FORTALECIMIENTO DE CAPACIDADES A GOBIERNOS LOCALES - AREAS TECNICAS MUNICIPALES | D84: ='Base GC'!H74 -> 148590 | E84: ='Base GC'!I74 -> 134201.4 | F84: =D84-E84 -> 14388.6 | G84: ='Base GC'!J74 -> 134201.4 | H84: ='Base GC'!K74 -> 26840.28 | I84: =D84-H84 -> 121749.72 | J84: =IF(D84=0,0,H84/D84) -> 0.18063315 | K84: ='Base GC'!Q74 -> Mayormente comprometido | L84: ='Base GC'!R74 -> Difícil | M84: ='Base GC'!M74 -> 0 | N84: ='Base GC'!S74 -> 14388.6 | O84: ='Base GC'!T74 -> 0 | P84: ='Base GC'!U74 -> 148590 | Q84: ='Base GC'!V74 -> 0 | R84: ='Base GC'!W74 -> 0 | S84: ='Base GC'!X74 -> s/d | T84: ='Base GC'!Y74 -> s/d | U84: ='Base GC'!Z74 -> s/d | ... Y84: ='Base GC'!AD74 -> GASTO CORRIENTE
A85: 20. SALUD | D85: =SUM(D86:D89) -> 827796 | E85: =SUM(E86:E89) -> 523242 | F85: =D85-E85 -> 304554 | G85: =SUM(G86:G89) -> 224145.26 | H85: =SUM(H86:H89) -> 170767.76 | I85: =D85-H85 -> 657028.24 | J85: =IF(D85=0,0,H85/D85) -> 0.20629208 | M85: =SUM(M86:M89) -> 299096.74 | N85: =SUM(N86:N89) -> 603650.74 | O85: =SUM(O86:O89) -> 0 | P85: =SUM(P86:P89) -> 424596 | Q85: =SUM(Q86:Q89) -> 0 | R85: =SUM(R86:R89) -> 403200 | S85: =SUM(S86:S89) -> 0 | T85: =SUM(T86:T89) -> 0 | ... X85: =SUM(X86:X89) -> 0
A86: =SUBTOTAL(103,$B$6:B86) -> 71 | B86: 468 | C86: VIGILANCIA DE LA CALIDAD DEL AGUA PARA EL CONSUMO HUMANO | D86: ='Base GC'!H75 -> 295200 | E86: ='Base GC'!I75 -> 295200 | F86: =D86-E86 -> 0 | G86: ='Base GC'!J75 -> 0 | H86: ='Base GC'!K75 -> 0 | I86: =D86-H86 -> 295200 | J86: =IF(D86=0,0,H86/D86) -> 0 | K86: ='Base GC'!Q75 -> Solo certificado | L86: ='Base GC'!R75 -> Posible | M86: ='Base GC'!M75 -> 295200 | N86: ='Base GC'!S75 -> 295200 | O86: ='Base GC'!T75 -> 0 | P86: ='Base GC'!U75 -> 0 | Q86: ='Base GC'!V75 -> 0 | R86: ='Base GC'!W75 -> 295200 | S86: ='Base GC'!X75 -> s/d | T86: ='Base GC'!Y75 -> s/d | U86: ='Base GC'!Z75 -> s/d | ... Y86: ='Base GC'!AD75
A87: =SUBTOTAL(103,$B$6:B87) -> 72 | B87: 296 | C87: MANTENIMIENTO DE INFRAESTRUCTURA PUBLICA · MANTENIMIENTO DE INFRAESTRUCTURA CONSTRUIDA | D87: ='Base GC'!H76 -> 276933 | E87: ='Base GC'!I76 -> 0 | F87: =D87-E87 -> 276933 | G87: ='Base GC'!J76 -> 0 | H87: ='Base GC'!K76 -> 0 | I87: =D87-H87 -> 276933 | J87: =IF(D87=0,0,H87/D87) -> 0 | K87: ='Base GC'!Q76 -> Sin certificar | L87: ='Base GC'!R76 -> Disponible | M87: ='Base GC'!M76 -> 0 | N87: ='Base GC'!S76 -> 276933 | O87: ='Base GC'!T76 -> 0 | P87: ='Base GC'!U76 -> 276933 | Q87: ='Base GC'!V76 -> 0 | R87: ='Base GC'!W76 -> 0 | S87: ='Base GC'!X76 -> s/d | T87: ='Base GC'!Y76 -> s/d | U87: ='Base GC'!Z76 -> s/d | ... Y87: ='Base GC'!AD76 -> GASTO CORRIENTE
A88: =SUBTOTAL(103,$B$6:B88) -> 73 | B88: 469 | C88: MONITOREO, SUPERVISION, EVALUACION Y CONTROL DEL PROGRAMA ARTICULADO NUTRICIONAL | D88: ='Base GC'!H77 -> 147663 | E88: ='Base GC'!I77 -> 120042 | F88: =D88-E88 -> 27621 | G88: ='Base GC'!J77 -> 116145.26 | H88: ='Base GC'!K77 -> 62767.76 | I88: =D88-H88 -> 84895.24 | J88: =IF(D88=0,0,H88/D88) -> 0.42507439 | K88: ='Base GC'!Q77 -> Mayormente comprometido | L88: ='Base GC'!R77 -> Difícil | M88: ='Base GC'!M77 -> 3896.74 | N88: ='Base GC'!S77 -> 31517.74 | O88: ='Base GC'!T77 -> 0 | P88: ='Base GC'!U77 -> 147663 | Q88: ='Base GC'!V77 -> 0 | R88: ='Base GC'!W77 -> 0 | S88: ='Base GC'!X77 -> s/d | T88: ='Base GC'!Y77 -> s/d | U88: ='Base GC'!Z77 -> s/d | ... Y88: ='Base GC'!AD77
A89: =SUBTOTAL(103,$B$6:B89) -> 74 | B89: 467 | C89: ADMINISTRAR SUPLEMENTO DE HIERRO Y ACIDO FOLICO A ADOLESCENTES · ADMINISTRAR SUPLEMENTO DE HIERRO Y ACIDO FOLICO A ADOLESCENTE | D89: ='Base GC'!H78 -> 108000 | E89: ='Base GC'!I78 -> 108000 | F89: =D89-E89 -> 0 | G89: ='Base GC'!J78 -> 108000 | H89: ='Base GC'!K78 -> 108000 | I89: =D89-H89 -> 0 | J89: =IF(D89=0,0,H89/D89) -> 1 | K89: ='Base GC'!Q78 -> Ejecutado | L89: ='Base GC'!R78 -> No usar | M89: ='Base GC'!M78 -> 0 | N89: ='Base GC'!S78 -> 0 | O89: ='Base GC'!T78 -> 0 | P89: ='Base GC'!U78 -> 0 | Q89: ='Base GC'!V78 -> 0 | R89: ='Base GC'!W78 -> 108000 | S89: ='Base GC'!X78 -> s/d | T89: ='Base GC'!Y78 -> s/d | U89: ='Base GC'!Z78 -> s/d | ... Y89: ='Base GC'!AD78
A90: 23. PROTECCION SOCIAL | D90: =SUM(D91:D94) -> 2310603 | E90: =SUM(E91:E94) -> 2093004.2 | F90: =D90-E90 -> 217598.77 | G90: =SUM(G91:G94) -> 2066307.9 | H90: =SUM(H91:H94) -> 1425517.1 | I90: =D90-H90 -> 885085.95 | J90: =IF(D90=0,0,H90/D90) -> 0.6169459 | M90: =SUM(M91:M94) -> 26696.3 | N90: =SUM(N91:N94) -> 244295.07 | O90: =SUM(O91:O94) -> 819196 | P90: =SUM(P91:P94) -> 1059244 | Q90: =SUM(Q91:Q94) -> 0 | R90: =SUM(R91:R94) -> 432163 | S90: =SUM(S91:S94) -> 0 | T90: =SUM(T91:T94) -> 0 | ... X90: =SUM(X91:X94) -> 0
A91: =SUBTOTAL(103,$B$6:B91) -> 75 | B91: 85 | C91: ATENCION, CUIDADO Y PROTECCION A NIÑAS, NIÑOS Y ADOLESCENTES EN DESPROTECCION FAMILIAR A TRAVES DE CENTROS DE ACOGIDA RESIDENCIAL BASICO | D91: ='Base GC'!H79 -> 1146585 | E91: ='Base GC'!I79 -> 1046247.6 | F91: =D91-E91 -> 100337.4 | G91: ='Base GC'!J79 -> 1025365.9 | H91: ='Base GC'!K79 -> 744832.42 | I91: =D91-H91 -> 401752.58 | J91: =IF(D91=0,0,H91/D91) -> 0.64960942 | K91: ='Base GC'!Q79 -> Mayormente comprometido | L91: ='Base GC'!R79 -> Difícil | M91: ='Base GC'!M79 -> 20881.7 | N91: ='Base GC'!S79 -> 121219.1 | O91: ='Base GC'!T79 -> 599215 | P91: ='Base GC'!U79 -> 337040 | Q91: ='Base GC'!V79 -> 0 | R91: ='Base GC'!W79 -> 210330 | S91: ='Base GC'!X79 -> s/d | T91: ='Base GC'!Y79 -> s/d | U91: ='Base GC'!Z79 -> s/d | ... Y91: ='Base GC'!AD79 -> GASTO CORRIENTE
A92: =SUBTOTAL(103,$B$6:B92) -> 76 | B92: 86 | C92: ATENCION, CUIDADO Y PROTECCION A NIÑAS, NIÑOS Y ADOLESCENTES EN DESPROTECCION FAMILIAR A TRAVES DE CENTROS DE ACOGIDA RESIDENCIAL BASICO | D92: ='Base GC'!H80 -> 774018 | E92: ='Base GC'!I80 -> 700313.5 | F92: =D92-E92 -> 73704.5 | G92: ='Base GC'!J80 -> 694498.9 | H92: ='Base GC'!K80 -> 447191.7 | I92: =D92-H92 -> 326826.3 | J92: =IF(D92=0,0,H92/D92) -> 0.57775362 | K92: ='Base GC'!Q80 -> Mayormente comprometido | L92: ='Base GC'!R80 -> Difícil | M92: ='Base GC'!M80 -> 5814.6 | N92: ='Base GC'!S80 -> 79519.1 | O92: ='Base GC'!T80 -> 219981 | P92: ='Base GC'!U80 -> 346706 | Q92: ='Base GC'!V80 -> 0 | R92: ='Base GC'!W80 -> 207331 | S92: ='Base GC'!X80 -> s/d | T92: ='Base GC'!Y80 -> s/d | U92: ='Base GC'!Z80 -> s/d | ... Y92: ='Base GC'!AD80 -> GASTO CORRIENTE
A93: =SUBTOTAL(103,$B$6:B93) -> 77 | B93: 302 | C93: MEJORAMIENTO Y ATENCION A LAS PERSONAS CON DISCAPACIDAD · ATENCION A LAS PERSONAS CON DISCAPACIDAD MEDIANTE ACCIONES DE LA OFICINA REGIONAL DE ATENCION A LA PERSONA CON DISCAPACIDAD (OREDIS) | D93: ='Base GC'!H81 -> 290000 | E93: ='Base GC'!I81 -> 284643.13 | F93: =D93-E93 -> 5356.87 | G93: ='Base GC'!J81 -> 284643.13 | H93: ='Base GC'!K81 -> 191992.93 | I93: =D93-H93 -> 98007.07 | J93: =IF(D93=0,0,H93/D93) -> 0.66204459 | K93: ='Base GC'!Q81 -> Mayormente comprometido | L93: ='Base GC'!R81 -> Difícil | M93: ='Base GC'!M81 -> 0 | N93: ='Base GC'!S81 -> 5356.87 | O93: ='Base GC'!T81 -> 0 | P93: ='Base GC'!U81 -> 275498 | Q93: ='Base GC'!V81 -> 0 | R93: ='Base GC'!W81 -> 14502 | S93: ='Base GC'!X81 -> s/d | T93: ='Base GC'!Y81 -> s/d | U93: ='Base GC'!Z81 -> s/d | ... Y93: ='Base GC'!AD81 -> GASTO CORRIENTE
A94: =SUBTOTAL(103,$B$6:B94) -> 78 | B94: 299 | C94: PROTECCION SOCIAL · MEJORAR LA CALIDAD DE VIDA DE LA POBLACION | D94: ='Base GC'!H82 -> 100000 | E94: ='Base GC'!I82 -> 61800 | F94: =D94-E94 -> 38200 | G94: ='Base GC'!J82 -> 61800 | H94: ='Base GC'!K82 -> 41500 | I94: =D94-H94 -> 58500 | J94: =IF(D94=0,0,H94/D94) -> 0.415 | K94: ='Base GC'!Q82 -> Mayormente comprometido | L94: ='Base GC'!R82 -> Difícil | M94: ='Base GC'!M82 -> 0 | N94: ='Base GC'!S82 -> 38200 | O94: ='Base GC'!T82 -> 0 | P94: ='Base GC'!U82 -> 100000 | Q94: ='Base GC'!V82 -> 0 | R94: ='Base GC'!W82 -> 0 | S94: ='Base GC'!X82 -> s/d | T94: ='Base GC'!Y82 -> s/d | U94: ='Base GC'!Z82 -> s/d | ... Y94: ='Base GC'!AD82 -> GASTO CORRIENTE
A95: 24. (sin nombre) | D95: =SUM(D96:D96) -> 2491773 | E95: =SUM(E96:E96) -> 2491773 | F95: =D95-E95 -> 0 | G95: =SUM(G96:G96) -> 2491773 | H95: =SUM(H96:H96) -> 1895535.6 | I95: =D95-H95 -> 596237.36 | J95: =IF(D95=0,0,H95/D95) -> 0.76071763 | M95: =SUM(M96:M96) -> 0 | N95: =SUM(N96:N96) -> 0 | O95: =SUM(O96:O96) -> 0 | P95: =SUM(P96:P96) -> 0 | Q95: =SUM(Q96:Q96) -> 0 | R95: =SUM(R96:R96) -> 2491773 | S95: =SUM(S96:S96) -> 0 | T95: =SUM(T96:T96) -> 0 | ... X95: =SUM(X96:X96) -> 0
A96: =SUBTOTAL(103,$B$6:B96) -> 79 | B96: 297 | C96: OBLIGACIONES PREVISIONALES · PAGO DE PENSIONES Y BENEFICIOS A CESANTES Y JUBILADOS | D96: ='Base GC'!H83 -> 2491773 | E96: ='Base GC'!I83 -> 2491773 | F96: =D96-E96 -> 0 | G96: ='Base GC'!J83 -> 2491773 | H96: ='Base GC'!K83 -> 1895535.6 | I96: =D96-H96 -> 596237.36 | J96: =IF(D96=0,0,H96/D96) -> 0.76071763 | K96: ='Base GC'!Q83 -> Mayormente comprometido | L96: ='Base GC'!R83 -> Difícil | M96: ='Base GC'!M83 -> 0 | N96: ='Base GC'!S83 -> 0 | O96: ='Base GC'!T83 -> 0 | P96: ='Base GC'!U83 -> 0 | Q96: ='Base GC'!V83 -> 0 | R96: ='Base GC'!W83 -> 2491773 | S96: ='Base GC'!X83 -> s/d | T96: ='Base GC'!Y83 -> s/d | U96: ='Base GC'!Z83 -> s/d | ... Y96: ='Base GC'!AD83 -> GASTO CORRIENTE
A97: 25. (sin nombre) | D97: =SUM(D98:D98) -> 1594115 | E97: =SUM(E98:E98) -> 0 | F97: =D97-E97 -> 1594115 | G97: =SUM(G98:G98) -> 0 | H97: =SUM(H98:H98) -> 0 | I97: =D97-H97 -> 1594115 | J97: =IF(D97=0,0,H97/D97) -> 0 | M97: =SUM(M98:M98) -> 0 | N97: =SUM(N98:N98) -> 1594115 | O97: =SUM(O98:O98) -> 0 | P97: =SUM(P98:P98) -> 0 | Q97: =SUM(Q98:Q98) -> 0 | R97: =SUM(R98:R98) -> 1594115 | S97: =SUM(S98:S98) -> 0 | T97: =SUM(T98:T98) -> 0 | ... X97: =SUM(X98:X98) -> 0
A98: =SUBTOTAL(103,$B$6:B98) -> 80 | B98: 288 | C98: ADMINISTRACION DEUDA INTERNA · SERVICIO DE LA DEUDA | D98: ='Base GC'!H84 -> 1594115 | E98: ='Base GC'!I84 -> 0 | F98: =D98-E98 -> 1594115 | G98: ='Base GC'!J84 -> 0 | H98: ='Base GC'!K84 -> 0 | I98: =D98-H98 -> 1594115 | J98: =IF(D98=0,0,H98/D98) -> 0 | K98: ='Base GC'!Q84 -> Sin certificar | L98: ='Base GC'!R84 -> Disponible | M98: ='Base GC'!M84 -> 0 | N98: ='Base GC'!S84 -> 1594115 | O98: ='Base GC'!T84 -> 0 | P98: ='Base GC'!U84 -> 0 | Q98: ='Base GC'!V84 -> 0 | R98: ='Base GC'!W84 -> 1594115 | S98: ='Base GC'!X84 -> s/d | T98: ='Base GC'!Y84 -> s/d | U98: ='Base GC'!Z84 -> s/d | ... Y98: ='Base GC'!AD84 -> GASTO CORRIENTE
A100: TOTAL GASTO CORRIENTE UE 001 | D100: =D5 -> 99795382 | E100: =E5 -> 81255206 | F100: =D100-E100 -> 18540176 | G100: =G5 -> 72637604 | H100: =H5 -> 56814243 | I100: =D100-H100 -> 42981139 | J100: =IF(D100=0,0,H100/D100) -> 0.56930733 | M100: =M5 -> 8617601.6 | N100: =N5 -> 27100845 | O100: =O5 -> 20504461 | P100: =P5 -> 40283830 | Q100: =Q5 -> 136213 | R100: =R5 -> 38870878 | S100: =S5 -> 0 | T100: =T5 -> 0 | ... X100: =X5 -> 0

Sheet Base GC
A1: Base gasto corriente UE 001 · al 08/10/2026
A2: Azul = dato de entrada; negro = fórmula. "s/d" en rubro = no se obtuvo de la API.
A4: UE | B4: Gerencia / Oficina | C4: Función | D4: Producto | E4: Actividad | F4: Meta | G4: Actividad / meta | H4: PIM 2026 | I4: Certificación | J4: Compromiso anual | K4: Devengado | L4: Saldo sin certificar (A-B) | M4: Certificado no comprometido | N4: Saldo sin devengar (A-C) | O4: % Devengado | P4: % Comprometido | Q4: Estado situacional | R4: Disponibilidad | S4: Disponible (PIM − compromiso) | T4: PIM 2.1 Personal | U4: PIM 2.3 Bienes y serv. | V4: PIM 2.5 Otros gastos | W4: PIM otras genéricas | X4: PIM · RO (00) | Y4: PIM · RDR (09) | Z4: PIM · DyT (13) | AA4: PIM · FONCOR (15) | AB4: PIM · CANON (18) | AC4: PIM · otros rubros | AD4: Ejecutora (Silucia) | AE4: Nota
A5: 001 | B5: SIN CLASIFICAR (completar en maestro.xlsx, hoja ClasifGC) | C5: 03. PLANEAMIENTO, GESTION Y RESERVA DE CONTINGENCIA | D5: 3999999 | E5: 5001253 | F5: 0486 | G5: TRANSFERENCIA DE RECURSOS PARA LA EJECUCION DE PROYECTOS DE INVERSION · TRANSFERENCIA FINANCIERA PARA PROYECTOS DE INVERSION | H5: 21854668 | I5: 21854668 | J5: 21800985 | K5: 21800985 | L5: =H5-I5 -> 0 | M5: =I5-J5 -> 53683 | N5: =H5-K5 -> 53683 | O5: =IF(H5>0,K5/H5,0) -> 0.99754364 | P5: =IF(H5>0,J5/H5,0) -> 0.99754364 | Q5: =IF(H5<=0,"Sin PIM",IF(K5/H5>=Config!$B$5,"Ejecutado",IF(J5/H5>=Config!$B$6,"Mayormente comprometido",IF(J5>0.005,"Parcialmente comprometido",IF(I5>0.005,"Solo certificado","Sin certificar"))))) -> Ejecutado | R5: =IF(Q5="Sin certificar","Disponible",IF(Q5="Solo certificado","Posible",IF(Q5="Parcialmente comprometido","Parcial",IF(Q5="Mayormente comprometido","Difícil",IF(Q5="Ejecutado","No usar","Sin PIM"))))) -> No usar | S5: =IF(OR(H5<=0,Q5="Ejecutado"),0,MAX(0,H5-J5)) -> 0 | T5: 0 | U5: 0 | V5: 0 | W5: 21854668 | X5: s/d | Y5: s/d | Z5: s/d | AA5: s/d | AB5: s/d | AC5: s/d
A6: 001 | B6: SIN CLASIFICAR (completar en maestro.xlsx, hoja ClasifGC) | C6: 03. PLANEAMIENTO, GESTION Y RESERVA DE CONTINGENCIA | D6: 3999999 | E6: 5000001 | F6: 0199 | G6: PLANEAMIENTO Y PRESUPUESTO · ACCIONES DE PLANEAMIENTO Y PRESUPUESTO | H6: 14397156 | I6: 8698687.6 | J6: 6321785.8 | K6: 1694723 | L6: =H6-I6 -> 5698468.4 | M6: =I6-J6 -> 2376901.8 | N6: =H6-K6 -> 12702433 | O6: =IF(H6>0,K6/H6,0) -> 0.11771235 | P6: =IF(H6>0,J6/H6,0) -> 0.43909962 | Q6: =IF(H6<=0,"Sin PIM",IF(K6/H6>=Config!$B$5,"Ejecutado",IF(J6/H6>=Config!$B$6,"Mayormente comprometido",IF(J6>0.005,"Parcialmente comprometido",IF(I6>0.005,"Solo certificado","Sin certificar"))))) -> Parcialmente comprometido | R6: =IF(Q6="Sin certificar","Disponible",IF(Q6="Solo certificado","Posible",IF(Q6="Parcialmente comprometido","Parcial",IF(Q6="Mayormente comprometido","Difícil",IF(Q6="Ejecutado","No usar","Sin PIM"))))) -> Parcial | S6: =IF(OR(H6<=0,Q6="Ejecutado"),0,MAX(0,H6-J6)) -> 8075370.2 | T6: 5491591 | U6: 6984992 | V6: 0 | W6: 1920573 | X6: s/d | Y6: s/d | Z6: s/d | AA6: s/d | AB6: s/d | AC6: s/d | AD6: GASTO CORRIENTE
A7: 001 | B7: SIN CLASIFICAR (completar en maestro.xlsx, hoja ClasifGC) | C7: 03. PLANEAMIENTO, GESTION Y RESERVA DE CONTINGENCIA | D7: 3999999 | E7: 5000003 | F7: 0203 | G7: GESTION ADMINISTRATIVA · MANTENIMIENTO Y REPARACION DE EQUIPO MECANICO | H7: 11561677 | I7: 10764477 | J7: 6753457.1 | K7: 5863914.2 | L7: =H7-I7 -> 797200.27 | M7: =I7-J7 -> 4011019.6 | N7: =H7-K7 -> 5697762.8 | O7: =IF(H7>0,K7/H7,0) -> 0.50718543 | P7: =IF(H7>0,J7/H7,0) -> 0.58412435 | Q7: =IF(H7<=0,"Sin PIM",IF(K7/H7>=Config!$B$5,"Ejecutado",IF(J7/H7>=Config!$B$6,"Mayormente comprometido",IF(J7>0.005,"Parcialmente comprometido",IF(I7>0.005,"Solo certificado","Sin certificar"))))) -> Mayormente comprometido | R7: =IF(Q7="Sin certificar","Disponible",IF(Q7="Solo certificado","Posible",IF(Q7="Parcialmente comprometido","Parcial",IF(Q7="Mayormente comprometido","Difícil",IF(Q7="Ejecutado","No usar","Sin PIM"))))) -> Difícil | S7: =IF(OR(H7<=0,Q7="Ejecutado"),0,MAX(0,H7-J7)) -> 4808219.9 | T7: 0 | U7: 11442377 | V7: 0 | W7: 119300 | X7: s/d | Y7: s/d | Z7: s/d | AA7: s/d | AB7: s/d | AC7: s/d | AD7: GASTO CORRIENTE
A8: 001 | B8: SIN CLASIFICAR (completar en maestro.xlsx, hoja ClasifGC) | C8: 03. PLANEAMIENTO, GESTION Y RESERVA DE CONTINGENCIA | D8: 3999999 | E8: 5000003 | F8: 0202 | G8: GESTION ADMINISTRATIVA | H8: 8960842 | I8: 8663999 | J8: 8547567.6 | K8: 6519476.6 | L8: =H8-I8 -> 296843.03 | M8: =I8-J8 -> 116431.38 | N8: =H8-K8 -> 2441365.4 | O8: =IF(H8>0,K8/H8,0) -> 0.72755178 | P8: =IF(H8>0,J8/H8,0) -> 0.95387996 | Q8: =IF(H8<=0,"Sin PIM",IF(K8/H8>=Config!$B$5,"Ejecutado",IF(J8/H8>=Config!$B$6,"Mayormente comprometido",IF(J8>0.005,"Parcialmente comprometido",IF(I8>0.005,"Solo certificado","Sin certificar"))))) -> Mayormente comprometido | R8: =IF(Q8="Sin certificar","Disponible",IF(Q8="Solo certificado","Posible",IF(Q8="Parcialmente comprometido","Parcial",IF(Q8="Mayormente comprometido","Difícil",IF(Q8="Ejecutado","No usar","Sin PIM"))))) -> Difícil | S8: =IF(OR(H8<=0,Q8="Ejecutado"),0,MAX(0,H8-J8)) -> 413274.41 | T8: 3202893 | U8: 4644868 | V8: 58501 | W8: 1054580 | X8: s/d | Y8: s/d | Z8: s/d | AA8: s/d | AB8: s/d | AC8: s/d | AD8: GASTO CORRIENTE
A9: 001 | B9: SIN CLASIFICAR (completar en maestro.xlsx, hoja ClasifGC) | C9: 03. PLANEAMIENTO, GESTION Y RESERVA DE CONTINGENCIA | D9: 3999999 | E9: 5001254 | F9: 0531 | G9: TRANSFERENCIA DE RECURSOS PARA LA EJECUCION DE ACTIVIDADES · TRANSFERENCIA FINANCIERA PARA ACTIVIDADES | H9: 4661250 | I9: 0 | J9: 0 | K9: 0 | L9: =H9-I9 -> 4661250 | M9: =I9-J9 -> 0 | N9: =H9-K9 -> 4661250 | O9: =IF(H9>0,K9/H9,0) -> 0 | P9: =IF(H9>0,J9/H9,0) -> 0 | Q9: =IF(H9<=0,"Sin PIM",IF(K9/H9>=Config!$B$5,"Ejecutado",IF(J9/H9>=Config!$B$6,"Mayormente comprometido",IF(J9>0.005,"Parcialmente comprometido",IF(I9>0.005,"Solo certificado","Sin certificar"))))) -> Sin certificar | R9: =IF(Q9="Sin certificar","Disponible",IF(Q9="Solo certificado","Posible",IF(Q9="Parcialmente comprometido","Parcial",IF(Q9="Mayormente comprometido","Difícil",IF(Q9="Ejecutado","No usar","Sin PIM"))))) -> Disponible | S9: =IF(OR(H9<=0,Q9="Ejecutado"),0,MAX(0,H9-J9)) -> 4661250 | T9: 0 | U9: 0 | V9: 0 | W9: 4661250 | X9: s/d | Y9: s/d | Z9: s/d | AA9: s/d | AB9: s/d | AC9: s/d
A10: 001 | B10: SIN CLASIFICAR (completar en maestro.xlsx, hoja ClasifGC) | C10: 03. PLANEAMIENTO, GESTION Y RESERVA DE CONTINGENCIA | D10: 3999999 | E10: 5001228 | F10: 0300 | G10: SUPERVISION Y CONTROL · SEGUIMIENTO DE FISCALIZACION DE LOS CONSEJOS REGIONALES Y CONCEJOS MUNICIPALES A NIVEL NACIONAL | H10: 3003455 | I10: 2361957.3 | J10: 2312089.7 | K10: 1164173.1 | L10: =H10-I10 -> 641497.68 | M10: =I10-J10 -> 49867.66 | N10: =H10-K10 -> 1839281.9 | O10: =IF(H10>0,K10/H10,0) -> 0.38761131 | P10: =IF(H10>0,J10/H10,0) -> 0.76980999 | Q10: =IF(H10<=0,"Sin PIM",IF(K10/H10>=Config!$B$5,"Ejecutado",IF(J10/H10>=Config!$B$6,"Mayormente comprometido",IF(J10>0.005,"Parcialmente comprometido",IF(I10>0.005,"Solo certificado","Sin certificar"))))) -> Mayormente comprometido | R10: =IF(Q10="Sin certificar","Disponible",IF(Q10="Solo certificado","Posible",IF(Q10="Parcialmente comprometido","Parcial",IF(Q10="Mayormente comprometido","Difícil",IF(Q10="Ejecutado","No usar","Sin PIM"))))) -> Difícil | S10: =IF(OR(H10<=0,Q10="Ejecutado"),0,MAX(0,H10-J10)) -> 691365.34 | T10: 1074678 | U10: 1928777 | V10: 0 | W10: 0 | X10: s/d | Y10: s/d | Z10: s/d | AA10: s/d | AB10: s/d | AC10: s/d | AD10: GASTO CORRIENTE
A11: 001 | B11: SIN CLASIFICAR (completar en maestro.xlsx, hoja ClasifGC) | C11: 03. PLANEAMIENTO, GESTION Y RESERVA DE CONTINGENCIA | D11: 3999999 | E11: 5000698 | F11: 0291 | G11: DESARROLLO SOCIAL REGIONAL · PROMOCION Y CONCERTACION DE INICIATIVAS SOCIALES | H11: 2564683 | I11: 2101980.8 | J11: 2022558.8 | K11: 1443358.5 | L11: =H11-I11 -> 462702.25 | M11: =I11-J11 -> 79422 | N11: =H11-K11 -> 1121324.5 | O11: =IF(H11>0,K11/H11,0) -> 0.56278243 | P11: =IF(H11>0,J11/H11,0) -> 0.78861939 | Q11: =IF(H11<=0,"Sin PIM",IF(K11/H11>=Config!$B$5,"Ejecutado",IF(J11/H11>=Config!$B$6,"Mayormente comprometido",IF(J11>0.005,"Parcialmente comprometido",IF(I11>0.005,"Solo certificado","Sin certificar"))))) -> Mayormente comprometido | R11: =IF(Q11="Sin certificar","Disponible",IF(Q11="Solo certificado","Posible",IF(Q11="Parcialmente comprometido","Parcial",IF(Q11="Mayormente comprometido","Difícil",IF(Q11="Ejecutado","No usar","Sin PIM"))))) -> Difícil | S11: =IF(OR(H11<=0,Q11="Ejecutado"),0,MAX(0,H11-J11)) -> 542124.25 | T11: 502598 | U11: 2037085 | V11: 0 | W11: 25000 | X11: s/d | Y11: s/d | Z11: s/d | AA11: s/d | AB11: s/d | AC11: s/d | AD11: GASTO CORRIENTE
A12: 001 | B12: SIN CLASIFICAR (completar en maestro.xlsx, hoja ClasifGC) | C12: 03. PLANEAMIENTO, GESTION Y RESERVA DE CONTINGENCIA | D12: 3999999 | E12: 5001031 | F12: 0298 | G12: PRESERVACION Y DIFUSION DE ACERVOS BIBLIOGRAFICOS, DOCUMENTALES Y ARCHIVISTICOS · CONSERVACION Y CATALOGACION DE ARCHIVOS Y DOCUMENTOS | H12: 1623842 | I12: 1611611.3 | J12: 1583926.5 | K12: 1213592.8 | L12: =H12-I12 -> 12230.72 | M12: =I12-J12 -> 27684.74 | N12: =H12-K12 -> 410249.25 | O12: =IF(H12>0,K12/H12,0) -> 0.74735889 | P12: =IF(H12>0,J12/H12,0) -> 0.97541912 | Q12: =IF(H12<=0,"Sin PIM",IF(K12/H12>=Config!$B$5,"Ejecutado",IF(J12/H12>=Config!$B$6,"Mayormente comprometido",IF(J12>0.005,"Parcialmente comprometido",IF(I12>0.005,"Solo certificado","Sin certificar"))))) -> Mayormente comprometido | R12: =IF(Q12="Sin certificar","Disponible",IF(Q12="Solo certificado","Posible",IF(Q12="Parcialmente comprometido","Parcial",IF(Q12="Mayormente comprometido","Difícil",IF(Q12="Ejecutado","No usar","Sin PIM"))))) -> Difícil | S12: =IF(OR(H12<=0,Q12="Ejecutado"),0,MAX(0,H12-J12)) -> 39915.46 | T12: 1076197 | U12: 540945 | V12: 0 | W12: 6700 | X12: s/d | Y12: s/d | Z12: s/d | AA12: s/d | AB12: s/d | AC12: s/d | AD12: GASTO CORRIENTE
A13: 001 | B13: SIN CLASIFICAR (completar en maestro.xlsx, hoja ClasifGC) | C13: 03. PLANEAMIENTO, GESTION Y RESERVA DE CONTINGENCIA | D13: 3999999 | E13: 5001949 | F13: 0301 | G13: DIRECCION Y GESTION REGIONAL | H13: 1255771 | I13: 1182688.9 | J13: 1102819 | K13: 800666.11 | L13: =H13-I13 -> 73082.14 | M13: =I13-J13 -> 79869.88 | N13: =H13-K13 -> 455104.89 | O13: =IF(H13>0,K13/H13,0) -> 0.63758927 | P13: =IF(H13>0,J13/H13,0) -> 0.87820071 | Q13: =IF(H13<=0,"Sin PIM",IF(K13/H13>=Config!$B$5,"Ejecutado",IF(J13/H13>=Config!$B$6,"Mayormente comprometido",IF(J13>0.005,"Parcialmente comprometido",IF(I13>0.005,"Solo certificado","Sin certificar"))))) -> Mayormente comprometido | R13: =IF(Q13="Sin certificar","Disponible",IF(Q13="Solo certificado","Posible",IF(Q13="Parcialmente comprometido","Parcial",IF(Q13="Mayormente comprometido","Difícil",IF(Q13="Ejecutado","No usar","Sin PIM"))))) -> Difícil | S13: =IF(OR(H13<=0,Q13="Ejecutado"),0,MAX(0,H13-J13)) -> 152952.02 | T13: 493713 | U13: 692246 | V13: 0 | W13: 69812 | X13: s/d | Y13: s/d | Z13: s/d | AA13: s/d | AB13: s/d | AC13: s/d | AD13: GASTO CORRIENTE
A14: 001 | B14: SIN CLASIFICAR (completar en maestro.xlsx, hoja ClasifGC) | C14: 03. PLANEAMIENTO, GESTION Y RESERVA DE CONTINGENCIA | D14: 3999999 | E14: 5001253 | F14: 0503 | G14: TRANSFERENCIA DE RECURSOS PARA LA EJECUCION DE PROYECTOS DE INVERSION · TRANSFERENCIA FINANCIERA PARA PROYECTOS DE INVERSION | H14: 1210000 | I14: 1210000 | J14: 1210000 | K14: 1210000 | L14: =H14-I14 -> 0 | M14: =I14-J14 -> 0 | N14: =H14-K14 -> 0 | O14: =IF(H14>0,K14/H14,0) -> 1 | P14: =IF(H14>0,J14/H14,0) -> 1 | Q14: =IF(H14<=0,"Sin PIM",IF(K14/H14>=Config!$B$5,"Ejecutado",IF(J14/H14>=Config!$B$6,"Mayormente comprometido",IF(J14>0.005,"Parcialmente comprometido",IF(I14>0.005,"Solo certificado","Sin certificar"))))) -> Ejecutado | R14: =IF(Q14="Sin certificar","Disponible",IF(Q14="Solo certificado","Posible",IF(Q14="Parcialmente comprometido","Parcial",IF(Q14="Mayormente comprometido","Difícil",IF(Q14="Ejecutado","No usar","Sin PIM"))))) -> No usar | S14: =IF(OR(H14<=0,Q14="Ejecutado"),0,MAX(0,H14-J14)) -> 0 | T14: 0 | U14: 0 | V14: 0 | W14: 1210000 | X14: s/d | Y14: s/d | Z14: s/d | AA14: s/d | AB14: s/d | AC14: s/d
A15: 001 | B15: SIN CLASIFICAR (completar en maestro.xlsx, hoja ClasifGC) | C15: 03. PLANEAMIENTO, GESTION Y RESERVA DE CONTINGENCIA | D15: 3999999 | E15: 5000825 | F15: 0293 | G15: GESTION DE LA INFRAESTRUCTURA · APOYO PARA EL DESARROLLO DE LOS PROYECTOS DE INVERSION | H15: 1103261 | I15: 1059124.8 | J15: 1024183.3 | K15: 825567.54 | L15: =H15-I15 -> 44136.2 | M15: =I15-J15 -> 34941.51 | N15: =H15-K15 -> 277693.46 | O15: =IF(H15>0,K15/H15,0) -> 0.74829758 | P15: =IF(H15>0,J15/H15,0) -> 0.92832366 | Q15: =IF(H15<=0,"Sin PIM",IF(K15/H15>=Config!$B$5,"Ejecutado",IF(J15/H15>=Config!$B$6,"Mayormente comprometido",IF(J15>0.005,"Parcialmente comprometido",IF(I15>0.005,"Solo certificado","Sin certificar"))))) -> Mayormente comprometido | R15: =IF(Q15="Sin certificar","Disponible",IF(Q15="Solo certificado","Posible",IF(Q15="Parcialmente comprometido","Parcial",IF(Q15="Mayormente comprometido","Difícil",IF(Q15="Ejecutado","No usar","Sin PIM"))))) -> Difícil | S15: =IF(OR(H15<=0,Q15="Ejecutado"),0,MAX(0,H15-J15)) -> 79077.71 | T15: 881261 | U15: 222000 | V15: 0 | W15: 0 | X15: s/d | Y15: s/d | Z15: s/d | AA15: s/d | AB15: s/d | AC15: s/d | AD15: GASTO CORRIENTE
A16: 001 | B16: SIN CLASIFICAR (completar en maestro.xlsx, hoja ClasifGC) | C16: 03. PLANEAMIENTO, GESTION Y RESERVA DE CONTINGENCIA | D16: 3999999 | E16: 5000486 | F16: 0289 | G16: ASESORAMIENTO Y GESTION DEL MEDIO AMBIENTE · PRESERVACION DEL MEDIO AMBIENTE Y AREAS NATURALES | H16: 993332 | I16: 906092.54 | J16: 901270.68 | K16: 644188.62 | L16: =H16-I16 -> 87239.46 | M16: =I16-J16 -> 4821.86 | N16: =H16-K16 -> 349143.38 | O16: =IF(H16>0,K16/H16,0) -> 0.6485129 | P16: =IF(H16>0,J16/H16,0) -> 0.90732069 | Q16: =IF(H16<=0,"Sin PIM",IF(K16/H16>=Config!$B$5,"Ejecutado",IF(J16/H16>=Config!$B$6,"Mayormente comprometido",IF(J16>0.005,"Parcialmente comprometido",IF(I16>0.005,"Solo certificado","Sin certificar"))))) -> Mayormente comprometido | R16: =IF(Q16="Sin certificar","Disponible",IF(Q16="Solo certificado","Posible",IF(Q16="Parcialmente comprometido","Parcial",IF(Q16="Mayormente comprometido","Difícil",IF(Q16="Ejecutado","No usar","Sin PIM"))))) -> Difícil | S16: =IF(OR(H16<=0,Q16="Ejecutado"),0,MAX(0,H16-J16)) -> 92061.32 | T16: 643691 | U16: 349641 | V16: 0 | W16: 0 | X16: s/d | Y16: s/d | Z16: s/d | AA16: s/d | AB16: s/d | AC16: s/d | AD16: GASTO CORRIENTE
A17: 001 | B17: SIN CLASIFICAR (completar en maestro.xlsx, hoja ClasifGC) | C17: 03. PLANEAMIENTO, GESTION Y RESERVA DE CONTINGENCIA | D17: 3999999 | E17: 5000688 | F17: 0290 | G17: DESARROLLO ECONOMICO REGIONAL · PROMOCION DE LA INVERSION PUBLICA Y PRIVADA | H17: 970311 | I17: 948256.66 | J17: 938404.66 | K17: 801780.79 | L17: =H17-I17 -> 22054.34 | M17: =I17-J17 -> 9852 | N17: =H17-K17 -> 168530.21 | O17: =IF(H17>0,K17/H17,0) -> 0.8263132 | P17: =IF(H17>0,J17/H17,0) -> 0.96711741 | Q17: =IF(H17<=0,"Sin PIM",IF(K17/H17>=Config!$B$5,"Ejecutado",IF(J17/H17>=Config!$B$6,"Mayormente comprometido",IF(J17>0.005,"Parcialmente comprometido",IF(I17>0.005,"Solo certificado","Sin certificar"))))) -> Mayormente comprometido | R17: =IF(Q17="Sin certificar","Disponible",IF(Q17="Solo certificado","Posible",IF(Q17="Parcialmente comprometido","Parcial",IF(Q17="Mayormente comprometido","Difícil",IF(Q17="Ejecutado","No usar","Sin PIM"))))) -> Difícil | S17: =IF(OR(H17<=0,Q17="Ejecutado"),0,MAX(0,H17-J17)) -> 31906.34 | T17: 463520 | U17: 506791 | V17: 0 | W17: 0 | X17: s/d | Y17: s/d | Z17: s/d | AA17: s/d | AB17: s/d | AC17: s/d | AD17: GASTO CORRIENTE
A18: 001 | B18: SIN CLASIFICAR (completar en maestro.xlsx, hoja ClasifGC) | C18: 03. PLANEAMIENTO, GESTION Y RESERVA DE CONTINGENCIA | D18: 3999999 | E18: 5000861 | F18: 0294 | G18: IMAGEN INSTITUCIONAL | H18: 933605 | I18: 864347.99 | J18: 853739.99 | K18: 735803.28 | L18: =H18-I18 -> 69257.01 | M18: =I18-J18 -> 10608 | N18: =H18-K18 -> 197801.72 | O18: =IF(H18>0,K18/H18,0) -> 0.78813125 | P18: =IF(H18>0,J18/H18,0) -> 0.91445525 | Q18: =IF(H18<=0,"Sin PIM",IF(K18/H18>=Config!$B$5,"Ejecutado",IF(J18/H18>=Config!$B$6,"Mayormente comprometido",IF(J18>0.005,"Parcialmente comprometido",IF(I18>0.005,"Solo certificado","Sin certificar"))))) -> Mayormente comprometido | R18: =IF(Q18="Sin certificar","Disponible",IF(Q18="Solo certificado","Posible",IF(Q18="Parcialmente comprometido","Parcial",IF(Q18="Mayormente comprometido","Difícil",IF(Q18="Ejecutado","No usar","Sin PIM"))))) -> Difícil | S18: =IF(OR(H18<=0,Q18="Ejecutado"),0,MAX(0,H18-J18)) -> 79865.01 | T18: 629248 | U18: 304357 | V18: 0 | W18: 0 | X18: s/d | Y18: s/d | Z18: s/d | AA18: s/d | AB18: s/d | AC18: s/d | AD18: GASTO CORRIENTE
A19: 001 | B19: SIN CLASIFICAR (completar en maestro.xlsx, hoja ClasifGC) | C19: 03. PLANEAMIENTO, GESTION Y RESERVA DE CONTINGENCIA | D19: 3999999 | E19: 5000002 | F19: 0201 | G19: CONDUCCION Y ORIENTACION SUPERIOR · CONDUCCION DE LA POLITICA INSTITUCIONAL | H19: 763130 | I19: 685481.91 | J19: 643674.15 | K19: 580873.67 | L19: =H19-I19 -> 77648.09 | M19: =I19-J19 -> 41807.76 | N19: =H19-K19 -> 182256.33 | O19: =IF(H19>0,K19/H19,0) -> 0.76117263 | P19: =IF(H19>0,J19/H19,0) -> 0.84346592 | Q19: =IF(H19<=0,"Sin PIM",IF(K19/H19>=Config!$B$5,"Ejecutado",IF(J19/H19>=Config!$B$6,"Mayormente comprometido",IF(J19>0.005,"Parcialmente comprometido",IF(I19>0.005,"Solo certificado","Sin certificar"))))) -> Mayormente comprometido | R19: =IF(Q19="Sin certificar","Disponible",IF(Q19="Solo certificado","Posible",IF(Q19="Parcialmente comprometido","Parcial",IF(Q19="Mayormente comprometido","Difícil",IF(Q19="Ejecutado","No usar","Sin PIM"))))) -> Difícil | S19: =IF(OR(H19<=0,Q19="Ejecutado"),0,MAX(0,H19-J19)) -> 119455.85 | T19: 504356 | U19: 258774 | V19: 0 | W19: 0 | X19: s/d | Y19: s/d | Z19: s/d | AA19: s/d | AB19: s/d | AC19: s/d | AD19: GASTO CORRIENTE
A20: 001 | B20: SIN CLASIFICAR (completar en maestro.xlsx, hoja ClasifGC) | C20: 03. PLANEAMIENTO, GESTION Y RESERVA DE CONTINGENCIA | D20: 3999999 | E20: 5001253 | F20: 0500 | G20: TRANSFERENCIA DE RECURSOS PARA LA EJECUCION DE PROYECTOS DE INVERSION · TRANSFERENCIA FINANCIERA PARA PROYECTOS DE INVERSION | H20: 761010 | I20: 761010 | J20: 761010 | K20: 761010 | L20: =H20-I20 -> 0 | M20: =I20-J20 -> 0 | N20: =H20-K20 -> 0 | O20: =IF(H20>0,K20/H20,0) -> 1 | P20: =IF(H20>0,J20/H20,0) -> 1 | Q20: =IF(H20<=0,"Sin PIM",IF(K20/H20>=Config!$B$5,"Ejecutado",IF(J20/H20>=Config!$B$6,"Mayormente comprometido",IF(J20>0.005,"Parcialmente comprometido",IF(I20>0.005,"Solo certificado","Sin certificar"))))) -> Ejecutado | R20: =IF(Q20="Sin certificar","Disponible",IF(Q20="Solo certificado","Posible",IF(Q20="Parcialmente comprometido","Parcial",IF(Q20="Mayormente comprometido","Difícil",IF(Q20="Ejecutado","No usar","Sin PIM"))))) -> No usar | S20: =IF(OR(H20<=0,Q20="Ejecutado"),0,MAX(0,H20-J20)) -> 0 | T20: 0 | U20: 0 | V20: 0 | W20: 761010 | X20: s/d | Y20: s/d | Z20: s/d | AA20: s/d | AB20: s/d | AC20: s/d
A21: 001 | B21: SIN CLASIFICAR (completar en maestro.xlsx, hoja ClasifGC) | C21: 03. PLANEAMIENTO, GESTION Y RESERVA DE CONTINGENCIA | D21: 3999999 | E21: 5000006 | F21: 0211 | G21: ACCIONES DE CONTROL Y AUDITORIA · MONITOREO DEL SISTEMA DE CONTROL | H21: 636054 | I21: 449913.28 | J21: 445815.28 | K21: 300766.77 | L21: =H21-I21 -> 186140.72 | M21: =I21-J21 -> 4098 | N21: =H21-K21 -> 335287.23 | O21: =IF(H21>0,K21/H21,0) -> 0.47286358 | P21: =IF(H21>0,J21/H21,0) -> 0.70090791 | Q21: =IF(H21<=0,"Sin PIM",IF(K21/H21>=Config!$B$5,"Ejecutado",IF(J21/H21>=Config!$B$6,"Mayormente comprometido",IF(J21>0.005,"Parcialmente comprometido",IF(I21>0.005,"Solo certificado","Sin certificar"))))) -> Mayormente comprometido | R21: =IF(Q21="Sin certificar","Disponible",IF(Q21="Solo certificado","Posible",IF(Q21="Parcialmente comprometido","Parcial",IF(Q21="Mayormente comprometido","Difícil",IF(Q21="Ejecutado","No usar","Sin PIM"))))) -> Difícil | S21: =IF(OR(H21<=0,Q21="Ejecutado"),0,MAX(0,H21-J21)) -> 190238.72 | T21: 316654 | U21: 197900 | V21: 0 | W21: 121500 | X21: s/d | Y21: s/d | Z21: s/d | AA21: s/d | AB21: s/d | AC21: s/d | AD21: GASTO CORRIENTE
A22: 001 | B22: SIN CLASIFICAR (completar en maestro.xlsx, hoja ClasifGC) | C22: 03. PLANEAMIENTO, GESTION Y RESERVA DE CONTINGENCIA | D22: 3999999 | E22: 5000004 | F22: 0209 | G22: ASESORAMIENTO TECNICO Y JURIDICO · ASESORAMIENTO DE NATURALEZA JURIDICA | H22: 533472 | I22: 497493.34 | J22: 482993.45 | K22: 375952.6 | L22: =H22-I22 -> 35978.66 | M22: =I22-J22 -> 14499.89 | N22: =H22-K22 -> 157519.4 | O22: =IF(H22>0,K22/H22,0) -> 0.7047279 | P22: =IF(H22>0,J22/H22,0) -> 0.90537732 | Q22: =IF(H22<=0,"Sin PIM",IF(K22/H22>=Config!$B$5,"Ejecutado",IF(J22/H22>=Config!$B$6,"Mayormente comprometido",IF(J22>0.005,"Parcialmente comprometido",IF(I22>0.005,"Solo certificado","Sin certificar"))))) -> Mayormente comprometido | R22: =IF(Q22="Sin certificar","Disponible",IF(Q22="Solo certificado","Posible",IF(Q22="Parcialmente comprometido","Parcial",IF(Q22="Mayormente comprometido","Difícil",IF(Q22="Ejecutado","No usar","Sin PIM"))))) -> Difícil | S22: =IF(OR(H22<=0,Q22="Ejecutado"),0,MAX(0,H22-J22)) -> 50478.55 | T22: 415061 | U22: 115411 | V22: 0 | W22: 3000 | X22: s/d | Y22: s/d | Z22: s/d | AA22: s/d | AB22: s/d | AC22: s/d | AD22: GASTO CORRIENTE
A23: 001 | B23: SIN CLASIFICAR (completar en maestro.xlsx, hoja ClasifGC) | C23: 03. PLANEAMIENTO, GESTION Y RESERVA DE CONTINGENCIA | D23: 3999999 | E23: 5000007 | F23: 0212 | G23: DEFENSA JUDICIAL DEL ESTADO · DEFENSA JURIDICA DEL ESTADO | H23: 508796 | I23: 490348.45 | J23: 487466.89 | K23: 341815.41 | L23: =H23-I23 -> 18447.55 | M23: =I23-J23 -> 2881.56 | N23: =H23-K23 -> 166980.59 | O23: =IF(H23>0,K23/H23,0) -> 0.6718123 | P23: =IF(H23>0,J23/H23,0) -> 0.95807925 | Q23: =IF(H23<=0,"Sin PIM",IF(K23/H23>=Config!$B$5,"Ejecutado",IF(J23/H23>=Config!$B$6,"Mayormente comprometido",IF(J23>0.005,"Parcialmente comprometido",IF(I23>0.005,"Solo certificado","Sin certificar"))))) -> Mayormente comprometido | R23: =IF(Q23="Sin certificar","Disponible",IF(Q23="Solo certificado","Posible",IF(Q23="Parcialmente comprometido","Parcial",IF(Q23="Mayormente comprometido","Difícil",IF(Q23="Ejecutado","No usar","Sin PIM"))))) -> Difícil | S23: =IF(OR(H23<=0,Q23="Ejecutado"),0,MAX(0,H23-J23)) -> 21329.11 | T23: 335275 | U23: 173521 | V23: 0 | W23: 0 | X23: s/d | Y23: s/d | Z23: s/d | AA23: s/d | AB23: s/d | AC23: s/d | AD23: GASTO CORRIENTE
A24: 001 | B24: SIN CLASIFICAR (completar en maestro.xlsx, hoja ClasifGC) | C24: 03. PLANEAMIENTO, GESTION Y RESERVA DE CONTINGENCIA | D24: 3999999 | E24: 5000825 | F24: 0312 | G24: GESTION DE LA INFRAESTRUCTURA · GESTION DE ESTUDIOS Y PROYECTOS DE INVERSION | H24: 306980 | I24: 233409.92 | J24: 233409.92 | K24: 130413.61 | L24: =H24-I24 -> 73570.08 | M24: =I24-J24 -> 0 | N24: =H24-K24 -> 176566.39 | O24: =IF(H24>0,K24/H24,0) -> 0.42482771 | P24: =IF(H24>0,J24/H24,0) -> 0.76034243 | Q24: =IF(H24<=0,"Sin PIM",IF(K24/H24>=Config!$B$5,"Ejecutado",IF(J24/H24>=Config!$B$6,"Mayormente comprometido",IF(J24>0.005,"Parcialmente comprometido",IF(I24>0.005,"Solo certificado","Sin certificar"))))) -> Mayormente comprometido | R24: =IF(Q24="Sin certificar","Disponible",IF(Q24="Solo certificado","Posible",IF(Q24="Parcialmente comprometido","Parcial",IF(Q24="Mayormente comprometido","Difícil",IF(Q24="Ejecutado","No usar","Sin PIM"))))) -> Difícil | S24: =IF(OR(H24<=0,Q24="Ejecutado"),0,MAX(0,H24-J24)) -> 73570.08 | T24: 0 | U24: 306980 | V24: 0 | W24: 0 | X24: s/d | Y24: s/d | Z24: s/d | AA24: s/d | AB24: s/d | AC24: s/d | AD24: GASTO CORRIENTE
A25: 001 | B25: SIN CLASIFICAR (completar en maestro.xlsx, hoja ClasifGC) | C25: 03. PLANEAMIENTO, GESTION Y RESERVA DE CONTINGENCIA | D25: 3999999 | E25: 5000002 | F25: 0200 | G25: CONDUCCION Y ORIENTACION SUPERIOR · GESTION ADMINISTRATIVA | H25: 254990 | I25: 254990 | J25: 254990 | K25: 162678.6 | L25: =H25-I25 -> 0 | M25: =I25-J25 -> 0 | N25: =H25-K25 -> 92311.4 | O25: =IF(H25>0,K25/H25,0) -> 0.63798031 | P25: =IF(H25>0,J25/H25,0) -> 1 | Q25: =IF(H25<=0,"Sin PIM",IF(K25/H25>=Config!$B$5,"Ejecutado",IF(J25/H25>=Config!$B$6,"Mayormente comprometido",IF(J25>0.005,"Parcialmente comprometido",IF(I25>0.005,"Solo certificado","Sin certificar"))))) -> Mayormente comprometido | R25: =IF(Q25="Sin certificar","Disponible",IF(Q25="Solo certificado","Posible",IF(Q25="Parcialmente comprometido","Parcial",IF(Q25="Mayormente comprometido","Difícil",IF(Q25="Ejecutado","No usar","Sin PIM"))))) -> Difícil | S25: =IF(OR(H25<=0,Q25="Ejecutado"),0,MAX(0,H25-J25)) -> 0 | T25: 254990 | U25: 0 | V25: 0 | W25: 0 | X25: s/d | Y25: s/d | Z25: s/d | AA25: s/d | AB25: s/d | AC25: s/d | AD25: GASTO CORRIENTE
A26: 001 | B26: SIN CLASIFICAR (completar en maestro.xlsx, hoja ClasifGC) | C26: 03. PLANEAMIENTO, GESTION Y RESERVA DE CONTINGENCIA | D26: 3999999 | E26: 5000001 | F26: 0472 | G26: PLANEAMIENTO Y PRESUPUESTO · FORTALECIMIENTO DE LOS GOBIERNOS REGIONALES EN MATERIA DE LAS FUNCIONES SECTORIALES TRANSFERIDAS | H26: 217664 | I26: 162400 | J26: 162400 | K26: 114200 | L26: =H26-I26 -> 55264 | M26: =I26-J26 -> 0 | N26: =H26-K26 -> 103464 | O26: =IF(H26>0,K26/H26,0) -> 0.52466186 | P26: =IF(H26>0,J26/H26,0) -> 0.74610409 | Q26: =IF(H26<=0,"Sin PIM",IF(K26/H26>=Config!$B$5,"Ejecutado",IF(J26/H26>=Config!$B$6,"Mayormente comprometido",IF(J26>0.005,"Parcialmente comprometido",IF(I26>0.005,"Solo certificado","Sin certificar"))))) -> Mayormente comprometido | R26: =IF(Q26="Sin certificar","Disponible",IF(Q26="Solo certificado","Posible",IF(Q26="Parcialmente comprometido","Parcial",IF(Q26="Mayormente comprometido","Difícil",IF(Q26="Ejecutado","No usar","Sin PIM"))))) -> Difícil | S26: =IF(OR(H26<=0,Q26="Ejecutado"),0,MAX(0,H26-J26)) -> 55264 | T26: 0 | U26: 217664 | V26: 0 | W26: 0 | X26: s/d | Y26: s/d | Z26: s/d | AA26: s/d | AB26: s/d | AC26: s/d | AD26: GASTO CORRIENTE
A27: 001 | B27: SIN CLASIFICAR (completar en maestro.xlsx, hoja ClasifGC) | C27: 03. PLANEAMIENTO, GESTION Y RESERVA DE CONTINGENCIA | D27: 3999999 | E27: 5001247 | F27: 0350 | G27: SUPERVISION Y LIQUIDACION DE OBRAS · SUPERVISION Y LIQUIDACION DE PROYECTOS DE INVERSION PUBLICA | H27: 118429 | I27: 102026.4 | J27: 101601.2 | K27: 34391.2 | L27: =H27-I27 -> 16402.6 | M27: =I27-J27 -> 425.2 | N27: =H27-K27 -> 84037.8 | O27: =IF(H27>0,K27/H27,0) -> 0.29039509 | P27: =IF(H27>0,J27/H27,0) -> 0.85790811 | Q27: =IF(H27<=0,"Sin PIM",IF(K27/H27>=Config!$B$5,"Ejecutado",IF(J27/H27>=Config!$B$6,"Mayormente comprometido",IF(J27>0.005,"Parcialmente comprometido",IF(I27>0.005,"Solo certificado","Sin certificar"))))) -> Mayormente comprometido | R27: =IF(Q27="Sin certificar","Disponible",IF(Q27="Solo certificado","Posible",IF(Q27="Parcialmente comprometido","Parcial",IF(Q27="Mayormente comprometido","Difícil",IF(Q27="Ejecutado","No usar","Sin PIM"))))) -> Difícil | S27: =IF(OR(H27<=0,Q27="Ejecutado"),0,MAX(0,H27-J27)) -> 16827.8 | T27: 0 | U27: 104741 | V27: 0 | W27: 13688 | X27: s/d | Y27: s/d | Z27: s/d | AA27: s/d | AB27: s/d | AC27: s/d | AD27: GASTO CORRIENTE
A28: 001 | B28: SIN CLASIFICAR (completar en maestro.xlsx, hoja ClasifGC) | C28: 03. PLANEAMIENTO, GESTION Y RESERVA DE CONTINGENCIA | D28: 3999999 | E28: 5000003 | F28: 0205 | G28: GESTION ADMINISTRATIVA · PAGO DE CUOTAS DEL REPRO-AFP | H28: 114535 | I28: 114535 | J28: 114535 | K28: 85901.13 | L28: =H28-I28 -> 0 | M28: =I28-J28 -> 0 | N28: =H28-K28 -> 28633.87 | O28: =IF(H28>0,K28/H28,0) -> 0.74999895 | P28: =IF(H28>0,J28/H28,0) -> 1 | Q28: =IF(H28<=0,"Sin PIM",IF(K28/H28>=Config!$B$5,"Ejecutado",IF(J28/H28>=Config!$B$6,"Mayormente comprometido",IF(J28>0.005,"Parcialmente comprometido",IF(I28>0.005,"Solo certificado","Sin certificar"))))) -> Mayormente comprometido | R28: =IF(Q28="Sin certificar","Disponible",IF(Q28="Solo certificado","Posible",IF(Q28="Parcialmente comprometido","Parcial",IF(Q28="Mayormente comprometido","Difícil",IF(Q28="Ejecutado","No usar","Sin PIM"))))) -> Difícil | S28: =IF(OR(H28<=0,Q28="Ejecutado"),0,MAX(0,H28-J28)) -> 0 | T28: 114535 | U28: 0 | V28: 0 | W28: 0 | X28: s/d | Y28: s/d | Z28: s/d | AA28: s/d | AB28: s/d | AC28: s/d | AD28: GASTO CORRIENTE
A29: 001 | B29: SIN CLASIFICAR (completar en maestro.xlsx, hoja ClasifGC) | C29: 03. PLANEAMIENTO, GESTION Y RESERVA DE CONTINGENCIA | D29: 3999999 | E29: 5000698 | F29: 0292 | G29: DESARROLLO SOCIAL REGIONAL · ASILO DE ANCIANOS VIRGEN DEL ROSARIO DE CHUCUITO | H29: 83162 | I29: 73936 | J29: 73936 | K29: 42003.67 | L29: =H29-I29 -> 9226 | M29: =I29-J29 -> 0 | N29: =H29-K29 -> 41158.33 | O29: =IF(H29>0,K29/H29,0) -> 0.50508249 | P29: =IF(H29>0,J29/H29,0) -> 0.88905991 | Q29: =IF(H29<=0,"Sin PIM",IF(K29/H29>=Config!$B$5,"Ejecutado",IF(J29/H29>=Config!$B$6,"Mayormente comprometido",IF(J29>0.005,"Parcialmente comprometido",IF(I29>0.005,"Solo certificado","Sin certificar"))))) -> Mayormente comprometido | R29: =IF(Q29="Sin certificar","Disponible",IF(Q29="Solo certificado","Posible",IF(Q29="Parcialmente comprometido","Parcial",IF(Q29="Mayormente comprometido","Difícil",IF(Q29="Ejecutado","No usar","Sin PIM"))))) -> Difícil | S29: =IF(OR(H29<=0,Q29="Ejecutado"),0,MAX(0,H29-J29)) -> 9226 | T29: 58601 | U29: 23061 | V29: 0 | W29: 1500 | X29: s/d | Y29: s/d | Z29: s/d | AA29: s/d | AB29: s/d | AC29: s/d | AD29: GASTO CORRIENTE
A30: 001 | B30: SIN CLASIFICAR (completar en maestro.xlsx, hoja ClasifGC) | C30: 03. PLANEAMIENTO, GESTION Y RESERVA DE CONTINGENCIA | D30: 3999999 | E30: 5000005 | F30: 0210 | G30: GESTION DE RECURSOS HUMANOS · IMPLEMENTACION DE NEGOCIACION COLECTIVA DESCENTRALIZADA | H30: 77042 | I30: 0 | J30: 0 | K30: 0 | L30: =H30-I30 -> 77042 | M30: =I30-J30 -> 0 | N30: =H30-K30 -> 77042 | O30: =IF(H30>0,K30/H30,0) -> 0 | P30: =IF(H30>0,J30/H30,0) -> 0 | Q30: =IF(H30<=0,"Sin PIM",IF(K30/H30>=Config!$B$5,"Ejecutado",IF(J30/H30>=Config!$B$6,"Mayormente comprometido",IF(J30>0.005,"Parcialmente comprometido",IF(I30>0.005,"Solo certificado","Sin certificar"))))) -> Sin certificar | R30: =IF(Q30="Sin certificar","Disponible",IF(Q30="Solo certificado","Posible",IF(Q30="Parcialmente comprometido","Parcial",IF(Q30="Mayormente comprometido","Difícil",IF(Q30="Ejecutado","No usar","Sin PIM"))))) -> Disponible | S30: =IF(OR(H30<=0,Q30="Ejecutado"),0,MAX(0,H30-J30)) -> 77042 | T30: 0 | U30: 0 | V30: 77042 | W30: 0 | X30: s/d | Y30: s/d | Z30: s/d | AA30: s/d | AB30: s/d | AC30: s/d | AD30: GASTO CORRIENTE
A31: 001 | B31: SIN CLASIFICAR (completar en maestro.xlsx, hoja ClasifGC) | C31: 03. PLANEAMIENTO, GESTION Y RESERVA DE CONTINGENCIA | D31: 3999999 | E31: 5000003 | F31: 0204 | G31: GESTION ADMINISTRATIVA · PAGO DE PLANILLAS | H31: 27333 | I31: 27333 | J31: 22410 | K31: 0 | L31: =H31-I31 -> 0 | M31: =I31-J31 -> 4923 | N31: =H31-K31 -> 27333 | O31: =IF(H31>0,K31/H31,0) -> 0 | P31: =IF(H31>0,J31/H31,0) -> 0.81988805 | Q31: =IF(H31<=0,"Sin PIM",IF(K31/H31>=Config!$B$5,"Ejecutado",IF(J31/H31>=Config!$B$6,"Mayormente comprometido",IF(J31>0.005,"Parcialmente comprometido",IF(I31>0.005,"Solo certificado","Sin certificar"))))) -> Mayormente comprometido | R31: =IF(Q31="Sin certificar","Disponible",IF(Q31="Solo certificado","Posible",IF(Q31="Parcialmente comprometido","Parcial",IF(Q31="Mayormente comprometido","Difícil",IF(Q31="Ejecutado","No usar","Sin PIM"))))) -> Difícil | S31: =IF(OR(H31<=0,Q31="Ejecutado"),0,MAX(0,H31-J31)) -> 4923 | T31: 27333 | U31: 0 | V31: 0 | W31: 0 | X31: s/d | Y31: s/d | Z31: s/d | AA31: s/d | AB31: s/d | AC31: s/d | AD31: GASTO CORRIENTE
A32: 001 | B32: SIN CLASIFICAR (completar en maestro.xlsx, hoja ClasifGC) | C32: 03. PLANEAMIENTO, GESTION Y RESERVA DE CONTINGENCIA | D32: 3999999 | E32: 5000001 | F32: 0198 | G32: PLANEAMIENTO Y PRESUPUESTO · CONDUCCION, SUPERVISION Y EVALUACION DE LOS PLANES Y PROGRAMAS, PRESUPUESTO Y COOPERACION TECNICA | H32: 0 | I32: 0 | J32: 0 | K32: 0 | L32: =H32-I32 -> 0 | M32: =I32-J32 -> 0 | N32: =H32-K32 -> 0 | O32: =IF(H32>0,K32/H32,0) -> 0 | P32: =IF(H32>0,J32/H32,0) -> 0 | Q32: =IF(H32<=0,"Sin PIM",IF(K32/H32>=Config!$B$5,"Ejecutado",IF(J32/H32>=Config!$B$6,"Mayormente comprometido",IF(J32>0.005,"Parcialmente comprometido",IF(I32>0.005,"Solo certificado","Sin certificar"))))) -> Sin PIM | R32: =IF(Q32="Sin certificar","Disponible",IF(Q32="Solo certificado","Posible",IF(Q32="Parcialmente comprometido","Parcial",IF(Q32="Mayormente comprometido","Difícil",IF(Q32="Ejecutado","No usar","Sin PIM"))))) -> Sin PIM | S32: =IF(OR(H32<=0,Q32="Ejecutado"),0,MAX(0,H32-J32)) -> 0 | T32: 0 | U32: 0 | V32: 0 | W32: 0 | X32: s/d | Y32: s/d | Z32: s/d | AA32: s/d | AB32: s/d | AC32: s/d | AD32: GASTO CORRIENTE
... A69: 001 | B69: SIN CLASIFICAR (completar en maestro.xlsx, hoja ClasifGC) | C69: 15. TRANSPORTE | D69: 3999999 | E69: 5000936 | F69: 0295 | G69: MANTENIMIENTO DE INFRAESTRUCTURA PUBLICA · MEJORAMIENTO DE INFRAESTRUCTURA SOCIAL | H69: 435935 | I69: 0 | J69: 0 | K69: 0 | L69: =H69-I69 -> 435935 | M69: =I69-J69 -> 0 | N69: =H69-K69 -> 435935 | O69: =IF(H69>0,K69/H69,0) -> 0 | P69: =IF(H69>0,J69/H69,0) -> 0 | Q69: =IF(H69<=0,"Sin PIM",IF(K69/H69>=Config!$B$5,"Ejecutado",IF(J69/H69>=Config!$B$6,"Mayormente comprometido",IF(J69>0.005,"Parcialmente comprometido",IF(I69>0.005,"Solo certificado","Sin certificar"))))) -> Sin certificar | R69: =IF(Q69="Sin certificar","Disponible",IF(Q69="Solo certificado","Posible",IF(Q69="Parcialmente comprometido","Parcial",IF(Q69="Mayormente comprometido","Difícil",IF(Q69="Ejecutado","No usar","Sin PIM"))))) -> Disponible | S69: =IF(OR(H69<=0,Q69="Ejecutado"),0,MAX(0,H69-J69)) -> 435935 | T69: 0 | U69: 435935 | V69: 0 | W69: 0 | X69: s/d | Y69: s/d | Z69: s/d | AA69: s/d | AB69: s/d | AC69: s/d | AD69: GASTO CORRIENTE
A70: 001 | B70: SIN CLASIFICAR (completar en maestro.xlsx, hoja ClasifGC) | C70: 17. AMBIENTE | D70: 3000676 | E70: 5005122 | F70: 0527 | G70: PROPUESTAS DE CREACION Y/O CATEGORIZACION DE AREAS NATURALES PROTEGIDAS ELABORADAS | H70: 17500 | I70: 0 | J70: 0 | K70: 0 | L70: =H70-I70 -> 17500 | M70: =I70-J70 -> 0 | N70: =H70-K70 -> 17500 | O70: =IF(H70>0,K70/H70,0) -> 0 | P70: =IF(H70>0,J70/H70,0) -> 0 | Q70: =IF(H70<=0,"Sin PIM",IF(K70/H70>=Config!$B$5,"Ejecutado",IF(J70/H70>=Config!$B$6,"Mayormente comprometido",IF(J70>0.005,"Parcialmente comprometido",IF(I70>0.005,"Solo certificado","Sin certificar"))))) -> Sin certificar | R70: =IF(Q70="Sin certificar","Disponible",IF(Q70="Solo certificado","Posible",IF(Q70="Parcialmente comprometido","Parcial",IF(Q70="Mayormente comprometido","Difícil",IF(Q70="Ejecutado","No usar","Sin PIM"))))) -> Disponible | S70: =IF(OR(H70<=0,Q70="Ejecutado"),0,MAX(0,H70-J70)) -> 17500 | T70: 0 | U70: 17500 | V70: 0 | W70: 0 | X70: s/d | Y70: s/d | Z70: s/d | AA70: s/d | AB70: s/d | AC70: s/d
A71: 001 | B71: SIN CLASIFICAR (completar en maestro.xlsx, hoja ClasifGC) | C71: 18. SANEAMIENTO | D71: 3000882 | E71: 5006299 | F71: 0017 | G71: POTABILIZACION Y OTRAS FORMAS DE DESINFECCION Y TRATAMIENTO · POTABILIZACION Y OTRAS FORMAS DE DESINFECCION Y TRATAMIENTO | H71: 685373 | I71: 621850 | J71: 627850 | K71: 108850 | L71: =H71-I71 -> 63523 | M71: =I71-J71 -> -6000 | N71: =H71-K71 -> 576523 | O71: =IF(H71>0,K71/H71,0) -> 0.15881863 | P71: =IF(H71>0,J71/H71,0) -> 0.91607052 | Q71: =IF(H71<=0,"Sin PIM",IF(K71/H71>=Config!$B$5,"Ejecutado",IF(J71/H71>=Config!$B$6,"Mayormente comprometido",IF(J71>0.005,"Parcialmente comprometido",IF(I71>0.005,"Solo certificado","Sin certificar"))))) -> Mayormente comprometido | R71: =IF(Q71="Sin certificar","Disponible",IF(Q71="Solo certificado","Posible",IF(Q71="Parcialmente comprometido","Parcial",IF(Q71="Mayormente comprometido","Difícil",IF(Q71="Ejecutado","No usar","Sin PIM"))))) -> Difícil | S71: =IF(OR(H71<=0,Q71="Ejecutado"),0,MAX(0,H71-J71)) -> 57523 | T71: 0 | U71: 204501 | V71: 0 | W71: 480872 | X71: s/d | Y71: s/d | Z71: s/d | AA71: s/d | AB71: s/d | AC71: s/d | AD71: GASTO CORRIENTE
A72: 001 | B72: SIN CLASIFICAR (completar en maestro.xlsx, hoja ClasifGC) | C72: 18. SANEAMIENTO | D72: 3000882 | E72: 5006302 | F72: 0018 | G72: FORTALECIMIENTO DE CAPACIDADES A PRESTADORES, GL - ATM y GR - D/GRVCS · FORTALECIMIENTO DE CAPACIDADES A PRESTADORES DE LOS SERVICIOS DE AGUA Y DISPOSICION SANITARIA DE EXCRETAS | H72: 483570 | I72: 446040 | J72: 446040 | K72: 89208 | L72: =H72-I72 -> 37530 | M72: =I72-J72 -> 0 | N72: =H72-K72 -> 394362 | O72: =IF(H72>0,K72/H72,0) -> 0.18447795 | P72: =IF(H72>0,J72/H72,0) -> 0.92238973 | Q72: =IF(H72<=0,"Sin PIM",IF(K72/H72>=Config!$B$5,"Ejecutado",IF(J72/H72>=Config!$B$6,"Mayormente comprometido",IF(J72>0.005,"Parcialmente comprometido",IF(I72>0.005,"Solo certificado","Sin certificar"))))) -> Mayormente comprometido | R72: =IF(Q72="Sin certificar","Disponible",IF(Q72="Solo certificado","Posible",IF(Q72="Parcialmente comprometido","Parcial",IF(Q72="Mayormente comprometido","Difícil",IF(Q72="Ejecutado","No usar","Sin PIM"))))) -> Difícil | S72: =IF(OR(H72<=0,Q72="Ejecutado"),0,MAX(0,H72-J72)) -> 37530 | T72: 0 | U72: 483570 | V72: 0 | W72: 0 | X72: s/d | Y72: s/d | Z72: s/d | AA72: s/d | AB72: s/d | AC72: s/d | AD72: GASTO CORRIENTE
A73: 001 | B73: SIN CLASIFICAR (completar en maestro.xlsx, hoja ClasifGC) | C73: 18. SANEAMIENTO | D73: 3000882 | E73: 5006304 | F73: 0466 | G73: MONITOREO DE LA PRESTACION DE LOS SERVICIOS DE AGUA POTABLE Y DISPOSICION SANITARIA DE EXCRETAS PARA HOGARES CONCENTRADOS | H73: 198613 | I73: 190176 | J73: 190176 | K73: 123000 | L73: =H73-I73 -> 8437 | M73: =I73-J73 -> 0 | N73: =H73-K73 -> 75613 | O73: =IF(H73>0,K73/H73,0) -> 0.61929481 | P73: =IF(H73>0,J73/H73,0) -> 0.9575204 | Q73: =IF(H73<=0,"Sin PIM",IF(K73/H73>=Config!$B$5,"Ejecutado",IF(J73/H73>=Config!$B$6,"Mayormente comprometido",IF(J73>0.005,"Parcialmente comprometido",IF(I73>0.005,"Solo certificado","Sin certificar"))))) -> Mayormente comprometido | R73: =IF(Q73="Sin certificar","Disponible",IF(Q73="Solo certificado","Posible",IF(Q73="Parcialmente comprometido","Parcial",IF(Q73="Mayormente comprometido","Difícil",IF(Q73="Ejecutado","No usar","Sin PIM"))))) -> Difícil | S73: =IF(OR(H73<=0,Q73="Ejecutado"),0,MAX(0,H73-J73)) -> 8437 | T73: 0 | U73: 198613 | V73: 0 | W73: 0 | X73: s/d | Y73: s/d | Z73: s/d | AA73: s/d | AB73: s/d | AC73: s/d | AD73: GASTO CORRIENTE
A74: 001 | B74: SIN CLASIFICAR (completar en maestro.xlsx, hoja ClasifGC) | C74: 18. SANEAMIENTO | D74: 3000882 | E74: 5006302 | F74: 0019 | G74: FORTALECIMIENTO DE CAPACIDADES A PRESTADORES, GL - ATM y GR - D/GRVCS · FORTALECIMIENTO DE CAPACIDADES A GOBIERNOS LOCALES - AREAS TECNICAS MUNICIPALES | H74: 148590 | I74: 134201.4 | J74: 134201.4 | K74: 26840.28 | L74: =H74-I74 -> 14388.6 | M74: =I74-J74 -> 0 | N74: =H74-K74 -> 121749.72 | O74: =IF(H74>0,K74/H74,0) -> 0.18063315 | P74: =IF(H74>0,J74/H74,0) -> 0.90316576 | Q74: =IF(H74<=0,"Sin PIM",IF(K74/H74>=Config!$B$5,"Ejecutado",IF(J74/H74>=Config!$B$6,"Mayormente comprometido",IF(J74>0.005,"Parcialmente comprometido",IF(I74>0.005,"Solo certificado","Sin certificar"))))) -> Mayormente comprometido | R74: =IF(Q74="Sin certificar","Disponible",IF(Q74="Solo certificado","Posible",IF(Q74="Parcialmente comprometido","Parcial",IF(Q74="Mayormente comprometido","Difícil",IF(Q74="Ejecutado","No usar","Sin PIM"))))) -> Difícil | S74: =IF(OR(H74<=0,Q74="Ejecutado"),0,MAX(0,H74-J74)) -> 14388.6 | T74: 0 | U74: 148590 | V74: 0 | W74: 0 | X74: s/d | Y74: s/d | Z74: s/d | AA74: s/d | AB74: s/d | AC74: s/d | AD74: GASTO CORRIENTE
A75: 001 | B75: SIN CLASIFICAR (completar en maestro.xlsx, hoja ClasifGC) | C75: 20. SALUD | D75: 3000927 | E75: 5004428 | F75: 0468 | G75: VIGILANCIA DE LA CALIDAD DEL AGUA PARA EL CONSUMO HUMANO | H75: 295200 | I75: 295200 | J75: 0 | K75: 0 | L75: =H75-I75 -> 0 | M75: =I75-J75 -> 295200 | N75: =H75-K75 -> 295200 | O75: =IF(H75>0,K75/H75,0) -> 0 | P75: =IF(H75>0,J75/H75,0) -> 0 | Q75: =IF(H75<=0,"Sin PIM",IF(K75/H75>=Config!$B$5,"Ejecutado",IF(J75/H75>=Config!$B$6,"Mayormente comprometido",IF(J75>0.005,"Parcialmente comprometido",IF(I75>0.005,"Solo certificado","Sin certificar"))))) -> Solo certificado | R75: =IF(Q75="Sin certificar","Disponible",IF(Q75="Solo certificado","Posible",IF(Q75="Parcialmente comprometido","Parcial",IF(Q75="Mayormente comprometido","Difícil",IF(Q75="Ejecutado","No usar","Sin PIM"))))) -> Posible | S75: =IF(OR(H75<=0,Q75="Ejecutado"),0,MAX(0,H75-J75)) -> 295200 | T75: 0 | U75: 0 | V75: 0 | W75: 295200 | X75: s/d | Y75: s/d | Z75: s/d | AA75: s/d | AB75: s/d | AC75: s/d
A76: 001 | B76: SIN CLASIFICAR (completar en maestro.xlsx, hoja ClasifGC) | C76: 20. SALUD | D76: 3999999 | E76: 5000936 | F76: 0296 | G76: MANTENIMIENTO DE INFRAESTRUCTURA PUBLICA · MANTENIMIENTO DE INFRAESTRUCTURA CONSTRUIDA | H76: 276933 | I76: 0 | J76: 0 | K76: 0 | L76: =H76-I76 -> 276933 | M76: =I76-J76 -> 0 | N76: =H76-K76 -> 276933 | O76: =IF(H76>0,K76/H76,0) -> 0 | P76: =IF(H76>0,J76/H76,0) -> 0 | Q76: =IF(H76<=0,"Sin PIM",IF(K76/H76>=Config!$B$5,"Ejecutado",IF(J76/H76>=Config!$B$6,"Mayormente comprometido",IF(J76>0.005,"Parcialmente comprometido",IF(I76>0.005,"Solo certificado","Sin certificar"))))) -> Sin certificar | R76: =IF(Q76="Sin certificar","Disponible",IF(Q76="Solo certificado","Posible",IF(Q76="Parcialmente comprometido","Parcial",IF(Q76="Mayormente comprometido","Difícil",IF(Q76="Ejecutado","No usar","Sin PIM"))))) -> Disponible | S76: =IF(OR(H76<=0,Q76="Ejecutado"),0,MAX(0,H76-J76)) -> 276933 | T76: 0 | U76: 276933 | V76: 0 | W76: 0 | X76: s/d | Y76: s/d | Z76: s/d | AA76: s/d | AB76: s/d | AC76: s/d | AD76: GASTO CORRIENTE
A77: 001 | B77: SIN CLASIFICAR (completar en maestro.xlsx, hoja ClasifGC) | C77: 20. SALUD | D77: 3000001 | E77: 5004426 | F77: 0469 | G77: MONITOREO, SUPERVISION, EVALUACION Y CONTROL DEL PROGRAMA ARTICULADO NUTRICIONAL | H77: 147663 | I77: 120042 | J77: 116145.26 | K77: 62767.76 | L77: =H77-I77 -> 27621 | M77: =I77-J77 -> 3896.74 | N77: =H77-K77 -> 84895.24 | O77: =IF(H77>0,K77/H77,0) -> 0.42507439 | P77: =IF(H77>0,J77/H77,0) -> 0.78655628 | Q77: =IF(H77<=0,"Sin PIM",IF(K77/H77>=Config!$B$5,"Ejecutado",IF(J77/H77>=Config!$B$6,"Mayormente comprometido",IF(J77>0.005,"Parcialmente comprometido",IF(I77>0.005,"Solo certificado","Sin certificar"))))) -> Mayormente comprometido | R77: =IF(Q77="Sin certificar","Disponible",IF(Q77="Solo certificado","Posible",IF(Q77="Parcialmente comprometido","Parcial",IF(Q77="Mayormente comprometido","Difícil",IF(Q77="Ejecutado","No usar","Sin PIM"))))) -> Difícil | S77: =IF(OR(H77<=0,Q77="Ejecutado"),0,MAX(0,H77-J77)) -> 31517.74 | T77: 0 | U77: 147663 | V77: 0 | W77: 0 | X77: s/d | Y77: s/d | Z77: s/d | AA77: s/d | AB77: s/d | AC77: s/d
A78: 001 | B78: SIN CLASIFICAR (completar en maestro.xlsx, hoja ClasifGC) | C78: 20. SALUD | D78: 3000879 | E78: 5006271 | F78: 0467 | G78: ADMINISTRAR SUPLEMENTO DE HIERRO Y ACIDO FOLICO A ADOLESCENTES · ADMINISTRAR SUPLEMENTO DE HIERRO Y ACIDO FOLICO A ADOLESCENTE | H78: 108000 | I78: 108000 | J78: 108000 | K78: 108000 | L78: =H78-I78 -> 0 | M78: =I78-J78 -> 0 | N78: =H78-K78 -> 0 | O78: =IF(H78>0,K78/H78,0) -> 1 | P78: =IF(H78>0,J78/H78,0) -> 1 | Q78: =IF(H78<=0,"Sin PIM",IF(K78/H78>=Config!$B$5,"Ejecutado",IF(J78/H78>=Config!$B$6,"Mayormente comprometido",IF(J78>0.005,"Parcialmente comprometido",IF(I78>0.005,"Solo certificado","Sin certificar"))))) -> Ejecutado | R78: =IF(Q78="Sin certificar","Disponible",IF(Q78="Solo certificado","Posible",IF(Q78="Parcialmente comprometido","Parcial",IF(Q78="Mayormente comprometido","Difícil",IF(Q78="Ejecutado","No usar","Sin PIM"))))) -> No usar | S78: =IF(OR(H78<=0,Q78="Ejecutado"),0,MAX(0,H78-J78)) -> 0 | T78: 0 | U78: 0 | V78: 0 | W78: 108000 | X78: s/d | Y78: s/d | Z78: s/d | AA78: s/d | AB78: s/d | AC78: s/d
A79: 001 | B79: SIN CLASIFICAR (completar en maestro.xlsx, hoja ClasifGC) | C79: 23. PROTECCION SOCIAL | D79: 3000889 | E79: 5006337 | F79: 0085 | G79: ATENCION, CUIDADO Y PROTECCION A NIÑAS, NIÑOS Y ADOLESCENTES EN DESPROTECCION FAMILIAR A TRAVES DE CENTROS DE ACOGIDA RESIDENCIAL BASICO | H79: 1146585 | I79: 1046247.6 | J79: 1025365.9 | K79: 744832.42 | L79: =H79-I79 -> 100337.4 | M79: =I79-J79 -> 20881.7 | N79: =H79-K79 -> 401752.58 | O79: =IF(H79>0,K79/H79,0) -> 0.64960942 | P79: =IF(H79>0,J79/H79,0) -> 0.89427814 | Q79: =IF(H79<=0,"Sin PIM",IF(K79/H79>=Config!$B$5,"Ejecutado",IF(J79/H79>=Config!$B$6,"Mayormente comprometido",IF(J79>0.005,"Parcialmente comprometido",IF(I79>0.005,"Solo certificado","Sin certificar"))))) -> Mayormente comprometido | R79: =IF(Q79="Sin certificar","Disponible",IF(Q79="Solo certificado","Posible",IF(Q79="Parcialmente comprometido","Parcial",IF(Q79="Mayormente comprometido","Difícil",IF(Q79="Ejecutado","No usar","Sin PIM"))))) -> Difícil | S79: =IF(OR(H79<=0,Q79="Ejecutado"),0,MAX(0,H79-J79)) -> 121219.1 | T79: 599215 | U79: 337040 | V79: 0 | W79: 210330 | X79: s/d | Y79: s/d | Z79: s/d | AA79: s/d | AB79: s/d | AC79: s/d | AD79: GASTO CORRIENTE
A80: 001 | B80: SIN CLASIFICAR (completar en maestro.xlsx, hoja ClasifGC) | C80: 23. PROTECCION SOCIAL | D80: 3000889 | E80: 5006337 | F80: 0086 | G80: ATENCION, CUIDADO Y PROTECCION A NIÑAS, NIÑOS Y ADOLESCENTES EN DESPROTECCION FAMILIAR A TRAVES DE CENTROS DE ACOGIDA RESIDENCIAL BASICO | H80: 774018 | I80: 700313.5 | J80: 694498.9 | K80: 447191.7 | L80: =H80-I80 -> 73704.5 | M80: =I80-J80 -> 5814.6 | N80: =H80-K80 -> 326826.3 | O80: =IF(H80>0,K80/H80,0) -> 0.57775362 | P80: =IF(H80>0,J80/H80,0) -> 0.89726453 | Q80: =IF(H80<=0,"Sin PIM",IF(K80/H80>=Config!$B$5,"Ejecutado",IF(J80/H80>=Config!$B$6,"Mayormente comprometido",IF(J80>0.005,"Parcialmente comprometido",IF(I80>0.005,"Solo certificado","Sin certificar"))))) -> Mayormente comprometido | R80: =IF(Q80="Sin certificar","Disponible",IF(Q80="Solo certificado","Posible",IF(Q80="Parcialmente comprometido","Parcial",IF(Q80="Mayormente comprometido","Difícil",IF(Q80="Ejecutado","No usar","Sin PIM"))))) -> Difícil | S80: =IF(OR(H80<=0,Q80="Ejecutado"),0,MAX(0,H80-J80)) -> 79519.1 | T80: 219981 | U80: 346706 | V80: 0 | W80: 207331 | X80: s/d | Y80: s/d | Z80: s/d | AA80: s/d | AB80: s/d | AC80: s/d | AD80: GASTO CORRIENTE
A81: 001 | B81: SIN CLASIFICAR (completar en maestro.xlsx, hoja ClasifGC) | C81: 23. PROTECCION SOCIAL | D81: 3999999 | E81: 5005387 | F81: 0302 | G81: MEJORAMIENTO Y ATENCION A LAS PERSONAS CON DISCAPACIDAD · ATENCION A LAS PERSONAS CON DISCAPACIDAD MEDIANTE ACCIONES DE LA OFICINA REGIONAL DE ATENCION A LA PERSONA CON DISCAPACIDAD (OREDIS) | H81: 290000 | I81: 284643.13 | J81: 284643.13 | K81: 191992.93 | L81: =H81-I81 -> 5356.87 | M81: =I81-J81 -> 0 | N81: =H81-K81 -> 98007.07 | O81: =IF(H81>0,K81/H81,0) -> 0.66204459 | P81: =IF(H81>0,J81/H81,0) -> 0.98152803 | Q81: =IF(H81<=0,"Sin PIM",IF(K81/H81>=Config!$B$5,"Ejecutado",IF(J81/H81>=Config!$B$6,"Mayormente comprometido",IF(J81>0.005,"Parcialmente comprometido",IF(I81>0.005,"Solo certificado","Sin certificar"))))) -> Mayormente comprometido | R81: =IF(Q81="Sin certificar","Disponible",IF(Q81="Solo certificado","Posible",IF(Q81="Parcialmente comprometido","Parcial",IF(Q81="Mayormente comprometido","Difícil",IF(Q81="Ejecutado","No usar","Sin PIM"))))) -> Difícil | S81: =IF(OR(H81<=0,Q81="Ejecutado"),0,MAX(0,H81-J81)) -> 5356.87 | T81: 0 | U81: 275498 | V81: 0 | W81: 14502 | X81: s/d | Y81: s/d | Z81: s/d | AA81: s/d | AB81: s/d | AC81: s/d | AD81: GASTO CORRIENTE
A82: 001 | B82: SIN CLASIFICAR (completar en maestro.xlsx, hoja ClasifGC) | C82: 23. PROTECCION SOCIAL | D82: 3999999 | E82: 5001122 | F82: 0299 | G82: PROTECCION SOCIAL · MEJORAR LA CALIDAD DE VIDA DE LA POBLACION | H82: 100000 | I82: 61800 | J82: 61800 | K82: 41500 | L82: =H82-I82 -> 38200 | M82: =I82-J82 -> 0 | N82: =H82-K82 -> 58500 | O82: =IF(H82>0,K82/H82,0) -> 0.415 | P82: =IF(H82>0,J82/H82,0) -> 0.618 | Q82: =IF(H82<=0,"Sin PIM",IF(K82/H82>=Config!$B$5,"Ejecutado",IF(J82/H82>=Config!$B$6,"Mayormente comprometido",IF(J82>0.005,"Parcialmente comprometido",IF(I82>0.005,"Solo certificado","Sin certificar"))))) -> Mayormente comprometido | R82: =IF(Q82="Sin certificar","Disponible",IF(Q82="Solo certificado","Posible",IF(Q82="Parcialmente comprometido","Parcial",IF(Q82="Mayormente comprometido","Difícil",IF(Q82="Ejecutado","No usar","Sin PIM"))))) -> Difícil | S82: =IF(OR(H82<=0,Q82="Ejecutado"),0,MAX(0,H82-J82)) -> 38200 | T82: 0 | U82: 100000 | V82: 0 | W82: 0 | X82: s/d | Y82: s/d | Z82: s/d | AA82: s/d | AB82: s/d | AC82: s/d | AD82: GASTO CORRIENTE
A83: 001 | B83: SIN CLASIFICAR (completar en maestro.xlsx, hoja ClasifGC) | C83: 24. (sin nombre) | D83: 3999999 | E83: 5000991 | F83: 0297 | G83: OBLIGACIONES PREVISIONALES · PAGO DE PENSIONES Y BENEFICIOS A CESANTES Y JUBILADOS | H83: 2491773 | I83: 2491773 | J83: 2491773 | K83: 1895535.6 | L83: =H83-I83 -> 0 | M83: =I83-J83 -> 0 | N83: =H83-K83 -> 596237.36 | O83: =IF(H83>0,K83/H83,0) -> 0.76071763 | P83: =IF(H83>0,J83/H83,0) -> 1 | Q83: =IF(H83<=0,"Sin PIM",IF(K83/H83>=Config!$B$5,"Ejecutado",IF(J83/H83>=Config!$B$6,"Mayormente comprometido",IF(J83>0.005,"Parcialmente comprometido",IF(I83>0.005,"Solo certificado","Sin certificar"))))) -> Mayormente comprometido | R83: =IF(Q83="Sin certificar","Disponible",IF(Q83="Solo certificado","Posible",IF(Q83="Parcialmente comprometido","Parcial",IF(Q83="Mayormente comprometido","Difícil",IF(Q83="Ejecutado","No usar","Sin PIM"))))) -> Difícil | S83: =IF(OR(H83<=0,Q83="Ejecutado"),0,MAX(0,H83-J83)) -> 0 | T83: 0 | U83: 0 | V83: 0 | W83: 2491773 | X83: s/d | Y83: s/d | Z83: s/d | AA83: s/d | AB83: s/d | AC83: s/d | AD83: GASTO CORRIENTE
A84: 001 | B84: SIN CLASIFICAR (completar en maestro.xlsx, hoja ClasifGC) | C84: 25. (sin nombre) | D84: 3999999 | E84: 5000376 | F84: 0288 | G84: ADMINISTRACION DEUDA INTERNA · SERVICIO DE LA DEUDA | H84: 1594115 | I84: 0 | J84: 0 | K84: 0 | L84: =H84-I84 -> 1594115 | M84: =I84-J84 -> 0 | N84: =H84-K84 -> 1594115 | O84: =IF(H84>0,K84/H84,0) -> 0 | P84: =IF(H84>0,J84/H84,0) -> 0 | Q84: =IF(H84<=0,"Sin PIM",IF(K84/H84>=Config!$B$5,"Ejecutado",IF(J84/H84>=Config!$B$6,"Mayormente comprometido",IF(J84>0.005,"Parcialmente comprometido",IF(I84>0.005,"Solo certificado","Sin certificar"))))) -> Sin certificar | R84: =IF(Q84="Sin certificar","Disponible",IF(Q84="Solo certificado","Posible",IF(Q84="Parcialmente comprometido","Parcial",IF(Q84="Mayormente comprometido","Difícil",IF(Q84="Ejecutado","No usar","Sin PIM"))))) -> Disponible | S84: =IF(OR(H84<=0,Q84="Ejecutado"),0,MAX(0,H84-J84)) -> 1594115 | T84: 0 | U84: 0 | V84: 0 | W84: 1594115 | X84: s/d | Y84: s/d | Z84: s/d | AA84: s/d | AB84: s/d | AC84: s/d | AD84: GASTO CORRIENTE

Sheet Control
A1: Control y conciliación
A3: Control | B3: Calculado | C3: Referencia | D3: Diferencia | E3: Resultado
A4: Hoja Gasto corriente: PIM = Base GC | B4: ='Gasto corriente'!D100 -> 99795382 | C4: 99795382 | D4: =B4-C4 -> 0 | E4: =IF(ABS(D4)<=0.5,"Conciliado","REVISAR") -> Conciliado
A5: Hoja Gasto corriente: Devengado = Base GC | B5: ='Gasto corriente'!H100 -> 56814243 | C5: 56814243 | D5: =B5-C5 -> 7.4505806e-09 | E5: =IF(ABS(D5)<=0.5,"Conciliado","REVISAR") -> Conciliado
A6: PIM de la Base GC = PIM de actividades de la UE 001 en la fuente de cifras | B6: =SUM('Base GC'!$H$5:$H$84) -> 99795382 | C6: 99795382 | D6: =B6-C6 -> 0 | E6: =IF(ABS(D6)<=0.5,"Conciliado","REVISAR") -> Conciliado
A7: PIM UE 001: proyectos + gasto corriente = TOTAL UE del reporte SIAF | B7: =905026984.0+SUM('Base GC'!$H$5:$H$84) -> 1004822366 | C7: 1004822366 | D7: =B7-C7 -> 0 | E7: =IF(ABS(D7)<=0.5,"Conciliado","REVISAR") -> Conciliado
A9: Alertas (informativo)
A10: Metas sin gerencia/oficina asignada (completar en maestro.xlsx, hoja ClasifGC) | B10: 80
A11: Metas sin rubro (la API de Datos Abiertos no respondió) | B11: 80
A12: Metas con oficina sugerida por Silucia (confirmar) | B12: 0
A14: Avisos de la corrida
A15: La API del MEF no devolvió las cifras (dump: el CSV llegó solo con encabezados (la tabla del MEF está vacía).; paginada: La API no devolvió registros para el filtro pedido.). Se usa el reporte SIAF (.xls).
A16: Cartera del MEF consultada SIN verificar el certificado SSL (no se pudo validar en esta PC).
A17: Rubro: La API del MEF no respondió o falló: dump: el CSV llegó solo con encabezados (la tabla del MEF está vacía).; dump: el CSV llegó solo con encabezados (la tabla del MEF está vacía).; paginada: La API no devolvió registros para el filtro pe
A18: Rubro: se usa la última copia de la API del MEF (08/10/2026 04:11); el PIM por rubro cambia poco de un día a otro.
A19: Rubro del gasto corriente: La API del MEF no respondió o falló: dump: el CSV llegó solo con encabezados (la tabla del MEF está vacía).; dump: el CSV llegó solo con encabezados (la tabla del MEF está vacía).; paginada: La API no devolvió registros para el filtro pe Queda "s/d".

Sheet Config
A1: Configuración (editable)
A3: Parámetro | B3: Valor | C3: Significado
A5: Umbral "Ejecutado" | B5: 0.9 | C5: Devengado / PIM ≥ este valor → "Ejecutado" (no usar).
A6: Umbral "Mayormente comprometido" | B6: 0.5 | C6: Compromiso / PIM ≥ este valor → "Mayormente comprometido".
A8: Datos de esta corrida
A9: Fecha de corte | B9: 08/10/2026
A10: Fuente de cifras | B10: Reporte SIAF PLIEGO--.xls
A11: Fuente de rubro | B11: No disponible
A12: Silucia | B12: 505 metas de la copia local del 07/10/2026 (sin token vigente; Silucia cambia cada ~3 meses)
A13: Generado | B13: 08/10/2026 05:23

Sheet Reglas
A1: Reglas aplicadas
A3: Estado situacional y disponibilidad: las mismas reglas y umbrales que el Excel de proyectos (hoja Config).
A4: Ojo: en gasto corriente (planillas, servicios básicos, contratos) un compromiso alto es normal y lo "no comprometido" puede ser pago por venir; el estado es una primera aproximación.
A5: GERENCIA / OFICINA: maestro.xlsx, hoja ClasifGC (UE + meta). Las metas nuevas se agregan solas con la oficina vacía (celda amarilla).
A6: Silucia (api/metas): las metas de gasto corriente llegan todas con la ejecutora "GASTO CORRIENTE" (sin oficina). Si Silucia empieza a traer otra ejecutora y esta figura en la hoja MapaEjecutoras, se sugiere esa oficina.
A7: GENÉRICAS: 2.1 personal y obligaciones sociales, 2.3 bienes y servicios, 2.5 otros gastos; "otras" incluye 2.2, 2.4, 2.6 y 2.7.
A8: RUBRO: PIM por rubro de financiamiento por meta, desde la API de Datos Abiertos del MEF ("s/d" si no respondió).
