Workbook

Sheet Resumen
A1: Proyectos de inversión · GORE Puno · mapeo de disponibilidad · al 09/10/2026
A2: Montos en soles. Todo se calcula desde la hoja Base. "Disponible legal" = saldo libre según las reglas de la hoja Reglas (no es PIM − compromiso).
A4: Disponible (verde) | B4: =SUMIFS(Base!$K$5:$K$504,Base!$J$5:$J$504,"Disponible") -> 0
A5: Con condiciones (amarillo) | B5: =SUMIFS(Base!$K$5:$K$504,Base!$J$5:$J$504,"Con condiciones") -> 9379726.4
A6: Restringido (PROCOMPITE / Anexo I) | B6: =SUMIFS(Base!$K$5:$K$504,Base!$J$5:$J$504,"Restringido") -> 1267703.2
A7: Potencial rebajando certificación | B7: =SUMIFS(Base!$L$5:$L$504,Base!$J$5:$J$504,"Disponible")+SUMIFS(Base!$L$5:$L$504,Base!$J$5:$J$504,"Con condiciones")+SUMIFS(Base!$L$5:$L$504,Base!$J$5:$J$504,"Rebajando certificación") -> 71996648
A8: Detalle ordenado por monto: hoja "Dónde hay plata". Lista completa y filtrable: hoja "Base".
A10: Por unidad ejecutora
A11: Unidad | B11: Proyectos (UE-CUI-meta) | C11: PIM 2026 | D11: Certificación | E11: Devengado | F11: Saldo sin certificar | G11: Disponible legal · Disponible | H11: Disponible legal · Con condiciones | I11: Disponible legal · Restringido | J11: PIM · No mover | K11: PIM · Sin saldo útil / rebajando cert. / bolsas / sin PIM | L11: Potencial rebajando certificación
A12: 001. REGION PUNO-SEDE CENTRAL | B12: =COUNTIFS(Base!$A$5:$A$504,"001") -> 437 | C12: =SUMIFS(Base!$N$5:$N$504,Base!$A$5:$A$504,"001") -> 895026984 | D12: =SUMIFS(Base!$O$5:$O$504,Base!$A$5:$A$504,"001") -> 8.3369771e+08 | E12: =SUMIFS(Base!$Q$5:$Q$504,Base!$A$5:$A$504,"001") -> 4.3781708e+08 | F12: =C12-D12 -> 61329277 | G12: =SUMIFS(Base!$K$5:$K$504,Base!$A$5:$A$504,"001",Base!$J$5:$J$504,"Disponible") -> 0 | H12: =SUMIFS(Base!$K$5:$K$504,Base!$A$5:$A$504,"001",Base!$J$5:$J$504,"Con condiciones") -> 8673724 | I12: =SUMIFS(Base!$K$5:$K$504,Base!$A$5:$A$504,"001",Base!$J$5:$J$504,"Restringido") -> 1267703.2 | J12: =SUMIFS(Base!$N$5:$N$504,Base!$A$5:$A$504,"001",Base!$J$5:$J$504,"No mover") -> 140037928 | K12: =C12-SUMIFS(Base!$N$5:$N$504,Base!$A$5:$A$504,"001",Base!$J$5:$J$504,"Disponible")-SUMIFS(Base!$N$5:$N$504,Base!$A$5:$A$504,"001",Base!$J$5:$J$504,"Con condiciones")-SUMIFS(Base!$N$5:$N$504,Base!$A$5:$A$504,"001",Base!$J$5:$J$504,"Restringido")-J12 -> 650989858 | L12: =SUMIFS(Base!$L$5:$L$504,Base!$A$5:$A$504,"001",Base!$J$5:$J$504,"Disponible")+SUMIFS(Base!$L$5:$L$504,Base!$A$5:$A$504,"001",Base!$J$5:$J$504,"Con condiciones")+SUMIFS(Base!$L$5:$L$504,Base!$A$5:$A$504,"001",Base!$J$5:$J$504,"Rebajando certificación") -> 71516769
A13: 002. REGION PUNO-PESQUERIA | B13: =COUNTIFS(Base!$A$5:$A$504,"002") -> 4 | C13: =SUMIFS(Base!$N$5:$N$504,Base!$A$5:$A$504,"002") -> 2582404 | D13: =SUMIFS(Base!$O$5:$O$504,Base!$A$5:$A$504,"002") -> 1853925.8 | E13: =SUMIFS(Base!$Q$5:$Q$504,Base!$A$5:$A$504,"002") -> 1594267.1 | F13: =C13-D13 -> 728478.18 | G13: =SUMIFS(Base!$K$5:$K$504,Base!$A$5:$A$504,"002",Base!$J$5:$J$504,"Disponible") -> 0 | H13: =SUMIFS(Base!$K$5:$K$504,Base!$A$5:$A$504,"002",Base!$J$5:$J$504,"Con condiciones") -> 45000 | I13: =SUMIFS(Base!$K$5:$K$504,Base!$A$5:$A$504,"002",Base!$J$5:$J$504,"Restringido") -> 0 | J13: =SUMIFS(Base!$N$5:$N$504,Base!$A$5:$A$504,"002",Base!$J$5:$J$504,"No mover") -> 119950 | K13: =C13-SUMIFS(Base!$N$5:$N$504,Base!$A$5:$A$504,"002",Base!$J$5:$J$504,"Disponible")-SUMIFS(Base!$N$5:$N$504,Base!$A$5:$A$504,"002",Base!$J$5:$J$504,"Con condiciones")-SUMIFS(Base!$N$5:$N$504,Base!$A$5:$A$504,"002",Base!$J$5:$J$504,"Restringido")-J13 -> 2417454 | L13: =SUMIFS(Base!$L$5:$L$504,Base!$A$5:$A$504,"002",Base!$J$5:$J$504,"Disponible")+SUMIFS(Base!$L$5:$L$504,Base!$A$5:$A$504,"002",Base!$J$5:$J$504,"Con condiciones")+SUMIFS(Base!$L$5:$L$504,Base!$A$5:$A$504,"002",Base!$J$5:$J$504,"Rebajando certificación") -> 0
A14: 003. REGION PUNO-PROGRAMA REGIONAL DE RIEGO Y DRENAJE | B14: =COUNTIFS(Base!$A$5:$A$504,"003") -> 41 | C14: =SUMIFS(Base!$N$5:$N$504,Base!$A$5:$A$504,"003") -> 55637342 | D14: =SUMIFS(Base!$O$5:$O$504,Base!$A$5:$A$504,"003") -> 51017385 | E14: =SUMIFS(Base!$Q$5:$Q$504,Base!$A$5:$A$504,"003") -> 33578062 | F14: =C14-D14 -> 4619956.5 | G14: =SUMIFS(Base!$K$5:$K$504,Base!$A$5:$A$504,"003",Base!$J$5:$J$504,"Disponible") -> 0 | H14: =SUMIFS(Base!$K$5:$K$504,Base!$A$5:$A$504,"003",Base!$J$5:$J$504,"Con condiciones") -> 661002.36 | I14: =SUMIFS(Base!$K$5:$K$504,Base!$A$5:$A$504,"003",Base!$J$5:$J$504,"Restringido") -> 0 | J14: =SUMIFS(Base!$N$5:$N$504,Base!$A$5:$A$504,"003",Base!$J$5:$J$504,"No mover") -> 18969913 | K14: =C14-SUMIFS(Base!$N$5:$N$504,Base!$A$5:$A$504,"003",Base!$J$5:$J$504,"Disponible")-SUMIFS(Base!$N$5:$N$504,Base!$A$5:$A$504,"003",Base!$J$5:$J$504,"Con condiciones")-SUMIFS(Base!$N$5:$N$504,Base!$A$5:$A$504,"003",Base!$J$5:$J$504,"Restringido")-J14 -> 21058189 | L14: =SUMIFS(Base!$L$5:$L$504,Base!$A$5:$A$504,"003",Base!$J$5:$J$504,"Disponible")+SUMIFS(Base!$L$5:$L$504,Base!$A$5:$A$504,"003",Base!$J$5:$J$504,"Con condiciones")+SUMIFS(Base!$L$5:$L$504,Base!$A$5:$A$504,"003",Base!$J$5:$J$504,"Rebajando certificación") -> 479878.3
A15: 005. REGION PUNO-PROGRAMA DE APOYO AL DESARROLLO RURAL ANDINO | B15: =COUNTIFS(Base!$A$5:$A$504,"005") -> 6 | C15: =SUMIFS(Base!$N$5:$N$504,Base!$A$5:$A$504,"005") -> 20087412 | D15: =SUMIFS(Base!$O$5:$O$504,Base!$A$5:$A$504,"005") -> 19625209 | E15: =SUMIFS(Base!$Q$5:$Q$504,Base!$A$5:$A$504,"005") -> 15134742 | F15: =C15-D15 -> 462203.04 | G15: =SUMIFS(Base!$K$5:$K$504,Base!$A$5:$A$504,"005",Base!$J$5:$J$504,"Disponible") -> 0 | H15: =SUMIFS(Base!$K$5:$K$504,Base!$A$5:$A$504,"005",Base!$J$5:$J$504,"Con condiciones") -> 0 | I15: =SUMIFS(Base!$K$5:$K$504,Base!$A$5:$A$504,"005",Base!$J$5:$J$504,"Restringido") -> 0 | J15: =SUMIFS(Base!$N$5:$N$504,Base!$A$5:$A$504,"005",Base!$J$5:$J$504,"No mover") -> 3912438 | K15: =C15-SUMIFS(Base!$N$5:$N$504,Base!$A$5:$A$504,"005",Base!$J$5:$J$504,"Disponible")-SUMIFS(Base!$N$5:$N$504,Base!$A$5:$A$504,"005",Base!$J$5:$J$504,"Con condiciones")-SUMIFS(Base!$N$5:$N$504,Base!$A$5:$A$504,"005",Base!$J$5:$J$504,"Restringido")-J15 -> 16174974 | L15: =SUMIFS(Base!$L$5:$L$504,Base!$A$5:$A$504,"005",Base!$J$5:$J$504,"Disponible")+SUMIFS(Base!$L$5:$L$504,Base!$A$5:$A$504,"005",Base!$J$5:$J$504,"Con condiciones")+SUMIFS(Base!$L$5:$L$504,Base!$A$5:$A$504,"005",Base!$J$5:$J$504,"Rebajando certificación") -> 0
A16: 100. REGION PUNO-AGRICULTURA | B16: =COUNTIFS(Base!$A$5:$A$504,"100") -> 10 | C16: =SUMIFS(Base!$N$5:$N$504,Base!$A$5:$A$504,"100") -> 14581394 | D16: =SUMIFS(Base!$O$5:$O$504,Base!$A$5:$A$504,"100") -> 12915991 | E16: =SUMIFS(Base!$Q$5:$Q$504,Base!$A$5:$A$504,"100") -> 11236501 | F16: =C16-D16 -> 1665402.6 | G16: =SUMIFS(Base!$K$5:$K$504,Base!$A$5:$A$504,"100",Base!$J$5:$J$504,"Disponible") -> 0 | H16: =SUMIFS(Base!$K$5:$K$504,Base!$A$5:$A$504,"100",Base!$J$5:$J$504,"Con condiciones") -> 0 | I16: =SUMIFS(Base!$K$5:$K$504,Base!$A$5:$A$504,"100",Base!$J$5:$J$504,"Restringido") -> 0 | J16: =SUMIFS(Base!$N$5:$N$504,Base!$A$5:$A$504,"100",Base!$J$5:$J$504,"No mover") -> 2070892 | K16: =C16-SUMIFS(Base!$N$5:$N$504,Base!$A$5:$A$504,"100",Base!$J$5:$J$504,"Disponible")-SUMIFS(Base!$N$5:$N$504,Base!$A$5:$A$504,"100",Base!$J$5:$J$504,"Con condiciones")-SUMIFS(Base!$N$5:$N$504,Base!$A$5:$A$504,"100",Base!$J$5:$J$504,"Restringido")-J16 -> 12510502 | L16: =SUMIFS(Base!$L$5:$L$504,Base!$A$5:$A$504,"100",Base!$J$5:$J$504,"Disponible")+SUMIFS(Base!$L$5:$L$504,Base!$A$5:$A$504,"100",Base!$J$5:$J$504,"Con condiciones")+SUMIFS(Base!$L$5:$L$504,Base!$A$5:$A$504,"100",Base!$J$5:$J$504,"Rebajando certificación") -> 0
A17: 302. REGION PUNO-EDUCACION MELGAR | B17: =COUNTIFS(Base!$A$5:$A$504,"302") -> 1 | C17: =SUMIFS(Base!$N$5:$N$504,Base!$A$5:$A$504,"302") -> 32592 | D17: =SUMIFS(Base!$O$5:$O$504,Base!$A$5:$A$504,"302") -> 0 | E17: =SUMIFS(Base!$Q$5:$Q$504,Base!$A$5:$A$504,"302") -> 0 | F17: =C17-D17 -> 32592 | G17: =SUMIFS(Base!$K$5:$K$504,Base!$A$5:$A$504,"302",Base!$J$5:$J$504,"Disponible") -> 0 | H17: =SUMIFS(Base!$K$5:$K$504,Base!$A$5:$A$504,"302",Base!$J$5:$J$504,"Con condiciones") -> 0 | I17: =SUMIFS(Base!$K$5:$K$504,Base!$A$5:$A$504,"302",Base!$J$5:$J$504,"Restringido") -> 0 | J17: =SUMIFS(Base!$N$5:$N$504,Base!$A$5:$A$504,"302",Base!$J$5:$J$504,"No mover") -> 32592 | K17: =C17-SUMIFS(Base!$N$5:$N$504,Base!$A$5:$A$504,"302",Base!$J$5:$J$504,"Disponible")-SUMIFS(Base!$N$5:$N$504,Base!$A$5:$A$504,"302",Base!$J$5:$J$504,"Con condiciones")-SUMIFS(Base!$N$5:$N$504,Base!$A$5:$A$504,"302",Base!$J$5:$J$504,"Restringido")-J17 -> 0 | L17: =SUMIFS(Base!$L$5:$L$504,Base!$A$5:$A$504,"302",Base!$J$5:$J$504,"Disponible")+SUMIFS(Base!$L$5:$L$504,Base!$A$5:$A$504,"302",Base!$J$5:$J$504,"Con condiciones")+SUMIFS(Base!$L$5:$L$504,Base!$A$5:$A$504,"302",Base!$J$5:$J$504,"Rebajando certificación") -> 0
A18: 413. GOB. REG. DPTO. DE PUNO - SALUD SAN ANTONIO DE PUTINA | B18: =COUNTIFS(Base!$A$5:$A$504,"413") -> 1 | C18: =SUMIFS(Base!$N$5:$N$504,Base!$A$5:$A$504,"413") -> 41800 | D18: =SUMIFS(Base!$O$5:$O$504,Base!$A$5:$A$504,"413") -> 41500 | E18: =SUMIFS(Base!$Q$5:$Q$504,Base!$A$5:$A$504,"413") -> 41500 | F18: =C18-D18 -> 300 | G18: =SUMIFS(Base!$K$5:$K$504,Base!$A$5:$A$504,"413",Base!$J$5:$J$504,"Disponible") -> 0 | H18: =SUMIFS(Base!$K$5:$K$504,Base!$A$5:$A$504,"413",Base!$J$5:$J$504,"Con condiciones") -> 0 | I18: =SUMIFS(Base!$K$5:$K$504,Base!$A$5:$A$504,"413",Base!$J$5:$J$504,"Restringido") -> 0 | J18: =SUMIFS(Base!$N$5:$N$504,Base!$A$5:$A$504,"413",Base!$J$5:$J$504,"No mover") -> 41800 | K18: =C18-SUMIFS(Base!$N$5:$N$504,Base!$A$5:$A$504,"413",Base!$J$5:$J$504,"Disponible")-SUMIFS(Base!$N$5:$N$504,Base!$A$5:$A$504,"413",Base!$J$5:$J$504,"Con condiciones")-SUMIFS(Base!$N$5:$N$504,Base!$A$5:$A$504,"413",Base!$J$5:$J$504,"Restringido")-J18 -> 0 | L18: =SUMIFS(Base!$L$5:$L$504,Base!$A$5:$A$504,"413",Base!$J$5:$J$504,"Disponible")+SUMIFS(Base!$L$5:$L$504,Base!$A$5:$A$504,"413",Base!$J$5:$J$504,"Con condiciones")+SUMIFS(Base!$L$5:$L$504,Base!$A$5:$A$504,"413",Base!$J$5:$J$504,"Rebajando certificación") -> 0
A19: TOTAL | B19: =SUM(B12:B18) -> 500 | C19: =SUM(C12:C18) -> 987989928 | D19: =SUM(D12:D18) -> 9.1915172e+08 | E19: =SUM(E12:E18) -> 4.9940215e+08 | F19: =SUM(F12:F18) -> 68838209 | G19: =SUM(G12:G18) -> 0 | H19: =SUM(H12:H18) -> 9379726.4 | I19: =SUM(I12:I18) -> 1267703.2 | ... L19: =SUM(L12:L18) -> 71996648
A22: UE 001 Sede Central · por gerencia / oficina
A23: Unidad | B23: Proyectos (UE-CUI-meta) | C23: PIM 2026 | D23: Certificación | E23: Devengado | F23: Saldo sin certificar | G23: Disponible legal · Disponible | H23: Disponible legal · Con condiciones | I23: Disponible legal · Restringido | J23: PIM · No mover | K23: PIM · Sin saldo útil / rebajando cert. / bolsas / sin PIM | L23: Potencial rebajando certificación
A24: GERENCIA DE INFRAESTRUCTURA | B24: =COUNTIFS(Base!$C$5:$C$504,$A24) -> 284 | C24: =SUMIFS(Base!$N$5:$N$504,Base!$C$5:$C$504,$A24) -> 760705923 | D24: =SUMIFS(Base!$O$5:$O$504,Base!$C$5:$C$504,$A24) -> 7.1370332e+08 | E24: =SUMIFS(Base!$Q$5:$Q$504,Base!$C$5:$C$504,$A24) -> 3.8595477e+08 | F24: =C24-D24 -> 47002599 | G24: =SUMIFS(Base!$K$5:$K$504,Base!$C$5:$C$504,$A24,Base!$J$5:$J$504,"Disponible") -> 0 | H24: =SUMIFS(Base!$K$5:$K$504,Base!$C$5:$C$504,$A24,Base!$J$5:$J$504,"Con condiciones") -> 6193074.6 | I24: =SUMIFS(Base!$K$5:$K$504,Base!$C$5:$C$504,$A24,Base!$J$5:$J$504,"Restringido") -> 0 | J24: =SUMIFS(Base!$N$5:$N$504,Base!$C$5:$C$504,$A24,Base!$J$5:$J$504,"No mover") -> 130870596 | K24: =C24-SUMIFS(Base!$N$5:$N$504,Base!$C$5:$C$504,$A24,Base!$J$5:$J$504,"Disponible")-SUMIFS(Base!$N$5:$N$504,Base!$C$5:$C$504,$A24,Base!$J$5:$J$504,"Con condiciones")-SUMIFS(Base!$N$5:$N$504,Base!$C$5:$C$504,$A24,Base!$J$5:$J$504,"Restringido")-J24 -> 544993457 | L24: =SUMIFS(Base!$L$5:$L$504,Base!$C$5:$C$504,$A24,Base!$J$5:$J$504,"Disponible")+SUMIFS(Base!$L$5:$L$504,Base!$C$5:$C$504,$A24,Base!$J$5:$J$504,"Con condiciones")+SUMIFS(Base!$L$5:$L$504,Base!$C$5:$C$504,$A24,Base!$J$5:$J$504,"Rebajando certificación") -> 71516769
A25: GERENCIA REGIONAL DE DESARROLLO ECONOMICO | B25: =COUNTIFS(Base!$C$5:$C$504,$A25) -> 83 | C25: =SUMIFS(Base!$N$5:$N$504,Base!$C$5:$C$504,$A25) -> 15438088 | D25: =SUMIFS(Base!$O$5:$O$504,Base!$C$5:$C$504,$A25) -> 13331382 | E25: =SUMIFS(Base!$Q$5:$Q$504,Base!$C$5:$C$504,$A25) -> 6947756.8 | F25: =C25-D25 -> 2106706.1 | G25: =SUMIFS(Base!$K$5:$K$504,Base!$C$5:$C$504,$A25,Base!$J$5:$J$504,"Disponible") -> 0 | H25: =SUMIFS(Base!$K$5:$K$504,Base!$C$5:$C$504,$A25,Base!$J$5:$J$504,"Con condiciones") -> 0 | I25: =SUMIFS(Base!$K$5:$K$504,Base!$C$5:$C$504,$A25,Base!$J$5:$J$504,"Restringido") -> 1267703.2 | J25: =SUMIFS(Base!$N$5:$N$504,Base!$C$5:$C$504,$A25,Base!$J$5:$J$504,"No mover") -> 2000129 | K25: =C25-SUMIFS(Base!$N$5:$N$504,Base!$C$5:$C$504,$A25,Base!$J$5:$J$504,"Disponible")-SUMIFS(Base!$N$5:$N$504,Base!$C$5:$C$504,$A25,Base!$J$5:$J$504,"Con condiciones")-SUMIFS(Base!$N$5:$N$504,Base!$C$5:$C$504,$A25,Base!$J$5:$J$504,"Restringido")-J25 -> 3757585 | L25: =SUMIFS(Base!$L$5:$L$504,Base!$C$5:$C$504,$A25,Base!$J$5:$J$504,"Disponible")+SUMIFS(Base!$L$5:$L$504,Base!$C$5:$C$504,$A25,Base!$J$5:$J$504,"Con condiciones")+SUMIFS(Base!$L$5:$L$504,Base!$C$5:$C$504,$A25,Base!$J$5:$J$504,"Rebajando certificación") -> 0
A26: GERENCIA REGIONAL DE RECURSOS NATURALES Y GESTION AMBIENTAL | B26: =COUNTIFS(Base!$C$5:$C$504,$A26) -> 11 | C26: =SUMIFS(Base!$N$5:$N$504,Base!$C$5:$C$504,$A26) -> 18155027 | D26: =SUMIFS(Base!$O$5:$O$504,Base!$C$5:$C$504,$A26) -> 15207567 | E26: =SUMIFS(Base!$Q$5:$Q$504,Base!$C$5:$C$504,$A26) -> 8757642.5 | F26: =C26-D26 -> 2947460 | G26: =SUMIFS(Base!$K$5:$K$504,Base!$C$5:$C$504,$A26,Base!$J$5:$J$504,"Disponible") -> 0 | H26: =SUMIFS(Base!$K$5:$K$504,Base!$C$5:$C$504,$A26,Base!$J$5:$J$504,"Con condiciones") -> 16045.8 | I26: =SUMIFS(Base!$K$5:$K$504,Base!$C$5:$C$504,$A26,Base!$J$5:$J$504,"Restringido") -> 0 | J26: =SUMIFS(Base!$N$5:$N$504,Base!$C$5:$C$504,$A26,Base!$J$5:$J$504,"No mover") -> 70632 | K26: =C26-SUMIFS(Base!$N$5:$N$504,Base!$C$5:$C$504,$A26,Base!$J$5:$J$504,"Disponible")-SUMIFS(Base!$N$5:$N$504,Base!$C$5:$C$504,$A26,Base!$J$5:$J$504,"Con condiciones")-SUMIFS(Base!$N$5:$N$504,Base!$C$5:$C$504,$A26,Base!$J$5:$J$504,"Restringido")-J26 -> 18064737 | L26: =SUMIFS(Base!$L$5:$L$504,Base!$C$5:$C$504,$A26,Base!$J$5:$J$504,"Disponible")+SUMIFS(Base!$L$5:$L$504,Base!$C$5:$C$504,$A26,Base!$J$5:$J$504,"Con condiciones")+SUMIFS(Base!$L$5:$L$504,Base!$C$5:$C$504,$A26,Base!$J$5:$J$504,"Rebajando certificación") -> 0
A27: PROYECTO ESPECIAL TRUCHAS TITICACA - PETT | B27: =COUNTIFS(Base!$C$5:$C$504,$A27) -> 3 | C27: =SUMIFS(Base!$N$5:$N$504,Base!$C$5:$C$504,$A27) -> 13183082 | D27: =SUMIFS(Base!$O$5:$O$504,Base!$C$5:$C$504,$A27) -> 12706541 | E27: =SUMIFS(Base!$Q$5:$Q$504,Base!$C$5:$C$504,$A27) -> 3714211.5 | F27: =C27-D27 -> 476541.15 | G27: =SUMIFS(Base!$K$5:$K$504,Base!$C$5:$C$504,$A27,Base!$J$5:$J$504,"Disponible") -> 0 | H27: =SUMIFS(Base!$K$5:$K$504,Base!$C$5:$C$504,$A27,Base!$J$5:$J$504,"Con condiciones") -> 0 | I27: =SUMIFS(Base!$K$5:$K$504,Base!$C$5:$C$504,$A27,Base!$J$5:$J$504,"Restringido") -> 0 | J27: =SUMIFS(Base!$N$5:$N$504,Base!$C$5:$C$504,$A27,Base!$J$5:$J$504,"No mover") -> 550560 | K27: =C27-SUMIFS(Base!$N$5:$N$504,Base!$C$5:$C$504,$A27,Base!$J$5:$J$504,"Disponible")-SUMIFS(Base!$N$5:$N$504,Base!$C$5:$C$504,$A27,Base!$J$5:$J$504,"Con condiciones")-SUMIFS(Base!$N$5:$N$504,Base!$C$5:$C$504,$A27,Base!$J$5:$J$504,"Restringido")-J27 -> 12632522 | L27: =SUMIFS(Base!$L$5:$L$504,Base!$C$5:$C$504,$A27,Base!$J$5:$J$504,"Disponible")+SUMIFS(Base!$L$5:$L$504,Base!$C$5:$C$504,$A27,Base!$J$5:$J$504,"Con condiciones")+SUMIFS(Base!$L$5:$L$504,Base!$C$5:$C$504,$A27,Base!$J$5:$J$504,"Rebajando certificación") -> 0
A28: PROYECTO ESPECIAL CAMELIDOS SUDAMERICANOS | B28: =COUNTIFS(Base!$C$5:$C$504,$A28) -> 2 | C28: =SUMIFS(Base!$N$5:$N$504,Base!$C$5:$C$504,$A28) -> 5603985 | D28: =SUMIFS(Base!$O$5:$O$504,Base!$C$5:$C$504,$A28) -> 5451423 | E28: =SUMIFS(Base!$Q$5:$Q$504,Base!$C$5:$C$504,$A28) -> 3504541.4 | F28: =C28-D28 -> 152562.05 | G28: =SUMIFS(Base!$K$5:$K$504,Base!$C$5:$C$504,$A28,Base!$J$5:$J$504,"Disponible") -> 0 | H28: =SUMIFS(Base!$K$5:$K$504,Base!$C$5:$C$504,$A28,Base!$J$5:$J$504,"Con condiciones") -> 0 | I28: =SUMIFS(Base!$K$5:$K$504,Base!$C$5:$C$504,$A28,Base!$J$5:$J$504,"Restringido") -> 0 | J28: =SUMIFS(Base!$N$5:$N$504,Base!$C$5:$C$504,$A28,Base!$J$5:$J$504,"No mover") -> 1332387 | K28: =C28-SUMIFS(Base!$N$5:$N$504,Base!$C$5:$C$504,$A28,Base!$J$5:$J$504,"Disponible")-SUMIFS(Base!$N$5:$N$504,Base!$C$5:$C$504,$A28,Base!$J$5:$J$504,"Con condiciones")-SUMIFS(Base!$N$5:$N$504,Base!$C$5:$C$504,$A28,Base!$J$5:$J$504,"Restringido")-J28 -> 4271598 | L28: =SUMIFS(Base!$L$5:$L$504,Base!$C$5:$C$504,$A28,Base!$J$5:$J$504,"Disponible")+SUMIFS(Base!$L$5:$L$504,Base!$C$5:$C$504,$A28,Base!$J$5:$J$504,"Con condiciones")+SUMIFS(Base!$L$5:$L$504,Base!$C$5:$C$504,$A28,Base!$J$5:$J$504,"Rebajando certificación") -> 0
A29: GERENCIA REGIONAL DE DESARROLLO SOCIAL | B29: =COUNTIFS(Base!$C$5:$C$504,$A29) -> 42 | C29: =SUMIFS(Base!$N$5:$N$504,Base!$C$5:$C$504,$A29) -> 74669674 | D29: =SUMIFS(Base!$O$5:$O$504,Base!$C$5:$C$504,$A29) -> 67493227 | E29: =SUMIFS(Base!$Q$5:$Q$504,Base!$C$5:$C$504,$A29) -> 23519606 | F29: =C29-D29 -> 7176446.7 | G29: =SUMIFS(Base!$K$5:$K$504,Base!$C$5:$C$504,$A29,Base!$J$5:$J$504,"Disponible") -> 0 | H29: =SUMIFS(Base!$K$5:$K$504,Base!$C$5:$C$504,$A29,Base!$J$5:$J$504,"Con condiciones") -> 2464603.6 | I29: =SUMIFS(Base!$K$5:$K$504,Base!$C$5:$C$504,$A29,Base!$J$5:$J$504,"Restringido") -> 0 | J29: =SUMIFS(Base!$N$5:$N$504,Base!$C$5:$C$504,$A29,Base!$J$5:$J$504,"No mover") -> 5193458 | K29: =C29-SUMIFS(Base!$N$5:$N$504,Base!$C$5:$C$504,$A29,Base!$J$5:$J$504,"Disponible")-SUMIFS(Base!$N$5:$N$504,Base!$C$5:$C$504,$A29,Base!$J$5:$J$504,"Con condiciones")-SUMIFS(Base!$N$5:$N$504,Base!$C$5:$C$504,$A29,Base!$J$5:$J$504,"Restringido")-J29 -> 60018920 | L29: =SUMIFS(Base!$L$5:$L$504,Base!$C$5:$C$504,$A29,Base!$J$5:$J$504,"Disponible")+SUMIFS(Base!$L$5:$L$504,Base!$C$5:$C$504,$A29,Base!$J$5:$J$504,"Con condiciones")+SUMIFS(Base!$L$5:$L$504,Base!$C$5:$C$504,$A29,Base!$J$5:$J$504,"Rebajando certificación") -> 0
A30: DIRECCIÓN DE ESTUDIOS DE PREINVERSIÓN | B30: =COUNTIFS(Base!$C$5:$C$504,$A30) -> 10 | C30: =SUMIFS(Base!$N$5:$N$504,Base!$C$5:$C$504,$A30) -> 7151039 | D30: =SUMIFS(Base!$O$5:$O$504,Base!$C$5:$C$504,$A30) -> 5784881 | E30: =SUMIFS(Base!$Q$5:$Q$504,Base!$C$5:$C$504,$A30) -> 5400403.3 | F30: =C30-D30 -> 1366158 | G30: =SUMIFS(Base!$K$5:$K$504,Base!$C$5:$C$504,$A30,Base!$J$5:$J$504,"Disponible") -> 0 | H30: =SUMIFS(Base!$K$5:$K$504,Base!$C$5:$C$504,$A30,Base!$J$5:$J$504,"Con condiciones") -> 0 | I30: =SUMIFS(Base!$K$5:$K$504,Base!$C$5:$C$504,$A30,Base!$J$5:$J$504,"Restringido") -> 0 | J30: =SUMIFS(Base!$N$5:$N$504,Base!$C$5:$C$504,$A30,Base!$J$5:$J$504,"No mover") -> 0 | K30: =C30-SUMIFS(Base!$N$5:$N$504,Base!$C$5:$C$504,$A30,Base!$J$5:$J$504,"Disponible")-SUMIFS(Base!$N$5:$N$504,Base!$C$5:$C$504,$A30,Base!$J$5:$J$504,"Con condiciones")-SUMIFS(Base!$N$5:$N$504,Base!$C$5:$C$504,$A30,Base!$J$5:$J$504,"Restringido")-J30 -> 7151039 | L30: =SUMIFS(Base!$L$5:$L$504,Base!$C$5:$C$504,$A30,Base!$J$5:$J$504,"Disponible")+SUMIFS(Base!$L$5:$L$504,Base!$C$5:$C$504,$A30,Base!$J$5:$J$504,"Con condiciones")+SUMIFS(Base!$L$5:$L$504,Base!$C$5:$C$504,$A30,Base!$J$5:$J$504,"Rebajando certificación") -> 0
A31: SIN CLASIFICAR (pendiente de asignar gerencia) | B31: =COUNTIFS(Base!$C$5:$C$504,$A31) -> 2 | C31: =SUMIFS(Base!$N$5:$N$504,Base!$C$5:$C$504,$A31) -> 120166 | D31: =SUMIFS(Base!$O$5:$O$504,Base!$C$5:$C$504,$A31) -> 19362 | E31: =SUMIFS(Base!$Q$5:$Q$504,Base!$C$5:$C$504,$A31) -> 18148.25 | F31: =C31-D31 -> 100804 | G31: =SUMIFS(Base!$K$5:$K$504,Base!$C$5:$C$504,$A31,Base!$J$5:$J$504,"Disponible") -> 0 | H31: =SUMIFS(Base!$K$5:$K$504,Base!$C$5:$C$504,$A31,Base!$J$5:$J$504,"Con condiciones") -> 0 | I31: =SUMIFS(Base!$K$5:$K$504,Base!$C$5:$C$504,$A31,Base!$J$5:$J$504,"Restringido") -> 0 | J31: =SUMIFS(Base!$N$5:$N$504,Base!$C$5:$C$504,$A31,Base!$J$5:$J$504,"No mover") -> 20166 | K31: =C31-SUMIFS(Base!$N$5:$N$504,Base!$C$5:$C$504,$A31,Base!$J$5:$J$504,"Disponible")-SUMIFS(Base!$N$5:$N$504,Base!$C$5:$C$504,$A31,Base!$J$5:$J$504,"Con condiciones")-SUMIFS(Base!$N$5:$N$504,Base!$C$5:$C$504,$A31,Base!$J$5:$J$504,"Restringido")-J31 -> 100000 | L31: =SUMIFS(Base!$L$5:$L$504,Base!$C$5:$C$504,$A31,Base!$J$5:$J$504,"Disponible")+SUMIFS(Base!$L$5:$L$504,Base!$C$5:$C$504,$A31,Base!$J$5:$J$504,"Con condiciones")+SUMIFS(Base!$L$5:$L$504,Base!$C$5:$C$504,$A31,Base!$J$5:$J$504,"Rebajando certificación") -> 0
A32: TOTAL | B32: =SUM(B24:B31) -> 437 | C32: =SUM(C24:C31) -> 895026984 | D32: =SUM(D24:D31) -> 8.3369771e+08 | E32: =SUM(E24:E31) -> 4.3781708e+08 | F32: =SUM(F24:F31) -> 61329277 | G32: =SUM(G24:G31) -> 0 | H32: =SUM(H24:H31) -> 8673724 | I32: =SUM(I24:I31) -> 1267703.2 | ... L32: =SUM(L24:L31) -> 71516769

Sheet Dónde hay plata
A1: ¿Dónde hay plata? · proyectos con saldo libre · al 09/10/2026
A2: Cada fila es un proyecto (UE-CUI-meta) con al menos S/ 10,000. VERDE = saldo libre sin condiciones. AMARILLO = saldo libre con las condiciones del último campo. AZUL (rebajando certificación) = no hay saldo libre, pero hay dinero certificado sin comprometer ni programar en el 12-B: solo sirve si la UEI rebaja la certificación. ★ = proyecto de la lista de Antony. Los rubros son el PIM por fuente de financiamiento.
A3: Verde (disponible) | D3: 0 | E3: 0 proyectos
A4: Amarillo (con condiciones) | D4: 9379726.4 | E4: 40 proyectos
A5: Azul (rebajando certificación) | D5: 71996648 | E5: 8 proyectos azules; la columna Potencial también existe en verdes y amarillos
A7: N° | B7: Semáforo | C7: UE | D7: Gerencia / Oficina | E7: CUI | F7: Proyecto | G7: Tipo de inversión | H7: Función | I7: Disponible legal (S/) | J7: Potencial rebajando certificación (S/) | K7: PIM 2026 | L7: Certificación | M7: Rubro principal | N7: RO (00) | O7: RDR (09) | P7: FONCOR (15) | Q7: CANON (18) | R7: ROOC (19) | S7: Otros rubros | T7: % Avance acumulado | U7: PMI 2026 (S/) | V7: PMI 2027 (S/) | W7: Motivo / condiciones
A8: 1 | B8: Con condiciones | C8: 001 | D8: GERENCIA DE INFRAESTRUCTURA | E8: 2658446 | F8: 2658446: PROYECTOS PARA EL DESARROLLO LOCAL | G8: Genérico | H8: 03. PLANEAMIENTO, GESTION Y RESERVA DE CONTINGENCIA | I8: 1376515 | J8: 0 | K8: 1376515 | L8: 0 | M8: CANON (18) | N8: 0 | O8: 0 | P8: 0 | Q8: 1376515 | R8: 0 | T8: s/d | U8: 0 | V8: 0 | W8: Sin Formato 12-B: validar con la OPMI
A9: 2 | B9: Con condiciones | C9: 001 | D9: GERENCIA DE INFRAESTRUCTURA | E9: 2585543 | F9: 2585543: MEJORAMIENTO Y AMPLIACION DEL SERVICIO DE EDUCACIÓN SUPERIOR TECNOLÓGICA EN EL INSTITUTO DE EDUCACIÓN SUPERIOR TECNOLÓGICO PUBLICO ACORA DEL DISTRITO DE ACORA DE LA PROVINCIA DE PUNO DEL DEPARTAMENTO DE PUNO | G9: Proyecto de inversión | H9: 22. EDUCACION | I9: 1045528.8 | J9: 193060.46 | K9: 15380884 | L9: 14335355 | M9: FONCOR (15) | N9: 0 | O9: 1000000 | P9: 14380884 | Q9: 0 | R9: 0 | T9: 0.55837026 | U9: 6000000 | V9: 3456765 | W9: Está programado en el PMI 2026 · Tiene monto en el PMI 2027 (S/ 3,456,765)
A10: 3 | B10: Con condiciones | C10: 001 | D10: GERENCIA REGIONAL DE DESARROLLO SOCIAL | E10: 2729834 | F10: 2729834: CONSTRUCCION DE AULA DE EDUCACION PRIMARIA, SERVICIOS HIGIENICOS Y/O VESTIDORES PARA ESTUDIANTES Y AMBIENTE DE GESTION ADMINISTRATIVA Y DIRECCION; ADQUISICION DE MOBILIARIO DE AULA; EN EL(LA) I.E. 72544 DISTRITO DE ALTO INAMBARI, PROVINCIA SANDIA, | G10: IOARR | H10: 22. EDUCACION | I10: 928545 | J10: 0 | K10: 928545 | L10: 0 | M10: RDR (09) | N10: 0 | O10: 928545 | P10: 0 | Q10: 0 | R10: 0 | T10: 0 | U10: 0 | V10: 0 | W10: El 12-B programa S/ 928,545 de un PIM de S/ 928,545: la UEI debe actualizarlo (el proyecto no está en ningún PMI)
A11: 4 | B11: Con condiciones | C11: 001 | D11: GERENCIA DE INFRAESTRUCTURA | E11: 2357091 | F11: 2357091: MEJORAMIENTO DE LA CAPACIDAD RESOLUTIVA DEL CENTRO DE SALUD COATA I-3 DE LA MICRORED JAE, RED DE SALUD PUNO - DIRESA PUNO, , - DISTRITO DE COATA - PROVINCIA DE PUNO - REGIÓN PUNO | G11: Proyecto de inversión | H11: 20. SALUD | I11: 789314 | J11: 0 | K11: 10399190 | L11: 9609876 | M11: FONCOR (15) | N11: 0 | O11: 194638 | P11: 8204552 | Q11: 2000000 | R11: 0 | T11: 0.089220482 | U11: 8282615 | V11: 10255200 | W11: Está programado en el PMI 2026 · Tiene monto en el PMI 2027 (S/ 10,255,200)
A12: 5 | B12: Con condiciones | C12: 001 | D12: GERENCIA DE INFRAESTRUCTURA | E12: 2504553 | F12: 2504553: MEJORAMIENTO DEL SERVICIO DE SALUD EN EL CENTRO DE SALUD YANAPATA DE LA MICRO RED COPANI, RED DE SALUD YUNGUYO, DISTRITO DE YUNGUYO - PROVINCIA DE YUNGUYO - DEPARTAMENTO DE PUNO | G12: Proyecto de inversión | H12: 20. SALUD | I12: 617941.43 | J12: 0 | K12: 8256172 | L12: 7558918.9 | M12: FONCOR (15) | N12: 0 | O12: 0 | P12: 8256172 | Q12: 0 | R12: 0 | T12: 0.45967288 | U12: 9468125 | V12: 933429 | W12: Está programado en el PMI 2026 · Tiene monto en el PMI 2027 (S/ 933,429)
A13: 6 | B13: Con condiciones | C13: 003 | D13: 003. REGION PUNO-PROGRAMA REGIONAL DE RIEGO Y DRENAJE | E13: 2566500 | F13: 2566500: MEJORAMIENTO Y AMPLIACION DEL SISTEMA DE RIEGO CHAJANA DEL DISTRITO DE ACORA - PROVINCIA DE PUNO - DEPARTAMENTO DE PUNO | G13: Proyecto de inversión | H13: 10. AGROPECUARIA | I13: 356798.11 | J13: 322975.69 | K13: 7723291 | L13: 7350044 | M13: FONCOR (15) | N13: 0 | O13: 0 | P13: 7723291 | Q13: 0 | R13: 0 | T13: 0.76208467 | U13: 4665000 | V13: 62456 | W13: Está programado en el PMI 2026 · Tiene monto en el PMI 2027 (S/ 62,456)
A14: 7 | B14: Con condiciones | C14: 001 | D14: GERENCIA REGIONAL DE DESARROLLO SOCIAL | E14: 2721991 | F14: 2721991: RENOVACION DE AULA DE EDUCACION PRIMARIA, AMBIENTE ADMINISTRATIVO, SERVICIOS HIGIENICOS Y/O VESTIDORES Y AMBIENTE DE USOS MULTIPLES; ADEMAS DE OTROS ACTIVOS EN CUATRO II.EE. PRIMARIA A NIVEL DISTRITAL (PUNO - SANDIA - SAN PEDRO DE PUTINA PUNCO) | G14: IOARR | H14: 22. EDUCACION | I14: 329210.45 | J14: 0 | K14: 3254770 | L14: 2925559.5 | M14: RDR (09) | N14: 0 | O14: 3254770 | P14: 0 | Q14: 0 | R14: 0 | T14: 0 | U14: 0 | V14: 0 | W14: El 12-B programa S/ 3,254,770 de un PIM de S/ 3,254,770: la UEI debe actualizarlo (el proyecto no está en ningún PMI)
A15: 8 | B15: Con condiciones | C15: 001 | D15: GERENCIA DE INFRAESTRUCTURA | E15: 2188542 | F15: 2188542: MEJORAMIENTO DE LA CAPACIDAD DE PRESTACION DE SERVICIOS DEPORTIVOS EN EL ESTADIO GUILLERMO BRICEÑO ROSAMEDINA DE LA CIUDAD DE JULIACA, PROVINCIA DE SAN ROMAN - PUNO | G15: Proyecto de inversión | H15: 21. CULTURA Y DEPORTE | I15: 309147.48 | J15: 2486795.5 | K15: 5921783 | L15: 5612635.5 | M15: FONCOR (15) | N15: 0 | O15: 0 | P15: 5921783 | Q15: 0 | R15: 0 | T15: 0.84657376 | U15: 1139986 | V15: 500000 | W15: Está programado en el PMI 2026 · Tiene monto en el PMI 2027 (S/ 500,000)
A16: 9 | B16: Con condiciones | C16: 003 | D16: 003. REGION PUNO-PROGRAMA REGIONAL DE RIEGO Y DRENAJE | E16: 2454391 | F16: 2454391: AMPLIACION DEL SERVICIO DE AGUA PARA RIEGO MEDIANTE LA CONSTRUCCIÓN DE LA REPRESA SAPANCCOTA DEL DISTRITO DE PUCARA - PROVINCIA DE LAMPA - DEPARTAMENTO DE PUNO | G16: Proyecto de inversión | H16: 10. AGROPECUARIA | I16: 304204.25 | J16: 156902.61 | K16: 7885949 | L16: 7581523.9 | M16: FONCOR (15) | N16: 0 | O16: 0 | P16: 7885949 | Q16: 0 | R16: 0 | T16: 0.85712275 | U16: 2780000 | V16: 108325 | W16: Está programado en el PMI 2026 · Tiene monto en el PMI 2027 (S/ 108,325)
A17: 10 | B17: Con condiciones | C17: 001 | D17: GERENCIA DE INFRAESTRUCTURA | E17: 2663002 | F17: 2663002: MEJORAMIENTO DEL SERVICIO DE EDUCACION SECUNDARIA EN I.E. HUAPACA SAN MIGUEL DE CENTRO POBLADO HUAPACA SAN MIGUEL DISTRITO DE POMATA DE LA PROVINCIA DE CHUCUITO DEL DEPARTAMENTO DE PUNO | G17: Proyecto de inversión | H17: 22. EDUCACION | I17: 292573 | J17: 0 | K17: 292573 | L17: 0 | M17: FONCOR (15) | N17: 0 | O17: 0 | P17: 292573 | Q17: 0 | R17: 0 | T17: 0.015207331 | U17: 0 | V17: 0 | W17: El 12-B programa S/ 292,573 de un PIM de S/ 292,573: la UEI debe actualizarlo (el proyecto no está en ningún PMI)
A18: 11 | B18: Con condiciones | C18: 001 | D18: GERENCIA DE INFRAESTRUCTURA | E18: 2436247 | F18: 2436247: MEJORAMIENTO DEL CAMINO VECINAL RUTA PU-713, EMP. PE 3S (AYAVIRI - DESV. CALUYO - TINAJANI - L. PROV. LAMPA), DISTRITO DE AYAVIRI - PROVINCIA DE MELGAR - DEPARTAMENTO DE PUNO | G18: Proyecto de inversión | H18: 15. TRANSPORTE | I18: 276235.8 | J18: 3131588.9 | K18: 22224878 | L18: 21948642 | M18: FONCOR (15) | N18: 0 | O18: 0 | P18: 22224878 | Q18: 0 | R18: 0 | T18: 0.11025308 | U18: 0 | V18: 0 | W18: Figura en un PMI (MUNICIPALIDAD PROVINCIAL DE MELGAR) sin monto 2026 en la Cartera del GR: validar con la OPMI
A19: 12 | B19: Con condiciones | C19: 001 | D19: GERENCIA DE INFRAESTRUCTURA | E19: 2570369 | F19: 2570369: MEJORAMIENTO DE LOS SERVICIOS DE EDUCACION SUPERIOR DEL INSTITUTO SUPERIOR TECNOLOGICO PUBLICA SAN JUAN DEL ORO DEL DISTRITO DE SAN JUAN DEL ORO - PROVINCIA DE SANDIA - DEPARTAMENTO DE PUNO | G19: Proyecto de inversión | H19: 22. EDUCACION | I19: 270568 | J19: 0 | K19: 5931027 | L19: 5660459 | M19: FONCOR (15) | N19: 0 | O19: 0 | P19: 5931027 | Q19: 0 | R19: 0 | T19: 0.13022156 | U19: 2769903 | V19: 8258956 | W19: Está programado en el PMI 2026 · Tiene monto en el PMI 2027 (S/ 8,258,956)
A20: 13 | B20: Con condiciones | C20: 001 | D20: GERENCIA DE INFRAESTRUCTURA | E20: 2527207 | F20: 2527207: RECUPERACION DEL PUENTE COLONIAL DE LAMPA, DISTRITO DE LAMPA - PROVINCIA DE LAMPA - DEPARTAMENTO DE PUNO | G20: Proyecto de inversión | H20: 21. CULTURA Y DEPORTE | I20: 229217 | J20: 0 | K20: 369217 | L20: 140000 | M20: FONCOR (15) | N20: 19217 | O20: 0 | P20: 350000 | Q20: 0 | R20: 0 | T20: 0.053688256 | U20: 0 | V20: 0 | W20: 12-B sin programación vigente: validar con la OPMI
... A55: 48 | B55: Rebajando certificación | C55: 001 | D55: GERENCIA DE INFRAESTRUCTURA | E55: 2714049 | F55: 2714049: REPARACION DE CAMPO DEPORTIVO; EN EL(LA) POLIDEPORTIVO AZANGARO DISTRITO DE AZANGARO, PROVINCIA AZANGARO, DEPARTAMENTO PUNO | G55: IOARR | H55: 21. CULTURA Y DEPORTE | I55: 0 | J55: 40369 | K55: 100021 | L55: 100021 | M55: FONCOR (15) | N55: 0 | O55: 0 | P55: 100021 | Q55: 0 | R55: 0 | T55: 0.013629045 | U55: 50000 | V55: 0 | W55: Sin saldo libre; hay S/ 40,369 certificados sin comprometer ni programar en el 12-B (requiere rebajar la certificación)

Sheet Cambios
A1: Qué cambió desde la corrida anterior
A2: Comparado con la corrida del 09/10/2026 19:48. Se listan proyectos nuevos, que ya no aparecen, que cambiaron de semáforo o cuyo disponible/PIM varió en S/ 1 000 o más.
A3: 20 cambios
A4: N° | B4: Tipo de cambio | C4: UE | D4: CUI | E4: Meta | F4: Proyecto | G4: Semáforo antes | H4: Semáforo ahora | I4: Disponible antes | J4: Disponible ahora | K4: Variación | L4: PIM antes | M4: PIM ahora
A5: 1 | B5: Cambió el semáforo + Cambió el disponible | C5: 001 | D5: 2650473 | E5: 0525 | F5: 2650473: CONSTRUCCION DE AULA DE EDUCACION SECUNDARIA, LABORATORIO Y/O TALLER, CERCO Y/O PORTADA Y SERVICIOS HIGIENICOS Y/O VESTIDORES; ADEMAS DE OTROS ACTIVOS EN EL(LA) I.E. AGROINDUSTRIAL DISTRITO DE PUTINA, PROVINCIA SAN ANTONIO DE PUTINA, DEPARTAMENTO | G5: Con condiciones | H5: Sin saldo útil | I5: 2394005 | J5: 0 | K5: -2394005 | L5: 2394005 | M5: 2394005
A6: 2 | B6: Cambió el semáforo + Cambió el disponible | C6: 001 | D6: 2278822 | E6: 0434 | F6: 2278822: MEJORAMIENTO DE LOS SERVICIOS DE SALUD DEL HOSPITAL RAFAEL ORTIZ RAVINES DE JULI, PROVINCIA DE CHUCUITO - REGION PUNO | G6: Con condiciones | H6: Sin saldo útil | I6: 2318512.3 | J6: 0 | K6: -2318512.3 | L6: 41519761 | M6: 41519761
A7: 3 | B7: Cambió el semáforo + Cambió el disponible | C7: 001 | D7: 2500458 | E7: 0460 | F7: 2500458: MEJORAMIENTO DEL SERVICIO EDUCATIVO EN LA IEP N° 70477 SAGRADO CORAZON DE JESUS DEL DISTRITO DE AYAVIRI - PROVINCIA DE MELGAR - DEPARTAMENTO DE PUNO | G7: Con condiciones | H7: Sin saldo útil | I7: 832498.14 | J7: 0 | K7: -832498.14 | L7: 4437995 | M7: 4437995
A8: 4 | B8: Cambió el semáforo + Cambió el disponible | C8: 001 | D8: 2511009 | E8: 0463 | F8: 2511009: MEJORAMIENTO DEL SERVICIO VIAL URBANO DE LA AVENIDA INDUSTRIAL DEL CENTRO POBLADO DE SALCEDO, DISTRITO DE PUNO - PROVINCIA DE PUNO - DEPARTAMENTO DE PUNO | G8: Con condiciones | H8: Sin saldo útil | I8: 789311.02 | J8: 0 | K8: -789311.02 | L8: 1827737 | M8: 1827737
A9: 5 | B9: Cambió el semáforo + Cambió el disponible | C9: 001 | D9: 2634040 | E9: 0128 | F9: 2634040: MEJORAMIENTO DEL SERVICIO DE TRANSITABILIDAD VIAL INTERURBANA EN EL CAMINO VECINAL, TRAMO DESVIO PUCARA - POBLACION SALINAS - ASILLO SALINAS (KM 0+000 - 1+900) DEL DISTRITO DE SAN JUAN DE SALINAS DE LA PROVINCIA DE AZANGARO DEL DEPARTAMENTO DE PUNO | G9: Con condiciones | H9: Sin saldo útil | I9: 693680.47 | J9: 0 | K9: -693680.47 | L9: 4106961 | M9: 4106961
A10: 6 | B10: Cambió el semáforo + Cambió el disponible | C10: 001 | D10: 2591951 | E10: 0119 | F10: 2591951: MEJORAMIENTO DEL SERVICIO DE TRANSITABILIDAD VIAL INTERURBANA EN EL CAMINO VECINAL DEL KM0+000 (DESVIO PUENTE OCRA CHUPA) AL KM 6+373 (C.P. PEDRO VILCAPAZA DE MORORCCO), DISTRITO DE MUÑANI DE LA PROVINCIA DE AZANGARO DEL DEPARTAMENTO DE PUNO | G10: Con condiciones | H10: Sin saldo útil | I10: 653343.71 | J10: 0 | K10: -653343.71 | L10: 6770858 | M10: 6770858
A11: 7 | B11: Cambió el semáforo + Cambió el disponible | C11: 001 | D11: 2518131 | E11: 0337 | F11: 2518131: AMPLIACION Y MEJORAMIENTO DE LOS SERVICIOS DE ADMINISTRACION DE JUSTICIA DE LOS ORGANOS JURISDICCIONALES DE LA SEDE CENTRAL DEL DISTRITO JUDICIAL DE PUNO, DISTRITO DE PUNO - PROVINCIA DE PUNO - DEPARTAMENTO DE PUNO | G11: Con condiciones | H11: Sin saldo útil | I11: 500000 | J11: 0 | K11: -500000 | L11: 500000 | M11: 500000
A12: 8 | B12: Cambió el semáforo + Cambió el disponible | C12: 001 | D12: 2590087 | E12: 0041 | F12: 2590087: MEJORAMIENTO DEL SERVICIO DE EDUCACION SECUNDARIA EN I.E. JOSE MARIA ARGUEDAS DISTRITO DE LLALLI DE LA PROVINCIA DE MELGAR DEL DEPARTAMENTO DE PUNO | G12: Con condiciones | H12: Sin saldo útil | I12: 498679.49 | J12: 0 | K12: -498679.49 | L12: 5799805 | M12: 5799805
A13: 9 | B13: Cambió el semáforo + Cambió el disponible | C13: 001 | D13: 2453224 | E13: 0455 | F13: 2453224: MEJORAMIENTO DE LOS SERVICIOS DE EDUCACION SECUNDARIA DE LA INSTITUCION EDUCATIVA LIBERTADOR JOSE DE SAN MARTIN DE HUARISANI DEL DISTRITO DE HUANCANE - PROVINCIA DE HUANCANE - DEPARTAMENTO DE PUNO | G13: Con condiciones | H13: Sin saldo útil | I13: 418706.06 | J13: 0 | K13: -418706.06 | L13: 4265759 | M13: 4265759
A14: 10 | B14: Cambió el semáforo + Cambió el disponible | C14: 001 | D14: 2617364 | E14: 0532 | F14: 2617364: 2617364: (MEJORAMIENTO DE INFRAESTRUCTURA DE EDUCACION BASICA REGULAR - nombre no disponible en fuentes) | G14: Con condiciones | H14: Sin saldo útil | I14: 218556 | J14: 0 | K14: -218556 | L14: 218556 | M14: 218556
A15: 11 | B15: Cambió el semáforo + Cambió el disponible | C15: 001 | D15: 2387422 | E15: 0105 | F15: 2387422: MEJORAMIENTO DE LA CARRETERA TRAMO II (PUENTE CULLCO) - PICHINCUTA - QUELCAHUECO - CORARACA DEL - DISTRITO DE ILAVE - PROVINCIA DE EL COLLAO - DEPARTAMENTO DE PUNO | G15: Con condiciones | H15: Sin saldo útil | I15: 169873.63 | J15: 0 | K15: -169873.63 | L15: 7751873 | M15: 7751873
A16: 12 | B16: Cambió el semáforo + Cambió el disponible | C16: 001 | D16: 2606991 | E16: 0306 | F16: 2606991: MEJORAMIENTO DEL SERVICIO DE EDUCACION INICIAL EN I.E. 69 DISTRITO DE ANTAUTA DE LA PROVINCIA DE MELGAR DEL DEPARTAMENTO DE PUNO | G16: Con condiciones | H16: Sin saldo útil | I16: 131818.37 | J16: 0 | K16: -131818.37 | L16: 3853164 | M16: 3853164
... A24: 20 | B24: Cambió el semáforo | C24: 001 | D24: 2427364 | E24: 0233 | F24: 2427364: MEJORAMIENTO DE LOS SERVICIOS DE SALUD DEL HOSPITAL ANTONIO BARRIONUEVO DISTRITO DE LAMPA - PROVINCIA DE LAMPA - DEPARTAMENTO DE PUNO | G24: Disponible | H24: Con condiciones | I24: 219373.94 | J24: 219373.94 | K24: -5.8207661e-11 | L24: 966193 | M24: 966193

Sheet Gerencia de Infraestructura
C1: ANEXO N° 01
B2: COMPORTAMIENTO DE EJECUCIÓN DE PROYECTOS DE INVERSION PUBLICA DEL AÑO FISCAL 2026 · Gerencia de Infraestructura · AL 09/10/2026
A4: N° | B4: META | C4: PROYECTO | D4: PIM 2026 (A) | E4: CERTIFICACIÓN (B) | F4: SALDO (A-B) | G4: DEVENGADO ( C ) | H4: SALDO (A-C) | I4: DEVEN % | J4: MODALIDAD DE EJECUCIÓN | K4: TIPO DE INVERSIÓN | L4: Monto Año 2026 (S/) | M4: Monto Año 2027 (S/) | N4: Monto Año 2028 (S/) | O4: Monto Año 2029 (S/) | P4: BASE LEGAL | Q4: SEMÁFORO | R4: % AVANCE FINANCIERO ACUMULADO | S4: DISPONIBLE LEGAL (S/) | T4: MOTIVO / CONDICIONES
A5: GERENCIA DE INFRAESTRUCTURA | D5: =D6+D122+D151+D196+D323 -> 760705923 | E5: =E6+E122+E151+E196+E323 -> 7.1370332e+08 | F5: =D5-E5 -> 47002599 | G5: =G6+G122+G151+G196+G323 -> 3.8595477e+08 | H5: =D5-G5 -> 3.7475116e+08 | I5: =IF(D5=0,0,G5/D5) -> 0.50736396 | S5: =S6+S122+S151+S196+S323 -> 6199045.1
A6: EJECUCIÓN POR ADMINISTRACIÓN DIRECTA | D6: =D7+D78 -> 501856577 | E6: =E7+E78 -> 4.7347402e+08 | F6: =D6-E6 -> 28382558 | G6: =G7+G78 -> 2.5912065e+08 | H6: =D6-G6 -> 2.4273593e+08 | I6: =IF(D6=0,0,G6/D6) -> 0.51632411 | S6: =S7+S78 -> 2570857.9
A7: EJECUCIÓN POR ADMINISTRACIÓN DIRECTA - DIRECTIVA 10 | D7: =D8+D11+D38+D63+D73+D75 -> 234460254 | E7: =E8+E11+E38+E63+E73+E75 -> 2.2391079e+08 | F7: =D7-E7 -> 10549460 | G7: =G8+G11+G38+G63+G73+G75 -> 99970240 | H7: =D7-G7 -> 1.3449001e+08 | I7: =IF(D7=0,0,G7/D7) -> 0.42638459 | S7: =S8+S11+S38+S63+S73+S75 -> 667641.68
A8: 20. SALUD | D8: =SUM(D9:D10) -> 53926751 | E8: =SUM(E9:E10) -> 53909348 | F8: =D8-E8 -> 17402.8 | G8: =SUM(G9:G10) -> 364124.26 | H8: =D8-G8 -> 53562627 | I8: =IF(D8=0,0,G8/D8) -> 0.006752201 | S8: =SUM(S9:S10) -> 0.1
A9: =SUBTOTAL(103,$B$6:B9) -> 1 | B9: 1 | C9: 2108576: CONSTRUCCION DEL HOSPITAL MATERNO INFANTIL DEL CONO SUR JULIACA | D9: =Base!N5 -> 167354 | E9: =Base!O5 -> 149951.3 | F9: =D9-E9 -> 17402.7 | G9: =Base!Q5 -> 102781.21 | H9: =D9-G9 -> 64572.79 | I9: =IF(D9=0,0,G9/D9) -> 0.61415449 | J9: =Base!AH5 -> Administración directa / Laudos arbitrales | K9: =Base!I5 -> Proyecto de inversión | L9: =Base!AA5 -> 12460540 | M9: =Base!AB5 -> 5731000 | N9: =Base!AC5 -> 5000000 | O9: =Base!AD5 -> 5000000 | P9: =IF(Base!AI5="","",Base!AI5) | Q9: =Base!J5 -> Sin saldo útil | R9: =Base!X5 -> 0.65811382 | S9: =Base!K5 -> 0 | T9: =Base!M5 -> Saldo libre menor a S/ 10,000
A10: =SUBTOTAL(103,$B$6:B10) -> 2 | B10: 220 | C10: 2279375: MEJORAMIENTO DE LOS SERVICIOS DE SALUD DEL HOSPITAL DE APOYO ILAVE, PROVINCIA DE EL COLLAO - REGION PUNO | D10: =Base!N6 -> 53759397 | E10: =Base!O6 -> 53759397 | F10: =D10-E10 -> 0.1 | G10: =Base!Q6 -> 261343.05 | H10: =D10-G10 -> 53498054 | I10: =IF(D10=0,0,G10/D10) -> 0.0048613464 | J10: =Base!AH6 -> Contrata / Expediente técnico / Administración directa / Laudos arbitrales | K10: =Base!I6 -> Proyecto de inversión | L10: =Base!AA6 -> No registrado en cartera | M10: =Base!AB6 -> No registrado en cartera | N10: =Base!AC6 -> No registrado en cartera | O10: =Base!AD6 -> No registrado en cartera | P10: =IF(Base!AI6="","",Base!AI6) | Q10: =Base!J6 -> Rebajando certificación | R10: =Base!X6 -> 0.38038553 | S10: =Base!K6 -> 0.1 | T10: =Base!M6 -> Sin saldo libre; hay S/ 48,063,959 certificados sin comprometer ni programar en el 12-B (requiere rebajar la certificación)
A11: 22. EDUCACION | D11: =SUM(D12:D37) -> 60810433 | E11: =SUM(E12:E37) -> 57629207 | F11: =D11-E11 -> 3181226.5 | G11: =SUM(G12:G37) -> 35508320 | H11: =D11-G11 -> 25302113 | I11: =IF(D11=0,0,G11/D11) -> 0.58391822 | S11: =SUM(S12:S37) -> 0
A12: =SUBTOTAL(103,$B$6:B12) -> 3 | B12: 223 | C12: 2323700: MEJORAMIENTO DEL SERVICIO EDUCATIVO DE LAS CARRERAS DE PRODUCCIÓN, AUTOMOTRIZ, MINERÍA, CONTABILIDAD, COMPUTACIÓN, SECRETARIADO, ENFERMERÍA, LABORATORIO CLÍNICO Y PRÓTESIS DENTAL DEL IST MANUEL NÚÑEZ BUTRÓN, JULIACA, SAN ROMÁN - PUNO | D12: =Base!N7 -> 10519577 | E12: =Base!O7 -> 10422241 | F12: =D12-E12 -> 97335.78 | G12: =Base!Q7 -> 7596372.7 | H12: =D12-G12 -> 2923204.3 | I12: =IF(D12=0,0,G12/D12) -> 0.72211769 | J12: =Base!AH7 -> Administración directa / Contrata / Personal/bienes/servicios | K12: =Base!I7 -> Proyecto de inversión | L12: =Base!AA7 -> 2546207 | M12: =Base!AB7 -> 638376 | N12: =Base!AC7 -> 2568939 | O12: =Base!AD7 -> 0 | P12: =IF(Base!AI7="","",Base!AI7) | Q12: =Base!J7 -> No mover | R12: =Base!X7 -> 0.93578067 | S12: =Base!K7 -> 0 | T12: =Base!M7 -> Avance financiero acumulado 94% (> 90%)
A13: =SUBTOTAL(103,$B$6:B13) -> 4 | B13: 224 | C13: 2335880: MEJORAMIENTO DEL SERVICIO EDUCATIVO DE LAS CARRERAS DE CONTABILIDAD, ENFERMERÍA TÉCNICA, COMPUTACIÓN E INFORMÁTICA, INDUSTRIA ALIMENTARIA Y PRODUCCIÓN AGROPECUARIA DEL ISEPA, PROVINCIA DE MELGAR - PUNO | D13: =Base!N8 -> 10208307 | E13: =Base!O8 -> 9968469.6 | F13: =D13-E13 -> 239837.38 | G13: =Base!Q8 -> 6440724.5 | H13: =D13-G13 -> 3767582.5 | I13: =IF(D13=0,0,G13/D13) -> 0.63092974 | J13: =Base!AH8 -> Administración directa / Equipamiento / Contrata / Personal/bienes/servicios | K13: =Base!I8 -> Proyecto de inversión | L13: =Base!AA8 -> 5597990 | M13: =Base!AB8 -> 1254673 | N13: =Base!AC8 -> 2493351 | O13: =Base!AD8 -> 0 | P13: =IF(Base!AI8="","",Base!AI8) | Q13: =Base!J8 -> Sin saldo útil | R13: =Base!X8 -> 0.85722109 | S13: =Base!K8 -> 0 | T13: =Base!M8 -> Saldo libre menor a S/ 10,000
A14: =SUBTOTAL(103,$B$6:B14) -> 5 | B14: 245 | C14: 2521936: MEJORAMIENTO Y AMPLIACION DEL SERVICIO DE EDUCACIÓN SUPERIOR TECNOLÓGICA EN EL INSTITUTO SUPERIOR TECNOLÓGICO PUBLICO DE MACUSANI DISTRITO DE MACUSANI - PROVINCIA DE CARABAYA - DEPARTAMENTO DE PUNO | D14: =Base!N9 -> 11203165 | E14: =Base!O9 -> 10889669 | F14: =D14-E14 -> 313496.41 | G14: =Base!Q9 -> 6395813.3 | H14: =D14-G14 -> 4807351.7 | I14: =IF(D14=0,0,G14/D14) -> 0.57089343 | J14: =Base!AH9 -> Administración directa / Equipamiento / Contrata / Personal/bienes/servicios | K14: =Base!I9 -> Proyecto de inversión | L14: =Base!AA9 -> 4902849 | M14: =Base!AB9 -> 60001 | N14: =Base!AC9 -> 2722594 | O14: =Base!AD9 -> 0 | P14: =IF(Base!AI9="","",Base!AI9) | Q14: =Base!J9 -> Sin saldo útil | R14: =Base!X9 -> 0.82345357 | S14: =Base!K9 -> 0 | T14: =Base!M9 -> Saldo libre menor a S/ 10,000
A15: =SUBTOTAL(103,$B$6:B15) -> 6 | B15: 29 | C15: 2344324: MEJORAMIENTO DE LOS SERVICIOS EDUCATIVOS DE LA I.E.S. MANUEL GONZALES PRADA, CENTRO POBLADO DE ISANI - DISTRITO DE ZEPITA - PROVINCIA DE CHUCUITO - REGIÓN PUNO | D15: =Base!N10 -> 2079431 | E15: =Base!O10 -> 1994037.5 | F15: =D15-E15 -> 85393.54 | G15: =Base!Q10 -> 1946470.9 | H15: =D15-G15 -> 132960.06 | I15: =IF(D15=0,0,G15/D15) -> 0.9360594 | J15: =Base!AH10 -> Administración directa / Equipamiento / Contrata / Personal/bienes/servicios | K15: =Base!I10 -> Proyecto de inversión | L15: =Base!AA10 -> 298669 | M15: =Base!AB10 -> 349669 | N15: =Base!AC10 -> 84977 | O15: =Base!AD10 -> 0 | P15: =IF(Base!AI10="","",Base!AI10) | Q15: =Base!J10 -> No mover | R15: =Base!X10 -> 0.96964318 | S15: =Base!K10 -> 0 | T15: =Base!M10 -> Devengado 2026 ≥ 90% del PIM
A16: =SUBTOTAL(103,$B$6:B16) -> 7 | B16: 315 | C16: 2490075: MEJORAMIENTO DEL SERVICIO EDUCATIVO DEL NIVEL SECUNDARIA DE LA I.E. AGROPECUARIO SAN JUAN DEL ORO EN EL DISTRITO DE SAN JUAN DEL ORO - PROVINCIA DE SANDIA - DEPARTAMENTO DE PUNO | D16: =Base!N11 -> 1425006 | E16: =Base!O11 -> 1239788.9 | F16: =D16-E16 -> 185217.1 | G16: =Base!Q11 -> 1170437 | H16: =D16-G16 -> 254569.02 | I16: =IF(D16=0,0,G16/D16) -> 0.82135583 | J16: =Base!AH11 -> Administración directa / Equipamiento / Contrata / Personal/bienes/servicios | K16: =Base!I11 -> Proyecto de inversión | L16: =Base!AA11 -> 1122019 | M16: =Base!AB11 -> 0 | N16: =Base!AC11 -> 32869 | O16: =Base!AD11 -> 0 | P16: =IF(Base!AI11="","",Base!AI11) | Q16: =Base!J11 -> No mover | R16: =Base!X11 -> 0.97538828 | S16: =Base!K11 -> 0 | T16: =Base!M11 -> Avance financiero acumulado 98% (> 90%)
A17: =SUBTOTAL(103,$B$6:B17) -> 8 | B17: 160 | C17: 2570978: MEJORAMIENTO DE LOS SERVICIOS DE EDUCACIÓN SUPERIOR DEL INSTITUTO SUPERIOR TECNOLÓGICO PUBLICA DE CABANILLAS DEL DISTRITO DE CABANILLAS - PROVINCIA DE SAN ROMAN - DEPARTAMENTO DE PUNO | D17: =Base!N12 -> 9222405 | E17: =Base!O12 -> 9014527.5 | F17: =D17-E17 -> 207877.47 | G17: =Base!Q12 -> 5421356.6 | H17: =D17-G17 -> 3801048.4 | I17: =IF(D17=0,0,G17/D17) -> 0.58784629 | J17: =Base!AH12 -> Administración directa / Equipamiento / Contrata / Personal/bienes/servicios | K17: =Base!I12 -> Proyecto de inversión | L17: =Base!AA12 -> 2595053 | M17: =Base!AB12 -> 255676 | N17: =Base!AC12 -> 1817178 | O17: =Base!AD12 -> 0 | P17: =IF(Base!AI12="","",Base!AI12) | Q17: =Base!J12 -> Sin saldo útil | R17: =Base!X12 -> 0.75434398 | S17: =Base!K12 -> 0 | T17: =Base!M12 -> Saldo libre menor a S/ 10,000
A18: =SUBTOTAL(103,$B$6:B18) -> 9 | B18: 162 | C18: 2591926: MEJORAMIENTO SERVICIO DE EDUCACIÓN SUPERIOR TECNOLÓGICA EN EL INSTITUTO SUPERIOR TECNOLÓGICO PUBLICO JOSE DOMINGO CHOQUEHUANCA DEL DISTRITO DE JOSE DOMINGO CHOQUEHUANCA DE LA PROVINCIA DE AZANGARO DEL DEPARTAMENTO DE PUNO | D18: =Base!N13 -> 5194033 | E18: =Base!O13 -> 5106124.8 | F18: =D18-E18 -> 87908.23 | G18: =Base!Q13 -> 1941765.3 | H18: =D18-G18 -> 3252267.7 | I18: =IF(D18=0,0,G18/D18) -> 0.37384539 | J18: =Base!AH13 -> Contrata / Personal/bienes/servicios | K18: =Base!I13 -> Proyecto de inversión | L18: =Base!AA13 -> 5194033 | M18: =Base!AB13 -> 6569076 | N18: =Base!AC13 -> 1 | O18: =Base!AD13 -> 0 | P18: =IF(Base!AI13="","",Base!AI13) | Q18: =Base!J13 -> Sin saldo útil | R18: =Base!X13 -> 0.198674 | S18: =Base!K13 -> 0 | T18: =Base!M13 -> Saldo libre menor a S/ 10,000
A19: =SUBTOTAL(103,$B$6:B19) -> 10 | B19: 44 | C19: 2629119: MEJORAMIENTO DEL SERVICIO DE EDUCACIÓN SECUNDARIA EN I.E. ROSASPATA DE CENTRO POBLADO ROSASPATA DISTRITO DE ROSASPATA DE LA PROVINCIA DE HUANCANE DEL DEPARTAMENTO DE PUNO | D19: =Base!N14 -> 3656326 | E19: =Base!O14 -> 3427173.6 | F19: =D19-E19 -> 229152.4 | G19: =Base!Q14 -> 2126125.4 | H19: =D19-G19 -> 1530200.6 | I19: =IF(D19=0,0,G19/D19) -> 0.58149229 | J19: =Base!AH14 -> Administración directa / Contrata / Personal/bienes/servicios / Equipamiento | K19: =Base!I14 -> Proyecto de inversión | L19: =Base!AA14 -> 2278000 | M19: =Base!AB14 -> 1683936 | N19: =Base!AC14 -> 1459275 | O19: =Base!AD14 -> 0 | P19: =IF(Base!AI14="","",Base!AI14) | Q19: =Base!J14 -> Sin saldo útil | R19: =Base!X14 -> 0.33790841 | S19: =Base!K14 -> 0 | T19: =Base!M14 -> Saldo libre menor a S/ 10,000
A20: =SUBTOTAL(103,$B$6:B20) -> 11 | B20: 248 | C20: 2539673: MEJORAMIENTO Y AMPLIACION DEL SERVICIO DE EDUCACIÓN SUPERIOR TECNOLÓGICA EN EL INSTITUTO SUPERIOR TECNOLÓGICO PÚBLICO DE JULI, DISTRITO DE JULI - PROVINCIA DE CHUCUITO - DEPARTAMENTO DE PUNO | D20: =Base!N15 -> 2000000 | E20: =Base!O15 -> 2000000 | F20: =D20-E20 -> 0 | G20: =Base!Q15 -> 0 | H20: =D20-G20 -> 2000000 | I20: =IF(D20=0,0,G20/D20) -> 0 | J20: =Base!AH15 -> Contrata | K20: =Base!I15 -> Proyecto de inversión | L20: =Base!AA15 -> 12000000 | M20: =Base!AB15 -> 14558623 | N20: =Base!AC15 -> 14894208 | O20: =Base!AD15 -> 10928387 | P20: =IF(Base!AI15="","",Base!AI15) | Q20: =Base!J15 -> Sin saldo útil | R20: =Base!X15 -> 0.019000383 | S20: =Base!K15 -> 0 | T20: =Base!M15 -> Saldo libre menor a S/ 10,000
A21: =SUBTOTAL(103,$B$6:B21) -> 12 | B21: 45 | C21: 2637985: MEJORAMIENTO DEL SERVICIO DE EDUCACIÓN SECUNDARIA EN I.E. LLAULLI DE CENTRO POBLADO LLAULLI DISTRITO DE MOHO DE LA PROVINCIA DE MOHO DEL DEPARTAMENTO DE PUNO | D21: =Base!N16 -> 0 | E21: =Base!O16 -> 0 | F21: =D21-E21 -> 0 | G21: =Base!Q16 -> 0 | H21: =D21-G21 -> 0 | I21: =IF(D21=0,0,G21/D21) -> 0 | J21: =Base!AH16 -> Contrata | K21: =Base!I16 -> Proyecto de inversión | L21: =Base!AA16 -> 100000 | M21: =Base!AB16 -> 1234564 | N21: =Base!AC16 -> 0 | O21: =Base!AD16 -> 3335545 | P21: =IF(Base!AI16="","",Base!AI16) | Q21: =Base!J16 -> Sin PIM | R21: =Base!X16 -> 0.042971887 | S21: =Base!K16 -> 0 | T21: =Base!M16 -> PIM igual a 0
A22: =SUBTOTAL(103,$B$6:B22) -> 13 | B22: 193 | C22: 2664940: MEJORAMIENTO DEL SERVICIO DE EDUCACIÓN INICIAL EN I.E. 1099 INMACULADA DISTRITO DE PUTINA DE LA PROVINCIA DE SAN ANTONIO DE PUTINA DEL DEPARTAMENTO DE PUNO | D22: =Base!N17 -> 1861270 | E22: =Base!O17 -> 1508764.4 | F22: =D22-E22 -> 352505.59 | G22: =Base!Q17 -> 1164545.4 | H22: =D22-G22 -> 696724.63 | I22: =IF(D22=0,0,G22/D22) -> 0.62567245 | J22: =Base!AH17 -> Administración directa / Contrata / Expediente técnico / Equipamiento / Personal/bienes/servicios | K22: =Base!I17 -> Proyecto de inversión | L22: =Base!AA17 -> 1410000 | M22: =Base!AB17 -> 833474 | N22: =Base!AC17 -> 0 | O22: =Base!AD17 -> 0 | P22: =IF(Base!AI17="","",Base!AI17) | Q22: =Base!J17 -> Sin saldo útil | R22: =Base!X17 -> 0.54824752 | S22: =Base!K17 -> 0 | T22: =Base!M17 -> Saldo libre menor a S/ 10,000
A23: =SUBTOTAL(103,$B$6:B23) -> 14 | B23: 46 | C23: 2637997: MEJORAMIENTO DEL SERVICIO DE EDUCACIÓN SECUNDARIA EN I.E. UMUCHI DISTRITO DE MOHO DE LA PROVINCIA DE MOHO DEL DEPARTAMENTO DE PUNO | D23: =Base!N18 -> 304829 | E23: =Base!O18 -> 0 | F23: =D23-E23 -> 304829 | G23: =Base!Q18 -> 0 | H23: =D23-G23 -> 304829 | I23: =IF(D23=0,0,G23/D23) -> 0 | J23: =Base!AH18 -> Contrata | K23: =Base!I18 -> Proyecto de inversión | L23: =Base!AA18 -> 100000 | M23: =Base!AB18 -> 0 | N23: =Base!AC18 -> 0 | O23: =Base!AD18 -> 4317457 | P23: =IF(Base!AI18="","",Base!AI18) | Q23: =Base!J18 -> Sin saldo útil | R23: =Base!X18 -> 0.04318336 | S23: =Base!K18 -> 0 | T23: =Base!M18 -> Saldo libre menor a S/ 10,000
... A37: =SUBTOTAL(103,$B$6:B37) -> 28 | B37: 37 | C37: 2467893: MEJORAMIENTO DEL SERVICIO EDUCATIVO DEL NIVEL SECUNDARIA DE LA I.E.S. TARACO DEL DISTRITO DE TARACO - PROVINCIA DE HUANCANE - DEPARTAMENTO DE PUNO | D37: =Base!N32 -> 50132 | E37: =Base!O32 -> 47450.05 | F37: =D37-E37 -> 2681.95 | G37: =Base!Q32 -> 47450.05 | H37: =D37-G37 -> 2681.95 | I37: =IF(D37=0,0,G37/D37) -> 0.94650223 | J37: =Base!AH32 -> Contrata | K37: =Base!I32 -> Proyecto de inversión | L37: =Base!AA32 -> 175369 | M37: =Base!AB32 -> 79091 | N37: =Base!AC32 -> 583672 | O37: =Base!AD32 -> 0 | P37: =IF(Base!AI32="","",Base!AI32) | Q37: =Base!J32 -> No mover | R37: =Base!X32 -> 0.97144619 | S37: =Base!K32 -> 0 | T37: =Base!M32 -> Devengado 2026 ≥ 90% del PIM
A38: 15. TRANSPORTE | D38: =SUM(D39:D62) -> 87794613 | E38: =SUM(E39:E62) -> 84022839 | F38: =D38-E38 -> 3771773.7 | G38: =SUM(G39:G62) -> 50834366 | H38: =D38-G38 -> 36960247 | I38: =IF(D38=0,0,G38/D38) -> 0.57901463 | S38: =SUM(S39:S62) -> 276235.8
A39: =SUBTOTAL(103,$B$6:B39) -> 29 | B39: 95 | C39: 2194702: MEJORAMIENTO DE LA CARRETERA (PU 675) POMATA - YOROHOCO, PROVINCIA DE CHUCUITO - PUNO | D39: =Base!N33 -> 18401182 | E39: =Base!O33 -> 17786618 | F39: =D39-E39 -> 614564.47 | G39: =Base!Q33 -> 15484260 | H39: =D39-G39 -> 2916922.1 | I39: =IF(D39=0,0,G39/D39) -> 0.84148181 | J39: =Base!AH33 -> Administración directa / Contrata / Personal/bienes/servicios | K39: =Base!I33 -> Proyecto de inversión | L39: =Base!AA33 -> 9922902 | M39: =Base!AB33 -> 180000 | N39: =Base!AC33 -> 0 | O39: =Base!AD33 -> 0 | P39: =IF(Base!AI33="","",Base!AI33) | Q39: =Base!J33 -> No mover | R39: =Base!X33 -> 0.97469281 | S39: =Base!K33 -> 0 | T39: =Base!M33 -> Avance financiero acumulado 97% (> 90%)
A40: =SUBTOTAL(103,$B$6:B40) -> 30 | B40: 98 | C40: 2287700: MEJORAMIENTO DE LA CARRETERA PU N-110: EMP. PE-34I ASIRUNI - ROSASPATA - HUAYRAPATA - EMP. PE-34I NINANTAYA, DISTRITOS DE VILQUECHICO-ROSASPATA-MOHO-HUAYRAPATA, PROVINCIA DE HUANCANÉ Y MOHO - PUNO | D40: =Base!N34 -> 10002053 | E40: =Base!O34 -> 9646351.5 | F40: =D40-E40 -> 355701.52 | G40: =Base!Q34 -> 5473965.1 | H40: =D40-G40 -> 4528087.9 | I40: =IF(D40=0,0,G40/D40) -> 0.54728415 | J40: =Base!AH34 -> Administración directa / Contrata / Personal/bienes/servicios | K40: =Base!I34 -> Proyecto de inversión | L40: =Base!AA34 -> 4289351 | M40: =Base!AB34 -> 500000 | N40: =Base!AC34 -> 109570 | O40: =Base!AD34 -> 0 | P40: =IF(Base!AI34="","",Base!AI34) | Q40: =Base!J34 -> No mover | R40: =Base!X34 -> 0.93520523 | S40: =Base!K34 -> 0 | T40: =Base!M34 -> Avance financiero acumulado 94% (> 90%)
A41: =SUBTOTAL(103,$B$6:B41) -> 31 | B41: 112 | C41: 2480499: MEJORAMIENTO DE LA CARRETERA PU 146; EMP PE - 34 I (HUANCANÉ) - HUERTAPATA - VISCACHANI - QUELLAHUYO - EMP PE - 34 (CACUÑA), DISTRITO DE HUANCANE - PROVINCIA DE HUANCANE - DEPARTAMENTO DE PUNO | D41: =Base!N35 -> 3297813 | E41: =Base!O35 -> 3286650.5 | F41: =D41-E41 -> 11162.55 | G41: =Base!Q35 -> 3269277.3 | H41: =D41-G41 -> 28535.72 | I41: =IF(D41=0,0,G41/D41) -> 0.99134708 | J41: =Base!AH35 -> Administración directa / Contrata | K41: =Base!I35 -> Proyecto de inversión | L41: =Base!AA35 -> 5406629 | M41: =Base!AB35 -> 0 | N41: =Base!AC35 -> 304959 | O41: =Base!AD35 -> 0 | P41: =IF(Base!AI35="","",Base!AI35) | Q41: =Base!J35 -> No mover | R41: =Base!X35 -> 1.0068845 | S41: =Base!K35 -> 0 | T41: =Base!M35 -> Devengado 2026 ≥ 90% del PIM
A42: =SUBTOTAL(103,$B$6:B42) -> 32 | B42: 99 | C42: 2300575: MEJORAMIENTO DE LA AVENIDA CIRCUNVALACIÓN II (EMP. PE- 3S-AV. HUANCANE-CIRCUNVALACION ESTE-EMP PE-3S) DE LA CIUDAD DE JULIACA- EMPALME PU-3S INICIO CON CIRCUNVALACION II - DISTRITO DE SAN MIGUEL - EMPALME PU-3S FINAL CON CIRCUNVALACION II - DISTRITO DE CARACOTO - PROVINCIA DE SAN ROMAN - REGIÓN PUNO | D42: =Base!N36 -> 2394023 | E42: =Base!O36 -> 2316938.8 | F42: =D42-E42 -> 77084.21 | G42: =Base!Q36 -> 1138698.8 | H42: =D42-G42 -> 1255324.2 | I42: =IF(D42=0,0,G42/D42) -> 0.4756424 | J42: =Base!AH36 -> Administración directa / Contrata / Personal/bienes/servicios | K42: =Base!I36 -> Proyecto de inversión | L42: =Base!AA36 -> 3545977 | M42: =Base!AB36 -> 1000000 | N42: =Base!AC36 -> 3651450 | O42: =Base!AD36 -> 1489826 | P42: =IF(Base!AI36="","",Base!AI36) | Q42: =Base!J36 -> Sin saldo útil | R42: =Base!X36 -> 0.72408467 | S42: =Base!K36 -> 0 | T42: =Base!M36 -> Saldo libre menor a S/ 10,000
A43: =SUBTOTAL(103,$B$6:B43) -> 33 | B43: 87 | C43: 2031310: CONSTRUCCION Y MEJORAMIENTO DE LA CARRETERA SAN JOSE (EMP. R 100) VALLE GRANDE -ISILLUMA DEL DISTRITO DE ALTO INAMBARI | D43: =Base!N37 -> 1122559 | E43: =Base!O37 -> 1117871 | F43: =D43-E43 -> 4687.95 | G43: =Base!Q37 -> 1042098.6 | H43: =D43-G43 -> 80460.44 | I43: =IF(D43=0,0,G43/D43) -> 0.92832409 | J43: =Base!AH37 -> Administración directa / Contrata / Personal/bienes/servicios | K43: =Base!I37 -> Proyecto de inversión | L43: =Base!AA37 -> 1404195 | M43: =Base!AB37 -> 324567 | N43: =Base!AC37 -> 0 | O43: =Base!AD37 -> 936265 | P43: =IF(Base!AI37="","",Base!AI37) | Q43: =Base!J37 -> No mover | R43: =Base!X37 -> 0.89200651 | S43: =Base!K37 -> 0 | T43: =Base!M37 -> Devengado 2026 ≥ 90% del PIM
A44: =SUBTOTAL(103,$B$6:B44) -> 34 | B44: 92 | C44: 2163760: MEJORAMIENTO DE LA INFRAESTRUCTURA VIAL TURISTICO, TRAMO PHUTINI - JAYU JAYU ACORA, DISTRITO DE ACORA - PUNO - PUNO | D44: =Base!N38 -> 1202934 | E44: =Base!O38 -> 1151623.8 | F44: =D44-E44 -> 51310.21 | G44: =Base!Q38 -> 1105100.4 | H44: =D44-G44 -> 97833.58 | I44: =IF(D44=0,0,G44/D44) -> 0.91867087 | J44: =Base!AH38 -> Administración directa / Contrata / Personal/bienes/servicios | K44: =Base!I38 -> Proyecto de inversión | L44: =Base!AA38 -> 2596051 | M44: =Base!AB38 -> 120000 | N44: =Base!AC38 -> 2215461 | O44: =Base!AD38 -> 3675255 | P44: =IF(Base!AI38="","",Base!AI38) | Q44: =Base!J38 -> No mover | R44: =Base!X38 -> 0.90934923 | S44: =Base!K38 -> 0 | T44: =Base!M38 -> Devengado 2026 ≥ 90% del PIM
A45: =SUBTOTAL(103,$B$6:B45) -> 35 | B45: 104 | C45: 2375549: CREACION DE LA INFRAESTRUCTURA DE INTEGRACION VIAL ENTRE SANDIA (CP. QUENEQUE) Y PATAMBUCO (C.P. TIRACA), DISTRITO DE SANDIA Y PATAMBUCO, PROVINCIA DE SANDIA - PUNO | D45: =Base!N39 -> 167638 | E45: =Base!O39 -> 167637.03 | F45: =D45-E45 -> 0.97 | G45: =Base!Q39 -> 124800.07 | H45: =D45-G45 -> 42837.93 | I45: =IF(D45=0,0,G45/D45) -> 0.7444617 | J45: =Base!AH39 -> Administración directa | K45: =Base!I39 -> Proyecto de inversión | L45: =Base!AA39 -> 1200000 | M45: =Base!AB39 -> 2500000 | N45: =Base!AC39 -> 2882362 | O45: =Base!AD39 -> 1526602 | P45: =IF(Base!AI39="","",Base!AI39) | Q45: =Base!J39 -> Sin saldo útil | R45: =Base!X39 -> 0.70750659 | S45: =Base!K39 -> 0 | T45: =Base!M39 -> Saldo libre menor a S/ 10,000
A46: =SUBTOTAL(103,$B$6:B46) -> 36 | B46: 101 | C46: 2321290: MEJORAMIENTO DE LOS SERVICIOS DE TRANSITABILIDAD DE LA VÍA VECINAL PU-595: DV. PAMPA BLANCA - RINCONADA - CERRO LUNAR, DISTRITO DE ANANEA, PROVINCIA DE SAN ANTONIO DE PUTINA - PUNO | D46: =Base!N40 -> 844818 | E46: =Base!O40 -> 75387.03 | F46: =D46-E46 -> 769430.97 | G46: =Base!Q40 -> 75387.03 | H46: =D46-G46 -> 769430.97 | I46: =IF(D46=0,0,G46/D46) -> 0.08923464 | J46: =Base!AH40 -> Contrata / Laudos arbitrales / Personal/bienes/servicios | K46: =Base!I40 -> Proyecto de inversión | L46: =Base!AA40 -> 1050000 | M46: =Base!AB40 -> 50000 | N46: =Base!AC40 -> 1054806 | O46: =Base!AD40 -> 0 | P46: =IF(Base!AI40="","",Base!AI40) | Q46: =Base!J40 -> Sin saldo útil | R46: =Base!X40 -> 0.768331 | S46: =Base!K40 -> 0 | T46: =Base!M40 -> Saldo libre menor a S/ 10,000
A47: =SUBTOTAL(103,$B$6:B47) -> 37 | B47: 166 | C47: 2475053: MEJORAMIENTO DEL SERVICIO DE MOVILIDAD URBANA DE LA AV. ANDRES AVELINO CACERES (TRAMO: AV. TUPAC YUPANQUI - AV. AVIACIÓN), AV. LOS GERANIOS DEL DISTRITO DE JULIACA - PROVINCIA DE SAN ROMAN - DEPARTAMENTO DE PUNO | D47: =Base!N41 -> 0 | E47: =Base!O41 -> 0 | F47: =D47-E47 -> 0 | G47: =Base!Q41 -> 0 | H47: =D47-G47 -> 0 | I47: =IF(D47=0,0,G47/D47) -> 0 | J47: =Base!AH41 -> Administración directa | K47: =Base!I41 -> Proyecto de inversión | L47: =Base!AA41 -> 675842 | M47: =Base!AB41 -> 110000 | N47: =Base!AC41 -> 0 | O47: =Base!AD41 -> 0 | P47: =IF(Base!AI41="","",Base!AI41) | Q47: =Base!J41 -> Sin PIM | R47: =Base!X41 -> 0.96159048 | S47: =Base!K41 -> 0 | T47: =Base!M41 -> PIM igual a 0
A48: =SUBTOTAL(103,$B$6:B48) -> 38 | B48: 90 | C48: 2131661: CONSTRUCCION Y MEJORAMIENTO DE LA CARRETERA DESVIO VILQUECHICO-COJATA-SINA-YANAHUAYA. | D48: =Base!N42 -> 459851 | E48: =Base!O42 -> 344060.18 | F48: =D48-E48 -> 115790.82 | G48: =Base!Q42 -> 300345.76 | H48: =D48-G48 -> 159505.24 | I48: =IF(D48=0,0,G48/D48) -> 0.65313712 | J48: =Base!AH42 -> Administración directa / Equipamiento | K48: =Base!I42 -> Proyecto de inversión | L48: =Base!AA42 -> 4800690 | M48: =Base!AB42 -> 4000000 | N48: =Base!AC42 -> 14883202 | O48: =Base!AD42 -> 19038629 | P48: =IF(Base!AI42="","",Base!AI42) | Q48: =Base!J42 -> Sin saldo útil | R48: =Base!X42 -> 0.75748519 | S48: =Base!K42 -> 0 | T48: =Base!M42 -> Saldo libre menor a S/ 10,000
A49: =SUBTOTAL(103,$B$6:B49) -> 39 | B49: 96 | C49: 2195487: MEJORAMIENTO DEL CAMINO VECINAL (EMP. PE 3S) HUAQUINA ZAPIJICANE - PTO JULI - CHUCASUYO DEL DISTRITO DE JULI - PROVINCIA DE CHUCUITO - DEPARTAMENTO DE PUNO | D49: =Base!N43 -> 91759 | E49: =Base!O43 -> 91758.5 | F49: =D49-E49 -> 0.5 | G49: =Base!Q43 -> 82094.58 | H49: =D49-G49 -> 9664.42 | I49: =IF(D49=0,0,G49/D49) -> 0.89467605 | J49: =Base!AH43 -> Contrata / Administración directa / Personal/bienes/servicios | K49: =Base!I43 -> Proyecto de inversión | L49: =Base!AA43 -> 774665 | M49: =Base!AB43 -> 0 | N49: =Base!AC43 -> 707599 | O49: =Base!AD43 -> 0 | P49: =IF(Base!AI43="","",Base!AI43) | Q49: =Base!J43 -> No mover | R49: =Base!X43 -> 0.99741452 | S49: =Base!K43 -> 0 | T49: =Base!M43 -> Avance financiero acumulado 100% (> 90%)
A50: =SUBTOTAL(103,$B$6:B50) -> 40 | B50: 113 | C50: 2514428: CREACION DEL SERVICIO DE INTERCONEXION DE MOVILIDAD URBANA EN LA VÍA TRONCAL DEL PUENTE YARAJA DISTRITO DE AZANGARO - PROVINCIA DE AZANGARO - DEPARTAMENTO DE PUNO | D50: =Base!N44 -> 104124 | E50: =Base!O44 -> 48234.88 | F50: =D50-E50 -> 55889.12 | G50: =Base!Q44 -> 48234.88 | H50: =D50-G50 -> 55889.12 | I50: =IF(D50=0,0,G50/D50) -> 0.46324459 | J50: =Base!AH44 -> Administración directa / Contrata / Personal/bienes/servicios | K50: =Base!I44 -> Proyecto de inversión | L50: =Base!AA44 -> 228677 | M50: =Base!AB44 -> 0 | N50: =Base!AC44 -> 0 | O50: =Base!AD44 -> 865181 | P50: =IF(Base!AI44="","",Base!AI44) | Q50: =Base!J44 -> No mover | R50: =Base!X44 -> 0.95446881 | S50: =Base!K44 -> 0 | T50: =Base!M44 -> Avance financiero acumulado 95% (> 90%)
... A62: =SUBTOTAL(103,$B$6:B62) -> 52 | B62: 108 | C62: 2443679: MEJORAMIENTO DEL SERVICIO DE TRANSITABILIDAD VEHICULAR DE LA CARRETERA TRAMO I: EMP- 34L (COJATA) ¿ HUANCASAYA, TRAMO II: HUANCASAYA ¿ TARUCANI-EMP-PU-115 (INCHUPALLA), DEL DISTRITO DE COJATA - PROVINCIA DE HUANCANE - DEPARTAMENTO DE PUNO | D62: =Base!N56 -> 0 | E62: =Base!O56 -> 0 | F62: =D62-E62 -> 0 | G62: =Base!Q56 -> 0 | H62: =D62-G62 -> 0 | I62: =IF(D62=0,0,G62/D62) -> 0 | J62: =Base!AH56 -> Contrata | K62: =Base!I56 -> Proyecto de inversión | L62: =Base!AA56 -> 800000 | M62: =Base!AB56 -> 2345478 | N62: =Base!AC56 -> 9005306 | O62: =Base!AD56 -> 19493721 | P62: =IF(Base!AI56="","",Base!AI56) | Q62: =Base!J56 -> Sin PIM | R62: =Base!X56 -> 0.03798335 | S62: =Base!K56 -> 0 | T62: =Base!M56 -> PIM igual a 0
A63: 21. CULTURA Y DEPORTE | D63: =SUM(D64:D72) -> 24086616 | E63: =SUM(E64:E72) -> 20655001 | F63: =D63-E63 -> 3431614.6 | G63: =SUM(G64:G72) -> 5596985.4 | H63: =D63-G63 -> 18489631 | I63: =IF(D63=0,0,G63/D63) -> 0.2323691 | S63: =SUM(S64:S72) -> 391405.78
A64: =SUBTOTAL(103,$B$6:B64) -> 53 | B64: 217 | C64: 2163853: MEJORAMIENTO DEL ESTADIO MUNICIPAL CESAR RAUL CARRERA DEL DISTRITO DE AZANGARO, PROVINCIA DE AZANGARO - PUNO | D64: =Base!N57 -> 5810277 | E64: =Base!O57 -> 5204423.6 | F64: =D64-E64 -> 605853.4 | G64: =Base!Q57 -> 1157372.6 | H64: =D64-G64 -> 4652904.4 | I64: =IF(D64=0,0,G64/D64) -> 0.19919405 | J64: =Base!AH57 -> Administración directa / Contrata / Personal/bienes/servicios | K64: =Base!I57 -> Proyecto de inversión | L64: =Base!AA57 -> 6269000 | M64: =Base!AB57 -> 1345765 | N64: =Base!AC57 -> 5566267 | O64: =Base!AD57 -> 0 | P64: =IF(Base!AI57="","",Base!AI57) | Q64: =Base!J57 -> Sin saldo útil | R64: =Base!X57 -> 0.6748575 | S64: =Base!K57 -> 0 | T64: =Base!M57 -> Saldo libre menor a S/ 10,000
A65: =SUBTOTAL(103,$B$6:B65) -> 54 | B65: 63 | C65: 2188542: MEJORAMIENTO DE LA CAPACIDAD DE PRESTACION DE SERVICIOS DEPORTIVOS EN EL ESTADIO GUILLERMO BRICEÑO ROSAMEDINA DE LA CIUDAD DE JULIACA, PROVINCIA DE SAN ROMAN - PUNO | D65: =Base!N58 -> 5921783 | E65: =Base!O58 -> 5612635.5 | F65: =D65-E65 -> 309147.48 | G65: =Base!Q58 -> 1271806.7 | H65: =D65-G65 -> 4649976.3 | I65: =IF(D65=0,0,G65/D65) -> 0.21476753 | J65: =Base!AH58 -> Administración directa / Equipamiento / Contrata / Laudos arbitrales / Personal/bienes/servicios | K65: =Base!I58 -> Proyecto de inversión | L65: =Base!AA58 -> 1139986 | M65: =Base!AB58 -> 500000 | N65: =Base!AC58 -> 3220643 | O65: =Base!AD58 -> 0 | P65: =IF(Base!AI58="","",Base!AI58) | Q65: =Base!J58 -> Con condiciones | R65: =Base!X58 -> 0.84657376 | S65: =Base!K58 -> 309147.48 | T65: =Base!M58 -> Está programado en el PMI 2026 · Tiene monto en el PMI 2027 (S/ 500,000)
A66: =SUBTOTAL(103,$B$6:B66) -> 55 | B66: 62 | C66: 2186641: MEJORAMIENTO DEL SERVICIO DEPORTIVO, CULTURAL Y RECREACIONAL EN LA CAPITAL DE LA REGION PUNO | D66: =Base!N59 -> 1180793 | E66: =Base!O59 -> 1110291.7 | F66: =D66-E66 -> 70501.27 | G66: =Base!Q59 -> 1081390.3 | H66: =D66-G66 -> 99402.73 | I66: =IF(D66=0,0,G66/D66) -> 0.91581697 | J66: =Base!AH59 -> Administración directa | K66: =Base!I59 -> Proyecto de inversión | L66: =Base!AA59 -> 11675669 | M66: =Base!AB59 -> 6000000 | N66: =Base!AC59 -> 6503691 | O66: =Base!AD59 -> 7526858 | P66: =IF(Base!AI59="","",Base!AI59) | Q66: =Base!J59 -> Con condiciones | R66: =Base!X59 -> 0.48417508 | S66: =Base!K59 -> 55258.302 | T66: =Base!M59 -> Está programado en el PMI 2026 · Tiene monto en el PMI 2027 (S/ 6,000,000)
A67: =SUBTOTAL(103,$B$6:B67) -> 56 | B67: 72 | C67: 2646100: CONSTRUCCION DE CAMPO DEPORTIVO Y SERVICIOS HIGIENICOS Y/O VESTIDORES PARA PERSONAL; REPARACION DE TRIBUNA Y/O PALCO; EN EL(LA) ESTADIO MUNICIPAL DE SAN PEDRO DE PUTINA PUNCO DISTRITO DE SAN PEDRO DE PUTINA PUNCO, PROVINCIA SANDIA, DEPARTAMENTO PUNO | D67: =Base!N60 -> 2167000 | E67: =Base!O60 -> 1860545 | F67: =D67-E67 -> 306455 | G67: =Base!Q60 -> 33059.94 | H67: =D67-G67 -> 2133940.1 | I67: =IF(D67=0,0,G67/D67) -> 0.015256087 | J67: =Base!AH60 -> Contrata / Personal/bienes/servicios | K67: =Base!I60 -> IOARR | L67: =Base!AA60 -> 2000000 | M67: =Base!AB60 -> 1547463 | N67: =Base!AC60 -> 0 | O67: =Base!AD60 -> 0 | P67: =IF(Base!AI60="","",Base!AI60) | Q67: =Base!J60 -> Con condiciones | R67: =Base!X60 -> 0.03577907 | S67: =Base!K60 -> 27000 | T67: =Base!M60 -> Está programado en el PMI 2026 · Tiene monto en el PMI 2027 (S/ 1,547,463)
A68: =SUBTOTAL(103,$B$6:B68) -> 57 | B68: 67 | C68: 2645380: CONSTRUCCION DE TRIBUNA Y/O PALCO, CAMPO DEPORTIVO Y PISTA DE ATLETISMO (DEPORTE RECREATIVO); REPARACION DE SERVICIOS HIGIENICOS Y/O VESTIDORES; ADEMÁS DE OTROS ACTIVOS EN EL(LA) ESTADIO MUNICIPAL FERNANDO ROMERO CARREÓN DISTRITO DE LAMPA, PROVINCIA LAMPA, DEPARTAMENTO PUNO | D68: =Base!N61 -> 2575916 | E68: =Base!O61 -> 2503779 | F68: =D68-E68 -> 72137 | G68: =Base!Q61 -> 23527.19 | H68: =D68-G68 -> 2552388.8 | I68: =IF(D68=0,0,G68/D68) -> 0.0091335238 | J68: =Base!AH61 -> Contrata / Personal/bienes/servicios | K68: =Base!I61 -> IOARR | L68: =Base!AA61 -> 2575916 | M68: =Base!AB61 -> 2345678 | N68: =Base!AC61 -> 1558799 | O68: =Base!AD61 -> 0 | P68: =IF(Base!AI61="","",Base!AI61) | Q68: =Base!J61 -> Sin saldo útil | R68: =Base!X61 -> 0.02192269 | S68: =Base!K61 -> 0 | T68: =Base!M61 -> Saldo libre menor a S/ 10,000
A69: =SUBTOTAL(103,$B$6:B69) -> 58 | B69: 71 | C69: 2646096: CONSTRUCCION DE TRIBUNA Y/O PALCO; REPARACION DE TRIBUNA Y/O PALCO Y CAMPO DEPORTIVO; EN EL(LA) ESTADIO JOSE CARLOS MARIATEGUI DISTRITO DE YUNGUYO, PROVINCIA YUNGUYO, DEPARTAMENTO PUNO | D69: =Base!N62 -> 2054253 | E69: =Base!O62 -> 1854253 | F69: =D69-E69 -> 200000 | G69: =Base!Q62 -> 0 | H69: =D69-G69 -> 2054253 | I69: =IF(D69=0,0,G69/D69) -> 0 | J69: =Base!AH62 -> Contrata | K69: =Base!I62 -> IOARR | L69: =Base!AA62 -> 2054253 | M69: =Base!AB62 -> 2546789 | N69: =Base!AC62 -> 0 | O69: =Base!AD62 -> 0 | P69: =IF(Base!AI62="","",Base!AI62) | Q69: =Base!J62 -> Sin saldo útil | R69: =Base!X62 -> 0.021490835 | S69: =Base!K62 -> 0 | T69: =Base!M62 -> Saldo libre menor a S/ 10,000
A70: =SUBTOTAL(103,$B$6:B70) -> 59 | B70: 65 | C70: 2645340: REPARACION DE TRIBUNA Y/O PALCO Y SERVICIOS HIGIENICOS Y/O VESTIDORES; CONSTRUCCION DE CAMPO DEPORTIVO; EN EL(LA) ESTADIO MUNICIPAL CRUCERO DISTRITO DE CRUCERO, PROVINCIA CARABAYA, DEPARTAMENTO PUNO | D70: =Base!N63 -> 2038388 | E70: =Base!O63 -> 2031210.5 | F70: =D70-E70 -> 7177.5 | G70: =Base!Q63 -> 1711781.1 | H70: =D70-G70 -> 326606.88 | I70: =IF(D70=0,0,G70/D70) -> 0.83977198 | J70: =Base!AH63 -> Contrata / Personal/bienes/servicios | K70: =Base!I63 -> IOARR | L70: =Base!AA63 -> 2028388 | M70: =Base!AB63 -> 2258011 | N70: =Base!AC63 -> 0 | O70: =Base!AD63 -> 0 | P70: =IF(Base!AI63="","",Base!AI63) | Q70: =Base!J63 -> Sin saldo útil | R70: =Base!X63 -> 0.41523256 | S70: =Base!K63 -> 0 | T70: =Base!M63 -> Saldo libre menor a S/ 10,000
A71: =SUBTOTAL(103,$B$6:B71) -> 60 | B71: 252 | C71: 2555837: REPARACION DE CAMPO DEPORTIVO; ADQUISICION DE EQUIPO NO DEPORTIVO PARA INSTALACIONES DEPORTIVAS; EN EL(LA) ESTADIO ENRIQUE TORRES BELON DISTRITO DE PUNO, PROVINCIA PUNO, DEPARTAMENTO PUNO | D71: =Base!N64 -> 2047936 | E71: =Base!O64 -> 377863 | F71: =D71-E71 -> 1670073 | G71: =Base!Q64 -> 318047.53 | H71: =D71-G71 -> 1729888.5 | I71: =IF(D71=0,0,G71/D71) -> 0.1553015 | J71: =Base!AH64 -> Contrata / Personal/bienes/servicios | K71: =Base!I64 -> IOARR | L71: =Base!AA64 -> 327863 | M71: =Base!AB64 -> 1876545 | N71: =Base!AC64 -> 0 | O71: =Base!AD64 -> 0 | P71: =IF(Base!AI64="","",Base!AI64) | Q71: =Base!J64 -> Sin saldo útil | R71: =Base!X64 -> 0.10913883 | S71: =Base!K64 -> 0 | T71: =Base!M64 -> Saldo libre menor a S/ 10,000
A72: =SUBTOTAL(103,$B$6:B72) -> 61 | B72: 260 | C72: 2593683: REPARACION DE PISTA DE ATLETISMO (COMPETENCIA); ADQUISICION DE TORRE DE ILUMINACION; EN EL(LA) ESTADIO ENRIQUE TORRES BELON DEL DISTRITO DE PUNO, PROVINCIA PUNO, DEPARTAMENTO PUNO | D72: =Base!N65 -> 290270 | E72: =Base!O65 -> 100000 | F72: =D72-E72 -> 190270 | G72: =Base!Q65 -> 0 | H72: =D72-G72 -> 290270 | I72: =IF(D72=0,0,G72/D72) -> 0 | J72: =Base!AH65 -> Contrata | K72: =Base!I65 -> IOARR | L72: =Base!AA65 -> 100000 | M72: =Base!AB65 -> 2089685 | N72: =Base!AC65 -> 3000000 | O72: =Base!AD65 -> 11639950 | P72: =IF(Base!AI65="","",Base!AI65) | Q72: =Base!J65 -> Sin saldo útil | R72: =Base!X65 -> 0.0080433598 | S72: =Base!K65 -> 0 | T72: =Base!M65 -> Saldo libre menor a S/ 10,000
A73: 03. PLANEAMIENTO, GESTION Y RESERVA DE CONTINGENCIA | D73: =SUM(D74:D74) -> 7609099 | E73: =SUM(E74:E74) -> 7595390.9 | F73: =D73-E73 -> 13708.12 | G73: =SUM(G74:G74) -> 7570246.4 | H73: =D73-G73 -> 38852.61 | I73: =IF(D73=0,0,G73/D73) -> 0.99489393 | S73: =SUM(S74:S74) -> 0
A74: =SUBTOTAL(103,$B$6:B74) -> 62 | B74: 259 | C74: 2592407: MEJORAMIENTO DE LOS SERVICIOS OPERATIVOS O MISIONALES INSTITUCIONALES EN LA OFICINA DE EQUIPO MECANICO DEL GOBIERNO REGIONAL PUNO DISTRITO DE PUNO DE LA PROVINCIA DE PUNO DEL DEPARTAMENTO DE PUNO | D74: =Base!N66 -> 7609099 | E74: =Base!O66 -> 7595390.9 | F74: =D74-E74 -> 13708.12 | G74: =Base!Q66 -> 7570246.4 | H74: =D74-G74 -> 38852.61 | I74: =IF(D74=0,0,G74/D74) -> 0.99489393 | J74: =Base!AH66 -> Equipamiento / Contrata / Personal/bienes/servicios | K74: =Base!I66 -> Proyecto de inversión | L74: =Base!AA66 -> 6185000 | M74: =Base!AB66 -> 1000000 | N74: =Base!AC66 -> 0 | O74: =Base!AD66 -> 1000000 | P74: =IF(Base!AI66="","",Base!AI66) | Q74: =Base!J66 -> No mover | R74: =Base!X66 -> 0.93648812 | S74: =Base!K66 -> 0 | T74: =Base!M66 -> Devengado 2026 ≥ 90% del PIM
A75: 23. PROTECCION SOCIAL | D75: =SUM(D76:D77) -> 232742 | E75: =SUM(E76:E77) -> 99007.59 | F75: =D75-E75 -> 133734.41 | G75: =SUM(G76:G77) -> 96198.77 | H75: =D75-G75 -> 136543.23 | I75: =IF(D75=0,0,G75/D75) -> 0.41332793 | S75: =SUM(S76:S77) -> 0
A76: =SUBTOTAL(103,$B$6:B76) -> 63 | B76: 456 | C76: 2230752: MEJORAMIENTO DE LOS SERVICIOS ASISTENCIALES DE LA ALDEA INFANTIL VIRGEN DE LA CANDELARIA EN EL BARRIO LA RINCONADA DEL CENTRO POBLADO DE SALCEDO, DISTRITO DE PUNO, PROVINCIA DE PUNO, REGION DE PUNO | D76: =Base!N67 -> 99230 | E76: =Base!O67 -> 99007.59 | F76: =D76-E76 -> 222.41 | G76: =Base!Q67 -> 96198.77 | H76: =D76-G76 -> 3031.23 | I76: =IF(D76=0,0,G76/D76) -> 0.96945248 | J76: =Base!AH67 -> Administración directa / Contrata / Personal/bienes/servicios | K76: =Base!I67 -> Proyecto de inversión | L76: =Base!AA67 -> 99230 | M76: =Base!AB67 -> 0 | N76: =Base!AC67 -> 0 | O76: =Base!AD67 -> 0 | P76: =IF(Base!AI67="","",Base!AI67) | Q76: =Base!J67 -> No mover | R76: =Base!X67 -> 0.98663822 | S76: =Base!K67 -> 0 | T76: =Base!M67 -> Devengado 2026 ≥ 90% del PIM
A77: =SUBTOTAL(103,$B$6:B77) -> 64 | B77: 458 | C77: 2194989: MEJORAMIENTO DE LOS SERVICIOS EDUCATIVOS EN LA INSTITUCION EDUCATIVA SECUNDARIA DANTE NAVA DEL CENTRO POBLADO SANTA CRUZ DE PUNA AYLLU, DISTRITO DE PATAMBUCO, PROVINCIA DE SANDIA, REGION PUNO | D77: =Base!N68 -> 133512 | E77: =Base!O68 -> 0 | F77: =D77-E77 -> 133512 | G77: =Base!Q68 -> 0 | H77: =D77-G77 -> 133512 | I77: =IF(D77=0,0,G77/D77) -> 0 | J77: =Base!AH68 -> Administración directa | K77: =Base!I68 -> Proyecto de inversión | L77: =Base!AA68 -> No registrado en cartera | M77: =Base!AB68 -> No registrado en cartera | N77: =Base!AC68 -> No registrado en cartera | O77: =Base!AD68 -> No registrado en cartera | P77: =IF(Base!AI68="","",Base!AI68) | Q77: =Base!J68 -> No mover | R77: =Base!X68 -> 0.98939334 | S77: =Base!K68 -> 0 | T77: =Base!M68 -> Avance financiero acumulado 99% (> 90%)
A78: EJECUCIÓN POR ADMINISTRACIÓN DIRECTA - DIRECTIVA 17 | D78: =D79+D86+D107+D118 -> 267396323 | E78: =E79+E86+E107+E118 -> 2.4956322e+08 | F78: =D78-E78 -> 17833098 | G78: =G79+G86+G107+G118 -> 1.5915041e+08 | H78: =D78-G78 -> 1.0824591e+08 | I78: =IF(D78=0,0,G78/D78) -> 0.59518549 | S78: =S79+S86+S107+S118 -> 1903216.2
A79: 20. SALUD | D79: =SUM(D80:D85) -> 32634907 | E79: =SUM(E80:E85) -> 31046889 | F79: =D79-E79 -> 1588017.8 | G79: =SUM(G80:G85) -> 13051954 | H79: =D79-G79 -> 19582953 | I79: =IF(D79=0,0,G79/D79) -> 0.39993844 | S79: =SUM(S80:S85) -> 828402.62
A80: =SUBTOTAL(103,$B$6:B80) -> 65 | B80: 242 | C80: 2504553: MEJORAMIENTO DEL SERVICIO DE SALUD EN EL CENTRO DE SALUD YANAPATA DE LA MICRO RED COPANI, RED DE SALUD YUNGUYO, DISTRITO DE YUNGUYO - PROVINCIA DE YUNGUYO - DEPARTAMENTO DE PUNO | D80: =Base!N69 -> 8256172 | E80: =Base!O69 -> 7558918.9 | F80: =D80-E80 -> 697253.09 | G80: =Base!Q69 -> 4485721.8 | H80: =D80-G80 -> 3770450.2 | I80: =IF(D80=0,0,G80/D80) -> 0.54331739 | J80: =Base!AH69 -> Administración directa / Equipamiento / Contrata / Personal/bienes/servicios | K80: =Base!I69 -> Proyecto de inversión | L80: =Base!AA69 -> 9468125 | M80: =Base!AB69 -> 933429 | N80: =Base!AC69 -> 6042788 | O80: =Base!AD69 -> 2500000 | P80: =IF(Base!AI69="","",Base!AI69) | Q80: =Base!J69 -> Con condiciones | R80: =Base!X69 -> 0.45967288 | S80: =Base!K69 -> 617941.43 | T80: =Base!M69 -> Está programado en el PMI 2026 · Tiene monto en el PMI 2027 (S/ 933,429)
A81: =SUBTOTAL(103,$B$6:B81) -> 66 | B81: 237 | C81: 2470517: MEJORAMIENTO DE LOS SERVICIOS DE SALUD DEL CENTRO DE SALUD COPANI DE LA MICRO RED COPANI, RED DE SALUD YUNGUYO, DISTRITO DE COPANI - PROVINCIA DE YUNGUYO - DEPARTAMENTO DE PUNO | D81: =Base!N70 -> 7374992 | E81: =Base!O70 -> 7374802 | F81: =D81-E81 -> 190 | G81: =Base!Q70 -> 0 | H81: =D81-G81 -> 7374992 | I81: =IF(D81=0,0,G81/D81) -> 0 | J81: =Base!AH70 -> Contrata | K81: =Base!I70 -> Proyecto de inversión | L81: =Base!AA70 -> 8000000 | M81: =Base!AB70 -> 8258658 | N81: =Base!AC70 -> 10741348 | O81: =Base!AD70 -> 1075057 | P81: =IF(Base!AI70="","",Base!AI70) | Q81: =Base!J70 -> Rebajando certificación | R81: =Base!X70 -> 0.047842837 | S81: =Base!K70 -> 190 | T81: =Base!M70 -> Sin saldo libre; hay S/ 6,993,828 certificados sin comprometer ni programar en el 12-B (requiere rebajar la certificación)
A82: =SUBTOTAL(103,$B$6:B82) -> 67 | B82: 228 | C82: 2357092: MEJORAMIENTO DE LOS SERVICIOS DE SALUD DEL CENTRO DE SALUD COJATA, DISTRITO DE COJATA - PROVINCIA DE HUANCANE - DEPARTAMENTO DE PUNO | D82: =Base!N71 -> 6997430 | E82: =Base!O71 -> 6787158.8 | F82: =D82-E82 -> 210271.19 | G82: =Base!Q71 -> 2630352.4 | H82: =D82-G82 -> 4367077.6 | I82: =IF(D82=0,0,G82/D82) -> 0.37590264 | J82: =Base!AH71 -> Administración directa / Contrata / Personal/bienes/servicios / Equipamiento | K82: =Base!I71 -> Proyecto de inversión | L82: =Base!AA71 -> 8000000 | M82: =Base!AB71 -> 10256256 | N82: =Base!AC71 -> 15069544 | O82: =Base!AD71 -> 4478827 | P82: =IF(Base!AI71="","",Base!AI71) | Q82: =Base!J71 -> Con condiciones | R82: =Base!X71 -> 0.20486183 | S82: =Base!K71 -> 210271.19 | T82: =Base!M71 -> Está programado en el PMI 2026 · Tiene monto en el PMI 2027 (S/ 10,256,256)
A83: =SUBTOTAL(103,$B$6:B83) -> 68 | B83: 241 | C83: 2494039: MEJORAMIENTO Y AMPLIACION DE LOS SERVICIOS DE SALUD EN EL ESTABLECIMIENTO DE SALUD UMACHIRI CATEGORÍA I-2 DEL DISTRITO DE UMACHIRI - PROVINCIA DE MELGAR - DEPARTAMENTO DE PUNO | D83: =Base!N72 -> 6688287 | E83: =Base!O72 -> 6161937.9 | F83: =D83-E83 -> 526349.08 | G83: =Base!Q72 -> 3692512.7 | H83: =D83-G83 -> 2995774.3 | I83: =IF(D83=0,0,G83/D83) -> 0.55208646 | J83: =Base!AH72 -> Administración directa / Equipamiento / Contrata / Personal/bienes/servicios | K83: =Base!I72 -> Proyecto de inversión | L83: =Base!AA72 -> 2822702 | M83: =Base!AB72 -> 65844 | N83: =Base!AC72 -> 0 | O83: =Base!AD72 -> 0 | P83: =IF(Base!AI72="","",Base!AI72) | Q83: =Base!J72 -> Sin saldo útil | R83: =Base!X72 -> 0.74288605 | S83: =Base!K72 -> 0 | T83: =Base!M72 -> Saldo libre menor a S/ 10,000
A84: =SUBTOTAL(103,$B$6:B84) -> 69 | B84: 221 | C84: 2290342: MEJORAMIENTO DE LA CAPACIDAD RESOLUTIVA DE LOS SERVICIOS DEL PUESTO DE SALUD I - 1 DEL CENTRO POBLADO DE CARI CARI DEL DISTRITO DE MAÑAZO - PROVINCIA DE PUNO - DEPARTAMENTO DE PUNO | D84: =Base!N73 -> 3318026 | E84: =Base!O73 -> 3164071.6 | F84: =D84-E84 -> 153954.43 | G84: =Base!Q73 -> 2243366.7 | H84: =D84-G84 -> 1074659.3 | I84: =IF(D84=0,0,G84/D84) -> 0.67611487 | J84: =Base!AH73 -> Administración directa / Equipamiento / Contrata / Expediente técnico / Personal/bienes/servicios | K84: =Base!I73 -> Proyecto de inversión | L84: =Base!AA73 -> 821892 | M84: =Base!AB73 -> 47336 | N84: =Base!AC73 -> 0 | O84: =Base!AD73 -> 0 | P84: =IF(Base!AI73="","",Base!AI73) | Q84: =Base!J73 -> Sin saldo útil | R84: =Base!X73 -> 0.75787094 | S84: =Base!K73 -> 0 | T84: =Base!M73 -> Saldo libre menor a S/ 10,000
A85: =SUBTOTAL(103,$B$6:B85) -> 70 | B85: 235 | C85: 2451529: MEJORAMIENTO DEL SERVICIO DE SALUD EN EL CENTRO DE SALUD PILCUYO DE LA MICRORED PILCUYO, RED DE SALUD EL COLLAO , DEL DISTRITO DE PILCUYO - PROVINCIA DE EL COLLAO - DEPARTAMENTO DE PUNO | D85: =Base!N74 -> 0 | E85: =Base!O74 -> 0 | F85: =D85-E85 -> 0 | G85: =Base!Q74 -> 0 | H85: =D85-G85 -> 0 | I85: =IF(D85=0,0,G85/D85) -> 0 | J85: =Base!AH74 -> Contrata | K85: =Base!I74 -> Proyecto de inversión | L85: =Base!AA74 -> 12571000 | M85: =Base!AB74 -> 5987564 | N85: =Base!AC74 -> 16094501 | O85: =Base!AD74 -> 22576094 | P85: =IF(Base!AI74="","",Base!AI74) | Q85: =Base!J74 -> Sin PIM | R85: =Base!X74 -> 0.037605346 | S85: =Base!K74 -> 0 | T85: =Base!M74 -> PIM igual a 0
A86: 22. EDUCACION | D86: =SUM(D87:D106) -> 160639248 | E86: =SUM(E87:E106) -> 1.502546e+08 | F86: =D86-E86 -> 10384648 | G86: =SUM(G87:G106) -> 1.0469469e+08 | H86: =D86-G86 -> 55944554 | I86: =IF(D86=0,0,G86/D86) -> 0.65173795 | S86: =SUM(S87:S106) -> 1061888.6
A87: =SUBTOTAL(103,$B$6:B87) -> 71 | B87: 35 | C87: 2411336: MEJORAMIENTO SERVICIO INTEGRAL DE LA INSTITUCION EDUCATIVA SECUNDARIA INDUSTRIAL PERU BIRF DISTRITO DE SAN MIGUEL - PROVINCIA DE SAN ROMAN - DEPARTAMENTO DE PUNO | D87: =Base!N75 -> 21914154 | E87: =Base!O75 -> 21779068 | F87: =D87-E87 -> 135085.94 | G87: =Base!Q75 -> 15564867 | H87: =D87-G87 -> 6349286.6 | I87: =IF(D87=0,0,G87/D87) -> 0.7102655 | J87: =Base!AH75 -> Administración directa / Equipamiento / Contrata / Personal/bienes/servicios / Laudos arbitrales | K87: =Base!I75 -> Proyecto de inversión | L87: =Base!AA75 -> 11955231 | M87: =Base!AB75 -> 2500000 | N87: =Base!AC75 -> 3884089 | O87: =Base!AD75 -> 0 | P87: =IF(Base!AI75="","",Base!AI75) | Q87: =Base!J75 -> Sin saldo útil | R87: =Base!X75 -> 0.80148154 | S87: =Base!K75 -> 0 | T87: =Base!M75 -> Saldo libre menor a S/ 10,000
A88: =SUBTOTAL(103,$B$6:B88) -> 72 | B88: 25 | C88: 2284935: MEJORAMIENTO DEL SERVICIO EDUCATIVO EN LA IES POLITÉCNICO REGIONAL LOS ANDES, DISTRITO DE JULIACA, PROVINCIA DE SAN ROMÁN - PUNO | D88: =Base!N76 -> 22276780 | E88: =Base!O76 -> 17932576 | F88: =D88-E88 -> 4344203.8 | G88: =Base!Q76 -> 15417466 | H88: =D88-G88 -> 6859314 | I88: =IF(D88=0,0,G88/D88) -> 0.69208683 | J88: =Base!AH76 -> Administración directa / Contrata / Personal/bienes/servicios / Equipamiento | K88: =Base!I76 -> Proyecto de inversión | L88: =Base!AA76 -> 15800000 | M88: =Base!AB76 -> 14789542 | N88: =Base!AC76 -> 15918407 | O88: =Base!AD76 -> 10295229 | P88: =IF(Base!AI76="","",Base!AI76) | Q88: =Base!J76 -> Sin saldo útil | R88: =Base!X76 -> 0.38846999 | S88: =Base!K76 -> 0 | T88: =Base!M76 -> Saldo libre menor a S/ 10,000
A89: =SUBTOTAL(103,$B$6:B89) -> 73 | B89: 229 | C89: 2357330: MEJORAMIENTO DE LOS SERVICIOS DE EDUCACIÓN SUPERIOR TECNOLÓGICA DEL IESTP HUANCANÉ DEL DISTRITO DE HUANCANE - PROVINCIA DE HUANCANE - DEPARTAMENTO DE PUNO | D89: =Base!N77 -> 17354707 | E89: =Base!O77 -> 17160547 | F89: =D89-E89 -> 194159.58 | G89: =Base!Q77 -> 8610007.7 | H89: =D89-G89 -> 8744699.3 | I89: =IF(D89=0,0,G89/D89) -> 0.49611945 | J89: =Base!AH77 -> Administración directa / Equipamiento / Contrata / Personal/bienes/servicios | K89: =Base!I77 -> Proyecto de inversión | L89: =Base!AA77 -> 12500000 | M89: =Base!AB77 -> 4806839 | N89: =Base!AC77 -> 753613 | O89: =Base!AD77 -> 0 | P89: =IF(Base!AI77="","",Base!AI77) | Q89: =Base!J77 -> Sin saldo útil | R89: =Base!X77 -> 0.59624892 | S89: =Base!K77 -> 0 | T89: =Base!M77 -> Saldo libre menor a S/ 10,000
A90: =SUBTOTAL(103,$B$6:B90) -> 74 | B90: 30 | C90: 2357322: MEJORAMIENTO SERVICIO EDUCATIVO EN LA IES. 32 MARIANO H. CORNEJO DE LA LOCALIDAD DE JULIACA - DISTRITO DE JULIACA - PROVINCIA DE SAN ROMAN - REGIÓN PUNO | D90: =Base!N78 -> 19795501 | E90: =Base!O78 -> 19793412 | F90: =D90-E90 -> 2089.28 | G90: =Base!Q78 -> 14545766 | H90: =D90-G90 -> 5249734.8 | I90: =IF(D90=0,0,G90/D90) -> 0.73480162 | J90: =Base!AH78 -> Administración directa / Equipamiento / Contrata / Personal/bienes/servicios | K90: =Base!I78 -> Proyecto de inversión | L90: =Base!AA78 -> 9609000 | M90: =Base!AB78 -> 897867 | N90: =Base!AC78 -> 6124874 | O90: =Base!AD78 -> 0 | P90: =IF(Base!AI78="","",Base!AI78) | Q90: =Base!J78 -> Sin saldo útil | R90: =Base!X78 -> 0.77209742 | S90: =Base!K78 -> 0 | T90: =Base!M78 -> Saldo libre menor a S/ 10,000
A91: =SUBTOTAL(103,$B$6:B91) -> 75 | B91: 33 | C91: 2385673: MEJORAMIENTO DEL SERVICIO EDUCATIVO DE LA I.E.S. LAS MERCEDES DE LA CIUDAD DE JULIACA - DISTRITO DE JULIACA - PROVINCIA DE SAN ROMAN - DEPARTAMENTO DE PUNO | D91: =Base!N79 -> 17241964 | E91: =Base!O79 -> 17144705 | F91: =D91-E91 -> 97259.44 | G91: =Base!Q79 -> 11639796 | H91: =D91-G91 -> 5602167.7 | I91: =IF(D91=0,0,G91/D91) -> 0.67508529 | J91: =Base!AH79 -> Administración directa / Contrata / Personal/bienes/servicios / Equipamiento | K91: =Base!I79 -> Proyecto de inversión | L91: =Base!AA79 -> 8016014 | M91: =Base!AB79 -> 10000000 | N91: =Base!AC79 -> 1057112 | O91: =Base!AD79 -> 2541629 | P91: =IF(Base!AI79="","",Base!AI79) | Q91: =Base!J79 -> Sin saldo útil | R91: =Base!X79 -> 0.62513894 | S91: =Base!K79 -> 0 | T91: =Base!M79 -> Saldo libre menor a S/ 10,000
A92: =SUBTOTAL(103,$B$6:B92) -> 76 | B92: 161 | C92: 2585543: MEJORAMIENTO Y AMPLIACION DEL SERVICIO DE EDUCACIÓN SUPERIOR TECNOLÓGICA EN EL INSTITUTO DE EDUCACIÓN SUPERIOR TECNOLÓGICO PUBLICO ACORA DEL DISTRITO DE ACORA DE LA PROVINCIA DE PUNO DEL DEPARTAMENTO DE PUNO | D92: =Base!N80 -> 15380884 | E92: =Base!O80 -> 14335355 | F92: =D92-E92 -> 1045528.8 | G92: =Base!Q80 -> 9463521.5 | H92: =D92-G92 -> 5917362.5 | I92: =IF(D92=0,0,G92/D92) -> 0.61527812 | J92: =Base!AH80 -> Administración directa / Equipamiento / Contrata / Personal/bienes/servicios | K92: =Base!I80 -> Proyecto de inversión | L92: =Base!AA80 -> 6000000 | M92: =Base!AB80 -> 3456765 | N92: =Base!AC80 -> 1108030 | O92: =Base!AD80 -> 0 | P92: =IF(Base!AI80="","",Base!AI80) | Q92: =Base!J80 -> Con condiciones | R92: =Base!X80 -> 0.55837026 | S92: =Base!K80 -> 1045528.8 | T92: =Base!M80 -> Está programado en el PMI 2026 · Tiene monto en el PMI 2027 (S/ 3,456,765)
A93: =SUBTOTAL(103,$B$6:B93) -> 77 | B93: 247 | C93: 2535611: MEJORAMIENTO Y AMPLIACION DEL SERVICIO DE EDUCACION SUPERIOR TECNOLOGICO PUBLICO EN EL INSTITUTO "ANDRES AVELINO CACERES" DISTRITO DE PUTINA - PROVINCIA DE SAN ANTONIO DE PUTINA - DEPARTAMENTO DE PUNO | D93: =Base!N81 -> 9666000 | E93: =Base!O81 -> 9227635.3 | F93: =D93-E93 -> 438364.67 | G93: =Base!Q81 -> 5594991.1 | H93: =D93-G93 -> 4071008.9 | I93: =IF(D93=0,0,G93/D93) -> 0.5788321 | J93: =Base!AH81 -> Administración directa / Contrata / Personal/bienes/servicios | K93: =Base!I81 -> Proyecto de inversión | L93: =Base!AA81 -> 7546000 | M93: =Base!AB81 -> 1410563 | N93: =Base!AC81 -> 1509243 | O93: =Base!AD81 -> 0 | P93: =IF(Base!AI81="","",Base!AI81) | Q93: =Base!J81 -> Sin saldo útil | R93: =Base!X81 -> 0.69838845 | S93: =Base!K81 -> 0 | T93: =Base!M81 -> Saldo libre menor a S/ 10,000
A94: =SUBTOTAL(103,$B$6:B94) -> 78 | B94: 39 | C94: 2538950: MEJORAMIENTO DEL SERVICIO EDUCATIVO DEL NIVEL PRIMARIO DE LA I.E. 71008 EN EL DISTRITO DE LAMPA - PROVINCIA DE LAMPA - DEPARTAMENTO DE PUNO | D94: =Base!N82 -> 6765264 | E94: =Base!O82 -> 6670193.8 | F94: =D94-E94 -> 95070.21 | G94: =Base!Q82 -> 4177875.5 | H94: =D94-G94 -> 2587388.5 | I94: =IF(D94=0,0,G94/D94) -> 0.61754804 | J94: =Base!AH82 -> Administración directa / Equipamiento / Contrata / Personal/bienes/servicios | K94: =Base!I82 -> Proyecto de inversión | L94: =Base!AA82 -> No registrado en cartera | M94: =Base!AB82 -> No registrado en cartera | N94: =Base!AC82 -> No registrado en cartera | O94: =Base!AD82 -> No registrado en cartera | P94: =IF(Base!AI82="","",Base!AI82) | Q94: =Base!J82 -> Sin saldo útil | R94: =Base!X82 -> 0.66274788 | S94: =Base!K82 -> 0 | T94: =Base!M82 -> Saldo libre menor a S/ 10,000
A95: =SUBTOTAL(103,$B$6:B95) -> 79 | B95: 26 | C95: 2289661: MEJORAMIENTO DE LOS SERVICIOS EDUCATIVOS EN LA I.E.S. DOS DE MAYO DE CARACOTO, DISTRITO DE CARACOTO - SAN ROMAN - PUNO | D95: =Base!N83 -> 4291327 | E95: =Base!O83 -> 4093667 | F95: =D95-E95 -> 197659.95 | G95: =Base!Q83 -> 3891386.8 | H95: =D95-G95 -> 399940.21 | I95: =IF(D95=0,0,G95/D95) -> 0.90680267 | J95: =Base!AH83 -> Administración directa / Contrata / Equipamiento / Personal/bienes/servicios | K95: =Base!I83 -> Proyecto de inversión | L95: =Base!AA83 -> No registrado en cartera | M95: =Base!AB83 -> No registrado en cartera | N95: =Base!AC83 -> No registrado en cartera | O95: =Base!AD83 -> No registrado en cartera | P95: =IF(Base!AI83="","",Base!AI83) | Q95: =Base!J83 -> No mover | R95: =Base!X83 -> 0.96908085 | S95: =Base!K83 -> 0 | T95: =Base!M83 -> Devengado 2026 ≥ 90% del PIM
A96: =SUBTOTAL(103,$B$6:B96) -> 80 | B96: 41 | C96: 2590087: MEJORAMIENTO DEL SERVICIO DE EDUCACION SECUNDARIA EN I.E. JOSE MARIA ARGUEDAS DISTRITO DE LLALLI DE LA PROVINCIA DE MELGAR DEL DEPARTAMENTO DE PUNO | D96: =Base!N84 -> 5799805 | E96: =Base!O84 -> 5301125.5 | F96: =D96-E96 -> 498679.49 | G96: =Base!Q84 -> 3934515.9 | H96: =D96-G96 -> 1865289.1 | I96: =IF(D96=0,0,G96/D96) -> 0.67838761 | J96: =Base!AH84 -> Administración directa / Contrata / Equipamiento / Personal/bienes/servicios | K96: =Base!I84 -> Proyecto de inversión | L96: =Base!AA84 -> No registrado en cartera | M96: =Base!AB84 -> No registrado en cartera | N96: =Base!AC84 -> No registrado en cartera | O96: =Base!AD84 -> No registrado en cartera | P96: =IF(Base!AI84="","",Base!AI84) | Q96: =Base!J84 -> Sin saldo útil | R96: =Base!X84 -> 0.87478149 | S96: =Base!K84 -> 0 | T96: =Base!M84 -> Saldo libre menor a S/ 10,000
A97: =SUBTOTAL(103,$B$6:B97) -> 81 | B97: 36 | C97: 2417765: MEJORAMIENTO Y AMPLIACION DEL SERVICIOS DE EDUCACION BASICA EN EL NIVEL PRIMARIO DE LA IEP Nº 72169 TAMBILLO, IEP Nº 72175 TAYACCUCHO, IEP Nº 72188 QUETY, IEP Nº 72642 MALLCUAPO, IEP Nº 72749 CALASUCA DEL DISTRITO DE ITUATA - PROVINCIA DE CARABAYA - DEPARTAMENTO DE PUNO DISTRITO DE ITUATA - PROVINCIA DE CARABAYA - DEPARTAMENTO DE PUNO | D97: =Base!N85 -> 4802506 | E97: =Base!O85 -> 4385171.6 | F97: =D97-E97 -> 417334.38 | G97: =Base!Q85 -> 3250907.8 | H97: =D97-G97 -> 1551598.2 | I97: =IF(D97=0,0,G97/D97) -> 0.67691905 | J97: =Base!AH85 -> Administración directa / Contrata / Equipamiento / Personal/bienes/servicios | K97: =Base!I85 -> Proyecto de inversión | L97: =Base!AA85 -> 3770000 | M97: =Base!AB85 -> 876556 | N97: =Base!AC85 -> 4649244 | O97: =Base!AD85 -> 7795363 | P97: =IF(Base!AI85="","",Base!AI85) | Q97: =Base!J85 -> Sin saldo útil | R97: =Base!X85 -> 0.43585894 | S97: =Base!K85 -> 0 | T97: =Base!M85 -> Saldo libre menor a S/ 10,000
A98: =SUBTOTAL(103,$B$6:B98) -> 82 | B98: 311 | C98: 2417765: MEJORAMIENTO Y AMPLIACION DEL SERVICIOS DE EDUCACION BASICA EN EL NIVEL PRIMARIO DE LA IEP Nº 72169 TAMBILLO, IEP Nº 72175 TAYACCUCHO, IEP Nº 72188 QUETY, IEP Nº 72642 MALLCUAPO, IEP Nº 72749 CALASUCA DEL DISTRITO DE ITUATA - PROVINCIA DE CARABAYA - DEPARTAMENTO DE PUNO DISTRITO DE ITUATA - PROVINCIA DE CARABAYA - DEPARTAMENTO DE PUNO | D98: =Base!N86 -> 4992699 | E98: =Base!O86 -> 4292921.5 | F98: =D98-E98 -> 699777.49 | G98: =Base!Q86 -> 3252598.6 | H98: =D98-G98 -> 1740100.4 | I98: =IF(D98=0,0,G98/D98) -> 0.651471 | J98: =Base!AH86 -> Administración directa / Contrata / Equipamiento / Personal/bienes/servicios | K98: =Base!I86 -> Proyecto de inversión | L98: =Base!AA86 -> 3770000 | M98: =Base!AB86 -> 876556 | N98: =Base!AC86 -> 4649244 | O98: =Base!AD86 -> 7795363 | P98: =IF(Base!AI86="","",Base!AI86) | Q98: =Base!J86 -> Sin saldo útil | R98: =Base!X86 -> 0.43585894 | S98: =Base!K86 -> 0 | T98: =Base!M86 -> Saldo libre menor a S/ 10,000
... A106: =SUBTOTAL(103,$B$6:B106) -> 90 | B106: 83 | C106: 2627406: RENOVACION DE AMBIENTE COMPLEMENTARIO, AULA DE EDUCACION SUPERIOR PEDAGOGICA Y CERCO PERIMETRICO; ADQUISICION DE MOBILIARIO DE AULA DE EDUCACION SUPERIOR PEDAGOGICA; ADEMÁS DE OTROS ACTIVOS EN EL(LA) INSTITUTO DE EDUCACION SUPERIOR PEDAGOGICA PUBLICO JULI DEL DISTRITO DE JULI, PROVINCIA CHUCUITO, DEPARTAMENTO PUNO | D106: =Base!N94 -> 61203 | E106: =Base!O94 -> 0 | F106: =D106-E106 -> 61203 | G106: =Base!Q94 -> 0 | H106: =D106-G106 -> 61203 | I106: =IF(D106=0,0,G106/D106) -> 0 | J106: =Base!AH94 -> Administración directa | K106: =Base!I94 -> IOARR | L106: =Base!AA94 -> 61203 | M106: =Base!AB94 -> 0 | N106: =Base!AC94 -> 0 | O106: =Base!AD94 -> 0 | P106: =IF(Base!AI94="","",Base!AI94) | Q106: =Base!J94 -> No mover | R106: =Base!X94 -> 0.96612365 | S106: =Base!K94 -> 0 | T106: =Base!M94 -> Avance financiero acumulado 97% (> 90%)
A107: 15. TRANSPORTE | D107: =SUM(D108:D117) -> 67673088 | E107: =SUM(E108:E117) -> 61870191 | F107: =D107-E107 -> 5802897.4 | G107: =SUM(G108:G117) -> 41195299 | H107: =D107-G107 -> 26477789 | I107: =IF(D107=0,0,G107/D107) -> 0.60873975 | S107: =SUM(S108:S117) -> 0
A108: =SUBTOTAL(103,$B$6:B108) -> 91 | B108: 110 | C108: 2456529: MEJORAMIENTO DE LA CARRETERA PU 147, EMP. PE-34I JIPATA - EMP. PE-34I MOHO, DISTRITO DE MOHO - PROVINCIA DE MOHO - DEPARTAMENTO DE PUNO | D108: =Base!N95 -> 23143575 | E108: =Base!O95 -> 22339570 | F108: =D108-E108 -> 804005.16 | G108: =Base!Q95 -> 12059018 | H108: =D108-G108 -> 11084557 | I108: =IF(D108=0,0,G108/D108) -> 0.52105253 | J108: =Base!AH95 -> Administración directa / Contrata / Personal/bienes/servicios | K108: =Base!I95 -> Proyecto de inversión | L108: =Base!AA95 -> 15500800 | M108: =Base!AB95 -> 4458489 | N108: =Base!AC95 -> 450011 | O108: =Base!AD95 -> 0 | P108: =IF(Base!AI95="","",Base!AI95) | Q108: =Base!J95 -> Sin saldo útil | R108: =Base!X95 -> 0.76108078 | S108: =Base!K95 -> 0 | T108: =Base!M95 -> Saldo libre menor a S/ 10,000
A109: =SUBTOTAL(103,$B$6:B109) -> 92 | B109: 103 | C109: 2343199: MEJORAMIENTO DE LA CARRETERA (EMP 34B) AZANGARO - (EMP PU-102) JILA PURINA DE LOS DISTRITO DE AZÁNGARO - DISTRITO DE TIRAPATA - PROVINCIA DE AZANGARO - REGIÓN PUNO | D109: =Base!N96 -> 14991498 | E109: =Base!O96 -> 14786013 | F109: =D109-E109 -> 205485.03 | G109: =Base!Q96 -> 11502167 | H109: =D109-G109 -> 3489331.3 | I109: =IF(D109=0,0,G109/D109) -> 0.76724599 | J109: =Base!AH96 -> Administración directa / Contrata / Personal/bienes/servicios | K109: =Base!I96 -> Proyecto de inversión | L109: =Base!AA96 -> 12491498 | M109: =Base!AB96 -> 632388 | N109: =Base!AC96 -> 41870 | O109: =Base!AD96 -> 0 | P109: =IF(Base!AI96="","",Base!AI96) | Q109: =Base!J96 -> No mover | R109: =Base!X96 -> 0.92713139 | S109: =Base!K96 -> 0 | T109: =Base!M96 -> Avance financiero acumulado 93% (> 90%)
A110: =SUBTOTAL(103,$B$6:B110) -> 93 | B110: 106 | C110: 2399543: MEJORAMIENTO DEL CAMINO VECINAL EMP. R01 (DV. LOANI) - CAMICACHI - EMP. R12 (ROSACANI) DISTRITO DE ILAVE - PROVINCIA DE EL COLLAO - REGION PUNO | D110: =Base!N97 -> 5270087 | E110: =Base!O97 -> 5222084.3 | F110: =D110-E110 -> 48002.71 | G110: =Base!Q97 -> 5220159.3 | H110: =D110-G110 -> 49927.71 | I110: =IF(D110=0,0,G110/D110) -> 0.99052621 | J110: =Base!AH97 -> Administración directa / Contrata / Personal/bienes/servicios | K110: =Base!I97 -> Proyecto de inversión | L110: =Base!AA97 -> No registrado en cartera | M110: =Base!AB97 -> No registrado en cartera | N110: =Base!AC97 -> No registrado en cartera | O110: =Base!AD97 -> No registrado en cartera | P110: =IF(Base!AI97="","",Base!AI97) | Q110: =Base!J97 -> No mover | R110: =Base!X97 -> 0.86114116 | S110: =Base!K97 -> 0 | T110: =Base!M97 -> Devengado 2026 ≥ 90% del PIM
A111: =SUBTOTAL(103,$B$6:B111) -> 94 | B111: 119 | C111: 2591951: MEJORAMIENTO DEL SERVICIO DE TRANSITABILIDAD VIAL INTERURBANA EN EL CAMINO VECINAL DEL KM0+000 (DESVIO PUENTE OCRA CHUPA) AL KM 6+373 (C.P. PEDRO VILCAPAZA DE MORORCCO), DISTRITO DE MUÑANI DE LA PROVINCIA DE AZANGARO DEL DEPARTAMENTO DE PUNO | D111: =Base!N98 -> 6770858 | E111: =Base!O98 -> 6117514.3 | F111: =D111-E111 -> 653343.71 | G111: =Base!Q98 -> 3961148.7 | H111: =D111-G111 -> 2809709.3 | I111: =IF(D111=0,0,G111/D111) -> 0.58502906 | J111: =Base!AH98 -> Administración directa / Contrata / Personal/bienes/servicios / Equipamiento | K111: =Base!I98 -> Proyecto de inversión | L111: =Base!AA98 -> No registrado en cartera | M111: =Base!AB98 -> No registrado en cartera | N111: =Base!AC98 -> No registrado en cartera | O111: =Base!AD98 -> No registrado en cartera | P111: =IF(Base!AI98="","",Base!AI98) | Q111: =Base!J98 -> Sin saldo útil | R111: =Base!X98 -> 0.5953725 | S111: =Base!K98 -> 0 | T111: =Base!M98 -> Saldo libre menor a S/ 10,000
A112: =SUBTOTAL(103,$B$6:B112) -> 95 | B112: 121 | C112: 2602163: MEJORAMIENTO DEL SERVICIO DE TRANSITABILIDAD VIAL INTERURBANA EN LA CARRETERA PU 866 (EMP PE 34 I) - EMP PU 110 (SULLCA), PU 870 (DV TOTORANI: EMP PU 866) - EMP PU 872 (OCCOPAMPA) , PU 872: EMP. PU ¿ 866 (HUAYRAPATA) ¿ OCCOPAMPA ¿ EMP. PU ¿ 870 DISTRITOS DE MOHO, HUAYRAPATA DE LA PROVINCIA DE MOHO DEL DEPARTAMENTO DE PUNO | D112: =Base!N99 -> 2308286 | E112: =Base!O99 -> 0 | F112: =D112-E112 -> 2308286 | G112: =Base!Q99 -> 0 | H112: =D112-G112 -> 2308286 | I112: =IF(D112=0,0,G112/D112) -> 0 | J112: =Base!AH99 -> Administración directa / Contrata | K112: =Base!I99 -> Proyecto de inversión | L112: =Base!AA99 -> 800000 | M112: =Base!AB99 -> 10345657 | N112: =Base!AC99 -> 0 | O112: =Base!AD99 -> 10973904 | P112: =IF(Base!AI99="","",Base!AI99) | Q112: =Base!J99 -> Sin saldo útil | R112: =Base!X99 -> 0.01537244 | S112: =Base!K99 -> 0 | T112: =Base!M99 -> Saldo libre menor a S/ 10,000
A113: =SUBTOTAL(103,$B$6:B113) -> 96 | B113: 463 | C113: 2511009: MEJORAMIENTO DEL SERVICIO VIAL URBANO DE LA AVENIDA INDUSTRIAL DEL CENTRO POBLADO DE SALCEDO, DISTRITO DE PUNO - PROVINCIA DE PUNO - DEPARTAMENTO DE PUNO | D113: =Base!N100 -> 1827737 | E113: =Base!O100 -> 1038426 | F113: =D113-E113 -> 789311.02 | G113: =Base!Q100 -> 13810.34 | H113: =D113-G113 -> 1813926.7 | I113: =IF(D113=0,0,G113/D113) -> 0.0075559777 | J113: =Base!AH100 -> Administración directa / Contrata | K113: =Base!I100 -> Proyecto de inversión | L113: =Base!AA100 -> No registrado en cartera | M113: =Base!AB100 -> No registrado en cartera | N113: =Base!AC100 -> No registrado en cartera | O113: =Base!AD100 -> No registrado en cartera | P113: =IF(Base!AI100="","",Base!AI100) | Q113: =Base!J100 -> Sin saldo útil | R113: =Base!X100 -> 0.0058794658 | S113: =Base!K100 -> 0 | T113: =Base!M100 -> Saldo libre menor a S/ 10,000
A114: =SUBTOTAL(103,$B$6:B114) -> 97 | B114: 128 | C114: 2634040: MEJORAMIENTO DEL SERVICIO DE TRANSITABILIDAD VIAL INTERURBANA EN EL CAMINO VECINAL, TRAMO DESVIO PUCARA - POBLACION SALINAS - ASILLO SALINAS (KM 0+000 - 1+900) DEL DISTRITO DE SAN JUAN DE SALINAS DE LA PROVINCIA DE AZANGARO DEL DEPARTAMENTO DE PUNO | D114: =Base!N101 -> 4106961 | E114: =Base!O101 -> 3413280.5 | F114: =D114-E114 -> 693680.47 | G114: =Base!Q101 -> 1831598.5 | H114: =D114-G114 -> 2275362.5 | I114: =IF(D114=0,0,G114/D114) -> 0.44597417 | J114: =Base!AH101 -> Administración directa / Contrata / Personal/bienes/servicios | K114: =Base!I101 -> Proyecto de inversión | L114: =Base!AA101 -> No registrado en cartera | M114: =Base!AB101 -> No registrado en cartera | N114: =Base!AC101 -> No registrado en cartera | O114: =Base!AD101 -> No registrado en cartera | P114: =IF(Base!AI101="","",Base!AI101) | Q114: =Base!J101 -> Sin saldo útil | R114: =Base!X101 -> 0.55031875 | S114: =Base!K101 -> 0 | T114: =Base!M101 -> Saldo libre menor a S/ 10,000
A115: =SUBTOTAL(103,$B$6:B115) -> 98 | B115: 105 | C115: 2387422: MEJORAMIENTO DE LA CARRETERA TRAMO II (PUENTE CULLCO) - PICHINCUTA - QUELCAHUECO - CORARACA DEL - DISTRITO DE ILAVE - PROVINCIA DE EL COLLAO - DEPARTAMENTO DE PUNO | D115: =Base!N102 -> 7751873 | E115: =Base!O102 -> 7581999.4 | F115: =D115-E115 -> 169873.63 | G115: =Base!Q102 -> 5292812.8 | H115: =D115-G115 -> 2459060.2 | I115: =IF(D115=0,0,G115/D115) -> 0.68277857 | J115: =Base!AH102 -> Administración directa / Contrata / Personal/bienes/servicios / Equipamiento | K115: =Base!I102 -> Proyecto de inversión | L115: =Base!AA102 -> No registrado en cartera | M115: =Base!AB102 -> No registrado en cartera | N115: =Base!AC102 -> No registrado en cartera | O115: =Base!AD102 -> No registrado en cartera | P115: =IF(Base!AI102="","",Base!AI102) | Q115: =Base!J102 -> Sin saldo útil | R115: =Base!X102 -> 0.82418887 | S115: =Base!K102 -> 0 | T115: =Base!M102 -> Saldo libre menor a S/ 10,000
A116: =SUBTOTAL(103,$B$6:B116) -> 99 | B116: 114 | C116: 2527184: MEJORAMIENTO DEL SERVICIO DE TRANSITABILIDAD VIAL DEL CAMINO VECINAL TRAMO VILLA PAXA A VENTILLA (PU- 1065) DEL DISTRITO DE PUNO - PROVINCIA DE PUNO - DEPARTAMENTO DE PUNO | D116: =Base!N103 -> 936343 | E116: =Base!O103 -> 868354.77 | F116: =D116-E116 -> 67988.23 | G116: =Base!Q103 -> 868354.72 | H116: =D116-G116 -> 67988.28 | I116: =IF(D116=0,0,G116/D116) -> 0.92738956 | J116: =Base!AH103 -> Administración directa / Contrata / Personal/bienes/servicios | K116: =Base!I103 -> Proyecto de inversión | L116: =Base!AA103 -> No registrado en cartera | M116: =Base!AB103 -> No registrado en cartera | N116: =Base!AC103 -> No registrado en cartera | O116: =Base!AD103 -> No registrado en cartera | P116: =IF(Base!AI103="","",Base!AI103) | Q116: =Base!J103 -> No mover | R116: =Base!X103 -> 0.99515548 | S116: =Base!K103 -> 0 | T116: =Base!M103 -> Devengado 2026 ≥ 90% del PIM
A117: =SUBTOTAL(103,$B$6:B117) -> 100 | B117: 167 | C117: 2519621: CREACION DEL SERVICIO DE TRANSITABILIDAD VEHICULAR Y PEATONAL EN EL JR. 7 DE JUNIO Y JR. BOLOGNESI CUADRA 10 DE LA LOCALIDAD DE YUNGUYO DEL DISTRITO DE YUNGUYO - PROVINCIA DE YUNGUYO - DEPARTAMENTO DE PUNO | D117: =Base!N104 -> 565870 | E117: =Base!O104 -> 502948.57 | F117: =D117-E117 -> 62921.43 | G117: =Base!Q104 -> 446229.16 | H117: =D117-G117 -> 119640.84 | I117: =IF(D117=0,0,G117/D117) -> 0.78857186 | J117: =Base!AH104 -> Administración directa / Contrata / Personal/bienes/servicios | K117: =Base!I104 -> Proyecto de inversión | L117: =Base!AA104 -> No registrado en cartera | M117: =Base!AB104 -> No registrado en cartera | N117: =Base!AC104 -> No registrado en cartera | O117: =Base!AD104 -> No registrado en cartera | P117: =IF(Base!AI104="","",Base!AI104) | Q117: =Base!J104 -> No mover | R117: =Base!X104 -> 0.9453248 | S117: =Base!K104 -> 0 | T117: =Base!M104 -> Avance financiero acumulado 95% (> 90%)
A118: 21. CULTURA Y DEPORTE | D118: =SUM(D119:D121) -> 6449080 | E118: =SUM(E119:E121) -> 6391544.6 | F118: =D118-E118 -> 57535.36 | G118: =SUM(G119:G121) -> 208464.85 | H118: =D118-G118 -> 6240615.2 | I118: =IF(D118=0,0,G118/D118) -> 0.032324742 | S118: =SUM(S119:S121) -> 12925
A119: =SUBTOTAL(103,$B$6:B119) -> 101 | B119: 69 | C119: 2645446: REPARACION DE TRIBUNA Y/O PALCO Y PISTA DE ATLETISMO (DEPORTE RECREATIVO); CONSTRUCCION DE CAMPO DEPORTIVO; EN EL(LA) ESTADIO DE LA GRAN UNIDAD SAN CARLOS DISTRITO DE PUNO, PROVINCIA PUNO, DEPARTAMENTO PUNO | D119: =Base!N105 -> 1075076 | E119: =Base!O105 -> 1062250 | F119: =D119-E119 -> 12826 | G119: =Base!Q105 -> 20822.47 | H119: =D119-G119 -> 1054253.5 | I119: =IF(D119=0,0,G119/D119) -> 0.01936837 | J119: =Base!AH105 -> Contrata / Expediente técnico | K119: =Base!I105 -> IOARR | L119: =Base!AA105 -> 1062638 | M119: =Base!AB105 -> 245874 | N119: =Base!AC105 -> 0 | O119: =Base!AD105 -> 0 | P119: =IF(Base!AI105="","",Base!AI105) | Q119: =Base!J105 -> Con condiciones | R119: =Base!X105 -> 0.033351064 | S119: =Base!K105 -> 12826 | T119: =Base!M105 -> Está programado en el PMI 2026 · Tiene monto en el PMI 2027 (S/ 245,874)
A120: =SUBTOTAL(103,$B$6:B120) -> 102 | B120: 73 | C120: 2646109: REPARACION DE TRIBUNA Y/O PALCO; CONSTRUCCION DE CAMPO DEPORTIVO Y TRIBUNA Y/O PALCO; EN EL(LA) ESTADIO MUNICIPAL DE JULI DISTRITO DE JULI, PROVINCIA CHUCUITO, DEPARTAMENTO PUNO | D120: =Base!N106 -> 4474004 | E120: =Base!O106 -> 4473905 | F120: =D120-E120 -> 99 | G120: =Base!Q106 -> 0 | H120: =D120-G120 -> 4474004 | I120: =IF(D120=0,0,G120/D120) -> 0 | J120: =Base!AH106 -> Contrata / Expediente técnico | K120: =Base!I106 -> IOARR | L120: =Base!AA106 -> 1556258 | M120: =Base!AB106 -> 2054256 | N120: =Base!AC106 -> 0 | O120: =Base!AD106 -> 994904 | P120: =IF(Base!AI106="","",Base!AI106) | Q120: =Base!J106 -> Rebajando certificación | R120: =Base!X106 -> 0.014878273 | S120: =Base!K106 -> 99 | T120: =Base!M106 -> Sin saldo libre; hay S/ 4,438,806 certificados sin comprometer ni programar en el 12-B (requiere rebajar la certificación)
A121: =SUBTOTAL(103,$B$6:B121) -> 103 | B121: 504 | C121: 2630072: CREACION DEL SERVICIO DE PRACTICA DEPORTIVA Y/O RECREATIVA EN COLISEO CERRADO DE AYAPATA DISTRITO DE AYAPATA DE LA PROVINCIA DE CARABAYA DEL DEPARTAMENTO DE PUNO | D121: =Base!N107 -> 900000 | E121: =Base!O107 -> 855389.64 | F121: =D121-E121 -> 44610.36 | G121: =Base!Q107 -> 187642.38 | H121: =D121-G121 -> 712357.62 | I121: =IF(D121=0,0,G121/D121) -> 0.20849153 | J121: =Base!AH107 -> Administración directa / Contrata / Personal/bienes/servicios / Equipamiento | K121: =Base!I107 -> Proyecto de inversión | L121: =Base!AA107 -> No registrado en cartera | M121: =Base!AB107 -> No registrado en cartera | N121: =Base!AC107 -> No registrado en cartera | O121: =Base!AD107 -> No registrado en cartera | P121: =IF(Base!AI107="","",Base!AI107) | Q121: =Base!J107 -> Sin saldo útil | R121: =Base!X107 -> 0.054533241 | S121: =Base!K107 -> 0 | T121: =Base!M107 -> Saldo libre menor a S/ 10,000
A122: EJECUCIÓN POR ADMINISTRACIÓN INDIRECTA (CONTRATA) | D122: =D123+D133+D144+D146+D149 -> 199274718 | E122: =E123+E133+E144+E146+E149 -> 1.9189904e+08 | F122: =D122-E122 -> 7375673.5 | G122: =G123+G133+G144+G146+G149 -> 1.0445987e+08 | H122: =D122-G122 -> 94814843 | I122: =IF(D122=0,0,G122/D122) -> 0.52420034 | S122: =S123+S133+S144+S146+S149 -> 278341.77
A123: 22. EDUCACION | D123: =SUM(D124:D132) -> 31210021 | E123: =SUM(E124:E132) -> 28924498 | F123: =D123-E123 -> 2285522.9 | G123: =SUM(G124:G132) -> 14467550 | H123: =D123-G123 -> 16742471 | I123: =IF(D123=0,0,G123/D123) -> 0.46355465 | S123: =SUM(S124:S132) -> 5679.97
A124: =SUBTOTAL(103,$B$6:B124) -> 104 | B124: 34 | C124: 2393398: MEJORAMIENTO DEL SERVICIO EDUCATIVO DE NIVEL SECUNDARIO EN LA I.E. A - 28 PERÚ BIRF CENTRO POBLADO DE AZANGARO - DISTRITO DE AZANGARO - PROVINCIA DE AZANGARO - REGIÓN PUNO | D124: =Base!N108 -> 8692228 | E124: =Base!O108 -> 8634477.4 | F124: =D124-E124 -> 57750.64 | G124: =Base!Q108 -> 4987667.5 | H124: =D124-G124 -> 3704560.5 | I124: =IF(D124=0,0,G124/D124) -> 0.57380772 | J124: =Base!AH108 -> Contrata / Personal/bienes/servicios / Equipamiento | K124: =Base!I108 -> Proyecto de inversión | L124: =Base!AA108 -> 12431185 | M124: =Base!AB108 -> 4843790 | N124: =Base!AC108 -> 2910115 | O124: =Base!AD108 -> 0 | P124: =IF(Base!AI108="","",Base!AI108) | Q124: =Base!J108 -> Sin saldo útil | R124: =Base!X108 -> 0.22546483 | S124: =Base!K108 -> 0 | T124: =Base!M108 -> Saldo libre menor a S/ 10,000
A125: =SUBTOTAL(103,$B$6:B125) -> 105 | B125: 460 | C125: 2500458: MEJORAMIENTO DEL SERVICIO EDUCATIVO EN LA IEP N° 70477 SAGRADO CORAZON DE JESUS DEL DISTRITO DE AYAVIRI - PROVINCIA DE MELGAR - DEPARTAMENTO DE PUNO | D125: =Base!N109 -> 4437995 | E125: =Base!O109 -> 3605496.9 | F125: =D125-E125 -> 832498.14 | G125: =Base!Q109 -> 2493396.7 | H125: =D125-G125 -> 1944598.3 | I125: =IF(D125=0,0,G125/D125) -> 0.56182954 | J125: =Base!AH109 -> Administración directa / Contrata / Equipamiento / Personal/bienes/servicios | K125: =Base!I109 -> Proyecto de inversión | L125: =Base!AA109 -> No registrado en cartera | M125: =Base!AB109 -> No registrado en cartera | N125: =Base!AC109 -> No registrado en cartera | O125: =Base!AD109 -> No registrado en cartera | P125: =IF(Base!AI109="","",Base!AI109) | Q125: =Base!J109 -> Sin saldo útil | R125: =Base!X109 -> 0.57195549 | S125: =Base!K109 -> 0 | T125: =Base!M109 -> Saldo libre menor a S/ 10,000
A126: =SUBTOTAL(103,$B$6:B126) -> 106 | B126: 455 | C126: 2453224: MEJORAMIENTO DE LOS SERVICIOS DE EDUCACION SECUNDARIA DE LA INSTITUCION EDUCATIVA LIBERTADOR JOSE DE SAN MARTIN DE HUARISANI DEL DISTRITO DE HUANCANE - PROVINCIA DE HUANCANE - DEPARTAMENTO DE PUNO | D126: =Base!N110 -> 4265759 | E126: =Base!O110 -> 3847052.9 | F126: =D126-E126 -> 418706.06 | G126: =Base!Q110 -> 2741829.6 | H126: =D126-G126 -> 1523929.4 | I126: =IF(D126=0,0,G126/D126) -> 0.64275305 | J126: =Base!AH110 -> Administración directa / Contrata / Equipamiento / Personal/bienes/servicios | K126: =Base!I110 -> Proyecto de inversión | L126: =Base!AA110 -> No registrado en cartera | M126: =Base!AB110 -> No registrado en cartera | N126: =Base!AC110 -> No registrado en cartera | O126: =Base!AD110 -> No registrado en cartera | P126: =IF(Base!AI110="","",Base!AI110) | Q126: =Base!J110 -> Sin saldo útil | R126: =Base!X110 -> 0.5950397 | S126: =Base!K110 -> 0 | T126: =Base!M110 -> Saldo libre menor a S/ 10,000
A127: =SUBTOTAL(103,$B$6:B127) -> 107 | B127: 172 | C127: 2250382: INSTALACION DE LOS SERVICIOS DE EDUCACION INICIAL EN LA I.E.I. CHIA, DEL C.P. DE CHIA, DEL DISTRITO DE OLLACHEA - PROVINCIA CARABAYA - REGION PUNO | D127: =Base!N111 -> 2342684 | E127: =Base!O111 -> 2160743.3 | F127: =D127-E127 -> 181940.67 | G127: =Base!Q111 -> 1123789.4 | H127: =D127-G127 -> 1218894.6 | I127: =IF(D127=0,0,G127/D127) -> 0.47970164 | J127: =Base!AH111 -> Administración directa / Contrata / Personal/bienes/servicios | K127: =Base!I111 -> Proyecto de inversión | L127: =Base!AA111 -> 800000 | M127: =Base!AB111 -> 26969 | N127: =Base!AC111 -> 0 | O127: =Base!AD111 -> 0 | P127: =IF(Base!AI111="","",Base!AI111) | Q127: =Base!J111 -> Sin saldo útil | R127: =Base!X111 -> 0.46033295 | S127: =Base!K111 -> 0 | T127: =Base!M111 -> Saldo libre menor a S/ 10,000
A128: =SUBTOTAL(103,$B$6:B128) -> 108 | B128: 28 | C128: 2344253: MEJORAMIENTO DEL SERVICIO EDUCATIVO EN LA I.E.S. JOSÉ ANTONIO ENCINAS FRANCO, CENTRO POBLADO DE LECHEMAYO DEL DISTRITO DE SAN GABAN - PROVINCIA DE CARABAYA - DEPARTAMENTO DE PUNO | D128: =Base!N112 -> 4026127 | E128: =Base!O112 -> 3941445.9 | F128: =D128-E128 -> 84681.06 | G128: =Base!Q112 -> 1387806.2 | H128: =D128-G128 -> 2638320.8 | I128: =IF(D128=0,0,G128/D128) -> 0.34470007 | J128: =Base!AH112 -> Contrata / Personal/bienes/servicios | K128: =Base!I112 -> Proyecto de inversión | L128: =Base!AA112 -> 2120577 | M128: =Base!AB112 -> 5094106 | N128: =Base!AC112 -> 4994536 | O128: =Base!AD112 -> 0 | P128: =IF(Base!AI112="","",Base!AI112) | Q128: =Base!J112 -> Sin saldo útil | R128: =Base!X112 -> 0.14634992 | S128: =Base!K112 -> 0 | T128: =Base!M112 -> Saldo libre menor a S/ 10,000
A129: =SUBTOTAL(103,$B$6:B129) -> 109 | B129: 32 | C129: 2385051: MEJORAMIENTO DEL SERVICIO EDUCATIVO EN LA I.E.S. SAN JUAN BOSCO DE SALCEDO CON JORNADA ESCOLAR COMPLETA DISTRITO DE PUNO - PROVINCIA DE PUNO - REGIÓN PUNO | D129: =Base!N113 -> 4927527 | E129: =Base!O113 -> 4223260.7 | F129: =D129-E129 -> 704266.31 | G129: =Base!Q113 -> 1725644.1 | H129: =D129-G129 -> 3201882.9 | I129: =IF(D129=0,0,G129/D129) -> 0.35020491 | J129: =Base!AH113 -> Administración directa / Contrata / Equipamiento / Personal/bienes/servicios | K129: =Base!I113 -> Proyecto de inversión | L129: =Base!AA113 -> 2000000 | M129: =Base!AB113 -> 8000000 | N129: =Base!AC113 -> 9133500 | O129: =Base!AD113 -> 8629252 | P129: =IF(Base!AI113="","",Base!AI113) | Q129: =Base!J113 -> Sin saldo útil | R129: =Base!X113 -> 0.069695982 | S129: =Base!K113 -> 0 | T129: =Base!M113 -> Saldo libre menor a S/ 10,000
A130: =SUBTOTAL(103,$B$6:B130) -> 110 | B130: 156 | C130: 2566572: MEJORAMIENTO Y AMPLIACION DE LOS SERVICIOS DE EDUCACIÓN SUPERIOR DEL INSTITUTO SUPERIOR TECNOLÓGICO PUBLICO DE NUÑOA DEL DISTRITO DE NUÑOA - PROVINCIA DE MELGAR - DEPARTAMENTO DE PUNO | D130: =Base!N114 -> 1479604 | E130: =Base!O114 -> 1473924 | F130: =D130-E130 -> 5679.97 | G130: =Base!Q114 -> 7416.86 | H130: =D130-G130 -> 1472187.1 | I130: =IF(D130=0,0,G130/D130) -> 0.0050127331 | J130: =Base!AH114 -> Contrata / Expediente técnico | K130: =Base!I114 -> Proyecto de inversión | L130: =Base!AA114 -> 3000000 | M130: =Base!AB114 -> 6984785 | N130: =Base!AC114 -> 0 | O130: =Base!AD114 -> 6681576 | P130: =IF(Base!AI114="","",Base!AI114) | Q130: =Base!J114 -> Rebajando certificación | R130: =Base!X114 -> 0.035062894 | S130: =Base!K114 -> 5679.97 | T130: =Base!M114 -> Sin saldo libre; hay S/ 1,335,804 certificados sin comprometer ni programar en el 12-B (requiere rebajar la certificación)
A131: =SUBTOTAL(103,$B$6:B131) -> 111 | B131: 506 | C131: 2501244: MEJORAMIENTO DEL SERVICIO EDUCATIVO DEL NIVEL SECUNDARIA DE LA I.E. AGROPECUARIO PAMPA YANAMAYO DEL DISTRITO DE ALTO INAMBARI - PROVINCIA DE SANDIA - DEPARTAMENTO DE PUNO | D131: =Base!N115 -> 1038097 | E131: =Base!O115 -> 1038097 | F131: =D131-E131 -> 0 | G131: =Base!Q115 -> 0 | H131: =D131-G131 -> 1038097 | I131: =IF(D131=0,0,G131/D131) -> 0 | J131: =Base!AH115 -> Contrata | K131: =Base!I115 -> Proyecto de inversión | L131: =Base!AA115 -> No registrado en cartera | M131: =Base!AB115 -> No registrado en cartera | N131: =Base!AC115 -> No registrado en cartera | O131: =Base!AD115 -> No registrado en cartera | P131: =IF(Base!AI115="","",Base!AI115) | Q131: =Base!J115 -> Rebajando certificación | R131: =Base!X115 -> 0.016293212 | S131: =Base!K115 -> 0 | T131: =Base!M115 -> Sin saldo libre; hay S/ 970,838 certificados sin comprometer ni programar en el 12-B (requiere rebajar la certificación)
A132: =SUBTOTAL(103,$B$6:B132) -> 112 | B132: 23 | C132: 2194501: INSTALACION DEL SERVICIO EDUCATIVO DE LA INSTITUCION EDUCATIVA SECUNDARIA SANTA MONICA EN EL DISTRITO DE JULIACA, PROVINCIA DE SAN ROMAN - PUNO. | D132: =Base!N116 -> 0 | E132: =Base!O116 -> 0 | F132: =D132-E132 -> 0 | G132: =Base!Q116 -> 0 | H132: =D132-G132 -> 0 | I132: =IF(D132=0,0,G132/D132) -> 0 | J132: =Base!AH116 -> Personal/bienes/servicios | K132: =Base!I116 -> Proyecto de inversión | L132: =Base!AA116 -> 144908 | M132: =Base!AB116 -> 229001 | N132: =Base!AC116 -> 0 | O132: =Base!AD116 -> 0 | P132: =IF(Base!AI116="","",Base!AI116) | Q132: =Base!J116 -> Sin PIM | R132: =Base!X116 -> 0.97223511 | S132: =Base!K116 -> 0 | T132: =Base!M116 -> PIM igual a 0
...

Sheet Gerencias y Oficinas
C1: ANEXO N° 02
B2: COMPORTAMIENTO DE EJECUCIÓN DE PROYECTOS DE INVERSION PUBLICA DEL AÑO FISCAL 2026 · Gerencias y Oficinas · AL 09/10/2026
A4: N° | B4: META | C4: PROYECTO | D4: PIM 2026 (A) | E4: CERTIFICACIÓN (B) | F4: SALDO (A-B) | G4: DEVENGADO ( C ) | H4: SALDO (A-C) | I4: DEVEN % | J4: MODALIDAD DE EJECUCIÓN | K4: TIPO DE INVERSIÓN | L4: Monto Año 2026 (S/) | M4: Monto Año 2027 (S/) | N4: Monto Año 2028 (S/) | O4: Monto Año 2029 (S/) | P4: BASE LEGAL | Q4: SEMÁFORO | R4: % AVANCE FINANCIERO ACUMULADO | S4: DISPONIBLE LEGAL (S/) | T4: MOTIVO / CONDICIONES
A5: GERENCIA REGIONAL DE DESARROLLO ECONOMICO | D5: =D6+D11+D14+D17+D82+D87 -> 15438088 | E5: =E6+E11+E14+E17+E82+E87 -> 13331382 | F5: =D5-E5 -> 2106706.1 | G5: =G6+G11+G14+G17+G82+G87 -> 6947756.8 | H5: =D5-G5 -> 8490331.2 | I5: =IF(D5=0,0,G5/D5) -> 0.45003998 | S5: =S6+S11+S14+S17+S82+S87 -> 1360506.2
A6: 09. TURISMO | D6: =SUM(D7:D10) -> 3137774 | E6: =SUM(E7:E10) -> 2421934 | F6: =D6-E6 -> 715839.98 | G6: =SUM(G7:G10) -> 1602346.4 | H6: =D6-G6 -> 1535427.6 | I6: =IF(D6=0,0,G6/D6) -> 0.51066342 | S6: =SUM(S7:S10) -> 36558.5
A7: =SUBTOTAL(103,$B$6:B7) -> 1 | B7: 20 | C7: 2526527: MEJORAMIENTO DE LAS CAPACIDADES PARA LA PRODUCTIVIDAD Y LA COMPETITIVIDAD DE ARTESANÍAS EN 13 PROVINCIAS DEL DEPARTAMENTO DE PUNO | D7: =Base!N287 -> 2659376 | E7: =Base!O287 -> 1980094.5 | F7: =D7-E7 -> 679281.48 | G7: =Base!Q287 -> 1386716.9 | H7: =D7-G7 -> 1272659.1 | I7: =IF(D7=0,0,G7/D7) -> 0.52144446 | J7: =Base!AH287 -> Contrata / Personal/bienes/servicios / Equipamiento | K7: =Base!I287 -> Proyecto de inversión | L7: =Base!AA287 -> 3659376 | M7: =Base!AB287 -> 55933 | N7: =Base!AC287 -> 0 | O7: =Base!AD287 -> 1953448 | P7: =IF(Base!AI287="","",Base!AI287) | Q7: =Base!J287 -> Sin saldo útil | R7: =Base!X287 -> 0.8234801 | S7: =Base!K287 -> 0 | T7: =Base!M287 -> Saldo libre menor a S/ 10,000
A8: =SUBTOTAL(103,$B$6:B8) -> 2 | B8: 383 | C8: 2717147: MEJORAMIENTO DE LOS SERVICIOS TURISTICOS DE AVENTURA Y ALOJAMIENTO RURAL EN LA ASOCIACION DE TURISMO VIVENCIAL COMUNITARIO LUQUINA CHICO, DISTRITO CHUCUITO, PROVINCIA PUNO, REGION PUNO. | D8: =Base!N288 -> 159946 | E8: =Base!O288 -> 154011 | F8: =D8-E8 -> 5935 | G8: =Base!Q288 -> 60441 | H8: =D8-G8 -> 99505 | I8: =IF(D8=0,0,G8/D8) -> 0.37788379 | J8: =Base!AH288 -> Equipamiento / Contrata | K8: =Base!I288 -> PROCOMPITE | L8: =Base!AA288 -> No registrado en cartera | M8: =Base!AB288 -> No registrado en cartera | N8: =Base!AC288 -> No registrado en cartera | O8: =Base!AD288 -> No registrado en cartera | P8: =IF(Base!AI288="","",Base!AI288) | Q8: =Base!J288 -> Restringido | R8: =Base!X288 -> s/d | S8: =Base!K288 -> 5935 | T8: =Base!M288 -> PROCOMPITE
A9: =SUBTOTAL(103,$B$6:B9) -> 3 | B9: 475 | C9: 2723296: MEJORAMIENTO DE LA PRODUCCION Y COMERCIALIZACION DE ARTESANIA DE FIBRA DE ALPACA Y LANA DE OVINO EN LA ASOCIACION DE ARTESANOS EMPRENDEDORES EN TEXTILERIA SAN JUAN BAUTISTA DE NAPA ROSASPATA, DISTRITO DE ROSASPATA, PROVINCIA DE HUANCANE, REGION PU | D9: =Base!N289 -> 159560 | E9: =Base!O289 -> 141270 | F9: =D9-E9 -> 18290 | G9: =Base!Q289 -> 57830 | H9: =D9-G9 -> 101730 | I9: =IF(D9=0,0,G9/D9) -> 0.36243419 | J9: =Base!AH289 -> Equipamiento / Contrata | K9: =Base!I289 -> PROCOMPITE | L9: =Base!AA289 -> No registrado en cartera | M9: =Base!AB289 -> No registrado en cartera | N9: =Base!AC289 -> No registrado en cartera | O9: =Base!AD289 -> No registrado en cartera | P9: =IF(Base!AI289="","",Base!AI289) | Q9: =Base!J289 -> Restringido | R9: =Base!X289 -> s/d | S9: =Base!K289 -> 18290 | T9: =Base!M289 -> PROCOMPITE
A10: =SUBTOTAL(103,$B$6:B10) -> 4 | B10: 410 | C10: 2717175: MEJORAMIENTO DE LOS SERVICIOS DE ALOJAMIENTO TURISTICO Y DEL TURISMO VIVENCIAL DE OBSERVACION ASTRONOMICA EN LA ASOCIACION DE TURISMO COMUNITARIO TIKA WASI LLACHON, DISTRITO DE CAPACHICA, PROVINCIA DE PUNO Y DEPARTAMENTO DE PUNO. | D10: =Base!N290 -> 158892 | E10: =Base!O290 -> 146558.5 | F10: =D10-E10 -> 12333.5 | G10: =Base!Q290 -> 97358.5 | H10: =D10-G10 -> 61533.5 | I10: =IF(D10=0,0,G10/D10) -> 0.61273381 | J10: =Base!AH290 -> Equipamiento / Contrata | K10: =Base!I290 -> PROCOMPITE | L10: =Base!AA290 -> No registrado en cartera | M10: =Base!AB290 -> No registrado en cartera | N10: =Base!AC290 -> No registrado en cartera | O10: =Base!AD290 -> No registrado en cartera | P10: =IF(Base!AI290="","",Base!AI290) | Q10: =Base!J290 -> Restringido | R10: =Base!X290 -> s/d | S10: =Base!K290 -> 12333.5 | T10: =Base!M290 -> PROCOMPITE
A11: 03. PLANEAMIENTO, GESTION Y RESERVA DE CONTINGENCIA | D11: =SUM(D12:D13) -> 243160 | E11: =SUM(E12:E13) -> 83160 | F11: =D11-E11 -> 160000 | G11: =SUM(G12:G13) -> 83100.4 | H11: =D11-G11 -> 160059.6 | I11: =IF(D11=0,0,G11/D11) -> 0.34175193 | S11: =SUM(S12:S13) -> 160000
A12: =SUBTOTAL(103,$B$6:B12) -> 5 | B12: 399 | C12: 2717164: MEJORAMIENTO DE LA CAPACIDAD PRODUCTIVA Y DE COMERCIALIZACION DE MIEL MEDIANTE EL FORTALECIMIENTO DE PROCESOS PRODUCTIVOS APICOLAS EN LA ASOCIACION DE PRODUCTORES AGROPECUARIOS MONTE SILOE KOLLA MISKI DISTRITO PLATERIA, PROVINCIA DE PUNO, REGION P | D12: =Base!N291 -> 160000 | E12: =Base!O291 -> 0 | F12: =D12-E12 -> 160000 | G12: =Base!Q291 -> 0 | H12: =D12-G12 -> 160000 | I12: =IF(D12=0,0,G12/D12) -> 0 | J12: =Base!AH291 -> Equipamiento / Contrata | K12: =Base!I291 -> PROCOMPITE | L12: =Base!AA291 -> No registrado en cartera | M12: =Base!AB291 -> No registrado en cartera | N12: =Base!AC291 -> No registrado en cartera | O12: =Base!AD291 -> No registrado en cartera | P12: =IF(Base!AI291="","",Base!AI291) | Q12: =Base!J291 -> Restringido | R12: =Base!X291 -> s/d | S12: =Base!K291 -> 160000 | T12: =Base!M291 -> PROCOMPITE
A13: =SUBTOTAL(103,$B$6:B13) -> 6 | B13: 373 | C13: 2676438: MEJORAMIENTO DE LA PRODUCCION DE MIEL DE ABEJA DE LA ASOCIACION DE APICULTORES Y PRODUCTORES AGROPECUARIOS DEL VALLE YANAHUAYA, DEL DISTRITO DE YANAHUARA PROVINCIA DE SANDIA DEPARTAMENTO DE PUNO | D13: =Base!N292 -> 83160 | E13: =Base!O292 -> 83160 | F13: =D13-E13 -> 0 | G13: =Base!Q292 -> 83100.4 | H13: =D13-G13 -> 59.6 | I13: =IF(D13=0,0,G13/D13) -> 0.99928331 | J13: =Base!AH292 -> Equipamiento | K13: =Base!I292 -> PROCOMPITE | L13: =Base!AA292 -> No registrado en cartera | M13: =Base!AB292 -> No registrado en cartera | N13: =Base!AC292 -> No registrado en cartera | O13: =Base!AD292 -> No registrado en cartera | P13: =IF(Base!AI292="","",Base!AI292) | Q13: =Base!J292 -> No mover | R13: =Base!X292 -> s/d | S13: =Base!K292 -> 0 | T13: =Base!M292 -> Devengado 2026 ≥ 90% del PIM
A14: 08. COMERCIO | D14: =SUM(D15:D16) -> 1098209 | E14: =SUM(E15:E16) -> 1005406 | F14: =D14-E14 -> 92802.97 | G14: =SUM(G15:G16) -> 686901.76 | H14: =D14-G14 -> 411307.24 | I14: =IF(D14=0,0,G14/D14) -> 0.62547453 | S14: =SUM(S15:S16) -> 92802.97
A15: =SUBTOTAL(103,$B$6:B15) -> 7 | B15: 216 | C15: 2016766: INICIATIVA A LA COMPETITIVIDAD | D15: =Base!N293 -> 928209 | E15: =Base!O293 -> 910751.03 | F15: =D15-E15 -> 17457.97 | G15: =Base!Q293 -> 642892.52 | H15: =D15-G15 -> 285316.48 | I15: =IF(D15=0,0,G15/D15) -> 0.69261612 | J15: =Base!AH293 -> Estudio de preinversión | K15: =Base!I293 -> Sin dato | L15: =Base!AA293 -> No registrado en cartera | M15: =Base!AB293 -> No registrado en cartera | N15: =Base!AC293 -> No registrado en cartera | O15: =Base!AD293 -> No registrado en cartera | P15: =IF(Base!AI293="","",Base!AI293) | Q15: =Base!J293 -> Bolsa genérica | R15: =Base!X293 -> s/d | S15: =Base!K293 -> 17457.97 | T15: =Base!M293 -> Código genérico (no es una inversión con CUI propio)
A16: =SUBTOTAL(103,$B$6:B16) -> 8 | B16: 493 | C16: 2016766: INICIATIVA A LA COMPETITIVIDAD | D16: =Base!N294 -> 170000 | E16: =Base!O294 -> 94655 | F16: =D16-E16 -> 75345 | G16: =Base!Q294 -> 44009.24 | H16: =D16-G16 -> 125990.76 | I16: =IF(D16=0,0,G16/D16) -> 0.25887788 | J16: =Base!AH294 -> Estudio de preinversión | K16: =Base!I294 -> Sin dato | L16: =Base!AA294 -> No registrado en cartera | M16: =Base!AB294 -> No registrado en cartera | N16: =Base!AC294 -> No registrado en cartera | O16: =Base!AD294 -> No registrado en cartera | P16: =IF(Base!AI294="","",Base!AI294) | Q16: =Base!J294 -> Bolsa genérica | R16: =Base!X294 -> s/d | S16: =Base!K294 -> 75345 | T16: =Base!M294 -> Código genérico (no es una inversión con CUI propio)
A17: 10. AGROPECUARIA | D17: =SUM(D18:D81) -> 8596003 | E17: =SUM(E18:E81) -> 7718163.1 | F17: =D17-E17 -> 877839.85 | G17: =SUM(G18:G81) -> 4006476.2 | H17: =D17-G17 -> 4589526.8 | I17: =IF(D17=0,0,G17/D17) -> 0.46608595 | S17: =SUM(S18:S81) -> 819724.36
A18: =SUBTOTAL(103,$B$6:B18) -> 9 | B18: 418 | C18: 2717186: MEJORAMIENTO DE LA PLANTA DE TRANSFORMACION DE GRANOS ANDINOS DEL GRUPO TURISTICO GASTRONOMICO SAMKA S.A.C., DISTRITO PUNO, PROVINCIA PUNO, REGION PUNO. | D18: =Base!N295 -> 350000 | E18: =Base!O295 -> 334060 | F18: =D18-E18 -> 15940 | G18: =Base!Q295 -> 65360 | H18: =D18-G18 -> 284640 | I18: =IF(D18=0,0,G18/D18) -> 0.18674286 | J18: =Base!AH295 -> Equipamiento / Contrata | K18: =Base!I295 -> PROCOMPITE | L18: =Base!AA295 -> No registrado en cartera | M18: =Base!AB295 -> No registrado en cartera | N18: =Base!AC295 -> No registrado en cartera | O18: =Base!AD295 -> No registrado en cartera | P18: =IF(Base!AI295="","",Base!AI295) | Q18: =Base!J295 -> Restringido | R18: =Base!X295 -> s/d | S18: =Base!K295 -> 15940 | T18: =Base!M295 -> PROCOMPITE
A19: =SUBTOTAL(103,$B$6:B19) -> 10 | B19: 424 | C19: 2717193: AMPLIACION DE LA CAPACIDAD PRODUCCION DE QUESO PARIA EN GRUPO NEBRASKA S.A.C. EN DISTRITO DE JULIACA PROVINCIA DE SAN ROMAN REGION PUNO | D19: =Base!N296 -> 349950 | E19: =Base!O296 -> 287705 | F19: =D19-E19 -> 62245 | G19: =Base!Q296 -> 136062 | H19: =D19-G19 -> 213888 | I19: =IF(D19=0,0,G19/D19) -> 0.38880411 | J19: =Base!AH296 -> Equipamiento / Contrata | K19: =Base!I296 -> PROCOMPITE | L19: =Base!AA296 -> No registrado en cartera | M19: =Base!AB296 -> No registrado en cartera | N19: =Base!AC296 -> No registrado en cartera | O19: =Base!AD296 -> No registrado en cartera | P19: =IF(Base!AI296="","",Base!AI296) | Q19: =Base!J296 -> Restringido | R19: =Base!X296 -> s/d | S19: =Base!K296 -> 62245 | T19: =Base!M296 -> PROCOMPITE
A20: =SUBTOTAL(103,$B$6:B20) -> 11 | B20: 413 | C20: 2717178: MEJORAMIENTO DEL CULTIVO DE HABAS EN CORPORACION PECUARIO AGRICOLA EMMANUEL S.A.C., DISTRITO DE ZEPITA, PROVINCIA DE CHUCUITO Y DEPARTAMENTO DE PUNO | D20: =Base!N297 -> 349899 | E20: =Base!O297 -> 307070 | F20: =D20-E20 -> 42829 | G20: =Base!Q297 -> 10500 | H20: =D20-G20 -> 339399 | I20: =IF(D20=0,0,G20/D20) -> 0.03000866 | J20: =Base!AH297 -> Equipamiento / Contrata | K20: =Base!I297 -> PROCOMPITE | L20: =Base!AA297 -> No registrado en cartera | M20: =Base!AB297 -> No registrado en cartera | N20: =Base!AC297 -> No registrado en cartera | O20: =Base!AD297 -> No registrado en cartera | P20: =IF(Base!AI297="","",Base!AI297) | Q20: =Base!J297 -> Restringido | R20: =Base!X297 -> s/d | S20: =Base!K297 -> 42829 | T20: =Base!M297 -> PROCOMPITE
A21: =SUBTOTAL(103,$B$6:B21) -> 12 | B21: 394 | C21: 2717158: MEJORAMIENTO DE LA PRODUCCION DE PACAS EN LA ASOCIACION DE PRODUCTORES AGROPECUARIOS Y FORESTALES SAN PEDRO DE FRAYLIMA, DISTRITO DE AZANGARO, PROVINCIA AZANGARO Y DEPARTAMENTO DE PUNO | D21: =Base!N298 -> 349792 | E21: =Base!O298 -> 321500 | F21: =D21-E21 -> 28292 | G21: =Base!Q298 -> 0 | H21: =D21-G21 -> 349792 | I21: =IF(D21=0,0,G21/D21) -> 0 | J21: =Base!AH298 -> Equipamiento / Contrata | K21: =Base!I298 -> PROCOMPITE | L21: =Base!AA298 -> No registrado en cartera | M21: =Base!AB298 -> No registrado en cartera | N21: =Base!AC298 -> No registrado en cartera | O21: =Base!AD298 -> No registrado en cartera | P21: =IF(Base!AI298="","",Base!AI298) | Q21: =Base!J298 -> Restringido | R21: =Base!X298 -> s/d | S21: =Base!K298 -> 28292 | T21: =Base!M298 -> PROCOMPITE
A22: =SUBTOTAL(103,$B$6:B22) -> 13 | B22: 408 | C22: 2717173: MEJORAMIENTO DE LA PRODUCCION DE DERIVADOS DE QUINUA EN HARINA EXTRUIDA Y POP EXTRUIDO DE LA EMPRESA CORPORACION DALSAR SOCIEDAD ANONIMA CERRADA DEL DISTRITO DE PUNO, PROVINCIA PUNO, DEPARTAMENTO PUNO. | D22: =Base!N299 -> 349792 | E22: =Base!O299 -> 329100 | F22: =D22-E22 -> 20692 | G22: =Base!Q299 -> 0 | H22: =D22-G22 -> 349792 | I22: =IF(D22=0,0,G22/D22) -> 0 | J22: =Base!AH299 -> Equipamiento / Contrata | K22: =Base!I299 -> PROCOMPITE | L22: =Base!AA299 -> No registrado en cartera | M22: =Base!AB299 -> No registrado en cartera | N22: =Base!AC299 -> No registrado en cartera | O22: =Base!AD299 -> No registrado en cartera | P22: =IF(Base!AI299="","",Base!AI299) | Q22: =Base!J299 -> Restringido | R22: =Base!X299 -> s/d | S22: =Base!K299 -> 20692 | T22: =Base!M299 -> PROCOMPITE
A23: =SUBTOTAL(103,$B$6:B23) -> 14 | B23: 421 | C23: 2717189: MEJORAMIENTO DE LA PRODUCCION DE YOGURT EN EL AEO AGROINDUSTRIA YOGULE S.A.C., DISTRITO DE CABANA, PROVINCIA SAN ROMAN, REGION PUNO | D23: =Base!N300 -> 346711 | E23: =Base!O300 -> 318955 | F23: =D23-E23 -> 27756 | G23: =Base!Q300 -> 112190 | H23: =D23-G23 -> 234521 | I23: =IF(D23=0,0,G23/D23) -> 0.32358362 | J23: =Base!AH300 -> Equipamiento / Contrata | K23: =Base!I300 -> PROCOMPITE | L23: =Base!AA300 -> No registrado en cartera | M23: =Base!AB300 -> No registrado en cartera | N23: =Base!AC300 -> No registrado en cartera | O23: =Base!AD300 -> No registrado en cartera | P23: =IF(Base!AI300="","",Base!AI300) | Q23: =Base!J300 -> Restringido | R23: =Base!X300 -> s/d | S23: =Base!K300 -> 27756 | T23: =Base!M300 -> PROCOMPITE
A24: =SUBTOTAL(103,$B$6:B24) -> 15 | B24: 387 | C24: 2717151: MEJORAMIENTO DE LA PRODUCCION DE LECHE FRESCA EN LA ASOCIACION DE PRODUCTORES AGROPECUARIOS SUMAC KANCHAY DE LA LIBERTAD NUNOA MELGAR PUNO, DISTRITO DE NUNOA, PROVINCIA DE MELGAR Y REGION PUNO | D24: =Base!N301 -> 269980 | E24: =Base!O301 -> 259749 | F24: =D24-E24 -> 10231 | G24: =Base!Q301 -> 255066 | H24: =D24-G24 -> 14914 | I24: =IF(D24=0,0,G24/D24) -> 0.94475887 | J24: =Base!AH301 -> Equipamiento / Contrata | K24: =Base!I301 -> PROCOMPITE | L24: =Base!AA301 -> No registrado en cartera | M24: =Base!AB301 -> No registrado en cartera | N24: =Base!AC301 -> No registrado en cartera | O24: =Base!AD301 -> No registrado en cartera | P24: =IF(Base!AI301="","",Base!AI301) | Q24: =Base!J301 -> No mover | R24: =Base!X301 -> s/d | S24: =Base!K301 -> 0 | T24: =Base!M301 -> Devengado 2026 ≥ 90% del PIM
A25: =SUBTOTAL(103,$B$6:B25) -> 16 | B25: 378 | C25: 2676440: MEJORAMIENTO DE LA PRODUCCION Y LA PRODUCTIVIDAD DE QUESO TIPO PARIA PASTEURIZADO DE LA EMPRESA DE PRODUCCION AGROPECUARIA MICA ASUNCION SAC DEL, DISTRITO DE AZANGARO, PROVINCIA AZANGARO, DEPARTAMENTO PUNO. | D25: =Base!N302 -> 209400 | E25: =Base!O302 -> 176550 | F25: =D25-E25 -> 32850 | G25: =Base!Q302 -> 136550 | H25: =D25-G25 -> 72850 | I25: =IF(D25=0,0,G25/D25) -> 0.65210124 | J25: =Base!AH302 -> Equipamiento / Contrata | K25: =Base!I302 -> PROCOMPITE | L25: =Base!AA302 -> No registrado en cartera | M25: =Base!AB302 -> No registrado en cartera | N25: =Base!AC302 -> No registrado en cartera | O25: =Base!AD302 -> No registrado en cartera | P25: =IF(Base!AI302="","",Base!AI302) | Q25: =Base!J302 -> Restringido | R25: =Base!X302 -> s/d | S25: =Base!K302 -> 32850 | T25: =Base!M302 -> PROCOMPITE
A26: =SUBTOTAL(103,$B$6:B26) -> 17 | B26: 392 | C26: 2717156: MEJORAMIENTO DE LA PRODUCCION Y LA COMERCIALIZACION DE LECHE FRESCA EN LA ORGANIZACION DE PRODUCTORES SAN JUAN DE FAON DEL DISTRITO DE HUATA, PROVINCIA DE PUNO, DEPARTAMENTO DE PUNO. | D26: =Base!N303 -> 160000 | E26: =Base!O303 -> 152601 | F26: =D26-E26 -> 7399 | G26: =Base!Q303 -> 143401 | H26: =D26-G26 -> 16599 | I26: =IF(D26=0,0,G26/D26) -> 0.89625625 | J26: =Base!AH303 -> Equipamiento / Contrata | K26: =Base!I303 -> PROCOMPITE | L26: =Base!AA303 -> No registrado en cartera | M26: =Base!AB303 -> No registrado en cartera | N26: =Base!AC303 -> No registrado en cartera | O26: =Base!AD303 -> No registrado en cartera | P26: =IF(Base!AI303="","",Base!AI303) | Q26: =Base!J303 -> Restringido | R26: =Base!X303 -> s/d | S26: =Base!K303 -> 7399 | T26: =Base!M303 -> PROCOMPITE
A27: =SUBTOTAL(103,$B$6:B27) -> 18 | B27: 393 | C27: 2717157: MEJORAMIENTO DE LA PRODUCCION Y ENGORDE DE GANADO VACUNO A TRAVES DE LA OPTIMIZACION DE LA ALIMENTACION EN LA ASOCIACION DE PRODUCTORES AGROPECUARIOS EL TORITO BRAVO DEL DISTRITO DE QUILCAPUNCO, PROVINCIA DE SAN ANTONIO DE PUTINA, REGION PUNO. | D27: =Base!N304 -> 160000 | E27: =Base!O304 -> 149840 | F27: =D27-E27 -> 10160 | G27: =Base!Q304 -> 18740 | H27: =D27-G27 -> 141260 | I27: =IF(D27=0,0,G27/D27) -> 0.117125 | J27: =Base!AH304 -> Equipamiento / Contrata | K27: =Base!I304 -> PROCOMPITE | L27: =Base!AA304 -> No registrado en cartera | M27: =Base!AB304 -> No registrado en cartera | N27: =Base!AC304 -> No registrado en cartera | O27: =Base!AD304 -> No registrado en cartera | P27: =IF(Base!AI304="","",Base!AI304) | Q27: =Base!J304 -> Restringido | R27: =Base!X304 -> s/d | S27: =Base!K304 -> 10160 | T27: =Base!M304 -> PROCOMPITE
A28: =SUBTOTAL(103,$B$6:B28) -> 19 | B28: 397 | C28: 2717161: MEJORAMIENTO DE LA CAPACIDAD DE TRANSFORMACION DE CHIPS DE PAPA NATIVA, EN LA AEO ASOCIACION DE PRODUCTORES MULTIPLES SAN ISIDRO DE TANTAMACO DEL DISTRITO DE MACUSANI, PROVINCIA DE CARABAYA, REGION DE PUNO | D28: =Base!N305 -> 160000 | E28: =Base!O305 -> 148990 | F28: =D28-E28 -> 11010 | G28: =Base!Q305 -> 26000 | H28: =D28-G28 -> 134000 | I28: =IF(D28=0,0,G28/D28) -> 0.1625 | J28: =Base!AH305 -> Equipamiento / Contrata | K28: =Base!I305 -> PROCOMPITE | L28: =Base!AA305 -> No registrado en cartera | M28: =Base!AB305 -> No registrado en cartera | N28: =Base!AC305 -> No registrado en cartera | O28: =Base!AD305 -> No registrado en cartera | P28: =IF(Base!AI305="","",Base!AI305) | Q28: =Base!J305 -> Restringido | R28: =Base!X305 -> s/d | S28: =Base!K305 -> 11010 | T28: =Base!M305 -> PROCOMPITE
A29: =SUBTOTAL(103,$B$6:B29) -> 20 | B29: 404 | C29: 2717169: CREACION DE UNA PLANTA PROCESADORA DE QUINUA EN LA AEO ASOCIACION DE PRODUCTORES AGROPECUARIOS ROQUE APAZA PAMPA DEL DISTRITO DE PAUCARCOLLA, PROVINCIA DE PUNO, DEPARTAMENTO DE PUNO | D29: =Base!N306 -> 160000 | E29: =Base!O306 -> 150870 | F29: =D29-E29 -> 9130 | G29: =Base!Q306 -> 45270 | H29: =D29-G29 -> 114730 | I29: =IF(D29=0,0,G29/D29) -> 0.2829375 | J29: =Base!AH306 -> Equipamiento / Contrata | K29: =Base!I306 -> PROCOMPITE | L29: =Base!AA306 -> No registrado en cartera | M29: =Base!AB306 -> No registrado en cartera | N29: =Base!AC306 -> No registrado en cartera | O29: =Base!AD306 -> No registrado en cartera | P29: =IF(Base!AI306="","",Base!AI306) | Q29: =Base!J306 -> Restringido | R29: =Base!X306 -> s/d | S29: =Base!K306 -> 9130 | T29: =Base!M306 -> PROCOMPITE
... A81: =SUBTOTAL(103,$B$6:B81) -> 72 | B81: 526 | C81: 2681133: MEJORAMIENTO DE LA PRODUCCION DE QUESOS TIPO PARIA PASTEURIZADO DE LA CENTRAL DE ASOCIACIONES GANADEROS LECHEROS Y AGRARIOS DEL DISTRITO DE VILQUE, DISTRITO DE VILQUE, PROVINCIA DE PUNO, REGION PUNO | D81: =Base!N358 -> 2795 | E81: =Base!O358 -> 2795 | F81: =D81-E81 -> 0 | G81: =Base!Q358 -> 0 | H81: =D81-G81 -> 2795 | I81: =IF(D81=0,0,G81/D81) -> 0 | J81: =Base!AH358 -> Contrata | K81: =Base!I358 -> PROCOMPITE | L81: =Base!AA358 -> No registrado en cartera | M81: =Base!AB358 -> No registrado en cartera | N81: =Base!AC358 -> No registrado en cartera | O81: =Base!AD358 -> No registrado en cartera | P81: =IF(Base!AI358="","",Base!AI358) | Q81: =Base!J358 -> Restringido | R81: =Base!X358 -> s/d | S81: =Base!K358 -> 0 | T81: =Base!M358 -> PROCOMPITE
A82: 11. PESCA | D82: =SUM(D83:D86) -> 1054126 | E82: =SUM(E83:E86) -> 893638.67 | F82: =D82-E82 -> 160487.33 | G82: =SUM(G83:G86) -> 30322 | H82: =D82-G82 -> 1023804 | I82: =IF(D82=0,0,G82/D82) -> 0.028765062 | S82: =SUM(S83:S86) -> 160487.33
A83: =SUBTOTAL(103,$B$6:B83) -> 73 | B83: 368 | C83: 2681278: MEJORAMIENTO DEL PROCESO DE PRODUCCION DE SELECCIONADOR DE TRUCHAS EN MAQUINARIAS ACUITROUT SOCIEDAD COMERCIAL DE RESPONSABILIDAD DE LA COMUNIDAD DE KOLLPAJAHUIRA, DISTRITO DE JULI, PROVINCIA DE CHUCUITO, DEPARTAMENTO DE PUNO | D83: =Base!N359 -> 179500 | E83: =Base!O359 -> 163750 | F83: =D83-E83 -> 15750 | G83: =Base!Q359 -> 3750 | H83: =D83-G83 -> 175750 | I83: =IF(D83=0,0,G83/D83) -> 0.020891365 | J83: =Base!AH359 -> Equipamiento / Contrata | K83: =Base!I359 -> PROCOMPITE | L83: =Base!AA359 -> No registrado en cartera | M83: =Base!AB359 -> No registrado en cartera | N83: =Base!AC359 -> No registrado en cartera | O83: =Base!AD359 -> No registrado en cartera | P83: =IF(Base!AI359="","",Base!AI359) | Q83: =Base!J359 -> Restringido | R83: =Base!X359 -> s/d | S83: =Base!K359 -> 15750 | T83: =Base!M359 -> PROCOMPITE
A84: =SUBTOTAL(103,$B$6:B84) -> 74 | B84: 375 | C84: 2681123: MEJORAMIENTO EN EL PROCESO DE VALOR AGREGADO DE TRUCHAS EN LA EMPRESA AMERICAN TROUT FARO S.R.L. EN EL DISTRITO DE POMATA, PROVINCIA DE CHUCUITO Y DEPARTAMENTO DE PUNO. | D84: =Base!N360 -> 175166 | E84: =Base!O360 -> 166872 | F84: =D84-E84 -> 8294 | G84: =Base!Q360 -> 5872 | H84: =D84-G84 -> 169294 | I84: =IF(D84=0,0,G84/D84) -> 0.033522487 | J84: =Base!AH360 -> Equipamiento / Contrata | K84: =Base!I360 -> PROCOMPITE | L84: =Base!AA360 -> No registrado en cartera | M84: =Base!AB360 -> No registrado en cartera | N84: =Base!AC360 -> No registrado en cartera | O84: =Base!AD360 -> No registrado en cartera | P84: =IF(Base!AI360="","",Base!AI360) | Q84: =Base!J360 -> Restringido | R84: =Base!X360 -> s/d | S84: =Base!K360 -> 8294 | T84: =Base!M360 -> PROCOMPITE
A85: =SUBTOTAL(103,$B$6:B85) -> 75 | B85: 417 | C85: 2717185: MEJORAMIENTO DE VALOR AGREGADO DE LA TRUCHA EN AQUA INDUSTRIAS EL FARO SOCIEDAD COMERCIAL DE RESPONSABILIDAD LIMITADA, DISTRITO DE POMATA, PROVINCIA DE CHUCUITO Y DEPARTAMENTO DE PUNO | D85: =Base!N361 -> 349792 | E85: =Base!O361 -> 325833.33 | F85: =D85-E85 -> 23958.67 | G85: =Base!Q361 -> 0 | H85: =D85-G85 -> 349792 | I85: =IF(D85=0,0,G85/D85) -> 0 | J85: =Base!AH361 -> Equipamiento / Contrata | K85: =Base!I361 -> PROCOMPITE | L85: =Base!AA361 -> No registrado en cartera | M85: =Base!AB361 -> No registrado en cartera | N85: =Base!AC361 -> No registrado en cartera | O85: =Base!AD361 -> No registrado en cartera | P85: =IF(Base!AI361="","",Base!AI361) | Q85: =Base!J361 -> Restringido | R85: =Base!X361 -> s/d | S85: =Base!K361 -> 23958.67 | T85: =Base!M361 -> PROCOMPITE
A86: =SUBTOTAL(103,$B$6:B86) -> 76 | B86: 474 | C86: 2723300: MEJORAMIENTO DE LA PRODUCCION Y TRANSFORMACION DE FILETE DE TRUCHA DE LA EMPRESA TITIKAKA TROUT PERU SOCIEDAD COMERCIAL DE RESPONSABILIDAD LIMITADA DEL DISTRITO DE POMATA, PROVINCIA DE CHUCUITO, REGION PUNO | D86: =Base!N362 -> 349668 | E86: =Base!O362 -> 237183.34 | F86: =D86-E86 -> 112484.66 | G86: =Base!Q362 -> 20700 | H86: =D86-G86 -> 328968 | I86: =IF(D86=0,0,G86/D86) -> 0.059199012 | J86: =Base!AH362 -> Equipamiento / Contrata | K86: =Base!I362 -> PROCOMPITE | L86: =Base!AA362 -> No registrado en cartera | M86: =Base!AB362 -> No registrado en cartera | N86: =Base!AC362 -> No registrado en cartera | O86: =Base!AD362 -> No registrado en cartera | P86: =IF(Base!AI362="","",Base!AI362) | Q86: =Base!J362 -> Restringido | R86: =Base!X362 -> s/d | S86: =Base!K362 -> 112484.66 | T86: =Base!M362 -> PROCOMPITE
A87: 14. INDUSTRIA | D87: =SUM(D88:D94) -> 1308816 | E87: =SUM(E88:E94) -> 1209080 | F87: =D87-E87 -> 99736 | G87: =SUM(G88:G94) -> 538610 | H87: =D87-G87 -> 770206 | I87: =IF(D87=0,0,G87/D87) -> 0.41152461 | S87: =SUM(S88:S94) -> 90933
A88: =SUBTOTAL(103,$B$6:B88) -> 77 | B88: 356 | C88: 2676422: MEJORAMIENTO DE LA COMPETITIVIDAD PRODUCTIVA DE LA CERAMICA TRADICIONAL DE CHECCA PUPUJA EN LA ASOCIACION CERAMICA TRADICIONAL ANCESTRAL CHACCA PUPUJA, DISTRITO DE JOSE DOMINGO CHOQUEHUANCA, PROVINCIA DE AZANGARO, REGION PUNO. | D88: =Base!N363 -> 5365 | E88: =Base!O363 -> 5364 | F88: =D88-E88 -> 1 | G88: =Base!Q363 -> 5364 | H88: =D88-G88 -> 1 | I88: =IF(D88=0,0,G88/D88) -> 0.99981361 | J88: =Base!AH363 -> Contrata | K88: =Base!I363 -> PROCOMPITE | L88: =Base!AA363 -> No registrado en cartera | M88: =Base!AB363 -> No registrado en cartera | N88: =Base!AC363 -> No registrado en cartera | O88: =Base!AD363 -> No registrado en cartera | P88: =IF(Base!AI363="","",Base!AI363) | Q88: =Base!J363 -> No mover | R88: =Base!X363 -> s/d | S88: =Base!K363 -> 0 | T88: =Base!M363 -> Devengado 2026 ≥ 90% del PIM
A89: =SUBTOTAL(103,$B$6:B89) -> 78 | B89: 374 | C89: 2681274: MEJORAMIENTO DEL PROCESO DE PRODUCCION DE ARTICULOS MECANICOS EN LA CORPORACION MARSAD S.A.C. DEL DISTRITO DE PUNO, PROVINCIA DE PUNO, REGION DE PUNO | D89: =Base!N364 -> 335890 | E89: =Base!O364 -> 314900 | F89: =D89-E89 -> 20990 | G89: =Base!Q364 -> 0 | H89: =D89-G89 -> 335890 | I89: =IF(D89=0,0,G89/D89) -> 0 | J89: =Base!AH364 -> Equipamiento / Contrata | K89: =Base!I364 -> PROCOMPITE | L89: =Base!AA364 -> No registrado en cartera | M89: =Base!AB364 -> No registrado en cartera | N89: =Base!AC364 -> No registrado en cartera | O89: =Base!AD364 -> No registrado en cartera | P89: =IF(Base!AI364="","",Base!AI364) | Q89: =Base!J364 -> Restringido | R89: =Base!X364 -> s/d | S89: =Base!K364 -> 20990 | T89: =Base!M364 -> PROCOMPITE
A90: =SUBTOTAL(103,$B$6:B90) -> 79 | B90: 377 | C90: 2681130: MEJORAMIENTO DE LA PRODUCCION DEL ENVASADO DE AGUA DE MESA DE LA EMPRESA GRUPO ANCCASI SOCIEDAD ANONIMA CERRADA DEL DISTRITO DE CORANI, PROVINCIA CARABAYA, DEPARTAMENTO PUNO | D90: =Base!N365 -> 157066 | E90: =Base!O365 -> 157066 | F90: =D90-E90 -> 0 | G90: =Base!Q365 -> 157066 | H90: =D90-G90 -> 0 | I90: =IF(D90=0,0,G90/D90) -> 1 | J90: =Base!AH365 -> Equipamiento / Contrata | K90: =Base!I365 -> PROCOMPITE | L90: =Base!AA365 -> No registrado en cartera | M90: =Base!AB365 -> No registrado en cartera | N90: =Base!AC365 -> No registrado en cartera | O90: =Base!AD365 -> No registrado en cartera | P90: =IF(Base!AI365="","",Base!AI365) | Q90: =Base!J365 -> No mover | R90: =Base!X365 -> s/d | S90: =Base!K365 -> 0 | T90: =Base!M365 -> Devengado 2026 ≥ 90% del PIM
A91: =SUBTOTAL(103,$B$6:B91) -> 80 | B91: 386 | C91: 2717150: MEJORAMIENTO DEL PROCESO PRODUCTIVO Y EL VALOR CULTURAL DE LAS CERAMICAS DE LA ASOCIACION DE ARTESANOS PRODUCTORES MUSUQ PAQARIY PUKARA, DEL DISTRITO DE PUCARA, PROVINCIA DE LAMPA, DEPARTAMENTO DE PUNO | D91: =Base!N366 -> 159345 | E91: =Base!O366 -> 150543 | F91: =D91-E91 -> 8802 | G91: =Base!Q366 -> 150263 | H91: =D91-G91 -> 9082 | I91: =IF(D91=0,0,G91/D91) -> 0.94300417 | J91: =Base!AH366 -> Equipamiento / Contrata | K91: =Base!I366 -> PROCOMPITE | L91: =Base!AA366 -> No registrado en cartera | M91: =Base!AB366 -> No registrado en cartera | N91: =Base!AC366 -> No registrado en cartera | O91: =Base!AD366 -> No registrado en cartera | P91: =IF(Base!AI366="","",Base!AI366) | Q91: =Base!J366 -> No mover | R91: =Base!X366 -> s/d | S91: =Base!K366 -> 0 | T91: =Base!M366 -> Devengado 2026 ≥ 90% del PIM
A92: =SUBTOTAL(103,$B$6:B92) -> 81 | B92: 473 | C92: 2723295: MEJORAMIENTO DE LA PRODUCCION Y COMERCIALIZACION DE QUESOS TIPO PARIA DE LA ASOCIACION AGROINDUSTRIAL YURAQ WASI DE LA COMUNIDAD CAMPESINA PRIMER JILAHUATA, DISTRITO DE AZANGARO, PROVINCIA DE AZANGARO, REGION PUNO | D92: =Base!N367 -> 160000 | E92: =Base!O367 -> 145797 | F92: =D92-E92 -> 14203 | G92: =Base!Q367 -> 139797 | H92: =D92-G92 -> 20203 | I92: =IF(D92=0,0,G92/D92) -> 0.87373125 | J92: =Base!AH367 -> Equipamiento / Contrata | K92: =Base!I367 -> PROCOMPITE | L92: =Base!AA367 -> No registrado en cartera | M92: =Base!AB367 -> No registrado en cartera | N92: =Base!AC367 -> No registrado en cartera | O92: =Base!AD367 -> No registrado en cartera | P92: =IF(Base!AI367="","",Base!AI367) | Q92: =Base!J367 -> Restringido | R92: =Base!X367 -> s/d | S92: =Base!K367 -> 14203 | T92: =Base!M367 -> PROCOMPITE
A93: =SUBTOTAL(103,$B$6:B93) -> 82 | B93: 476 | C93: 2723301: MEJORAMIENTO DE LA TRANSFORMACION Y COMERCIALIZACION DE HILOS Y PRENDAS DE TONOS Y TENIDOS NATURALES DE FIBRA DE ALPACA EN LA ASOCIACION DE ARTESANAS KISWAR TIKA, DISTRITO DE OCUVIRI, PROVINCIA LAMPA, REGION PUNO | D93: =Base!N368 -> 141150 | E93: =Base!O368 -> 115290 | F93: =D93-E93 -> 25860 | G93: =Base!Q368 -> 0 | H93: =D93-G93 -> 141150 | I93: =IF(D93=0,0,G93/D93) -> 0 | J93: =Base!AH368 -> Equipamiento / Contrata | K93: =Base!I368 -> PROCOMPITE | L93: =Base!AA368 -> No registrado en cartera | M93: =Base!AB368 -> No registrado en cartera | N93: =Base!AC368 -> No registrado en cartera | O93: =Base!AD368 -> No registrado en cartera | P93: =IF(Base!AI368="","",Base!AI368) | Q93: =Base!J368 -> Restringido | R93: =Base!X368 -> s/d | S93: =Base!K368 -> 25860 | T93: =Base!M368 -> PROCOMPITE
A94: =SUBTOTAL(103,$B$6:B94) -> 83 | B94: 477 | C94: 2723299: MEJORAMIENTO DE LA CAPACIDAD PRODUCTIVA DE HELADOS ARTESANALES A BASE DE GRANOS ANDINOS DEL GRUPO DE PRODUCTORES, COMERCIALIZACION Y TRANSFORMACION DE CEREALES ANDINOS SAN SANTIAGO S.A.C., DEL DISTRITO DE PUNO, PROVINCIA DE PUNO, REGION DE PUNO. | D94: =Base!N369 -> 350000 | E94: =Base!O369 -> 320120 | F94: =D94-E94 -> 29880 | G94: =Base!Q369 -> 86120 | H94: =D94-G94 -> 263880 | I94: =IF(D94=0,0,G94/D94) -> 0.24605714 | J94: =Base!AH369 -> Equipamiento / Contrata | K94: =Base!I369 -> PROCOMPITE | L94: =Base!AA369 -> No registrado en cartera | M94: =Base!AB369 -> No registrado en cartera | N94: =Base!AC369 -> No registrado en cartera | O94: =Base!AD369 -> No registrado en cartera | P94: =IF(Base!AI369="","",Base!AI369) | Q94: =Base!J369 -> Restringido | R94: =Base!X369 -> s/d | S94: =Base!K369 -> 29880 | T94: =Base!M369 -> PROCOMPITE
A95: GERENCIA REGIONAL DE RECURSOS NATURALES Y GESTION AMBIENTAL | D95: =D96+D100+D102 -> 18155027 | E95: =E96+E100+E102 -> 15207567 | F95: =D95-E95 -> 2947460 | G95: =G96+G100+G102 -> 8757642.5 | H95: =D95-G95 -> 9397384.5 | I95: =IF(D95=0,0,G95/D95) -> 0.48238113 | S95: =S96+S100+S102 -> 19805.09
A96: 05. ORDEN PUBLICO Y SEGURIDAD | D96: =SUM(D97:D99) -> 16120710 | E96: =SUM(E97:E99) -> 15043261 | F96: =D96-E96 -> 1077449.2 | G96: =SUM(G97:G99) -> 8626797.8 | H96: =D96-G96 -> 7493912.2 | I96: =IF(D96=0,0,G96/D96) -> 0.53513759 | S96: =SUM(S97:S99) -> 16046.09
A97: =SUBTOTAL(103,$B$6:B97) -> 84 | B97: 4 | C97: 2183634: MEJORAMIENTO DE LA DEFENSA RIBEREÑA EN LAS MARGENES DERECHA E IZQUIERDA DEL RIO RAMIS EN LOS TRAMOS DE SACASCO, COLLANA, CHACAMARCA, PATASCACHI, YANAOCO, TUNI GRANDE, RAMIS Y BALSAPATA DE LAS PROVINCIAS DE HUANCANE Y AZANGARO - REGION PUNO | D97: =Base!N370 -> 10918999 | E97: =Base!O370 -> 10081159 | F97: =D97-E97 -> 837840.11 | G97: =Base!Q370 -> 5853517.8 | H97: =D97-G97 -> 5065481.2 | I97: =IF(D97=0,0,G97/D97) -> 0.53608557 | J97: =Base!AH370 -> Administración directa / Contrata / Personal/bienes/servicios | K97: =Base!I370 -> Proyecto de inversión | L97: =Base!AA370 -> 10517000 | M97: =Base!AB370 -> 7783178 | N97: =Base!AC370 -> 1598000 | O97: =Base!AD370 -> 2000000 | P97: =IF(Base!AI370="","",Base!AI370) | Q97: =Base!J370 -> Sin saldo útil | R97: =Base!X370 -> 0.72696591 | S97: =Base!K370 -> 0 | T97: =Base!M370 -> Saldo libre menor a S/ 10,000
A98: =SUBTOTAL(103,$B$6:B98) -> 85 | B98: 6 | C98: 2532916: CREACION DEL SERVICIO DE PROTECCIÓN EN RIBERAS DEL RÍO LORIPONGO Y MOLLA AMBOS MÁRGENES VULNERABLES ANTE EL PELIGRO DE INUNDACIÓN EN LA LOCALIDAD DE LARAQUERI Y CENTRO POBLADO DE HUARIJUYO DEL DISTRITO DE PICHACANI - PROVINCIA DE PUNO - DEPARTAMENTO DE PUNO | D98: =Base!N371 -> 19658 | E98: =Base!O371 -> 3612 | F98: =D98-E98 -> 16046 | G98: =Base!Q371 -> 0 | H98: =D98-G98 -> 19658 | I98: =IF(D98=0,0,G98/D98) -> 0 | J98: =Base!AH371 -> Expediente técnico | K98: =Base!I371 -> Proyecto de inversión | L98: =Base!AA371 -> 200000 | M98: =Base!AB371 -> 2915452 | N98: =Base!AC371 -> 2124684 | O98: =Base!AD371 -> 2000000 | P98: =IF(Base!AI371="","",Base!AI371) | Q98: =Base!J371 -> Con condiciones | R98: =Base!X371 -> 0.029585979 | S98: =Base!K371 -> 16045.8 | T98: =Base!M371 -> Está programado en el PMI 2026 · Tiene monto en el PMI 2027 (S/ 2,915,452)
A99: =SUBTOTAL(103,$B$6:B99) -> 86 | B99: 303 | C99: 2520451: CREACION DEL SERVICIO DE PROTECCION EN RIBERAS DEL RIO QUELLOMAYO MARGEN DERECHO VULNERABLES ANTE EL PELIGRO DE INUNDACION EN LA LOCALIDAD DE SAN GABAN, DEL DISTRITO DE SAN GABAN - PROVINCIA DE CARABAYA - DEPARTAMENTO DE PUNO | D99: =Base!N372 -> 5182053 | E99: =Base!O372 -> 4958489.9 | F99: =D99-E99 -> 223563.11 | G99: =Base!Q372 -> 2773280 | H99: =D99-G99 -> 2408773 | I99: =IF(D99=0,0,G99/D99) -> 0.53517013 | J99: =Base!AH372 -> Administración directa / Contrata / Personal/bienes/servicios | K99: =Base!I372 -> Proyecto de inversión | L99: =Base!AA372 -> 409040 | M99: =Base!AB372 -> 29865 | N99: =Base!AC372 -> 0 | O99: =Base!AD372 -> 0 | P99: =IF(Base!AI372="","",Base!AI372) | Q99: =Base!J372 -> Sin saldo útil | R99: =Base!X372 -> 0.8361878 | S99: =Base!K372 -> 0.29 | T99: =Base!M372 -> Saldo libre menor a S/ 10,000
A100: 10. AGROPECUARIA | D100: =SUM(D101:D101) -> 1800000 | E100: =SUM(E101:E101) -> 26893 | F100: =D100-E100 -> 1773107 | G100: =SUM(G101:G101) -> 26892.69 | H100: =D100-G100 -> 1773107.3 | I100: =IF(D100=0,0,G100/D100) -> 0.014940383 | S100: =SUM(S101:S101) -> 0
A101: =SUBTOTAL(103,$B$6:B101) -> 87 | B101: 5 | C101: 2474102: MEJORAMIENTO DEL SERVICIO DE PROTECCIÓN FRENTE A TORMENTAS ELÉCTRICAS EN 4 PROVINCIAS DEL DEPARTAMENTO DE PUNO | D101: =Base!N373 -> 1800000 | E101: =Base!O373 -> 26893 | F101: =D101-E101 -> 1773107 | G101: =Base!Q373 -> 26892.69 | H101: =D101-G101 -> 1773107.3 | I101: =IF(D101=0,0,G101/D101) -> 0.014940383 | J101: =Base!AH373 -> Personal/bienes/servicios / Contrata / Equipamiento / Expediente técnico | K101: =Base!I373 -> Proyecto de inversión | L101: =Base!AA373 -> 300000 | M101: =Base!AB373 -> 4508196 | N101: =Base!AC373 -> 5000000 | O101: =Base!AD373 -> 1000000 | P101: =IF(Base!AI373="","",Base!AI373) | Q101: =Base!J373 -> Sin saldo útil | R101: =Base!X373 -> 0.0072312945 | S101: =Base!K373 -> 0 | T101: =Base!M373 -> Saldo libre menor a S/ 10,000
A102: 17. AMBIENTE | D102: =SUM(D103:D109) -> 234317 | E102: =SUM(E103:E109) -> 137413.2 | F102: =D102-E102 -> 96903.8 | G102: =SUM(G103:G109) -> 103951.95 | H102: =D102-G102 -> 130365.05 | I102: =IF(D102=0,0,G102/D102) -> 0.44363811 | S102: =SUM(S103:S109) -> 3759
A103: =SUBTOTAL(103,$B$6:B103) -> 88 | B103: 7 | C103: 2533866: RECUPERACION DE ECOSISTEMAS DEGRADADOS POR VERTIMIENTO DE AGUAS RESIDUALES Y RESIDUOS SOLIDOS EN LA DESEMBOCADURA DEL RIO COATA, EN LOS DISTRITOS DE HUATA, COATA, CAPACHICA, JULIACA Y SAN MIGUEL EN LAS PROVINCIAS DE PUNO Y SAN ROMAN DEL DEPARTAMENTO DE PUNO | D103: =Base!N374 -> 32099 | E103: =Base!O374 -> 0 | F103: =D103-E103 -> 32099 | G103: =Base!Q374 -> 0 | H103: =D103-G103 -> 32099 | I103: =IF(D103=0,0,G103/D103) -> 0 | J103: =Base!AH374 -> Contrata | K103: =Base!I374 -> Proyecto de inversión | L103: =Base!AA374 -> 500000 | M103: =Base!AB374 -> 0 | N103: =Base!AC374 -> 0 | O103: =Base!AD374 -> 0 | P103: =IF(Base!AI374="","",Base!AI374) | Q103: =Base!J374 -> Sin saldo útil | R103: =Base!X374 -> 0.049073349 | S103: =Base!K374 -> 0 | T103: =Base!M374 -> Saldo libre menor a S/ 10,000
A104: =SUBTOTAL(103,$B$6:B104) -> 89 | B104: 152 | C104: 2250970: MEJORAMIENTO DEL SERVICIO DE CONSERVACION DE LA DIVERSIDAD BIOLOGICA EN SELVA VERDE, SAN GABAN, PUNTA PERDIDA, COTACUCHO, PUNO, JUCUMARINI, CUSHINI, RIO CONDOR, RIO TAVARA, Y PACO PACUNI, DISTRITOS DE AYAPATA, SAN GABAN, SANTA ROSA, VILQUE CHICO-PUNO | D104: =Base!N375 -> 30000 | E104: =Base!O375 -> 23434 | F104: =D104-E104 -> 6566 | G104: =Base!Q375 -> 13106.35 | H104: =D104-G104 -> 16893.65 | I104: =IF(D104=0,0,G104/D104) -> 0.43687833 | J104: =Base!AH375 -> Contrata / Personal/bienes/servicios | K104: =Base!I375 -> Proyecto de inversión | L104: =Base!AA375 -> 2080646 | M104: =Base!AB375 -> 70728 | N104: =Base!AC375 -> 300000 | O104: =Base!AD375 -> 300000 | P104: =IF(Base!AI375="","",Base!AI375) | Q104: =Base!J375 -> Sin saldo útil | R104: =Base!X375 -> 0.2896079 | S104: =Base!K375 -> 3758 | T104: =Base!M375 -> Saldo libre menor a S/ 10,000
A105: =SUBTOTAL(103,$B$6:B105) -> 90 | B105: 154 | C105: 2631070: RECUPERACION DE LOS SERVICIOS ECOSISTÉMICOS EN 19 UNIDADES PRODUCTORAS 19 DISTRITOS DE 13 PROVINCIAS DEL DEPARTAMENTO DE PUNO | D105: =Base!N376 -> 90586 | E105: =Base!O376 -> 90435.2 | F105: =D105-E105 -> 150.8 | G105: =Base!Q376 -> 78301.6 | H105: =D105-G105 -> 12284.4 | I105: =IF(D105=0,0,G105/D105) -> 0.86438964 | J105: =Base!AH376 -> Expediente técnico | K105: =Base!I376 -> Proyecto de inversión | L105: =Base!AA376 -> 100000 | M105: =Base!AB376 -> 0 | N105: =Base!AC376 -> 2000000 | O105: =Base!AD376 -> 2000000 | P105: =IF(Base!AI376="","",Base!AI376) | Q105: =Base!J376 -> Sin saldo útil | R105: =Base!X376 -> 0.01500586 | S105: =Base!K376 -> 1 | T105: =Base!M376 -> Saldo libre menor a S/ 10,000
A106: =SUBTOTAL(103,$B$6:B106) -> 91 | B106: 250 | C106: 2549395: RECUPERACION DE ECOSISTEMAS DEGRADADOS EN LAS UNIDADES HIDROGRAFICAS: LLALLIMAYO DE LA UH 018 PUCARA Y UH 019 AZANGARO, DE LA CUENCA RAMIS DEL DEPARTAMENTO DE PUNO, REGION PUNO 5 PROVINCIAS DEL DEPARTAMENTO DE PUNO | D106: =Base!N377 -> 0 | E106: =Base!O377 -> 0 | F106: =D106-E106 -> 0 | G106: =Base!Q377 -> 0 | H106: =D106-G106 -> 0 | I106: =IF(D106=0,0,G106/D106) -> 0 | J106: =Base!AH377 -> Contrata | K106: =Base!I377 -> Proyecto de inversión | L106: =Base!AA377 -> 800000 | M106: =Base!AB377 -> 0 | N106: =Base!AC377 -> 0 | O106: =Base!AD377 -> 0 | P106: =IF(Base!AI377="","",Base!AI377) | Q106: =Base!J377 -> Sin PIM | R106: =Base!X377 -> 0.011277933 | S106: =Base!K377 -> 0 | T106: =Base!M377 -> PIM igual a 0
A107: =SUBTOTAL(103,$B$6:B107) -> 92 | B107: 253 | C107: 2566295: RECUPERACION DE ECOSISTEMAS DEGRADADOS EN ZONAS ALTO ANDINAS EN CABECERA DE CUENCA DE LAS UH0172, UH0178 Y UH0171 CUENCA SUCHES EN 4 PROVINCIAS DEL DEPARTAMENTO DE PUNO | D107: =Base!N378 -> 0 | E107: =Base!O378 -> 0 | F107: =D107-E107 -> 0 | G107: =Base!Q378 -> 0 | H107: =D107-G107 -> 0 | I107: =IF(D107=0,0,G107/D107) -> 0 | J107: =Base!AH378 -> Personal/bienes/servicios | K107: =Base!I378 -> Proyecto de inversión | L107: =Base!AA378 -> 200000 | M107: =Base!AB378 -> 0 | N107: =Base!AC378 -> 0 | O107: =Base!AD378 -> 0 | P107: =IF(Base!AI378="","",Base!AI378) | Q107: =Base!J378 -> Sin PIM | R107: =Base!X378 -> 0.018111099 | S107: =Base!K378 -> 0 | T107: =Base!M378 -> PIM igual a 0
A108: =SUBTOTAL(103,$B$6:B108) -> 93 | B108: 465 | C108: 2260735: MEJORAMIENTO DE LA GESTION INTEGRADA DE LOS RECURSOS HIDRICOS EN CUENCAS DE LA REGION PUNO | D108: =Base!N379 -> 70632 | E108: =Base!O379 -> 12544 | F108: =D108-E108 -> 58088 | G108: =Base!Q379 -> 12544 | H108: =D108-G108 -> 58088 | I108: =IF(D108=0,0,G108/D108) -> 0.17759656 | J108: =Base!AH379 -> Contrata / Personal/bienes/servicios | K108: =Base!I379 -> Proyecto de inversión | L108: =Base!AA379 -> 70632 | M108: =Base!AB379 -> 0 | N108: =Base!AC379 -> 0 | O108: =Base!AD379 -> 0 | P108: =IF(Base!AI379="","",Base!AI379) | Q108: =Base!J379 -> No mover | R108: =Base!X379 -> 1.0089435 | S108: =Base!K379 -> 0 | T108: =Base!M379 -> Avance financiero acumulado 101% (> 90%)
A109: =SUBTOTAL(103,$B$6:B109) -> 94 | B109: 471 | C109: 2684838: MEJORAMIENTO Y AMPLIACION DEL SERVICIO DE LIMPIEZA PÚBLICA EN 7 UNIDADES PRODUCTORAS 7 DISTRITOS DE LA PROVINCIA DE MELGAR DEL DEPARTAMENTO DE PUNO | D109: =Base!N380 -> 11000 | E109: =Base!O380 -> 11000 | F109: =D109-E109 -> 0 | G109: =Base!Q380 -> 0 | H109: =D109-G109 -> 11000 | I109: =IF(D109=0,0,G109/D109) -> 0 | J109: =Base!AH380 -> Contrata / Administración directa | K109: =Base!I380 -> Proyecto de inversión | L109: =Base!AA380 -> 11000 | M109: =Base!AB380 -> 164792 | N109: =Base!AC380 -> 9322563 | O109: =Base!AD380 -> 9322563 | P109: =IF(Base!AI380="","",Base!AI380) | Q109: =Base!J380 -> Sin saldo útil | R109: =Base!X380 -> 0 | S109: =Base!K380 -> 0 | T109: =Base!M380 -> Saldo libre menor a S/ 10,000
A110: PROYECTO ESPECIAL TRUCHAS TITICACA - PETT | D110: =D111 -> 13183082 | E110: =E111 -> 12706541 | F110: =D110-E110 -> 476541.15 | G110: =G111 -> 3714211.5 | H110: =D110-G110 -> 9468870.5 | I110: =IF(D110=0,0,G110/D110) -> 0.28174076 | S110: =S111 -> 0
A111: 03. PLANEAMIENTO, GESTION Y RESERVA DE CONTINGENCIA | D111: =SUM(D112:D114) -> 13183082 | E111: =SUM(E112:E114) -> 12706541 | F111: =D111-E111 -> 476541.15 | G111: =SUM(G112:G114) -> 3714211.5 | H111: =D111-G111 -> 9468870.5 | I111: =IF(D111=0,0,G111/D111) -> 0.28174076 | S111: =SUM(S112:S114) -> 0
A112: =SUBTOTAL(103,$B$6:B112) -> 95 | B112: 59 | C112: 2324613: MEJORAMIENTO DE LAS CAPACIDADES TECNOLÓGICAS EN EL MANEJO DE CADENA PRODUCTIVA DE TRUCHA EN LA REGIÓN PUNO | D112: =Base!N381 -> 550560 | E112: =Base!O381 -> 519500 | F112: =D112-E112 -> 31060 | G112: =Base!Q381 -> 517920.09 | H112: =D112-G112 -> 32639.91 | I112: =IF(D112=0,0,G112/D112) -> 0.94071507 | J112: =Base!AH381 -> Personal/bienes/servicios / Contrata | K112: =Base!I381 -> Proyecto de inversión | L112: =Base!AA381 -> 100560 | M112: =Base!AB381 -> 93700 | N112: =Base!AC381 -> 0 | O112: =Base!AD381 -> 0 | P112: =IF(Base!AI381="","",Base!AI381) | Q112: =Base!J381 -> No mover | R112: =Base!X381 -> 1.0014383 | S112: =Base!K381 -> 0 | T112: =Base!M381 -> Devengado 2026 ≥ 90% del PIM
A113: =SUBTOTAL(103,$B$6:B113) -> 96 | B113: 60 | C113: 2603148: MEJORAMIENTO DE LOS SERVICIOS DE APOYO AL DESARROLLO PRODUCTIVO EN 19 UNIDADES PRODUCTORAS 19 DISTRITOS DE 7 PROVINCIAS DEL DEPARTAMENTO DE PUNO | D113: =Base!N382 -> 12532522 | E113: =Base!O382 -> 12187041 | F113: =D113-E113 -> 345481.15 | G113: =Base!Q382 -> 3196291.4 | H113: =D113-G113 -> 9336230.6 | I113: =IF(D113=0,0,G113/D113) -> 0.25503976 | J113: =Base!AH382 -> Administración directa / Personal/bienes/servicios / Contrata / Equipamiento | K113: =Base!I382 -> Proyecto de inversión | L113: =Base!AA382 -> 1000000 | M113: =Base!AB382 -> 4832260 | N113: =Base!AC382 -> 1000000 | O113: =Base!AD382 -> 1000000 | P113: =IF(Base!AI382="","",Base!AI382) | Q113: =Base!J382 -> Sin saldo útil | R113: =Base!X382 -> 0.1296822 | S113: =Base!K382 -> 0 | T113: =Base!M382 -> Saldo libre menor a S/ 10,000
A114: =SUBTOTAL(103,$B$6:B114) -> 97 | B114: 61 | C114: 2603160: MEJORAMIENTO DE LOS SERVICIOS DE APOYO AL DESARROLLO PRODUCTIVO EN 4 UNIDADES PRODUCTORAS 4 DISTRITOS DE LAS PROVINCIAS DE SANDIA, CARABAYA DEL DEPARTAMENTO DE PUNO | D114: =Base!N383 -> 100000 | E114: =Base!O383 -> 0 | F114: =D114-E114 -> 100000 | G114: =Base!Q383 -> 0 | H114: =D114-G114 -> 100000 | I114: =IF(D114=0,0,G114/D114) -> 0 | J114: =Base!AH383 -> Personal/bienes/servicios | K114: =Base!I383 -> Proyecto de inversión | L114: =Base!AA383 -> 100000 | M114: =Base!AB383 -> 0 | N114: =Base!AC383 -> 0 | O114: =Base!AD383 -> 0 | P114: =IF(Base!AI383="","",Base!AI383) | Q114: =Base!J383 -> Sin saldo útil | R114: =Base!X383 -> 0.022524297 | S114: =Base!K383 -> 0 | T114: =Base!M383 -> Saldo libre menor a S/ 10,000
A115: PROYECTO ESPECIAL CAMELIDOS SUDAMERICANOS | D115: =D116+D118 -> 5603985 | E115: =E116+E118 -> 5451423 | F115: =D115-E115 -> 152562.05 | G115: =G116+G118 -> 3504541.4 | H115: =D115-G115 -> 2099443.6 | I115: =IF(D115=0,0,G115/D115) -> 0.62536594 | S115: =S116+S118 -> 0
A116: 03. PLANEAMIENTO, GESTION Y RESERVA DE CONTINGENCIA | D116: =SUM(D117:D117) -> 1332387 | E116: =SUM(E117:E117) -> 1332216.6 | F116: =D116-E116 -> 170.39 | G116: =SUM(G117:G117) -> 1212326 | H116: =D116-G116 -> 120061 | I116: =IF(D116=0,0,G116/D116) -> 0.90989029 | S116: =SUM(S117:S117) -> 0
A117: =SUBTOTAL(103,$B$6:B117) -> 98 | B117: 218 | C117: 2187217: MEJORAMIENTO DE LA CADENA DE VALOR DE LA FIBRA DE ALPACA EN LA REGION PUNO | D117: =Base!N384 -> 1332387 | E117: =Base!O384 -> 1332216.6 | F117: =D117-E117 -> 170.39 | G117: =Base!Q384 -> 1212326 | H117: =D117-G117 -> 120061 | I117: =IF(D117=0,0,G117/D117) -> 0.90989029 | J117: =Base!AH384 -> Contrata / Personal/bienes/servicios | K117: =Base!I384 -> Proyecto de inversión | L117: =Base!AA384 -> 630478 | M117: =Base!AB384 -> 188781 | N117: =Base!AC384 -> 2845395 | O117: =Base!AD384 -> 2772809 | P117: =IF(Base!AI384="","",Base!AI384) | Q117: =Base!J384 -> No mover | R117: =Base!X384 -> 0.94614982 | S117: =Base!K384 -> 0 | T117: =Base!M384 -> Devengado 2026 ≥ 90% del PIM
A118: 10. AGROPECUARIA | D118: =SUM(D119:D119) -> 4271598 | E118: =SUM(E119:E119) -> 4119206.3 | F118: =D118-E118 -> 152391.66 | G118: =SUM(G119:G119) -> 2292215.4 | H118: =D118-G118 -> 1979382.6 | I118: =IF(D118=0,0,G118/D118) -> 0.53661776 | S118: =SUM(S119:S119) -> 0
A119: =SUBTOTAL(103,$B$6:B119) -> 99 | B119: 264 | C119: 2603155: MEJORAMIENTO DE LOS SERVICIOS DE APOYO AL DESARROLLO PRODUCTIVO EN 37 UNIDADES PRODUCTORAS 37 DISTRITOS DE 11 PROVINCIAS DEL DEPARTAMENTO DE PUNO | D119: =Base!N385 -> 4271598 | E119: =Base!O385 -> 4119206.3 | F119: =D119-E119 -> 152391.66 | G119: =Base!Q385 -> 2292215.4 | H119: =D119-G119 -> 1979382.6 | I119: =IF(D119=0,0,G119/D119) -> 0.53661776 | J119: =Base!AH385 -> Personal/bienes/servicios / Contrata / Equipamiento | K119: =Base!I385 -> Proyecto de inversión | L119: =Base!AA385 -> 1500000 | M119: =Base!AB385 -> 4950944 | N119: =Base!AC385 -> 5144103 | O119: =Base!AD385 -> 4718085 | P119: =IF(Base!AI385="","",Base!AI385) | Q119: =Base!J385 -> Sin saldo útil | R119: =Base!X385 -> 0.061885681 | S119: =Base!K385 -> 0 | T119: =Base!M385 -> Saldo libre menor a S/ 10,000
A120: GERENCIA REGIONAL DE DESARROLLO SOCIAL | D120: =D121+D149+D162+D165 -> 74669674 | E120: =E121+E149+E162+E165 -> 67493227 | F120: =D120-E120 -> 7176446.7 | G120: =G121+G149+G162+G165 -> 23519606 | H120: =D120-G120 -> 51150068 | I120: =IF(D120=0,0,G120/D120) -> 0.31498204 | S120: =S121+S149+S162+S165 -> 2464603.6
A121: 20. SALUD | D121: =SUM(D122:D148) -> 52935028 | E121: =SUM(E122:E148) -> 48889834 | F121: =D121-E121 -> 4045193.9 | G121: =SUM(G122:G148) -> 17051815 | H121: =D121-G121 -> 35883213 | I121: =IF(D121=0,0,G121/D121) -> 0.32212725 | S121: =SUM(S122:S148) -> 296533
A122: =SUBTOTAL(103,$B$6:B122) -> 100 | B122: 195 | C122: 2154443: MEJORAMIENTO DEL ESTADO NUTRICIONAL DEL NIÑO MENOR DE TRES AÑOS Y LA MADRE GESTANTE EN LAS PROVINCIAS DE AZANGARO, LAMPA Y SAN ROMAN DE LA REGION PUNO | D122: =Base!N386 -> 0 | E122: =Base!O386 -> 0 | F122: =D122-E122 -> 0 | G122: =Base!Q386 -> 0 | H122: =D122-G122 -> 0 | I122: =IF(D122=0,0,G122/D122) -> 0 | J122: =Base!AH386 -> Personal/bienes/servicios | K122: =Base!I386 -> Proyecto de inversión | L122: =Base!AA386 -> 4098 | M122: =Base!AB386 -> 0 | N122: =Base!AC386 -> 0 | O122: =Base!AD386 -> 0 | P122: =IF(Base!AI386="","",Base!AI386) | Q122: =Base!J386 -> Sin PIM | R122: =Base!X386 -> 0.99955412 | S122: =Base!K386 -> 0 | T122: =Base!M386 -> PIM igual a 0
A123: =SUBTOTAL(103,$B$6:B123) -> 101 | B123: 196 | C123: 2159149: MEJORAMIENTO DE LAS CAPACIDADES PARA PREVENIR LA DESNUTRICION CRONICA, EN MENORES DE 3 AÑOS EN LAS PROVINCIAS DE CARABAYA, MELGAR Y SANDIA DE LA REGION PUNO | D123: =Base!N387 -> 0 | E123: =Base!O387 -> 0 | F123: =D123-E123 -> 0 | G123: =Base!Q387 -> 0 | H123: =D123-G123 -> 0 | I123: =IF(D123=0,0,G123/D123) -> 0 | J123: =Base!AH387 -> Personal/bienes/servicios | K123: =Base!I387 -> Proyecto de inversión | L123: =Base!AA387 -> 87917 | M123: =Base!AB387 -> 0 | N123: =Base!AC387 -> 0 | O123: =Base!AD387 -> 0 | P123: =IF(Base!AI387="","",Base!AI387) | Q123: =Base!J387 -> Sin PIM | R123: =Base!X387 -> 0.9914231 | S123: =Base!K387 -> 0 | T123: =Base!M387 -> PIM igual a 0
A124: =SUBTOTAL(103,$B$6:B124) -> 102 | B124: 239 | C124: 2488048: CREACION DEL SERVICIO DE ANÁLISIS DE BIOLOGIA MOLECULAR DE DIAGNÓSTICO COVID-19 EN EL LABORATORIO DE REFERENCIA REGIONAL DE LA DIRESA PUNO, DISTRITO DE PUNO - PROVINCIA DE PUNO - DEPARTAMENTO DE PUNO | D124: =Base!N388 -> 0 | E124: =Base!O388 -> 0 | F124: =D124-E124 -> 0 | G124: =Base!Q388 -> 0 | H124: =D124-G124 -> 0 | I124: =IF(D124=0,0,G124/D124) -> 0 | J124: =Base!AH388 -> Administración directa | K124: =Base!I388 -> Proyecto de inversión | L124: =Base!AA388 -> 276105 | M124: =Base!AB388 -> 0 | N124: =Base!AC388 -> 0 | O124: =Base!AD388 -> 0 | P124: =IF(Base!AI388="","",Base!AI388) | Q124: =Base!J388 -> Sin PIM | R124: =Base!X388 -> 0.98687953 | S124: =Base!K388 -> 0 | T124: =Base!M388 -> PIM igual a 0
A125: =SUBTOTAL(103,$B$6:B125) -> 103 | B125: 249 | C125: 2544369: ADQUISICION DE AMBULANCIA RURAL Y AMBULANCIA RURAL; EN CINCUENTA Y CINCO ESTABLECIMIENTOS DE SALUD I.4, ESTABLECIMIENTOS DE SALUD I.2, ESTABLECIMIENTOS DE SALUD I.3 A NIVEL DEPARTAMENTAL (PUNO) | D125: =Base!N389 -> 0 | E125: =Base!O389 -> 0 | F125: =D125-E125 -> 0 | G125: =Base!Q389 -> 0 | H125: =D125-G125 -> 0 | I125: =IF(D125=0,0,G125/D125) -> 0 | J125: =Base!AH389 -> Personal/bienes/servicios | K125: =Base!I389 -> IOARR | L125: =Base!AA389 -> 89896 | M125: =Base!AB389 -> 0 | N125: =Base!AC389 -> 0 | O125: =Base!AD389 -> 0 | P125: =IF(Base!AI389="","",Base!AI389) | Q125: =Base!J389 -> Sin PIM | R125: =Base!X389 -> 0.996091 | S125: =Base!K389 -> 0 | T125: =Base!M389 -> PIM igual a 0
A126: =SUBTOTAL(103,$B$6:B126) -> 104 | B126: 254 | C126: 2567368: ADQUISICION DE MAMOGRAFO; EN EL(LA) EESS SAN MARTIN DE P. (MACUSANI) - MACUSANI DISTRITO DE MACUSANI, PROVINCIA CARABAYA, DEPARTAMENTO PUNO | D126: =Base!N390 -> 2390440 | E126: =Base!O390 -> 2386020 | F126: =D126-E126 -> 4420 | G126: =Base!Q390 -> 824976.09 | H126: =D126-G126 -> 1565463.9 | I126: =IF(D126=0,0,G126/D126) -> 0.34511474 | J126: =Base!AH390 -> Equipamiento / Contrata / Personal/bienes/servicios | K126: =Base!I390 -> IOARR | L126: =Base!AA390 -> 21175 | M126: =Base!AB390 -> 2971 | N126: =Base!AC390 -> 1 | O126: =Base!AD390 -> 0 | P126: =IF(Base!AI390="","",Base!AI390) | Q126: =Base!J390 -> Sin saldo útil | R126: =Base!X390 -> 0.39721295 | S126: =Base!K390 -> 0 | T126: =Base!M390 -> Saldo libre menor a S/ 10,000
A127: =SUBTOTAL(103,$B$6:B127) -> 105 | B127: 255 | C127: 2567375: ADQUISICION DE TOMOGRAFO COMPUTARIZADO MULTICORTE; EN EL(LA) EESS SAN MARTIN DE P. (MACUSANI) - MACUSANI DISTRITO DE MACUSANI, PROVINCIA CARABAYA, DEPARTAMENTO PUNO | D127: =Base!N391 -> 20600 | E127: =Base!O391 -> 20600 | F127: =D127-E127 -> 0 | G127: =Base!Q391 -> 17783.6 | H127: =D127-G127 -> 2816.4 | I127: =IF(D127=0,0,G127/D127) -> 0.86328155 | J127: =Base!AH391 -> Contrata | K127: =Base!I391 -> IOARR | L127: =Base!AA391 -> 40062 | M127: =Base!AB391 -> 0 | N127: =Base!AC391 -> 0 | O127: =Base!AD391 -> 0 | P127: =IF(Base!AI391="","",Base!AI391) | Q127: =Base!J391 -> No mover | R127: =Base!X391 -> 0.9730025 | S127: =Base!K391 -> 0 | T127: =Base!M391 -> Avance financiero acumulado 97% (> 90%)
A128: =SUBTOTAL(103,$B$6:B128) -> 106 | B128: 263 | C128: 2600443: ADQUISICION DE SISTEMA DE CIRUGIA LAPAROSCOPICA, TOMOGRAFO, MESA DE OPERACIONES HIDRAULICA/ELECTRICA Y LAMPARA QUIRURGICA DE TECHO; ADEMÁS DE OTROS ACTIVOS EN EL(LA) YUNGUYO DISTRITO DE YUNGUYO, PROVINCIA YUNGUYO, DEPARTAMENTO PUNO | D128: =Base!N392 -> 3517960 | E128: =Base!O392 -> 3472430.1 | F128: =D128-E128 -> 45529.9 | G128: =Base!Q392 -> 2179648.5 | H128: =D128-G128 -> 1338311.5 | I128: =IF(D128=0,0,G128/D128) -> 0.6195774 | J128: =Base!AH392 -> Equipamiento / Contrata / Personal/bienes/servicios | K128: =Base!I392 -> IOARR | L128: =Base!AA392 -> 2000000 | M128: =Base!AB392 -> 64020 | N128: =Base!AC392 -> 1401972 | O128: =Base!AD392 -> 495265 | P128: =IF(Base!AI392="","",Base!AI392) | Q128: =Base!J392 -> Sin saldo útil | R128: =Base!X392 -> 0.36907735 | S128: =Base!K392 -> 0 | T128: =Base!M392 -> Saldo libre menor a S/ 10,000
A129: =SUBTOTAL(103,$B$6:B129) -> 107 | B129: 281 | C129: 2650340: ADQUISICION DE MESA DE OPERACIONES HIDRAULICA/ELECTRICA, ESTERILIZADOR CON GENERADOR ELECTRICO DE VAPOR (INS), EQUIPOS BIOMEDICOS Y COCHE DE PARO; ADEMÁS DE OTROS ACTIVOS EN EL(LA) PUTINA DISTRITO DE PUTINA, PROVINCIA SAN ANTONIO DE PUTINA, DEPARTAMENTO PUNO | D129: =Base!N393 -> 2170829 | E129: =Base!O393 -> 2170829 | F129: =D129-E129 -> 0 | G129: =Base!Q393 -> 147448.3 | H129: =D129-G129 -> 2023380.7 | I129: =IF(D129=0,0,G129/D129) -> 0.067922577 | J129: =Base!AH393 -> Equipamiento / Contrata | K129: =Base!I393 -> IOARR | L129: =Base!AA393 -> 2421000 | M129: =Base!AB393 -> 2508625 | N129: =Base!AC393 -> 546908 | O129: =Base!AD393 -> 170650 | P129: =IF(Base!AI393="","",Base!AI393) | Q129: =Base!J393 -> Sin saldo útil | R129: =Base!X393 -> 0.10186447 | S129: =Base!K393 -> 0 | T129: =Base!M393 -> Saldo libre menor a S/ 10,000
A130: =SUBTOTAL(103,$B$6:B130) -> 108 | B130: 285 | C130: 2684028: ADQUISICION DE AMBULANCIA URBANA; EN ONCE ESTABLECIMIENTOS DE SALUD II.1, ESTABLECIMIENTOS DE SALUD II.2 A NIVEL DEPARTAMENTAL (PUNO) | D130: =Base!N394 -> 31336 | E130: =Base!O394 -> 0 | F130: =D130-E130 -> 31336 | G130: =Base!Q394 -> 0 | H130: =D130-G130 -> 31336 | I130: =IF(D130=0,0,G130/D130) -> 0 | J130: =Base!AH394 -> Contrata | K130: =Base!I394 -> IOARR | L130: =Base!AA394 -> 513444 | M130: =Base!AB394 -> 0 | N130: =Base!AC394 -> 0 | O130: =Base!AD394 -> 0 | P130: =IF(Base!AI394="","",Base!AI394) | Q130: =Base!J394 -> Sin saldo útil | R130: =Base!X394 -> 0.0032174969 | S130: =Base!K394 -> 0 | T130: =Base!M394 -> Saldo libre menor a S/ 10,000
A131: =SUBTOTAL(103,$B$6:B131) -> 109 | B131: 287 | C131: 2685776: ADQUISICION DE ANALIZADOR DE GASES Y ELECTROLITOS, ESPECTROFOTOMETRO, EQUIPO DE RAYOS X DENTAL Y BIDESTILADOR DE AGUA; ADEMÁS DE OTROS ACTIVOS EN EL(LA) MOHO DISTRITO DE MOHO, PROVINCIA MOHO, DEPARTAMENTO PUNO | D131: =Base!N395 -> 1263865 | E131: =Base!O395 -> 1181167.9 | F131: =D131-E131 -> 82697.06 | G131: =Base!Q395 -> 146441.28 | H131: =D131-G131 -> 1117423.7 | I131: =IF(D131=0,0,G131/D131) -> 0.11586782 | J131: =Base!AH395 -> Equipamiento / Contrata / Personal/bienes/servicios | K131: =Base!I395 -> IOARR | L131: =Base!AA395 -> 894000 | M131: =Base!AB395 -> 0 | N131: =Base!AC395 -> 825648 | O131: =Base!AD395 -> 825648 | P131: =IF(Base!AI395="","",Base!AI395) | Q131: =Base!J395 -> Sin saldo útil | R131: =Base!X395 -> 0.057077693 | S131: =Base!K395 -> 0 | T131: =Base!M395 -> Saldo libre menor a S/ 10,000
A132: =SUBTOTAL(103,$B$6:B132) -> 110 | B132: 313 | C132: 2694246: ADQUISICION DE MAMOGRAFO, COLONOVIDEOENDOSCOPIO, MESA DE OPERACIONES HIDRAULICA/ELECTRICA Y CALDERO; ADEMÁS DE OTROS ACTIVOS EN EL(LA) HOSPITAL REGIONAL MANUEL NUÑEZ BUTRON HOSPITAL REGIONAL MANUEL NUÑEZ BUTRON DISTRITO DE PUNO, PROVINCIA PUNO, DEPARTAMENTO PUNO | D132: =Base!N396 -> 8483998 | E132: =Base!O396 -> 8474782.3 | F132: =D132-E132 -> 9215.69 | G132: =Base!Q396 -> 5322446.1 | H132: =D132-G132 -> 3161551.9 | I132: =IF(D132=0,0,G132/D132) -> 0.62735117 | J132: =Base!AH396 -> Equipamiento / Contrata / Personal/bienes/servicios | K132: =Base!I396 -> IOARR | L132: =Base!AA396 -> 2578971 | M132: =Base!AB396 -> 22487 | N132: =Base!AC396 -> 500000 | O132: =Base!AD396 -> 500000 | P132: =IF(Base!AI396="","",Base!AI396) | Q132: =Base!J396 -> Sin saldo útil | R132: =Base!X396 -> 0.42727112 | S132: =Base!K396 -> 0 | T132: =Base!M396 -> Saldo libre menor a S/ 10,000
A133: =SUBTOTAL(103,$B$6:B133) -> 111 | B133: 314 | C133: 2611144: ADQUISICION DE ANALIZADOR DE GASES Y ELECTROLITOS, ASPIRADOR DE SECRECIONES, BOMBA DE INFUSION Y COCHE DE PARO EQUIPADO; ADEMÁS DE OTROS ACTIVOS EN EL(LA) CARLOS MONJE MEDRANO DISTRITO DE JULIACA, PROVINCIA SAN ROMAN, DEPARTAMENTO PUNO | D133: =Base!N397 -> 4219373 | E133: =Base!O397 -> 4183621 | F133: =D133-E133 -> 35751.97 | G133: =Base!Q397 -> 3829328.1 | H133: =D133-G133 -> 390044.92 | I133: =IF(D133=0,0,G133/D133) -> 0.90755856 | J133: =Base!AH397 -> Equipamiento / Contrata | K133: =Base!I397 -> IOARR | L133: =Base!AA397 -> 3305500 | M133: =Base!AB397 -> 177809 | N133: =Base!AC397 -> 150483 | O133: =Base!AD397 -> 0 | P133: =IF(Base!AI397="","",Base!AI397) | Q133: =Base!J397 -> No mover | R133: =Base!X397 -> 0.97847198 | S133: =Base!K397 -> 0 | T133: =Base!M397 -> Devengado 2026 ≥ 90% del PIM
... A148: =SUBTOTAL(103,$B$6:B148) -> 126 | B148: 524 | C148: 2733644: ADQUISICION DE PATRULLEROS Y PATRULLEROS; EN EL(LA) FRENTE POLICIAL PUNO - COMISARIAS EN LAS 13 PROVINCIAS DE LA REGION PUNO, DISTRITO DE PUNO, PROVINCIA PUNO, DEPARTAMENTO PUNO | D148: =Base!N412 -> 25610 | E148: =Base!O412 -> 0 | F148: =D148-E148 -> 25610 | G148: =Base!Q412 -> 0 | H148: =D148-G148 -> 25610 | I148: =IF(D148=0,0,G148/D148) -> 0 | J148: =Base!AH412 -> Expediente técnico | K148: =Base!I412 -> IOARR | L148: =Base!AA412 -> No registrado en cartera | M148: =Base!AB412 -> No registrado en cartera | N148: =Base!AC412 -> No registrado en cartera | O148: =Base!AD412 -> No registrado en cartera | P148: =IF(Base!AI412="","",Base!AI412) | Q148: =Base!J412 -> Con condiciones | R148: =Base!X412 -> 0 | S148: =Base!K412 -> 25610 | T148: =Base!M412 -> Sin Formato 12-B: validar con la OPMI
A149: 22. EDUCACION | D149: =SUM(D150:D161) -> 9798393 | E149: =SUM(E150:E161) -> 7621399.4 | F149: =D149-E149 -> 2176993.6 | G149: =SUM(G150:G161) -> 606651.92 | H149: =D149-G149 -> 9191741.1 | I149: =IF(D149=0,0,G149/D149) -> 0.06191341 | S149: =SUM(S150:S161) -> 2168070.6
A150: =SUBTOTAL(103,$B$6:B150) -> 127 | B150: 512 | C150: 2721991: RENOVACION DE AULA DE EDUCACION PRIMARIA, AMBIENTE ADMINISTRATIVO, SERVICIOS HIGIENICOS Y/O VESTIDORES Y AMBIENTE DE USOS MULTIPLES; ADEMAS DE OTROS ACTIVOS EN CUATRO II.EE. PRIMARIA A NIVEL DISTRITAL (PUNO - SANDIA - SAN PEDRO DE PUTINA PUNCO) | D150: =Base!N413 -> 3254770 | E150: =Base!O413 -> 2925559.5 | F150: =D150-E150 -> 329210.45 | G150: =Base!Q413 -> 0 | H150: =D150-G150 -> 3254770 | I150: =IF(D150=0,0,G150/D150) -> 0 | J150: =Base!AH413 -> Contrata / Expediente técnico / Personal/bienes/servicios | K150: =Base!I413 -> IOARR | L150: =Base!AA413 -> No registrado en cartera | M150: =Base!AB413 -> No registrado en cartera | N150: =Base!AC413 -> No registrado en cartera | O150: =Base!AD413 -> No registrado en cartera | P150: =IF(Base!AI413="","",Base!AI413) | Q150: =Base!J413 -> Con condiciones | R150: =Base!X413 -> 0 | S150: =Base!K413 -> 329210.45 | T150: =Base!M413 -> El 12-B programa S/ 3,254,770 de un PIM de S/ 3,254,770: la UEI debe actualizarlo (el proyecto no está en ningún PMI)
A151: =SUBTOTAL(103,$B$6:B151) -> 128 | B151: 513 | C151: 2721892: CONSTRUCCION DE AULA DE EDUCACION SECUNDARIA, AMBIENTE ADMINISTRATIVO Y SERVICIOS HIGIENICOS Y/O VESTIDORES; ADQUISICION DE MOBILIARIO DE AULA; EN EL(LA) IE PUERTO DE EDEN DISTRITO DE SAN PEDRO DE PUTINA PUNCO, PROVINCIA SANDIA, DEPARTAMENTO PUNO | D151: =Base!N414 -> 1007572 | E151: =Base!O414 -> 838299.38 | F151: =D151-E151 -> 169272.62 | G151: =Base!Q414 -> 0 | H151: =D151-G151 -> 1007572 | I151: =IF(D151=0,0,G151/D151) -> 0 | J151: =Base!AH414 -> Contrata / Expediente técnico / Personal/bienes/servicios | K151: =Base!I414 -> IOARR | L151: =Base!AA414 -> No registrado en cartera | M151: =Base!AB414 -> No registrado en cartera | N151: =Base!AC414 -> No registrado en cartera | O151: =Base!AD414 -> No registrado en cartera | P151: =IF(Base!AI414="","",Base!AI414) | Q151: =Base!J414 -> Con condiciones | R151: =Base!X414 -> 0 | S151: =Base!K414 -> 169272.62 | T151: =Base!M414 -> El 12-B programa S/ 1,007,572 de un PIM de S/ 1,007,572: la UEI debe actualizarlo (el proyecto no está en ningún PMI)
A152: =SUBTOTAL(103,$B$6:B152) -> 129 | B152: 515 | C152: 2719529: RENOVACION DE AULA DE EDUCACION PRIMARIA, SERVICIOS HIGIENICOS Y/O VESTIDORES Y AMBIENTE DE USOS MULTIPLES; ADQUISICION DE MOBILIARIO DE AULA; EN TRES II.EE. PRIMARIA A NIVEL DISTRITAL (PUNO - SANDIA - ALTO INAMBARI) | D152: =Base!N415 -> 1688098 | E152: =Base!O415 -> 1486603.2 | F152: =D152-E152 -> 201494.77 | G152: =Base!Q415 -> 0 | H152: =D152-G152 -> 1688098 | I152: =IF(D152=0,0,G152/D152) -> 0 | J152: =Base!AH415 -> Contrata / Expediente técnico / Personal/bienes/servicios | K152: =Base!I415 -> IOARR | L152: =Base!AA415 -> No registrado en cartera | M152: =Base!AB415 -> No registrado en cartera | N152: =Base!AC415 -> No registrado en cartera | O152: =Base!AD415 -> No registrado en cartera | P152: =IF(Base!AI415="","",Base!AI415) | Q152: =Base!J415 -> Con condiciones | R152: =Base!X415 -> 0 | S152: =Base!K415 -> 201494.77 | T152: =Base!M415 -> El 12-B programa S/ 1,688,098 de un PIM de S/ 1,688,098: la UEI debe actualizarlo (el proyecto no está en ningún PMI)
A153: =SUBTOTAL(103,$B$6:B153) -> 130 | B153: 509 | C153: 2723359: CONSTRUCCION DE AULA DE EDUCACION SECUNDARIA; ADQUISICION DE MOBILIARIO DE AULA; EN EL(LA) IE SECUNDARIA SANTA ROSA DISTRITO DE ALTO INAMBARI, PROVINCIA SANDIA, DEPARTAMENTO PUNO | D153: =Base!N416 -> 680748 | E153: =Base!O416 -> 538302.92 | F153: =D153-E153 -> 142445.08 | G153: =Base!Q416 -> 0 | H153: =D153-G153 -> 680748 | I153: =IF(D153=0,0,G153/D153) -> 0 | J153: =Base!AH416 -> Contrata / Expediente técnico / Personal/bienes/servicios | K153: =Base!I416 -> IOARR | L153: =Base!AA416 -> No registrado en cartera | M153: =Base!AB416 -> No registrado en cartera | N153: =Base!AC416 -> No registrado en cartera | O153: =Base!AD416 -> No registrado en cartera | P153: =IF(Base!AI416="","",Base!AI416) | Q153: =Base!J416 -> Con condiciones | R153: =Base!X416 -> 0 | S153: =Base!K416 -> 142445.08 | T153: =Base!M416 -> El 12-B programa S/ 680,748 de un PIM de S/ 680,748: la UEI debe actualizarlo (el proyecto no está en ningún PMI)
A154: =SUBTOTAL(103,$B$6:B154) -> 131 | B154: 510 | C154: 2721888: CONSTRUCCION DE AULA DE EDUCACION SECUNDARIA; ADQUISICION DE MOBILIARIO DE AULA; EN EL(LA) IE I.E. SECUNDARIA JOSE MARIA ARGUEDAS EN LA LOCALIDAD CCAPUNA, DISTRITO DE SANDIA, PROVINCIA SANDIA, DEPARTAMENTO PUNO | D154: =Base!N417 -> 670100 | E154: =Base!O417 -> 532791.97 | F154: =D154-E154 -> 137308.03 | G154: =Base!Q417 -> 0 | H154: =D154-G154 -> 670100 | I154: =IF(D154=0,0,G154/D154) -> 0 | J154: =Base!AH417 -> Contrata / Expediente técnico / Personal/bienes/servicios | K154: =Base!I417 -> IOARR | L154: =Base!AA417 -> No registrado en cartera | M154: =Base!AB417 -> No registrado en cartera | N154: =Base!AC417 -> No registrado en cartera | O154: =Base!AD417 -> No registrado en cartera | P154: =IF(Base!AI417="","",Base!AI417) | Q154: =Base!J417 -> Con condiciones | R154: =Base!X417 -> 0 | S154: =Base!K417 -> 137308.03 | T154: =Base!M417 -> El 12-B programa S/ 670,100 de un PIM de S/ 670,100: la UEI debe actualizarlo (el proyecto no está en ningún PMI)
A155: =SUBTOTAL(103,$B$6:B155) -> 132 | B155: 511 | C155: 2721886: CONSTRUCCION DE AULA DE EDUCACION INICIAL; ADQUISICION DE MOBILIARIO DE AULA; EN EL(LA) IE INICIAL N° 1048 DE HUENCALLA DISTRITO DE SANDIA, PROVINCIA SANDIA, DEPARTAMENTO PUNO | D155: =Base!N418 -> 388514 | E155: =Base!O418 -> 269223.84 | F155: =D155-E155 -> 119290.16 | G155: =Base!Q418 -> 0 | H155: =D155-G155 -> 388514 | I155: =IF(D155=0,0,G155/D155) -> 0 | J155: =Base!AH418 -> Contrata / Expediente técnico / Personal/bienes/servicios | K155: =Base!I418 -> IOARR | L155: =Base!AA418 -> No registrado en cartera | M155: =Base!AB418 -> No registrado en cartera | N155: =Base!AC418 -> No registrado en cartera | O155: =Base!AD418 -> No registrado en cartera | P155: =IF(Base!AI418="","",Base!AI418) | Q155: =Base!J418 -> Con condiciones | R155: =Base!X418 -> 0 | S155: =Base!K418 -> 119290.16 | T155: =Base!M418 -> El 12-B programa S/ 388,514 de un PIM de S/ 388,514: la UEI debe actualizarlo (el proyecto no está en ningún PMI)
A156: =SUBTOTAL(103,$B$6:B156) -> 133 | B156: 514 | C156: 2721889: CONSTRUCCION DE AULA DE EDUCACION INICIAL Y AMBIENTE ADMINISTRATIVO; ADQUISICION DE MOBILIARIO DE AULA Y EQUIPAMIENTO DE AULA; EN EL(LA) IE 1027 EN LA LOCALIDAD ISILLUMA, DISTRITO DE ALTO INAMBARI, PROVINCIA SANDIA, DEPARTAMENTO PUNO | D156: =Base!N419 -> 542416 | E156: =Base!O419 -> 401911.51 | F156: =D156-E156 -> 140504.49 | G156: =Base!Q419 -> 0 | H156: =D156-G156 -> 542416 | I156: =IF(D156=0,0,G156/D156) -> 0 | J156: =Base!AH419 -> Contrata / Expediente técnico / Personal/bienes/servicios | K156: =Base!I419 -> IOARR | L156: =Base!AA419 -> No registrado en cartera | M156: =Base!AB419 -> No registrado en cartera | N156: =Base!AC419 -> No registrado en cartera | O156: =Base!AD419 -> No registrado en cartera | P156: =IF(Base!AI419="","",Base!AI419) | Q156: =Base!J419 -> Con condiciones | R156: =Base!X419 -> 0 | S156: =Base!K419 -> 140504.49 | T156: =Base!M419 -> El 12-B programa S/ 542,416 de un PIM de S/ 542,416: la UEI debe actualizarlo (el proyecto no está en ningún PMI)
A157: =SUBTOTAL(103,$B$6:B157) -> 134 | B157: 516 | C157: 2729834: CONSTRUCCION DE AULA DE EDUCACION PRIMARIA, SERVICIOS HIGIENICOS Y/O VESTIDORES PARA ESTUDIANTES Y AMBIENTE DE GESTION ADMINISTRATIVA Y DIRECCION; ADQUISICION DE MOBILIARIO DE AULA; EN EL(LA) I.E. 72544 DISTRITO DE ALTO INAMBARI, PROVINCIA SANDIA, | D157: =Base!N420 -> 928545 | E157: =Base!O420 -> 0 | F157: =D157-E157 -> 928545 | G157: =Base!Q420 -> 0 | H157: =D157-G157 -> 928545 | I157: =IF(D157=0,0,G157/D157) -> 0 | J157: =Base!AH420 -> Contrata / Expediente técnico | K157: =Base!I420 -> IOARR | L157: =Base!AA420 -> No registrado en cartera | M157: =Base!AB420 -> No registrado en cartera | N157: =Base!AC420 -> No registrado en cartera | O157: =Base!AD420 -> No registrado en cartera | P157: =IF(Base!AI420="","",Base!AI420) | Q157: =Base!J420 -> Con condiciones | R157: =Base!X420 -> 0 | S157: =Base!K420 -> 928545 | T157: =Base!M420 -> El 12-B programa S/ 928,545 de un PIM de S/ 928,545: la UEI debe actualizarlo (el proyecto no está en ningún PMI)
A158: =SUBTOTAL(103,$B$6:B158) -> 135 | B158: 348 | C158: 2693441: ADQUISICION DE EQUIPO DE AULA DE EDUCACION SECUNDARIA; EN EL(LA) I.E. GLORIOSO SAN CARLOS DISTRITO DE PUNO, PROVINCIA PUNO, DEPARTAMENTO PUNO | D158: =Base!N421 -> 70059 | E158: =Base!O421 -> 70057.9 | F158: =D158-E158 -> 1.1 | G158: =Base!Q421 -> 70029.94 | H158: =D158-G158 -> 29.06 | I158: =IF(D158=0,0,G158/D158) -> 0.99958521 | J158: =Base!AH421 -> Otro (SOFTWARES) / Contrata / Personal/bienes/servicios | K158: =Base!I421 -> IOARR | L158: =Base!AA421 -> 105988 | M158: =Base!AB421 -> 0 | N158: =Base!AC421 -> 35929 | O158: =Base!AD421 -> 0 | P158: =IF(Base!AI421="","",Base!AI421) | Q158: =Base!J421 -> No mover | R158: =Base!X421 -> 0.9519164 | S158: =Base!K421 -> 0 | T158: =Base!M421 -> Devengado 2026 ≥ 90% del PIM
A159: =SUBTOTAL(103,$B$6:B159) -> 136 | B159: 349 | C159: 2692840: ADQUISICION DE EQUIPO DE AULA DE EDUCACION PRIMARIA; EN EL(LA) I.E. GLORIOSO SAN CARLOS DISTRITO DE PUNO, PROVINCIA PUNO, DEPARTAMENTO PUNO | D159: =Base!N422 -> 100785 | E159: =Base!O422 -> 100589.42 | F159: =D159-E159 -> 195.58 | G159: =Base!Q422 -> 88974.89 | H159: =D159-G159 -> 11810.11 | I159: =IF(D159=0,0,G159/D159) -> 0.88281877 | J159: =Base!AH422 -> Contrata / Otro (SOFTWARES) / Personal/bienes/servicios | K159: =Base!I422 -> IOARR | L159: =Base!AA422 -> 155899 | M159: =Base!AB422 -> 0 | N159: =Base!AC422 -> 55114 | O159: =Base!AD422 -> 0 | P159: =IF(Base!AI422="","",Base!AI422) | Q159: =Base!J422 -> Sin saldo útil | R159: =Base!X422 -> 0.87610894 | S159: =Base!K422 -> 0 | T159: =Base!M422 -> Saldo libre menor a S/ 10,000
A160: =SUBTOTAL(103,$B$6:B160) -> 137 | B160: 461 | C160: 2699544: ADQUISICION DE EQUIPAMIENTO DE AULA; EN SIETE II.EE. INICIAL DISTRITO DE SAN JUAN DE SALINAS, PROVINCIA AZANGARO, DEPARTAMENTO PUNO | D160: =Base!N423 -> 195079 | E160: =Base!O423 -> 186354 | F160: =D160-E160 -> 8725 | G160: =Base!Q423 -> 176804.43 | H160: =D160-G160 -> 18274.57 | I160: =IF(D160=0,0,G160/D160) -> 0.90632221 | J160: =Base!AH423 -> Administración directa / Equipamiento / Contrata / Personal/bienes/servicios | K160: =Base!I423 -> IOARR | L160: =Base!AA423 -> 195079 | M160: =Base!AB423 -> 23547 | N160: =Base!AC423 -> 1 | O160: =Base!AD423 -> 0 | P160: =IF(Base!AI423="","",Base!AI423) | Q160: =Base!J423 -> No mover | R160: =Base!X423 -> 0.82550468 | S160: =Base!K423 -> 0 | T160: =Base!M423 -> Devengado 2026 ≥ 90% del PIM
A161: =SUBTOTAL(103,$B$6:B161) -> 138 | B161: 345 | C161: 2699546: ADQUISICION DE EQUIPAMIENTO DE AULA DE INNOVACION PEDAGOGICA; EN OCHO II.EE. PRIMARIA DISTRITO DE SAN JUAN DE SALINAS, PROVINCIA AZANGARO, DEPARTAMENTO PUNO | D161: =Base!N438 -> 271707 | E161: =Base!O438 -> 271705.69 | F161: =D161-E161 -> 1.31 | G161: =Base!Q438 -> 270842.66 | H161: =D161-G161 -> 864.34 | I161: =IF(D161=0,0,G161/D161) -> 0.99681885 | J161: =Base!AH438 -> Equipamiento / Administración directa / Contrata / Personal/bienes/servicios | K161: =Base!I438 -> IOARR | L161: =Base!AA438 -> 267733 | M161: =Base!AB438 -> 20886 | N161: =Base!AC438 -> 0 | O161: =Base!AD438 -> 0 | P161: =IF(Base!AI438="","",Base!AI438) | Q161: =Base!J438 -> No mover | R161: =Base!X438 -> 0.9304428 | S161: =Base!K438 -> 0 | T161: =Base!M438 -> Devengado 2026 ≥ 90% del PIM
A162: 05. ORDEN PUBLICO Y SEGURIDAD | D162: =SUM(D163:D164) -> 11936253 | E162: =SUM(E163:E164) -> 10981994 | F162: =D162-E162 -> 954259.22 | G162: =SUM(G163:G164) -> 5861139.6 | H162: =D162-G162 -> 6075113.4 | I162: =IF(D162=0,0,G162/D162) -> 0.49103681 | S162: =SUM(S163:S164) -> 0
A163: =SUBTOTAL(103,$B$6:B163) -> 139 | B163: 3 | C163: 2683535: MEJORAMIENTO DEL SERVICIO DE SEGURIDAD CIUDADANA LOCAL EN 73 UNIDADES PRODUCTORAS 73 DISTRITOS DE 11 PROVINCIAS DEL DEPARTAMENTO DE PUNO 11 PROVINCIAS DEL DEPARTAMENTO DE PUNO | D163: =Base!N424 -> 6654893 | E163: =Base!O424 -> 6543805.7 | F163: =D163-E163 -> 111087.31 | G163: =Base!Q424 -> 5720623 | H163: =D163-G163 -> 934270.03 | I163: =IF(D163=0,0,G163/D163) -> 0.85961156 | J163: =Base!AH424 -> Equipamiento / Contrata / Personal/bienes/servicios | K163: =Base!I424 -> Proyecto de inversión | L163: =Base!AA424 -> 100000 | M163: =Base!AB424 -> 218816 | N163: =Base!AC424 -> 309853 | O163: =Base!AD424 -> 0 | P163: =IF(Base!AI424="","",Base!AI424) | Q163: =Base!J424 -> Sin saldo útil | R163: =Base!X424 -> 0.83885732 | S163: =Base!K424 -> 0 | T163: =Base!M424 -> Saldo libre menor a S/ 10,000
A164: =SUBTOTAL(103,$B$6:B164) -> 140 | B164: 286 | C164: 2685431: ADQUISICION DE AMBULANCIA URBANA, CAMIONETA, CAMIÓN PLATAFORMA Y CAMION CISTERNA; ADEMÁS DE OTROS ACTIVOS EN CINCO COMPAÑÍA DE BOMBEROS A NIVEL DEPARTAMENTAL (PUNO) | D164: =Base!N425 -> 5281360 | E164: =Base!O425 -> 4438188.1 | F164: =D164-E164 -> 843171.91 | G164: =Base!Q425 -> 140516.63 | H164: =D164-G164 -> 5140843.4 | I164: =IF(D164=0,0,G164/D164) -> 0.026606145 | J164: =Base!AH425 -> Equipamiento / Contrata / Personal/bienes/servicios | K164: =Base!I425 -> IOARR | L164: =Base!AA425 -> 5358341 | M164: =Base!AB425 -> 6902686 | N164: =Base!AC425 -> 800000 | O164: =Base!AD425 -> 800000 | P164: =IF(Base!AI425="","",Base!AI425) | Q164: =Base!J425 -> Sin saldo útil | R164: =Base!X425 -> 0.0067445677 | S164: =Base!K425 -> 0 | T164: =Base!M425 -> Saldo libre menor a S/ 10,000
A165: 23. PROTECCION SOCIAL | D165: =SUM(D166:D166) -> 0 | E165: =SUM(E166:E166) -> 0 | F165: =D165-E165 -> 0 | G165: =SUM(G166:G166) -> 0 | H165: =D165-G165 -> 0 | I165: =IF(D165=0,0,G165/D165) -> 0 | S165: =SUM(S166:S166) -> 0
A166: =SUBTOTAL(103,$B$6:B166) -> 141 | B166: 266 | C166: 2608728: REPARACION DE AMBIENTE DE RESIDENCIA; ADQUISICION DE EQUIPAMIENTO DE AMBIENTES DE BIENESTAR Y SERVICIOS GENERALES Y MOBILIARIO DE AMBIENTES DE BIENESTAR Y SERVICIOS GENERALES; EN EL(LA) ALDEA INFANTIL NIÑO SAN SALVADOR DEL DISTRITO DE CAPACHICA, PROVINCIA PUNO, DEPARTAMENTO PUNO | D166: =Base!N426 -> 0 | E166: =Base!O426 -> 0 | F166: =D166-E166 -> 0 | G166: =Base!Q426 -> 0 | H166: =D166-G166 -> 0 | I166: =IF(D166=0,0,G166/D166) -> 0 | J166: =Base!AH426 -> Contrata | K166: =Base!I426 -> IOARR | L166: =Base!AA426 -> 200000 | M166: =Base!AB426 -> 0 | N166: =Base!AC426 -> 0 | O166: =Base!AD426 -> 0 | P166: =IF(Base!AI426="","",Base!AI426) | Q166: =Base!J426 -> Sin PIM | R166: =Base!X426 -> 0.064582631 | S166: =Base!K426 -> 0 | T166: =Base!M426 -> PIM igual a 0
...

Sheet Sin clasificar
C1: ANEXO N° 03
B2: COMPORTAMIENTO DE EJECUCIÓN DE PROYECTOS DE INVERSION PUBLICA DEL AÑO FISCAL 2026 · PROYECTOS SIN GERENCIA ASIGNADA · AL 09/10/2026
A4: N° | B4: META | C4: PROYECTO | D4: PIM 2026 (A) | E4: CERTIFICACIÓN (B) | F4: SALDO (A-B) | G4: DEVENGADO ( C ) | H4: SALDO (A-C) | I4: DEVEN % | J4: MODALIDAD DE EJECUCIÓN | K4: TIPO DE INVERSIÓN | L4: Monto Año 2026 (S/) | M4: Monto Año 2027 (S/) | N4: Monto Año 2028 (S/) | O4: Monto Año 2029 (S/) | P4: BASE LEGAL | Q4: SEMÁFORO | R4: % AVANCE FINANCIERO ACUMULADO | S4: DISPONIBLE LEGAL (S/) | T4: MOTIVO / CONDICIONES
A5: SIN CLASIFICAR (pendiente de asignar gerencia) | D5: =D6+D8 -> 120166 | E5: =E6+E8 -> 19362 | F5: =D5-E5 -> 100804 | G5: =G6+G8 -> 18148.25 | H5: =D5-G5 -> 102017.75 | I5: =IF(D5=0,0,G5/D5) -> 0.1510265 | S5: =S6+S8 -> 0
A6: 20. SALUD | D6: =SUM(D7:D7) -> 100000 | E6: =SUM(E7:E7) -> 0 | F6: =D6-E6 -> 100000 | G6: =SUM(G7:G7) -> 0 | H6: =D6-G6 -> 100000 | I6: =IF(D6=0,0,G6/D6) -> 0 | S6: =SUM(S7:S7) -> 0
A7: =SUBTOTAL(103,$B$6:B7) -> 1 | B7: 533 | C7: 2681141: MEJORAMIENTO DEL SERVICIO DE ATENCIÓN DE SALUD BÁSICOS EN HUACULLANI DISTRITO DE HUACULLANI DE LA PROVINCIA DE CHUCUITO DEL DEPARTAMENTO DE PUNO | D7: =Base!N440 -> 100000 | E7: =Base!O440 -> 0 | F7: =D7-E7 -> 100000 | G7: =Base!Q440 -> 0 | H7: =D7-G7 -> 100000 | I7: =IF(D7=0,0,G7/D7) -> 0 | J7: =Base!AH440 -> Expediente técnico | K7: =Base!I440 -> Proyecto de inversión | L7: =Base!AA440 -> 100000 | M7: =Base!AB440 -> 0 | N7: =Base!AC440 -> 3681052 | O7: =Base!AD440 -> 4156140 | P7: =IF(Base!AI440="","",Base!AI440) | Q7: =Base!J440 -> Sin saldo útil | R7: =Base!X440 -> 0 | S7: =Base!K440 -> 0 | T7: =Base!M440 -> Saldo libre menor a S/ 10,000
A8: 22. EDUCACION | D8: =SUM(D9:D9) -> 20166 | E8: =SUM(E9:E9) -> 19362 | F8: =D8-E8 -> 804 | G8: =SUM(G9:G9) -> 18148.25 | H8: =D8-G8 -> 2017.75 | I8: =IF(D8=0,0,G8/D8) -> 0.89994297 | S8: =SUM(S9:S9) -> 0
A9: =SUBTOTAL(103,$B$6:B9) -> 2 | B9: 499 | C9: 2231037: MEJORAMIENTO DE LOS SERVICIOS EDUCATIVOS EN LA I.E.I. N 596 MUNAYPATA DEL CENTRO POBLADO DE MUNAYPATA, DISTRITO DE OLLACHEA PROVINCIA DE CARABAYA PUNO | D9: =Base!N441 -> 20166 | E9: =Base!O441 -> 19362 | F9: =D9-E9 -> 804 | G9: =Base!Q441 -> 18148.25 | H9: =D9-G9 -> 2017.75 | I9: =IF(D9=0,0,G9/D9) -> 0.89994297 | J9: =Base!AH441 -> Contrata / Personal/bienes/servicios | K9: =Base!I441 -> Proyecto de inversión | L9: =Base!AA441 -> 20166 | M9: =Base!AB441 -> 0 | N9: =Base!AC441 -> 0 | O9: =Base!AD441 -> 0 | P9: =IF(Base!AI441="","",Base!AI441) | Q9: =Base!J441 -> No mover | R9: =Base!X441 -> 0.92298233 | S9: =Base!K441 -> 0 | T9: =Base!M441 -> Avance financiero acumulado 92% (> 90%)
A11: TOTAL PROYECTOS SIN GERENCIA ASIGNADA | D11: =D5 -> 120166 | E11: =E5 -> 19362 | F11: =D11-E11 -> 100804 | G11: =G5 -> 18148.25 | H11: =D11-G11 -> 102017.75 | I11: =IF(D11=0,0,G11/D11) -> 0.1510265 | S11: =S5 -> 0

Sheet Otras UE
C1: ANEXO N° 04
B2: COMPORTAMIENTO DE EJECUCIÓN DE PROYECTOS DE INVERSION PUBLICA DEL AÑO FISCAL 2026 · OTRAS UNIDADES EJECUTORAS · AL 09/10/2026
A4: N° | B4: META | C4: PROYECTO | D4: PIM 2026 (A) | E4: CERTIFICACIÓN (B) | F4: SALDO (A-B) | G4: DEVENGADO ( C ) | H4: SALDO (A-C) | I4: DEVEN % | J4: MODALIDAD DE EJECUCIÓN | K4: TIPO DE INVERSIÓN | L4: Monto Año 2026 (S/) | M4: Monto Año 2027 (S/) | N4: Monto Año 2028 (S/) | O4: Monto Año 2029 (S/) | P4: BASE LEGAL | Q4: SEMÁFORO | R4: % AVANCE FINANCIERO ACUMULADO | S4: DISPONIBLE LEGAL (S/) | T4: MOTIVO / CONDICIONES
A5: 002. REGION PUNO-PESQUERIA | D5: =D6+D9 -> 2582404 | E5: =E6+E9 -> 1853925.8 | F5: =D5-E5 -> 728478.18 | G5: =G6+G9 -> 1594267.1 | H5: =D5-G5 -> 988136.88 | I5: =IF(D5=0,0,G5/D5) -> 0.61735775 | S5: =S6+S9 -> 45000
A6: 11. PESCA | D6: =SUM(D7:D8) -> 2462454 | E6: =SUM(E7:E8) -> 1739634.6 | F6: =D6-E6 -> 722819.4 | G6: =SUM(G7:G8) -> 1523975.9 | H6: =D6-G6 -> 938478.1 | I6: =IF(D6=0,0,G6/D6) -> 0.61888502 | S6: =SUM(S7:S8) -> 45000
A7: =SUBTOTAL(103,$B$6:B7) -> 1 | B7: 5 | C7: 2336682: RECUPERACION DE LA BIOMASA DEL CARACHI GRIS Y AMARILLO EN ZONAS DE DESOVE DE LA CUENCA DEL LAGO TITICACA DE LA REGION PUNO | D7: =Base!N442 -> 2417454 | E7: =Base!O442 -> 1739634.6 | F7: =D7-E7 -> 677819.4 | G7: =Base!Q442 -> 1523975.9 | H7: =D7-G7 -> 893478.1 | I7: =IF(D7=0,0,G7/D7) -> 0.63040534 | J7: =Base!AH442 -> Contrata / Personal/bienes/servicios / Equipamiento | K7: =Base!I442 -> Proyecto de inversión | L7: =Base!AA442 -> 1050000 | M7: =Base!AB442 -> 2062045 | N7: =Base!AC442 -> 1715201 | O7: =Base!AD442 -> 0 | P7: =IF(Base!AI442="","",Base!AI442) | Q7: =Base!J442 -> Sin saldo útil | R7: =Base!X442 -> 0.60532851 | S7: =Base!K442 -> 0 | T7: =Base!M442 -> Saldo libre menor a S/ 10,000
A8: =SUBTOTAL(103,$B$6:B8) -> 2 | B8: 24 | C8: 2714101: (EXPEDIENTE TECNICO - nombre no disponible en fuentes) | D8: =Base!N444 -> 45000 | E8: =Base!O444 -> 0 | F8: =D8-E8 -> 45000 | G8: =Base!Q444 -> 0 | H8: =D8-G8 -> 45000 | I8: =IF(D8=0,0,G8/D8) -> 0 | J8: =Base!AH444 -> Expediente técnico | K8: =Base!I444 -> IOARR | L8: =Base!AA444 -> No registrado en cartera | M8: =Base!AB444 -> No registrado en cartera | N8: =Base!AC444 -> No registrado en cartera | O8: =Base!AD444 -> No registrado en cartera | P8: =IF(Base!AI444="","",Base!AI444) | Q8: =Base!J444 -> Con condiciones | R8: =Base!X444 -> 0 | S8: =Base!K444 -> 45000 | T8: =Base!M444 -> El 12-B programa S/ 1,346,495 de un PIM de S/ 45,000: la UEI debe actualizarlo (el proyecto no está en ningún PMI)
A9: 14. INDUSTRIA | D9: =SUM(D10:D11) -> 119950 | E9: =SUM(E10:E11) -> 114291.22 | F9: =D9-E9 -> 5658.78 | G9: =SUM(G10:G11) -> 70291.22 | H9: =D9-G9 -> 49658.78 | I9: =IF(D9=0,0,G9/D9) -> 0.58600434 | S9: =SUM(S10:S11) -> 0
A10: =SUBTOTAL(103,$B$6:B10) -> 3 | B10: 15 | C10: 2230619: MEJORAMIENTO DE LA PRODUCCIÓN Y PRODUCTIVIDAD DE LAS MYPE DE LAS PRINCIPALES LINEAS DE PRODUCCION EN LAS PROVINCIAS DE PUNO, SAN ROMÁN Y EL COLLAO DE LA REGIÓN PUNO | D10: =Base!N443 -> 119950 | E10: =Base!O443 -> 114291.22 | F10: =D10-E10 -> 5658.78 | G10: =Base!Q443 -> 70291.22 | H10: =D10-G10 -> 49658.78 | I10: =IF(D10=0,0,G10/D10) -> 0.58600434 | J10: =Base!AH443 -> Contrata | K10: =Base!I443 -> Proyecto de inversión | L10: =Base!AA443 -> 287404 | M10: =Base!AB443 -> 77681 | N10: =Base!AC443 -> 0 | O10: =Base!AD443 -> 0 | P10: =IF(Base!AI443="","",Base!AI443) | Q10: =Base!J443 -> No mover | R10: =Base!X443 -> 0.94084791 | S10: =Base!K443 -> 0 | T10: =Base!M443 -> Avance financiero acumulado 94% (> 90%)
A11: =SUBTOTAL(103,$B$6:B11) -> 4 | B11: 14 | C11: 2230619: MEJORAMIENTO DE LA PRODUCCIÓN Y PRODUCTIVIDAD DE LAS MYPE DE LAS PRINCIPALES LINEAS DE PRODUCCION EN LAS PROVINCIAS DE PUNO, SAN ROMÁN Y EL COLLAO DE LA REGIÓN PUNO | D11: =Base!N445 -> 0 | E11: =Base!O445 -> 0 | F11: =D11-E11 -> 0 | G11: =Base!Q445 -> 0 | H11: =D11-G11 -> 0 | I11: =IF(D11=0,0,G11/D11) -> 0 | J11: =Base!AH445 -> Contrata | K11: =Base!I445 -> Proyecto de inversión | L11: =Base!AA445 -> 287404 | M11: =Base!AB445 -> 77681 | N11: =Base!AC445 -> 0 | O11: =Base!AD445 -> 0 | P11: =IF(Base!AI445="","",Base!AI445) | Q11: =Base!J445 -> Sin PIM | R11: =Base!X445 -> 0.94084791 | S11: =Base!K445 -> 0 | T11: =Base!M445 -> PIM igual a 0
A12: 003. REGION PUNO-PROGRAMA REGIONAL DE RIEGO Y DRENAJE | D12: =D13+D54 -> 55637342 | E12: =E13+E54 -> 51017385 | F12: =D12-E12 -> 4619956.5 | G12: =G13+G54 -> 33578062 | H12: =D12-G12 -> 22059280 | I12: =IF(D12=0,0,G12/D12) -> 0.60351664 | S12: =S13+S54 -> 750170.69
A13: 10. AGROPECUARIA | D13: =SUM(D14:D53) -> 55637342 | E13: =SUM(E14:E53) -> 51017385 | F13: =D13-E13 -> 4619956.5 | G13: =SUM(G14:G53) -> 33578062 | H13: =D13-G13 -> 22059280 | I13: =IF(D13=0,0,G13/D13) -> 0.60351664 | S13: =SUM(S14:S53) -> 750170.69
A14: =SUBTOTAL(103,$B$6:B14) -> 5 | B14: 40 | C14: 2651742: MEJORAMIENTO Y AMPLIACION DEL SERVICIO DE PROVISIÓN DE AGUA PARA RIEGO EN LA MICROCUENCA DEL RÍO CONDORIRI DISTRITO DE AZANGARO DE LA PROVINCIA DE AZANGARO DEL DEPARTAMENTO DE PUNO | D14: =Base!N446 -> 8376232 | E14: =Base!O446 -> 7854544.8 | F14: =D14-E14 -> 521687.23 | G14: =Base!Q446 -> 87757.47 | H14: =D14-G14 -> 8288474.5 | I14: =IF(D14=0,0,G14/D14) -> 0.010476963 | J14: =Base!AH446 -> Administración directa / Personal/bienes/servicios / Equipamiento / Contrata | K14: =Base!I446 -> Proyecto de inversión | L14: =Base!AA446 -> 5730000 | M14: =Base!AB446 -> 7379001 | N14: =Base!AC446 -> 1300000 | O14: =Base!AD446 -> 1500000 | P14: =IF(Base!AI446="","",Base!AI446) | Q14: =Base!J446 -> Sin saldo útil | R14: =Base!X446 -> 0.074652761 | S14: =Base!K446 -> 0 | T14: =Base!M446 -> Saldo libre menor a S/ 10,000
A15: =SUBTOTAL(103,$B$6:B15) -> 6 | B15: 3 | C15: 2454391: AMPLIACION DEL SERVICIO DE AGUA PARA RIEGO MEDIANTE LA CONSTRUCCIÓN DE LA REPRESA SAPANCCOTA DEL DISTRITO DE PUCARA - PROVINCIA DE LAMPA - DEPARTAMENTO DE PUNO | D15: =Base!N447 -> 7885949 | E15: =Base!O447 -> 7581523.9 | F15: =D15-E15 -> 304425.13 | G15: =Base!Q447 -> 6423232.3 | H15: =D15-G15 -> 1462716.7 | I15: =IF(D15=0,0,G15/D15) -> 0.81451608 | J15: =Base!AH447 -> Administración directa / Contrata / Personal/bienes/servicios / Equipamiento | K15: =Base!I447 -> Proyecto de inversión | L15: =Base!AA447 -> 2780000 | M15: =Base!AB447 -> 108325 | N15: =Base!AC447 -> 0 | O15: =Base!AD447 -> 0 | P15: =IF(Base!AI447="","",Base!AI447) | Q15: =Base!J447 -> Con condiciones | R15: =Base!X447 -> 0.85712275 | S15: =Base!K447 -> 304204.25 | T15: =Base!M447 -> Está programado en el PMI 2026 · Tiene monto en el PMI 2027 (S/ 108,325)
A16: =SUBTOTAL(103,$B$6:B16) -> 7 | B16: 12 | C16: 2566500: MEJORAMIENTO Y AMPLIACION DEL SISTEMA DE RIEGO CHAJANA DEL DISTRITO DE ACORA - PROVINCIA DE PUNO - DEPARTAMENTO DE PUNO | D16: =Base!N448 -> 7723291 | E16: =Base!O448 -> 7350044 | F16: =D16-E16 -> 373246.95 | G16: =Base!Q448 -> 5496208.6 | H16: =D16-G16 -> 2227082.4 | I16: =IF(D16=0,0,G16/D16) -> 0.71164075 | J16: =Base!AH448 -> Administración directa / Contrata / Personal/bienes/servicios | K16: =Base!I448 -> Proyecto de inversión | L16: =Base!AA448 -> 4665000 | M16: =Base!AB448 -> 62456 | N16: =Base!AC448 -> 0 | O16: =Base!AD448 -> 0 | P16: =IF(Base!AI448="","",Base!AI448) | Q16: =Base!J448 -> Con condiciones | R16: =Base!X448 -> 0.76208467 | S16: =Base!K448 -> 356798.11 | T16: =Base!M448 -> Está programado en el PMI 2026 · Tiene monto en el PMI 2027 (S/ 62,456)
A17: =SUBTOTAL(103,$B$6:B17) -> 8 | B17: 33 | C17: 2651742: MEJORAMIENTO Y AMPLIACION DEL SERVICIO DE PROVISIÓN DE AGUA PARA RIEGO EN LA MICROCUENCA DEL RÍO CONDORIRI DISTRITO DE AZANGARO DE LA PROVINCIA DE AZANGARO DEL DEPARTAMENTO DE PUNO | D17: =Base!N449 -> 5353000 | E17: =Base!O449 -> 4519176.4 | F17: =D17-E17 -> 833823.55 | G17: =Base!Q449 -> 1249313.7 | H17: =D17-G17 -> 4103686.3 | I17: =IF(D17=0,0,G17/D17) -> 0.23338571 | J17: =Base!AH449 -> Administración directa / Contrata / Personal/bienes/servicios / Equipamiento | K17: =Base!I449 -> Proyecto de inversión | L17: =Base!AA449 -> 5730000 | M17: =Base!AB449 -> 7379001 | N17: =Base!AC449 -> 1300000 | O17: =Base!AD449 -> 1500000 | P17: =IF(Base!AI449="","",Base!AI449) | Q17: =Base!J449 -> Sin saldo útil | R17: =Base!X449 -> 0.074652761 | S17: =Base!K449 -> 0 | T17: =Base!M449 -> Saldo libre menor a S/ 10,000
A18: =SUBTOTAL(103,$B$6:B18) -> 9 | B18: 6 | C18: 2477014: CREACION DEL SERVICIO DE AGUA PARA RIEGO TECNIFICADO EN LAS COMUNIDADES DE IPARO, ARICATO, QUENEQUE, MORORIA, CCAPUNA Y APABUCO DEL DISTRITO DE SANDIA - PROVINCIA DE SANDIA - DEPARTAMENTO DE PUNO | D18: =Base!N450 -> 5062649 | E18: =Base!O450 -> 4791585.1 | F18: =D18-E18 -> 271063.87 | G18: =Base!Q450 -> 4676286.7 | H18: =D18-G18 -> 386362.29 | I18: =IF(D18=0,0,G18/D18) -> 0.92368377 | J18: =Base!AH450 -> Administración directa / Contrata / Equipamiento / Personal/bienes/servicios | K18: =Base!I450 -> Proyecto de inversión | L18: =Base!AA450 -> 1750000 | M18: =Base!AB450 -> 0 | N18: =Base!AC450 -> 0 | O18: =Base!AD450 -> 0 | P18: =IF(Base!AI450="","",Base!AI450) | Q18: =Base!J450 -> No mover | R18: =Base!X450 -> 0.98119187 | S18: =Base!K450 -> 0 | T18: =Base!M450 -> Devengado 2026 ≥ 90% del PIM
A19: =SUBTOTAL(103,$B$6:B19) -> 10 | B19: 8 | C19: 2540745: MEJORAMIENTO Y AMPLIACION DEL SERVICIO DE AGUA PARA LOS SISTEMAS DE RIEGO HUALLATIRI, HUAYRAPATA Y HUARANCA GRANDE DEL DISTRITO DE HUAYRAPATA - PROVINCIA DE MOHO - DEPARTAMENTO DE PUNO | D19: =Base!N451 -> 4860569 | E19: =Base!O451 -> 4527702.8 | F19: =D19-E19 -> 332866.25 | G19: =Base!Q451 -> 4364263.5 | H19: =D19-G19 -> 496305.55 | I19: =IF(D19=0,0,G19/D19) -> 0.89789147 | J19: =Base!AH451 -> Administración directa / Contrata / Personal/bienes/servicios | K19: =Base!I451 -> Proyecto de inversión | L19: =Base!AA451 -> 1580000 | M19: =Base!AB451 -> 285490 | N19: =Base!AC451 -> 0 | O19: =Base!AD451 -> 0 | P19: =IF(Base!AI451="","",Base!AI451) | Q19: =Base!J451 -> No mover | R19: =Base!X451 -> 0.93568216 | S19: =Base!K451 -> 0 | T19: =Base!M451 -> Avance financiero acumulado 94% (> 90%)
A20: =SUBTOTAL(103,$B$6:B20) -> 11 | B20: 9 | C20: 2540745: MEJORAMIENTO Y AMPLIACION DEL SERVICIO DE AGUA PARA LOS SISTEMAS DE RIEGO HUALLATIRI, HUAYRAPATA Y HUARANCA GRANDE DEL DISTRITO DE HUAYRAPATA - PROVINCIA DE MOHO - DEPARTAMENTO DE PUNO | D20: =Base!N452 -> 3664997 | E20: =Base!O452 -> 3623868 | F20: =D20-E20 -> 41129.02 | G20: =Base!Q452 -> 3096526.7 | H20: =D20-G20 -> 568470.32 | I20: =IF(D20=0,0,G20/D20) -> 0.84489201 | J20: =Base!AH452 -> Administración directa / Contrata / Personal/bienes/servicios | K20: =Base!I452 -> Proyecto de inversión | L20: =Base!AA452 -> 1580000 | M20: =Base!AB452 -> 285490 | N20: =Base!AC452 -> 0 | O20: =Base!AD452 -> 0 | P20: =IF(Base!AI452="","",Base!AI452) | Q20: =Base!J452 -> No mover | R20: =Base!X452 -> 0.93568216 | S20: =Base!K452 -> 0 | T20: =Base!M452 -> Avance financiero acumulado 94% (> 90%)
A21: =SUBTOTAL(103,$B$6:B21) -> 12 | B21: 28 | C21: 2651742: MEJORAMIENTO Y AMPLIACION DEL SERVICIO DE PROVISIÓN DE AGUA PARA RIEGO EN LA MICROCUENCA DEL RÍO CONDORIRI DISTRITO DE AZANGARO DE LA PROVINCIA DE AZANGARO DEL DEPARTAMENTO DE PUNO | D21: =Base!N453 -> 3422000 | E21: =Base!O453 -> 2189475.5 | F21: =D21-E21 -> 1232524.5 | G21: =Base!Q453 -> 706719.22 | H21: =D21-G21 -> 2715280.8 | I21: =IF(D21=0,0,G21/D21) -> 0.20652227 | J21: =Base!AH453 -> Administración directa / Contrata / Personal/bienes/servicios | K21: =Base!I453 -> Proyecto de inversión | L21: =Base!AA453 -> 5730000 | M21: =Base!AB453 -> 7379001 | N21: =Base!AC453 -> 1300000 | O21: =Base!AD453 -> 1500000 | P21: =IF(Base!AI453="","",Base!AI453) | Q21: =Base!J453 -> Sin saldo útil | R21: =Base!X453 -> 0.074652761 | S21: =Base!K453 -> 0 | T21: =Base!M453 -> Saldo libre menor a S/ 10,000
A22: =SUBTOTAL(103,$B$6:B22) -> 13 | B22: 5 | C22: 2470845: MEJORAMIENTO Y AMPLIACION DEL SERVICIO DE AGUA PARA RIEGO TECNIFICADO EN LAS COMUNIDADES DE SAN JUAN DE TAHUACO Y MACHACMARCA DEL DISTRITO DE YUNGUYO - PROVINCIA DE YUNGUYO - DEPARTAMENTO DE PUNO | D22: =Base!N454 -> 1998145 | E22: =Base!O454 -> 1935732.3 | F22: =D22-E22 -> 62412.69 | G22: =Base!Q454 -> 1849231.4 | H22: =D22-G22 -> 148913.65 | I22: =IF(D22=0,0,G22/D22) -> 0.92547405 | J22: =Base!AH454 -> Administración directa / Contrata / Personal/bienes/servicios / Equipamiento | K22: =Base!I454 -> Proyecto de inversión | L22: =Base!AA454 -> 1850000 | M22: =Base!AB454 -> 0 | N22: =Base!AC454 -> 0 | O22: =Base!AD454 -> 0 | P22: =IF(Base!AI454="","",Base!AI454) | Q22: =Base!J454 -> No mover | R22: =Base!X454 -> 0.94127153 | S22: =Base!K454 -> 0 | T22: =Base!M454 -> Devengado 2026 ≥ 90% del PIM
A23: =SUBTOTAL(103,$B$6:B23) -> 14 | B23: 21 | C23: 2477014: CREACION DEL SERVICIO DE AGUA PARA RIEGO TECNIFICADO EN LAS COMUNIDADES DE IPARO, ARICATO, QUENEQUE, MORORIA, CCAPUNA Y APABUCO DEL DISTRITO DE SANDIA - PROVINCIA DE SANDIA - DEPARTAMENTO DE PUNO | D23: =Base!N455 -> 1888290 | E23: =Base!O455 -> 1878163.8 | F23: =D23-E23 -> 10126.19 | G23: =Base!Q455 -> 1807695.8 | H23: =D23-G23 -> 80594.22 | I23: =IF(D23=0,0,G23/D23) -> 0.95731894 | J23: =Base!AH455 -> Administración directa / Contrata / Personal/bienes/servicios | K23: =Base!I455 -> Proyecto de inversión | L23: =Base!AA455 -> 1750000 | M23: =Base!AB455 -> 0 | N23: =Base!AC455 -> 0 | O23: =Base!AD455 -> 0 | P23: =IF(Base!AI455="","",Base!AI455) | Q23: =Base!J455 -> No mover | R23: =Base!X455 -> 0.98119187 | S23: =Base!K455 -> 0 | T23: =Base!M455 -> Devengado 2026 ≥ 90% del PIM
A24: =SUBTOTAL(103,$B$6:B24) -> 15 | B24: 17 | C24: 2651742: MEJORAMIENTO Y AMPLIACION DEL SERVICIO DE PROVISIÓN DE AGUA PARA RIEGO EN LA MICROCUENCA DEL RÍO CONDORIRI DISTRITO DE AZANGARO DE LA PROVINCIA DE AZANGARO DEL DEPARTAMENTO DE PUNO | D24: =Base!N456 -> 1733600 | E24: =Base!O456 -> 1695198.5 | F24: =D24-E24 -> 38401.49 | G24: =Base!Q456 -> 1216702.3 | H24: =D24-G24 -> 516897.69 | I24: =IF(D24=0,0,G24/D24) -> 0.70183567 | J24: =Base!AH456 -> Administración directa / Contrata / Personal/bienes/servicios | K24: =Base!I456 -> Proyecto de inversión | L24: =Base!AA456 -> 5730000 | M24: =Base!AB456 -> 7379001 | N24: =Base!AC456 -> 1300000 | O24: =Base!AD456 -> 1500000 | P24: =IF(Base!AI456="","",Base!AI456) | Q24: =Base!J456 -> Sin saldo útil | R24: =Base!X456 -> 0.074652761 | S24: =Base!K456 -> 0 | T24: =Base!M456 -> Saldo libre menor a S/ 10,000
A25: =SUBTOTAL(103,$B$6:B25) -> 16 | B25: 36 | C25: 2001621: (ESTUDIOS DE PRE - INVERSION - nombre no disponible en fuentes) | D25: =Base!N457 -> 390300 | E25: =Base!O457 -> 369779.36 | F25: =D25-E25 -> 20520.64 | G25: =Base!Q457 -> 221110.7 | H25: =D25-G25 -> 169189.3 | I25: =IF(D25=0,0,G25/D25) -> 0.56651473 | J25: =Base!AH457 -> Estudio de preinversión | K25: =Base!I457 -> Sin dato | L25: =Base!AA457 -> No registrado en cartera | M25: =Base!AB457 -> No registrado en cartera | N25: =Base!AC457 -> No registrado en cartera | O25: =Base!AD457 -> No registrado en cartera | P25: =IF(Base!AI457="","",Base!AI457) | Q25: =Base!J457 -> Bolsa genérica | R25: =Base!X457 -> s/d | S25: =Base!K457 -> 20520.64 | T25: =Base!M457 -> Código genérico (no es una inversión con CUI propio)
... A51: =SUBTOTAL(103,$B$6:B51) -> 42 | B51: 11 | C51: 2541758: CREACION DEL SERVICIO DE AGUA PARA RIEGO MEDIANTE SIEMBRA Y COSECHA DE AGUA EN LAS COMUNIDADES DE CAYATTOCCO, CARABAYA, QQUETE Y UPINA DEL DISTRITO DE ITUATA - PROVINCIA DE CARABAYA - DEPARTAMENTO DE PUNO | D51: =Base!N483 -> 0 | E51: =Base!O483 -> 0 | F51: =D51-E51 -> 0 | G51: =Base!Q483 -> 0 | H51: =D51-G51 -> 0 | I51: =IF(D51=0,0,G51/D51) -> 0 | J51: =Base!AH483 -> Administración directa | K51: =Base!I483 -> Proyecto de inversión | L51: =Base!AA483 -> 1315000 | M51: =Base!AB483 -> 0 | N51: =Base!AC483 -> 0 | O51: =Base!AD483 -> 0 | P51: =IF(Base!AI483="","",Base!AI483) | Q51: =Base!J483 -> Sin PIM | R51: =Base!X483 -> 0.021772857 | S51: =Base!K483 -> 0 | T51: =Base!M483 -> PIM igual a 0
