Workbook

Sheet Resumen
A1: Proyectos de inversión · GORE Puno · mapeo de disponibilidad · al 07/10/2026
A2: Montos en soles. Todo se calcula desde la hoja Base. Los umbrales se cambian en la hoja Config.
A3: CIFRAS DESACTUALIZADAS: copia de la API del MEF del 07/10/2026 04:08. Suba el reporte SIAF (.xls) o espere a que la API se recupere.
A4: Por unidad ejecutora
A5: Unidad | B5: Proyectos (UE-CUI-meta) | C5: PIM 2026 | D5: Certificación | E5: Compromiso anual | F5: Devengado | G5: Saldo sin certificar | H5: Disponible (PIM − comprom.) | I5: PIM · Sin certificar | J5: PIM · Solo certificado | K5: PIM · Parcialmente comprometido | L5: PIM · Mayormente comprometido | M5: PIM · Ejecutado | N5: PIM · Sin PIM
A6: 001. REGION PUNO-SEDE CENTRAL | B6: =COUNTIFS(Base!$A$5:$A$509,"001") -> 442 | C6: =SUMIFS(Base!$I$5:$I$509,Base!$A$5:$A$509,"001") -> 905026984 | D6: =SUMIFS(Base!$J$5:$J$509,Base!$A$5:$A$509,"001") -> 8.4314313e+08 | E6: =SUMIFS(Base!$K$5:$K$509,Base!$A$5:$A$509,"001") -> 6.1616797e+08 | F6: =SUMIFS(Base!$L$5:$L$509,Base!$A$5:$A$509,"001") -> 4.3355968e+08 | G6: =C6-D6 -> 61883857 | H6: =SUMIFS(Base!$T$5:$T$509,Base!$A$5:$A$509,"001") -> 2.8488673e+08 | I6: =SUMIFS(Base!$I$5:$I$509,Base!$A$5:$A$509,"001",Base!$R$5:$R$509,"Sin certificar") -> 13108238 | J6: =SUMIFS(Base!$I$5:$I$509,Base!$A$5:$A$509,"001",Base!$R$5:$R$509,"Solo certificado") -> 30270090 | K6: =SUMIFS(Base!$I$5:$I$509,Base!$A$5:$A$509,"001",Base!$R$5:$R$509,"Parcialmente comprometido") -> 180309975 | L6: =SUMIFS(Base!$I$5:$I$509,Base!$A$5:$A$509,"001",Base!$R$5:$R$509,"Mayormente comprometido") -> 599703144 | M6: =SUMIFS(Base!$I$5:$I$509,Base!$A$5:$A$509,"001",Base!$R$5:$R$509,"Ejecutado") -> 81635537 | N6: =SUMIFS(Base!$I$5:$I$509,Base!$A$5:$A$509,"001",Base!$R$5:$R$509,"Sin PIM") -> 0
A7: 002. REGION PUNO-PESQUERIA | B7: =COUNTIFS(Base!$A$5:$A$509,"002") -> 4 | C7: =SUMIFS(Base!$I$5:$I$509,Base!$A$5:$A$509,"002") -> 2582404 | D7: =SUMIFS(Base!$J$5:$J$509,Base!$A$5:$A$509,"002") -> 1853925.8 | E7: =SUMIFS(Base!$K$5:$K$509,Base!$A$5:$A$509,"002") -> 1829425.8 | F7: =SUMIFS(Base!$L$5:$L$509,Base!$A$5:$A$509,"002") -> 1562395.5 | G7: =C7-D7 -> 728478.18 | H7: =SUMIFS(Base!$T$5:$T$509,Base!$A$5:$A$509,"002") -> 752978.18 | I7: =SUMIFS(Base!$I$5:$I$509,Base!$A$5:$A$509,"002",Base!$R$5:$R$509,"Sin certificar") -> 45000 | J7: =SUMIFS(Base!$I$5:$I$509,Base!$A$5:$A$509,"002",Base!$R$5:$R$509,"Solo certificado") -> 0 | K7: =SUMIFS(Base!$I$5:$I$509,Base!$A$5:$A$509,"002",Base!$R$5:$R$509,"Parcialmente comprometido") -> 0 | L7: =SUMIFS(Base!$I$5:$I$509,Base!$A$5:$A$509,"002",Base!$R$5:$R$509,"Mayormente comprometido") -> 2537404 | M7: =SUMIFS(Base!$I$5:$I$509,Base!$A$5:$A$509,"002",Base!$R$5:$R$509,"Ejecutado") -> 0 | N7: =SUMIFS(Base!$I$5:$I$509,Base!$A$5:$A$509,"002",Base!$R$5:$R$509,"Sin PIM") -> 0
A8: 003. REGION PUNO-PROGRAMA REGIONAL DE RIEGO Y DRENAJE | B8: =COUNTIFS(Base!$A$5:$A$509,"003") -> 41 | C8: =SUMIFS(Base!$I$5:$I$509,Base!$A$5:$A$509,"003") -> 45637342 | D8: =SUMIFS(Base!$J$5:$J$509,Base!$A$5:$A$509,"003") -> 42133907 | E8: =SUMIFS(Base!$K$5:$K$509,Base!$A$5:$A$509,"003") -> 39187593 | F8: =SUMIFS(Base!$L$5:$L$509,Base!$A$5:$A$509,"003") -> 33578062 | G8: =C8-D8 -> 3503435.2 | H8: =SUMIFS(Base!$T$5:$T$509,Base!$A$5:$A$509,"003") -> 6009941.8 | I8: =SUMIFS(Base!$I$5:$I$509,Base!$A$5:$A$509,"003",Base!$R$5:$R$509,"Sin certificar") -> 0 | J8: =SUMIFS(Base!$I$5:$I$509,Base!$A$5:$A$509,"003",Base!$R$5:$R$509,"Solo certificado") -> 0 | K8: =SUMIFS(Base!$I$5:$I$509,Base!$A$5:$A$509,"003",Base!$R$5:$R$509,"Parcialmente comprometido") -> 1331516 | L8: =SUMIFS(Base!$I$5:$I$509,Base!$A$5:$A$509,"003",Base!$R$5:$R$509,"Mayormente comprometido") -> 33424668 | M8: =SUMIFS(Base!$I$5:$I$509,Base!$A$5:$A$509,"003",Base!$R$5:$R$509,"Ejecutado") -> 10881158 | N8: =SUMIFS(Base!$I$5:$I$509,Base!$A$5:$A$509,"003",Base!$R$5:$R$509,"Sin PIM") -> 0
A9: 005. REGION PUNO-PROGRAMA DE APOYO AL DESARROLLO RURAL ANDINO | B9: =COUNTIFS(Base!$A$5:$A$509,"005") -> 6 | C9: =SUMIFS(Base!$I$5:$I$509,Base!$A$5:$A$509,"005") -> 20087412 | D9: =SUMIFS(Base!$J$5:$J$509,Base!$A$5:$A$509,"005") -> 19634939 | E9: =SUMIFS(Base!$K$5:$K$509,Base!$A$5:$A$509,"005") -> 17859680 | F9: =SUMIFS(Base!$L$5:$L$509,Base!$A$5:$A$509,"005") -> 15129330 | G9: =C9-D9 -> 452473.04 | H9: =SUMIFS(Base!$T$5:$T$509,Base!$A$5:$A$509,"005") -> 2225313 | I9: =SUMIFS(Base!$I$5:$I$509,Base!$A$5:$A$509,"005",Base!$R$5:$R$509,"Sin certificar") -> 30000 | J9: =SUMIFS(Base!$I$5:$I$509,Base!$A$5:$A$509,"005",Base!$R$5:$R$509,"Solo certificado") -> 0 | K9: =SUMIFS(Base!$I$5:$I$509,Base!$A$5:$A$509,"005",Base!$R$5:$R$509,"Parcialmente comprometido") -> 0 | L9: =SUMIFS(Base!$I$5:$I$509,Base!$A$5:$A$509,"005",Base!$R$5:$R$509,"Mayormente comprometido") -> 17454263 | M9: =SUMIFS(Base!$I$5:$I$509,Base!$A$5:$A$509,"005",Base!$R$5:$R$509,"Ejecutado") -> 2603149 | N9: =SUMIFS(Base!$I$5:$I$509,Base!$A$5:$A$509,"005",Base!$R$5:$R$509,"Sin PIM") -> 0
A10: 100. REGION PUNO-AGRICULTURA | B10: =COUNTIFS(Base!$A$5:$A$509,"100") -> 10 | C10: =SUMIFS(Base!$I$5:$I$509,Base!$A$5:$A$509,"100") -> 14581394 | D10: =SUMIFS(Base!$J$5:$J$509,Base!$A$5:$A$509,"100") -> 12563071 | E10: =SUMIFS(Base!$K$5:$K$509,Base!$A$5:$A$509,"100") -> 12197514 | F10: =SUMIFS(Base!$L$5:$L$509,Base!$A$5:$A$509,"100") -> 11236501 | G10: =C10-D10 -> 2018322.8 | H10: =SUMIFS(Base!$T$5:$T$509,Base!$A$5:$A$509,"100") -> 2368535.4 | I10: =SUMIFS(Base!$I$5:$I$509,Base!$A$5:$A$509,"100",Base!$R$5:$R$509,"Sin certificar") -> 471850 | J10: =SUMIFS(Base!$I$5:$I$509,Base!$A$5:$A$509,"100",Base!$R$5:$R$509,"Solo certificado") -> 0 | K10: =SUMIFS(Base!$I$5:$I$509,Base!$A$5:$A$509,"100",Base!$R$5:$R$509,"Parcialmente comprometido") -> 0 | L10: =SUMIFS(Base!$I$5:$I$509,Base!$A$5:$A$509,"100",Base!$R$5:$R$509,"Mayormente comprometido") -> 12109544 | M10: =SUMIFS(Base!$I$5:$I$509,Base!$A$5:$A$509,"100",Base!$R$5:$R$509,"Ejecutado") -> 2000000 | N10: =SUMIFS(Base!$I$5:$I$509,Base!$A$5:$A$509,"100",Base!$R$5:$R$509,"Sin PIM") -> 0
A11: 302. REGION PUNO-EDUCACION MELGAR | B11: =COUNTIFS(Base!$A$5:$A$509,"302") -> 1 | C11: =SUMIFS(Base!$I$5:$I$509,Base!$A$5:$A$509,"302") -> 32592 | D11: =SUMIFS(Base!$J$5:$J$509,Base!$A$5:$A$509,"302") -> 0 | E11: =SUMIFS(Base!$K$5:$K$509,Base!$A$5:$A$509,"302") -> 0 | F11: =SUMIFS(Base!$L$5:$L$509,Base!$A$5:$A$509,"302") -> 0 | G11: =C11-D11 -> 32592 | H11: =SUMIFS(Base!$T$5:$T$509,Base!$A$5:$A$509,"302") -> 32592 | I11: =SUMIFS(Base!$I$5:$I$509,Base!$A$5:$A$509,"302",Base!$R$5:$R$509,"Sin certificar") -> 32592 | J11: =SUMIFS(Base!$I$5:$I$509,Base!$A$5:$A$509,"302",Base!$R$5:$R$509,"Solo certificado") -> 0 | K11: =SUMIFS(Base!$I$5:$I$509,Base!$A$5:$A$509,"302",Base!$R$5:$R$509,"Parcialmente comprometido") -> 0 | L11: =SUMIFS(Base!$I$5:$I$509,Base!$A$5:$A$509,"302",Base!$R$5:$R$509,"Mayormente comprometido") -> 0 | M11: =SUMIFS(Base!$I$5:$I$509,Base!$A$5:$A$509,"302",Base!$R$5:$R$509,"Ejecutado") -> 0 | N11: =SUMIFS(Base!$I$5:$I$509,Base!$A$5:$A$509,"302",Base!$R$5:$R$509,"Sin PIM") -> 0
A12: 413. GOB. REG. DPTO. DE PUNO - SALUD SAN ANTONIO DE PUTINA | B12: =COUNTIFS(Base!$A$5:$A$509,"413") -> 1 | C12: =SUMIFS(Base!$I$5:$I$509,Base!$A$5:$A$509,"413") -> 41800 | D12: =SUMIFS(Base!$J$5:$J$509,Base!$A$5:$A$509,"413") -> 41500 | E12: =SUMIFS(Base!$K$5:$K$509,Base!$A$5:$A$509,"413") -> 41500 | F12: =SUMIFS(Base!$L$5:$L$509,Base!$A$5:$A$509,"413") -> 41500 | G12: =C12-D12 -> 300 | H12: =SUMIFS(Base!$T$5:$T$509,Base!$A$5:$A$509,"413") -> 0 | I12: =SUMIFS(Base!$I$5:$I$509,Base!$A$5:$A$509,"413",Base!$R$5:$R$509,"Sin certificar") -> 0 | J12: =SUMIFS(Base!$I$5:$I$509,Base!$A$5:$A$509,"413",Base!$R$5:$R$509,"Solo certificado") -> 0 | K12: =SUMIFS(Base!$I$5:$I$509,Base!$A$5:$A$509,"413",Base!$R$5:$R$509,"Parcialmente comprometido") -> 0 | L12: =SUMIFS(Base!$I$5:$I$509,Base!$A$5:$A$509,"413",Base!$R$5:$R$509,"Mayormente comprometido") -> 0 | M12: =SUMIFS(Base!$I$5:$I$509,Base!$A$5:$A$509,"413",Base!$R$5:$R$509,"Ejecutado") -> 41800 | N12: =SUMIFS(Base!$I$5:$I$509,Base!$A$5:$A$509,"413",Base!$R$5:$R$509,"Sin PIM") -> 0
A13: TOTAL | B13: =SUM(B6:B12) -> 505 | C13: =SUM(C6:C12) -> 987989928 | D13: =SUM(D6:D12) -> 9.1937047e+08 | E13: =SUM(E6:E12) -> 6.8728368e+08 | F13: =SUM(F6:F12) -> 4.9510747e+08 | G13: =SUM(G6:G12) -> 68619458 | H13: =SUM(H6:H12) -> 2.9627609e+08 | I13: =SUM(I6:I12) -> 13687680 | ... N13: =SUM(N6:N12) -> 0
A16: UE 001 Sede Central · por gerencia / oficina
A17: Unidad | B17: Proyectos (UE-CUI-meta) | C17: PIM 2026 | D17: Certificación | E17: Compromiso anual | F17: Devengado | G17: Saldo sin certificar | H17: Disponible (PIM − comprom.) | I17: PIM · Sin certificar | J17: PIM · Solo certificado | K17: PIM · Parcialmente comprometido | L17: PIM · Mayormente comprometido | M17: PIM · Ejecutado | N17: PIM · Sin PIM
A18: GERENCIA DE INFRAESTRUCTURA | B18: =COUNTIFS(Base!$C$5:$C$509,$A18) -> 289 | C18: =SUMIFS(Base!$I$5:$I$509,Base!$C$5:$C$509,$A18) -> 770705923 | D18: =SUMIFS(Base!$J$5:$J$509,Base!$C$5:$C$509,$A18) -> 7.2293211e+08 | E18: =SUMIFS(Base!$K$5:$K$509,Base!$C$5:$C$509,$A18) -> 548920995 | F18: =SUMIFS(Base!$L$5:$L$509,Base!$C$5:$C$509,$A18) -> 3.8171135e+08 | G18: =C18-D18 -> 47773815 | H18: =SUMIFS(Base!$T$5:$T$509,Base!$C$5:$C$509,$A18) -> 2.1839586e+08 | I18: =SUMIFS(Base!$I$5:$I$509,Base!$C$5:$C$509,$A18,Base!$R$5:$R$509,"Sin certificar") -> 11235029 | J18: =SUMIFS(Base!$I$5:$I$509,Base!$C$5:$C$509,$A18,Base!$R$5:$R$509,"Solo certificado") -> 21115897 | K18: =SUMIFS(Base!$I$5:$I$509,Base!$C$5:$C$509,$A18,Base!$R$5:$R$509,"Parcialmente comprometido") -> 128716981 | L18: =SUMIFS(Base!$I$5:$I$509,Base!$C$5:$C$509,$A18,Base!$R$5:$R$509,"Mayormente comprometido") -> 539163563 | M18: =SUMIFS(Base!$I$5:$I$509,Base!$C$5:$C$509,$A18,Base!$R$5:$R$509,"Ejecutado") -> 70474453 | N18: =SUMIFS(Base!$I$5:$I$509,Base!$C$5:$C$509,$A18,Base!$R$5:$R$509,"Sin PIM") -> 0
A19: GERENCIA REGIONAL DE DESARROLLO ECONOMICO | B19: =COUNTIFS(Base!$C$5:$C$509,$A19) -> 83 | C19: =SUMIFS(Base!$I$5:$I$509,Base!$C$5:$C$509,$A19) -> 15438088 | D19: =SUMIFS(Base!$J$5:$J$509,Base!$C$5:$C$509,$A19) -> 13246424 | E19: =SUMIFS(Base!$K$5:$K$509,Base!$C$5:$C$509,$A19) -> 9068413.4 | F19: =SUMIFS(Base!$L$5:$L$509,Base!$C$5:$C$509,$A19) -> 6937956.8 | G19: =C19-D19 -> 2191664.1 | H19: =SUMIFS(Base!$T$5:$T$509,Base!$C$5:$C$509,$A19) -> 6297331.5 | I19: =SUMIFS(Base!$I$5:$I$509,Base!$C$5:$C$509,$A19,Base!$R$5:$R$509,"Sin certificar") -> 160000 | J19: =SUMIFS(Base!$I$5:$I$509,Base!$C$5:$C$509,$A19,Base!$R$5:$R$509,"Solo certificado") -> 891317 | K19: =SUMIFS(Base!$I$5:$I$509,Base!$C$5:$C$509,$A19,Base!$R$5:$R$509,"Parcialmente comprometido") -> 4222909 | L19: =SUMIFS(Base!$I$5:$I$509,Base!$C$5:$C$509,$A19,Base!$R$5:$R$509,"Mayormente comprometido") -> 8207733 | M19: =SUMIFS(Base!$I$5:$I$509,Base!$C$5:$C$509,$A19,Base!$R$5:$R$509,"Ejecutado") -> 1956129 | N19: =SUMIFS(Base!$I$5:$I$509,Base!$C$5:$C$509,$A19,Base!$R$5:$R$509,"Sin PIM") -> 0
A20: GERENCIA REGIONAL DE RECURSOS NATURALES Y GESTION AMBIENTAL | B20: =COUNTIFS(Base!$C$5:$C$509,$A20) -> 11 | C20: =SUMIFS(Base!$I$5:$I$509,Base!$C$5:$C$509,$A20) -> 18155027 | D20: =SUMIFS(Base!$J$5:$J$509,Base!$C$5:$C$509,$A20) -> 15578094 | E20: =SUMIFS(Base!$K$5:$K$509,Base!$C$5:$C$509,$A20) -> 15208932 | F20: =SUMIFS(Base!$L$5:$L$509,Base!$C$5:$C$509,$A20) -> 8757642.5 | G20: =C20-D20 -> 2576932.7 | H20: =SUMIFS(Base!$T$5:$T$509,Base!$C$5:$C$509,$A20) -> 2946095.4 | I20: =SUMIFS(Base!$I$5:$I$509,Base!$C$5:$C$509,$A20,Base!$R$5:$R$509,"Sin certificar") -> 32099 | J20: =SUMIFS(Base!$I$5:$I$509,Base!$C$5:$C$509,$A20,Base!$R$5:$R$509,"Solo certificado") -> 30658 | K20: =SUMIFS(Base!$I$5:$I$509,Base!$C$5:$C$509,$A20,Base!$R$5:$R$509,"Parcialmente comprometido") -> 1870632 | L20: =SUMIFS(Base!$I$5:$I$509,Base!$C$5:$C$509,$A20,Base!$R$5:$R$509,"Mayormente comprometido") -> 16221638 | M20: =SUMIFS(Base!$I$5:$I$509,Base!$C$5:$C$509,$A20,Base!$R$5:$R$509,"Ejecutado") -> 0 | N20: =SUMIFS(Base!$I$5:$I$509,Base!$C$5:$C$509,$A20,Base!$R$5:$R$509,"Sin PIM") -> 0
A21: PROYECTO ESPECIAL TRUCHAS TITICACA - PETT | B21: =COUNTIFS(Base!$C$5:$C$509,$A21) -> 3 | C21: =SUMIFS(Base!$I$5:$I$509,Base!$C$5:$C$509,$A21) -> 13183082 | D21: =SUMIFS(Base!$J$5:$J$509,Base!$C$5:$C$509,$A21) -> 12706541 | E21: =SUMIFS(Base!$K$5:$K$509,Base!$C$5:$C$509,$A21) -> 6500647.1 | F21: =SUMIFS(Base!$L$5:$L$509,Base!$C$5:$C$509,$A21) -> 3714211.5 | G21: =C21-D21 -> 476541.15 | H21: =SUMIFS(Base!$T$5:$T$509,Base!$C$5:$C$509,$A21) -> 6651033.8 | I21: =SUMIFS(Base!$I$5:$I$509,Base!$C$5:$C$509,$A21,Base!$R$5:$R$509,"Sin certificar") -> 100000 | J21: =SUMIFS(Base!$I$5:$I$509,Base!$C$5:$C$509,$A21,Base!$R$5:$R$509,"Solo certificado") -> 0 | K21: =SUMIFS(Base!$I$5:$I$509,Base!$C$5:$C$509,$A21,Base!$R$5:$R$509,"Parcialmente comprometido") -> 12532522 | L21: =SUMIFS(Base!$I$5:$I$509,Base!$C$5:$C$509,$A21,Base!$R$5:$R$509,"Mayormente comprometido") -> 0 | M21: =SUMIFS(Base!$I$5:$I$509,Base!$C$5:$C$509,$A21,Base!$R$5:$R$509,"Ejecutado") -> 550560 | N21: =SUMIFS(Base!$I$5:$I$509,Base!$C$5:$C$509,$A21,Base!$R$5:$R$509,"Sin PIM") -> 0
A22: PROYECTO ESPECIAL CAMELIDOS SUDAMERICANOS | B22: =COUNTIFS(Base!$C$5:$C$509,$A22) -> 2 | C22: =SUMIFS(Base!$I$5:$I$509,Base!$C$5:$C$509,$A22) -> 5603985 | D22: =SUMIFS(Base!$J$5:$J$509,Base!$C$5:$C$509,$A22) -> 5402770 | E22: =SUMIFS(Base!$K$5:$K$509,Base!$C$5:$C$509,$A22) -> 4078169.4 | F22: =SUMIFS(Base!$L$5:$L$509,Base!$C$5:$C$509,$A22) -> 3499541.4 | G22: =C22-D22 -> 201215.05 | H22: =SUMIFS(Base!$T$5:$T$509,Base!$C$5:$C$509,$A22) -> 1522323.7 | I22: =SUMIFS(Base!$I$5:$I$509,Base!$C$5:$C$509,$A22,Base!$R$5:$R$509,"Sin certificar") -> 0 | J22: =SUMIFS(Base!$I$5:$I$509,Base!$C$5:$C$509,$A22,Base!$R$5:$R$509,"Solo certificado") -> 0 | K22: =SUMIFS(Base!$I$5:$I$509,Base!$C$5:$C$509,$A22,Base!$R$5:$R$509,"Parcialmente comprometido") -> 0 | L22: =SUMIFS(Base!$I$5:$I$509,Base!$C$5:$C$509,$A22,Base!$R$5:$R$509,"Mayormente comprometido") -> 4271598 | M22: =SUMIFS(Base!$I$5:$I$509,Base!$C$5:$C$509,$A22,Base!$R$5:$R$509,"Ejecutado") -> 1332387 | N22: =SUMIFS(Base!$I$5:$I$509,Base!$C$5:$C$509,$A22,Base!$R$5:$R$509,"Sin PIM") -> 0
A23: GERENCIA REGIONAL DE DESARROLLO SOCIAL | B23: =COUNTIFS(Base!$C$5:$C$509,$A23) -> 42 | C23: =SUMIFS(Base!$I$5:$I$509,Base!$C$5:$C$509,$A23) -> 74669674 | D23: =SUMIFS(Base!$J$5:$J$509,Base!$C$5:$C$509,$A23) -> 67480327 | E23: =SUMIFS(Base!$K$5:$K$509,Base!$C$5:$C$509,$A23) -> 26597962 | F23: =SUMIFS(Base!$L$5:$L$509,Base!$C$5:$C$509,$A23) -> 23520433 | G23: =C23-D23 -> 7189346.7 | H23: =SUMIFS(Base!$T$5:$T$509,Base!$C$5:$C$509,$A23) -> 47699720 | I23: =SUMIFS(Base!$I$5:$I$509,Base!$C$5:$C$509,$A23,Base!$R$5:$R$509,"Sin certificar") -> 1256414 | J23: =SUMIFS(Base!$I$5:$I$509,Base!$C$5:$C$509,$A23,Base!$R$5:$R$509,"Solo certificado") -> 8232218 | K23: =SUMIFS(Base!$I$5:$I$509,Base!$C$5:$C$509,$A23,Base!$R$5:$R$509,"Parcialmente comprometido") -> 32966931 | L23: =SUMIFS(Base!$I$5:$I$509,Base!$C$5:$C$509,$A23,Base!$R$5:$R$509,"Mayormente comprometido") -> 27433858 | M23: =SUMIFS(Base!$I$5:$I$509,Base!$C$5:$C$509,$A23,Base!$R$5:$R$509,"Ejecutado") -> 4780253 | N23: =SUMIFS(Base!$I$5:$I$509,Base!$C$5:$C$509,$A23,Base!$R$5:$R$509,"Sin PIM") -> 0
A24: DIRECCIÓN DE ESTUDIOS DE PREINVERSIÓN | B24: =COUNTIFS(Base!$C$5:$C$509,$A24) -> 10 | C24: =SUMIFS(Base!$I$5:$I$509,Base!$C$5:$C$509,$A24) -> 7151039 | D24: =SUMIFS(Base!$J$5:$J$509,Base!$C$5:$C$509,$A24) -> 5777501 | E24: =SUMIFS(Base!$K$5:$K$509,Base!$C$5:$C$509,$A24) -> 5773489.2 | F24: =SUMIFS(Base!$L$5:$L$509,Base!$C$5:$C$509,$A24) -> 5400403.3 | G24: =C24-D24 -> 1373538 | H24: =SUMIFS(Base!$T$5:$T$509,Base!$C$5:$C$509,$A24) -> 1273568.9 | I24: =SUMIFS(Base!$I$5:$I$509,Base!$C$5:$C$509,$A24,Base!$R$5:$R$509,"Sin certificar") -> 224696 | J24: =SUMIFS(Base!$I$5:$I$509,Base!$C$5:$C$509,$A24,Base!$R$5:$R$509,"Solo certificado") -> 0 | K24: =SUMIFS(Base!$I$5:$I$509,Base!$C$5:$C$509,$A24,Base!$R$5:$R$509,"Parcialmente comprometido") -> 0 | L24: =SUMIFS(Base!$I$5:$I$509,Base!$C$5:$C$509,$A24,Base!$R$5:$R$509,"Mayormente comprometido") -> 4384588 | M24: =SUMIFS(Base!$I$5:$I$509,Base!$C$5:$C$509,$A24,Base!$R$5:$R$509,"Ejecutado") -> 2541755 | N24: =SUMIFS(Base!$I$5:$I$509,Base!$C$5:$C$509,$A24,Base!$R$5:$R$509,"Sin PIM") -> 0
A25: SIN CLASIFICAR (pendiente de asignar gerencia) | B25: =COUNTIFS(Base!$C$5:$C$509,$A25) -> 2 | C25: =SUMIFS(Base!$I$5:$I$509,Base!$C$5:$C$509,$A25) -> 120166 | D25: =SUMIFS(Base!$J$5:$J$509,Base!$C$5:$C$509,$A25) -> 19362 | E25: =SUMIFS(Base!$K$5:$K$509,Base!$C$5:$C$509,$A25) -> 19362 | F25: =SUMIFS(Base!$L$5:$L$509,Base!$C$5:$C$509,$A25) -> 18148.25 | G25: =C25-D25 -> 100804 | H25: =SUMIFS(Base!$T$5:$T$509,Base!$C$5:$C$509,$A25) -> 100804 | I25: =SUMIFS(Base!$I$5:$I$509,Base!$C$5:$C$509,$A25,Base!$R$5:$R$509,"Sin certificar") -> 100000 | J25: =SUMIFS(Base!$I$5:$I$509,Base!$C$5:$C$509,$A25,Base!$R$5:$R$509,"Solo certificado") -> 0 | K25: =SUMIFS(Base!$I$5:$I$509,Base!$C$5:$C$509,$A25,Base!$R$5:$R$509,"Parcialmente comprometido") -> 0 | L25: =SUMIFS(Base!$I$5:$I$509,Base!$C$5:$C$509,$A25,Base!$R$5:$R$509,"Mayormente comprometido") -> 20166 | M25: =SUMIFS(Base!$I$5:$I$509,Base!$C$5:$C$509,$A25,Base!$R$5:$R$509,"Ejecutado") -> 0 | N25: =SUMIFS(Base!$I$5:$I$509,Base!$C$5:$C$509,$A25,Base!$R$5:$R$509,"Sin PIM") -> 0
A26: TOTAL | B26: =SUM(B18:B25) -> 442 | C26: =SUM(C18:C25) -> 905026984 | D26: =SUM(D18:D25) -> 8.4314313e+08 | E26: =SUM(E18:E25) -> 6.1616797e+08 | F26: =SUM(F18:F25) -> 4.3355968e+08 | G26: =SUM(G18:G25) -> 61883857 | H26: =SUM(H18:H25) -> 2.8488673e+08 | I26: =SUM(I18:I25) -> 13108238 | ... N26: =SUM(N18:N25) -> 0

Sheet Gerencia de Infraestructura
C1: ANEXO N° 01
B2: COMPORTAMIENTO DE EJECUCIÓN DE PROYECTOS DE INVERSION PUBLICA DEL AÑO FISCAL 2026 · Gerencia de Infraestructura · AL 07/10/2026
A4: N° | B4: META | C4: PROYECTO | D4: PIM 2026 (A) | E4: CERTIFICACIÓN (B) | F4: SALDO (A-B) | G4: DEVENGADO ( C ) | H4: SALDO (A-C) | I4: DEVEN % | J4: MODALIDAD DE EJECUCIÓN | K4: ESTADO SITUACIONAL PROYECTO | L4: Monto Año 2026 (S/) | M4: Monto Año 2027 (S/) | N4: Monto Año 2028 (S/) | O4: Monto Año 2029 (S/) | P4: BASE LEGAL | Q4: DISPONIBILIDAD | R4: CERTIFICADO NO COMPROMETIDO | S4: DISPONIBLE (PIM − COMPROM.)
A5: GERENCIA DE INFRAESTRUCTURA | D5: =D6+D122+D151+D201+D328 -> 770705923 | E5: =E6+E122+E151+E201+E328 -> 7.2293211e+08 | F5: =D5-E5 -> 47773815 | G5: =G6+G122+G151+G201+G328 -> 3.8171135e+08 | H5: =D5-G5 -> 3.8899458e+08 | I5: =IF(D5=0,0,G5/D5) -> 0.49527496 | R5: =R6+R122+R151+R201+R328 -> 1.7401111e+08 | S5: =S6+S122+S151+S201+S328 -> 2.1839586e+08
A6: EJECUCIÓN POR ADMINISTRACIÓN DIRECTA | D6: =D7+D78 -> 501856577 | E6: =E7+E78 -> 4.7258296e+08 | F6: =D6-E6 -> 29273617 | G6: =G7+G78 -> 2.5907445e+08 | H6: =D6-G6 -> 2.4278213e+08 | I6: =IF(D6=0,0,G6/D6) -> 0.51623205 | R6: =R7+R78 -> 1.2174969e+08 | S6: =S7+S78 -> 1.504391e+08
A7: EJECUCIÓN POR ADMINISTRACIÓN DIRECTA - DIRECTIVA 10 | D7: =D8+D11+D38+D63+D73+D75 -> 234460254 | E7: =E8+E11+E38+E63+E73+E75 -> 2.2363717e+08 | F7: =D7-E7 -> 10823083 | G7: =G8+G11+G38+G63+G73+G75 -> 99970240 | H7: =D7-G7 -> 1.3449001e+08 | I7: =IF(D7=0,0,G7/D7) -> 0.42638459 | R7: =R8+R11+R38+R63+R73+R75 -> 79279485 | S7: =S8+S11+S38+S63+S73+S75 -> 89851832
A8: 20. SALUD | D8: =SUM(D9:D10) -> 53926751 | E8: =SUM(E9:E10) -> 53909348 | F8: =D8-E8 -> 17402.8 | G8: =SUM(G9:G10) -> 364124.26 | H8: =D8-G8 -> 53562627 | I8: =IF(D8=0,0,G8/D8) -> 0.006752201 | R8: =SUM(R9:R10) -> 53496483 | S8: =SUM(S9:S10) -> 53513885
A9: =SUBTOTAL(103,$B$6:B9) -> 1 | B9: 1 | C9: =Base!H5 -> 2108576: CONSTRUCCION DEL HOSPITAL MATERNO INFANTIL DEL CONO SUR JULIACA | D9: =Base!I5 -> 167354 | E9: =Base!J5 -> 149951.3 | F9: =D9-E9 -> 17402.7 | G9: =Base!L5 -> 102781.21 | H9: =D9-G9 -> 64572.79 | I9: =IF(D9=0,0,G9/D9) -> 0.61415449 | J9: =Base!U5 -> Administración directa / Laudos arbitrales | K9: =Base!R5 -> Mayormente comprometido | L9: =Base!V5 -> 12460540 | M9: =Base!W5 -> 5731000 | N9: =Base!X5 -> 5000000 | O9: =Base!Y5 -> 5000000 | P9: =IF(Base!Z5="","",Base!Z5) | Q9: =Base!S5 -> Difícil | R9: =Base!N5 -> 0 | S9: =Base!T5 -> 17402.7
A10: =SUBTOTAL(103,$B$6:B10) -> 2 | B10: 220 | C10: =Base!H6 -> 2279375: MEJORAMIENTO DE LOS SERVICIOS DE SALUD DEL HOSPITAL DE APOYO ILAVE, PROVINCIA DE EL COLLAO - REGION PUNO | D10: =Base!I6 -> 53759397 | E10: =Base!J6 -> 53759397 | F10: =D10-E10 -> 0.1 | G10: =Base!L6 -> 261343.05 | H10: =D10-G10 -> 53498054 | I10: =IF(D10=0,0,G10/D10) -> 0.0048613464 | J10: =Base!U6 -> Contrata / Expediente técnico / Administración directa / Laudos arbitrales | K10: =Base!R6 -> Parcialmente comprometido | L10: =Base!V6 -> No registrado en cartera | M10: =Base!W6 -> No registrado en cartera | N10: =Base!X6 -> No registrado en cartera | O10: =Base!Y6 -> No registrado en cartera | P10: =IF(Base!Z6="","",Base!Z6) | Q10: =Base!S6 -> Parcial | R10: =Base!N6 -> 53496483 | S10: =Base!T6 -> 53496483
A11: 22. EDUCACION | D11: =SUM(D12:D37) -> 60810433 | E11: =SUM(E12:E37) -> 57496092 | F11: =D11-E11 -> 3314341 | G11: =SUM(G12:G37) -> 35508320 | H11: =D11-G11 -> 25302113 | I11: =IF(D11=0,0,G11/D11) -> 0.58391822 | R11: =SUM(R12:R37) -> 9719553.3 | S11: =SUM(S12:S37) -> 12937091
A12: =SUBTOTAL(103,$B$6:B12) -> 3 | B12: 223 | C12: =Base!H7 -> 2323700: MEJORAMIENTO DEL SERVICIO EDUCATIVO DE LAS CARRERAS DE PRODUCCIÓN, AUTOMOTRIZ, MINERÍA, CONTABILIDAD, COMPUTACIÓN, SECRETARIADO, ENFERMERÍA, LABORATORIO CLÍNICO Y PRÓTESIS DENTAL DEL IST MANUEL NÚÑEZ BUTRÓN, JULIACA, SAN ROMÁN - PUNO | D12: =Base!I7 -> 10519577 | E12: =Base!J7 -> 10386241 | F12: =D12-E12 -> 133335.78 | G12: =Base!L7 -> 7596372.7 | H12: =D12-G12 -> 2923204.3 | I12: =IF(D12=0,0,G12/D12) -> 0.72211769 | J12: =Base!U7 -> Administración directa / Contrata / Personal/bienes/servicios | K12: =Base!R7 -> Mayormente comprometido | L12: =Base!V7 -> 2546207 | M12: =Base!W7 -> 638376 | N12: =Base!X7 -> 2568939 | O12: =Base!Y7 -> 0 | P12: =IF(Base!Z7="","",Base!Z7) | Q12: =Base!S7 -> Difícil | R12: =Base!N7 -> 1903152 | S12: =Base!T7 -> 2036487.8
A13: =SUBTOTAL(103,$B$6:B13) -> 4 | B13: 224 | C13: =Base!H8 -> 2335880: MEJORAMIENTO DEL SERVICIO EDUCATIVO DE LAS CARRERAS DE CONTABILIDAD, ENFERMERÍA TÉCNICA, COMPUTACIÓN E INFORMÁTICA, INDUSTRIA ALIMENTARIA Y PRODUCCIÓN AGROPECUARIA DEL ISEPA, PROVINCIA DE MELGAR - PUNO | D13: =Base!I8 -> 10208307 | E13: =Base!J8 -> 9968469.6 | F13: =D13-E13 -> 239837.38 | G13: =Base!L8 -> 6440724.5 | H13: =D13-G13 -> 3767582.5 | I13: =IF(D13=0,0,G13/D13) -> 0.63092974 | J13: =Base!U8 -> Administración directa / Equipamiento / Contrata / Personal/bienes/servicios | K13: =Base!R8 -> Mayormente comprometido | L13: =Base!V8 -> 5597990 | M13: =Base!W8 -> 1254673 | N13: =Base!X8 -> 2493351 | O13: =Base!Y8 -> 0 | P13: =IF(Base!Z8="","",Base!Z8) | Q13: =Base!S8 -> Difícil | R13: =Base!N8 -> 20231.28 | S13: =Base!T8 -> 260068.66
A14: =SUBTOTAL(103,$B$6:B14) -> 5 | B14: 245 | C14: =Base!H9 -> 2521936: MEJORAMIENTO Y AMPLIACION DEL SERVICIO DE EDUCACIÓN SUPERIOR TECNOLÓGICA EN EL INSTITUTO SUPERIOR TECNOLÓGICO PUBLICO DE MACUSANI DISTRITO DE MACUSANI - PROVINCIA DE CARABAYA - DEPARTAMENTO DE PUNO | D14: =Base!I9 -> 11203165 | E14: =Base!J9 -> 10889669 | F14: =D14-E14 -> 313496.41 | G14: =Base!L9 -> 6395813.3 | H14: =D14-G14 -> 4807351.7 | I14: =IF(D14=0,0,G14/D14) -> 0.57089343 | J14: =Base!U9 -> Administración directa / Equipamiento / Contrata / Personal/bienes/servicios | K14: =Base!R9 -> Mayormente comprometido | L14: =Base!V9 -> 4902849 | M14: =Base!W9 -> 60001 | N14: =Base!X9 -> 2722594 | O14: =Base!Y9 -> 0 | P14: =IF(Base!Z9="","",Base!Z9) | Q14: =Base!S9 -> Difícil | R14: =Base!N9 -> 2168178.7 | S14: =Base!T9 -> 2481675.1
A15: =SUBTOTAL(103,$B$6:B15) -> 6 | B15: 29 | C15: =Base!H10 -> 2344324: MEJORAMIENTO DE LOS SERVICIOS EDUCATIVOS DE LA I.E.S. MANUEL GONZALES PRADA, CENTRO POBLADO DE ISANI - DISTRITO DE ZEPITA - PROVINCIA DE CHUCUITO - REGIÓN PUNO | D15: =Base!I10 -> 2079431 | E15: =Base!J10 -> 1994037.5 | F15: =D15-E15 -> 85393.54 | G15: =Base!L10 -> 1946470.9 | H15: =D15-G15 -> 132960.06 | I15: =IF(D15=0,0,G15/D15) -> 0.9360594 | J15: =Base!U10 -> Administración directa / Equipamiento / Contrata / Personal/bienes/servicios | K15: =Base!R10 -> Ejecutado | L15: =Base!V10 -> 298669 | M15: =Base!W10 -> 349669 | N15: =Base!X10 -> 84977 | O15: =Base!Y10 -> 0 | P15: =IF(Base!Z10="","",Base!Z10) | Q15: =Base!S10 -> No usar | R15: =Base!N10 -> 7297 | S15: =Base!T10 -> 0
A16: =SUBTOTAL(103,$B$6:B16) -> 7 | B16: 315 | C16: =Base!H11 -> 2490075: MEJORAMIENTO DEL SERVICIO EDUCATIVO DEL NIVEL SECUNDARIA DE LA I.E. AGROPECUARIO SAN JUAN DEL ORO EN EL DISTRITO DE SAN JUAN DEL ORO - PROVINCIA DE SANDIA - DEPARTAMENTO DE PUNO | D16: =Base!I11 -> 1425006 | E16: =Base!J11 -> 1239788.9 | F16: =D16-E16 -> 185217.1 | G16: =Base!L11 -> 1170437 | H16: =D16-G16 -> 254569.02 | I16: =IF(D16=0,0,G16/D16) -> 0.82135583 | J16: =Base!U11 -> Administración directa / Equipamiento / Contrata / Personal/bienes/servicios | K16: =Base!R11 -> Mayormente comprometido | L16: =Base!V11 -> 1122019 | M16: =Base!W11 -> 0 | N16: =Base!X11 -> 32869 | O16: =Base!Y11 -> 0 | P16: =IF(Base!Z11="","",Base!Z11) | Q16: =Base!S11 -> Difícil | R16: =Base!N11 -> 500 | S16: =Base!T11 -> 185717.1
A17: =SUBTOTAL(103,$B$6:B17) -> 8 | B17: 160 | C17: =Base!H12 -> 2570978: MEJORAMIENTO DE LOS SERVICIOS DE EDUCACIÓN SUPERIOR DEL INSTITUTO SUPERIOR TECNOLÓGICO PUBLICA DE CABANILLAS DEL DISTRITO DE CABANILLAS - PROVINCIA DE SAN ROMAN - DEPARTAMENTO DE PUNO | D17: =Base!I12 -> 9222405 | E17: =Base!J12 -> 9003232.5 | F17: =D17-E17 -> 219172.47 | G17: =Base!L12 -> 5421356.6 | H17: =D17-G17 -> 3801048.4 | I17: =IF(D17=0,0,G17/D17) -> 0.58784629 | J17: =Base!U12 -> Administración directa / Equipamiento / Contrata / Personal/bienes/servicios | K17: =Base!R12 -> Mayormente comprometido | L17: =Base!V12 -> 2595053 | M17: =Base!W12 -> 255676 | N17: =Base!X12 -> 1817178 | O17: =Base!Y12 -> 0 | P17: =IF(Base!Z12="","",Base!Z12) | Q17: =Base!S12 -> Difícil | R17: =Base!N12 -> 2161615.2 | S17: =Base!T12 -> 2380787.7
A18: =SUBTOTAL(103,$B$6:B18) -> 9 | B18: 162 | C18: =Base!H13 -> 2591926: MEJORAMIENTO SERVICIO DE EDUCACIÓN SUPERIOR TECNOLÓGICA EN EL INSTITUTO SUPERIOR TECNOLÓGICO PUBLICO JOSE DOMINGO CHOQUEHUANCA DEL DISTRITO DE JOSE DOMINGO CHOQUEHUANCA DE LA PROVINCIA DE AZANGARO DEL DEPARTAMENTO DE PUNO | D18: =Base!I13 -> 5194033 | E18: =Base!J13 -> 5106124.8 | F18: =D18-E18 -> 87908.23 | G18: =Base!L13 -> 1941765.3 | H18: =D18-G18 -> 3252267.7 | I18: =IF(D18=0,0,G18/D18) -> 0.37384539 | J18: =Base!U13 -> Contrata / Personal/bienes/servicios | K18: =Base!R13 -> Mayormente comprometido | L18: =Base!V13 -> 5194033 | M18: =Base!W13 -> 6569076 | N18: =Base!X13 -> 1 | O18: =Base!Y13 -> 0 | P18: =IF(Base!Z13="","",Base!Z13) | Q18: =Base!S13 -> Difícil | R18: =Base!N13 -> 822146.13 | S18: =Base!T13 -> 910054.36
A19: =SUBTOTAL(103,$B$6:B19) -> 10 | B19: 44 | C19: =Base!H14 -> 2629119: MEJORAMIENTO DEL SERVICIO DE EDUCACIÓN SECUNDARIA EN I.E. ROSASPATA DE CENTRO POBLADO ROSASPATA DISTRITO DE ROSASPATA DE LA PROVINCIA DE HUANCANE DEL DEPARTAMENTO DE PUNO | D19: =Base!I14 -> 3656326 | E19: =Base!J14 -> 3383177.1 | F19: =D19-E19 -> 273148.9 | G19: =Base!L14 -> 2126125.4 | H19: =D19-G19 -> 1530200.6 | I19: =IF(D19=0,0,G19/D19) -> 0.58149229 | J19: =Base!U14 -> Administración directa / Contrata / Personal/bienes/servicios / Equipamiento | K19: =Base!R14 -> Mayormente comprometido | L19: =Base!V14 -> 2278000 | M19: =Base!W14 -> 1683936 | N19: =Base!X14 -> 1459275 | O19: =Base!Y14 -> 0 | P19: =IF(Base!Z14="","",Base!Z14) | Q19: =Base!S14 -> Difícil | R19: =Base!N14 -> 285937.63 | S19: =Base!T14 -> 559086.53
A20: =SUBTOTAL(103,$B$6:B20) -> 11 | B20: 248 | C20: =Base!H15 -> 2539673: MEJORAMIENTO Y AMPLIACION DEL SERVICIO DE EDUCACIÓN SUPERIOR TECNOLÓGICA EN EL INSTITUTO SUPERIOR TECNOLÓGICO PÚBLICO DE JULI, DISTRITO DE JULI - PROVINCIA DE CHUCUITO - DEPARTAMENTO DE PUNO | D20: =Base!I15 -> 2000000 | E20: =Base!J15 -> 2000000 | F20: =D20-E20 -> 0 | G20: =Base!L15 -> 0 | H20: =D20-G20 -> 2000000 | I20: =IF(D20=0,0,G20/D20) -> 0 | J20: =Base!U15 -> Contrata | K20: =Base!R15 -> Solo certificado | L20: =Base!V15 -> 12000000 | M20: =Base!W15 -> 14558623 | N20: =Base!X15 -> 14894208 | O20: =Base!Y15 -> 10928387 | P20: =IF(Base!Z15="","",Base!Z15) | Q20: =Base!S15 -> Posible | R20: =Base!N15 -> 2000000 | S20: =Base!T15 -> 2000000
A21: =SUBTOTAL(103,$B$6:B21) -> 12 | B21: 45 | C21: =Base!H16 -> 2637985: MEJORAMIENTO DEL SERVICIO DE EDUCACIÓN SECUNDARIA EN I.E. LLAULLI DE CENTRO POBLADO LLAULLI DISTRITO DE MOHO DE LA PROVINCIA DE MOHO DEL DEPARTAMENTO DE PUNO | D21: =Base!I16 -> 0 | E21: =Base!J16 -> 0 | F21: =D21-E21 -> 0 | G21: =Base!L16 -> 0 | H21: =D21-G21 -> 0 | I21: =IF(D21=0,0,G21/D21) -> 0 | J21: =Base!U16 -> Contrata | K21: =Base!R16 -> Sin PIM | L21: =Base!V16 -> 100000 | M21: =Base!W16 -> 1234564 | N21: =Base!X16 -> 0 | O21: =Base!Y16 -> 3335545 | P21: =IF(Base!Z16="","",Base!Z16) | Q21: =Base!S16 -> Sin PIM | R21: =Base!N16 -> 0 | S21: =Base!T16 -> 0
A22: =SUBTOTAL(103,$B$6:B22) -> 13 | B22: 193 | C22: =Base!H17 -> 2664940: MEJORAMIENTO DEL SERVICIO DE EDUCACIÓN INICIAL EN I.E. 1099 INMACULADA DISTRITO DE PUTINA DE LA PROVINCIA DE SAN ANTONIO DE PUTINA DEL DEPARTAMENTO DE PUNO | D22: =Base!I17 -> 1861270 | E22: =Base!J17 -> 1466941.4 | F22: =D22-E22 -> 394328.59 | G22: =Base!L17 -> 1164545.4 | H22: =D22-G22 -> 696724.63 | I22: =IF(D22=0,0,G22/D22) -> 0.62567245 | J22: =Base!U17 -> Administración directa / Contrata / Expediente técnico / Equipamiento / Personal/bienes/servicios | K22: =Base!R17 -> Mayormente comprometido | L22: =Base!V17 -> 1410000 | M22: =Base!W17 -> 833474 | N22: =Base!X17 -> 0 | O22: =Base!Y17 -> 0 | P22: =IF(Base!Z17="","",Base!Z17) | Q22: =Base!S17 -> Difícil | R22: =Base!N17 -> 15375 | S22: =Base!T17 -> 409703.59
A23: =SUBTOTAL(103,$B$6:B23) -> 14 | B23: 46 | C23: =Base!H18 -> 2637997: MEJORAMIENTO DEL SERVICIO DE EDUCACIÓN SECUNDARIA EN I.E. UMUCHI DISTRITO DE MOHO DE LA PROVINCIA DE MOHO DEL DEPARTAMENTO DE PUNO | D23: =Base!I18 -> 304829 | E23: =Base!J18 -> 0 | F23: =D23-E23 -> 304829 | G23: =Base!L18 -> 0 | H23: =D23-G23 -> 304829 | I23: =IF(D23=0,0,G23/D23) -> 0 | J23: =Base!U18 -> Contrata | K23: =Base!R18 -> Sin certificar | L23: =Base!V18 -> 100000 | M23: =Base!W18 -> 0 | N23: =Base!X18 -> 0 | O23: =Base!Y18 -> 4317457 | P23: =IF(Base!Z18="","",Base!Z18) | Q23: =Base!S18 -> Disponible | R23: =Base!N18 -> 0 | S23: =Base!T18 -> 304829
... A37: =SUBTOTAL(103,$B$6:B37) -> 28 | B37: 37 | C37: =Base!H32 -> 2467893: MEJORAMIENTO DEL SERVICIO EDUCATIVO DEL NIVEL SECUNDARIA DE LA I.E.S. TARACO DEL DISTRITO DE TARACO - PROVINCIA DE HUANCANE - DEPARTAMENTO DE PUNO | D37: =Base!I32 -> 50132 | E37: =Base!J32 -> 47450.05 | F37: =D37-E37 -> 2681.95 | G37: =Base!L32 -> 47450.05 | H37: =D37-G37 -> 2681.95 | I37: =IF(D37=0,0,G37/D37) -> 0.94650223 | J37: =Base!U32 -> Contrata | K37: =Base!R32 -> Ejecutado | L37: =Base!V32 -> 175369 | M37: =Base!W32 -> 79091 | N37: =Base!X32 -> 583672 | O37: =Base!Y32 -> 0 | P37: =IF(Base!Z32="","",Base!Z32) | Q37: =Base!S32 -> No usar | R37: =Base!N32 -> 0 | S37: =Base!T32 -> 0
A38: 15. TRANSPORTE | D38: =SUM(D39:D62) -> 87794613 | E38: =SUM(E39:E62) -> 83882331 | F38: =D38-E38 -> 3912282.3 | G38: =SUM(G39:G62) -> 50834366 | H38: =D38-G38 -> 36960247 | I38: =IF(D38=0,0,G38/D38) -> 0.57901463 | R38: =SUM(R39:R62) -> 8305567 | S38: =SUM(S39:S62) -> 12150688
A39: =SUBTOTAL(103,$B$6:B39) -> 29 | B39: 95 | C39: =Base!H33 -> 2194702: MEJORAMIENTO DE LA CARRETERA (PU 675) POMATA - YOROHOCO, PROVINCIA DE CHUCUITO - PUNO | D39: =Base!I33 -> 18401182 | E39: =Base!J33 -> 17764558 | F39: =D39-E39 -> 636624.07 | G39: =Base!L33 -> 15484260 | H39: =D39-G39 -> 2916922.1 | I39: =IF(D39=0,0,G39/D39) -> 0.84148181 | J39: =Base!U33 -> Administración directa / Contrata / Personal/bienes/servicios | K39: =Base!R33 -> Mayormente comprometido | L39: =Base!V33 -> 9922902 | M39: =Base!W33 -> 180000 | N39: =Base!X33 -> 0 | O39: =Base!Y33 -> 0 | P39: =IF(Base!Z33="","",Base!Z33) | Q39: =Base!S33 -> Difícil | R39: =Base!N33 -> 564551.4 | S39: =Base!T33 -> 1201175.5
A40: =SUBTOTAL(103,$B$6:B40) -> 30 | B40: 98 | C40: =Base!H34 -> 2287700: MEJORAMIENTO DE LA CARRETERA PU N-110: EMP. PE-34I ASIRUNI - ROSASPATA - HUAYRAPATA - EMP. PE-34I NINANTAYA, DISTRITOS DE VILQUECHICO-ROSASPATA-MOHO-HUAYRAPATA, PROVINCIA DE HUANCANÉ Y MOHO - PUNO | D40: =Base!I34 -> 10002053 | E40: =Base!J34 -> 9636351.5 | F40: =D40-E40 -> 365701.52 | G40: =Base!L34 -> 5473965.1 | H40: =D40-G40 -> 4528087.9 | I40: =IF(D40=0,0,G40/D40) -> 0.54728415 | J40: =Base!U34 -> Administración directa / Contrata / Personal/bienes/servicios | K40: =Base!R34 -> Mayormente comprometido | L40: =Base!V34 -> 4289351 | M40: =Base!W34 -> 500000 | N40: =Base!X34 -> 109570 | O40: =Base!Y34 -> 0 | P40: =IF(Base!Z34="","",Base!Z34) | Q40: =Base!S34 -> Difícil | R40: =Base!N34 -> 41193.21 | S40: =Base!T34 -> 406894.73
A41: =SUBTOTAL(103,$B$6:B41) -> 31 | B41: 112 | C41: =Base!H35 -> 2480499: MEJORAMIENTO DE LA CARRETERA PU 146; EMP PE - 34 I (HUANCANÉ) - HUERTAPATA - VISCACHANI - QUELLAHUYO - EMP PE - 34 (CACUÑA), DISTRITO DE HUANCANE - PROVINCIA DE HUANCANE - DEPARTAMENTO DE PUNO | D41: =Base!I35 -> 3297813 | E41: =Base!J35 -> 3286650.5 | F41: =D41-E41 -> 11162.55 | G41: =Base!L35 -> 3269277.3 | H41: =D41-G41 -> 28535.72 | I41: =IF(D41=0,0,G41/D41) -> 0.99134708 | J41: =Base!U35 -> Administración directa / Contrata | K41: =Base!R35 -> Ejecutado | L41: =Base!V35 -> 5406629 | M41: =Base!W35 -> 0 | N41: =Base!X35 -> 304959 | O41: =Base!Y35 -> 0 | P41: =IF(Base!Z35="","",Base!Z35) | Q41: =Base!S35 -> No usar | R41: =Base!N35 -> 0 | S41: =Base!T35 -> 0
A42: =SUBTOTAL(103,$B$6:B42) -> 32 | B42: 99 | C42: =Base!H36 -> 2300575: MEJORAMIENTO DE LA AVENIDA CIRCUNVALACIÓN II (EMP. PE- 3S-AV. HUANCANE-CIRCUNVALACION ESTE-EMP PE-3S) DE LA CIUDAD DE JULIACA- EMPALME PU-3S INICIO CON CIRCUNVALACION II - DISTRITO DE SAN MIGUEL - EMPALME PU-3S FINAL CON CIRCUNVALACION II - DISTRITO DE CARACOTO - PROVINCIA DE SAN ROMAN - REGIÓN PUNO | D42: =Base!I36 -> 2394023 | E42: =Base!J36 -> 2316938.8 | F42: =D42-E42 -> 77084.21 | G42: =Base!L36 -> 1138698.8 | H42: =D42-G42 -> 1255324.2 | I42: =IF(D42=0,0,G42/D42) -> 0.4756424 | J42: =Base!U36 -> Administración directa / Contrata / Personal/bienes/servicios | K42: =Base!R36 -> Mayormente comprometido | L42: =Base!V36 -> 3545977 | M42: =Base!W36 -> 1000000 | N42: =Base!X36 -> 3651450 | O42: =Base!Y36 -> 1489826 | P42: =IF(Base!Z36="","",Base!Z36) | Q42: =Base!S36 -> Difícil | R42: =Base!N36 -> 6195 | S42: =Base!T36 -> 83279.21
A43: =SUBTOTAL(103,$B$6:B43) -> 33 | B43: 87 | C43: =Base!H37 -> 2031310: CONSTRUCCION Y MEJORAMIENTO DE LA CARRETERA SAN JOSE (EMP. R 100) VALLE GRANDE -ISILLUMA DEL DISTRITO DE ALTO INAMBARI | D43: =Base!I37 -> 1122559 | E43: =Base!J37 -> 1117871 | F43: =D43-E43 -> 4687.95 | G43: =Base!L37 -> 1042098.6 | H43: =D43-G43 -> 80460.44 | I43: =IF(D43=0,0,G43/D43) -> 0.92832409 | J43: =Base!U37 -> Administración directa / Contrata / Personal/bienes/servicios | K43: =Base!R37 -> Ejecutado | L43: =Base!V37 -> 1404195 | M43: =Base!W37 -> 324567 | N43: =Base!X37 -> 0 | O43: =Base!Y37 -> 936265 | P43: =IF(Base!Z37="","",Base!Z37) | Q43: =Base!S37 -> No usar | R43: =Base!N37 -> 0 | S43: =Base!T37 -> 0
A44: =SUBTOTAL(103,$B$6:B44) -> 34 | B44: 92 | C44: =Base!H38 -> 2163760: MEJORAMIENTO DE LA INFRAESTRUCTURA VIAL TURISTICO, TRAMO PHUTINI - JAYU JAYU ACORA, DISTRITO DE ACORA - PUNO - PUNO | D44: =Base!I38 -> 1202934 | E44: =Base!J38 -> 1151623.8 | F44: =D44-E44 -> 51310.21 | G44: =Base!L38 -> 1105100.4 | H44: =D44-G44 -> 97833.58 | I44: =IF(D44=0,0,G44/D44) -> 0.91867087 | J44: =Base!U38 -> Administración directa / Contrata / Personal/bienes/servicios | K44: =Base!R38 -> Ejecutado | L44: =Base!V38 -> 2596051 | M44: =Base!W38 -> 120000 | N44: =Base!X38 -> 2215461 | O44: =Base!Y38 -> 3675255 | P44: =IF(Base!Z38="","",Base!Z38) | Q44: =Base!S38 -> No usar | R44: =Base!N38 -> 0 | S44: =Base!T38 -> 0
A45: =SUBTOTAL(103,$B$6:B45) -> 35 | B45: 104 | C45: =Base!H39 -> 2375549: CREACION DE LA INFRAESTRUCTURA DE INTEGRACION VIAL ENTRE SANDIA (CP. QUENEQUE) Y PATAMBUCO (C.P. TIRACA), DISTRITO DE SANDIA Y PATAMBUCO, PROVINCIA DE SANDIA - PUNO | D45: =Base!I39 -> 167638 | E45: =Base!J39 -> 167637.03 | F45: =D45-E45 -> 0.97 | G45: =Base!L39 -> 124800.07 | H45: =D45-G45 -> 42837.93 | I45: =IF(D45=0,0,G45/D45) -> 0.7444617 | J45: =Base!U39 -> Administración directa | K45: =Base!R39 -> Mayormente comprometido | L45: =Base!V39 -> 1200000 | M45: =Base!W39 -> 2500000 | N45: =Base!X39 -> 2882362 | O45: =Base!Y39 -> 1526602 | P45: =IF(Base!Z39="","",Base!Z39) | Q45: =Base!S39 -> Difícil | R45: =Base!N39 -> 0 | S45: =Base!T39 -> 0.97
A46: =SUBTOTAL(103,$B$6:B46) -> 36 | B46: 101 | C46: =Base!H40 -> 2321290: MEJORAMIENTO DE LOS SERVICIOS DE TRANSITABILIDAD DE LA VÍA VECINAL PU-595: DV. PAMPA BLANCA - RINCONADA - CERRO LUNAR, DISTRITO DE ANANEA, PROVINCIA DE SAN ANTONIO DE PUTINA - PUNO | D46: =Base!I40 -> 844818 | E46: =Base!J40 -> 75387.03 | F46: =D46-E46 -> 769430.97 | G46: =Base!L40 -> 75387.03 | H46: =D46-G46 -> 769430.97 | I46: =IF(D46=0,0,G46/D46) -> 0.08923464 | J46: =Base!U40 -> Contrata / Laudos arbitrales / Personal/bienes/servicios | K46: =Base!R40 -> Parcialmente comprometido | L46: =Base!V40 -> 1050000 | M46: =Base!W40 -> 50000 | N46: =Base!X40 -> 1054806 | O46: =Base!Y40 -> 0 | P46: =IF(Base!Z40="","",Base!Z40) | Q46: =Base!S40 -> Parcial | R46: =Base!N40 -> 0 | S46: =Base!T40 -> 769430.97
A47: =SUBTOTAL(103,$B$6:B47) -> 37 | B47: 166 | C47: =Base!H41 -> 2475053: MEJORAMIENTO DEL SERVICIO DE MOVILIDAD URBANA DE LA AV. ANDRES AVELINO CACERES (TRAMO: AV. TUPAC YUPANQUI - AV. AVIACIÓN), AV. LOS GERANIOS DEL DISTRITO DE JULIACA - PROVINCIA DE SAN ROMAN - DEPARTAMENTO DE PUNO | D47: =Base!I41 -> 0 | E47: =Base!J41 -> 0 | F47: =D47-E47 -> 0 | G47: =Base!L41 -> 0 | H47: =D47-G47 -> 0 | I47: =IF(D47=0,0,G47/D47) -> 0 | J47: =Base!U41 -> Administración directa | K47: =Base!R41 -> Sin PIM | L47: =Base!V41 -> 675842 | M47: =Base!W41 -> 110000 | N47: =Base!X41 -> 0 | O47: =Base!Y41 -> 0 | P47: =IF(Base!Z41="","",Base!Z41) | Q47: =Base!S41 -> Sin PIM | R47: =Base!N41 -> 0 | S47: =Base!T41 -> 0
A48: =SUBTOTAL(103,$B$6:B48) -> 38 | B48: 90 | C48: =Base!H42 -> 2131661: CONSTRUCCION Y MEJORAMIENTO DE LA CARRETERA DESVIO VILQUECHICO-COJATA-SINA-YANAHUAYA. | D48: =Base!I42 -> 459851 | E48: =Base!J42 -> 344060.18 | F48: =D48-E48 -> 115790.82 | G48: =Base!L42 -> 300345.76 | H48: =D48-G48 -> 159505.24 | I48: =IF(D48=0,0,G48/D48) -> 0.65313712 | J48: =Base!U42 -> Administración directa / Equipamiento | K48: =Base!R42 -> Mayormente comprometido | L48: =Base!V42 -> 4800690 | M48: =Base!W42 -> 4000000 | N48: =Base!X42 -> 14883202 | O48: =Base!Y42 -> 19038629 | P48: =IF(Base!Z42="","",Base!Z42) | Q48: =Base!S42 -> Difícil | R48: =Base!N42 -> 0 | S48: =Base!T42 -> 115790.82
A49: =SUBTOTAL(103,$B$6:B49) -> 39 | B49: 96 | C49: =Base!H43 -> 2195487: MEJORAMIENTO DEL CAMINO VECINAL (EMP. PE 3S) HUAQUINA ZAPIJICANE - PTO JULI - CHUCASUYO DEL DISTRITO DE JULI - PROVINCIA DE CHUCUITO - DEPARTAMENTO DE PUNO | D49: =Base!I43 -> 91759 | E49: =Base!J43 -> 91758.5 | F49: =D49-E49 -> 0.5 | G49: =Base!L43 -> 82094.58 | H49: =D49-G49 -> 9664.42 | I49: =IF(D49=0,0,G49/D49) -> 0.89467605 | J49: =Base!U43 -> Contrata / Administración directa / Personal/bienes/servicios | K49: =Base!R43 -> Mayormente comprometido | L49: =Base!V43 -> 774665 | M49: =Base!W43 -> 0 | N49: =Base!X43 -> 707599 | O49: =Base!Y43 -> 0 | P49: =IF(Base!Z43="","",Base!Z43) | Q49: =Base!S43 -> Difícil | R49: =Base!N43 -> 9450 | S49: =Base!T43 -> 9450.5
A50: =SUBTOTAL(103,$B$6:B50) -> 40 | B50: 113 | C50: =Base!H44 -> 2514428: CREACION DEL SERVICIO DE INTERCONEXION DE MOVILIDAD URBANA EN LA VÍA TRONCAL DEL PUENTE YARAJA DISTRITO DE AZANGARO - PROVINCIA DE AZANGARO - DEPARTAMENTO DE PUNO | D50: =Base!I44 -> 104124 | E50: =Base!J44 -> 48234.88 | F50: =D50-E50 -> 55889.12 | G50: =Base!L44 -> 48234.88 | H50: =D50-G50 -> 55889.12 | I50: =IF(D50=0,0,G50/D50) -> 0.46324459 | J50: =Base!U44 -> Administración directa / Contrata / Personal/bienes/servicios | K50: =Base!R44 -> Parcialmente comprometido | L50: =Base!V44 -> 228677 | M50: =Base!W44 -> 0 | N50: =Base!X44 -> 0 | O50: =Base!Y44 -> 865181 | P50: =IF(Base!Z44="","",Base!Z44) | Q50: =Base!S44 -> Parcial | R50: =Base!N44 -> 0 | S50: =Base!T44 -> 55889.12
... A62: =SUBTOTAL(103,$B$6:B62) -> 52 | B62: 108 | C62: =Base!H56 -> 2443679: MEJORAMIENTO DEL SERVICIO DE TRANSITABILIDAD VEHICULAR DE LA CARRETERA TRAMO I: EMP- 34L (COJATA) ¿ HUANCASAYA, TRAMO II: HUANCASAYA ¿ TARUCANI-EMP-PU-115 (INCHUPALLA), DEL DISTRITO DE COJATA - PROVINCIA DE HUANCANE - DEPARTAMENTO DE PUNO | D62: =Base!I56 -> 0 | E62: =Base!J56 -> 0 | F62: =D62-E62 -> 0 | G62: =Base!L56 -> 0 | H62: =D62-G62 -> 0 | I62: =IF(D62=0,0,G62/D62) -> 0 | J62: =Base!U56 -> Contrata | K62: =Base!R56 -> Sin PIM | L62: =Base!V56 -> 800000 | M62: =Base!W56 -> 2345478 | N62: =Base!X56 -> 9005306 | O62: =Base!Y56 -> 19493721 | P62: =IF(Base!Z56="","",Base!Z56) | Q62: =Base!S56 -> Sin PIM | R62: =Base!N56 -> 0 | S62: =Base!T56 -> 0
A63: 21. CULTURA Y DEPORTE | D63: =SUM(D64:D72) -> 24086616 | E63: =SUM(E64:E72) -> 20655001 | F63: =D63-E63 -> 3431614.6 | G63: =SUM(G64:G72) -> 5596985.4 | H63: =D63-G63 -> 18489631 | I63: =IF(D63=0,0,G63/D63) -> 0.2323691 | R63: =SUM(R64:R72) -> 7755541.8 | S63: =SUM(S64:S72) -> 11116655
A64: =SUBTOTAL(103,$B$6:B64) -> 53 | B64: 217 | C64: =Base!H57 -> 2163853: MEJORAMIENTO DEL ESTADIO MUNICIPAL CESAR RAUL CARRERA DEL DISTRITO DE AZANGARO, PROVINCIA DE AZANGARO - PUNO | D64: =Base!I57 -> 5810277 | E64: =Base!J57 -> 5204423.6 | F64: =D64-E64 -> 605853.4 | G64: =Base!L57 -> 1157372.6 | H64: =D64-G64 -> 4652904.4 | I64: =IF(D64=0,0,G64/D64) -> 0.19919405 | J64: =Base!U57 -> Administración directa / Contrata / Personal/bienes/servicios | K64: =Base!R57 -> Mayormente comprometido | L64: =Base!V57 -> 6269000 | M64: =Base!W57 -> 1345765 | N64: =Base!X57 -> 5566267 | O64: =Base!Y57 -> 0 | P64: =IF(Base!Z57="","",Base!Z57) | Q64: =Base!S57 -> Difícil | R64: =Base!N57 -> 2044173.5 | S64: =Base!T57 -> 2650027
A65: =SUBTOTAL(103,$B$6:B65) -> 54 | B65: 63 | C65: =Base!H58 -> 2188542: MEJORAMIENTO DE LA CAPACIDAD DE PRESTACION DE SERVICIOS DEPORTIVOS EN EL ESTADIO GUILLERMO BRICEÑO ROSAMEDINA DE LA CIUDAD DE JULIACA, PROVINCIA DE SAN ROMAN - PUNO | D65: =Base!I58 -> 5921783 | E65: =Base!J58 -> 5612635.5 | F65: =D65-E65 -> 309147.48 | G65: =Base!L58 -> 1271806.7 | H65: =D65-G65 -> 4649976.3 | I65: =IF(D65=0,0,G65/D65) -> 0.21476753 | J65: =Base!U58 -> Administración directa / Equipamiento / Contrata / Laudos arbitrales / Personal/bienes/servicios | K65: =Base!R58 -> Parcialmente comprometido | L65: =Base!V58 -> 1139986 | M65: =Base!W58 -> 500000 | N65: =Base!X58 -> 3220643 | O65: =Base!Y58 -> 0 | P65: =IF(Base!Z58="","",Base!Z58) | Q65: =Base!S58 -> Parcial | R65: =Base!N58 -> 3349455.2 | S65: =Base!T58 -> 3658602.6
A66: =SUBTOTAL(103,$B$6:B66) -> 55 | B66: 62 | C66: =Base!H59 -> 2186641: MEJORAMIENTO DEL SERVICIO DEPORTIVO, CULTURAL Y RECREACIONAL EN LA CAPITAL DE LA REGION PUNO | D66: =Base!I59 -> 1180793 | E66: =Base!J59 -> 1110291.7 | F66: =D66-E66 -> 70501.27 | G66: =Base!L59 -> 1081390.3 | H66: =D66-G66 -> 99402.73 | I66: =IF(D66=0,0,G66/D66) -> 0.91581697 | J66: =Base!U59 -> Administración directa | K66: =Base!R59 -> Ejecutado | L66: =Base!V59 -> 11675669 | M66: =Base!W59 -> 6000000 | N66: =Base!X59 -> 6503691 | O66: =Base!Y59 -> 7526858 | P66: =IF(Base!Z59="","",Base!Z59) | Q66: =Base!S59 -> No usar | R66: =Base!N59 -> 0 | S66: =Base!T59 -> 0
A67: =SUBTOTAL(103,$B$6:B67) -> 56 | B67: 72 | C67: =Base!H60 -> 2646100: CONSTRUCCION DE CAMPO DEPORTIVO Y SERVICIOS HIGIENICOS Y/O VESTIDORES PARA PERSONAL; REPARACION DE TRIBUNA Y/O PALCO; EN EL(LA) ESTADIO MUNICIPAL DE SAN PEDRO DE PUTINA PUNCO DISTRITO DE SAN PEDRO DE PUTINA PUNCO, PROVINCIA SANDIA, DEPARTAMENTO PUNO | D67: =Base!I60 -> 2167000 | E67: =Base!J60 -> 1860545 | F67: =D67-E67 -> 306455 | G67: =Base!L60 -> 33059.94 | H67: =D67-G67 -> 2133940.1 | I67: =IF(D67=0,0,G67/D67) -> 0.015256087 | J67: =Base!U60 -> Contrata / Personal/bienes/servicios | K67: =Base!R60 -> Mayormente comprometido | L67: =Base!V60 -> 2000000 | M67: =Base!W60 -> 1547463 | N67: =Base!X60 -> 0 | O67: =Base!Y60 -> 0 | P67: =IF(Base!Z60="","",Base!Z60) | Q67: =Base!S60 -> Difícil | R67: =Base!N60 -> 4210.2 | S67: =Base!T60 -> 310665.2
A68: =SUBTOTAL(103,$B$6:B68) -> 57 | B68: 67 | C68: =Base!H61 -> 2645380: CONSTRUCCION DE TRIBUNA Y/O PALCO, CAMPO DEPORTIVO Y PISTA DE ATLETISMO (DEPORTE RECREATIVO); REPARACION DE SERVICIOS HIGIENICOS Y/O VESTIDORES; ADEMÁS DE OTROS ACTIVOS EN EL(LA) ESTADIO MUNICIPAL FERNANDO ROMERO CARREÓN DISTRITO DE LAMPA, PROVINCIA LAMPA, DEPARTAMENTO PUNO | D68: =Base!I61 -> 2575916 | E68: =Base!J61 -> 2503779 | F68: =D68-E68 -> 72137 | G68: =Base!L61 -> 23527.19 | H68: =D68-G68 -> 2552388.8 | I68: =IF(D68=0,0,G68/D68) -> 0.0091335238 | J68: =Base!U61 -> Contrata / Personal/bienes/servicios | K68: =Base!R61 -> Mayormente comprometido | L68: =Base!V61 -> 2575916 | M68: =Base!W61 -> 2345678 | N68: =Base!X61 -> 1558799 | O68: =Base!Y61 -> 0 | P68: =IF(Base!Z61="","",Base!Z61) | Q68: =Base!S61 -> Difícil | R68: =Base!N61 -> 392219 | S68: =Base!T61 -> 464356
A69: =SUBTOTAL(103,$B$6:B69) -> 58 | B69: 71 | C69: =Base!H62 -> 2646096: CONSTRUCCION DE TRIBUNA Y/O PALCO; REPARACION DE TRIBUNA Y/O PALCO Y CAMPO DEPORTIVO; EN EL(LA) ESTADIO JOSE CARLOS MARIATEGUI DISTRITO DE YUNGUYO, PROVINCIA YUNGUYO, DEPARTAMENTO PUNO | D69: =Base!I62 -> 2054253 | E69: =Base!J62 -> 1854253 | F69: =D69-E69 -> 200000 | G69: =Base!L62 -> 0 | H69: =D69-G69 -> 2054253 | I69: =IF(D69=0,0,G69/D69) -> 0 | J69: =Base!U62 -> Contrata | K69: =Base!R62 -> Solo certificado | L69: =Base!V62 -> 2054253 | M69: =Base!W62 -> 2546789 | N69: =Base!X62 -> 0 | O69: =Base!Y62 -> 0 | P69: =IF(Base!Z62="","",Base!Z62) | Q69: =Base!S62 -> Posible | R69: =Base!N62 -> 1854253 | S69: =Base!T62 -> 2054253
A70: =SUBTOTAL(103,$B$6:B70) -> 59 | B70: 65 | C70: =Base!H63 -> 2645340: REPARACION DE TRIBUNA Y/O PALCO Y SERVICIOS HIGIENICOS Y/O VESTIDORES; CONSTRUCCION DE CAMPO DEPORTIVO; EN EL(LA) ESTADIO MUNICIPAL CRUCERO DISTRITO DE CRUCERO, PROVINCIA CARABAYA, DEPARTAMENTO PUNO | D70: =Base!I63 -> 2038388 | E70: =Base!J63 -> 2031210.5 | F70: =D70-E70 -> 7177.5 | G70: =Base!L63 -> 1711781.1 | H70: =D70-G70 -> 326606.88 | I70: =IF(D70=0,0,G70/D70) -> 0.83977198 | J70: =Base!U63 -> Contrata / Personal/bienes/servicios | K70: =Base!R63 -> Mayormente comprometido | L70: =Base!V63 -> 2028388 | M70: =Base!W63 -> 2258011 | N70: =Base!X63 -> 0 | O70: =Base!Y63 -> 0 | P70: =IF(Base!Z63="","",Base!Z63) | Q70: =Base!S63 -> Difícil | R70: =Base!N63 -> 0.13 | S70: =Base!T63 -> 7177.63
A71: =SUBTOTAL(103,$B$6:B71) -> 60 | B71: 252 | C71: =Base!H64 -> 2555837: REPARACION DE CAMPO DEPORTIVO; ADQUISICION DE EQUIPO NO DEPORTIVO PARA INSTALACIONES DEPORTIVAS; EN EL(LA) ESTADIO ENRIQUE TORRES BELON DISTRITO DE PUNO, PROVINCIA PUNO, DEPARTAMENTO PUNO | D71: =Base!I64 -> 2047936 | E71: =Base!J64 -> 377863 | F71: =D71-E71 -> 1670073 | G71: =Base!L64 -> 318047.53 | H71: =D71-G71 -> 1729888.5 | I71: =IF(D71=0,0,G71/D71) -> 0.1553015 | J71: =Base!U64 -> Contrata / Personal/bienes/servicios | K71: =Base!R64 -> Parcialmente comprometido | L71: =Base!V64 -> 327863 | M71: =Base!W64 -> 1876545 | N71: =Base!X64 -> 0 | O71: =Base!Y64 -> 0 | P71: =IF(Base!Z64="","",Base!Z64) | Q71: =Base!S64 -> Parcial | R71: =Base!N64 -> 11230.77 | S71: =Base!T64 -> 1681303.8
A72: =SUBTOTAL(103,$B$6:B72) -> 61 | B72: 260 | C72: =Base!H65 -> 2593683: REPARACION DE PISTA DE ATLETISMO (COMPETENCIA); ADQUISICION DE TORRE DE ILUMINACION; EN EL(LA) ESTADIO ENRIQUE TORRES BELON DEL DISTRITO DE PUNO, PROVINCIA PUNO, DEPARTAMENTO PUNO | D72: =Base!I65 -> 290270 | E72: =Base!J65 -> 100000 | F72: =D72-E72 -> 190270 | G72: =Base!L65 -> 0 | H72: =D72-G72 -> 290270 | I72: =IF(D72=0,0,G72/D72) -> 0 | J72: =Base!U65 -> Contrata | K72: =Base!R65 -> Solo certificado | L72: =Base!V65 -> 100000 | M72: =Base!W65 -> 2089685 | N72: =Base!X65 -> 3000000 | O72: =Base!Y65 -> 11639950 | P72: =IF(Base!Z65="","",Base!Z65) | Q72: =Base!S65 -> Posible | R72: =Base!N65 -> 100000 | S72: =Base!T65 -> 290270
A73: 03. PLANEAMIENTO, GESTION Y RESERVA DE CONTINGENCIA | D73: =SUM(D74:D74) -> 7609099 | E73: =SUM(E74:E74) -> 7595390.9 | F73: =D73-E73 -> 13708.12 | G73: =SUM(G74:G74) -> 7570246.4 | H73: =D73-G73 -> 38852.61 | I73: =IF(D73=0,0,G73/D73) -> 0.99489393 | R73: =SUM(R74:R74) -> 0 | S73: =SUM(S74:S74) -> 0
A74: =SUBTOTAL(103,$B$6:B74) -> 62 | B74: 259 | C74: =Base!H66 -> 2592407: MEJORAMIENTO DE LOS SERVICIOS OPERATIVOS O MISIONALES INSTITUCIONALES EN LA OFICINA DE EQUIPO MECANICO DEL GOBIERNO REGIONAL PUNO DISTRITO DE PUNO DE LA PROVINCIA DE PUNO DEL DEPARTAMENTO DE PUNO | D74: =Base!I66 -> 7609099 | E74: =Base!J66 -> 7595390.9 | F74: =D74-E74 -> 13708.12 | G74: =Base!L66 -> 7570246.4 | H74: =D74-G74 -> 38852.61 | I74: =IF(D74=0,0,G74/D74) -> 0.99489393 | J74: =Base!U66 -> Equipamiento / Contrata / Personal/bienes/servicios | K74: =Base!R66 -> Ejecutado | L74: =Base!V66 -> 6185000 | M74: =Base!W66 -> 1000000 | N74: =Base!X66 -> 0 | O74: =Base!Y66 -> 1000000 | P74: =IF(Base!Z66="","",Base!Z66) | Q74: =Base!S66 -> No usar | R74: =Base!N66 -> 0 | S74: =Base!T66 -> 0
A75: 23. PROTECCION SOCIAL | D75: =SUM(D76:D77) -> 232742 | E75: =SUM(E76:E77) -> 99007.59 | F75: =D75-E75 -> 133734.41 | G75: =SUM(G76:G77) -> 96198.77 | H75: =D75-G75 -> 136543.23 | I75: =IF(D75=0,0,G75/D75) -> 0.41332793 | R75: =SUM(R76:R77) -> 2340 | S75: =SUM(S76:S77) -> 133512
A76: =SUBTOTAL(103,$B$6:B76) -> 63 | B76: 456 | C76: =Base!H67 -> 2230752: MEJORAMIENTO DE LOS SERVICIOS ASISTENCIALES DE LA ALDEA INFANTIL VIRGEN DE LA CANDELARIA EN EL BARRIO LA RINCONADA DEL CENTRO POBLADO DE SALCEDO, DISTRITO DE PUNO, PROVINCIA DE PUNO, REGION DE PUNO | D76: =Base!I67 -> 99230 | E76: =Base!J67 -> 99007.59 | F76: =D76-E76 -> 222.41 | G76: =Base!L67 -> 96198.77 | H76: =D76-G76 -> 3031.23 | I76: =IF(D76=0,0,G76/D76) -> 0.96945248 | J76: =Base!U67 -> Administración directa / Contrata / Personal/bienes/servicios | K76: =Base!R67 -> Ejecutado | L76: =Base!V67 -> 99230 | M76: =Base!W67 -> 0 | N76: =Base!X67 -> 0 | O76: =Base!Y67 -> 0 | P76: =IF(Base!Z67="","",Base!Z67) | Q76: =Base!S67 -> No usar | R76: =Base!N67 -> 2340 | S76: =Base!T67 -> 0
A77: =SUBTOTAL(103,$B$6:B77) -> 64 | B77: 458 | C77: =Base!H68 -> 2194989: MEJORAMIENTO DE LOS SERVICIOS EDUCATIVOS EN LA INSTITUCION EDUCATIVA SECUNDARIA DANTE NAVA DEL CENTRO POBLADO SANTA CRUZ DE PUNA AYLLU, DISTRITO DE PATAMBUCO, PROVINCIA DE SANDIA, REGION PUNO | D77: =Base!I68 -> 133512 | E77: =Base!J68 -> 0 | F77: =D77-E77 -> 133512 | G77: =Base!L68 -> 0 | H77: =D77-G77 -> 133512 | I77: =IF(D77=0,0,G77/D77) -> 0 | J77: =Base!U68 -> Administración directa | K77: =Base!R68 -> Sin certificar | L77: =Base!V68 -> No registrado en cartera | M77: =Base!W68 -> No registrado en cartera | N77: =Base!X68 -> No registrado en cartera | O77: =Base!Y68 -> No registrado en cartera | P77: =IF(Base!Z68="","",Base!Z68) | Q77: =Base!S68 -> Disponible | R77: =Base!N68 -> 0 | S77: =Base!T68 -> 133512
A78: EJECUCIÓN POR ADMINISTRACIÓN DIRECTA - DIRECTIVA 17 | D78: =D79+D86+D107+D118 -> 267396323 | E78: =E79+E86+E107+E118 -> 2.4894579e+08 | F78: =D78-E78 -> 18450534 | G78: =G79+G86+G107+G118 -> 1.5910421e+08 | H78: =D78-G78 -> 1.0829211e+08 | I78: =IF(D78=0,0,G78/D78) -> 0.59501271 | R78: =R79+R86+R107+R118 -> 42470206 | S78: =S79+S86+S107+S118 -> 60587270
A79: 20. SALUD | D79: =SUM(D80:D85) -> 32634907 | E79: =SUM(E80:E85) -> 31001164 | F79: =D79-E79 -> 1633743.5 | G79: =SUM(G80:G85) -> 13051954 | H79: =D79-G79 -> 19582953 | I79: =IF(D79=0,0,G79/D79) -> 0.39993844 | R79: =SUM(R80:R85) -> 12178687 | S79: =SUM(S80:S85) -> 13812430
A80: =SUBTOTAL(103,$B$6:B80) -> 65 | B80: 242 | C80: =Base!H69 -> 2504553: MEJORAMIENTO DEL SERVICIO DE SALUD EN EL CENTRO DE SALUD YANAPATA DE LA MICRO RED COPANI, RED DE SALUD YUNGUYO, DISTRITO DE YUNGUYO - PROVINCIA DE YUNGUYO - DEPARTAMENTO DE PUNO | D80: =Base!I69 -> 8256172 | E80: =Base!J69 -> 7527846.9 | F80: =D80-E80 -> 728325.09 | G80: =Base!L69 -> 4485721.8 | H80: =D80-G80 -> 3770450.2 | I80: =IF(D80=0,0,G80/D80) -> 0.54331739 | J80: =Base!U69 -> Administración directa / Equipamiento / Contrata / Personal/bienes/servicios | K80: =Base!R69 -> Mayormente comprometido | L80: =Base!V69 -> 9468125 | M80: =Base!W69 -> 933429 | N80: =Base!X69 -> 6042788 | O80: =Base!Y69 -> 2500000 | P80: =IF(Base!Z69="","",Base!Z69) | Q80: =Base!S69 -> Difícil | R80: =Base!N69 -> 1800668.5 | S80: =Base!T69 -> 2528993.6
A81: =SUBTOTAL(103,$B$6:B81) -> 66 | B81: 237 | C81: =Base!H70 -> 2470517: MEJORAMIENTO DE LOS SERVICIOS DE SALUD DEL CENTRO DE SALUD COPANI DE LA MICRO RED COPANI, RED DE SALUD YUNGUYO, DISTRITO DE COPANI - PROVINCIA DE YUNGUYO - DEPARTAMENTO DE PUNO | D81: =Base!I70 -> 7374992 | E81: =Base!J70 -> 7374802 | F81: =D81-E81 -> 190 | G81: =Base!L70 -> 0 | H81: =D81-G81 -> 7374992 | I81: =IF(D81=0,0,G81/D81) -> 0 | J81: =Base!U70 -> Contrata | K81: =Base!R70 -> Solo certificado | L81: =Base!V70 -> 8000000 | M81: =Base!W70 -> 8258658 | N81: =Base!X70 -> 10741348 | O81: =Base!Y70 -> 1075057 | P81: =IF(Base!Z70="","",Base!Z70) | Q81: =Base!S70 -> Posible | R81: =Base!N70 -> 7374802 | S81: =Base!T70 -> 7374992
A82: =SUBTOTAL(103,$B$6:B82) -> 67 | B82: 228 | C82: =Base!H71 -> 2357092: MEJORAMIENTO DE LOS SERVICIOS DE SALUD DEL CENTRO DE SALUD COJATA, DISTRITO DE COJATA - PROVINCIA DE HUANCANE - DEPARTAMENTO DE PUNO | D82: =Base!I71 -> 6997430 | E82: =Base!J71 -> 6787158.8 | F82: =D82-E82 -> 210271.19 | G82: =Base!L71 -> 2630352.4 | H82: =D82-G82 -> 4367077.6 | I82: =IF(D82=0,0,G82/D82) -> 0.37590264 | J82: =Base!U71 -> Administración directa / Contrata / Personal/bienes/servicios / Equipamiento | K82: =Base!R71 -> Mayormente comprometido | L82: =Base!V71 -> 8000000 | M82: =Base!W71 -> 10256256 | N82: =Base!X71 -> 15069544 | O82: =Base!Y71 -> 4478827 | P82: =IF(Base!Z71="","",Base!Z71) | Q82: =Base!S71 -> Difícil | R82: =Base!N71 -> 1421093.7 | S82: =Base!T71 -> 1631364.9
A83: =SUBTOTAL(103,$B$6:B83) -> 68 | B83: 241 | C83: =Base!H72 -> 2494039: MEJORAMIENTO Y AMPLIACION DE LOS SERVICIOS DE SALUD EN EL ESTABLECIMIENTO DE SALUD UMACHIRI CATEGORÍA I-2 DEL DISTRITO DE UMACHIRI - PROVINCIA DE MELGAR - DEPARTAMENTO DE PUNO | D83: =Base!I72 -> 6688287 | E83: =Base!J72 -> 6156914.2 | F83: =D83-E83 -> 531372.77 | G83: =Base!L72 -> 3692512.7 | H83: =D83-G83 -> 2995774.3 | I83: =IF(D83=0,0,G83/D83) -> 0.55208646 | J83: =Base!U72 -> Administración directa / Equipamiento / Contrata / Personal/bienes/servicios | K83: =Base!R72 -> Mayormente comprometido | L83: =Base!V72 -> 2822702 | M83: =Base!W72 -> 65844 | N83: =Base!X72 -> 0 | O83: =Base!Y72 -> 0 | P83: =IF(Base!Z72="","",Base!Z72) | Q83: =Base!S72 -> Difícil | R83: =Base!N72 -> 1255808.5 | S83: =Base!T72 -> 1787181.3
A84: =SUBTOTAL(103,$B$6:B84) -> 69 | B84: 221 | C84: =Base!H73 -> 2290342: MEJORAMIENTO DE LA CAPACIDAD RESOLUTIVA DE LOS SERVICIOS DEL PUESTO DE SALUD I - 1 DEL CENTRO POBLADO DE CARI CARI DEL DISTRITO DE MAÑAZO - PROVINCIA DE PUNO - DEPARTAMENTO DE PUNO | D84: =Base!I73 -> 3318026 | E84: =Base!J73 -> 3154441.6 | F84: =D84-E84 -> 163584.43 | G84: =Base!L73 -> 2243366.7 | H84: =D84-G84 -> 1074659.3 | I84: =IF(D84=0,0,G84/D84) -> 0.67611487 | J84: =Base!U73 -> Administración directa / Equipamiento / Contrata / Expediente técnico / Personal/bienes/servicios | K84: =Base!R73 -> Mayormente comprometido | L84: =Base!V73 -> 821892 | M84: =Base!W73 -> 47336 | N84: =Base!X73 -> 0 | O84: =Base!Y73 -> 0 | P84: =IF(Base!Z73="","",Base!Z73) | Q84: =Base!S73 -> Difícil | R84: =Base!N73 -> 326314.17 | S84: =Base!T73 -> 489898.6
A85: =SUBTOTAL(103,$B$6:B85) -> 70 | B85: 235 | C85: =Base!H74 -> 2451529: MEJORAMIENTO DEL SERVICIO DE SALUD EN EL CENTRO DE SALUD PILCUYO DE LA MICRORED PILCUYO, RED DE SALUD EL COLLAO , DEL DISTRITO DE PILCUYO - PROVINCIA DE EL COLLAO - DEPARTAMENTO DE PUNO | D85: =Base!I74 -> 0 | E85: =Base!J74 -> 0 | F85: =D85-E85 -> 0 | G85: =Base!L74 -> 0 | H85: =D85-G85 -> 0 | I85: =IF(D85=0,0,G85/D85) -> 0 | J85: =Base!U74 -> Contrata | K85: =Base!R74 -> Sin PIM | L85: =Base!V74 -> 12571000 | M85: =Base!W74 -> 5987564 | N85: =Base!X74 -> 16094501 | O85: =Base!Y74 -> 22576094 | P85: =IF(Base!Z74="","",Base!Z74) | Q85: =Base!S74 -> Sin PIM | R85: =Base!N74 -> 0 | S85: =Base!T74 -> 0
A86: 22. EDUCACION | D86: =SUM(D87:D106) -> 160639248 | E86: =SUM(E87:E106) -> 1.5009595e+08 | F86: =D86-E86 -> 10543296 | G86: =SUM(G87:G106) -> 1.0464849e+08 | H86: =D86-G86 -> 55990754 | I86: =IF(D86=0,0,G86/D86) -> 0.65145035 | R86: =SUM(R87:R106) -> 17011197 | S86: =SUM(S87:S106) -> 27337014
A87: =SUBTOTAL(103,$B$6:B87) -> 71 | B87: 35 | C87: =Base!H75 -> 2411336: MEJORAMIENTO SERVICIO INTEGRAL DE LA INSTITUCION EDUCATIVA SECUNDARIA INDUSTRIAL PERU BIRF DISTRITO DE SAN MIGUEL - PROVINCIA DE SAN ROMAN - DEPARTAMENTO DE PUNO | D87: =Base!I75 -> 21914154 | E87: =Base!J75 -> 21776068 | F87: =D87-E87 -> 138085.94 | G87: =Base!L75 -> 15564867 | H87: =D87-G87 -> 6349286.6 | I87: =IF(D87=0,0,G87/D87) -> 0.7102655 | J87: =Base!U75 -> Administración directa / Equipamiento / Contrata / Personal/bienes/servicios / Laudos arbitrales | K87: =Base!R75 -> Mayormente comprometido | L87: =Base!V75 -> 11955231 | M87: =Base!W75 -> 2500000 | N87: =Base!X75 -> 3884089 | O87: =Base!Y75 -> 0 | P87: =IF(Base!Z75="","",Base!Z75) | Q87: =Base!S75 -> Difícil | R87: =Base!N75 -> 1248743.9 | S87: =Base!T75 -> 1386829.9
A88: =SUBTOTAL(103,$B$6:B88) -> 72 | B88: 25 | C88: =Base!H76 -> 2284935: MEJORAMIENTO DEL SERVICIO EDUCATIVO EN LA IES POLITÉCNICO REGIONAL LOS ANDES, DISTRITO DE JULIACA, PROVINCIA DE SAN ROMÁN - PUNO | D88: =Base!I76 -> 22276780 | E88: =Base!J76 -> 17912911 | F88: =D88-E88 -> 4363868.8 | G88: =Base!L76 -> 15417466 | H88: =D88-G88 -> 6859314 | I88: =IF(D88=0,0,G88/D88) -> 0.69208683 | J88: =Base!U76 -> Administración directa / Contrata / Personal/bienes/servicios / Equipamiento | K88: =Base!R76 -> Mayormente comprometido | L88: =Base!V76 -> 15800000 | M88: =Base!W76 -> 14789542 | N88: =Base!X76 -> 15918407 | O88: =Base!Y76 -> 10295229 | P88: =IF(Base!Z76="","",Base!Z76) | Q88: =Base!S76 -> Difícil | R88: =Base!N76 -> 195132.49 | S88: =Base!T76 -> 4559001.3
A89: =SUBTOTAL(103,$B$6:B89) -> 73 | B89: 229 | C89: =Base!H77 -> 2357330: MEJORAMIENTO DE LOS SERVICIOS DE EDUCACIÓN SUPERIOR TECNOLÓGICA DEL IESTP HUANCANÉ DEL DISTRITO DE HUANCANE - PROVINCIA DE HUANCANE - DEPARTAMENTO DE PUNO | D89: =Base!I77 -> 17354707 | E89: =Base!J77 -> 17083718 | F89: =D89-E89 -> 270988.58 | G89: =Base!L77 -> 8610007.7 | H89: =D89-G89 -> 8744699.3 | I89: =IF(D89=0,0,G89/D89) -> 0.49611945 | J89: =Base!U77 -> Administración directa / Equipamiento / Contrata / Personal/bienes/servicios | K89: =Base!R77 -> Mayormente comprometido | L89: =Base!V77 -> 12500000 | M89: =Base!W77 -> 4806839 | N89: =Base!X77 -> 753613 | O89: =Base!Y77 -> 0 | P89: =IF(Base!Z77="","",Base!Z77) | Q89: =Base!S77 -> Difícil | R89: =Base!N77 -> 3707733.7 | S89: =Base!T77 -> 3978722.3
A90: =SUBTOTAL(103,$B$6:B90) -> 74 | B90: 30 | C90: =Base!H78 -> 2357322: MEJORAMIENTO SERVICIO EDUCATIVO EN LA IES. 32 MARIANO H. CORNEJO DE LA LOCALIDAD DE JULIACA - DISTRITO DE JULIACA - PROVINCIA DE SAN ROMAN - REGIÓN PUNO | D90: =Base!I78 -> 19795501 | E90: =Base!J78 -> 19793412 | F90: =D90-E90 -> 2089.28 | G90: =Base!L78 -> 14545766 | H90: =D90-G90 -> 5249734.8 | I90: =IF(D90=0,0,G90/D90) -> 0.73480162 | J90: =Base!U78 -> Administración directa / Equipamiento / Contrata / Personal/bienes/servicios | K90: =Base!R78 -> Mayormente comprometido | L90: =Base!V78 -> 9609000 | M90: =Base!W78 -> 897867 | N90: =Base!X78 -> 6124874 | O90: =Base!Y78 -> 0 | P90: =IF(Base!Z78="","",Base!Z78) | Q90: =Base!S78 -> Difícil | R90: =Base!N78 -> 1659217 | S90: =Base!T78 -> 1661306.3
A91: =SUBTOTAL(103,$B$6:B91) -> 75 | B91: 33 | C91: =Base!H79 -> 2385673: MEJORAMIENTO DEL SERVICIO EDUCATIVO DE LA I.E.S. LAS MERCEDES DE LA CIUDAD DE JULIACA - DISTRITO DE JULIACA - PROVINCIA DE SAN ROMAN - DEPARTAMENTO DE PUNO | D91: =Base!I79 -> 17241964 | E91: =Base!J79 -> 17144705 | F91: =D91-E91 -> 97259.44 | G91: =Base!L79 -> 11639796 | H91: =D91-G91 -> 5602167.7 | I91: =IF(D91=0,0,G91/D91) -> 0.67508529 | J91: =Base!U79 -> Administración directa / Contrata / Personal/bienes/servicios / Equipamiento | K91: =Base!R79 -> Mayormente comprometido | L91: =Base!V79 -> 8016014 | M91: =Base!W79 -> 10000000 | N91: =Base!X79 -> 1057112 | O91: =Base!Y79 -> 2541629 | P91: =IF(Base!Z79="","",Base!Z79) | Q91: =Base!S79 -> Difícil | R91: =Base!N79 -> 2244212.2 | S91: =Base!T79 -> 2341471.6
A92: =SUBTOTAL(103,$B$6:B92) -> 76 | B92: 161 | C92: =Base!H80 -> 2585543: MEJORAMIENTO Y AMPLIACION DEL SERVICIO DE EDUCACIÓN SUPERIOR TECNOLÓGICA EN EL INSTITUTO DE EDUCACIÓN SUPERIOR TECNOLÓGICO PUBLICO ACORA DEL DISTRITO DE ACORA DE LA PROVINCIA DE PUNO DEL DEPARTAMENTO DE PUNO | D92: =Base!I80 -> 15380884 | E92: =Base!J80 -> 14270657 | F92: =D92-E92 -> 1110226.8 | G92: =Base!L80 -> 9463521.5 | H92: =D92-G92 -> 5917362.5 | I92: =IF(D92=0,0,G92/D92) -> 0.61527812 | J92: =Base!U80 -> Administración directa / Equipamiento / Contrata / Personal/bienes/servicios | K92: =Base!R80 -> Mayormente comprometido | L92: =Base!V80 -> 6000000 | M92: =Base!W80 -> 3456765 | N92: =Base!X80 -> 1108030 | O92: =Base!Y80 -> 0 | P92: =IF(Base!Z80="","",Base!Z80) | Q92: =Base!S80 -> Difícil | R92: =Base!N80 -> 3007700.4 | S92: =Base!T80 -> 4117927.3
A93: =SUBTOTAL(103,$B$6:B93) -> 77 | B93: 247 | C93: =Base!H81 -> 2535611: MEJORAMIENTO Y AMPLIACION DEL SERVICIO DE EDUCACION SUPERIOR TECNOLOGICO PUBLICO EN EL INSTITUTO "ANDRES AVELINO CACERES" DISTRITO DE PUTINA - PROVINCIA DE SAN ANTONIO DE PUTINA - DEPARTAMENTO DE PUNO | D93: =Base!I81 -> 9666000 | E93: =Base!J81 -> 9191703.8 | F93: =D93-E93 -> 474296.17 | G93: =Base!L81 -> 5594991.1 | H93: =D93-G93 -> 4071008.9 | I93: =IF(D93=0,0,G93/D93) -> 0.5788321 | J93: =Base!U81 -> Administración directa / Contrata / Personal/bienes/servicios | K93: =Base!R81 -> Mayormente comprometido | L93: =Base!V81 -> 7546000 | M93: =Base!W81 -> 1410563 | N93: =Base!X81 -> 1509243 | O93: =Base!Y81 -> 0 | P93: =IF(Base!Z81="","",Base!Z81) | Q93: =Base!S81 -> Difícil | R93: =Base!N81 -> 2370407.1 | S93: =Base!T81 -> 2844703.3
A94: =SUBTOTAL(103,$B$6:B94) -> 78 | B94: 39 | C94: =Base!H82 -> 2538950: MEJORAMIENTO DEL SERVICIO EDUCATIVO DEL NIVEL PRIMARIO DE LA I.E. 71008 EN EL DISTRITO DE LAMPA - PROVINCIA DE LAMPA - DEPARTAMENTO DE PUNO | D94: =Base!I82 -> 6765264 | E94: =Base!J82 -> 6659441.2 | F94: =D94-E94 -> 105822.81 | G94: =Base!L82 -> 4177875.5 | H94: =D94-G94 -> 2587388.5 | I94: =IF(D94=0,0,G94/D94) -> 0.61754804 | J94: =Base!U82 -> Administración directa / Equipamiento / Contrata / Personal/bienes/servicios | K94: =Base!R82 -> Mayormente comprometido | L94: =Base!V82 -> No registrado en cartera | M94: =Base!W82 -> No registrado en cartera | N94: =Base!X82 -> No registrado en cartera | O94: =Base!Y82 -> No registrado en cartera | P94: =IF(Base!Z82="","",Base!Z82) | Q94: =Base!S82 -> Difícil | R94: =Base!N82 -> 1300971.4 | S94: =Base!T82 -> 1406794.2
A95: =SUBTOTAL(103,$B$6:B95) -> 79 | B95: 26 | C95: =Base!H83 -> 2289661: MEJORAMIENTO DE LOS SERVICIOS EDUCATIVOS EN LA I.E.S. DOS DE MAYO DE CARACOTO, DISTRITO DE CARACOTO - SAN ROMAN - PUNO | D95: =Base!I83 -> 4291327 | E95: =Base!J83 -> 4093667 | F95: =D95-E95 -> 197659.95 | G95: =Base!L83 -> 3891386.8 | H95: =D95-G95 -> 399940.21 | I95: =IF(D95=0,0,G95/D95) -> 0.90680267 | J95: =Base!U83 -> Administración directa / Contrata / Equipamiento / Personal/bienes/servicios | K95: =Base!R83 -> Ejecutado | L95: =Base!V83 -> No registrado en cartera | M95: =Base!W83 -> No registrado en cartera | N95: =Base!X83 -> No registrado en cartera | O95: =Base!Y83 -> No registrado en cartera | P95: =IF(Base!Z83="","",Base!Z83) | Q95: =Base!S83 -> No usar | R95: =Base!N83 -> 741.38 | S95: =Base!T83 -> 0
A96: =SUBTOTAL(103,$B$6:B96) -> 80 | B96: 41 | C96: =Base!H84 -> 2590087: MEJORAMIENTO DEL SERVICIO DE EDUCACION SECUNDARIA EN I.E. JOSE MARIA ARGUEDAS DISTRITO DE LLALLI DE LA PROVINCIA DE MELGAR DEL DEPARTAMENTO DE PUNO | D96: =Base!I84 -> 5799805 | E96: =Base!J84 -> 5459070.3 | F96: =D96-E96 -> 340734.7 | G96: =Base!L84 -> 3888315.9 | H96: =D96-G96 -> 1911489.1 | I96: =IF(D96=0,0,G96/D96) -> 0.67042183 | J96: =Base!U84 -> Administración directa / Contrata / Equipamiento / Personal/bienes/servicios | K96: =Base!R84 -> Mayormente comprometido | L96: =Base!V84 -> No registrado en cartera | M96: =Base!W84 -> No registrado en cartera | N96: =Base!X84 -> No registrado en cartera | O96: =Base!Y84 -> No registrado en cartera | P96: =IF(Base!Z84="","",Base!Z84) | Q96: =Base!S84 -> Difícil | R96: =Base!N84 -> 454923.03 | S96: =Base!T84 -> 795657.73
A97: =SUBTOTAL(103,$B$6:B97) -> 81 | B97: 36 | C97: =Base!H85 -> 2417765: MEJORAMIENTO Y AMPLIACION DEL SERVICIOS DE EDUCACION BASICA EN EL NIVEL PRIMARIO DE LA IEP Nº 72169 TAMBILLO, IEP Nº 72175 TAYACCUCHO, IEP Nº 72188 QUETY, IEP Nº 72642 MALLCUAPO, IEP Nº 72749 CALASUCA DEL DISTRITO DE ITUATA - PROVINCIA DE CARABAYA - DEPARTAMENTO DE PUNO DISTRITO DE ITUATA - PROVINCIA DE CARABAYA - DEPARTAMENTO DE PUNO | D97: =Base!I85 -> 4802506 | E97: =Base!J85 -> 4376181.6 | F97: =D97-E97 -> 426324.38 | G97: =Base!L85 -> 3250907.8 | H97: =D97-G97 -> 1551598.2 | I97: =IF(D97=0,0,G97/D97) -> 0.67691905 | J97: =Base!U85 -> Administración directa / Contrata / Equipamiento / Personal/bienes/servicios | K97: =Base!R85 -> Mayormente comprometido | L97: =Base!V85 -> 3770000 | M97: =Base!W85 -> 876556 | N97: =Base!X85 -> 4649244 | O97: =Base!Y85 -> 7795363 | P97: =IF(Base!Z85="","",Base!Z85) | Q97: =Base!S85 -> Difícil | R97: =Base!N85 -> 284023 | S97: =Base!T85 -> 710347.38
A98: =SUBTOTAL(103,$B$6:B98) -> 82 | B98: 311 | C98: =Base!H86 -> 2417765: MEJORAMIENTO Y AMPLIACION DEL SERVICIOS DE EDUCACION BASICA EN EL NIVEL PRIMARIO DE LA IEP Nº 72169 TAMBILLO, IEP Nº 72175 TAYACCUCHO, IEP Nº 72188 QUETY, IEP Nº 72642 MALLCUAPO, IEP Nº 72749 CALASUCA DEL DISTRITO DE ITUATA - PROVINCIA DE CARABAYA - DEPARTAMENTO DE PUNO DISTRITO DE ITUATA - PROVINCIA DE CARABAYA - DEPARTAMENTO DE PUNO | D98: =Base!I86 -> 4992699 | E98: =Base!J86 -> 4276945.2 | F98: =D98-E98 -> 715753.79 | G98: =Base!L86 -> 3252598.6 | H98: =D98-G98 -> 1740100.4 | I98: =IF(D98=0,0,G98/D98) -> 0.651471 | J98: =Base!U86 -> Administración directa / Contrata / Equipamiento / Personal/bienes/servicios | K98: =Base!R86 -> Mayormente comprometido | L98: =Base!V86 -> 3770000 | M98: =Base!W86 -> 876556 | N98: =Base!X86 -> 4649244 | O98: =Base!Y86 -> 7795363 | P98: =IF(Base!Z86="","",Base!Z86) | Q98: =Base!S86 -> Difícil | R98: =Base!N86 -> 158173.25 | S98: =Base!T86 -> 873927.04
... A106: =SUBTOTAL(103,$B$6:B106) -> 90 | B106: 83 | C106: =Base!H94 -> 2627406: RENOVACION DE AMBIENTE COMPLEMENTARIO, AULA DE EDUCACION SUPERIOR PEDAGOGICA Y CERCO PERIMETRICO; ADQUISICION DE MOBILIARIO DE AULA DE EDUCACION SUPERIOR PEDAGOGICA; ADEMÁS DE OTROS ACTIVOS EN EL(LA) INSTITUTO DE EDUCACION SUPERIOR PEDAGOGICA PUBLICO JULI DEL DISTRITO DE JULI, PROVINCIA CHUCUITO, DEPARTAMENTO PUNO | D106: =Base!I94 -> 61203 | E106: =Base!J94 -> 0 | F106: =D106-E106 -> 61203 | G106: =Base!L94 -> 0 | H106: =D106-G106 -> 61203 | I106: =IF(D106=0,0,G106/D106) -> 0 | J106: =Base!U94 -> Administración directa | K106: =Base!R94 -> Sin certificar | L106: =Base!V94 -> 61203 | M106: =Base!W94 -> 0 | N106: =Base!X94 -> 0 | O106: =Base!Y94 -> 0 | P106: =IF(Base!Z94="","",Base!Z94) | Q106: =Base!S94 -> Disponible | R106: =Base!N94 -> 0 | S106: =Base!T94 -> 61203
A107: 15. TRANSPORTE | D107: =SUM(D108:D117) -> 67673088 | E107: =SUM(E108:E117) -> 61457129 | F107: =D107-E107 -> 6215958.7 | G107: =SUM(G108:G117) -> 41195299 | H107: =D107-G107 -> 26477789 | I107: =IF(D107=0,0,G107/D107) -> 0.60873975 | R107: =SUM(R108:R117) -> 7451118.2 | S107: =SUM(S108:S117) -> 13551086
A108: =SUBTOTAL(103,$B$6:B108) -> 91 | B108: 110 | C108: =Base!H95 -> 2456529: MEJORAMIENTO DE LA CARRETERA PU 147, EMP. PE-34I JIPATA - EMP. PE-34I MOHO, DISTRITO DE MOHO - PROVINCIA DE MOHO - DEPARTAMENTO DE PUNO | D108: =Base!I95 -> 23143575 | E108: =Base!J95 -> 22275711 | F108: =D108-E108 -> 867864.16 | G108: =Base!L95 -> 12059018 | H108: =D108-G108 -> 11084557 | I108: =IF(D108=0,0,G108/D108) -> 0.52105253 | J108: =Base!U95 -> Administración directa / Contrata / Personal/bienes/servicios | K108: =Base!R95 -> Mayormente comprometido | L108: =Base!V95 -> 15500800 | M108: =Base!W95 -> 4458489 | N108: =Base!X95 -> 450011 | O108: =Base!Y95 -> 0 | P108: =IF(Base!Z95="","",Base!Z95) | Q108: =Base!S95 -> Difícil | R108: =Base!N95 -> 3243862 | S108: =Base!T95 -> 4111726.2
A109: =SUBTOTAL(103,$B$6:B109) -> 92 | B109: 103 | C109: =Base!H96 -> 2343199: MEJORAMIENTO DE LA CARRETERA (EMP 34B) AZANGARO - (EMP PU-102) JILA PURINA DE LOS DISTRITO DE AZÁNGARO - DISTRITO DE TIRAPATA - PROVINCIA DE AZANGARO - REGIÓN PUNO | D109: =Base!I96 -> 14991498 | E109: =Base!J96 -> 14685003 | F109: =D109-E109 -> 306495.03 | G109: =Base!L96 -> 11502167 | H109: =D109-G109 -> 3489331.3 | I109: =IF(D109=0,0,G109/D109) -> 0.76724599 | J109: =Base!U96 -> Administración directa / Contrata / Personal/bienes/servicios | K109: =Base!R96 -> Mayormente comprometido | L109: =Base!V96 -> 12491498 | M109: =Base!W96 -> 632388 | N109: =Base!X96 -> 41870 | O109: =Base!Y96 -> 0 | P109: =IF(Base!Z96="","",Base!Z96) | Q109: =Base!S96 -> Difícil | R109: =Base!N96 -> 1100297.9 | S109: =Base!T96 -> 1406792.9
A110: =SUBTOTAL(103,$B$6:B110) -> 93 | B110: 106 | C110: =Base!H97 -> 2399543: MEJORAMIENTO DEL CAMINO VECINAL EMP. R01 (DV. LOANI) - CAMICACHI - EMP. R12 (ROSACANI) DISTRITO DE ILAVE - PROVINCIA DE EL COLLAO - REGION PUNO | D110: =Base!I97 -> 5270087 | E110: =Base!J97 -> 5222084.3 | F110: =D110-E110 -> 48002.71 | G110: =Base!L97 -> 5220159.3 | H110: =D110-G110 -> 49927.71 | I110: =IF(D110=0,0,G110/D110) -> 0.99052621 | J110: =Base!U97 -> Administración directa / Contrata / Personal/bienes/servicios | K110: =Base!R97 -> Ejecutado | L110: =Base!V97 -> No registrado en cartera | M110: =Base!W97 -> No registrado en cartera | N110: =Base!X97 -> No registrado en cartera | O110: =Base!Y97 -> No registrado en cartera | P110: =IF(Base!Z97="","",Base!Z97) | Q110: =Base!S97 -> No usar | R110: =Base!N97 -> 0 | S110: =Base!T97 -> 0
A111: =SUBTOTAL(103,$B$6:B111) -> 94 | B111: 119 | C111: =Base!H98 -> 2591951: MEJORAMIENTO DEL SERVICIO DE TRANSITABILIDAD VIAL INTERURBANA EN EL CAMINO VECINAL DEL KM0+000 (DESVIO PUENTE OCRA CHUPA) AL KM 6+373 (C.P. PEDRO VILCAPAZA DE MORORCCO), DISTRITO DE MUÑANI DE LA PROVINCIA DE AZANGARO DEL DEPARTAMENTO DE PUNO | D111: =Base!I98 -> 6770858 | E111: =Base!J98 -> 6051014.3 | F111: =D111-E111 -> 719843.71 | G111: =Base!L98 -> 3961148.7 | H111: =D111-G111 -> 2809709.3 | I111: =IF(D111=0,0,G111/D111) -> 0.58502906 | J111: =Base!U98 -> Administración directa / Contrata / Personal/bienes/servicios / Equipamiento | K111: =Base!R98 -> Mayormente comprometido | L111: =Base!V98 -> No registrado en cartera | M111: =Base!W98 -> No registrado en cartera | N111: =Base!X98 -> No registrado en cartera | O111: =Base!Y98 -> No registrado en cartera | P111: =IF(Base!Z98="","",Base!Z98) | Q111: =Base!S98 -> Difícil | R111: =Base!N98 -> 902544.19 | S111: =Base!T98 -> 1622387.9
A112: =SUBTOTAL(103,$B$6:B112) -> 95 | B112: 121 | C112: =Base!H99 -> 2602163: MEJORAMIENTO DEL SERVICIO DE TRANSITABILIDAD VIAL INTERURBANA EN LA CARRETERA PU 866 (EMP PE 34 I) - EMP PU 110 (SULLCA), PU 870 (DV TOTORANI: EMP PU 866) - EMP PU 872 (OCCOPAMPA) , PU 872: EMP. PU ¿ 866 (HUAYRAPATA) ¿ OCCOPAMPA ¿ EMP. PU ¿ 870 DISTRITOS DE MOHO, HUAYRAPATA DE LA PROVINCIA DE MOHO DEL DEPARTAMENTO DE PUNO | D112: =Base!I99 -> 2308286 | E112: =Base!J99 -> 0 | F112: =D112-E112 -> 2308286 | G112: =Base!L99 -> 0 | H112: =D112-G112 -> 2308286 | I112: =IF(D112=0,0,G112/D112) -> 0 | J112: =Base!U99 -> Administración directa / Contrata | K112: =Base!R99 -> Sin certificar | L112: =Base!V99 -> 800000 | M112: =Base!W99 -> 10345657 | N112: =Base!X99 -> 0 | O112: =Base!Y99 -> 10973904 | P112: =IF(Base!Z99="","",Base!Z99) | Q112: =Base!S99 -> Disponible | R112: =Base!N99 -> 0 | S112: =Base!T99 -> 2308286
A113: =SUBTOTAL(103,$B$6:B113) -> 96 | B113: 463 | C113: =Base!H100 -> 2511009: MEJORAMIENTO DEL SERVICIO VIAL URBANO DE LA AVENIDA INDUSTRIAL DEL CENTRO POBLADO DE SALCEDO, DISTRITO DE PUNO - PROVINCIA DE PUNO - DEPARTAMENTO DE PUNO | D113: =Base!I100 -> 1827737 | E113: =Base!J100 -> 1014426 | F113: =D113-E113 -> 813311.02 | G113: =Base!L100 -> 13810.34 | H113: =D113-G113 -> 1813926.7 | I113: =IF(D113=0,0,G113/D113) -> 0.0075559777 | J113: =Base!U100 -> Administración directa / Contrata | K113: =Base!R100 -> Parcialmente comprometido | L113: =Base!V100 -> No registrado en cartera | M113: =Base!W100 -> No registrado en cartera | N113: =Base!X100 -> No registrado en cartera | O113: =Base!Y100 -> No registrado en cartera | P113: =IF(Base!Z100="","",Base!Z100) | Q113: =Base!S100 -> Parcial | R113: =Base!N100 -> 615214.38 | S113: =Base!T100 -> 1428525.4
A114: =SUBTOTAL(103,$B$6:B114) -> 97 | B114: 128 | C114: =Base!H101 -> 2634040: MEJORAMIENTO DEL SERVICIO DE TRANSITABILIDAD VIAL INTERURBANA EN EL CAMINO VECINAL, TRAMO DESVIO PUCARA - POBLACION SALINAS - ASILLO SALINAS (KM 0+000 - 1+900) DEL DISTRITO DE SAN JUAN DE SALINAS DE LA PROVINCIA DE AZANGARO DEL DEPARTAMENTO DE PUNO | D114: =Base!I101 -> 4106961 | E114: =Base!J101 -> 3355560.2 | F114: =D114-E114 -> 751400.79 | G114: =Base!L101 -> 1831598.5 | H114: =D114-G114 -> 2275362.5 | I114: =IF(D114=0,0,G114/D114) -> 0.44597417 | J114: =Base!U101 -> Administración directa / Contrata / Personal/bienes/servicios | K114: =Base!R101 -> Mayormente comprometido | L114: =Base!V101 -> No registrado en cartera | M114: =Base!W101 -> No registrado en cartera | N114: =Base!X101 -> No registrado en cartera | O114: =Base!Y101 -> No registrado en cartera | P114: =IF(Base!Z101="","",Base!Z101) | Q114: =Base!S101 -> Difícil | R114: =Base!N101 -> 572769.27 | S114: =Base!T101 -> 1324170.1
A115: =SUBTOTAL(103,$B$6:B115) -> 98 | B115: 105 | C115: =Base!H102 -> 2387422: MEJORAMIENTO DE LA CARRETERA TRAMO II (PUENTE CULLCO) - PICHINCUTA - QUELCAHUECO - CORARACA DEL - DISTRITO DE ILAVE - PROVINCIA DE EL COLLAO - DEPARTAMENTO DE PUNO | D115: =Base!I102 -> 7751873 | E115: =Base!J102 -> 7482027.4 | F115: =D115-E115 -> 269845.63 | G115: =Base!L102 -> 5292812.8 | H115: =D115-G115 -> 2459060.2 | I115: =IF(D115=0,0,G115/D115) -> 0.68277857 | J115: =Base!U102 -> Administración directa / Contrata / Personal/bienes/servicios / Equipamiento | K115: =Base!R102 -> Mayormente comprometido | L115: =Base!V102 -> No registrado en cartera | M115: =Base!W102 -> No registrado en cartera | N115: =Base!X102 -> No registrado en cartera | O115: =Base!Y102 -> No registrado en cartera | P115: =IF(Base!Z102="","",Base!Z102) | Q115: =Base!S102 -> Difícil | R115: =Base!N102 -> 1013904.5 | S115: =Base!T102 -> 1283750.1
A116: =SUBTOTAL(103,$B$6:B116) -> 99 | B116: 114 | C116: =Base!H103 -> 2527184: MEJORAMIENTO DEL SERVICIO DE TRANSITABILIDAD VIAL DEL CAMINO VECINAL TRAMO VILLA PAXA A VENTILLA (PU- 1065) DEL DISTRITO DE PUNO - PROVINCIA DE PUNO - DEPARTAMENTO DE PUNO | D116: =Base!I103 -> 936343 | E116: =Base!J103 -> 868354.77 | F116: =D116-E116 -> 67988.23 | G116: =Base!L103 -> 868354.72 | H116: =D116-G116 -> 67988.28 | I116: =IF(D116=0,0,G116/D116) -> 0.92738956 | J116: =Base!U103 -> Administración directa / Contrata / Personal/bienes/servicios | K116: =Base!R103 -> Ejecutado | L116: =Base!V103 -> No registrado en cartera | M116: =Base!W103 -> No registrado en cartera | N116: =Base!X103 -> No registrado en cartera | O116: =Base!Y103 -> No registrado en cartera | P116: =IF(Base!Z103="","",Base!Z103) | Q116: =Base!S103 -> No usar | R116: =Base!N103 -> 0 | S116: =Base!T103 -> 0
A117: =SUBTOTAL(103,$B$6:B117) -> 100 | B117: 167 | C117: =Base!H104 -> 2519621: CREACION DEL SERVICIO DE TRANSITABILIDAD VEHICULAR Y PEATONAL EN EL JR. 7 DE JUNIO Y JR. BOLOGNESI CUADRA 10 DE LA LOCALIDAD DE YUNGUYO DEL DISTRITO DE YUNGUYO - PROVINCIA DE YUNGUYO - DEPARTAMENTO DE PUNO | D117: =Base!I104 -> 565870 | E117: =Base!J104 -> 502948.57 | F117: =D117-E117 -> 62921.43 | G117: =Base!L104 -> 446229.16 | H117: =D117-G117 -> 119640.84 | I117: =IF(D117=0,0,G117/D117) -> 0.78857186 | J117: =Base!U104 -> Administración directa / Contrata / Personal/bienes/servicios | K117: =Base!R104 -> Mayormente comprometido | L117: =Base!V104 -> No registrado en cartera | M117: =Base!W104 -> No registrado en cartera | N117: =Base!X104 -> No registrado en cartera | O117: =Base!Y104 -> No registrado en cartera | P117: =IF(Base!Z104="","",Base!Z104) | Q117: =Base!S104 -> Difícil | R117: =Base!N104 -> 2526 | S117: =Base!T104 -> 65447.43
A118: 21. CULTURA Y DEPORTE | D118: =SUM(D119:D121) -> 6449080 | E118: =SUM(E119:E121) -> 6391544.6 | F118: =D118-E118 -> 57535.36 | G118: =SUM(G119:G121) -> 208464.85 | H118: =D118-G118 -> 6240615.2 | I118: =IF(D118=0,0,G118/D118) -> 0.032324742 | R118: =SUM(R119:R121) -> 5829204.1 | S118: =SUM(S119:S121) -> 5886739.5
A119: =SUBTOTAL(103,$B$6:B119) -> 101 | B119: 69 | C119: =Base!H105 -> 2645446: REPARACION DE TRIBUNA Y/O PALCO Y PISTA DE ATLETISMO (DEPORTE RECREATIVO); CONSTRUCCION DE CAMPO DEPORTIVO; EN EL(LA) ESTADIO DE LA GRAN UNIDAD SAN CARLOS DISTRITO DE PUNO, PROVINCIA PUNO, DEPARTAMENTO PUNO | D119: =Base!I105 -> 1075076 | E119: =Base!J105 -> 1062250 | F119: =D119-E119 -> 12826 | G119: =Base!L105 -> 20822.47 | H119: =D119-G119 -> 1054253.5 | I119: =IF(D119=0,0,G119/D119) -> 0.01936837 | J119: =Base!U105 -> Contrata / Expediente técnico | K119: =Base!R105 -> Parcialmente comprometido | L119: =Base!V105 -> 1062638 | M119: =Base!W105 -> 245874 | N119: =Base!X105 -> 0 | O119: =Base!Y105 -> 0 | P119: =IF(Base!Z105="","",Base!Z105) | Q119: =Base!S105 -> Parcial | R119: =Base!N105 -> 1036832 | S119: =Base!T105 -> 1049658
A120: =SUBTOTAL(103,$B$6:B120) -> 102 | B120: 73 | C120: =Base!H106 -> 2646109: REPARACION DE TRIBUNA Y/O PALCO; CONSTRUCCION DE CAMPO DEPORTIVO Y TRIBUNA Y/O PALCO; EN EL(LA) ESTADIO MUNICIPAL DE JULI DISTRITO DE JULI, PROVINCIA CHUCUITO, DEPARTAMENTO PUNO | D120: =Base!I106 -> 4474004 | E120: =Base!J106 -> 4473905 | F120: =D120-E120 -> 99 | G120: =Base!L106 -> 0 | H120: =D120-G120 -> 4474004 | I120: =IF(D120=0,0,G120/D120) -> 0 | J120: =Base!U106 -> Contrata / Expediente técnico | K120: =Base!R106 -> Solo certificado | L120: =Base!V106 -> 1556258 | M120: =Base!W106 -> 2054256 | N120: =Base!X106 -> 0 | O120: =Base!Y106 -> 994904 | P120: =IF(Base!Z106="","",Base!Z106) | Q120: =Base!S106 -> Posible | R120: =Base!N106 -> 4473905 | S120: =Base!T106 -> 4474004
A121: =SUBTOTAL(103,$B$6:B121) -> 103 | B121: 504 | C121: =Base!H107 -> 2630072: CREACION DEL SERVICIO DE PRACTICA DEPORTIVA Y/O RECREATIVA EN COLISEO CERRADO DE AYAPATA DISTRITO DE AYAPATA DE LA PROVINCIA DE CARABAYA DEL DEPARTAMENTO DE PUNO | D121: =Base!I107 -> 900000 | E121: =Base!J107 -> 855389.64 | F121: =D121-E121 -> 44610.36 | G121: =Base!L107 -> 187642.38 | H121: =D121-G121 -> 712357.62 | I121: =IF(D121=0,0,G121/D121) -> 0.20849153 | J121: =Base!U107 -> Administración directa / Contrata / Personal/bienes/servicios / Equipamiento | K121: =Base!R107 -> Mayormente comprometido | L121: =Base!V107 -> No registrado en cartera | M121: =Base!W107 -> No registrado en cartera | N121: =Base!X107 -> No registrado en cartera | O121: =Base!Y107 -> No registrado en cartera | P121: =IF(Base!Z107="","",Base!Z107) | Q121: =Base!S107 -> Difícil | R121: =Base!N107 -> 318467.1 | S121: =Base!T107 -> 363077.46
A122: EJECUCIÓN POR ADMINISTRACIÓN INDIRECTA (CONTRATA) | D122: =D123+D133+D144+D146+D149 -> 209274718 | E122: =E123+E133+E144+E146+E149 -> 2.0185841e+08 | F122: =D122-E122 -> 7416312.5 | G122: =G123+G133+G144+G146+G149 -> 1.0445183e+08 | H122: =D122-G122 -> 1.0482289e+08 | I122: =IF(D122=0,0,G122/D122) -> 0.49911347 | R122: =R123+R133+R144+R146+R149 -> 45812634 | S122: =S123+S133+S144+S146+S149 -> 50438356
A123: 22. EDUCACION | D123: =SUM(D124:D132) -> 41210021 | E123: =SUM(E124:E132) -> 38883859 | F123: =D123-E123 -> 2326161.9 | G123: =SUM(G124:G132) -> 14467550 | H123: =D123-G123 -> 26742471 | I123: =IF(D123=0,0,G123/D123) -> 0.35106875 | R123: =SUM(R124:R132) -> 7350691.2 | S123: =SUM(S124:S132) -> 9676853.1
A124: =SUBTOTAL(103,$B$6:B124) -> 104 | B124: 34 | C124: =Base!H108 -> 2393398: MEJORAMIENTO DEL SERVICIO EDUCATIVO DE NIVEL SECUNDARIO EN LA I.E. A - 28 PERÚ BIRF CENTRO POBLADO DE AZANGARO - DISTRITO DE AZANGARO - PROVINCIA DE AZANGARO - REGIÓN PUNO | D124: =Base!I108 -> 18692228 | E124: =Base!J108 -> 18634477 | F124: =D124-E124 -> 57750.64 | G124: =Base!L108 -> 4987667.5 | H124: =D124-G124 -> 13704560 | I124: =IF(D124=0,0,G124/D124) -> 0.26683109 | J124: =Base!U108 -> Contrata / Personal/bienes/servicios / Equipamiento | K124: =Base!R108 -> Mayormente comprometido | L124: =Base!V108 -> 12431185 | M124: =Base!W108 -> 4843790 | N124: =Base!X108 -> 2910115 | O124: =Base!Y108 -> 0 | P124: =IF(Base!Z108="","",Base!Z108) | Q124: =Base!S108 -> Difícil | R124: =Base!N108 -> 458048.96 | S124: =Base!T108 -> 515799.6
A125: =SUBTOTAL(103,$B$6:B125) -> 105 | B125: 460 | C125: =Base!H109 -> 2500458: MEJORAMIENTO DEL SERVICIO EDUCATIVO EN LA IEP N° 70477 SAGRADO CORAZON DE JESUS DEL DISTRITO DE AYAVIRI - PROVINCIA DE MELGAR - DEPARTAMENTO DE PUNO | D125: =Base!I109 -> 4437995 | E125: =Base!J109 -> 3573868.9 | F125: =D125-E125 -> 864126.14 | G125: =Base!L109 -> 2493396.7 | H125: =D125-G125 -> 1944598.3 | I125: =IF(D125=0,0,G125/D125) -> 0.56182954 | J125: =Base!U109 -> Administración directa / Contrata / Equipamiento / Personal/bienes/servicios | K125: =Base!R109 -> Mayormente comprometido | L125: =Base!V109 -> No registrado en cartera | M125: =Base!W109 -> No registrado en cartera | N125: =Base!X109 -> No registrado en cartera | O125: =Base!Y109 -> No registrado en cartera | P125: =IF(Base!Z109="","",Base!Z109) | Q125: =Base!S109 -> Difícil | R125: =Base!N109 -> 382467.87 | S125: =Base!T109 -> 1246594
A126: =SUBTOTAL(103,$B$6:B126) -> 106 | B126: 455 | C126: =Base!H110 -> 2453224: MEJORAMIENTO DE LOS SERVICIOS DE EDUCACION SECUNDARIA DE LA INSTITUCION EDUCATIVA LIBERTADOR JOSE DE SAN MARTIN DE HUARISANI DEL DISTRITO DE HUANCANE - PROVINCIA DE HUANCANE - DEPARTAMENTO DE PUNO | D126: =Base!I110 -> 4265759 | E126: =Base!J110 -> 3847052.9 | F126: =D126-E126 -> 418706.06 | G126: =Base!L110 -> 2741829.6 | H126: =D126-G126 -> 1523929.4 | I126: =IF(D126=0,0,G126/D126) -> 0.64275305 | J126: =Base!U110 -> Administración directa / Contrata / Equipamiento / Personal/bienes/servicios | K126: =Base!R110 -> Mayormente comprometido | L126: =Base!V110 -> No registrado en cartera | M126: =Base!W110 -> No registrado en cartera | N126: =Base!X110 -> No registrado en cartera | O126: =Base!Y110 -> No registrado en cartera | P126: =IF(Base!Z110="","",Base!Z110) | Q126: =Base!S110 -> Difícil | R126: =Base!N110 -> 142724.81 | S126: =Base!T110 -> 561430.87
A127: =SUBTOTAL(103,$B$6:B127) -> 107 | B127: 172 | C127: =Base!H111 -> 2250382: INSTALACION DE LOS SERVICIOS DE EDUCACION INICIAL EN LA I.E.I. CHIA, DEL C.P. DE CHIA, DEL DISTRITO DE OLLACHEA - PROVINCIA CARABAYA - REGION PUNO | D127: =Base!I111 -> 2342684 | E127: =Base!J111 -> 2159343.3 | F127: =D127-E127 -> 183340.67 | G127: =Base!L111 -> 1123789.4 | H127: =D127-G127 -> 1218894.6 | I127: =IF(D127=0,0,G127/D127) -> 0.47970164 | J127: =Base!U111 -> Administración directa / Contrata / Personal/bienes/servicios | K127: =Base!R111 -> Mayormente comprometido | L127: =Base!V111 -> 800000 | M127: =Base!W111 -> 26969 | N127: =Base!X111 -> 0 | O127: =Base!Y111 -> 0 | P127: =IF(Base!Z111="","",Base!Z111) | Q127: =Base!S111 -> Difícil | R127: =Base!N111 -> 200755.67 | S127: =Base!T111 -> 384096.34
A128: =SUBTOTAL(103,$B$6:B128) -> 108 | B128: 28 | C128: =Base!H112 -> 2344253: MEJORAMIENTO DEL SERVICIO EDUCATIVO EN LA I.E.S. JOSÉ ANTONIO ENCINAS FRANCO, CENTRO POBLADO DE LECHEMAYO DEL DISTRITO DE SAN GABAN - PROVINCIA DE CARABAYA - DEPARTAMENTO DE PUNO | D128: =Base!I112 -> 4026127 | E128: =Base!J112 -> 3933834.9 | F128: =D128-E128 -> 92292.06 | G128: =Base!L112 -> 1387806.2 | H128: =D128-G128 -> 2638320.8 | I128: =IF(D128=0,0,G128/D128) -> 0.34470007 | J128: =Base!U112 -> Contrata / Personal/bienes/servicios | K128: =Base!R112 -> Mayormente comprometido | L128: =Base!V112 -> 2120577 | M128: =Base!W112 -> 5094106 | N128: =Base!X112 -> 4994536 | O128: =Base!Y112 -> 0 | P128: =IF(Base!Z112="","",Base!Z112) | Q128: =Base!S112 -> Difícil | R128: =Base!N112 -> 1705554.4 | S128: =Base!T112 -> 1797846.5
A129: =SUBTOTAL(103,$B$6:B129) -> 109 | B129: 32 | C129: =Base!H113 -> 2385051: MEJORAMIENTO DEL SERVICIO EDUCATIVO EN LA I.E.S. SAN JUAN BOSCO DE SALCEDO CON JORNADA ESCOLAR COMPLETA DISTRITO DE PUNO - PROVINCIA DE PUNO - REGIÓN PUNO | D129: =Base!I113 -> 4927527 | E129: =Base!J113 -> 4223260.7 | F129: =D129-E129 -> 704266.31 | G129: =Base!L113 -> 1725644.1 | H129: =D129-G129 -> 3201882.9 | I129: =IF(D129=0,0,G129/D129) -> 0.35020491 | J129: =Base!U113 -> Administración directa / Contrata / Equipamiento / Personal/bienes/servicios | K129: =Base!R113 -> Parcialmente comprometido | L129: =Base!V113 -> 2000000 | M129: =Base!W113 -> 8000000 | N129: =Base!X113 -> 9133500 | O129: =Base!Y113 -> 8629252 | P129: =IF(Base!Z113="","",Base!Z113) | Q129: =Base!S113 -> Parcial | R129: =Base!N113 -> 1958580.5 | S129: =Base!T113 -> 2662846.8
A130: =SUBTOTAL(103,$B$6:B130) -> 110 | B130: 156 | C130: =Base!H114 -> 2566572: MEJORAMIENTO Y AMPLIACION DE LOS SERVICIOS DE EDUCACIÓN SUPERIOR DEL INSTITUTO SUPERIOR TECNOLÓGICO PUBLICO DE NUÑOA DEL DISTRITO DE NUÑOA - PROVINCIA DE MELGAR - DEPARTAMENTO DE PUNO | D130: =Base!I114 -> 1479604 | E130: =Base!J114 -> 1473924 | F130: =D130-E130 -> 5679.97 | G130: =Base!L114 -> 7416.86 | H130: =D130-G130 -> 1472187.1 | I130: =IF(D130=0,0,G130/D130) -> 0.0050127331 | J130: =Base!U114 -> Contrata / Expediente técnico | K130: =Base!R114 -> Parcialmente comprometido | L130: =Base!V114 -> 3000000 | M130: =Base!W114 -> 6984785 | N130: =Base!X114 -> 0 | O130: =Base!Y114 -> 6681576 | P130: =IF(Base!Z114="","",Base!Z114) | Q130: =Base!S114 -> Parcial | R130: =Base!N114 -> 1464462 | S130: =Base!T114 -> 1470142
A131: =SUBTOTAL(103,$B$6:B131) -> 111 | B131: 506 | C131: =Base!H115 -> 2501244: MEJORAMIENTO DEL SERVICIO EDUCATIVO DEL NIVEL SECUNDARIA DE LA I.E. AGROPECUARIO PAMPA YANAMAYO DEL DISTRITO DE ALTO INAMBARI - PROVINCIA DE SANDIA - DEPARTAMENTO DE PUNO | D131: =Base!I115 -> 1038097 | E131: =Base!J115 -> 1038097 | F131: =D131-E131 -> 0 | G131: =Base!L115 -> 0 | H131: =D131-G131 -> 1038097 | I131: =IF(D131=0,0,G131/D131) -> 0 | J131: =Base!U115 -> Contrata | K131: =Base!R115 -> Solo certificado | L131: =Base!V115 -> No registrado en cartera | M131: =Base!W115 -> No registrado en cartera | N131: =Base!X115 -> No registrado en cartera | O131: =Base!Y115 -> No registrado en cartera | P131: =IF(Base!Z115="","",Base!Z115) | Q131: =Base!S115 -> Posible | R131: =Base!N115 -> 1038097 | S131: =Base!T115 -> 1038097
A132: =SUBTOTAL(103,$B$6:B132) -> 112 | B132: 23 | C132: =Base!H116 -> 2194501: INSTALACION DEL SERVICIO EDUCATIVO DE LA INSTITUCION EDUCATIVA SECUNDARIA SANTA MONICA EN EL DISTRITO DE JULIACA, PROVINCIA DE SAN ROMAN - PUNO. | D132: =Base!I116 -> 0 | E132: =Base!J116 -> 0 | F132: =D132-E132 -> 0 | G132: =Base!L116 -> 0 | H132: =D132-G132 -> 0 | I132: =IF(D132=0,0,G132/D132) -> 0 | J132: =Base!U116 -> Personal/bienes/servicios | K132: =Base!R116 -> Sin PIM | L132: =Base!V116 -> 144908 | M132: =Base!W116 -> 229001 | N132: =Base!X116 -> 0 | O132: =Base!Y116 -> 0 | P132: =IF(Base!Z116="","",Base!Z116) | Q132: =Base!S116 -> Sin PIM | R132: =Base!N116 -> 0 | S132: =Base!T116 -> 0
...

Sheet Gerencias y Oficinas
C1: ANEXO N° 02
B2: COMPORTAMIENTO DE EJECUCIÓN DE PROYECTOS DE INVERSION PUBLICA DEL AÑO FISCAL 2026 · Gerencias y Oficinas · AL 07/10/2026
A4: N° | B4: META | C4: PROYECTO | D4: PIM 2026 (A) | E4: CERTIFICACIÓN (B) | F4: SALDO (A-B) | G4: DEVENGADO ( C ) | H4: SALDO (A-C) | I4: DEVEN % | J4: MODALIDAD DE EJECUCIÓN | K4: ESTADO SITUACIONAL PROYECTO | L4: Monto Año 2026 (S/) | M4: Monto Año 2027 (S/) | N4: Monto Año 2028 (S/) | O4: Monto Año 2029 (S/) | P4: BASE LEGAL | Q4: DISPONIBILIDAD | R4: CERTIFICADO NO COMPROMETIDO | S4: DISPONIBLE (PIM − COMPROM.)
A5: GERENCIA REGIONAL DE DESARROLLO ECONOMICO | D5: =D6+D11+D14+D17+D82+D87 -> 15438088 | E5: =E6+E11+E14+E17+E82+E87 -> 13246424 | F5: =D5-E5 -> 2191664.1 | G5: =G6+G11+G14+G17+G82+G87 -> 6937956.8 | H5: =D5-G5 -> 8500131.2 | I5: =IF(D5=0,0,G5/D5) -> 0.44940518 | R5: =R6+R11+R14+R17+R82+R87 -> 4178010.5 | S5: =S6+S11+S14+S17+S82+S87 -> 6297331.5
A6: 09. TURISMO | D6: =SUM(D7:D10) -> 3137774 | E6: =SUM(E7:E10) -> 2421934 | F6: =D6-E6 -> 715839.98 | G6: =SUM(G7:G10) -> 1602346.4 | H6: =D6-G6 -> 1535427.6 | I6: =IF(D6=0,0,G6/D6) -> 0.51066342 | R6: =SUM(R7:R10) -> 320662.23 | S6: =SUM(S7:S10) -> 1036502.2
A7: =SUBTOTAL(103,$B$6:B7) -> 1 | B7: 20 | C7: =Base!H292 -> 2526527: MEJORAMIENTO DE LAS CAPACIDADES PARA LA PRODUCTIVIDAD Y LA COMPETITIVIDAD DE ARTESANÍAS EN 13 PROVINCIAS DEL DEPARTAMENTO DE PUNO | D7: =Base!I292 -> 2659376 | E7: =Base!J292 -> 1980094.5 | F7: =D7-E7 -> 679281.48 | G7: =Base!L292 -> 1386716.9 | H7: =D7-G7 -> 1272659.1 | I7: =IF(D7=0,0,G7/D7) -> 0.52144446 | J7: =Base!U292 -> Contrata / Personal/bienes/servicios / Equipamiento | K7: =Base!R292 -> Mayormente comprometido | L7: =Base!V292 -> 3659376 | M7: =Base!W292 -> 55933 | N7: =Base!X292 -> 0 | O7: =Base!Y292 -> 1953448 | P7: =IF(Base!Z292="","",Base!Z292) | Q7: =Base!S292 -> Difícil | R7: =Base!N292 -> 125022.23 | S7: =Base!T292 -> 804303.71
A8: =SUBTOTAL(103,$B$6:B8) -> 2 | B8: 383 | C8: =Base!H293 -> 2717147: MEJORAMIENTO DE LOS SERVICIOS TURISTICOS DE AVENTURA Y ALOJAMIENTO RURAL EN LA ASOCIACION DE TURISMO VIVENCIAL COMUNITARIO LUQUINA CHICO, DISTRITO CHUCUITO, PROVINCIA PUNO, REGION PUNO. | D8: =Base!I293 -> 159946 | E8: =Base!J293 -> 154011 | F8: =D8-E8 -> 5935 | G8: =Base!L293 -> 60441 | H8: =D8-G8 -> 99505 | I8: =IF(D8=0,0,G8/D8) -> 0.37788379 | J8: =Base!U293 -> Equipamiento / Contrata | K8: =Base!R293 -> Mayormente comprometido | L8: =Base!V293 -> No registrado en cartera | M8: =Base!W293 -> No registrado en cartera | N8: =Base!X293 -> No registrado en cartera | O8: =Base!Y293 -> No registrado en cartera | P8: =IF(Base!Z293="","",Base!Z293) | Q8: =Base!S293 -> Difícil | R8: =Base!N293 -> 63000 | S8: =Base!T293 -> 68935
A9: =SUBTOTAL(103,$B$6:B9) -> 3 | B9: 475 | C9: =Base!H294 -> 2723296: MEJORAMIENTO DE LA PRODUCCION Y COMERCIALIZACION DE ARTESANIA DE FIBRA DE ALPACA Y LANA DE OVINO EN LA ASOCIACION DE ARTESANOS EMPRENDEDORES EN TEXTILERIA SAN JUAN BAUTISTA DE NAPA ROSASPATA, DISTRITO DE ROSASPATA, PROVINCIA DE HUANCANE, REGION PU | D9: =Base!I294 -> 159560 | E9: =Base!J294 -> 141270 | F9: =D9-E9 -> 18290 | G9: =Base!L294 -> 57830 | H9: =D9-G9 -> 101730 | I9: =IF(D9=0,0,G9/D9) -> 0.36243419 | J9: =Base!U294 -> Equipamiento / Contrata | K9: =Base!R294 -> Parcialmente comprometido | L9: =Base!V294 -> No registrado en cartera | M9: =Base!W294 -> No registrado en cartera | N9: =Base!X294 -> No registrado en cartera | O9: =Base!Y294 -> No registrado en cartera | P9: =IF(Base!Z294="","",Base!Z294) | Q9: =Base!S294 -> Parcial | R9: =Base!N294 -> 83440 | S9: =Base!T294 -> 101730
A10: =SUBTOTAL(103,$B$6:B10) -> 4 | B10: 410 | C10: =Base!H295 -> 2717175: MEJORAMIENTO DE LOS SERVICIOS DE ALOJAMIENTO TURISTICO Y DEL TURISMO VIVENCIAL DE OBSERVACION ASTRONOMICA EN LA ASOCIACION DE TURISMO COMUNITARIO TIKA WASI LLACHON, DISTRITO DE CAPACHICA, PROVINCIA DE PUNO Y DEPARTAMENTO DE PUNO. | D10: =Base!I295 -> 158892 | E10: =Base!J295 -> 146558.5 | F10: =D10-E10 -> 12333.5 | G10: =Base!L295 -> 97358.5 | H10: =D10-G10 -> 61533.5 | I10: =IF(D10=0,0,G10/D10) -> 0.61273381 | J10: =Base!U295 -> Equipamiento / Contrata | K10: =Base!R295 -> Mayormente comprometido | L10: =Base!V295 -> No registrado en cartera | M10: =Base!W295 -> No registrado en cartera | N10: =Base!X295 -> No registrado en cartera | O10: =Base!Y295 -> No registrado en cartera | P10: =IF(Base!Z295="","",Base!Z295) | Q10: =Base!S295 -> Difícil | R10: =Base!N295 -> 49200 | S10: =Base!T295 -> 61533.5
A11: 03. PLANEAMIENTO, GESTION Y RESERVA DE CONTINGENCIA | D11: =SUM(D12:D13) -> 243160 | E11: =SUM(E12:E13) -> 83160 | F11: =D11-E11 -> 160000 | G11: =SUM(G12:G13) -> 83100.4 | H11: =D11-G11 -> 160059.6 | I11: =IF(D11=0,0,G11/D11) -> 0.34175193 | R11: =SUM(R12:R13) -> 59.6 | S11: =SUM(S12:S13) -> 160000
A12: =SUBTOTAL(103,$B$6:B12) -> 5 | B12: 399 | C12: =Base!H296 -> 2717164: MEJORAMIENTO DE LA CAPACIDAD PRODUCTIVA Y DE COMERCIALIZACION DE MIEL MEDIANTE EL FORTALECIMIENTO DE PROCESOS PRODUCTIVOS APICOLAS EN LA ASOCIACION DE PRODUCTORES AGROPECUARIOS MONTE SILOE KOLLA MISKI DISTRITO PLATERIA, PROVINCIA DE PUNO, REGION P | D12: =Base!I296 -> 160000 | E12: =Base!J296 -> 0 | F12: =D12-E12 -> 160000 | G12: =Base!L296 -> 0 | H12: =D12-G12 -> 160000 | I12: =IF(D12=0,0,G12/D12) -> 0 | J12: =Base!U296 -> Equipamiento / Contrata | K12: =Base!R296 -> Sin certificar | L12: =Base!V296 -> No registrado en cartera | M12: =Base!W296 -> No registrado en cartera | N12: =Base!X296 -> No registrado en cartera | O12: =Base!Y296 -> No registrado en cartera | P12: =IF(Base!Z296="","",Base!Z296) | Q12: =Base!S296 -> Disponible | R12: =Base!N296 -> 0 | S12: =Base!T296 -> 160000
A13: =SUBTOTAL(103,$B$6:B13) -> 6 | B13: 373 | C13: =Base!H297 -> 2676438: MEJORAMIENTO DE LA PRODUCCION DE MIEL DE ABEJA DE LA ASOCIACION DE APICULTORES Y PRODUCTORES AGROPECUARIOS DEL VALLE YANAHUAYA, DEL DISTRITO DE YANAHUARA PROVINCIA DE SANDIA DEPARTAMENTO DE PUNO | D13: =Base!I297 -> 83160 | E13: =Base!J297 -> 83160 | F13: =D13-E13 -> 0 | G13: =Base!L297 -> 83100.4 | H13: =D13-G13 -> 59.6 | I13: =IF(D13=0,0,G13/D13) -> 0.99928331 | J13: =Base!U297 -> Equipamiento | K13: =Base!R297 -> Ejecutado | L13: =Base!V297 -> No registrado en cartera | M13: =Base!W297 -> No registrado en cartera | N13: =Base!X297 -> No registrado en cartera | O13: =Base!Y297 -> No registrado en cartera | P13: =IF(Base!Z297="","",Base!Z297) | Q13: =Base!S297 -> No usar | R13: =Base!N297 -> 59.6 | S13: =Base!T297 -> 0
A14: 08. COMERCIO | D14: =SUM(D15:D16) -> 1098209 | E14: =SUM(E15:E16) -> 995606.03 | F14: =D14-E14 -> 102602.97 | G14: =SUM(G15:G16) -> 677101.76 | H14: =D14-G14 -> 421107.24 | I14: =IF(D14=0,0,G14/D14) -> 0.61655091 | R14: =SUM(R15:R16) -> 2578.68 | S14: =SUM(S15:S16) -> 105181.65
A15: =SUBTOTAL(103,$B$6:B15) -> 7 | B15: 216 | C15: =Base!H298 -> 2016766: INICIATIVA A LA COMPETITIVIDAD | D15: =Base!I298 -> 928209 | E15: =Base!J298 -> 900951.03 | F15: =D15-E15 -> 27257.97 | G15: =Base!L298 -> 633092.52 | H15: =D15-G15 -> 295116.48 | I15: =IF(D15=0,0,G15/D15) -> 0.68205816 | J15: =Base!U298 -> Estudio de preinversión | K15: =Base!R298 -> Mayormente comprometido | L15: =Base!V298 -> No registrado en cartera | M15: =Base!W298 -> No registrado en cartera | N15: =Base!X298 -> No registrado en cartera | O15: =Base!Y298 -> No registrado en cartera | P15: =IF(Base!Z298="","",Base!Z298) | Q15: =Base!S298 -> Difícil | R15: =Base!N298 -> 1277.92 | S15: =Base!T298 -> 28535.89
A16: =SUBTOTAL(103,$B$6:B16) -> 8 | B16: 493 | C16: =Base!H299 -> 2016766: INICIATIVA A LA COMPETITIVIDAD | D16: =Base!I299 -> 170000 | E16: =Base!J299 -> 94655 | F16: =D16-E16 -> 75345 | G16: =Base!L299 -> 44009.24 | H16: =D16-G16 -> 125990.76 | I16: =IF(D16=0,0,G16/D16) -> 0.25887788 | J16: =Base!U299 -> Estudio de preinversión | K16: =Base!R299 -> Mayormente comprometido | L16: =Base!V299 -> No registrado en cartera | M16: =Base!W299 -> No registrado en cartera | N16: =Base!X299 -> No registrado en cartera | O16: =Base!Y299 -> No registrado en cartera | P16: =IF(Base!Z299="","",Base!Z299) | Q16: =Base!S299 -> Difícil | R16: =Base!N299 -> 1300.76 | S16: =Base!T299 -> 76645.76
A17: 10. AGROPECUARIA | D17: =SUM(D18:D81) -> 8596003 | E17: =SUM(E18:E81) -> 7643005.1 | F17: =D17-E17 -> 952997.85 | G17: =SUM(G18:G81) -> 4006476.2 | H17: =D17-G17 -> 4589526.8 | I17: =IF(D17=0,0,G17/D17) -> 0.46608595 | R17: =SUM(R18:R81) -> 2852543.3 | S17: =SUM(S18:S81) -> 3742340.6
A18: =SUBTOTAL(103,$B$6:B18) -> 9 | B18: 418 | C18: =Base!H300 -> 2717186: MEJORAMIENTO DE LA PLANTA DE TRANSFORMACION DE GRANOS ANDINOS DEL GRUPO TURISTICO GASTRONOMICO SAMKA S.A.C., DISTRITO PUNO, PROVINCIA PUNO, REGION PUNO. | D18: =Base!I300 -> 350000 | E18: =Base!J300 -> 334060 | F18: =D18-E18 -> 15940 | G18: =Base!L300 -> 65360 | H18: =D18-G18 -> 284640 | I18: =IF(D18=0,0,G18/D18) -> 0.18674286 | J18: =Base!U300 -> Equipamiento / Contrata | K18: =Base!R300 -> Mayormente comprometido | L18: =Base!V300 -> No registrado en cartera | M18: =Base!W300 -> No registrado en cartera | N18: =Base!X300 -> No registrado en cartera | O18: =Base!Y300 -> No registrado en cartera | P18: =IF(Base!Z300="","",Base!Z300) | Q18: =Base!S300 -> Difícil | R18: =Base!N300 -> 126700 | S18: =Base!T300 -> 142640
A19: =SUBTOTAL(103,$B$6:B19) -> 10 | B19: 424 | C19: =Base!H301 -> 2717193: AMPLIACION DE LA CAPACIDAD PRODUCCION DE QUESO PARIA EN GRUPO NEBRASKA S.A.C. EN DISTRITO DE JULIACA PROVINCIA DE SAN ROMAN REGION PUNO | D19: =Base!I301 -> 349950 | E19: =Base!J301 -> 287705 | F19: =D19-E19 -> 62245 | G19: =Base!L301 -> 136062 | H19: =D19-G19 -> 213888 | I19: =IF(D19=0,0,G19/D19) -> 0.38880411 | J19: =Base!U301 -> Equipamiento / Contrata | K19: =Base!R301 -> Parcialmente comprometido | L19: =Base!V301 -> No registrado en cartera | M19: =Base!W301 -> No registrado en cartera | N19: =Base!X301 -> No registrado en cartera | O19: =Base!Y301 -> No registrado en cartera | P19: =IF(Base!Z301="","",Base!Z301) | Q19: =Base!S301 -> Parcial | R19: =Base!N301 -> 142043 | S19: =Base!T301 -> 204288
A20: =SUBTOTAL(103,$B$6:B20) -> 11 | B20: 413 | C20: =Base!H302 -> 2717178: MEJORAMIENTO DEL CULTIVO DE HABAS EN CORPORACION PECUARIO AGRICOLA EMMANUEL S.A.C., DISTRITO DE ZEPITA, PROVINCIA DE CHUCUITO Y DEPARTAMENTO DE PUNO | D20: =Base!I302 -> 349899 | E20: =Base!J302 -> 307070 | F20: =D20-E20 -> 42829 | G20: =Base!L302 -> 10500 | H20: =D20-G20 -> 339399 | I20: =IF(D20=0,0,G20/D20) -> 0.03000866 | J20: =Base!U302 -> Equipamiento / Contrata | K20: =Base!R302 -> Parcialmente comprometido | L20: =Base!V302 -> No registrado en cartera | M20: =Base!W302 -> No registrado en cartera | N20: =Base!X302 -> No registrado en cartera | O20: =Base!Y302 -> No registrado en cartera | P20: =IF(Base!Z302="","",Base!Z302) | Q20: =Base!S302 -> Parcial | R20: =Base!N302 -> 255000 | S20: =Base!T302 -> 297829
A21: =SUBTOTAL(103,$B$6:B21) -> 12 | B21: 394 | C21: =Base!H303 -> 2717158: MEJORAMIENTO DE LA PRODUCCION DE PACAS EN LA ASOCIACION DE PRODUCTORES AGROPECUARIOS Y FORESTALES SAN PEDRO DE FRAYLIMA, DISTRITO DE AZANGARO, PROVINCIA AZANGARO Y DEPARTAMENTO DE PUNO | D21: =Base!I303 -> 349792 | E21: =Base!J303 -> 321500 | F21: =D21-E21 -> 28292 | G21: =Base!L303 -> 0 | H21: =D21-G21 -> 349792 | I21: =IF(D21=0,0,G21/D21) -> 0 | J21: =Base!U303 -> Equipamiento / Contrata | K21: =Base!R303 -> Solo certificado | L21: =Base!V303 -> No registrado en cartera | M21: =Base!W303 -> No registrado en cartera | N21: =Base!X303 -> No registrado en cartera | O21: =Base!Y303 -> No registrado en cartera | P21: =IF(Base!Z303="","",Base!Z303) | Q21: =Base!S303 -> Posible | R21: =Base!N303 -> 321500 | S21: =Base!T303 -> 349792
A22: =SUBTOTAL(103,$B$6:B22) -> 13 | B22: 408 | C22: =Base!H304 -> 2717173: MEJORAMIENTO DE LA PRODUCCION DE DERIVADOS DE QUINUA EN HARINA EXTRUIDA Y POP EXTRUIDO DE LA EMPRESA CORPORACION DALSAR SOCIEDAD ANONIMA CERRADA DEL DISTRITO DE PUNO, PROVINCIA PUNO, DEPARTAMENTO PUNO. | D22: =Base!I304 -> 349792 | E22: =Base!J304 -> 329100 | F22: =D22-E22 -> 20692 | G22: =Base!L304 -> 0 | H22: =D22-G22 -> 349792 | I22: =IF(D22=0,0,G22/D22) -> 0 | J22: =Base!U304 -> Equipamiento / Contrata | K22: =Base!R304 -> Solo certificado | L22: =Base!V304 -> No registrado en cartera | M22: =Base!W304 -> No registrado en cartera | N22: =Base!X304 -> No registrado en cartera | O22: =Base!Y304 -> No registrado en cartera | P22: =IF(Base!Z304="","",Base!Z304) | Q22: =Base!S304 -> Posible | R22: =Base!N304 -> 329100 | S22: =Base!T304 -> 349792
A23: =SUBTOTAL(103,$B$6:B23) -> 14 | B23: 421 | C23: =Base!H305 -> 2717189: MEJORAMIENTO DE LA PRODUCCION DE YOGURT EN EL AEO AGROINDUSTRIA YOGULE S.A.C., DISTRITO DE CABANA, PROVINCIA SAN ROMAN, REGION PUNO | D23: =Base!I305 -> 346711 | E23: =Base!J305 -> 318955 | F23: =D23-E23 -> 27756 | G23: =Base!L305 -> 112190 | H23: =D23-G23 -> 234521 | I23: =IF(D23=0,0,G23/D23) -> 0.32358362 | J23: =Base!U305 -> Equipamiento / Contrata | K23: =Base!R305 -> Parcialmente comprometido | L23: =Base!V305 -> No registrado en cartera | M23: =Base!W305 -> No registrado en cartera | N23: =Base!X305 -> No registrado en cartera | O23: =Base!Y305 -> No registrado en cartera | P23: =IF(Base!Z305="","",Base!Z305) | Q23: =Base!S305 -> Parcial | R23: =Base!N305 -> 200010 | S23: =Base!T305 -> 227766
A24: =SUBTOTAL(103,$B$6:B24) -> 15 | B24: 387 | C24: =Base!H306 -> 2717151: MEJORAMIENTO DE LA PRODUCCION DE LECHE FRESCA EN LA ASOCIACION DE PRODUCTORES AGROPECUARIOS SUMAC KANCHAY DE LA LIBERTAD NUNOA MELGAR PUNO, DISTRITO DE NUNOA, PROVINCIA DE MELGAR Y REGION PUNO | D24: =Base!I306 -> 269980 | E24: =Base!J306 -> 259749 | F24: =D24-E24 -> 10231 | G24: =Base!L306 -> 255066 | H24: =D24-G24 -> 14914 | I24: =IF(D24=0,0,G24/D24) -> 0.94475887 | J24: =Base!U306 -> Equipamiento / Contrata | K24: =Base!R306 -> Ejecutado | L24: =Base!V306 -> No registrado en cartera | M24: =Base!W306 -> No registrado en cartera | N24: =Base!X306 -> No registrado en cartera | O24: =Base!Y306 -> No registrado en cartera | P24: =IF(Base!Z306="","",Base!Z306) | Q24: =Base!S306 -> No usar | R24: =Base!N306 -> 1500 | S24: =Base!T306 -> 0
A25: =SUBTOTAL(103,$B$6:B25) -> 16 | B25: 378 | C25: =Base!H307 -> 2676440: MEJORAMIENTO DE LA PRODUCCION Y LA PRODUCTIVIDAD DE QUESO TIPO PARIA PASTEURIZADO DE LA EMPRESA DE PRODUCCION AGROPECUARIA MICA ASUNCION SAC DEL, DISTRITO DE AZANGARO, PROVINCIA AZANGARO, DEPARTAMENTO PUNO. | D25: =Base!I307 -> 209400 | E25: =Base!J307 -> 176550 | F25: =D25-E25 -> 32850 | G25: =Base!L307 -> 136550 | H25: =D25-G25 -> 72850 | I25: =IF(D25=0,0,G25/D25) -> 0.65210124 | J25: =Base!U307 -> Equipamiento / Contrata | K25: =Base!R307 -> Mayormente comprometido | L25: =Base!V307 -> No registrado en cartera | M25: =Base!W307 -> No registrado en cartera | N25: =Base!X307 -> No registrado en cartera | O25: =Base!Y307 -> No registrado en cartera | P25: =IF(Base!Z307="","",Base!Z307) | Q25: =Base!S307 -> Difícil | R25: =Base!N307 -> 0 | S25: =Base!T307 -> 32850
A26: =SUBTOTAL(103,$B$6:B26) -> 17 | B26: 392 | C26: =Base!H308 -> 2717156: MEJORAMIENTO DE LA PRODUCCION Y LA COMERCIALIZACION DE LECHE FRESCA EN LA ORGANIZACION DE PRODUCTORES SAN JUAN DE FAON DEL DISTRITO DE HUATA, PROVINCIA DE PUNO, DEPARTAMENTO DE PUNO. | D26: =Base!I308 -> 160000 | E26: =Base!J308 -> 143401 | F26: =D26-E26 -> 16599 | G26: =Base!L308 -> 143401 | H26: =D26-G26 -> 16599 | I26: =IF(D26=0,0,G26/D26) -> 0.89625625 | J26: =Base!U308 -> Equipamiento / Contrata | K26: =Base!R308 -> Mayormente comprometido | L26: =Base!V308 -> No registrado en cartera | M26: =Base!W308 -> No registrado en cartera | N26: =Base!X308 -> No registrado en cartera | O26: =Base!Y308 -> No registrado en cartera | P26: =IF(Base!Z308="","",Base!Z308) | Q26: =Base!S308 -> Difícil | R26: =Base!N308 -> 0 | S26: =Base!T308 -> 16599
A27: =SUBTOTAL(103,$B$6:B27) -> 18 | B27: 393 | C27: =Base!H309 -> 2717157: MEJORAMIENTO DE LA PRODUCCION Y ENGORDE DE GANADO VACUNO A TRAVES DE LA OPTIMIZACION DE LA ALIMENTACION EN LA ASOCIACION DE PRODUCTORES AGROPECUARIOS EL TORITO BRAVO DEL DISTRITO DE QUILCAPUNCO, PROVINCIA DE SAN ANTONIO DE PUTINA, REGION PUNO. | D27: =Base!I309 -> 160000 | E27: =Base!J309 -> 149840 | F27: =D27-E27 -> 10160 | G27: =Base!L309 -> 18740 | H27: =D27-G27 -> 141260 | I27: =IF(D27=0,0,G27/D27) -> 0.117125 | J27: =Base!U309 -> Equipamiento / Contrata | K27: =Base!R309 -> Parcialmente comprometido | L27: =Base!V309 -> No registrado en cartera | M27: =Base!W309 -> No registrado en cartera | N27: =Base!X309 -> No registrado en cartera | O27: =Base!Y309 -> No registrado en cartera | P27: =IF(Base!Z309="","",Base!Z309) | Q27: =Base!S309 -> Parcial | R27: =Base!N309 -> 115800 | S27: =Base!T309 -> 125960
A28: =SUBTOTAL(103,$B$6:B28) -> 19 | B28: 397 | C28: =Base!H310 -> 2717161: MEJORAMIENTO DE LA CAPACIDAD DE TRANSFORMACION DE CHIPS DE PAPA NATIVA, EN LA AEO ASOCIACION DE PRODUCTORES MULTIPLES SAN ISIDRO DE TANTAMACO DEL DISTRITO DE MACUSANI, PROVINCIA DE CARABAYA, REGION DE PUNO | D28: =Base!I310 -> 160000 | E28: =Base!J310 -> 148990 | F28: =D28-E28 -> 11010 | G28: =Base!L310 -> 26000 | H28: =D28-G28 -> 134000 | I28: =IF(D28=0,0,G28/D28) -> 0.1625 | J28: =Base!U310 -> Equipamiento / Contrata | K28: =Base!R310 -> Mayormente comprometido | L28: =Base!V310 -> No registrado en cartera | M28: =Base!W310 -> No registrado en cartera | N28: =Base!X310 -> No registrado en cartera | O28: =Base!Y310 -> No registrado en cartera | P28: =IF(Base!Z310="","",Base!Z310) | Q28: =Base!S310 -> Difícil | R28: =Base!N310 -> 1000 | S28: =Base!T310 -> 12010
A29: =SUBTOTAL(103,$B$6:B29) -> 20 | B29: 404 | C29: =Base!H311 -> 2717169: CREACION DE UNA PLANTA PROCESADORA DE QUINUA EN LA AEO ASOCIACION DE PRODUCTORES AGROPECUARIOS ROQUE APAZA PAMPA DEL DISTRITO DE PAUCARCOLLA, PROVINCIA DE PUNO, DEPARTAMENTO DE PUNO | D29: =Base!I311 -> 160000 | E29: =Base!J311 -> 150870 | F29: =D29-E29 -> 9130 | G29: =Base!L311 -> 45270 | H29: =D29-G29 -> 114730 | I29: =IF(D29=0,0,G29/D29) -> 0.2829375 | J29: =Base!U311 -> Equipamiento / Contrata | K29: =Base!R311 -> Parcialmente comprometido | L29: =Base!V311 -> No registrado en cartera | M29: =Base!W311 -> No registrado en cartera | N29: =Base!X311 -> No registrado en cartera | O29: =Base!Y311 -> No registrado en cartera | P29: =IF(Base!Z311="","",Base!Z311) | Q29: =Base!S311 -> Parcial | R29: =Base!N311 -> 99600 | S29: =Base!T311 -> 108730
... A81: =SUBTOTAL(103,$B$6:B81) -> 72 | B81: 526 | C81: =Base!H363 -> 2681133: MEJORAMIENTO DE LA PRODUCCION DE QUESOS TIPO PARIA PASTEURIZADO DE LA CENTRAL DE ASOCIACIONES GANADEROS LECHEROS Y AGRARIOS DEL DISTRITO DE VILQUE, DISTRITO DE VILQUE, PROVINCIA DE PUNO, REGION PUNO | D81: =Base!I363 -> 2795 | E81: =Base!J363 -> 2795 | F81: =D81-E81 -> 0 | G81: =Base!L363 -> 0 | H81: =D81-G81 -> 2795 | I81: =IF(D81=0,0,G81/D81) -> 0 | J81: =Base!U363 -> Contrata | K81: =Base!R363 -> Solo certificado | L81: =Base!V363 -> No registrado en cartera | M81: =Base!W363 -> No registrado en cartera | N81: =Base!X363 -> No registrado en cartera | O81: =Base!Y363 -> No registrado en cartera | P81: =IF(Base!Z363="","",Base!Z363) | Q81: =Base!S363 -> Posible | R81: =Base!N363 -> 2795 | S81: =Base!T363 -> 2795
A82: 11. PESCA | D82: =SUM(D83:D86) -> 1054126 | E82: =SUM(E83:E86) -> 893638.67 | F82: =D82-E82 -> 160487.33 | G82: =SUM(G83:G86) -> 30322 | H82: =D82-G82 -> 1023804 | I82: =IF(D82=0,0,G82/D82) -> 0.028765062 | R82: =SUM(R83:R86) -> 680966.67 | S82: =SUM(S83:S86) -> 841454
A83: =SUBTOTAL(103,$B$6:B83) -> 73 | B83: 368 | C83: =Base!H364 -> 2681278: MEJORAMIENTO DEL PROCESO DE PRODUCCION DE SELECCIONADOR DE TRUCHAS EN MAQUINARIAS ACUITROUT SOCIEDAD COMERCIAL DE RESPONSABILIDAD DE LA COMUNIDAD DE KOLLPAJAHUIRA, DISTRITO DE JULI, PROVINCIA DE CHUCUITO, DEPARTAMENTO DE PUNO | D83: =Base!I364 -> 179500 | E83: =Base!J364 -> 163750 | F83: =D83-E83 -> 15750 | G83: =Base!L364 -> 3750 | H83: =D83-G83 -> 175750 | I83: =IF(D83=0,0,G83/D83) -> 0.020891365 | J83: =Base!U364 -> Equipamiento / Contrata | K83: =Base!R364 -> Parcialmente comprometido | L83: =Base!V364 -> No registrado en cartera | M83: =Base!W364 -> No registrado en cartera | N83: =Base!X364 -> No registrado en cartera | O83: =Base!Y364 -> No registrado en cartera | P83: =IF(Base!Z364="","",Base!Z364) | Q83: =Base!S364 -> Parcial | R83: =Base!N364 -> 160000 | S83: =Base!T364 -> 175750
A84: =SUBTOTAL(103,$B$6:B84) -> 74 | B84: 375 | C84: =Base!H365 -> 2681123: MEJORAMIENTO EN EL PROCESO DE VALOR AGREGADO DE TRUCHAS EN LA EMPRESA AMERICAN TROUT FARO S.R.L. EN EL DISTRITO DE POMATA, PROVINCIA DE CHUCUITO Y DEPARTAMENTO DE PUNO. | D84: =Base!I365 -> 175166 | E84: =Base!J365 -> 166872 | F84: =D84-E84 -> 8294 | G84: =Base!L365 -> 5872 | H84: =D84-G84 -> 169294 | I84: =IF(D84=0,0,G84/D84) -> 0.033522487 | J84: =Base!U365 -> Equipamiento / Contrata | K84: =Base!R365 -> Mayormente comprometido | L84: =Base!V365 -> No registrado en cartera | M84: =Base!W365 -> No registrado en cartera | N84: =Base!X365 -> No registrado en cartera | O84: =Base!Y365 -> No registrado en cartera | P84: =IF(Base!Z365="","",Base!Z365) | Q84: =Base!S365 -> Difícil | R84: =Base!N365 -> 6300 | S84: =Base!T365 -> 14594
A85: =SUBTOTAL(103,$B$6:B85) -> 75 | B85: 417 | C85: =Base!H366 -> 2717185: MEJORAMIENTO DE VALOR AGREGADO DE LA TRUCHA EN AQUA INDUSTRIAS EL FARO SOCIEDAD COMERCIAL DE RESPONSABILIDAD LIMITADA, DISTRITO DE POMATA, PROVINCIA DE CHUCUITO Y DEPARTAMENTO DE PUNO | D85: =Base!I366 -> 349792 | E85: =Base!J366 -> 325833.33 | F85: =D85-E85 -> 23958.67 | G85: =Base!L366 -> 0 | H85: =D85-G85 -> 349792 | I85: =IF(D85=0,0,G85/D85) -> 0 | J85: =Base!U366 -> Equipamiento / Contrata | K85: =Base!R366 -> Parcialmente comprometido | L85: =Base!V366 -> No registrado en cartera | M85: =Base!W366 -> No registrado en cartera | N85: =Base!X366 -> No registrado en cartera | O85: =Base!Y366 -> No registrado en cartera | P85: =IF(Base!Z366="","",Base!Z366) | Q85: =Base!S366 -> Parcial | R85: =Base!N366 -> 308833.33 | S85: =Base!T366 -> 332792
A86: =SUBTOTAL(103,$B$6:B86) -> 76 | B86: 474 | C86: =Base!H367 -> 2723300: MEJORAMIENTO DE LA PRODUCCION Y TRANSFORMACION DE FILETE DE TRUCHA DE LA EMPRESA TITIKAKA TROUT PERU SOCIEDAD COMERCIAL DE RESPONSABILIDAD LIMITADA DEL DISTRITO DE POMATA, PROVINCIA DE CHUCUITO, REGION PUNO | D86: =Base!I367 -> 349668 | E86: =Base!J367 -> 237183.34 | F86: =D86-E86 -> 112484.66 | G86: =Base!L367 -> 20700 | H86: =D86-G86 -> 328968 | I86: =IF(D86=0,0,G86/D86) -> 0.059199012 | J86: =Base!U367 -> Equipamiento / Contrata | K86: =Base!R367 -> Parcialmente comprometido | L86: =Base!V367 -> No registrado en cartera | M86: =Base!W367 -> No registrado en cartera | N86: =Base!X367 -> No registrado en cartera | O86: =Base!Y367 -> No registrado en cartera | P86: =IF(Base!Z367="","",Base!Z367) | Q86: =Base!S367 -> Parcial | R86: =Base!N367 -> 205833.34 | S86: =Base!T367 -> 318318
A87: 14. INDUSTRIA | D87: =SUM(D88:D94) -> 1308816 | E87: =SUM(E88:E94) -> 1209080 | F87: =D87-E87 -> 99736 | G87: =SUM(G88:G94) -> 538610 | H87: =D87-G87 -> 770206 | I87: =IF(D87=0,0,G87/D87) -> 0.41152461 | R87: =SUM(R88:R94) -> 321200 | S87: =SUM(S88:S94) -> 411853
A88: =SUBTOTAL(103,$B$6:B88) -> 77 | B88: 356 | C88: =Base!H368 -> 2676422: MEJORAMIENTO DE LA COMPETITIVIDAD PRODUCTIVA DE LA CERAMICA TRADICIONAL DE CHECCA PUPUJA EN LA ASOCIACION CERAMICA TRADICIONAL ANCESTRAL CHACCA PUPUJA, DISTRITO DE JOSE DOMINGO CHOQUEHUANCA, PROVINCIA DE AZANGARO, REGION PUNO. | D88: =Base!I368 -> 5365 | E88: =Base!J368 -> 5364 | F88: =D88-E88 -> 1 | G88: =Base!L368 -> 5364 | H88: =D88-G88 -> 1 | I88: =IF(D88=0,0,G88/D88) -> 0.99981361 | J88: =Base!U368 -> Contrata | K88: =Base!R368 -> Ejecutado | L88: =Base!V368 -> No registrado en cartera | M88: =Base!W368 -> No registrado en cartera | N88: =Base!X368 -> No registrado en cartera | O88: =Base!Y368 -> No registrado en cartera | P88: =IF(Base!Z368="","",Base!Z368) | Q88: =Base!S368 -> No usar | R88: =Base!N368 -> 0 | S88: =Base!T368 -> 0
A89: =SUBTOTAL(103,$B$6:B89) -> 78 | B89: 374 | C89: =Base!H369 -> 2681274: MEJORAMIENTO DEL PROCESO DE PRODUCCION DE ARTICULOS MECANICOS EN LA CORPORACION MARSAD S.A.C. DEL DISTRITO DE PUNO, PROVINCIA DE PUNO, REGION DE PUNO | D89: =Base!I369 -> 335890 | E89: =Base!J369 -> 314900 | F89: =D89-E89 -> 20990 | G89: =Base!L369 -> 0 | H89: =D89-G89 -> 335890 | I89: =IF(D89=0,0,G89/D89) -> 0 | J89: =Base!U369 -> Equipamiento / Contrata | K89: =Base!R369 -> Mayormente comprometido | L89: =Base!V369 -> No registrado en cartera | M89: =Base!W369 -> No registrado en cartera | N89: =Base!X369 -> No registrado en cartera | O89: =Base!Y369 -> No registrado en cartera | P89: =IF(Base!Z369="","",Base!Z369) | Q89: =Base!S369 -> Difícil | R89: =Base!N369 -> 1020 | S89: =Base!T369 -> 22010
A90: =SUBTOTAL(103,$B$6:B90) -> 79 | B90: 377 | C90: =Base!H370 -> 2681130: MEJORAMIENTO DE LA PRODUCCION DEL ENVASADO DE AGUA DE MESA DE LA EMPRESA GRUPO ANCCASI SOCIEDAD ANONIMA CERRADA DEL DISTRITO DE CORANI, PROVINCIA CARABAYA, DEPARTAMENTO PUNO | D90: =Base!I370 -> 157066 | E90: =Base!J370 -> 157066 | F90: =D90-E90 -> 0 | G90: =Base!L370 -> 157066 | H90: =D90-G90 -> 0 | I90: =IF(D90=0,0,G90/D90) -> 1 | J90: =Base!U370 -> Equipamiento / Contrata | K90: =Base!R370 -> Ejecutado | L90: =Base!V370 -> No registrado en cartera | M90: =Base!W370 -> No registrado en cartera | N90: =Base!X370 -> No registrado en cartera | O90: =Base!Y370 -> No registrado en cartera | P90: =IF(Base!Z370="","",Base!Z370) | Q90: =Base!S370 -> No usar | R90: =Base!N370 -> 0 | S90: =Base!T370 -> 0
A91: =SUBTOTAL(103,$B$6:B91) -> 80 | B91: 386 | C91: =Base!H371 -> 2717150: MEJORAMIENTO DEL PROCESO PRODUCTIVO Y EL VALOR CULTURAL DE LAS CERAMICAS DE LA ASOCIACION DE ARTESANOS PRODUCTORES MUSUQ PAQARIY PUKARA, DEL DISTRITO DE PUCARA, PROVINCIA DE LAMPA, DEPARTAMENTO DE PUNO | D91: =Base!I371 -> 159345 | E91: =Base!J371 -> 150543 | F91: =D91-E91 -> 8802 | G91: =Base!L371 -> 150263 | H91: =D91-G91 -> 9082 | I91: =IF(D91=0,0,G91/D91) -> 0.94300417 | J91: =Base!U371 -> Equipamiento / Contrata | K91: =Base!R371 -> Ejecutado | L91: =Base!V371 -> No registrado en cartera | M91: =Base!W371 -> No registrado en cartera | N91: =Base!X371 -> No registrado en cartera | O91: =Base!Y371 -> No registrado en cartera | P91: =IF(Base!Z371="","",Base!Z371) | Q91: =Base!S371 -> No usar | R91: =Base!N371 -> 280 | S91: =Base!T371 -> 0
A92: =SUBTOTAL(103,$B$6:B92) -> 81 | B92: 473 | C92: =Base!H372 -> 2723295: MEJORAMIENTO DE LA PRODUCCION Y COMERCIALIZACION DE QUESOS TIPO PARIA DE LA ASOCIACION AGROINDUSTRIAL YURAQ WASI DE LA COMUNIDAD CAMPESINA PRIMER JILAHUATA, DISTRITO DE AZANGARO, PROVINCIA DE AZANGARO, REGION PUNO | D92: =Base!I372 -> 160000 | E92: =Base!J372 -> 145797 | F92: =D92-E92 -> 14203 | G92: =Base!L372 -> 139797 | H92: =D92-G92 -> 20203 | I92: =IF(D92=0,0,G92/D92) -> 0.87373125 | J92: =Base!U372 -> Equipamiento / Contrata | K92: =Base!R372 -> Mayormente comprometido | L92: =Base!V372 -> No registrado en cartera | M92: =Base!W372 -> No registrado en cartera | N92: =Base!X372 -> No registrado en cartera | O92: =Base!Y372 -> No registrado en cartera | P92: =IF(Base!Z372="","",Base!Z372) | Q92: =Base!S372 -> Difícil | R92: =Base!N372 -> 0 | S92: =Base!T372 -> 14203
A93: =SUBTOTAL(103,$B$6:B93) -> 82 | B93: 476 | C93: =Base!H373 -> 2723301: MEJORAMIENTO DE LA TRANSFORMACION Y COMERCIALIZACION DE HILOS Y PRENDAS DE TONOS Y TENIDOS NATURALES DE FIBRA DE ALPACA EN LA ASOCIACION DE ARTESANAS KISWAR TIKA, DISTRITO DE OCUVIRI, PROVINCIA LAMPA, REGION PUNO | D93: =Base!I373 -> 141150 | E93: =Base!J373 -> 115290 | F93: =D93-E93 -> 25860 | G93: =Base!L373 -> 0 | H93: =D93-G93 -> 141150 | I93: =IF(D93=0,0,G93/D93) -> 0 | J93: =Base!U373 -> Equipamiento / Contrata | K93: =Base!R373 -> Parcialmente comprometido | L93: =Base!V373 -> No registrado en cartera | M93: =Base!W373 -> No registrado en cartera | N93: =Base!X373 -> No registrado en cartera | O93: =Base!Y373 -> No registrado en cartera | P93: =IF(Base!Z373="","",Base!Z373) | Q93: =Base!S373 -> Parcial | R93: =Base!N373 -> 85900 | S93: =Base!T373 -> 111760
A94: =SUBTOTAL(103,$B$6:B94) -> 83 | B94: 477 | C94: =Base!H374 -> 2723299: MEJORAMIENTO DE LA CAPACIDAD PRODUCTIVA DE HELADOS ARTESANALES A BASE DE GRANOS ANDINOS DEL GRUPO DE PRODUCTORES, COMERCIALIZACION Y TRANSFORMACION DE CEREALES ANDINOS SAN SANTIAGO S.A.C., DEL DISTRITO DE PUNO, PROVINCIA DE PUNO, REGION DE PUNO. | D94: =Base!I374 -> 350000 | E94: =Base!J374 -> 320120 | F94: =D94-E94 -> 29880 | G94: =Base!L374 -> 86120 | H94: =D94-G94 -> 263880 | I94: =IF(D94=0,0,G94/D94) -> 0.24605714 | J94: =Base!U374 -> Equipamiento / Contrata | K94: =Base!R374 -> Parcialmente comprometido | L94: =Base!V374 -> No registrado en cartera | M94: =Base!W374 -> No registrado en cartera | N94: =Base!X374 -> No registrado en cartera | O94: =Base!Y374 -> No registrado en cartera | P94: =IF(Base!Z374="","",Base!Z374) | Q94: =Base!S374 -> Parcial | R94: =Base!N374 -> 234000 | S94: =Base!T374 -> 263880
A95: GERENCIA REGIONAL DE RECURSOS NATURALES Y GESTION AMBIENTAL | D95: =D96+D100+D102 -> 18155027 | E95: =E96+E100+E102 -> 15578094 | F95: =D95-E95 -> 2576932.7 | G95: =G96+G100+G102 -> 8757642.5 | H95: =D95-G95 -> 9397384.5 | I95: =IF(D95=0,0,G95/D95) -> 0.48238113 | R95: =R96+R100+R102 -> 369162.68 | S95: =S96+S100+S102 -> 2946095.4
A96: 05. ORDEN PUBLICO Y SEGURIDAD | D96: =SUM(D97:D99) -> 16120710 | E96: =SUM(E97:E99) -> 15413788 | F96: =D96-E96 -> 706921.89 | G96: =SUM(G97:G99) -> 8626797.8 | H96: =D96-G96 -> 7493912.2 | I96: =IF(D96=0,0,G96/D96) -> 0.53513759 | R96: =SUM(R97:R99) -> 357984.08 | S96: =SUM(S97:S99) -> 1064906
A97: =SUBTOTAL(103,$B$6:B97) -> 84 | B97: 4 | C97: =Base!H375 -> 2183634: MEJORAMIENTO DE LA DEFENSA RIBEREÑA EN LAS MARGENES DERECHA E IZQUIERDA DEL RIO RAMIS EN LOS TRAMOS DE SACASCO, COLLANA, CHACAMARCA, PATASCACHI, YANAOCO, TUNI GRANDE, RAMIS Y BALSAPATA DE LAS PROVINCIAS DE HUANCANE Y AZANGARO - REGION PUNO | D97: =Base!I375 -> 10918999 | E97: =Base!J375 -> 10451686 | F97: =D97-E97 -> 467312.78 | G97: =Base!L375 -> 5853517.8 | H97: =D97-G97 -> 5065481.2 | I97: =IF(D97=0,0,G97/D97) -> 0.53608557 | J97: =Base!U375 -> Administración directa / Contrata / Personal/bienes/servicios | K97: =Base!R375 -> Mayormente comprometido | L97: =Base!V375 -> 10517000 | M97: =Base!W375 -> 7783178 | N97: =Base!X375 -> 1598000 | O97: =Base!Y375 -> 2000000 | P97: =IF(Base!Z375="","",Base!Z375) | Q97: =Base!S375 -> Difícil | R97: =Base!N375 -> 583.33 | S97: =Base!T375 -> 467896.11
A98: =SUBTOTAL(103,$B$6:B98) -> 85 | B98: 6 | C98: =Base!H376 -> 2532916: CREACION DEL SERVICIO DE PROTECCIÓN EN RIBERAS DEL RÍO LORIPONGO Y MOLLA AMBOS MÁRGENES VULNERABLES ANTE EL PELIGRO DE INUNDACIÓN EN LA LOCALIDAD DE LARAQUERI Y CENTRO POBLADO DE HUARIJUYO DEL DISTRITO DE PICHACANI - PROVINCIA DE PUNO - DEPARTAMENTO DE PUNO | D98: =Base!I376 -> 19658 | E98: =Base!J376 -> 3612 | F98: =D98-E98 -> 16046 | G98: =Base!L376 -> 0 | H98: =D98-G98 -> 19658 | I98: =IF(D98=0,0,G98/D98) -> 0 | J98: =Base!U376 -> Expediente técnico | K98: =Base!R376 -> Solo certificado | L98: =Base!V376 -> 200000 | M98: =Base!W376 -> 2915452 | N98: =Base!X376 -> 2124684 | O98: =Base!Y376 -> 2000000 | P98: =IF(Base!Z376="","",Base!Z376) | Q98: =Base!S376 -> Posible | R98: =Base!N376 -> 3612 | S98: =Base!T376 -> 19658
A99: =SUBTOTAL(103,$B$6:B99) -> 86 | B99: 303 | C99: =Base!H377 -> 2520451: CREACION DEL SERVICIO DE PROTECCION EN RIBERAS DEL RIO QUELLOMAYO MARGEN DERECHO VULNERABLES ANTE EL PELIGRO DE INUNDACION EN LA LOCALIDAD DE SAN GABAN, DEL DISTRITO DE SAN GABAN - PROVINCIA DE CARABAYA - DEPARTAMENTO DE PUNO | D99: =Base!I377 -> 5182053 | E99: =Base!J377 -> 4958489.9 | F99: =D99-E99 -> 223563.11 | G99: =Base!L377 -> 2773280 | H99: =D99-G99 -> 2408773 | I99: =IF(D99=0,0,G99/D99) -> 0.53517013 | J99: =Base!U377 -> Administración directa / Contrata / Personal/bienes/servicios | K99: =Base!R377 -> Mayormente comprometido | L99: =Base!V377 -> 409040 | M99: =Base!W377 -> 29865 | N99: =Base!X377 -> 0 | O99: =Base!Y377 -> 0 | P99: =IF(Base!Z377="","",Base!Z377) | Q99: =Base!S377 -> Difícil | R99: =Base!N377 -> 353788.75 | S99: =Base!T377 -> 577351.86
A100: 10. AGROPECUARIA | D100: =SUM(D101:D101) -> 1800000 | E100: =SUM(E101:E101) -> 26893 | F100: =D100-E100 -> 1773107 | G100: =SUM(G101:G101) -> 26892.69 | H100: =D100-G100 -> 1773107.3 | I100: =IF(D100=0,0,G100/D100) -> 0.014940383 | R100: =SUM(R101:R101) -> 0 | S100: =SUM(S101:S101) -> 1773107
A101: =SUBTOTAL(103,$B$6:B101) -> 87 | B101: 5 | C101: =Base!H378 -> 2474102: MEJORAMIENTO DEL SERVICIO DE PROTECCIÓN FRENTE A TORMENTAS ELÉCTRICAS EN 4 PROVINCIAS DEL DEPARTAMENTO DE PUNO | D101: =Base!I378 -> 1800000 | E101: =Base!J378 -> 26893 | F101: =D101-E101 -> 1773107 | G101: =Base!L378 -> 26892.69 | H101: =D101-G101 -> 1773107.3 | I101: =IF(D101=0,0,G101/D101) -> 0.014940383 | J101: =Base!U378 -> Personal/bienes/servicios / Contrata / Equipamiento / Expediente técnico | K101: =Base!R378 -> Parcialmente comprometido | L101: =Base!V378 -> 300000 | M101: =Base!W378 -> 4508196 | N101: =Base!X378 -> 5000000 | O101: =Base!Y378 -> 1000000 | P101: =IF(Base!Z378="","",Base!Z378) | Q101: =Base!S378 -> Parcial | R101: =Base!N378 -> 0 | S101: =Base!T378 -> 1773107
A102: 17. AMBIENTE | D102: =SUM(D103:D109) -> 234317 | E102: =SUM(E103:E109) -> 137413.2 | F102: =D102-E102 -> 96903.8 | G102: =SUM(G103:G109) -> 103951.95 | H102: =D102-G102 -> 130365.05 | I102: =IF(D102=0,0,G102/D102) -> 0.44363811 | R102: =SUM(R103:R109) -> 11178.6 | S102: =SUM(S103:S109) -> 108082.4
A103: =SUBTOTAL(103,$B$6:B103) -> 88 | B103: 7 | C103: =Base!H379 -> 2533866: RECUPERACION DE ECOSISTEMAS DEGRADADOS POR VERTIMIENTO DE AGUAS RESIDUALES Y RESIDUOS SOLIDOS EN LA DESEMBOCADURA DEL RIO COATA, EN LOS DISTRITOS DE HUATA, COATA, CAPACHICA, JULIACA Y SAN MIGUEL EN LAS PROVINCIAS DE PUNO Y SAN ROMAN DEL DEPARTAMENTO DE PUNO | D103: =Base!I379 -> 32099 | E103: =Base!J379 -> 0 | F103: =D103-E103 -> 32099 | G103: =Base!L379 -> 0 | H103: =D103-G103 -> 32099 | I103: =IF(D103=0,0,G103/D103) -> 0 | J103: =Base!U379 -> Contrata | K103: =Base!R379 -> Sin certificar | L103: =Base!V379 -> 500000 | M103: =Base!W379 -> 0 | N103: =Base!X379 -> 0 | O103: =Base!Y379 -> 0 | P103: =IF(Base!Z379="","",Base!Z379) | Q103: =Base!S379 -> Disponible | R103: =Base!N379 -> 0 | S103: =Base!T379 -> 32099
A104: =SUBTOTAL(103,$B$6:B104) -> 89 | B104: 152 | C104: =Base!H380 -> 2250970: MEJORAMIENTO DEL SERVICIO DE CONSERVACION DE LA DIVERSIDAD BIOLOGICA EN SELVA VERDE, SAN GABAN, PUNTA PERDIDA, COTACUCHO, PUNO, JUCUMARINI, CUSHINI, RIO CONDOR, RIO TAVARA, Y PACO PACUNI, DISTRITOS DE AYAPATA, SAN GABAN, SANTA ROSA, VILQUE CHICO-PUNO | D104: =Base!I380 -> 30000 | E104: =Base!J380 -> 23434 | F104: =D104-E104 -> 6566 | G104: =Base!L380 -> 13106.35 | H104: =D104-G104 -> 16893.65 | I104: =IF(D104=0,0,G104/D104) -> 0.43687833 | J104: =Base!U380 -> Contrata / Personal/bienes/servicios | K104: =Base!R380 -> Mayormente comprometido | L104: =Base!V380 -> 2080646 | M104: =Base!W380 -> 70728 | N104: =Base!X380 -> 300000 | O104: =Base!Y380 -> 300000 | P104: =IF(Base!Z380="","",Base!Z380) | Q104: =Base!S380 -> Difícil | R104: =Base!N380 -> 0 | S104: =Base!T380 -> 6566
A105: =SUBTOTAL(103,$B$6:B105) -> 90 | B105: 154 | C105: =Base!H381 -> 2631070: RECUPERACION DE LOS SERVICIOS ECOSISTÉMICOS EN 19 UNIDADES PRODUCTORAS 19 DISTRITOS DE 13 PROVINCIAS DEL DEPARTAMENTO DE PUNO | D105: =Base!I381 -> 90586 | E105: =Base!J381 -> 90435.2 | F105: =D105-E105 -> 150.8 | G105: =Base!L381 -> 78301.6 | H105: =D105-G105 -> 12284.4 | I105: =IF(D105=0,0,G105/D105) -> 0.86438964 | J105: =Base!U381 -> Expediente técnico | K105: =Base!R381 -> Mayormente comprometido | L105: =Base!V381 -> 100000 | M105: =Base!W381 -> 0 | N105: =Base!X381 -> 2000000 | O105: =Base!Y381 -> 2000000 | P105: =IF(Base!Z381="","",Base!Z381) | Q105: =Base!S381 -> Difícil | R105: =Base!N381 -> 178.6 | S105: =Base!T381 -> 329.4
A106: =SUBTOTAL(103,$B$6:B106) -> 91 | B106: 250 | C106: =Base!H382 -> 2549395: RECUPERACION DE ECOSISTEMAS DEGRADADOS EN LAS UNIDADES HIDROGRAFICAS: LLALLIMAYO DE LA UH 018 PUCARA Y UH 019 AZANGARO, DE LA CUENCA RAMIS DEL DEPARTAMENTO DE PUNO, REGION PUNO 5 PROVINCIAS DEL DEPARTAMENTO DE PUNO | D106: =Base!I382 -> 0 | E106: =Base!J382 -> 0 | F106: =D106-E106 -> 0 | G106: =Base!L382 -> 0 | H106: =D106-G106 -> 0 | I106: =IF(D106=0,0,G106/D106) -> 0 | J106: =Base!U382 -> Contrata | K106: =Base!R382 -> Sin PIM | L106: =Base!V382 -> 800000 | M106: =Base!W382 -> 0 | N106: =Base!X382 -> 0 | O106: =Base!Y382 -> 0 | P106: =IF(Base!Z382="","",Base!Z382) | Q106: =Base!S382 -> Sin PIM | R106: =Base!N382 -> 0 | S106: =Base!T382 -> 0
A107: =SUBTOTAL(103,$B$6:B107) -> 92 | B107: 253 | C107: =Base!H383 -> 2566295: RECUPERACION DE ECOSISTEMAS DEGRADADOS EN ZONAS ALTO ANDINAS EN CABECERA DE CUENCA DE LAS UH0172, UH0178 Y UH0171 CUENCA SUCHES EN 4 PROVINCIAS DEL DEPARTAMENTO DE PUNO | D107: =Base!I383 -> 0 | E107: =Base!J383 -> 0 | F107: =D107-E107 -> 0 | G107: =Base!L383 -> 0 | H107: =D107-G107 -> 0 | I107: =IF(D107=0,0,G107/D107) -> 0 | J107: =Base!U383 -> Personal/bienes/servicios | K107: =Base!R383 -> Sin PIM | L107: =Base!V383 -> 200000 | M107: =Base!W383 -> 0 | N107: =Base!X383 -> 0 | O107: =Base!Y383 -> 0 | P107: =IF(Base!Z383="","",Base!Z383) | Q107: =Base!S383 -> Sin PIM | R107: =Base!N383 -> 0 | S107: =Base!T383 -> 0
A108: =SUBTOTAL(103,$B$6:B108) -> 93 | B108: 465 | C108: =Base!H384 -> 2260735: MEJORAMIENTO DE LA GESTION INTEGRADA DE LOS RECURSOS HIDRICOS EN CUENCAS DE LA REGION PUNO | D108: =Base!I384 -> 70632 | E108: =Base!J384 -> 12544 | F108: =D108-E108 -> 58088 | G108: =Base!L384 -> 12544 | H108: =D108-G108 -> 58088 | I108: =IF(D108=0,0,G108/D108) -> 0.17759656 | J108: =Base!U384 -> Contrata / Personal/bienes/servicios | K108: =Base!R384 -> Parcialmente comprometido | L108: =Base!V384 -> 70632 | M108: =Base!W384 -> 0 | N108: =Base!X384 -> 0 | O108: =Base!Y384 -> 0 | P108: =IF(Base!Z384="","",Base!Z384) | Q108: =Base!S384 -> Parcial | R108: =Base!N384 -> 0 | S108: =Base!T384 -> 58088
A109: =SUBTOTAL(103,$B$6:B109) -> 94 | B109: 471 | C109: =Base!H385 -> 2684838: MEJORAMIENTO Y AMPLIACION DEL SERVICIO DE LIMPIEZA PÚBLICA EN 7 UNIDADES PRODUCTORAS 7 DISTRITOS DE LA PROVINCIA DE MELGAR DEL DEPARTAMENTO DE PUNO | D109: =Base!I385 -> 11000 | E109: =Base!J385 -> 11000 | F109: =D109-E109 -> 0 | G109: =Base!L385 -> 0 | H109: =D109-G109 -> 11000 | I109: =IF(D109=0,0,G109/D109) -> 0 | J109: =Base!U385 -> Contrata / Administración directa | K109: =Base!R385 -> Solo certificado | L109: =Base!V385 -> 11000 | M109: =Base!W385 -> 164792 | N109: =Base!X385 -> 9322563 | O109: =Base!Y385 -> 9322563 | P109: =IF(Base!Z385="","",Base!Z385) | Q109: =Base!S385 -> Posible | R109: =Base!N385 -> 11000 | S109: =Base!T385 -> 11000
A110: PROYECTO ESPECIAL TRUCHAS TITICACA - PETT | D110: =D111 -> 13183082 | E110: =E111 -> 12706541 | F110: =D110-E110 -> 476541.15 | G110: =G111 -> 3714211.5 | H110: =D110-G110 -> 9468870.5 | I110: =IF(D110=0,0,G110/D110) -> 0.28174076 | R110: =R111 -> 6205893.7 | S110: =S111 -> 6651033.8
A111: 03. PLANEAMIENTO, GESTION Y RESERVA DE CONTINGENCIA | D111: =SUM(D112:D114) -> 13183082 | E111: =SUM(E112:E114) -> 12706541 | F111: =D111-E111 -> 476541.15 | G111: =SUM(G112:G114) -> 3714211.5 | H111: =D111-G111 -> 9468870.5 | I111: =IF(D111=0,0,G111/D111) -> 0.28174076 | R111: =SUM(R112:R114) -> 6205893.7 | S111: =SUM(S112:S114) -> 6651033.8
A112: =SUBTOTAL(103,$B$6:B112) -> 95 | B112: 59 | C112: =Base!H386 -> 2324613: MEJORAMIENTO DE LAS CAPACIDADES TECNOLÓGICAS EN EL MANEJO DE CADENA PRODUCTIVA DE TRUCHA EN LA REGIÓN PUNO | D112: =Base!I386 -> 550560 | E112: =Base!J386 -> 519500 | F112: =D112-E112 -> 31060 | G112: =Base!L386 -> 517920.09 | H112: =D112-G112 -> 32639.91 | I112: =IF(D112=0,0,G112/D112) -> 0.94071507 | J112: =Base!U386 -> Personal/bienes/servicios / Contrata | K112: =Base!R386 -> Ejecutado | L112: =Base!V386 -> 100560 | M112: =Base!W386 -> 93700 | N112: =Base!X386 -> 0 | O112: =Base!Y386 -> 0 | P112: =IF(Base!Z386="","",Base!Z386) | Q112: =Base!S386 -> No usar | R112: =Base!N386 -> 341.06 | S112: =Base!T386 -> 0
A113: =SUBTOTAL(103,$B$6:B113) -> 96 | B113: 60 | C113: =Base!H387 -> 2603148: MEJORAMIENTO DE LOS SERVICIOS DE APOYO AL DESARROLLO PRODUCTIVO EN 19 UNIDADES PRODUCTORAS 19 DISTRITOS DE 7 PROVINCIAS DEL DEPARTAMENTO DE PUNO | D113: =Base!I387 -> 12532522 | E113: =Base!J387 -> 12187041 | F113: =D113-E113 -> 345481.15 | G113: =Base!L387 -> 3196291.4 | H113: =D113-G113 -> 9336230.6 | I113: =IF(D113=0,0,G113/D113) -> 0.25503976 | J113: =Base!U387 -> Administración directa / Personal/bienes/servicios / Contrata / Equipamiento | K113: =Base!R387 -> Parcialmente comprometido | L113: =Base!V387 -> 1000000 | M113: =Base!W387 -> 4832260 | N113: =Base!X387 -> 1000000 | O113: =Base!Y387 -> 1000000 | P113: =IF(Base!Z387="","",Base!Z387) | Q113: =Base!S387 -> Parcial | R113: =Base!N387 -> 6205552.7 | S113: =Base!T387 -> 6551033.8
A114: =SUBTOTAL(103,$B$6:B114) -> 97 | B114: 61 | C114: =Base!H388 -> 2603160: MEJORAMIENTO DE LOS SERVICIOS DE APOYO AL DESARROLLO PRODUCTIVO EN 4 UNIDADES PRODUCTORAS 4 DISTRITOS DE LAS PROVINCIAS DE SANDIA, CARABAYA DEL DEPARTAMENTO DE PUNO | D114: =Base!I388 -> 100000 | E114: =Base!J388 -> 0 | F114: =D114-E114 -> 100000 | G114: =Base!L388 -> 0 | H114: =D114-G114 -> 100000 | I114: =IF(D114=0,0,G114/D114) -> 0 | J114: =Base!U388 -> Personal/bienes/servicios | K114: =Base!R388 -> Sin certificar | L114: =Base!V388 -> 100000 | M114: =Base!W388 -> 0 | N114: =Base!X388 -> 0 | O114: =Base!Y388 -> 0 | P114: =IF(Base!Z388="","",Base!Z388) | Q114: =Base!S388 -> Disponible | R114: =Base!N388 -> 0 | S114: =Base!T388 -> 100000
A115: PROYECTO ESPECIAL CAMELIDOS SUDAMERICANOS | D115: =D116+D118 -> 5603985 | E115: =E116+E118 -> 5402770 | F115: =D115-E115 -> 201215.05 | G115: =G116+G118 -> 3499541.4 | H115: =D115-G115 -> 2104443.6 | I115: =IF(D115=0,0,G115/D115) -> 0.62447372 | R115: =R116+R118 -> 1324600.5 | S115: =S116+S118 -> 1522323.7
A116: 03. PLANEAMIENTO, GESTION Y RESERVA DE CONTINGENCIA | D116: =SUM(D117:D117) -> 1332387 | E116: =SUM(E117:E117) -> 1332216.6 | F116: =D116-E116 -> 170.39 | G116: =SUM(G117:G117) -> 1212326 | H116: =D116-G116 -> 120061 | I116: =IF(D116=0,0,G116/D116) -> 0.90989029 | R116: =SUM(R117:R117) -> 3321.5 | S116: =SUM(S117:S117) -> 0
A117: =SUBTOTAL(103,$B$6:B117) -> 98 | B117: 218 | C117: =Base!H389 -> 2187217: MEJORAMIENTO DE LA CADENA DE VALOR DE LA FIBRA DE ALPACA EN LA REGION PUNO | D117: =Base!I389 -> 1332387 | E117: =Base!J389 -> 1332216.6 | F117: =D117-E117 -> 170.39 | G117: =Base!L389 -> 1212326 | H117: =D117-G117 -> 120061 | I117: =IF(D117=0,0,G117/D117) -> 0.90989029 | J117: =Base!U389 -> Contrata / Personal/bienes/servicios | K117: =Base!R389 -> Ejecutado | L117: =Base!V389 -> 630478 | M117: =Base!W389 -> 188781 | N117: =Base!X389 -> 2845395 | O117: =Base!Y389 -> 2772809 | P117: =IF(Base!Z389="","",Base!Z389) | Q117: =Base!S389 -> No usar | R117: =Base!N389 -> 3321.5 | S117: =Base!T389 -> 0
A118: 10. AGROPECUARIA | D118: =SUM(D119:D119) -> 4271598 | E118: =SUM(E119:E119) -> 4070553.3 | F118: =D118-E118 -> 201044.66 | G118: =SUM(G119:G119) -> 2287215.4 | H118: =D118-G118 -> 1984382.6 | I118: =IF(D118=0,0,G118/D118) -> 0.53544724 | R118: =SUM(R119:R119) -> 1321279 | S118: =SUM(S119:S119) -> 1522323.7
A119: =SUBTOTAL(103,$B$6:B119) -> 99 | B119: 264 | C119: =Base!H390 -> 2603155: MEJORAMIENTO DE LOS SERVICIOS DE APOYO AL DESARROLLO PRODUCTIVO EN 37 UNIDADES PRODUCTORAS 37 DISTRITOS DE 11 PROVINCIAS DEL DEPARTAMENTO DE PUNO | D119: =Base!I390 -> 4271598 | E119: =Base!J390 -> 4070553.3 | F119: =D119-E119 -> 201044.66 | G119: =Base!L390 -> 2287215.4 | H119: =D119-G119 -> 1984382.6 | I119: =IF(D119=0,0,G119/D119) -> 0.53544724 | J119: =Base!U390 -> Personal/bienes/servicios / Contrata / Equipamiento | K119: =Base!R390 -> Mayormente comprometido | L119: =Base!V390 -> 1500000 | M119: =Base!W390 -> 4950944 | N119: =Base!X390 -> 5144103 | O119: =Base!Y390 -> 4718085 | P119: =IF(Base!Z390="","",Base!Z390) | Q119: =Base!S390 -> Difícil | R119: =Base!N390 -> 1321279 | S119: =Base!T390 -> 1522323.7
A120: GERENCIA REGIONAL DE DESARROLLO SOCIAL | D120: =D121+D149+D162+D165 -> 74669674 | E120: =E121+E149+E162+E165 -> 67480327 | F120: =D120-E120 -> 7189346.7 | G120: =G121+G149+G162+G165 -> 23520433 | H120: =D120-G120 -> 51149241 | I120: =IF(D120=0,0,G120/D120) -> 0.31499311 | R120: =R121+R149+R162+R165 -> 40882366 | S120: =S121+S149+S162+S165 -> 47699719
A121: 20. SALUD | D121: =SUM(D122:D148) -> 52935028 | E121: =SUM(E122:E148) -> 48878434 | F121: =D121-E121 -> 4056593.9 | G121: =SUM(G122:G148) -> 17052641 | H121: =D121-G121 -> 35882387 | I121: =IF(D121=0,0,G121/D121) -> 0.32214286 | R121: =SUM(R122:R148) -> 28837113 | S121: =SUM(S122:S148) -> 32530442
A122: =SUBTOTAL(103,$B$6:B122) -> 100 | B122: 195 | C122: =Base!H391 -> 2154443: MEJORAMIENTO DEL ESTADO NUTRICIONAL DEL NIÑO MENOR DE TRES AÑOS Y LA MADRE GESTANTE EN LAS PROVINCIAS DE AZANGARO, LAMPA Y SAN ROMAN DE LA REGION PUNO | D122: =Base!I391 -> 0 | E122: =Base!J391 -> 0 | F122: =D122-E122 -> 0 | G122: =Base!L391 -> 0 | H122: =D122-G122 -> 0 | I122: =IF(D122=0,0,G122/D122) -> 0 | J122: =Base!U391 -> Personal/bienes/servicios | K122: =Base!R391 -> Sin PIM | L122: =Base!V391 -> 4098 | M122: =Base!W391 -> 0 | N122: =Base!X391 -> 0 | O122: =Base!Y391 -> 0 | P122: =IF(Base!Z391="","",Base!Z391) | Q122: =Base!S391 -> Sin PIM | R122: =Base!N391 -> 0 | S122: =Base!T391 -> 0
A123: =SUBTOTAL(103,$B$6:B123) -> 101 | B123: 196 | C123: =Base!H392 -> 2159149: MEJORAMIENTO DE LAS CAPACIDADES PARA PREVENIR LA DESNUTRICION CRONICA, EN MENORES DE 3 AÑOS EN LAS PROVINCIAS DE CARABAYA, MELGAR Y SANDIA DE LA REGION PUNO | D123: =Base!I392 -> 0 | E123: =Base!J392 -> 0 | F123: =D123-E123 -> 0 | G123: =Base!L392 -> 0 | H123: =D123-G123 -> 0 | I123: =IF(D123=0,0,G123/D123) -> 0 | J123: =Base!U392 -> Personal/bienes/servicios | K123: =Base!R392 -> Sin PIM | L123: =Base!V392 -> 87917 | M123: =Base!W392 -> 0 | N123: =Base!X392 -> 0 | O123: =Base!Y392 -> 0 | P123: =IF(Base!Z392="","",Base!Z392) | Q123: =Base!S392 -> Sin PIM | R123: =Base!N392 -> 0 | S123: =Base!T392 -> 0
A124: =SUBTOTAL(103,$B$6:B124) -> 102 | B124: 239 | C124: =Base!H393 -> 2488048: CREACION DEL SERVICIO DE ANÁLISIS DE BIOLOGIA MOLECULAR DE DIAGNÓSTICO COVID-19 EN EL LABORATORIO DE REFERENCIA REGIONAL DE LA DIRESA PUNO, DISTRITO DE PUNO - PROVINCIA DE PUNO - DEPARTAMENTO DE PUNO | D124: =Base!I393 -> 0 | E124: =Base!J393 -> 0 | F124: =D124-E124 -> 0 | G124: =Base!L393 -> 0 | H124: =D124-G124 -> 0 | I124: =IF(D124=0,0,G124/D124) -> 0 | J124: =Base!U393 -> Administración directa | K124: =Base!R393 -> Sin PIM | L124: =Base!V393 -> 276105 | M124: =Base!W393 -> 0 | N124: =Base!X393 -> 0 | O124: =Base!Y393 -> 0 | P124: =IF(Base!Z393="","",Base!Z393) | Q124: =Base!S393 -> Sin PIM | R124: =Base!N393 -> 0 | S124: =Base!T393 -> 0
A125: =SUBTOTAL(103,$B$6:B125) -> 103 | B125: 249 | C125: =Base!H394 -> 2544369: ADQUISICION DE AMBULANCIA RURAL Y AMBULANCIA RURAL; EN CINCUENTA Y CINCO ESTABLECIMIENTOS DE SALUD I.4, ESTABLECIMIENTOS DE SALUD I.2, ESTABLECIMIENTOS DE SALUD I.3 A NIVEL DEPARTAMENTAL (PUNO) | D125: =Base!I394 -> 0 | E125: =Base!J394 -> 0 | F125: =D125-E125 -> 0 | G125: =Base!L394 -> 0 | H125: =D125-G125 -> 0 | I125: =IF(D125=0,0,G125/D125) -> 0 | J125: =Base!U394 -> Personal/bienes/servicios | K125: =Base!R394 -> Sin PIM | L125: =Base!V394 -> 89896 | M125: =Base!W394 -> 0 | N125: =Base!X394 -> 0 | O125: =Base!Y394 -> 0 | P125: =IF(Base!Z394="","",Base!Z394) | Q125: =Base!S394 -> Sin PIM | R125: =Base!N394 -> 0 | S125: =Base!T394 -> 0
A126: =SUBTOTAL(103,$B$6:B126) -> 104 | B126: 254 | C126: =Base!H395 -> 2567368: ADQUISICION DE MAMOGRAFO; EN EL(LA) EESS SAN MARTIN DE P. (MACUSANI) - MACUSANI DISTRITO DE MACUSANI, PROVINCIA CARABAYA, DEPARTAMENTO PUNO | D126: =Base!I395 -> 2390440 | E126: =Base!J395 -> 2386020 | F126: =D126-E126 -> 4420 | G126: =Base!L395 -> 824976.09 | H126: =D126-G126 -> 1565463.9 | I126: =IF(D126=0,0,G126/D126) -> 0.34511474 | J126: =Base!U395 -> Equipamiento / Contrata / Personal/bienes/servicios | K126: =Base!R395 -> Mayormente comprometido | L126: =Base!V395 -> 21175 | M126: =Base!W395 -> 2971 | N126: =Base!X395 -> 1 | O126: =Base!Y395 -> 0 | P126: =IF(Base!Z395="","",Base!Z395) | Q126: =Base!S395 -> Difícil | R126: =Base!N395 -> 0 | S126: =Base!T395 -> 4420
A127: =SUBTOTAL(103,$B$6:B127) -> 105 | B127: 255 | C127: =Base!H396 -> 2567375: ADQUISICION DE TOMOGRAFO COMPUTARIZADO MULTICORTE; EN EL(LA) EESS SAN MARTIN DE P. (MACUSANI) - MACUSANI DISTRITO DE MACUSANI, PROVINCIA CARABAYA, DEPARTAMENTO PUNO | D127: =Base!I396 -> 20600 | E127: =Base!J396 -> 20600 | F127: =D127-E127 -> 0 | G127: =Base!L396 -> 17783.6 | H127: =D127-G127 -> 2816.4 | I127: =IF(D127=0,0,G127/D127) -> 0.86328155 | J127: =Base!U396 -> Contrata | K127: =Base!R396 -> Mayormente comprometido | L127: =Base!V396 -> 40062 | M127: =Base!W396 -> 0 | N127: =Base!X396 -> 0 | O127: =Base!Y396 -> 0 | P127: =IF(Base!Z396="","",Base!Z396) | Q127: =Base!S396 -> Difícil | R127: =Base!N396 -> 0 | S127: =Base!T396 -> 0
A128: =SUBTOTAL(103,$B$6:B128) -> 106 | B128: 263 | C128: =Base!H397 -> 2600443: ADQUISICION DE SISTEMA DE CIRUGIA LAPAROSCOPICA, TOMOGRAFO, MESA DE OPERACIONES HIDRAULICA/ELECTRICA Y LAMPARA QUIRURGICA DE TECHO; ADEMÁS DE OTROS ACTIVOS EN EL(LA) YUNGUYO DISTRITO DE YUNGUYO, PROVINCIA YUNGUYO, DEPARTAMENTO PUNO | D128: =Base!I397 -> 3517960 | E128: =Base!J397 -> 3461030.1 | F128: =D128-E128 -> 56929.9 | G128: =Base!L397 -> 2179648.5 | H128: =D128-G128 -> 1338311.5 | I128: =IF(D128=0,0,G128/D128) -> 0.6195774 | J128: =Base!U397 -> Equipamiento / Contrata / Personal/bienes/servicios | K128: =Base!R397 -> Mayormente comprometido | L128: =Base!V397 -> 2000000 | M128: =Base!W397 -> 64020 | N128: =Base!X397 -> 1401972 | O128: =Base!Y397 -> 495265 | P128: =IF(Base!Z397="","",Base!Z397) | Q128: =Base!S397 -> Difícil | R128: =Base!N397 -> 1228353 | S128: =Base!T397 -> 1285282.9
A129: =SUBTOTAL(103,$B$6:B129) -> 107 | B129: 281 | C129: =Base!H398 -> 2650340: ADQUISICION DE MESA DE OPERACIONES HIDRAULICA/ELECTRICA, ESTERILIZADOR CON GENERADOR ELECTRICO DE VAPOR (INS), EQUIPOS BIOMEDICOS Y COCHE DE PARO; ADEMÁS DE OTROS ACTIVOS EN EL(LA) PUTINA DISTRITO DE PUTINA, PROVINCIA SAN ANTONIO DE PUTINA, DEPARTAMENTO PUNO | D129: =Base!I398 -> 2170829 | E129: =Base!J398 -> 2170829 | F129: =D129-E129 -> 0 | G129: =Base!L398 -> 147448.3 | H129: =D129-G129 -> 2023380.7 | I129: =IF(D129=0,0,G129/D129) -> 0.067922577 | J129: =Base!U398 -> Equipamiento / Contrata | K129: =Base!R398 -> Parcialmente comprometido | L129: =Base!V398 -> 2421000 | M129: =Base!W398 -> 2508625 | N129: =Base!X398 -> 546908 | O129: =Base!Y398 -> 170650 | P129: =IF(Base!Z398="","",Base!Z398) | Q129: =Base!S398 -> Parcial | R129: =Base!N398 -> 2020000 | S129: =Base!T398 -> 2020000
A130: =SUBTOTAL(103,$B$6:B130) -> 108 | B130: 285 | C130: =Base!H399 -> 2684028: ADQUISICION DE AMBULANCIA URBANA; EN ONCE ESTABLECIMIENTOS DE SALUD II.1, ESTABLECIMIENTOS DE SALUD II.2 A NIVEL DEPARTAMENTAL (PUNO) | D130: =Base!I399 -> 31336 | E130: =Base!J399 -> 0 | F130: =D130-E130 -> 31336 | G130: =Base!L399 -> 0 | H130: =D130-G130 -> 31336 | I130: =IF(D130=0,0,G130/D130) -> 0 | J130: =Base!U399 -> Contrata | K130: =Base!R399 -> Sin certificar | L130: =Base!V399 -> 513444 | M130: =Base!W399 -> 0 | N130: =Base!X399 -> 0 | O130: =Base!Y399 -> 0 | P130: =IF(Base!Z399="","",Base!Z399) | Q130: =Base!S399 -> Disponible | R130: =Base!N399 -> 0 | S130: =Base!T399 -> 31336
A131: =SUBTOTAL(103,$B$6:B131) -> 109 | B131: 287 | C131: =Base!H400 -> 2685776: ADQUISICION DE ANALIZADOR DE GASES Y ELECTROLITOS, ESPECTROFOTOMETRO, EQUIPO DE RAYOS X DENTAL Y BIDESTILADOR DE AGUA; ADEMÁS DE OTROS ACTIVOS EN EL(LA) MOHO DISTRITO DE MOHO, PROVINCIA MOHO, DEPARTAMENTO PUNO | D131: =Base!I400 -> 1263865 | E131: =Base!J400 -> 1181167.9 | F131: =D131-E131 -> 82697.06 | G131: =Base!L400 -> 146441.28 | H131: =D131-G131 -> 1117423.7 | I131: =IF(D131=0,0,G131/D131) -> 0.11586782 | J131: =Base!U400 -> Equipamiento / Contrata / Personal/bienes/servicios | K131: =Base!R400 -> Parcialmente comprometido | L131: =Base!V400 -> 894000 | M131: =Base!W400 -> 0 | N131: =Base!X400 -> 825648 | O131: =Base!Y400 -> 825648 | P131: =IF(Base!Z400="","",Base!Z400) | Q131: =Base!S400 -> Parcial | R131: =Base!N400 -> 1027198.8 | S131: =Base!T400 -> 1109895.9
A132: =SUBTOTAL(103,$B$6:B132) -> 110 | B132: 313 | C132: =Base!H401 -> 2694246: ADQUISICION DE MAMOGRAFO, COLONOVIDEOENDOSCOPIO, MESA DE OPERACIONES HIDRAULICA/ELECTRICA Y CALDERO; ADEMÁS DE OTROS ACTIVOS EN EL(LA) HOSPITAL REGIONAL MANUEL NUÑEZ BUTRON HOSPITAL REGIONAL MANUEL NUÑEZ BUTRON DISTRITO DE PUNO, PROVINCIA PUNO, DEPARTAMENTO PUNO | D132: =Base!I401 -> 8483998 | E132: =Base!J401 -> 8474782.3 | F132: =D132-E132 -> 9215.69 | G132: =Base!L401 -> 5322446.1 | H132: =D132-G132 -> 3161551.9 | I132: =IF(D132=0,0,G132/D132) -> 0.62735117 | J132: =Base!U401 -> Equipamiento / Contrata / Personal/bienes/servicios | K132: =Base!R401 -> Mayormente comprometido | L132: =Base!V401 -> 2578971 | M132: =Base!W401 -> 22487 | N132: =Base!X401 -> 500000 | O132: =Base!Y401 -> 500000 | P132: =IF(Base!Z401="","",Base!Z401) | Q132: =Base!S401 -> Difícil | R132: =Base!N401 -> 3150027 | S132: =Base!T401 -> 3159242.7
A133: =SUBTOTAL(103,$B$6:B133) -> 111 | B133: 314 | C133: =Base!H402 -> 2611144: ADQUISICION DE ANALIZADOR DE GASES Y ELECTROLITOS, ASPIRADOR DE SECRECIONES, BOMBA DE INFUSION Y COCHE DE PARO EQUIPADO; ADEMÁS DE OTROS ACTIVOS EN EL(LA) CARLOS MONJE MEDRANO DISTRITO DE JULIACA, PROVINCIA SAN ROMAN, DEPARTAMENTO PUNO | D133: =Base!I402 -> 4219373 | E133: =Base!J402 -> 4183621 | F133: =D133-E133 -> 35751.97 | G133: =Base!L402 -> 3829328.1 | H133: =D133-G133 -> 390044.92 | I133: =IF(D133=0,0,G133/D133) -> 0.90755856 | J133: =Base!U402 -> Equipamiento / Contrata | K133: =Base!R402 -> Ejecutado | L133: =Base!V402 -> 3305500 | M133: =Base!W402 -> 177809 | N133: =Base!X402 -> 150483 | O133: =Base!Y402 -> 0 | P133: =IF(Base!Z402="","",Base!Z402) | Q133: =Base!S402 -> No usar | R133: =Base!N402 -> 326806.53 | S133: =Base!T402 -> 0
... A148: =SUBTOTAL(103,$B$6:B148) -> 126 | B148: 524 | C148: =Base!H417 -> 2733644: ADQUISICION DE PATRULLEROS Y PATRULLEROS; EN EL(LA) FRENTE POLICIAL PUNO - COMISARIAS EN LAS 13 PROVINCIAS DE LA REGION PUNO, DISTRITO DE PUNO, PROVINCIA PUNO, DEPARTAMENTO PUNO | D148: =Base!I417 -> 25610 | E148: =Base!J417 -> 0 | F148: =D148-E148 -> 25610 | G148: =Base!L417 -> 0 | H148: =D148-G148 -> 25610 | I148: =IF(D148=0,0,G148/D148) -> 0 | J148: =Base!U417 -> Expediente técnico | K148: =Base!R417 -> Sin certificar | L148: =Base!V417 -> No registrado en cartera | M148: =Base!W417 -> No registrado en cartera | N148: =Base!X417 -> No registrado en cartera | O148: =Base!Y417 -> No registrado en cartera | P148: =IF(Base!Z417="","",Base!Z417) | Q148: =Base!S417 -> Disponible | R148: =Base!N417 -> 0 | S148: =Base!T417 -> 25610
A149: 22. EDUCACION | D149: =SUM(D150:D161) -> 9798393 | E149: =SUM(E150:E161) -> 7621399.4 | F149: =D149-E149 -> 2176993.6 | G149: =SUM(G150:G161) -> 606651.92 | H149: =D149-G149 -> 9191741.1 | I149: =IF(D149=0,0,G149/D149) -> 0.06191341 | R149: =SUM(R150:R161) -> 6997418.1 | S149: =SUM(S150:S161) -> 9165684.3
A150: =SUBTOTAL(103,$B$6:B150) -> 127 | B150: 512 | C150: =Base!H418 -> 2721991: RENOVACION DE AULA DE EDUCACION PRIMARIA, AMBIENTE ADMINISTRATIVO, SERVICIOS HIGIENICOS Y/O VESTIDORES Y AMBIENTE DE USOS MULTIPLES; ADEMAS DE OTROS ACTIVOS EN CUATRO II.EE. PRIMARIA A NIVEL DISTRITAL (PUNO - SANDIA - SAN PEDRO DE PUTINA PUNCO) | D150: =Base!I418 -> 3254770 | E150: =Base!J418 -> 2925559.5 | F150: =D150-E150 -> 329210.45 | G150: =Base!L418 -> 0 | H150: =D150-G150 -> 3254770 | I150: =IF(D150=0,0,G150/D150) -> 0 | J150: =Base!U418 -> Contrata / Expediente técnico / Personal/bienes/servicios | K150: =Base!R418 -> Solo certificado | L150: =Base!V418 -> No registrado en cartera | M150: =Base!W418 -> No registrado en cartera | N150: =Base!X418 -> No registrado en cartera | O150: =Base!Y418 -> No registrado en cartera | P150: =IF(Base!Z418="","",Base!Z418) | Q150: =Base!S418 -> Posible | R150: =Base!N418 -> 2925559.5 | S150: =Base!T418 -> 3254770
A151: =SUBTOTAL(103,$B$6:B151) -> 128 | B151: 513 | C151: =Base!H419 -> 2721892: CONSTRUCCION DE AULA DE EDUCACION SECUNDARIA, AMBIENTE ADMINISTRATIVO Y SERVICIOS HIGIENICOS Y/O VESTIDORES; ADQUISICION DE MOBILIARIO DE AULA; EN EL(LA) IE PUERTO DE EDEN DISTRITO DE SAN PEDRO DE PUTINA PUNCO, PROVINCIA SANDIA, DEPARTAMENTO PUNO | D151: =Base!I419 -> 1007572 | E151: =Base!J419 -> 838299.38 | F151: =D151-E151 -> 169272.62 | G151: =Base!L419 -> 0 | H151: =D151-G151 -> 1007572 | I151: =IF(D151=0,0,G151/D151) -> 0 | J151: =Base!U419 -> Contrata / Expediente técnico / Personal/bienes/servicios | K151: =Base!R419 -> Solo certificado | L151: =Base!V419 -> No registrado en cartera | M151: =Base!W419 -> No registrado en cartera | N151: =Base!X419 -> No registrado en cartera | O151: =Base!Y419 -> No registrado en cartera | P151: =IF(Base!Z419="","",Base!Z419) | Q151: =Base!S419 -> Posible | R151: =Base!N419 -> 838299.38 | S151: =Base!T419 -> 1007572
A152: =SUBTOTAL(103,$B$6:B152) -> 129 | B152: 515 | C152: =Base!H420 -> 2719529: RENOVACION DE AULA DE EDUCACION PRIMARIA, SERVICIOS HIGIENICOS Y/O VESTIDORES Y AMBIENTE DE USOS MULTIPLES; ADQUISICION DE MOBILIARIO DE AULA; EN TRES II.EE. PRIMARIA A NIVEL DISTRITAL (PUNO - SANDIA - ALTO INAMBARI) | D152: =Base!I420 -> 1688098 | E152: =Base!J420 -> 1486603.2 | F152: =D152-E152 -> 201494.77 | G152: =Base!L420 -> 0 | H152: =D152-G152 -> 1688098 | I152: =IF(D152=0,0,G152/D152) -> 0 | J152: =Base!U420 -> Contrata / Expediente técnico / Personal/bienes/servicios | K152: =Base!R420 -> Solo certificado | L152: =Base!V420 -> No registrado en cartera | M152: =Base!W420 -> No registrado en cartera | N152: =Base!X420 -> No registrado en cartera | O152: =Base!Y420 -> No registrado en cartera | P152: =IF(Base!Z420="","",Base!Z420) | Q152: =Base!S420 -> Posible | R152: =Base!N420 -> 1486603.2 | S152: =Base!T420 -> 1688098
A153: =SUBTOTAL(103,$B$6:B153) -> 130 | B153: 509 | C153: =Base!H421 -> 2723359: CONSTRUCCION DE AULA DE EDUCACION SECUNDARIA; ADQUISICION DE MOBILIARIO DE AULA; EN EL(LA) IE SECUNDARIA SANTA ROSA DISTRITO DE ALTO INAMBARI, PROVINCIA SANDIA, DEPARTAMENTO PUNO | D153: =Base!I421 -> 680748 | E153: =Base!J421 -> 538302.92 | F153: =D153-E153 -> 142445.08 | G153: =Base!L421 -> 0 | H153: =D153-G153 -> 680748 | I153: =IF(D153=0,0,G153/D153) -> 0 | J153: =Base!U421 -> Contrata / Expediente técnico / Personal/bienes/servicios | K153: =Base!R421 -> Solo certificado | L153: =Base!V421 -> No registrado en cartera | M153: =Base!W421 -> No registrado en cartera | N153: =Base!X421 -> No registrado en cartera | O153: =Base!Y421 -> No registrado en cartera | P153: =IF(Base!Z421="","",Base!Z421) | Q153: =Base!S421 -> Posible | R153: =Base!N421 -> 538302.92 | S153: =Base!T421 -> 680748
A154: =SUBTOTAL(103,$B$6:B154) -> 131 | B154: 510 | C154: =Base!H422 -> 2721888: CONSTRUCCION DE AULA DE EDUCACION SECUNDARIA; ADQUISICION DE MOBILIARIO DE AULA; EN EL(LA) IE I.E. SECUNDARIA JOSE MARIA ARGUEDAS EN LA LOCALIDAD CCAPUNA, DISTRITO DE SANDIA, PROVINCIA SANDIA, DEPARTAMENTO PUNO | D154: =Base!I422 -> 670100 | E154: =Base!J422 -> 532791.97 | F154: =D154-E154 -> 137308.03 | G154: =Base!L422 -> 0 | H154: =D154-G154 -> 670100 | I154: =IF(D154=0,0,G154/D154) -> 0 | J154: =Base!U422 -> Contrata / Expediente técnico / Personal/bienes/servicios | K154: =Base!R422 -> Solo certificado | L154: =Base!V422 -> No registrado en cartera | M154: =Base!W422 -> No registrado en cartera | N154: =Base!X422 -> No registrado en cartera | O154: =Base!Y422 -> No registrado en cartera | P154: =IF(Base!Z422="","",Base!Z422) | Q154: =Base!S422 -> Posible | R154: =Base!N422 -> 532791.97 | S154: =Base!T422 -> 670100
A155: =SUBTOTAL(103,$B$6:B155) -> 132 | B155: 511 | C155: =Base!H423 -> 2721886: CONSTRUCCION DE AULA DE EDUCACION INICIAL; ADQUISICION DE MOBILIARIO DE AULA; EN EL(LA) IE INICIAL N° 1048 DE HUENCALLA DISTRITO DE SANDIA, PROVINCIA SANDIA, DEPARTAMENTO PUNO | D155: =Base!I423 -> 388514 | E155: =Base!J423 -> 269223.84 | F155: =D155-E155 -> 119290.16 | G155: =Base!L423 -> 0 | H155: =D155-G155 -> 388514 | I155: =IF(D155=0,0,G155/D155) -> 0 | J155: =Base!U423 -> Contrata / Expediente técnico / Personal/bienes/servicios | K155: =Base!R423 -> Solo certificado | L155: =Base!V423 -> No registrado en cartera | M155: =Base!W423 -> No registrado en cartera | N155: =Base!X423 -> No registrado en cartera | O155: =Base!Y423 -> No registrado en cartera | P155: =IF(Base!Z423="","",Base!Z423) | Q155: =Base!S423 -> Posible | R155: =Base!N423 -> 269223.84 | S155: =Base!T423 -> 388514
A156: =SUBTOTAL(103,$B$6:B156) -> 133 | B156: 514 | C156: =Base!H424 -> 2721889: CONSTRUCCION DE AULA DE EDUCACION INICIAL Y AMBIENTE ADMINISTRATIVO; ADQUISICION DE MOBILIARIO DE AULA Y EQUIPAMIENTO DE AULA; EN EL(LA) IE 1027 EN LA LOCALIDAD ISILLUMA, DISTRITO DE ALTO INAMBARI, PROVINCIA SANDIA, DEPARTAMENTO PUNO | D156: =Base!I424 -> 542416 | E156: =Base!J424 -> 401911.51 | F156: =D156-E156 -> 140504.49 | G156: =Base!L424 -> 0 | H156: =D156-G156 -> 542416 | I156: =IF(D156=0,0,G156/D156) -> 0 | J156: =Base!U424 -> Contrata / Expediente técnico / Personal/bienes/servicios | K156: =Base!R424 -> Solo certificado | L156: =Base!V424 -> No registrado en cartera | M156: =Base!W424 -> No registrado en cartera | N156: =Base!X424 -> No registrado en cartera | O156: =Base!Y424 -> No registrado en cartera | P156: =IF(Base!Z424="","",Base!Z424) | Q156: =Base!S424 -> Posible | R156: =Base!N424 -> 401911.51 | S156: =Base!T424 -> 542416
A157: =SUBTOTAL(103,$B$6:B157) -> 134 | B157: 516 | C157: =Base!H425 -> 2729834: CONSTRUCCION DE AULA DE EDUCACION PRIMARIA, SERVICIOS HIGIENICOS Y/O VESTIDORES PARA ESTUDIANTES Y AMBIENTE DE GESTION ADMINISTRATIVA Y DIRECCION; ADQUISICION DE MOBILIARIO DE AULA; EN EL(LA) I.E. 72544 DISTRITO DE ALTO INAMBARI, PROVINCIA SANDIA, | D157: =Base!I425 -> 928545 | E157: =Base!J425 -> 0 | F157: =D157-E157 -> 928545 | G157: =Base!L425 -> 0 | H157: =D157-G157 -> 928545 | I157: =IF(D157=0,0,G157/D157) -> 0 | J157: =Base!U425 -> Contrata / Expediente técnico | K157: =Base!R425 -> Sin certificar | L157: =Base!V425 -> No registrado en cartera | M157: =Base!W425 -> No registrado en cartera | N157: =Base!X425 -> No registrado en cartera | O157: =Base!Y425 -> No registrado en cartera | P157: =IF(Base!Z425="","",Base!Z425) | Q157: =Base!S425 -> Disponible | R157: =Base!N425 -> 0 | S157: =Base!T425 -> 928545
A158: =SUBTOTAL(103,$B$6:B158) -> 135 | B158: 348 | C158: =Base!H426 -> 2693441: ADQUISICION DE EQUIPO DE AULA DE EDUCACION SECUNDARIA; EN EL(LA) I.E. GLORIOSO SAN CARLOS DISTRITO DE PUNO, PROVINCIA PUNO, DEPARTAMENTO PUNO | D158: =Base!I426 -> 70059 | E158: =Base!J426 -> 70057.9 | F158: =D158-E158 -> 1.1 | G158: =Base!L426 -> 70029.94 | H158: =D158-G158 -> 29.06 | I158: =IF(D158=0,0,G158/D158) -> 0.99958521 | J158: =Base!U426 -> Otro (SOFTWARES) / Contrata / Personal/bienes/servicios | K158: =Base!R426 -> Ejecutado | L158: =Base!V426 -> 105988 | M158: =Base!W426 -> 0 | N158: =Base!X426 -> 35929 | O158: =Base!Y426 -> 0 | P158: =IF(Base!Z426="","",Base!Z426) | Q158: =Base!S426 -> No usar | R158: =Base!N426 -> 0 | S158: =Base!T426 -> 0
A159: =SUBTOTAL(103,$B$6:B159) -> 136 | B159: 349 | C159: =Base!H427 -> 2692840: ADQUISICION DE EQUIPO DE AULA DE EDUCACION PRIMARIA; EN EL(LA) I.E. GLORIOSO SAN CARLOS DISTRITO DE PUNO, PROVINCIA PUNO, DEPARTAMENTO PUNO | D159: =Base!I427 -> 100785 | E159: =Base!J427 -> 100589.42 | F159: =D159-E159 -> 195.58 | G159: =Base!L427 -> 88974.89 | H159: =D159-G159 -> 11810.11 | I159: =IF(D159=0,0,G159/D159) -> 0.88281877 | J159: =Base!U427 -> Contrata / Otro (SOFTWARES) / Personal/bienes/servicios | K159: =Base!R427 -> Mayormente comprometido | L159: =Base!V427 -> 155899 | M159: =Base!W427 -> 0 | N159: =Base!X427 -> 55114 | O159: =Base!Y427 -> 0 | P159: =IF(Base!Z427="","",Base!Z427) | Q159: =Base!S427 -> Difícil | R159: =Base!N427 -> 4725.75 | S159: =Base!T427 -> 4921.33
A160: =SUBTOTAL(103,$B$6:B160) -> 137 | B160: 461 | C160: =Base!H428 -> 2699544: ADQUISICION DE EQUIPAMIENTO DE AULA; EN SIETE II.EE. INICIAL DISTRITO DE SAN JUAN DE SALINAS, PROVINCIA AZANGARO, DEPARTAMENTO PUNO | D160: =Base!I428 -> 195079 | E160: =Base!J428 -> 186354 | F160: =D160-E160 -> 8725 | G160: =Base!L428 -> 176804.43 | H160: =D160-G160 -> 18274.57 | I160: =IF(D160=0,0,G160/D160) -> 0.90632221 | J160: =Base!U428 -> Administración directa / Equipamiento / Contrata / Personal/bienes/servicios | K160: =Base!R428 -> Ejecutado | L160: =Base!V428 -> 195079 | M160: =Base!W428 -> 23547 | N160: =Base!X428 -> 1 | O160: =Base!Y428 -> 0 | P160: =IF(Base!Z428="","",Base!Z428) | Q160: =Base!S428 -> No usar | R160: =Base!N428 -> 0 | S160: =Base!T428 -> 0
A161: =SUBTOTAL(103,$B$6:B161) -> 138 | B161: 345 | C161: =Base!H443 -> 2699546: ADQUISICION DE EQUIPAMIENTO DE AULA DE INNOVACION PEDAGOGICA; EN OCHO II.EE. PRIMARIA DISTRITO DE SAN JUAN DE SALINAS, PROVINCIA AZANGARO, DEPARTAMENTO PUNO | D161: =Base!I443 -> 271707 | E161: =Base!J443 -> 271705.69 | F161: =D161-E161 -> 1.31 | G161: =Base!L443 -> 270842.66 | H161: =D161-G161 -> 864.34 | I161: =IF(D161=0,0,G161/D161) -> 0.99681885 | J161: =Base!U443 -> Equipamiento / Administración directa / Contrata / Personal/bienes/servicios | K161: =Base!R443 -> Ejecutado | L161: =Base!V443 -> 267733 | M161: =Base!W443 -> 20886 | N161: =Base!X443 -> 0 | O161: =Base!Y443 -> 0 | P161: =IF(Base!Z443="","",Base!Z443) | Q161: =Base!S443 -> No usar | R161: =Base!N443 -> 0 | S161: =Base!T443 -> 0
A162: 05. ORDEN PUBLICO Y SEGURIDAD | D162: =SUM(D163:D164) -> 11936253 | E162: =SUM(E163:E164) -> 10980494 | F162: =D162-E162 -> 955759.22 | G162: =SUM(G163:G164) -> 5861139.6 | H162: =D162-G162 -> 6075113.4 | I162: =IF(D162=0,0,G162/D162) -> 0.49103681 | R162: =SUM(R163:R164) -> 5047834.4 | S162: =SUM(S163:S164) -> 6003593.6
A163: =SUBTOTAL(103,$B$6:B163) -> 139 | B163: 3 | C163: =Base!H429 -> 2683535: MEJORAMIENTO DEL SERVICIO DE SEGURIDAD CIUDADANA LOCAL EN 73 UNIDADES PRODUCTORAS 73 DISTRITOS DE 11 PROVINCIAS DEL DEPARTAMENTO DE PUNO 11 PROVINCIAS DEL DEPARTAMENTO DE PUNO | D163: =Base!I429 -> 6654893 | E163: =Base!J429 -> 6543805.7 | F163: =D163-E163 -> 111087.31 | G163: =Base!L429 -> 5720623 | H163: =D163-G163 -> 934270.03 | I163: =IF(D163=0,0,G163/D163) -> 0.85961156 | J163: =Base!U429 -> Equipamiento / Contrata / Personal/bienes/servicios | K163: =Base!R429 -> Mayormente comprometido | L163: =Base!V429 -> 100000 | M163: =Base!W429 -> 218816 | N163: =Base!X429 -> 309853 | O163: =Base!Y429 -> 0 | P163: =IF(Base!Z429="","",Base!Z429) | Q163: =Base!S429 -> Difícil | R163: =Base!N429 -> 788056 | S163: =Base!T429 -> 899143.31
A164: =SUBTOTAL(103,$B$6:B164) -> 140 | B164: 286 | C164: =Base!H430 -> 2685431: ADQUISICION DE AMBULANCIA URBANA, CAMIONETA, CAMIÓN PLATAFORMA Y CAMION CISTERNA; ADEMÁS DE OTROS ACTIVOS EN CINCO COMPAÑÍA DE BOMBEROS A NIVEL DEPARTAMENTAL (PUNO) | D164: =Base!I430 -> 5281360 | E164: =Base!J430 -> 4436688.1 | F164: =D164-E164 -> 844671.91 | G164: =Base!L430 -> 140516.63 | H164: =D164-G164 -> 5140843.4 | I164: =IF(D164=0,0,G164/D164) -> 0.026606145 | J164: =Base!U430 -> Equipamiento / Contrata / Personal/bienes/servicios | K164: =Base!R430 -> Parcialmente comprometido | L164: =Base!V430 -> 5358341 | M164: =Base!W430 -> 6902686 | N164: =Base!X430 -> 800000 | O164: =Base!Y430 -> 800000 | P164: =IF(Base!Z430="","",Base!Z430) | Q164: =Base!S430 -> Parcial | R164: =Base!N430 -> 4259778.4 | S164: =Base!T430 -> 5104450.3
A165: 23. PROTECCION SOCIAL | D165: =SUM(D166:D166) -> 0 | E165: =SUM(E166:E166) -> 0 | F165: =D165-E165 -> 0 | G165: =SUM(G166:G166) -> 0 | H165: =D165-G165 -> 0 | I165: =IF(D165=0,0,G165/D165) -> 0 | R165: =SUM(R166:R166) -> 0 | S165: =SUM(S166:S166) -> 0
A166: =SUBTOTAL(103,$B$6:B166) -> 141 | B166: 266 | C166: =Base!H431 -> 2608728: REPARACION DE AMBIENTE DE RESIDENCIA; ADQUISICION DE EQUIPAMIENTO DE AMBIENTES DE BIENESTAR Y SERVICIOS GENERALES Y MOBILIARIO DE AMBIENTES DE BIENESTAR Y SERVICIOS GENERALES; EN EL(LA) ALDEA INFANTIL NIÑO SAN SALVADOR DEL DISTRITO DE CAPACHICA, PROVINCIA PUNO, DEPARTAMENTO PUNO | D166: =Base!I431 -> 0 | E166: =Base!J431 -> 0 | F166: =D166-E166 -> 0 | G166: =Base!L431 -> 0 | H166: =D166-G166 -> 0 | I166: =IF(D166=0,0,G166/D166) -> 0 | J166: =Base!U431 -> Contrata | K166: =Base!R431 -> Sin PIM | L166: =Base!V431 -> 200000 | M166: =Base!W431 -> 0 | N166: =Base!X431 -> 0 | O166: =Base!Y431 -> 0 | P166: =IF(Base!Z431="","",Base!Z431) | Q166: =Base!S431 -> Sin PIM | R166: =Base!N431 -> 0 | S166: =Base!T431 -> 0
...

Sheet Sin clasificar
C1: ANEXO N° 03
B2: COMPORTAMIENTO DE EJECUCIÓN DE PROYECTOS DE INVERSION PUBLICA DEL AÑO FISCAL 2026 · PROYECTOS SIN GERENCIA ASIGNADA · AL 07/10/2026
A4: N° | B4: META | C4: PROYECTO | D4: PIM 2026 (A) | E4: CERTIFICACIÓN (B) | F4: SALDO (A-B) | G4: DEVENGADO ( C ) | H4: SALDO (A-C) | I4: DEVEN % | J4: MODALIDAD DE EJECUCIÓN | K4: ESTADO SITUACIONAL PROYECTO | L4: Monto Año 2026 (S/) | M4: Monto Año 2027 (S/) | N4: Monto Año 2028 (S/) | O4: Monto Año 2029 (S/) | P4: BASE LEGAL | Q4: DISPONIBILIDAD | R4: CERTIFICADO NO COMPROMETIDO | S4: DISPONIBLE (PIM − COMPROM.)
A5: SIN CLASIFICAR (pendiente de asignar gerencia) | D5: =D6+D8 -> 120166 | E5: =E6+E8 -> 19362 | F5: =D5-E5 -> 100804 | G5: =G6+G8 -> 18148.25 | H5: =D5-G5 -> 102017.75 | I5: =IF(D5=0,0,G5/D5) -> 0.1510265 | R5: =R6+R8 -> 0 | S5: =S6+S8 -> 100804
A6: 20. SALUD | D6: =SUM(D7:D7) -> 100000 | E6: =SUM(E7:E7) -> 0 | F6: =D6-E6 -> 100000 | G6: =SUM(G7:G7) -> 0 | H6: =D6-G6 -> 100000 | I6: =IF(D6=0,0,G6/D6) -> 0 | R6: =SUM(R7:R7) -> 0 | S6: =SUM(S7:S7) -> 100000
A7: =SUBTOTAL(103,$B$6:B7) -> 1 | B7: 533 | C7: =Base!H445 -> 2681141: MEJORAMIENTO DEL SERVICIO DE ATENCIÓN DE SALUD BÁSICOS EN HUACULLANI DISTRITO DE HUACULLANI DE LA PROVINCIA DE CHUCUITO DEL DEPARTAMENTO DE PUNO | D7: =Base!I445 -> 100000 | E7: =Base!J445 -> 0 | F7: =D7-E7 -> 100000 | G7: =Base!L445 -> 0 | H7: =D7-G7 -> 100000 | I7: =IF(D7=0,0,G7/D7) -> 0 | J7: =Base!U445 -> Expediente técnico | K7: =Base!R445 -> Sin certificar | L7: =Base!V445 -> 100000 | M7: =Base!W445 -> 0 | N7: =Base!X445 -> 3681052 | O7: =Base!Y445 -> 4156140 | P7: =IF(Base!Z445="","",Base!Z445) | Q7: =Base!S445 -> Disponible | R7: =Base!N445 -> 0 | S7: =Base!T445 -> 100000
A8: 22. EDUCACION | D8: =SUM(D9:D9) -> 20166 | E8: =SUM(E9:E9) -> 19362 | F8: =D8-E8 -> 804 | G8: =SUM(G9:G9) -> 18148.25 | H8: =D8-G8 -> 2017.75 | I8: =IF(D8=0,0,G8/D8) -> 0.89994297 | R8: =SUM(R9:R9) -> 0 | S8: =SUM(S9:S9) -> 804
A9: =SUBTOTAL(103,$B$6:B9) -> 2 | B9: 499 | C9: =Base!H446 -> 2231037: MEJORAMIENTO DE LOS SERVICIOS EDUCATIVOS EN LA I.E.I. N 596 MUNAYPATA DEL CENTRO POBLADO DE MUNAYPATA, DISTRITO DE OLLACHEA PROVINCIA DE CARABAYA PUNO | D9: =Base!I446 -> 20166 | E9: =Base!J446 -> 19362 | F9: =D9-E9 -> 804 | G9: =Base!L446 -> 18148.25 | H9: =D9-G9 -> 2017.75 | I9: =IF(D9=0,0,G9/D9) -> 0.89994297 | J9: =Base!U446 -> Contrata / Personal/bienes/servicios | K9: =Base!R446 -> Mayormente comprometido | L9: =Base!V446 -> 20166 | M9: =Base!W446 -> 0 | N9: =Base!X446 -> 0 | O9: =Base!Y446 -> 0 | P9: =IF(Base!Z446="","",Base!Z446) | Q9: =Base!S446 -> Difícil | R9: =Base!N446 -> 0 | S9: =Base!T446 -> 804
A11: TOTAL PROYECTOS SIN GERENCIA ASIGNADA | D11: =D5 -> 120166 | E11: =E5 -> 19362 | F11: =D11-E11 -> 100804 | G11: =G5 -> 18148.25 | H11: =D11-G11 -> 102017.75 | I11: =IF(D11=0,0,G11/D11) -> 0.1510265 | R11: =R5 -> 0 | S11: =S5 -> 100804

Sheet UE 002
C1: ANEXO N° 04
B2: COMPORTAMIENTO DE EJECUCIÓN DE PROYECTOS DE INVERSION PUBLICA DEL AÑO FISCAL 2026 · UE 002 · AL 07/10/2026
A4: N° | B4: META | C4: PROYECTO | D4: PIM 2026 (A) | E4: CERTIFICACIÓN (B) | F4: SALDO (A-B) | G4: DEVENGADO ( C ) | H4: SALDO (A-C) | I4: DEVEN % | J4: MODALIDAD DE EJECUCIÓN | K4: ESTADO SITUACIONAL PROYECTO | L4: Monto Año 2026 (S/) | M4: Monto Año 2027 (S/) | N4: Monto Año 2028 (S/) | O4: Monto Año 2029 (S/) | P4: BASE LEGAL | Q4: DISPONIBILIDAD | R4: CERTIFICADO NO COMPROMETIDO | S4: DISPONIBLE (PIM − COMPROM.)
A5: 002. REGION PUNO-PESQUERIA | D5: =D6+D9 -> 2582404 | E5: =E6+E9 -> 1853925.8 | F5: =D5-E5 -> 728478.18 | G5: =G6+G9 -> 1562395.5 | H5: =D5-G5 -> 1020008.5 | I5: =IF(D5=0,0,G5/D5) -> 0.60501592 | R5: =R6+R9 -> 24500 | S5: =S6+S9 -> 752978.18
A6: 11. PESCA | D6: =SUM(D7:D8) -> 2462454 | E6: =SUM(E7:E8) -> 1739634.6 | F6: =D6-E6 -> 722819.4 | G6: =SUM(G7:G8) -> 1492104.3 | H6: =D6-G6 -> 970349.7 | I6: =IF(D6=0,0,G6/D6) -> 0.605942 | R6: =SUM(R7:R8) -> 24500 | S6: =SUM(S7:S8) -> 747319.4
A7: =SUBTOTAL(103,$B$6:B7) -> 1 | B7: 5 | C7: =Base!H447 -> 2336682: RECUPERACION DE LA BIOMASA DEL CARACHI GRIS Y AMARILLO EN ZONAS DE DESOVE DE LA CUENCA DEL LAGO TITICACA DE LA REGION PUNO | D7: =Base!I447 -> 2417454 | E7: =Base!J447 -> 1739634.6 | F7: =D7-E7 -> 677819.4 | G7: =Base!L447 -> 1492104.3 | H7: =D7-G7 -> 925349.7 | I7: =IF(D7=0,0,G7/D7) -> 0.61722138 | J7: =Base!U447 -> Contrata / Personal/bienes/servicios / Equipamiento | K7: =Base!R447 -> Mayormente comprometido | L7: =Base!V447 -> 1050000 | M7: =Base!W447 -> 2062045 | N7: =Base!X447 -> 1715201 | O7: =Base!Y447 -> 0 | P7: =IF(Base!Z447="","",Base!Z447) | Q7: =Base!S447 -> Difícil | R7: =Base!N447 -> 24500 | S7: =Base!T447 -> 702319.4
A8: =SUBTOTAL(103,$B$6:B8) -> 2 | B8: 24 | C8: =Base!H449 -> 2714101: (EXPEDIENTE TECNICO - nombre no disponible en fuentes) | D8: =Base!I449 -> 45000 | E8: =Base!J449 -> 0 | F8: =D8-E8 -> 45000 | G8: =Base!L449 -> 0 | H8: =D8-G8 -> 45000 | I8: =IF(D8=0,0,G8/D8) -> 0 | J8: =Base!U449 -> Expediente técnico | K8: =Base!R449 -> Sin certificar | L8: =Base!V449 -> No registrado en cartera | M8: =Base!W449 -> No registrado en cartera | N8: =Base!X449 -> No registrado en cartera | O8: =Base!Y449 -> No registrado en cartera | P8: =IF(Base!Z449="","",Base!Z449) | Q8: =Base!S449 -> Disponible | R8: =Base!N449 -> 0 | S8: =Base!T449 -> 45000
A9: 14. INDUSTRIA | D9: =SUM(D10:D11) -> 119950 | E9: =SUM(E10:E11) -> 114291.22 | F9: =D9-E9 -> 5658.78 | G9: =SUM(G10:G11) -> 70291.22 | H9: =D9-G9 -> 49658.78 | I9: =IF(D9=0,0,G9/D9) -> 0.58600434 | R9: =SUM(R10:R11) -> 0 | S9: =SUM(S10:S11) -> 5658.78
A10: =SUBTOTAL(103,$B$6:B10) -> 3 | B10: 15 | C10: =Base!H448 -> 2230619: MEJORAMIENTO DE LA PRODUCCIÓN Y PRODUCTIVIDAD DE LAS MYPE DE LAS PRINCIPALES LINEAS DE PRODUCCION EN LAS PROVINCIAS DE PUNO, SAN ROMÁN Y EL COLLAO DE LA REGIÓN PUNO | D10: =Base!I448 -> 119950 | E10: =Base!J448 -> 114291.22 | F10: =D10-E10 -> 5658.78 | G10: =Base!L448 -> 70291.22 | H10: =D10-G10 -> 49658.78 | I10: =IF(D10=0,0,G10/D10) -> 0.58600434 | J10: =Base!U448 -> Contrata | K10: =Base!R448 -> Mayormente comprometido | L10: =Base!V448 -> 287404 | M10: =Base!W448 -> 77681 | N10: =Base!X448 -> 0 | O10: =Base!Y448 -> 0 | P10: =IF(Base!Z448="","",Base!Z448) | Q10: =Base!S448 -> Difícil | R10: =Base!N448 -> 0 | S10: =Base!T448 -> 5658.78
A11: =SUBTOTAL(103,$B$6:B11) -> 4 | B11: 14 | C11: =Base!H450 -> 2230619: MEJORAMIENTO DE LA PRODUCCIÓN Y PRODUCTIVIDAD DE LAS MYPE DE LAS PRINCIPALES LINEAS DE PRODUCCION EN LAS PROVINCIAS DE PUNO, SAN ROMÁN Y EL COLLAO DE LA REGIÓN PUNO | D11: =Base!I450 -> 0 | E11: =Base!J450 -> 0 | F11: =D11-E11 -> 0 | G11: =Base!L450 -> 0 | H11: =D11-G11 -> 0 | I11: =IF(D11=0,0,G11/D11) -> 0 | J11: =Base!U450 -> Contrata | K11: =Base!R450 -> Sin PIM | L11: =Base!V450 -> 287404 | M11: =Base!W450 -> 77681 | N11: =Base!X450 -> 0 | O11: =Base!Y450 -> 0 | P11: =IF(Base!Z450="","",Base!Z450) | Q11: =Base!S450 -> Sin PIM | R11: =Base!N450 -> 0 | S11: =Base!T450 -> 0
A13: TOTAL UE 002 | D13: =D5 -> 2582404 | E13: =E5 -> 1853925.8 | F13: =D13-E13 -> 728478.18 | G13: =G5 -> 1562395.5 | H13: =D13-G13 -> 1020008.5 | I13: =IF(D13=0,0,G13/D13) -> 0.60501592 | R13: =R5 -> 24500 | S13: =S5 -> 752978.18

Sheet UE 003
C1: ANEXO N° 05
B2: COMPORTAMIENTO DE EJECUCIÓN DE PROYECTOS DE INVERSION PUBLICA DEL AÑO FISCAL 2026 · UE 003 · AL 07/10/2026
A4: N° | B4: META | C4: PROYECTO | D4: PIM 2026 (A) | E4: CERTIFICACIÓN (B) | F4: SALDO (A-B) | G4: DEVENGADO ( C ) | H4: SALDO (A-C) | I4: DEVEN % | J4: MODALIDAD DE EJECUCIÓN | K4: ESTADO SITUACIONAL PROYECTO | L4: Monto Año 2026 (S/) | M4: Monto Año 2027 (S/) | N4: Monto Año 2028 (S/) | O4: Monto Año 2029 (S/) | P4: BASE LEGAL | Q4: DISPONIBILIDAD | R4: CERTIFICADO NO COMPROMETIDO | S4: DISPONIBLE (PIM − COMPROM.)
A5: 003. REGION PUNO-PROGRAMA REGIONAL DE RIEGO Y DRENAJE | D5: =D6+D47 -> 45637342 | E5: =E6+E47 -> 42133907 | F5: =D5-E5 -> 3503435.2 | G5: =G6+G47 -> 33578062 | H5: =D5-G5 -> 12059280 | I5: =IF(D5=0,0,G5/D5) -> 0.73575849 | R5: =R6+R47 -> 2946314.2 | S5: =S6+S47 -> 6009941.8
A6: 10. AGROPECUARIA | D6: =SUM(D7:D46) -> 45637342 | E6: =SUM(E7:E46) -> 42133907 | F6: =D6-E6 -> 3503435.2 | G6: =SUM(G7:G46) -> 33578062 | H6: =D6-G6 -> 12059280 | I6: =IF(D6=0,0,G6/D6) -> 0.73575849 | R6: =SUM(R7:R46) -> 2946314.2 | S6: =SUM(S7:S46) -> 6009941.8
A7: =SUBTOTAL(103,$B$6:B7) -> 1 | B7: 3 | C7: =Base!H451 -> 2454391: AMPLIACION DEL SERVICIO DE AGUA PARA RIEGO MEDIANTE LA CONSTRUCCIÓN DE LA REPRESA SAPANCCOTA DEL DISTRITO DE PUCARA - PROVINCIA DE LAMPA - DEPARTAMENTO DE PUNO | D7: =Base!I451 -> 7885949 | E7: =Base!J451 -> 7535969.9 | F7: =D7-E7 -> 349979.13 | G7: =Base!L451 -> 6423232.3 | H7: =D7-G7 -> 1462716.7 | I7: =IF(D7=0,0,G7/D7) -> 0.81451608 | J7: =Base!U451 -> Administración directa / Contrata / Personal/bienes/servicios / Equipamiento | K7: =Base!R451 -> Mayormente comprometido | L7: =Base!V451 -> 2780000 | M7: =Base!W451 -> 108325 | N7: =Base!X451 -> 0 | O7: =Base!Y451 -> 0 | P7: =IF(Base!Z451="","",Base!Z451) | Q7: =Base!S451 -> Difícil | R7: =Base!N451 -> 156681.73 | S7: =Base!T451 -> 506660.86
A8: =SUBTOTAL(103,$B$6:B8) -> 2 | B8: 12 | C8: =Base!H452 -> 2566500: MEJORAMIENTO Y AMPLIACION DEL SISTEMA DE RIEGO CHAJANA DEL DISTRITO DE ACORA - PROVINCIA DE PUNO - DEPARTAMENTO DE PUNO | D8: =Base!I452 -> 7723291 | E8: =Base!J452 -> 7122044 | F8: =D8-E8 -> 601246.95 | G8: =Base!L452 -> 5496208.6 | H8: =D8-G8 -> 2227082.4 | I8: =IF(D8=0,0,G8/D8) -> 0.71164075 | J8: =Base!U452 -> Administración directa / Contrata / Personal/bienes/servicios | K8: =Base!R452 -> Mayormente comprometido | L8: =Base!V452 -> 4665000 | M8: =Base!W452 -> 62456 | N8: =Base!X452 -> 0 | O8: =Base!Y452 -> 0 | P8: =IF(Base!Z452="","",Base!Z452) | Q8: =Base!S452 -> Difícil | R8: =Base!N452 -> 114617.25 | S8: =Base!T452 -> 715864.2
A9: =SUBTOTAL(103,$B$6:B9) -> 3 | B9: 6 | C9: =Base!H453 -> 2477014: CREACION DEL SERVICIO DE AGUA PARA RIEGO TECNIFICADO EN LAS COMUNIDADES DE IPARO, ARICATO, QUENEQUE, MORORIA, CCAPUNA Y APABUCO DEL DISTRITO DE SANDIA - PROVINCIA DE SANDIA - DEPARTAMENTO DE PUNO | D9: =Base!I453 -> 5062649 | E9: =Base!J453 -> 4785961.1 | F9: =D9-E9 -> 276687.87 | G9: =Base!L453 -> 4676286.7 | H9: =D9-G9 -> 386362.29 | I9: =IF(D9=0,0,G9/D9) -> 0.92368377 | J9: =Base!U453 -> Administración directa / Contrata / Equipamiento / Personal/bienes/servicios | K9: =Base!R453 -> Ejecutado | L9: =Base!V453 -> 1750000 | M9: =Base!W453 -> 0 | N9: =Base!X453 -> 0 | O9: =Base!Y453 -> 0 | P9: =IF(Base!Z453="","",Base!Z453) | Q9: =Base!S453 -> No usar | R9: =Base!N453 -> 2177.02 | S9: =Base!T453 -> 0
A10: =SUBTOTAL(103,$B$6:B10) -> 4 | B10: 8 | C10: =Base!H454 -> 2540745: MEJORAMIENTO Y AMPLIACION DEL SERVICIO DE AGUA PARA LOS SISTEMAS DE RIEGO HUALLATIRI, HUAYRAPATA Y HUARANCA GRANDE DEL DISTRITO DE HUAYRAPATA - PROVINCIA DE MOHO - DEPARTAMENTO DE PUNO | D10: =Base!I454 -> 4860569 | E10: =Base!J454 -> 4504302.8 | F10: =D10-E10 -> 356266.25 | G10: =Base!L454 -> 4364263.5 | H10: =D10-G10 -> 496305.55 | I10: =IF(D10=0,0,G10/D10) -> 0.89789147 | J10: =Base!U454 -> Administración directa / Contrata / Personal/bienes/servicios | K10: =Base!R454 -> Mayormente comprometido | L10: =Base!V454 -> 1580000 | M10: =Base!W454 -> 285490 | N10: =Base!X454 -> 0 | O10: =Base!Y454 -> 0 | P10: =IF(Base!Z454="","",Base!Z454) | Q10: =Base!S454 -> Difícil | R10: =Base!N454 -> 18168.46 | S10: =Base!T454 -> 374434.71
A11: =SUBTOTAL(103,$B$6:B11) -> 5 | B11: 33 | C11: =Base!H455 -> 2651742: MEJORAMIENTO Y AMPLIACION DEL SERVICIO DE PROVISIÓN DE AGUA PARA RIEGO EN LA MICROCUENCA DEL RÍO CONDORIRI DISTRITO DE AZANGARO DE LA PROVINCIA DE AZANGARO DEL DEPARTAMENTO DE PUNO | D11: =Base!I455 -> 4471000 | E11: =Base!J455 -> 4168004.5 | F11: =D11-E11 -> 302995.55 | G11: =Base!L455 -> 1249313.7 | H11: =D11-G11 -> 3221686.3 | I11: =IF(D11=0,0,G11/D11) -> 0.27942601 | J11: =Base!U455 -> Administración directa / Contrata / Personal/bienes/servicios / Equipamiento | K11: =Base!R455 -> Mayormente comprometido | L11: =Base!V455 -> 5730000 | M11: =Base!W455 -> 7379001 | N11: =Base!X455 -> 1300000 | O11: =Base!Y455 -> 1500000 | P11: =IF(Base!Z455="","",Base!Z455) | Q11: =Base!S455 -> Difícil | R11: =Base!N455 -> 1185387.5 | S11: =Base!T455 -> 1488383
A12: =SUBTOTAL(103,$B$6:B12) -> 6 | B12: 9 | C12: =Base!H456 -> 2540745: MEJORAMIENTO Y AMPLIACION DEL SERVICIO DE AGUA PARA LOS SISTEMAS DE RIEGO HUALLATIRI, HUAYRAPATA Y HUARANCA GRANDE DEL DISTRITO DE HUAYRAPATA - PROVINCIA DE MOHO - DEPARTAMENTO DE PUNO | D12: =Base!I456 -> 3664997 | E12: =Base!J456 -> 3273868 | F12: =D12-E12 -> 391129.02 | G12: =Base!L456 -> 3096526.7 | H12: =D12-G12 -> 568470.32 | I12: =IF(D12=0,0,G12/D12) -> 0.84489201 | J12: =Base!U456 -> Administración directa / Contrata / Personal/bienes/servicios | K12: =Base!R456 -> Mayormente comprometido | L12: =Base!V456 -> 1580000 | M12: =Base!W456 -> 285490 | N12: =Base!X456 -> 0 | O12: =Base!Y456 -> 0 | P12: =IF(Base!Z456="","",Base!Z456) | Q12: =Base!S456 -> Difícil | R12: =Base!N456 -> 2188.26 | S12: =Base!T456 -> 393317.28
A13: =SUBTOTAL(103,$B$6:B13) -> 7 | B13: 28 | C13: =Base!H457 -> 2651742: MEJORAMIENTO Y AMPLIACION DEL SERVICIO DE PROVISIÓN DE AGUA PARA RIEGO EN LA MICROCUENCA DEL RÍO CONDORIRI DISTRITO DE AZANGARO DE LA PROVINCIA DE AZANGARO DEL DEPARTAMENTO DE PUNO | D13: =Base!I457 -> 1999000 | E13: =Base!J457 -> 1989475.5 | F13: =D13-E13 -> 9524.49 | G13: =Base!L457 -> 706719.22 | H13: =D13-G13 -> 1292280.8 | I13: =IF(D13=0,0,G13/D13) -> 0.35353638 | J13: =Base!U457 -> Administración directa / Contrata / Personal/bienes/servicios | K13: =Base!R457 -> Mayormente comprometido | L13: =Base!V457 -> 5730000 | M13: =Base!W457 -> 7379001 | N13: =Base!X457 -> 1300000 | O13: =Base!Y457 -> 1500000 | P13: =IF(Base!Z457="","",Base!Z457) | Q13: =Base!S457 -> Difícil | R13: =Base!N457 -> 754724.99 | S13: =Base!T457 -> 764249.48
A14: =SUBTOTAL(103,$B$6:B14) -> 8 | B14: 5 | C14: =Base!H458 -> 2470845: MEJORAMIENTO Y AMPLIACION DEL SERVICIO DE AGUA PARA RIEGO TECNIFICADO EN LAS COMUNIDADES DE SAN JUAN DE TAHUACO Y MACHACMARCA DEL DISTRITO DE YUNGUYO - PROVINCIA DE YUNGUYO - DEPARTAMENTO DE PUNO | D14: =Base!I458 -> 1998145 | E14: =Base!J458 -> 1935732.3 | F14: =D14-E14 -> 62412.69 | G14: =Base!L458 -> 1849231.4 | H14: =D14-G14 -> 148913.65 | I14: =IF(D14=0,0,G14/D14) -> 0.92547405 | J14: =Base!U458 -> Administración directa / Contrata / Personal/bienes/servicios / Equipamiento | K14: =Base!R458 -> Ejecutado | L14: =Base!V458 -> 1850000 | M14: =Base!W458 -> 0 | N14: =Base!X458 -> 0 | O14: =Base!Y458 -> 0 | P14: =IF(Base!Z458="","",Base!Z458) | Q14: =Base!S458 -> No usar | R14: =Base!N458 -> 3346.41 | S14: =Base!T458 -> 0
A15: =SUBTOTAL(103,$B$6:B15) -> 9 | B15: 21 | C15: =Base!H459 -> 2477014: CREACION DEL SERVICIO DE AGUA PARA RIEGO TECNIFICADO EN LAS COMUNIDADES DE IPARO, ARICATO, QUENEQUE, MORORIA, CCAPUNA Y APABUCO DEL DISTRITO DE SANDIA - PROVINCIA DE SANDIA - DEPARTAMENTO DE PUNO | D15: =Base!I459 -> 1888290 | E15: =Base!J459 -> 1816163.8 | F15: =D15-E15 -> 72126.19 | G15: =Base!L459 -> 1807695.8 | H15: =D15-G15 -> 80594.22 | I15: =IF(D15=0,0,G15/D15) -> 0.95731894 | J15: =Base!U459 -> Administración directa / Contrata / Personal/bienes/servicios | K15: =Base!R459 -> Ejecutado | L15: =Base!V459 -> 1750000 | M15: =Base!W459 -> 0 | N15: =Base!X459 -> 0 | O15: =Base!Y459 -> 0 | P15: =IF(Base!Z459="","",Base!Z459) | Q15: =Base!S459 -> No usar | R15: =Base!N459 -> 268.75 | S15: =Base!T459 -> 0
A16: =SUBTOTAL(103,$B$6:B16) -> 10 | B16: 17 | C16: =Base!H460 -> 2651742: MEJORAMIENTO Y AMPLIACION DEL SERVICIO DE PROVISIÓN DE AGUA PARA RIEGO EN LA MICROCUENCA DEL RÍO CONDORIRI DISTRITO DE AZANGARO DE LA PROVINCIA DE AZANGARO DEL DEPARTAMENTO DE PUNO | D16: =Base!I460 -> 1733600 | E16: =Base!J460 -> 1432971.5 | F16: =D16-E16 -> 300628.49 | G16: =Base!L460 -> 1216702.3 | H16: =D16-G16 -> 516897.69 | I16: =IF(D16=0,0,G16/D16) -> 0.70183567 | J16: =Base!U460 -> Administración directa / Contrata / Personal/bienes/servicios | K16: =Base!R460 -> Mayormente comprometido | L16: =Base!V460 -> 5730000 | M16: =Base!W460 -> 7379001 | N16: =Base!X460 -> 1300000 | O16: =Base!Y460 -> 1500000 | P16: =IF(Base!Z460="","",Base!Z460) | Q16: =Base!S460 -> Difícil | R16: =Base!N460 -> 135510 | S16: =Base!T460 -> 436138.49
A17: =SUBTOTAL(103,$B$6:B17) -> 11 | B17: 40 | C17: =Base!H461 -> 2651742: MEJORAMIENTO Y AMPLIACION DEL SERVICIO DE PROVISIÓN DE AGUA PARA RIEGO EN LA MICROCUENCA DEL RÍO CONDORIRI DISTRITO DE AZANGARO DE LA PROVINCIA DE AZANGARO DEL DEPARTAMENTO DE PUNO | D17: =Base!I461 -> 681232 | E17: =Base!J461 -> 500567.77 | F17: =D17-E17 -> 180664.23 | G17: =Base!L461 -> 87757.47 | H17: =D17-G17 -> 593474.53 | I17: =IF(D17=0,0,G17/D17) -> 0.12882171 | J17: =Base!U461 -> Administración directa / Personal/bienes/servicios / Equipamiento / Contrata | K17: =Base!R461 -> Parcialmente comprometido | L17: =Base!V461 -> 5730000 | M17: =Base!W461 -> 7379001 | N17: =Base!X461 -> 1300000 | O17: =Base!Y461 -> 1500000 | P17: =IF(Base!Z461="","",Base!Z461) | Q17: =Base!S461 -> Parcial | R17: =Base!N461 -> 268748.47 | S17: =Base!T461 -> 449412.7
A18: =SUBTOTAL(103,$B$6:B18) -> 12 | B18: 36 | C18: =Base!H462 -> 2001621: (ESTUDIOS DE PRE - INVERSION - nombre no disponible en fuentes) | D18: =Base!I462 -> 390300 | E18: =Base!J462 -> 369779.36 | F18: =D18-E18 -> 20520.64 | G18: =Base!L462 -> 221110.7 | H18: =D18-G18 -> 169189.3 | I18: =IF(D18=0,0,G18/D18) -> 0.56651473 | J18: =Base!U462 -> Estudio de preinversión | K18: =Base!R462 -> Mayormente comprometido | L18: =Base!V462 -> No registrado en cartera | M18: =Base!W462 -> No registrado en cartera | N18: =Base!X462 -> No registrado en cartera | O18: =Base!Y462 -> No registrado en cartera | P18: =IF(Base!Z462="","",Base!Z462) | Q18: =Base!S462 -> Difícil | R18: =Base!N462 -> 119658.66 | S18: =Base!T462 -> 140179.3
... A44: =SUBTOTAL(103,$B$6:B44) -> 38 | B44: 11 | C44: =Base!H488 -> 2541758: CREACION DEL SERVICIO DE AGUA PARA RIEGO MEDIANTE SIEMBRA Y COSECHA DE AGUA EN LAS COMUNIDADES DE CAYATTOCCO, CARABAYA, QQUETE Y UPINA DEL DISTRITO DE ITUATA - PROVINCIA DE CARABAYA - DEPARTAMENTO DE PUNO | D44: =Base!I488 -> 0 | E44: =Base!J488 -> 0 | F44: =D44-E44 -> 0 | G44: =Base!L488 -> 0 | H44: =D44-G44 -> 0 | I44: =IF(D44=0,0,G44/D44) -> 0 | J44: =Base!U488 -> Administración directa | K44: =Base!R488 -> Sin PIM | L44: =Base!V488 -> 1315000 | M44: =Base!W488 -> 0 | N44: =Base!X488 -> 0 | O44: =Base!Y488 -> 0 | P44: =IF(Base!Z488="","",Base!Z488) | Q44: =Base!S488 -> Sin PIM | R44: =Base!N488 -> 0 | S44: =Base!T488 -> 0
A45: =SUBTOTAL(103,$B$6:B45) -> 39 | B45: 15 | C45: =Base!H490 -> 2634779: CREACION DEL SERVICIO DE PROVISIÓN DE AGUA PARA RIEGO EN LAS COMUNIDADES , MEDIANTE POZOS TUBULARES EN LOS DISTRITOS DE HUANCANE, VILQUE CHICO DE LA PROVINCIA DE HUANCANE DEL DEPARTAMENTO DE PUNO | D45: =Base!I490 -> 0 | E45: =Base!J490 -> 0 | F45: =D45-E45 -> 0 | G45: =Base!L490 -> 0 | H45: =D45-G45 -> 0 | I45: =IF(D45=0,0,G45/D45) -> 0 | J45: =Base!U490 -> Administración directa | K45: =Base!R490 -> Sin PIM | L45: =Base!V490 -> 7834316 | M45: =Base!W490 -> 8107762 | N45: =Base!X490 -> 700000 | O45: =Base!Y490 -> 900000 | P45: =IF(Base!Z490="","",Base!Z490) | Q45: =Base!S490 -> Sin PIM | R45: =Base!N490 -> 0 | S45: =Base!T490 -> 0
A46: =SUBTOTAL(103,$B$6:B46) -> 40 | B46: 16 | C46: =Base!H491 -> 2651727: MEJORAMIENTO Y AMPLIACION DEL SERVICIO DE PROVISIÓN DE AGUA PARA RIEGO EN 16 UNIDADES PRODUCTORAS 3 DISTRITOS DE LA PROVINCIA DE MOHO DEL DEPARTAMENTO DE PUNO | D46: =Base!I491 -> 0 | E46: =Base!J491 -> 0 | F46: =D46-E46 -> 0 | G46: =Base!L491 -> 0 | H46: =D46-G46 -> 0 | I46: =IF(D46=0,0,G46/D46) -> 0 | J46: =Base!U491 -> Administración directa | K46: =Base!R491 -> Sin PIM | L46: =Base!V491 -> 6500000 | M46: =Base!W491 -> 4715948 | N46: =Base!X491 -> 5327000 | O46: =Base!Y491 -> 7815000 | P46: =IF(Base!Z491="","",Base!Z491) | Q46: =Base!S491 -> Sin PIM | R46: =Base!N491 -> 0 | S46: =Base!T491 -> 0
A47: 03. PLANEAMIENTO, GESTION Y RESERVA DE CONTINGENCIA | D47: =SUM(D48:D48) -> 0 | E47: =SUM(E48:E48) -> 0 | F47: =D47-E47 -> 0 | G47: =SUM(G48:G48) -> 0 | H47: =D47-G47 -> 0 | I47: =IF(D47=0,0,G47/D47) -> 0 | R47: =SUM(R48:R48) -> 0 | S47: =SUM(S48:S48) -> 0
A48: =SUBTOTAL(103,$B$6:B48) -> 41 | B48: 18 | C48: =Base!H489 -> 2616977: ADQUISICION DE MAQUINA PERFORADORA; EN EL(LA) REGIÓN PUNO - PROGRAMA REGIONAL DE RIEGO Y DRENAJE, PARA LA EXPLORACIÓN Y CAPTACIÓN DE AGUAS SUBTERRÁNEAS MEDIANTE POZOS TUBULARES PARA RIEGO, EN EL DISTRITO DE PUNO, PROVINCIA PUNO, DEPARTAMENTO PUNO | D48: =Base!I489 -> 0 | E48: =Base!J489 -> 0 | F48: =D48-E48 -> 0 | G48: =Base!L489 -> 0 | H48: =D48-G48 -> 0 | I48: =IF(D48=0,0,G48/D48) -> 0 | J48: =Base!U489 -> Contrata | K48: =Base!R489 -> Sin PIM | L48: =Base!V489 -> 50000 | M48: =Base!W489 -> 27160 | N48: =Base!X489 -> 200000 | O48: =Base!Y489 -> 200000 | P48: =IF(Base!Z489="","",Base!Z489) | Q48: =Base!S489 -> Sin PIM | R48: =Base!N489 -> 0 | S48: =Base!T489 -> 0
A50: TOTAL UE 003 | D50: =D5 -> 45637342 | E50: =E5 -> 42133907 | F50: =D50-E50 -> 3503435.2 | G50: =G5 -> 33578062 | H50: =D50-G50 -> 12059280 | I50: =IF(D50=0,0,G50/D50) -> 0.73575849 | R50: =R5 -> 2946314.2 | S50: =S5 -> 6009941.8

Sheet UE 005
C1: ANEXO N° 06
B2: COMPORTAMIENTO DE EJECUCIÓN DE PROYECTOS DE INVERSION PUBLICA DEL AÑO FISCAL 2026 · UE 005 · AL 07/10/2026
A4: N° | B4: META | C4: PROYECTO | D4: PIM 2026 (A) | E4: CERTIFICACIÓN (B) | F4: SALDO (A-B) | G4: DEVENGADO ( C ) | H4: SALDO (A-C) | I4: DEVEN % | J4: MODALIDAD DE EJECUCIÓN | K4: ESTADO SITUACIONAL PROYECTO | L4: Monto Año 2026 (S/) | M4: Monto Año 2027 (S/) | N4: Monto Año 2028 (S/) | O4: Monto Año 2029 (S/) | P4: BASE LEGAL | Q4: DISPONIBILIDAD | R4: CERTIFICADO NO COMPROMETIDO | S4: DISPONIBLE (PIM − COMPROM.)
A5: 005. REGION PUNO-PROGRAMA DE APOYO AL DESARROLLO RURAL ANDINO | D5: =D6 -> 20087412 | E5: =E6 -> 19634939 | F5: =D5-E5 -> 452473.04 | G5: =G6 -> 15129330 | H5: =D5-G5 -> 4958082.2 | I5: =IF(D5=0,0,G5/D5) -> 0.75317467 | R5: =R6 -> 1775258.5 | S5: =S6 -> 2225313
A6: 10. AGROPECUARIA | D6: =SUM(D7:D12) -> 20087412 | E6: =SUM(E7:E12) -> 19634939 | F6: =D6-E6 -> 452473.04 | G6: =SUM(G7:G12) -> 15129330 | H6: =D6-G6 -> 4958082.2 | I6: =IF(D6=0,0,G6/D6) -> 0.75317467 | R6: =SUM(R7:R12) -> 1775258.5 | S6: =SUM(S7:S12) -> 2225313
A7: =SUBTOTAL(103,$B$6:B7) -> 1 | B7: 4 | C7: =Base!H492 -> 2559663: AMPLIACION PARA EL MEJORAMIENTO DE LA PRODUCTIVIDAD DE CARNE Y LANA DE OVINOS 6 PROVINCIAS DEL DEPARTAMENTO DE PUNO | D7: =Base!I492 -> 10473026 | E7: =Base!J492 -> 10363410 | F7: =D7-E7 -> 109615.68 | G7: =Base!L492 -> 8610776.9 | H7: =D7-G7 -> 1862249.1 | I7: =IF(D7=0,0,G7/D7) -> 0.82218615 | J7: =Base!U492 -> Contrata / Personal/bienes/servicios / Equipamiento | K7: =Base!R492 -> Mayormente comprometido | L7: =Base!V492 -> 3820398 | M7: =Base!W492 -> 9531185 | N7: =Base!X492 -> 1200000 | O7: =Base!Y492 -> 610419 | P7: =IF(Base!Z492="","",Base!Z492) | Q7: =Base!S492 -> Difícil | R7: =Base!N492 -> 931710.72 | S7: =Base!T492 -> 1041326.4
A8: =SUBTOTAL(103,$B$6:B8) -> 2 | B8: 5 | C8: =Base!H493 -> 2631496: MEJORAMIENTO DE LOS SERVICIOS DE APOYO AL DESARROLLO PRODUCTIVO EN CAPACIDADES DE TRANSFORMACIÓN Y COMERCIALIZACIÓN DE LA CADENA PRODUCTIVA DE OVINOS EN LAS 5 PROVINCIAS DE LA ZONA SUR DEL DEPARTAMENTO DE PUNO DE PRADERA EN EL DISTRITO DE JULIACA DE LA PROVINCIA DE SAN ROMAN DEL DEPARTAMENTO DE PUNO | D8: =Base!I493 -> 5701948 | E8: =Base!J493 -> 5519793 | F8: =D8-E8 -> 182155 | G8: =Base!L493 -> 2802264.6 | H8: =D8-G8 -> 2899683.4 | I8: =IF(D8=0,0,G8/D8) -> 0.49145742 | J8: =Base!U493 -> Contrata / Equipamiento / Personal/bienes/servicios / Otro (ANIMALES REPRODUCTORES) | K8: =Base!R493 -> Mayormente comprometido | L8: =Base!V493 -> 5141948 | M8: =Base!W493 -> 7818572 | N8: =Base!X493 -> 2825581 | O8: =Base!Y493 -> 9181810 | P8: =IF(Base!Z493="","",Base!Z493) | Q8: =Base!S493 -> Difícil | R8: =Base!N493 -> 843179.34 | S8: =Base!T493 -> 1025334.3
A9: =SUBTOTAL(103,$B$6:B9) -> 3 | B9: 8 | C9: =Base!H494 -> 2479852: MEJORAMIENTO DE LA TRANSFERENCIA TECNOLÓGICA EN LA PRODUCCIÓN Y VALOR AGREGADO DE LA CADENA PRODUCTIVA DE VACUNOS DE CARNE EN LA REGIÓN PUNO 9 PROVINCIAS DEL DEPARTAMENTO DE PUNO | D9: =Base!I494 -> 2603149 | E9: =Base!J494 -> 2600805.4 | F9: =D9-E9 -> 2343.56 | G9: =Base!L494 -> 2578514.2 | H9: =D9-G9 -> 24634.76 | I9: =IF(D9=0,0,G9/D9) -> 0.99053655 | J9: =Base!U494 -> Equipamiento / Administración directa | K9: =Base!R494 -> Ejecutado | L9: =Base!V494 -> 6632458 | M9: =Base!W494 -> 451100 | N9: =Base!X494 -> 500000 | O9: =Base!Y494 -> 500000 | P9: =IF(Base!Z494="","",Base!Z494) | Q9: =Base!S494 -> No usar | R9: =Base!N494 -> 75 | S9: =Base!T494 -> 0
A10: =SUBTOTAL(103,$B$6:B10) -> 4 | B10: 2 | C10: =Base!H495 -> 2479852: MEJORAMIENTO DE LA TRANSFERENCIA TECNOLÓGICA EN LA PRODUCCIÓN Y VALOR AGREGADO DE LA CADENA PRODUCTIVA DE VACUNOS DE CARNE EN LA REGIÓN PUNO 9 PROVINCIAS DEL DEPARTAMENTO DE PUNO | D10: =Base!I495 -> 1279289 | E10: =Base!J495 -> 1150930.2 | F10: =D10-E10 -> 128358.8 | G10: =Base!L495 -> 1137774 | H10: =D10-G10 -> 141514.99 | I10: =IF(D10=0,0,G10/D10) -> 0.88937997 | J10: =Base!U495 -> Contrata / Personal/bienes/servicios | K10: =Base!R495 -> Mayormente comprometido | L10: =Base!V495 -> 6632458 | M10: =Base!W495 -> 451100 | N10: =Base!X495 -> 500000 | O10: =Base!Y495 -> 500000 | P10: =IF(Base!Z495="","",Base!Z495) | Q10: =Base!S495 -> Difícil | R10: =Base!N495 -> 293.46 | S10: =Base!T495 -> 128652.26
A11: =SUBTOTAL(103,$B$6:B11) -> 5 | B11: 1 | C11: =Base!H496 -> 2325694: MEJORAMIENTO DE LA TECNIFICACION DE PROCESOS PARA LA CADENA PRODUCTIVA DE LA LECHE EN LA REGION PUNO | D11: =Base!I496 -> 30000 | E11: =Base!J496 -> 0 | F11: =D11-E11 -> 30000 | G11: =Base!L496 -> 0 | H11: =D11-G11 -> 30000 | I11: =IF(D11=0,0,G11/D11) -> 0 | J11: =Base!U496 -> Contrata | K11: =Base!R496 -> Sin certificar | L11: =Base!V496 -> 2215165 | M11: =Base!W496 -> 30192 | N11: =Base!X496 -> 745055 | O11: =Base!Y496 -> 1459918 | P11: =IF(Base!Z496="","",Base!Z496) | Q11: =Base!S496 -> Disponible | R11: =Base!N496 -> 0 | S11: =Base!T496 -> 30000
A12: =SUBTOTAL(103,$B$6:B12) -> 6 | B12: 3 | C12: =Base!H497 -> 2538654: MEJORAMIENTO DE LA PRESTACIÓN DE SERVICIOS DE INNOVACIÓN Y TRANSFERENCIA TECNOLÓGICA PARA EL DESARROLLO COMPETITIVO DE LA PRODUCCIÓN PECUARIA 8 PROVINCIAS DEL DEPARTAMENTO DE PUNO | D12: =Base!I497 -> 0 | E12: =Base!J497 -> 0 | F12: =D12-E12 -> 0 | G12: =Base!L497 -> 0 | H12: =D12-G12 -> 0 | I12: =IF(D12=0,0,G12/D12) -> 0 | J12: =Base!U497 -> Contrata / Personal/bienes/servicios | K12: =Base!R497 -> Sin PIM | L12: =Base!V497 -> 500000 | M12: =Base!W497 -> 0 | N12: =Base!X497 -> 0 | O12: =Base!Y497 -> 0 | P12: =IF(Base!Z497="","",Base!Z497) | Q12: =Base!S497 -> Sin PIM | R12: =Base!N497 -> 0 | S12: =Base!T497 -> 0
A14: TOTAL UE 005 | D14: =D5 -> 20087412 | E14: =E5 -> 19634939 | F14: =D14-E14 -> 452473.04 | G14: =G5 -> 15129330 | H14: =D14-G14 -> 4958082.2 | I14: =IF(D14=0,0,G14/D14) -> 0.75317467 | R14: =R5 -> 1775258.5 | S14: =S5 -> 2225313

Sheet UE 100
C1: ANEXO N° 07
B2: COMPORTAMIENTO DE EJECUCIÓN DE PROYECTOS DE INVERSION PUBLICA DEL AÑO FISCAL 2026 · UE 100 · AL 07/10/2026
A4: N° | B4: META | C4: PROYECTO | D4: PIM 2026 (A) | E4: CERTIFICACIÓN (B) | F4: SALDO (A-B) | G4: DEVENGADO ( C ) | H4: SALDO (A-C) | I4: DEVEN % | J4: MODALIDAD DE EJECUCIÓN | K4: ESTADO SITUACIONAL PROYECTO | L4: Monto Año 2026 (S/) | M4: Monto Año 2027 (S/) | N4: Monto Año 2028 (S/) | O4: Monto Año 2029 (S/) | P4: BASE LEGAL | Q4: DISPONIBILIDAD | R4: CERTIFICADO NO COMPROMETIDO | S4: DISPONIBLE (PIM − COMPROM.)
A5: 100. REGION PUNO-AGRICULTURA | D5: =D6+D15 -> 14581394 | E5: =E6+E15 -> 12563071 | F5: =D5-E5 -> 2018322.8 | G5: =G6+G15 -> 11236501 | H5: =D5-G5 -> 3344893.1 | I5: =IF(D5=0,0,G5/D5) -> 0.77060539 | R5: =R6+R15 -> 365557.07 | S5: =S6+S15 -> 2368535.4
A6: 10. AGROPECUARIA | D6: =SUM(D7:D14) -> 14427894 | E6: =SUM(E7:E14) -> 12473220 | F6: =D6-E6 -> 1954674.3 | G6: =SUM(G7:G14) -> 11200700 | H6: =D6-G6 -> 3227193.6 | I6: =IF(D6=0,0,G6/D6) -> 0.77632261 | R6: =SUM(R7:R14) -> 363057.07 | S6: =SUM(S7:S14) -> 2302386.9
A7: =SUBTOTAL(103,$B$6:B7) -> 1 | B7: 27 | C7: =Base!H498 -> 2557255: MEJORAMIENTO DE CAPACIDADES PARA LA CONSERVACIÓN Y MANEJO DE CAMÉLIDOS SUDAMERICANOS DOMÉSTICOS DE LAS RAZAS SURI Y HUACAYA DE COLOR EN ZONAS ALTOANDINAS 6 PROVINCIAS DEL DEPARTAMENTO DE PUNO | D7: =Base!I498 -> 7439155 | E7: =Base!J498 -> 6108586.4 | F7: =D7-E7 -> 1330568.6 | G7: =Base!L498 -> 5504731.6 | H7: =D7-G7 -> 1934423.4 | I7: =IF(D7=0,0,G7/D7) -> 0.73996732 | J7: =Base!U498 -> Contrata / Personal/bienes/servicios / Equipamiento | K7: =Base!R498 -> Mayormente comprometido | L7: =Base!V498 -> 500000 | M7: =Base!W498 -> 4356339 | N7: =Base!X498 -> 4468789 | O7: =Base!Y498 -> 15297612 | P7: =IF(Base!Z498="","",Base!Z498) | Q7: =Base!S498 -> Difícil | R7: =Base!N498 -> 200338.77 | S7: =Base!T498 -> 1530907.3
A8: =SUBTOTAL(103,$B$6:B8) -> 2 | B8: 3 | C8: =Base!H499 -> 2470873: MEJORAMIENTO DE CAPACIDADES PARA EL DESARROLLO INTEGRAL DE LOS CULTIVOS DE FRUTALES EN LA SELVA DE LAS PROVINCIAS DE SANDIA Y CARABAYA DEL DEPARTAMENTO DE PUNO | D8: =Base!I499 -> 4417847 | E8: =Base!J499 -> 4295083.8 | F8: =D8-E8 -> 122763.23 | G8: =Base!L499 -> 3703840.5 | H8: =D8-G8 -> 714006.47 | I8: =IF(D8=0,0,G8/D8) -> 0.83838135 | J8: =Base!U499 -> Contrata / Personal/bienes/servicios / Expediente técnico | K8: =Base!R499 -> Mayormente comprometido | L8: =Base!V499 -> 8534000 | M8: =Base!W499 -> 7018517 | N8: =Base!X499 -> 6966429 | O8: =Base!Y499 -> 5165856 | P8: =IF(Base!Z499="","",Base!Z499) | Q8: =Base!S499 -> Difícil | R8: =Base!N499 -> 147374.35 | S8: =Base!T499 -> 270137.58
A9: =SUBTOTAL(103,$B$6:B9) -> 3 | B9: 26 | C9: =Base!H500 -> 2511053: MEJORAMIENTO DE CAPACIDADES PRODUCTIVAS PARA PROMOVER LA SEGURIDAD ALIMENTARIA EN LA REACTIVACIÓN ECONÓMICA DE LAS 13 PROVINCIAS DEL DEPARTAMENTO DE PUNO | D9: =Base!I500 -> 2000000 | E9: =Base!J500 -> 1999999.5 | F9: =D9-E9 -> 0.47 | G9: =Base!L500 -> 1956578.2 | H9: =D9-G9 -> 43421.78 | I9: =IF(D9=0,0,G9/D9) -> 0.97828911 | J9: =Base!U500 -> Personal/bienes/servicios / Contrata / Otro (OTROS ANIMALES) | K9: =Base!R500 -> Ejecutado | L9: =Base!V500 -> 2000000 | M9: =Base!W500 -> 37016 | N9: =Base!X500 -> 0 | O9: =Base!Y500 -> 0 | P9: =IF(Base!Z500="","",Base!Z500) | Q9: =Base!S500 -> No usar | R9: =Base!N500 -> 15343.95 | S9: =Base!T500 -> 0
A10: =SUBTOTAL(103,$B$6:B10) -> 4 | B10: 34 | C10: =Base!H501 -> 2629018: MEJORAMIENTO DE LOS SERVICIOS DE APOYO AL DESARROLLO PRODUCTIVO DE PASTOS Y FORRAJES EN 14 UNIDADES PRODUCTORAS DE 84 DISTRITOS DE 13 PROVINCIAS DEL DEPARTAMENTO DE PUNO | D10: =Base!I501 -> 431850 | E10: =Base!J501 -> 0 | F10: =D10-E10 -> 431850 | G10: =Base!L501 -> 0 | H10: =D10-G10 -> 431850 | I10: =IF(D10=0,0,G10/D10) -> 0 | J10: =Base!U501 -> Personal/bienes/servicios / Otro (SEMILLAS Y ALMACIGOS) / Contrata | K10: =Base!R501 -> Sin certificar | L10: =Base!V501 -> 500000 | M10: =Base!W501 -> 0 | N10: =Base!X501 -> 0 | O10: =Base!Y501 -> 0 | P10: =IF(Base!Z501="","",Base!Z501) | Q10: =Base!S501 -> Disponible | R10: =Base!N501 -> 0 | S10: =Base!T501 -> 431850
A11: =SUBTOTAL(103,$B$6:B11) -> 5 | B11: 12 | C11: =Base!H503 -> 2629018: MEJORAMIENTO DE LOS SERVICIOS DE APOYO AL DESARROLLO PRODUCTIVO DE PASTOS Y FORRAJES EN 14 UNIDADES PRODUCTORAS DE 84 DISTRITOS DE 13 PROVINCIAS DEL DEPARTAMENTO DE PUNO | D11: =Base!I503 -> 68150 | E11: =Base!J503 -> 39550 | F11: =D11-E11 -> 28600 | G11: =Base!L503 -> 35550 | H11: =D11-G11 -> 32600 | I11: =IF(D11=0,0,G11/D11) -> 0.52164343 | J11: =Base!U503 -> Expediente técnico | K11: =Base!R503 -> Mayormente comprometido | L11: =Base!V503 -> 500000 | M11: =Base!W503 -> 0 | N11: =Base!X503 -> 0 | O11: =Base!Y503 -> 0 | P11: =IF(Base!Z503="","",Base!Z503) | Q11: =Base!S503 -> Difícil | R11: =Base!N503 -> 0 | S11: =Base!T503 -> 28600
A12: =SUBTOTAL(103,$B$6:B12) -> 6 | B12: 32 | C12: =Base!H504 -> 2313145: (SUPERVISION Y LIQUIDACION DE OBRAS - nombre no disponible en fuentes) | D12: =Base!I504 -> 40000 | E12: =Base!J504 -> 0 | F12: =D12-E12 -> 40000 | G12: =Base!L504 -> 0 | H12: =D12-G12 -> 40000 | I12: =IF(D12=0,0,G12/D12) -> 0 | J12: =Base!U504 -> Contrata | K12: =Base!R504 -> Sin certificar | L12: =Base!V504 -> No registrado en cartera | M12: =Base!W504 -> No registrado en cartera | N12: =Base!X504 -> No registrado en cartera | O12: =Base!Y504 -> No registrado en cartera | P12: =IF(Base!Z504="","",Base!Z504) | Q12: =Base!S504 -> Disponible | R12: =Base!N504 -> 0 | S12: =Base!T504 -> 40000
A13: =SUBTOTAL(103,$B$6:B13) -> 7 | B13: 30 | C13: =Base!H505 -> 2318520: MEJORAMIENTO DE LA CAPACIDAD AGROPRODUCTIVA DE GRANOS ANDINOS ORGANICOS DE QUINUA, CAÑIHUA, HABA Y TARWI EN LA REGION PUNO | D13: =Base!I505 -> 30892 | E13: =Base!J505 -> 30000 | F13: =D13-E13 -> 892 | G13: =Base!L505 -> 0 | H13: =D13-G13 -> 30892 | I13: =IF(D13=0,0,G13/D13) -> 0 | J13: =Base!U505 -> Contrata | K13: =Base!R505 -> Mayormente comprometido | L13: =Base!V505 -> 770194 | M13: =Base!W505 -> 0 | N13: =Base!X505 -> 0 | O13: =Base!Y505 -> 0 | P13: =IF(Base!Z505="","",Base!Z505) | Q13: =Base!S505 -> Difícil | R13: =Base!N505 -> 0 | S13: =Base!T505 -> 892
A14: =SUBTOTAL(103,$B$6:B14) -> 8 | B14: 11 | C14: =Base!H507 -> 2557255: MEJORAMIENTO DE CAPACIDADES PARA LA CONSERVACIÓN Y MANEJO DE CAMÉLIDOS SUDAMERICANOS DOMÉSTICOS DE LAS RAZAS SURI Y HUACAYA DE COLOR EN ZONAS ALTOANDINAS 6 PROVINCIAS DEL DEPARTAMENTO DE PUNO | D14: =Base!I507 -> 0 | E14: =Base!J507 -> 0 | F14: =D14-E14 -> 0 | G14: =Base!L507 -> 0 | H14: =D14-G14 -> 0 | I14: =IF(D14=0,0,G14/D14) -> 0 | J14: =Base!U507 -> Personal/bienes/servicios | K14: =Base!R507 -> Sin PIM | L14: =Base!V507 -> 500000 | M14: =Base!W507 -> 4356339 | N14: =Base!X507 -> 4468789 | O14: =Base!Y507 -> 15297612 | P14: =IF(Base!Z507="","",Base!Z507) | Q14: =Base!S507 -> Sin PIM | R14: =Base!N507 -> 0 | S14: =Base!T507 -> 0
A15: 03. PLANEAMIENTO, GESTION Y RESERVA DE CONTINGENCIA | D15: =SUM(D16:D17) -> 153500 | E15: =SUM(E16:E17) -> 89851.5 | F15: =D15-E15 -> 63648.5 | G15: =SUM(G16:G17) -> 35800.5 | H15: =D15-G15 -> 117699.5 | I15: =IF(D15=0,0,G15/D15) -> 0.23322801 | R15: =SUM(R16:R17) -> 2500 | S15: =SUM(S16:S17) -> 66148.5
A16: =SUBTOTAL(103,$B$6:B16) -> 9 | B16: 31 | C16: =Base!H502 -> 2001621: (ESTUDIOS DE PRE - INVERSION - nombre no disponible en fuentes) | D16: =Base!I502 -> 133500 | E16: =Base!J502 -> 69851.5 | F16: =D16-E16 -> 63648.5 | G16: =Base!L502 -> 35800.5 | H16: =D16-G16 -> 97699.5 | I16: =IF(D16=0,0,G16/D16) -> 0.26816854 | J16: =Base!U502 -> Estudio de preinversión | K16: =Base!R502 -> Mayormente comprometido | L16: =Base!V502 -> No registrado en cartera | M16: =Base!W502 -> No registrado en cartera | N16: =Base!X502 -> No registrado en cartera | O16: =Base!Y502 -> No registrado en cartera | P16: =IF(Base!Z502="","",Base!Z502) | Q16: =Base!S502 -> Difícil | R16: =Base!N502 -> 0 | S16: =Base!T502 -> 63648.5
A17: =SUBTOTAL(103,$B$6:B17) -> 10 | B17: 29 | C17: =Base!H506 -> 2615902: REMODELACION DE AUDITORIO; ADQUISICION DE EQUIPOS COMPLEMENTARIOS; REPARACION DE ESCALERA DE ACCESO Y ; EN EL(LA) DIRECCIÓN REGIONAL AGRARIA SEDE CENTRAL DISTRITO DE PUNO, PROVINCIA PUNO, DEPARTAMENTO PUNO | D17: =Base!I506 -> 20000 | E17: =Base!J506 -> 20000 | F17: =D17-E17 -> 0 | G17: =Base!L506 -> 0 | H17: =D17-G17 -> 20000 | I17: =IF(D17=0,0,G17/D17) -> 0 | J17: =Base!U506 -> Expediente técnico | K17: =Base!R506 -> Mayormente comprometido | L17: =Base!V506 -> 20000 | M17: =Base!W506 -> 0 | N17: =Base!X506 -> 0 | O17: =Base!Y506 -> 0 | P17: =IF(Base!Z506="","",Base!Z506) | Q17: =Base!S506 -> Difícil | R17: =Base!N506 -> 2500 | S17: =Base!T506 -> 2500
A19: TOTAL UE 100 | D19: =D5 -> 14581394 | E19: =E5 -> 12563071 | F19: =D19-E19 -> 2018322.8 | G19: =G5 -> 11236501 | H19: =D19-G19 -> 3344893.1 | I19: =IF(D19=0,0,G19/D19) -> 0.77060539 | R19: =R5 -> 365557.07 | S19: =S5 -> 2368535.4

Sheet UE 302
C1: ANEXO N° 08
B2: COMPORTAMIENTO DE EJECUCIÓN DE PROYECTOS DE INVERSION PUBLICA DEL AÑO FISCAL 2026 · UE 302 · AL 07/10/2026
A4: N° | B4: META | C4: PROYECTO | D4: PIM 2026 (A) | E4: CERTIFICACIÓN (B) | F4: SALDO (A-B) | G4: DEVENGADO ( C ) | H4: SALDO (A-C) | I4: DEVEN % | J4: MODALIDAD DE EJECUCIÓN | K4: ESTADO SITUACIONAL PROYECTO | L4: Monto Año 2026 (S/) | M4: Monto Año 2027 (S/) | N4: Monto Año 2028 (S/) | O4: Monto Año 2029 (S/) | P4: BASE LEGAL | Q4: DISPONIBILIDAD | R4: CERTIFICADO NO COMPROMETIDO | S4: DISPONIBLE (PIM − COMPROM.)
A5: 302. REGION PUNO-EDUCACION MELGAR | D5: =D6 -> 32592 | E5: =E6 -> 0 | F5: =D5-E5 -> 32592 | G5: =G6 -> 0 | H5: =D5-G5 -> 32592 | I5: =IF(D5=0,0,G5/D5) -> 0 | R5: =R6 -> 0 | S5: =S6 -> 32592
A6: 22. EDUCACION | D6: =SUM(D7:D7) -> 32592 | E6: =SUM(E7:E7) -> 0 | F6: =D6-E6 -> 32592 | G6: =SUM(G7:G7) -> 0 | H6: =D6-G6 -> 32592 | I6: =IF(D6=0,0,G6/D6) -> 0 | R6: =SUM(R7:R7) -> 0 | S6: =SUM(S7:S7) -> 32592
A7: =SUBTOTAL(103,$B$6:B7) -> 1 | B7: 63 | C7: =Base!H508 -> 2393101: MEJORAMIENTO Y AMPLIACION DEL SERVICIO ADMINISTRATIVO DE LA UNIDAD DE GESTIÓN EDUCATIVA LOCAL MELGAR EN EL DISTRITO DE AYAVIRI, PROVINCIA DE MELGAR, REGIÓN PUNO | D7: =Base!I508 -> 32592 | E7: =Base!J508 -> 0 | F7: =D7-E7 -> 32592 | G7: =Base!L508 -> 0 | H7: =D7-G7 -> 32592 | I7: =IF(D7=0,0,G7/D7) -> 0 | J7: =Base!U508 -> Administración directa / Contrata / Personal/bienes/servicios | K7: =Base!R508 -> Sin certificar | L7: =Base!V508 -> 154969 | M7: =Base!W508 -> 0 | N7: =Base!X508 -> 0 | O7: =Base!Y508 -> 0 | P7: =IF(Base!Z508="","",Base!Z508) | Q7: =Base!S508 -> Disponible | R7: =Base!N508 -> 0 | S7: =Base!T508 -> 32592
A9: TOTAL UE 302 | D9: =D5 -> 32592 | E9: =E5 -> 0 | F9: =D9-E9 -> 32592 | G9: =G5 -> 0 | H9: =D9-G9 -> 32592 | I9: =IF(D9=0,0,G9/D9) -> 0 | R9: =R5 -> 0 | S9: =S5 -> 32592

Sheet UE 413
C1: ANEXO N° 09
B2: COMPORTAMIENTO DE EJECUCIÓN DE PROYECTOS DE INVERSION PUBLICA DEL AÑO FISCAL 2026 · UE 413 · AL 07/10/2026
A4: N° | B4: META | C4: PROYECTO | D4: PIM 2026 (A) | E4: CERTIFICACIÓN (B) | F4: SALDO (A-B) | G4: DEVENGADO ( C ) | H4: SALDO (A-C) | I4: DEVEN % | J4: MODALIDAD DE EJECUCIÓN | K4: ESTADO SITUACIONAL PROYECTO | L4: Monto Año 2026 (S/) | M4: Monto Año 2027 (S/) | N4: Monto Año 2028 (S/) | O4: Monto Año 2029 (S/) | P4: BASE LEGAL | Q4: DISPONIBILIDAD | R4: CERTIFICADO NO COMPROMETIDO | S4: DISPONIBLE (PIM − COMPROM.)
A5: 413. GOB. REG. DPTO. DE PUNO - SALUD SAN ANTONIO DE PUTINA | D5: =D6 -> 41800 | E5: =E6 -> 41500 | F5: =D5-E5 -> 300 | G5: =G6 -> 41500 | H5: =D5-G5 -> 300 | I5: =IF(D5=0,0,G5/D5) -> 0.99282297 | R5: =R6 -> 0 | S5: =S6 -> 0
A6: 20. SALUD | D6: =SUM(D7:D7) -> 41800 | E6: =SUM(E7:E7) -> 41500 | F6: =D6-E6 -> 300 | G6: =SUM(G7:G7) -> 41500 | H6: =D6-G6 -> 300 | I6: =IF(D6=0,0,G6/D6) -> 0.99282297 | R6: =SUM(R7:R7) -> 0 | S6: =SUM(S7:S7) -> 0
A7: =SUBTOTAL(103,$B$6:B7) -> 1 | B7: 121 | C7: =Base!H509 -> 2730957: ADQUISICION DE UNIDAD DENTAL Y AUTOCLAVE; EN EL(LA) ANANEA DISTRITO DE ANANEA, PROVINCIA SAN ANTONIO DE PUTINA, DEPARTAMENTO PUNO | D7: =Base!I509 -> 41800 | E7: =Base!J509 -> 41500 | F7: =D7-E7 -> 300 | G7: =Base!L509 -> 41500 | H7: =D7-G7 -> 300 | I7: =IF(D7=0,0,G7/D7) -> 0.99282297 | J7: =Base!U509 -> Equipamiento | K7: =Base!R509 -> Ejecutado | L7: =Base!V509 -> 43800 | M7: =Base!W509 -> 0 | N7: =Base!X509 -> 0 | O7: =Base!Y509 -> 0 | P7: =IF(Base!Z509="","",Base!Z509) | Q7: =Base!S509 -> No usar | R7: =Base!N509 -> 0 | S7: =Base!T509 -> 0
A9: TOTAL UE 413 | D9: =D5 -> 41800 | E9: =E5 -> 41500 | F9: =D9-E9 -> 300 | G9: =G5 -> 41500 | H9: =D9-G9 -> 300 | I9: =IF(D9=0,0,G9/D9) -> 0.99282297 | R9: =R5 -> 0 | S9: =S5 -> 0

Sheet Saldo al expediente
A1: COMPORTAMIENTO DE PROYECTOS DE INVERSION PUBLICA AL 07/10/2026 · por función · saldo al expediente
A2: Saldo = Costo actualizado − Ejecución acumulada al 2025 − PIM 2026 (lo que falta financiar después de 2026). Un CUI se cuenta una vez por UE; no sumar el costo entre UE.
A3: Rubro: API Datos Abiertos MEF (por UE y CUI), descargada 07/10/2026 23:35.
A4: N° | B4: META(S) | C4: NOMBRE DEL PROYECTO | D4: COSTO ACTUALIZADO (Cartera) | E4: EJEC. ACUM. AL 31/12/2025 (Cartera) | F4: RECURSOS ORDINARIOS (00) | G4: RDR (09) | H4: FONCOR (15) | I4: CANON (18) | J4: ROOC (19) | K4: PIM SIN RUBRO ASIGNADO | L4: PIM 2026 | M4: SALDO AL EXPEDIENTE / INVERSIÓN | N4: OBSERVACIÓN
A5: 001. REGION PUNO-SEDE CENTRAL | D5: =D6+D81+D217+D300+D320+D331+D335+D337+D339+D342+D348+D357+D359+D426+D431+D439+D445 -> 7618330795 | E5: =E6+E81+E217+E300+E320+E331+E335+E337+E339+E342+E348+E357+E359+E426+E431+E439+E445 -> 2327687674 | F5: =F6+F81+F217+F300+F320+F331+F335+F337+F339+F342+F348+F357+F359+F426+F431+F439+F445 -> 112127099 | G5: =G6+G81+G217+G300+G320+G331+G335+G337+G339+G342+G348+G357+G359+G426+G431+G439+G445 -> 86065132 | H5: =H6+H81+H217+H300+H320+H331+H335+H337+H339+H342+H348+H357+H359+H426+H431+H439+H445 -> 593390307 | I5: =I6+I81+I217+I300+I320+I331+I335+I337+I339+I342+I348+I357+I359+I426+I431+I439+I445 -> 100705416 | J5: =J6+J81+J217+J300+J320+J331+J335+J337+J339+J342+J348+J357+J359+J426+J431+J439+J445 -> 12739030 | K5: =K6+K81+K217+K300+K320+K331+K335+K337+K339+K342+K348+K357+K359+K426+K431+K439+K445 -> 0 | ... M5: =M6+M81+M217+M300+M320+M331+M335+M337+M339+M342+M348+M357+M359+M426+M431+M439+M445 -> 4656714083
A6: 20. SALUD | D6: =SUM(D7:D80) -> 1674331985 | E6: =SUM(E7:E80) -> 403119733 | F6: =SUM(F7:F80) -> 109909702 | G6: =SUM(G7:G80) -> 57506088 | H6: =SUM(H7:H80) -> 92336809 | I6: =SUM(I7:I80) -> 36785019 | J6: =SUM(J7:J80) -> 12739030 | K6: =SUM(K7:K80) -> 0 | ... M6: =SUM(M7:M80) -> 1115282455
A7: 1 | B7: 219 | C7: 2251136: MEJORAMIENTO DE LA CAPACIDAD RESOLUTIVA DEL HOSPITAL LUCIO ALDAZABAL PAUCA DE REDES HUANCANE, PROVINCIA DE HUANCANE - REGION PUNO | D7: No registrado en cartera | E7: No registrado en cartera | F7: =INDEX('Rubro por CUI'!$E$5:$E$460,MATCH("001|2251136",'Rubro por CUI'!$N$5:$N$460,0)) -> 56150305 | G7: =INDEX('Rubro por CUI'!$F$5:$F$460,MATCH("001|2251136",'Rubro por CUI'!$N$5:$N$460,0)) -> 0 | H7: =INDEX('Rubro por CUI'!$G$5:$G$460,MATCH("001|2251136",'Rubro por CUI'!$N$5:$N$460,0)) -> 0 | I7: =INDEX('Rubro por CUI'!$H$5:$H$460,MATCH("001|2251136",'Rubro por CUI'!$N$5:$N$460,0)) -> 0 | J7: =INDEX('Rubro por CUI'!$I$5:$I$460,MATCH("001|2251136",'Rubro por CUI'!$N$5:$N$460,0)) -> 0 | K7: =L7-SUM(F7:J7) -> 0 | L7: =SUMIFS(Base!$I$5:$I$509,Base!$A$5:$A$509,"001",Base!$F$5:$F$509,"2251136") -> 56150305 | M7: No registrado en cartera | N7: Sin datos en Cartera: no se puede calcular el saldo
A8: 2 | B8: 220 | C8: 2279375: MEJORAMIENTO DE LOS SERVICIOS DE SALUD DEL HOSPITAL DE APOYO ILAVE, PROVINCIA DE EL COLLAO - REGION PUNO | D8: No registrado en cartera | E8: No registrado en cartera | F8: =INDEX('Rubro por CUI'!$E$5:$E$460,MATCH("001|2279375",'Rubro por CUI'!$N$5:$N$460,0)) -> 53759397 | G8: =INDEX('Rubro por CUI'!$F$5:$F$460,MATCH("001|2279375",'Rubro por CUI'!$N$5:$N$460,0)) -> 0 | H8: =INDEX('Rubro por CUI'!$G$5:$G$460,MATCH("001|2279375",'Rubro por CUI'!$N$5:$N$460,0)) -> 0 | I8: =INDEX('Rubro por CUI'!$H$5:$H$460,MATCH("001|2279375",'Rubro por CUI'!$N$5:$N$460,0)) -> 0 | J8: =INDEX('Rubro por CUI'!$I$5:$I$460,MATCH("001|2279375",'Rubro por CUI'!$N$5:$N$460,0)) -> 0 | K8: =L8-SUM(F8:J8) -> 0 | L8: =SUMIFS(Base!$I$5:$I$509,Base!$A$5:$A$509,"001",Base!$F$5:$F$509,"2279375") -> 53759397 | M8: No registrado en cartera | N8: Sin datos en Cartera: no se puede calcular el saldo
