Workbook

Sheet Resumen
A1: GORE Puno · UE 001 Sede Central · mapeo de disponibilidad por proyecto
A2: Al 06/10/2026. PIM por estado situacional (suma de PIM de los proyectos en cada estado). Fórmulas sobre la hoja Base.
A4: Gerencia / Oficina | B4: Proyectos (CUI-meta) | C4: PIM 2026 | D4: Certificación | E4: Saldo sin certificar | F4: Devengado | G4: PIM · Sin certificar | H4: PIM · Solo certificado | I4: PIM · Comprometido | J4: PIM · Devengado total | K4: PIM · Sin PIM
A5: GERENCIA DE INFRAESTRUCTURA | B5: =COUNTIFS(Base!$B$5:$B$440,$A5) -> 281 | C5: =SUMIFS(Base!$H$5:$H$440,Base!$B$5:$B$440,$A5) -> 770204814 | D5: =SUMIFS(Base!$I$5:$I$440,Base!$B$5:$B$440,$A5) -> 7.2264955e+08 | E5: =C5-D5 -> 47555259 | F5: =SUMIFS(Base!$K$5:$K$440,Base!$B$5:$B$440,$A5) -> 3.8172744e+08 | G5: =SUMIFS(Base!$H$5:$H$440,Base!$B$5:$B$440,$A5,Base!$P$5:$P$440,"Sin certificar") -> 11016473 | H5: =SUMIFS(Base!$H$5:$H$440,Base!$B$5:$B$440,$A5,Base!$P$5:$P$440,"Solo certificado") -> 31515087 | I5: =SUMIFS(Base!$H$5:$H$440,Base!$B$5:$B$440,$A5,Base!$P$5:$P$440,"Comprometido") -> 727673254 | J5: =SUMIFS(Base!$H$5:$H$440,Base!$B$5:$B$440,$A5,Base!$P$5:$P$440,"Devengado total") -> 0 | K5: =SUMIFS(Base!$H$5:$H$440,Base!$B$5:$B$440,$A5,Base!$P$5:$P$440,"Sin PIM") -> 0
A6: GERENCIA REGIONAL DE DESARROLLO ECONOMICO | B6: =COUNTIFS(Base!$B$5:$B$440,$A6) -> 83 | C6: =SUMIFS(Base!$H$5:$H$440,Base!$B$5:$B$440,$A6) -> 15438088 | D6: =SUMIFS(Base!$I$5:$I$440,Base!$B$5:$B$440,$A6) -> 13246424 | E6: =C6-D6 -> 2191664.1 | F6: =SUMIFS(Base!$K$5:$K$440,Base!$B$5:$B$440,$A6) -> 6937956.8 | G6: =SUMIFS(Base!$H$5:$H$440,Base!$B$5:$B$440,$A6,Base!$P$5:$P$440,"Sin certificar") -> 160000 | H6: =SUMIFS(Base!$H$5:$H$440,Base!$B$5:$B$440,$A6,Base!$P$5:$P$440,"Solo certificado") -> 891317 | I6: =SUMIFS(Base!$H$5:$H$440,Base!$B$5:$B$440,$A6,Base!$P$5:$P$440,"Comprometido") -> 14139325 | J6: =SUMIFS(Base!$H$5:$H$440,Base!$B$5:$B$440,$A6,Base!$P$5:$P$440,"Devengado total") -> 247446 | K6: =SUMIFS(Base!$H$5:$H$440,Base!$B$5:$B$440,$A6,Base!$P$5:$P$440,"Sin PIM") -> 0
A7: GERENCIA REGIONAL DE RECURSOS NATURALES Y GESTION AMBIENTAL | B7: =COUNTIFS(Base!$B$5:$B$440,$A7) -> 11 | C7: =SUMIFS(Base!$H$5:$H$440,Base!$B$5:$B$440,$A7) -> 18155027 | D7: =SUMIFS(Base!$I$5:$I$440,Base!$B$5:$B$440,$A7) -> 15578094 | E7: =C7-D7 -> 2576932.7 | F7: =SUMIFS(Base!$K$5:$K$440,Base!$B$5:$B$440,$A7) -> 8757642.5 | G7: =SUMIFS(Base!$H$5:$H$440,Base!$B$5:$B$440,$A7,Base!$P$5:$P$440,"Sin certificar") -> 32099 | H7: =SUMIFS(Base!$H$5:$H$440,Base!$B$5:$B$440,$A7,Base!$P$5:$P$440,"Solo certificado") -> 30658 | I7: =SUMIFS(Base!$H$5:$H$440,Base!$B$5:$B$440,$A7,Base!$P$5:$P$440,"Comprometido") -> 18092270 | J7: =SUMIFS(Base!$H$5:$H$440,Base!$B$5:$B$440,$A7,Base!$P$5:$P$440,"Devengado total") -> 0 | K7: =SUMIFS(Base!$H$5:$H$440,Base!$B$5:$B$440,$A7,Base!$P$5:$P$440,"Sin PIM") -> 0
A8: PROYECTO ESPECIAL TRUCHAS TITICACA - PETT | B8: =COUNTIFS(Base!$B$5:$B$440,$A8) -> 3 | C8: =SUMIFS(Base!$H$5:$H$440,Base!$B$5:$B$440,$A8) -> 13183082 | D8: =SUMIFS(Base!$I$5:$I$440,Base!$B$5:$B$440,$A8) -> 12706541 | E8: =C8-D8 -> 476541.15 | F8: =SUMIFS(Base!$K$5:$K$440,Base!$B$5:$B$440,$A8) -> 3714211.5 | G8: =SUMIFS(Base!$H$5:$H$440,Base!$B$5:$B$440,$A8,Base!$P$5:$P$440,"Sin certificar") -> 100000 | H8: =SUMIFS(Base!$H$5:$H$440,Base!$B$5:$B$440,$A8,Base!$P$5:$P$440,"Solo certificado") -> 0 | I8: =SUMIFS(Base!$H$5:$H$440,Base!$B$5:$B$440,$A8,Base!$P$5:$P$440,"Comprometido") -> 13083082 | J8: =SUMIFS(Base!$H$5:$H$440,Base!$B$5:$B$440,$A8,Base!$P$5:$P$440,"Devengado total") -> 0 | K8: =SUMIFS(Base!$H$5:$H$440,Base!$B$5:$B$440,$A8,Base!$P$5:$P$440,"Sin PIM") -> 0
A9: PROYECTO ESPECIAL CAMELIDOS SUDAMERICANOS | B9: =COUNTIFS(Base!$B$5:$B$440,$A9) -> 2 | C9: =SUMIFS(Base!$H$5:$H$440,Base!$B$5:$B$440,$A9) -> 5603985 | D9: =SUMIFS(Base!$I$5:$I$440,Base!$B$5:$B$440,$A9) -> 5402770 | E9: =C9-D9 -> 201215.05 | F9: =SUMIFS(Base!$K$5:$K$440,Base!$B$5:$B$440,$A9) -> 3499541.4 | G9: =SUMIFS(Base!$H$5:$H$440,Base!$B$5:$B$440,$A9,Base!$P$5:$P$440,"Sin certificar") -> 0 | H9: =SUMIFS(Base!$H$5:$H$440,Base!$B$5:$B$440,$A9,Base!$P$5:$P$440,"Solo certificado") -> 0 | I9: =SUMIFS(Base!$H$5:$H$440,Base!$B$5:$B$440,$A9,Base!$P$5:$P$440,"Comprometido") -> 5603985 | J9: =SUMIFS(Base!$H$5:$H$440,Base!$B$5:$B$440,$A9,Base!$P$5:$P$440,"Devengado total") -> 0 | K9: =SUMIFS(Base!$H$5:$H$440,Base!$B$5:$B$440,$A9,Base!$P$5:$P$440,"Sin PIM") -> 0
A10: GERENCIA REGIONAL DE DESARROLLO SOCIAL | B10: =COUNTIFS(Base!$B$5:$B$440,$A10) -> 41 | C10: =SUMIFS(Base!$H$5:$H$440,Base!$B$5:$B$440,$A10) -> 74397967 | D10: =SUMIFS(Base!$I$5:$I$440,Base!$B$5:$B$440,$A10) -> 67208622 | E10: =C10-D10 -> 7189345.4 | F10: =SUMIFS(Base!$K$5:$K$440,Base!$B$5:$B$440,$A10) -> 23249590 | G10: =SUMIFS(Base!$H$5:$H$440,Base!$B$5:$B$440,$A10,Base!$P$5:$P$440,"Sin certificar") -> 1256414 | H10: =SUMIFS(Base!$H$5:$H$440,Base!$B$5:$B$440,$A10,Base!$P$5:$P$440,"Solo certificado") -> 8232218 | I10: =SUMIFS(Base!$H$5:$H$440,Base!$B$5:$B$440,$A10,Base!$P$5:$P$440,"Comprometido") -> 64909335 | J10: =SUMIFS(Base!$H$5:$H$440,Base!$B$5:$B$440,$A10,Base!$P$5:$P$440,"Devengado total") -> 0 | K10: =SUMIFS(Base!$H$5:$H$440,Base!$B$5:$B$440,$A10,Base!$P$5:$P$440,"Sin PIM") -> 0
A11: DIRECCIÓN DE ESTUDIOS DE PREINVERSIÓN | B11: =COUNTIFS(Base!$B$5:$B$440,$A11) -> 10 | C11: =SUMIFS(Base!$H$5:$H$440,Base!$B$5:$B$440,$A11) -> 7151039 | D11: =SUMIFS(Base!$I$5:$I$440,Base!$B$5:$B$440,$A11) -> 5777501 | E11: =C11-D11 -> 1373538 | F11: =SUMIFS(Base!$K$5:$K$440,Base!$B$5:$B$440,$A11) -> 5400403.3 | G11: =SUMIFS(Base!$H$5:$H$440,Base!$B$5:$B$440,$A11,Base!$P$5:$P$440,"Sin certificar") -> 224696 | H11: =SUMIFS(Base!$H$5:$H$440,Base!$B$5:$B$440,$A11,Base!$P$5:$P$440,"Solo certificado") -> 0 | I11: =SUMIFS(Base!$H$5:$H$440,Base!$B$5:$B$440,$A11,Base!$P$5:$P$440,"Comprometido") -> 6926343 | J11: =SUMIFS(Base!$H$5:$H$440,Base!$B$5:$B$440,$A11,Base!$P$5:$P$440,"Devengado total") -> 0 | K11: =SUMIFS(Base!$H$5:$H$440,Base!$B$5:$B$440,$A11,Base!$P$5:$P$440,"Sin PIM") -> 0
A12: SIN CLASIFICAR (pendiente de asignar gerencia) | B12: =COUNTIFS(Base!$B$5:$B$440,$A12) -> 5 | C12: =SUMIFS(Base!$H$5:$H$440,Base!$B$5:$B$440,$A12) -> 892982 | D12: =SUMIFS(Base!$I$5:$I$440,Base!$B$5:$B$440,$A12) -> 573620.69 | E12: =C12-D12 -> 319361.31 | F12: =SUMIFS(Base!$K$5:$K$440,Base!$B$5:$B$440,$A12) -> 288990.91 | G12: =SUMIFS(Base!$H$5:$H$440,Base!$B$5:$B$440,$A12,Base!$P$5:$P$440,"Sin certificar") -> 318556 | H12: =SUMIFS(Base!$H$5:$H$440,Base!$B$5:$B$440,$A12,Base!$P$5:$P$440,"Solo certificado") -> 0 | I12: =SUMIFS(Base!$H$5:$H$440,Base!$B$5:$B$440,$A12,Base!$P$5:$P$440,"Comprometido") -> 574426 | J12: =SUMIFS(Base!$H$5:$H$440,Base!$B$5:$B$440,$A12,Base!$P$5:$P$440,"Devengado total") -> 0 | K12: =SUMIFS(Base!$H$5:$H$440,Base!$B$5:$B$440,$A12,Base!$P$5:$P$440,"Sin PIM") -> 0
A13: TOTAL UE 001 | B13: =SUM(B5:B12) -> 436 | C13: =SUM(C5:C12) -> 905026984 | D13: =SUM(D5:D12) -> 8.4314313e+08 | E13: =SUM(E5:E12) -> 61883857 | F13: =SUM(F5:F12) -> 4.3357577e+08 | G13: =SUM(G5:G12) -> 13108238 | H13: =SUM(H5:H12) -> 40669280 | I13: =SUM(I5:I12) -> 851002020 | ... K13: =SUM(K5:K12) -> 0
A15: Definición provisional de Estado situacional (sujeta a mejora):
A16: Sin certificar: PIM > 0 y sin certificación → disponible.
A17: Solo certificado: con certificación y sin compromiso → posible.
A18: Comprometido: con compromiso anual → no disponible.
A19: Devengado total: devengado ≥ PIM.
A20: Sin PIM: PIM = 0 (categoría añadida para casos de borde).

Sheet Gerencia de Infraestructura
C1: ANEXO N° 01
B2: COMPORTAMIENTO DE EJECUCIÓN DE PROYECTOS DE INVERSION PUBLICA DEL AÑO FISCAL 2026 DE GERENCIAS REGIONALES Y UNIDADES EJECUTORAS · UE 001 · AL 06/10/2026
A4: N° | B4: META | C4: PROYECTO | D4: PIM 2026 (A) | E4: CERTIFICACIÓN (B) | F4: SALDO (A-B) | G4: DEVENGADO ( C ) | H4: SALDO (A-C) | I4: DEVEN % | J4: MODALIDAD DE EJECUCIÓN | K4: ESTADO SITUACIONAL PROYECTO | L4: Monto Año 2026 (S/) | M4: Monto Año 2027 (S/) | N4: Monto Año 2028 (S/) | O4: Monto Año 2029 (S/) | P4: BASE LEGAL
A6: GERENCIA DE INFRAESTRUCTURA | D6: =D7+D123+D152+D196 -> 770204814 | E6: =E7+E123+E152+E196 -> 7.2264955e+08 | F6: =F7+F123+F152+F196 -> 47555259 | G6: =G7+G123+G152+G196 -> 3.8172744e+08 | H6: =H7+H123+H152+H196 -> 3.8847738e+08 | I6: =IF(D6=0,0,G6/D6) -> 0.49561809
A7: EJECUCIÓN POR ADMINISTRACIÓN DIRECTA | D7: =D8+D79 -> 501856577 | E7: =E8+E79 -> 4.7258296e+08 | F7: =F8+F79 -> 29273617 | G7: =G8+G79 -> 2.5907445e+08 | H7: =H8+H79 -> 2.4278213e+08 | I7: =IF(D7=0,0,G7/D7) -> 0.51623205
A8: EJECUCIÓN POR ADMINISTRACIÓN DIRECTA - DIRECTIVA 10 | D8: =D9+D12+D39+D64+D74+D76 -> 234460254 | E8: =E9+E12+E39+E64+E74+E76 -> 2.2363717e+08 | F8: =F9+F12+F39+F64+F74+F76 -> 10823083 | G8: =G9+G12+G39+G64+G74+G76 -> 99970240 | H8: =H9+H12+H39+H64+H74+H76 -> 1.3449001e+08 | I8: =IF(D8=0,0,G8/D8) -> 0.42638459
A9: 20. SALUD | D9: =SUM(D10:D11) -> 53926751 | E9: =SUM(E10:E11) -> 53909348 | F9: =SUM(F10:F11) -> 17402.8 | G9: =SUM(G10:G11) -> 364124.26 | H9: =SUM(H10:H11) -> 53562627 | I9: =IF(D9=0,0,G9/D9) -> 0.006752201
A10: =SUBTOTAL(103,$B$6:B10) -> 1 | B10: 1 | C10: =Base!G5 -> 2108576: CONSTRUCCION DEL HOSPITAL MATERNO INFANTIL DEL CONO SUR JULIACA | D10: =Base!H5 -> 167354 | E10: =Base!I5 -> 149951.3 | F10: =D10-E10 -> 17402.7 | G10: =Base!K5 -> 102781.21 | H10: =D10-G10 -> 64572.79 | I10: =IF(D10=0,0,G10/D10) -> 0.61415449 | J10: =Base!O5 -> Administración directa / Laudos arbitrales | K10: =Base!P5 -> Comprometido | L10: =Base!Q5 -> 12460540 | M10: =Base!R5 -> 5731000 | N10: =Base!S5 -> 5000000 | O10: =Base!T5 -> 5000000 | P10: =IF(Base!U5="","",Base!U5)
A11: =SUBTOTAL(103,$B$6:B11) -> 2 | B11: 220 | C11: =Base!G6 -> 2279375: MEJORAMIENTO DE LOS SERVICIOS DE SALUD DEL HOSPITAL DE APOYO ILAVE, PROVINCIA DE EL COLLAO - REGION PUNO | D11: =Base!H6 -> 53759397 | E11: =Base!I6 -> 53759397 | F11: =D11-E11 -> 0.1 | G11: =Base!K6 -> 261343.05 | H11: =D11-G11 -> 53498054 | I11: =IF(D11=0,0,G11/D11) -> 0.0048613464 | J11: =Base!O6 -> Contrata / Expediente técnico / Administración directa / Laudos arbitrales | K11: =Base!P6 -> Comprometido | L11: =Base!Q6 -> No registrado en cartera | M11: =Base!R6 -> No registrado en cartera | N11: =Base!S6 -> No registrado en cartera | O11: =Base!T6 -> No registrado en cartera | P11: =IF(Base!U6="","",Base!U6)
A12: 22. EDUCACION | D12: =SUM(D13:D38) -> 60810433 | E12: =SUM(E13:E38) -> 57496092 | F12: =SUM(F13:F38) -> 3314341 | G12: =SUM(G13:G38) -> 35508320 | H12: =SUM(H13:H38) -> 25302113 | I12: =IF(D12=0,0,G12/D12) -> 0.58391822
A13: =SUBTOTAL(103,$B$6:B13) -> 3 | B13: 223 | C13: =Base!G7 -> 2323700: MEJORAMIENTO DEL SERVICIO EDUCATIVO DE LAS CARRERAS DE PRODUCCION, AUTOMOTRIZ, MINERIA, CONTABILIDAD, COMPUTACION, SECRETARIADO, ENFERMERIA, LABORATORIO CLINICO Y PROTESIS DENTAL DEL IST MANUEL NUÑEZ BUTRON, JULIACA, SAN ROMAN - PUNO | D13: =Base!H7 -> 10519577 | E13: =Base!I7 -> 10386241 | F13: =D13-E13 -> 133335.78 | G13: =Base!K7 -> 7596372.7 | H13: =D13-G13 -> 2923204.3 | I13: =IF(D13=0,0,G13/D13) -> 0.72211769 | J13: =Base!O7 -> Administración directa / Contrata / Personal/bienes/servicios | K13: =Base!P7 -> Comprometido | L13: =Base!Q7 -> 2546207 | M13: =Base!R7 -> 638376 | N13: =Base!S7 -> 2568939 | O13: =Base!T7 -> 0 | P13: =IF(Base!U7="","",Base!U7)
A14: =SUBTOTAL(103,$B$6:B14) -> 4 | B14: 224 | C14: =Base!G8 -> 2335880: MEJORAMIENTO DEL SERVICIO EDUCATIVO DE LAS CARRERAS DE CONTABILIDAD, ENFERMERIA TECNICA, COMPUTACION E INFORMATICA, INDUSTRIA ALIMENTARIA Y PRODUCCION AGROPECUARIA DEL ISEPA, PROVINCIA DE MELGAR - PUNO | D14: =Base!H8 -> 10208307 | E14: =Base!I8 -> 9968469.6 | F14: =D14-E14 -> 239837.38 | G14: =Base!K8 -> 6440724.5 | H14: =D14-G14 -> 3767582.5 | I14: =IF(D14=0,0,G14/D14) -> 0.63092974 | J14: =Base!O8 -> Administración directa / Equipamiento / Contrata / Personal/bienes/servicios | K14: =Base!P8 -> Comprometido | L14: =Base!Q8 -> 5597990 | M14: =Base!R8 -> 1254673 | N14: =Base!S8 -> 2493351 | O14: =Base!T8 -> 0 | P14: =IF(Base!U8="","",Base!U8)
A15: =SUBTOTAL(103,$B$6:B15) -> 5 | B15: 245 | C15: =Base!G9 -> 2521936: MEJORAMIENTO Y AMPLIACION DEL SERVICIO DE EDUCACION SUPERIOR TECNOLOGICA EN EL INSTITUTO SUPERIOR TECNOLOGICO PUBLICO DE MACUSANI DISTRITO DE MACUSANI - PROVINCIA DE CARABAYA - DEPARTAMENTO DE PUNO | D15: =Base!H9 -> 11203165 | E15: =Base!I9 -> 10889669 | F15: =D15-E15 -> 313496.41 | G15: =Base!K9 -> 6395813.3 | H15: =D15-G15 -> 4807351.7 | I15: =IF(D15=0,0,G15/D15) -> 0.57089343 | J15: =Base!O9 -> Administración directa / Equipamiento / Contrata / Personal/bienes/servicios | K15: =Base!P9 -> Comprometido | L15: =Base!Q9 -> 4902849 | M15: =Base!R9 -> 60001 | N15: =Base!S9 -> 2722594 | O15: =Base!T9 -> 0 | P15: =IF(Base!U9="","",Base!U9)
A16: =SUBTOTAL(103,$B$6:B16) -> 6 | B16: 29 | C16: =Base!G10 -> 2344324: MEJORAMIENTO DE LOS SERVICIOS EDUCATIVOS DE LA I.E.S. MANUEL GONZALES PRADA, CENTRO POBLADO DE ISANI - DISTRITO DE ZEPITA - PROVINCIA DE CHUCUITO - REGION PUNO | D16: =Base!H10 -> 2079431 | E16: =Base!I10 -> 1994037.5 | F16: =D16-E16 -> 85393.54 | G16: =Base!K10 -> 1946470.9 | H16: =D16-G16 -> 132960.06 | I16: =IF(D16=0,0,G16/D16) -> 0.9360594 | J16: =Base!O10 -> Administración directa / Equipamiento / Contrata / Personal/bienes/servicios | K16: =Base!P10 -> Comprometido | L16: =Base!Q10 -> 298669 | M16: =Base!R10 -> 349669 | N16: =Base!S10 -> 84977 | O16: =Base!T10 -> 0 | P16: =IF(Base!U10="","",Base!U10)
A17: =SUBTOTAL(103,$B$6:B17) -> 7 | B17: 315 | C17: =Base!G11 -> 2490075: MEJORAMIENTO DEL SERVICIO EDUCATIVO DEL NIVEL SECUNDARIA DE LA I.E. AGROPECUARIO SAN JUAN DEL ORO EN EL DISTRITO DE SAN JUAN DEL ORO - PROVINCIA DE SANDIA - DEPARTAMENTO DE PUNO | D17: =Base!H11 -> 1425006 | E17: =Base!I11 -> 1239788.9 | F17: =D17-E17 -> 185217.1 | G17: =Base!K11 -> 1170437 | H17: =D17-G17 -> 254569.02 | I17: =IF(D17=0,0,G17/D17) -> 0.82135583 | J17: =Base!O11 -> Administración directa / Equipamiento / Contrata / Personal/bienes/servicios | K17: =Base!P11 -> Comprometido | L17: =Base!Q11 -> 1122019 | M17: =Base!R11 -> 0 | N17: =Base!S11 -> 32869 | O17: =Base!T11 -> 0 | P17: =IF(Base!U11="","",Base!U11)
A18: =SUBTOTAL(103,$B$6:B18) -> 8 | B18: 160 | C18: =Base!G12 -> 2570978: MEJORAMIENTO DE LOS SERVICIOS DE EDUCACION SUPERIOR DEL INSTITUTO SUPERIOR TECNOLOGICO PUBLICA DE CABANILLAS DEL DISTRITO DE CABANILLAS - PROVINCIA DE SAN ROMAN - DEPARTAMENTO DE PUNO | D18: =Base!H12 -> 9222405 | E18: =Base!I12 -> 9003232.5 | F18: =D18-E18 -> 219172.47 | G18: =Base!K12 -> 5421356.6 | H18: =D18-G18 -> 3801048.4 | I18: =IF(D18=0,0,G18/D18) -> 0.58784629 | J18: =Base!O12 -> Administración directa / Equipamiento / Contrata / Personal/bienes/servicios | K18: =Base!P12 -> Comprometido | L18: =Base!Q12 -> 2595053 | M18: =Base!R12 -> 255676 | N18: =Base!S12 -> 1817178 | O18: =Base!T12 -> 0 | P18: =IF(Base!U12="","",Base!U12)
A19: =SUBTOTAL(103,$B$6:B19) -> 9 | B19: 162 | C19: =Base!G13 -> 2591926: MEJORAMIENTO SERVICIO DE EDUCACION SUPERIOR TECNOLOGICA EN EL INSTITUTO SUPERIOR TECNOLOGICO PUBLICO JOSE DOMINGO CHOQUEHUANCA DEL DISTRITO DE JOSE DOMINGO CHOQUEHUANCA DE LA PROVINCIA DE AZANGARO DEL DEPARTAMENTO DE PUNO | D19: =Base!H13 -> 5194033 | E19: =Base!I13 -> 5106124.8 | F19: =D19-E19 -> 87908.23 | G19: =Base!K13 -> 1941765.3 | H19: =D19-G19 -> 3252267.7 | I19: =IF(D19=0,0,G19/D19) -> 0.37384539 | J19: =Base!O13 -> Contrata / Personal/bienes/servicios | K19: =Base!P13 -> Comprometido | L19: =Base!Q13 -> 5194033 | M19: =Base!R13 -> 6569076 | N19: =Base!S13 -> 1 | O19: =Base!T13 -> 0 | P19: =IF(Base!U13="","",Base!U13)
A20: =SUBTOTAL(103,$B$6:B20) -> 10 | B20: 44 | C20: =Base!G14 -> 2629119.MEJORAMIENTO DEL SERVICIO DE EDUCACION SECUNDARIA EN I.E. ROSASPATA DE CENTRO POBLADO ROSASPATA DISTRITO DE ROSASPATA DE LA PROVINCIA DE HUANCANE DEL DEPARTAMENTO DE PUNO | D20: =Base!H14 -> 3656326 | E20: =Base!I14 -> 3383177.1 | F20: =D20-E20 -> 273148.9 | G20: =Base!K14 -> 2126125.4 | H20: =D20-G20 -> 1530200.6 | I20: =IF(D20=0,0,G20/D20) -> 0.58149229 | J20: =Base!O14 -> Administración directa / Contrata / Personal/bienes/servicios / Equipamiento | K20: =Base!P14 -> Comprometido | L20: =Base!Q14 -> 2278000 | M20: =Base!R14 -> 1683936 | N20: =Base!S14 -> 1459275 | O20: =Base!T14 -> 0 | P20: =IF(Base!U14="","",Base!U14)
A21: =SUBTOTAL(103,$B$6:B21) -> 11 | B21: 248 | C21: =Base!G15 -> 2539673: MEJORAMIENTO Y AMPLIACION DEL SERVICIO DE EDUCACION SUPERIOR TECNOLOGICA EN EL INSTITUTO SUPERIOR TECNOLOGICO PUBLICO DE JULI, DISTRITO DE JULI - PROVINCIA DE CHUCUITO - DEPARTAMENTO DE PUNO | D21: =Base!H15 -> 2000000 | E21: =Base!I15 -> 2000000 | F21: =D21-E21 -> 0 | G21: =Base!K15 -> 0 | H21: =D21-G21 -> 2000000 | I21: =IF(D21=0,0,G21/D21) -> 0 | J21: =Base!O15 -> Contrata | K21: =Base!P15 -> Solo certificado | L21: =Base!Q15 -> 12000000 | M21: =Base!R15 -> 14558623 | N21: =Base!S15 -> 14894208 | O21: =Base!T15 -> 10928387 | P21: =IF(Base!U15="","",Base!U15)
A22: =SUBTOTAL(103,$B$6:B22) -> 12 | B22: 45 | C22: =Base!G16 -> 2637985: MEJORAMIENTO DEL SERVICIO DE EDUCACION SECUNDARIA EN I.E. LLAULLI DE CENTRO POBLADO LLAULLI DISTRITO DE MOHO DE LA PROVINCIA DE MOHO DEL DEPARTAMENTO DE PUNO | D22: =Base!H16 -> 0 | E22: =Base!I16 -> 0 | F22: =D22-E22 -> 0 | G22: =Base!K16 -> 0 | H22: =D22-G22 -> 0 | I22: =IF(D22=0,0,G22/D22) -> 0 | J22: =Base!O16 -> Contrata | K22: =Base!P16 -> Sin PIM | L22: =Base!Q16 -> 100000 | M22: =Base!R16 -> 1234564 | N22: =Base!S16 -> 0 | O22: =Base!T16 -> 3335545 | P22: =IF(Base!U16="","",Base!U16)
A23: =SUBTOTAL(103,$B$6:B23) -> 13 | B23: 193 | C23: =Base!G17 -> 2664940: MEJORAMIENTO DEL SERVICIO DE EDUCACION INICIAL EN I.E. 1099 INMACULADA DISTRITO DE PUTINA DE LA PROVINCIA DE SAN ANTONIO DE PUTINA DEL DEPARTAMENTO DE PUNO | D23: =Base!H17 -> 1861270 | E23: =Base!I17 -> 1466941.4 | F23: =D23-E23 -> 394328.59 | G23: =Base!K17 -> 1164545.4 | H23: =D23-G23 -> 696724.63 | I23: =IF(D23=0,0,G23/D23) -> 0.62567245 | J23: =Base!O17 -> Administración directa / Contrata / Expediente técnico / Equipamiento / Personal/bienes/servicios | K23: =Base!P17 -> Comprometido | L23: =Base!Q17 -> 1410000 | M23: =Base!R17 -> 833474 | N23: =Base!S17 -> 0 | O23: =Base!T17 -> 0 | P23: =IF(Base!U17="","",Base!U17)
A24: =SUBTOTAL(103,$B$6:B24) -> 14 | B24: 46 | C24: =Base!G18 -> 2637997: MEJORAMIENTO DEL SERVICIO DE EDUCACION SECUNDARIA EN I.E. UMUCHI DISTRITO DE MOHO DE LA PROVINCIA DE MOHO DEL DEPARTAMENTO DE PUNO | D24: =Base!H18 -> 304829 | E24: =Base!I18 -> 0 | F24: =D24-E24 -> 304829 | G24: =Base!K18 -> 0 | H24: =D24-G24 -> 304829 | I24: =IF(D24=0,0,G24/D24) -> 0 | J24: =Base!O18 -> Contrata | K24: =Base!P18 -> Sin certificar | L24: =Base!Q18 -> 100000 | M24: =Base!R18 -> 0 | N24: =Base!S18 -> 0 | O24: =Base!T18 -> 4317457 | P24: =IF(Base!U18="","",Base!U18)
... A38: =SUBTOTAL(103,$B$6:B38) -> 28 | B38: 37 | C38: =Base!G32 -> 2467893: MEJORAMIENTO DEL SERVICIO EDUCATIVO DEL NIVEL SECUNDARIA DE LA I.E.S. TARACO DEL DISTRITO DE TARACO - PROVINCIA DE HUANCANE - DEPARTAMENTO DE PUNO | D38: =Base!H32 -> 50132 | E38: =Base!I32 -> 47450.05 | F38: =D38-E38 -> 2681.95 | G38: =Base!K32 -> 47450.05 | H38: =D38-G38 -> 2681.95 | I38: =IF(D38=0,0,G38/D38) -> 0.94650223 | J38: =Base!O32 -> Contrata | K38: =Base!P32 -> Comprometido | L38: =Base!Q32 -> 175369 | M38: =Base!R32 -> 79091 | N38: =Base!S32 -> 583672 | O38: =Base!T32 -> 0 | P38: =IF(Base!U32="","",Base!U32)
A39: 15. TRANSPORTE | D39: =SUM(D40:D63) -> 87794613 | E39: =SUM(E40:E63) -> 83882331 | F39: =SUM(F40:F63) -> 3912282.3 | G39: =SUM(G40:G63) -> 50834366 | H39: =SUM(H40:H63) -> 36960247 | I39: =IF(D39=0,0,G39/D39) -> 0.57901463
A40: =SUBTOTAL(103,$B$6:B40) -> 29 | B40: 95 | C40: =Base!G33 -> 2194702: MEJORAMIENTO DE LA CARRETERA (PU 675) POMATA - YOROHOCO, PROVINCIA DE CHUCUITO - PUNO | D40: =Base!H33 -> 18401182 | E40: =Base!I33 -> 17764558 | F40: =D40-E40 -> 636624.07 | G40: =Base!K33 -> 15484260 | H40: =D40-G40 -> 2916922.1 | I40: =IF(D40=0,0,G40/D40) -> 0.84148181 | J40: =Base!O33 -> Administración directa / Contrata / Personal/bienes/servicios | K40: =Base!P33 -> Comprometido | L40: =Base!Q33 -> 9922902 | M40: =Base!R33 -> 180000 | N40: =Base!S33 -> 0 | O40: =Base!T33 -> 0 | P40: =IF(Base!U33="","",Base!U33)
A41: =SUBTOTAL(103,$B$6:B41) -> 30 | B41: 98 | C41: =Base!G34 -> 2287700: MEJORAMIENTO DE LA CARRETERA PU N-110: EMP. PE-34I ASIRUNI - ROSASPATA - HUAYRAPATA - EMP. PE-34I NINANTAYA, DISTRITOS DE VILQUECHICO-ROSASPATA-MOHO-HUAYRAPATA, PROVINCIA DE HUANCANE Y MOHO - PUNO | D41: =Base!H34 -> 10002053 | E41: =Base!I34 -> 9636351.5 | F41: =D41-E41 -> 365701.52 | G41: =Base!K34 -> 5473965.1 | H41: =D41-G41 -> 4528087.9 | I41: =IF(D41=0,0,G41/D41) -> 0.54728415 | J41: =Base!O34 -> Administración directa / Contrata / Personal/bienes/servicios | K41: =Base!P34 -> Comprometido | L41: =Base!Q34 -> 4289351 | M41: =Base!R34 -> 500000 | N41: =Base!S34 -> 109570 | O41: =Base!T34 -> 0 | P41: =IF(Base!U34="","",Base!U34)
A42: =SUBTOTAL(103,$B$6:B42) -> 31 | B42: 112 | C42: =Base!G35 -> 2480499: MEJORAMIENTO DE LA CARRETERA PU 146; EMP PE - 34 I (HUANCANE) - HUERTAPATA - VISCACHANI - QUELLAHUYO - EMP PE - 34 (CACUÑA), DISTRITO DE HUANCANE - PROVINCIA DE HUANCANE - DEPARTAMENTO DE PUNO | D42: =Base!H35 -> 3297813 | E42: =Base!I35 -> 3286650.5 | F42: =D42-E42 -> 11162.55 | G42: =Base!K35 -> 3269277.3 | H42: =D42-G42 -> 28535.72 | I42: =IF(D42=0,0,G42/D42) -> 0.99134708 | J42: =Base!O35 -> Administración directa / Contrata | K42: =Base!P35 -> Comprometido | L42: =Base!Q35 -> 5406629 | M42: =Base!R35 -> 0 | N42: =Base!S35 -> 304959 | O42: =Base!T35 -> 0 | P42: =IF(Base!U35="","",Base!U35)
A43: =SUBTOTAL(103,$B$6:B43) -> 32 | B43: 99 | C43: =Base!G36 -> 2300575: MEJORAMIENTO DE LA AVENIDA CIRCUNVALACION II (EMP. PE- 3S-AV. HUANCANE-CIRCUNVALACION ESTE-EMP PE-3S) DE LA CIUDAD DE JULIACA- EMPALME PU-3S INICIO CON CIRCUNVALACION II - DISTRITO DE SAN MIGUEL - EMPALME PU-3S FINAL CON CIRCUNVALACION II - DISTRITO DE CARACOTO - PROVINCIA DE SAN ROMAN - REGION PUNO | D43: =Base!H36 -> 2394023 | E43: =Base!I36 -> 2316938.8 | F43: =D43-E43 -> 77084.21 | G43: =Base!K36 -> 1138698.8 | H43: =D43-G43 -> 1255324.2 | I43: =IF(D43=0,0,G43/D43) -> 0.4756424 | J43: =Base!O36 -> Administración directa / Contrata / Personal/bienes/servicios | K43: =Base!P36 -> Comprometido | L43: =Base!Q36 -> 3545977 | M43: =Base!R36 -> 1000000 | N43: =Base!S36 -> 3651450 | O43: =Base!T36 -> 1489826 | P43: =IF(Base!U36="","",Base!U36)
A44: =SUBTOTAL(103,$B$6:B44) -> 33 | B44: 87 | C44: =Base!G37 -> 2031310: CONSTRUCCION Y MEJORAMIENTO DE LA CARRETERA SAN JOSE (EMP. R 100) VALLE GRANDE -ISILLUMA DEL DISTRITO DE ALTO INAMBARI | D44: =Base!H37 -> 1122559 | E44: =Base!I37 -> 1117871.1 | F44: =D44-E44 -> 4687.95 | G44: =Base!K37 -> 1042098.6 | H44: =D44-G44 -> 80460.44 | I44: =IF(D44=0,0,G44/D44) -> 0.92832409 | J44: =Base!O37 -> Administración directa / Contrata / Personal/bienes/servicios | K44: =Base!P37 -> Comprometido | L44: =Base!Q37 -> 1404195 | M44: =Base!R37 -> 324567 | N44: =Base!S37 -> 0 | O44: =Base!T37 -> 936265 | P44: =IF(Base!U37="","",Base!U37)
A45: =SUBTOTAL(103,$B$6:B45) -> 34 | B45: 92 | C45: =Base!G38 -> 2163760: MEJORAMIENTO DE LA INFRAESTRUCTURA VIAL TURISTICO, TRAMO PHUTINI - JAYU JAYU, DISTRITO DE ACORA - PUNO - PUNO | D45: =Base!H38 -> 1202934 | E45: =Base!I38 -> 1151623.8 | F45: =D45-E45 -> 51310.21 | G45: =Base!K38 -> 1105100.4 | H45: =D45-G45 -> 97833.58 | I45: =IF(D45=0,0,G45/D45) -> 0.91867087 | J45: =Base!O38 -> Administración directa / Contrata / Personal/bienes/servicios | K45: =Base!P38 -> Comprometido | L45: =Base!Q38 -> 2596051 | M45: =Base!R38 -> 120000 | N45: =Base!S38 -> 2215461 | O45: =Base!T38 -> 3675255 | P45: =IF(Base!U38="","",Base!U38)
A46: =SUBTOTAL(103,$B$6:B46) -> 35 | B46: 104 | C46: =Base!G39 -> 2375549: CREACION DE LA INFRAESTRUCTURA DE INTEGRACION VIAL ENTRE SANDIA (CP. QUENEQUE) Y PATAMBUCO (C.P. TIRACA), DISTRITO DE SANDIA Y PATAMBUCO, PROVINCIA DE SANDIA - PUNO | D46: =Base!H39 -> 167638 | E46: =Base!I39 -> 167637.03 | F46: =D46-E46 -> 0.97 | G46: =Base!K39 -> 124800.07 | H46: =D46-G46 -> 42837.93 | I46: =IF(D46=0,0,G46/D46) -> 0.7444617 | J46: =Base!O39 -> Administración directa | K46: =Base!P39 -> Comprometido | L46: =Base!Q39 -> 1200000 | M46: =Base!R39 -> 2500000 | N46: =Base!S39 -> 2882362 | O46: =Base!T39 -> 1526602 | P46: =IF(Base!U39="","",Base!U39)
A47: =SUBTOTAL(103,$B$6:B47) -> 36 | B47: 101 | C47: =Base!G40 -> 2321290: MEJORAMIENTO DE LOS SERVICIOS DE TRANSITABILIDAD DE LA VIA VECINAL PU-595: DV. PAMPA BLANCA - RINCONADA - CERRO LUNAR, DISTRITO DE ANANEA, PROVINCIA DE SAN ANTONIO DE PUTINA - PUNO | D47: =Base!H40 -> 844818 | E47: =Base!I40 -> 75387.03 | F47: =D47-E47 -> 769430.97 | G47: =Base!K40 -> 75387.03 | H47: =D47-G47 -> 769430.97 | I47: =IF(D47=0,0,G47/D47) -> 0.08923464 | J47: =Base!O40 -> Contrata / Laudos arbitrales / Personal/bienes/servicios | K47: =Base!P40 -> Comprometido | L47: =Base!Q40 -> 1050000 | M47: =Base!R40 -> 50000 | N47: =Base!S40 -> 1054806 | O47: =Base!T40 -> 0 | P47: =IF(Base!U40="","",Base!U40)
A48: =SUBTOTAL(103,$B$6:B48) -> 37 | B48: 166 | C48: =Base!G41 -> 2475053: MEJORAMIENTO DEL SERVICIO DE MOVILIDAD URBANA DE LA AV. ANDRES AVELINO CACERES (TRAMO: AV. TUPAC YUPANQUI - AV. AVIACION), AV. LOS GERANIOS DEL DISTRITO DE JULIACA - PROVINCIA DE SAN ROMAN - DEPARTAMENTO DE PUNO | D48: =Base!H41 -> 0 | E48: =Base!I41 -> 0 | F48: =D48-E48 -> 0 | G48: =Base!K41 -> 0 | H48: =D48-G48 -> 0 | I48: =IF(D48=0,0,G48/D48) -> 0 | J48: =Base!O41 -> Administración directa | K48: =Base!P41 -> Sin PIM | L48: =Base!Q41 -> 675842 | M48: =Base!R41 -> 110000 | N48: =Base!S41 -> 0 | O48: =Base!T41 -> 0 | P48: =IF(Base!U41="","",Base!U41)
A49: =SUBTOTAL(103,$B$6:B49) -> 38 | B49: 90 | C49: =Base!G42 -> 2131661: CONSTRUCCION Y MEJORAMIENTO DE LA CARRETERA DESVIO VILQUECHICO-COJATA-SINA-YANAHUAYA | D49: =Base!H42 -> 459851 | E49: =Base!I42 -> 344060.18 | F49: =D49-E49 -> 115790.82 | G49: =Base!K42 -> 300345.76 | H49: =D49-G49 -> 159505.24 | I49: =IF(D49=0,0,G49/D49) -> 0.65313712 | J49: =Base!O42 -> Administración directa / Equipamiento | K49: =Base!P42 -> Comprometido | L49: =Base!Q42 -> 4800690 | M49: =Base!R42 -> 4000000 | N49: =Base!S42 -> 14883202 | O49: =Base!T42 -> 19038629 | P49: =IF(Base!U42="","",Base!U42)
A50: =SUBTOTAL(103,$B$6:B50) -> 39 | B50: 96 | C50: =Base!G43 -> 2195487: MEJORAMIENTO DEL CAMINO VECINAL (EMP. PE 3S) HUAQUINA ZAPIJICANE - PTO JULI - CHUCASUYO DEL DISTRITO DE JULI - PROVINCIA DE CHUCUITO - DEPARTAMENTO DE PUNO | D50: =Base!H43 -> 91759 | E50: =Base!I43 -> 91758.5 | F50: =D50-E50 -> 0.5 | G50: =Base!K43 -> 82094.58 | H50: =D50-G50 -> 9664.42 | I50: =IF(D50=0,0,G50/D50) -> 0.89467605 | J50: =Base!O43 -> Contrata / Administración directa / Personal/bienes/servicios | K50: =Base!P43 -> Comprometido | L50: =Base!Q43 -> 774665 | M50: =Base!R43 -> 0 | N50: =Base!S43 -> 707599 | O50: =Base!T43 -> 0 | P50: =IF(Base!U43="","",Base!U43)
A51: =SUBTOTAL(103,$B$6:B51) -> 40 | B51: 113 | C51: =Base!G44 -> 2514428: CREACION DEL SERVICIO DE INTERCONEXION DE MOVILIDAD URBANA EN LA VIA TRONCAL DEL PUENTE YARAJA DISTRITO DE AZANGARO - PROVINCIA DE AZANGARO - DEPARTAMENTO DE PUNO | D51: =Base!H44 -> 104124 | E51: =Base!I44 -> 48234.88 | F51: =D51-E51 -> 55889.12 | G51: =Base!K44 -> 48234.88 | H51: =D51-G51 -> 55889.12 | I51: =IF(D51=0,0,G51/D51) -> 0.46324459 | J51: =Base!O44 -> Administración directa / Contrata / Personal/bienes/servicios | K51: =Base!P44 -> Comprometido | L51: =Base!Q44 -> 228677 | M51: =Base!R44 -> 0 | N51: =Base!S44 -> 0 | O51: =Base!T44 -> 865181 | P51: =IF(Base!U44="","",Base!U44)
... A63: =SUBTOTAL(103,$B$6:B63) -> 52 | B63: 108 | C63: =Base!G56 -> 2443679: MEJORAMIENTO DEL SERVICIO DE TRANSITABILIDAD VEHICULAR DE LA CARRETERA TRAMO I: EMP- 34L (COJATA) - HUANCASAYA, TRAMO II: HUANCASAYA - TARUCANI-EMP-PU-115 (INCHUPALLA), DEL DISTRITO DE COJATA - PROVINCIA DE HUANCANE - DEPARTAMENTO DE PUNO | D63: =Base!H56 -> 0 | E63: =Base!I56 -> 0 | F63: =D63-E63 -> 0 | G63: =Base!K56 -> 0 | H63: =D63-G63 -> 0 | I63: =IF(D63=0,0,G63/D63) -> 0 | J63: =Base!O56 -> Contrata | K63: =Base!P56 -> Sin PIM | L63: =Base!Q56 -> 800000 | M63: =Base!R56 -> 2345478 | N63: =Base!S56 -> 9005306 | O63: =Base!T56 -> 19493721 | P63: =IF(Base!U56="","",Base!U56)
A64: 21. CULTURA Y DEPORTE | D64: =SUM(D65:D73) -> 24086616 | E64: =SUM(E65:E73) -> 20655001 | F64: =SUM(F65:F73) -> 3431614.6 | G64: =SUM(G65:G73) -> 5596985.4 | H64: =SUM(H65:H73) -> 18489631 | I64: =IF(D64=0,0,G64/D64) -> 0.2323691
A65: =SUBTOTAL(103,$B$6:B65) -> 53 | B65: 217 | C65: =Base!G57 -> 2163853: MEJORAMIENTO DEL ESTADIO MUNICIPAL CESAR RAUL CARRERA DEL DISTRITO DE AZANGARO, PROVINCIA DE AZANGARO - PUNO | D65: =Base!H57 -> 5810277 | E65: =Base!I57 -> 5204423.6 | F65: =D65-E65 -> 605853.4 | G65: =Base!K57 -> 1157372.6 | H65: =D65-G65 -> 4652904.4 | I65: =IF(D65=0,0,G65/D65) -> 0.19919405 | J65: =Base!O57 -> Administración directa / Contrata / Personal/bienes/servicios | K65: =Base!P57 -> Comprometido | L65: =Base!Q57 -> 6269000 | M65: =Base!R57 -> 1345765 | N65: =Base!S57 -> 5566267 | O65: =Base!T57 -> 0 | P65: =IF(Base!U57="","",Base!U57)
A66: =SUBTOTAL(103,$B$6:B66) -> 54 | B66: 63 | C66: =Base!G58 -> 2188542: MEJORAMIENTO DE LA CAPACIDAD DE PRESTACION DE SERVICIOS DEPORTIVOS EN EL ESTADIO GUILLERMO BRICEÑO ROSAMEDINA DE LA CIUDAD DE JULIACA, PROVINCIA DE SAN ROMAN - PUNO | D66: =Base!H58 -> 5921783 | E66: =Base!I58 -> 5612635.5 | F66: =D66-E66 -> 309147.48 | G66: =Base!K58 -> 1271806.7 | H66: =D66-G66 -> 4649976.3 | I66: =IF(D66=0,0,G66/D66) -> 0.21476753 | J66: =Base!O58 -> Administración directa / Equipamiento / Contrata / Laudos arbitrales / Personal/bienes/servicios | K66: =Base!P58 -> Comprometido | L66: =Base!Q58 -> 1139986 | M66: =Base!R58 -> 500000 | N66: =Base!S58 -> 3220643 | O66: =Base!T58 -> 0 | P66: =IF(Base!U58="","",Base!U58)
A67: =SUBTOTAL(103,$B$6:B67) -> 55 | B67: 62 | C67: =Base!G59 -> 2186641: MEJORAMIENTO DEL SERVICIO DEPORTIVO, CULTURAL Y RECREACIONAL EN LA CAPITAL DE LA REGION PUNO | D67: =Base!H59 -> 1180793 | E67: =Base!I59 -> 1110291.7 | F67: =D67-E67 -> 70501.27 | G67: =Base!K59 -> 1081390.3 | H67: =D67-G67 -> 99402.73 | I67: =IF(D67=0,0,G67/D67) -> 0.91581697 | J67: =Base!O59 -> Administración directa | K67: =Base!P59 -> Comprometido | L67: =Base!Q59 -> 11675669 | M67: =Base!R59 -> 6000000 | N67: =Base!S59 -> 6503691 | O67: =Base!T59 -> 7526858 | P67: =IF(Base!U59="","",Base!U59)
A68: =SUBTOTAL(103,$B$6:B68) -> 56 | B68: 72 | C68: =Base!G60 -> 2646100: CONSTRUCCION DE CAMPO DEPORTIVO Y SERVICIOS HIGIENICOS Y/O VESTIDORES PARA PERSONAL; REPARACION DE TRIBUNA Y/O PALCO; EN EL(LA) ESTADIO MUNICIPAL DE SAN PEDRO DE PUTINA PUNCO DISTRITO DE SAN PEDRO DE PUTINA PUNCO, PROVINCIA SANDIA, DEPARTAMENTO PUNO | D68: =Base!H60 -> 2167000 | E68: =Base!I60 -> 1860545 | F68: =D68-E68 -> 306455 | G68: =Base!K60 -> 33059.94 | H68: =D68-G68 -> 2133940.1 | I68: =IF(D68=0,0,G68/D68) -> 0.015256087 | J68: =Base!O60 -> Contrata / Personal/bienes/servicios | K68: =Base!P60 -> Comprometido | L68: =Base!Q60 -> 2000000 | M68: =Base!R60 -> 1547463 | N68: =Base!S60 -> 0 | O68: =Base!T60 -> 0 | P68: =IF(Base!U60="","",Base!U60)
A69: =SUBTOTAL(103,$B$6:B69) -> 57 | B69: 67 | C69: =Base!G61 -> 2645380: CONSTRUCCION DE TRIBUNA Y/O PALCO, CAMPO DEPORTIVO Y PISTA DE ATLETISMO (DEPORTE RECREATIVO); REPARACION DE SERVICIOS HIGIENICOS Y/O VESTIDORES; ADEMAS DE OTROS ACTIVOS EN EL(LA) ESTADIO MUNICIPAL FERNANDO ROMERO CARREON DISTRITO DE LAMPA, PROVINCIA LAMPA, DEPARTAMENTO PUNO | D69: =Base!H61 -> 2575916 | E69: =Base!I61 -> 2503779 | F69: =D69-E69 -> 72137 | G69: =Base!K61 -> 23527.19 | H69: =D69-G69 -> 2552388.8 | I69: =IF(D69=0,0,G69/D69) -> 0.0091335238 | J69: =Base!O61 -> Contrata / Personal/bienes/servicios | K69: =Base!P61 -> Comprometido | L69: =Base!Q61 -> 2575916 | M69: =Base!R61 -> 2345678 | N69: =Base!S61 -> 1558799 | O69: =Base!T61 -> 0 | P69: =IF(Base!U61="","",Base!U61)
A70: =SUBTOTAL(103,$B$6:B70) -> 58 | B70: 71 | C70: =Base!G62 -> 2646096: CONSTRUCCION DE TRIBUNA Y/O PALCO; REPARACION DE TRIBUNA Y/O PALCO Y CAMPO DEPORTIVO; EN EL(LA) ESTADIO JOSE CARLOS MARIATEGUI DISTRITO DE YUNGUYO, PROVINCIA YUNGUYO, DEPARTAMENTO PUNO | D70: =Base!H62 -> 2054253 | E70: =Base!I62 -> 1854253 | F70: =D70-E70 -> 200000 | G70: =Base!K62 -> 0 | H70: =D70-G70 -> 2054253 | I70: =IF(D70=0,0,G70/D70) -> 0 | J70: =Base!O62 -> Contrata | K70: =Base!P62 -> Solo certificado | L70: =Base!Q62 -> 2054253 | M70: =Base!R62 -> 2546789 | N70: =Base!S62 -> 0 | O70: =Base!T62 -> 0 | P70: =IF(Base!U62="","",Base!U62)
A71: =SUBTOTAL(103,$B$6:B71) -> 59 | B71: 65 | C71: =Base!G63 -> 2645340: REPARACION DE TRIBUNA Y/O PALCO Y SERVICIOS HIGIENICOS Y/O VESTIDORES; CONSTRUCCION DE CAMPO DEPORTIVO; EN EL(LA) ESTADIO MUNICIPAL CRUCERO DISTRITO DE CRUCERO, PROVINCIA CARABAYA, DEPARTAMENTO PUNO | D71: =Base!H63 -> 2038388 | E71: =Base!I63 -> 2031210.5 | F71: =D71-E71 -> 7177.5 | G71: =Base!K63 -> 1711781.1 | H71: =D71-G71 -> 326606.88 | I71: =IF(D71=0,0,G71/D71) -> 0.83977198 | J71: =Base!O63 -> Contrata / Personal/bienes/servicios | K71: =Base!P63 -> Comprometido | L71: =Base!Q63 -> 2028388 | M71: =Base!R63 -> 2258011 | N71: =Base!S63 -> 0 | O71: =Base!T63 -> 0 | P71: =IF(Base!U63="","",Base!U63)
A72: =SUBTOTAL(103,$B$6:B72) -> 60 | B72: 252 | C72: =Base!G64 -> 2555837: REPARACION DE CAMPO DEPORTIVO; ADQUISICION DE EQUIPO NO DEPORTIVO PARA INSTALACIONES DEPORTIVAS; EN EL(LA) ESTADIO ENRIQUE TORRES BELON DISTRITO DE PUNO, PROVINCIA PUNO, DEPARTAMENTO PUNO | D72: =Base!H64 -> 2047936 | E72: =Base!I64 -> 377863 | F72: =D72-E72 -> 1670073 | G72: =Base!K64 -> 318047.53 | H72: =D72-G72 -> 1729888.5 | I72: =IF(D72=0,0,G72/D72) -> 0.1553015 | J72: =Base!O64 -> Contrata / Personal/bienes/servicios | K72: =Base!P64 -> Comprometido | L72: =Base!Q64 -> 327863 | M72: =Base!R64 -> 1876545 | N72: =Base!S64 -> 0 | O72: =Base!T64 -> 0 | P72: =IF(Base!U64="","",Base!U64)
A73: =SUBTOTAL(103,$B$6:B73) -> 61 | B73: 260 | C73: =Base!G65 -> 2593683: REPARACION DE PISTA DE ATLETISMO (COMPETENCIA); ADQUISICION DE TORRE DE ILUMINACION; EN EL(LA) ESTADIO ENRIQUE TORRES BELON DEL DISTRITO DE PUNO, PROVINCIA PUNO, DEPARTAMENTO PUNO | D73: =Base!H65 -> 290270 | E73: =Base!I65 -> 100000 | F73: =D73-E73 -> 190270 | G73: =Base!K65 -> 0 | H73: =D73-G73 -> 290270 | I73: =IF(D73=0,0,G73/D73) -> 0 | J73: =Base!O65 -> Contrata | K73: =Base!P65 -> Solo certificado | L73: =Base!Q65 -> 100000 | M73: =Base!R65 -> 2089685 | N73: =Base!S65 -> 3000000 | O73: =Base!T65 -> 11639950 | P73: =IF(Base!U65="","",Base!U65)
A74: 03. PLANEAMIENTO, GESTION Y RESERVA DE CONTINGENCIA | D74: =SUM(D75) -> 7609099 | E74: =SUM(E75) -> 7595390.9 | F74: =SUM(F75) -> 13708.12 | G74: =SUM(G75) -> 7570246.4 | H74: =SUM(H75) -> 38852.61 | I74: =IF(D74=0,0,G74/D74) -> 0.99489393
A75: =SUBTOTAL(103,$B$6:B75) -> 62 | B75: 259 | C75: =Base!G66 -> 2592407: MEJORAMIENTO DE LOS SERVICIOS OPERATIVOS O MISIONALES INSTITUCIONALES EN LA OFICINA DE EQUIPO MECANICO DEL GOBIERNO REGIONAL PUNO DISTRITO DE PUNO DE LA PROVINCIA DE PUNO DEL DEPARTAMENTO DE PUNO | D75: =Base!H66 -> 7609099 | E75: =Base!I66 -> 7595390.9 | F75: =D75-E75 -> 13708.12 | G75: =Base!K66 -> 7570246.4 | H75: =D75-G75 -> 38852.61 | I75: =IF(D75=0,0,G75/D75) -> 0.99489393 | J75: =Base!O66 -> Equipamiento / Contrata / Personal/bienes/servicios | K75: =Base!P66 -> Comprometido | L75: =Base!Q66 -> 6185000 | M75: =Base!R66 -> 1000000 | N75: =Base!S66 -> 0 | O75: =Base!T66 -> 1000000 | P75: =IF(Base!U66="","",Base!U66)
A76: 23. PROTECCION SOCIAL | D76: =SUM(D77:D78) -> 232742 | E76: =SUM(E77:E78) -> 99007.59 | F76: =SUM(F77:F78) -> 133734.41 | G76: =SUM(G77:G78) -> 96198.77 | H76: =SUM(H77:H78) -> 136543.23 | I76: =IF(D76=0,0,G76/D76) -> 0.41332793
A77: =SUBTOTAL(103,$B$6:B77) -> 63 | B77: 456 | C77: =Base!G67 -> 2230752: MEJORAMIENTO DE LOS SERVICIOS ASISTENCIALES DE LA ALDEA INFANTIL VIRGEN DE LA CANDELARIA EN EL BARRIO LA RINCONADA DEL CENTRO POBLADO DE SALCEDO, DISTRITO DE PUNO, PROVINCIA DE PUNO, REGION DE PUNO | D77: =Base!H67 -> 99230 | E77: =Base!I67 -> 99007.59 | F77: =D77-E77 -> 222.41 | G77: =Base!K67 -> 96198.77 | H77: =D77-G77 -> 3031.23 | I77: =IF(D77=0,0,G77/D77) -> 0.96945248 | J77: =Base!O67 -> Administración directa / Contrata / Personal/bienes/servicios | K77: =Base!P67 -> Comprometido | L77: =Base!Q67 -> 99230 | M77: =Base!R67 -> 0 | N77: =Base!S67 -> 0 | O77: =Base!T67 -> 0 | P77: =IF(Base!U67="","",Base!U67)
A78: =SUBTOTAL(103,$B$6:B78) -> 64 | B78: 458 | C78: =Base!G68 -> 2194989: MEJORAMIENTO DE LOS SERVICIOS EDUCATIVOS EN LA INSTITUCION EDUCATIVA SECUNDARIA DANTE NAVA DEL CENTRO POBLADO SANTA CRUZ DE PUNA AYLLU, DISTRITO DE PATAMBUCO, PROVINCIA DE SANDIA, REGION PUNO | D78: =Base!H68 -> 133512 | E78: =Base!I68 -> 0 | F78: =D78-E78 -> 133512 | G78: =Base!K68 -> 0 | H78: =D78-G78 -> 133512 | I78: =IF(D78=0,0,G78/D78) -> 0 | J78: =Base!O68 -> Administración directa | K78: =Base!P68 -> Sin certificar | L78: =Base!Q68 -> No registrado en cartera | M78: =Base!R68 -> No registrado en cartera | N78: =Base!S68 -> No registrado en cartera | O78: =Base!T68 -> No registrado en cartera | P78: =IF(Base!U68="","",Base!U68)
A79: EJECUCIÓN POR ADMINISTRACIÓN DIRECTA - DIRECTIVA 17 | D79: =D80+D87+D108+D119 -> 267396323 | E79: =E80+E87+E108+E119 -> 2.4894579e+08 | F79: =F80+F87+F108+F119 -> 18450534 | G79: =G80+G87+G108+G119 -> 1.5910421e+08 | H79: =H80+H87+H108+H119 -> 1.0829211e+08 | I79: =IF(D79=0,0,G79/D79) -> 0.59501271
A80: 20. SALUD | D80: =SUM(D81:D86) -> 32634907 | E80: =SUM(E81:E86) -> 31001164 | F80: =SUM(F81:F86) -> 1633743.5 | G80: =SUM(G81:G86) -> 13051954 | H80: =SUM(H81:H86) -> 19582953 | I80: =IF(D80=0,0,G80/D80) -> 0.39993844
A81: =SUBTOTAL(103,$B$6:B81) -> 65 | B81: 242 | C81: =Base!G69 -> 2504553: MEJORAMIENTO DEL SERVICIO DE SALUD EN EL CENTRO DE SALUD YANAPATA DE LA MICRO RED COPANI, RED DE SALUD YUNGUYO, DISTRITO DE YUNGUYO - PROVINCIA DE YUNGUYO - DEPARTAMENTO DE PUNO | D81: =Base!H69 -> 8256172 | E81: =Base!I69 -> 7527846.9 | F81: =D81-E81 -> 728325.09 | G81: =Base!K69 -> 4485721.8 | H81: =D81-G81 -> 3770450.2 | I81: =IF(D81=0,0,G81/D81) -> 0.54331739 | J81: =Base!O69 -> Administración directa / Equipamiento / Contrata / Personal/bienes/servicios | K81: =Base!P69 -> Comprometido | L81: =Base!Q69 -> 9468125 | M81: =Base!R69 -> 933429 | N81: =Base!S69 -> 6042788 | O81: =Base!T69 -> 2500000 | P81: =IF(Base!U69="","",Base!U69)
A82: =SUBTOTAL(103,$B$6:B82) -> 66 | B82: 237 | C82: =Base!G70 -> 2470517: MEJORAMIENTO DE LOS SERVICIOS DE SALUD DEL CENTRO DE SALUD COPANI DE LA MICRO RED COPANI, RED DE SALUD YUNGUYO, DISTRITO DE COPANI - PROVINCIA DE YUNGUYO - DEPARTAMENTO DE PUNO | D82: =Base!H70 -> 7374992 | E82: =Base!I70 -> 7374802 | F82: =D82-E82 -> 190 | G82: =Base!K70 -> 0 | H82: =D82-G82 -> 7374992 | I82: =IF(D82=0,0,G82/D82) -> 0 | J82: =Base!O70 -> Contrata | K82: =Base!P70 -> Solo certificado | L82: =Base!Q70 -> 8000000 | M82: =Base!R70 -> 8258658 | N82: =Base!S70 -> 10741348 | O82: =Base!T70 -> 1075057 | P82: =IF(Base!U70="","",Base!U70)
A83: =SUBTOTAL(103,$B$6:B83) -> 67 | B83: 228 | C83: =Base!G71 -> 2357092: MEJORAMIENTO DE LA CAPACIDAD RESOLUTIVA DEL CENTRO DE SALUD COJATA I-4, DE LA MICRO RED COJATA, RED DE SALUD HUANCANE, DIRESA PUNO, DISTRITO DE COJATA - PROVINCIA DE HUANCANE - DEPARTAMENTO DE PUNO | D83: =Base!H71 -> 6997430 | E83: =Base!I71 -> 6787158.8 | F83: =D83-E83 -> 210271.19 | G83: =Base!K71 -> 2630352.4 | H83: =D83-G83 -> 4367077.6 | I83: =IF(D83=0,0,G83/D83) -> 0.37590264 | J83: =Base!O71 -> Administración directa / Contrata / Personal/bienes/servicios / Equipamiento | K83: =Base!P71 -> Comprometido | L83: =Base!Q71 -> 8000000 | M83: =Base!R71 -> 10256256 | N83: =Base!S71 -> 15069544 | O83: =Base!T71 -> 4478827 | P83: =IF(Base!U71="","",Base!U71)
A84: =SUBTOTAL(103,$B$6:B84) -> 68 | B84: 241 | C84: =Base!G72 -> 2494039: MEJORAMIENTO Y AMPLIACION DE LOS SERVICIOS DE SALUD EN EL ESTABLECIMIENTO DE SALUD UMACHIRI CATEGORIA I-2 DEL DISTRITO DE UMACHIRI - PROVINCIA DE MELGAR - DEPARTAMENTO DE PUNO | D84: =Base!H72 -> 6688287 | E84: =Base!I72 -> 6156914.2 | F84: =D84-E84 -> 531372.77 | G84: =Base!K72 -> 3692512.7 | H84: =D84-G84 -> 2995774.3 | I84: =IF(D84=0,0,G84/D84) -> 0.55208646 | J84: =Base!O72 -> Administración directa / Equipamiento / Contrata / Personal/bienes/servicios | K84: =Base!P72 -> Comprometido | L84: =Base!Q72 -> 2822702 | M84: =Base!R72 -> 65844 | N84: =Base!S72 -> 0 | O84: =Base!T72 -> 0 | P84: =IF(Base!U72="","",Base!U72)
A85: =SUBTOTAL(103,$B$6:B85) -> 69 | B85: 221 | C85: =Base!G73 -> 2290342: MEJORAMIENTO DE LA CAPACIDAD RESOLUTIVA DE LOS SERVICIOS DEL PUESTO DE SALUD I - 1 DEL CENTRO POBLADO DE CARI CARI DEL DISTRITO DE MAÑAZO - PROVINCIA DE PUNO - DEPARTAMENTO DE PUNO | D85: =Base!H73 -> 3318026 | E85: =Base!I73 -> 3154441.6 | F85: =D85-E85 -> 163584.43 | G85: =Base!K73 -> 2243366.7 | H85: =D85-G85 -> 1074659.3 | I85: =IF(D85=0,0,G85/D85) -> 0.67611487 | J85: =Base!O73 -> Administración directa / Equipamiento / Contrata / Expediente técnico / Personal/bienes/servicios | K85: =Base!P73 -> Comprometido | L85: =Base!Q73 -> 821892 | M85: =Base!R73 -> 47336 | N85: =Base!S73 -> 0 | O85: =Base!T73 -> 0 | P85: =IF(Base!U73="","",Base!U73)
A86: =SUBTOTAL(103,$B$6:B86) -> 70 | B86: 235 | C86: =Base!G74 -> 2451529: MEJORAMIENTO DEL SERVICIO DE SALUD EN EL CENTRO DE SALUD PILCUYO DE LA MICRORED PILCUYO, RED DE SALUD EL COLLAO, DEL DISTRITO DE PILCUYO - PROVINCIA DE EL COLLAO - DEPARTAMENTO DE PUNO | D86: =Base!H74 -> 0 | E86: =Base!I74 -> 0 | F86: =D86-E86 -> 0 | G86: =Base!K74 -> 0 | H86: =D86-G86 -> 0 | I86: =IF(D86=0,0,G86/D86) -> 0 | J86: =Base!O74 -> Contrata | K86: =Base!P74 -> Sin PIM | L86: =Base!Q74 -> 12571000 | M86: =Base!R74 -> 5987564 | N86: =Base!S74 -> 16094501 | O86: =Base!T74 -> 22576094 | P86: =IF(Base!U74="","",Base!U74)
A87: 22. EDUCACION | D87: =SUM(D88:D107) -> 160639248 | E87: =SUM(E88:E107) -> 1.5009595e+08 | F87: =SUM(F88:F107) -> 10543296 | G87: =SUM(G88:G107) -> 1.0464849e+08 | H87: =SUM(H88:H107) -> 55990754 | I87: =IF(D87=0,0,G87/D87) -> 0.65145035
A88: =SUBTOTAL(103,$B$6:B88) -> 71 | B88: 35 | C88: =Base!G75 -> 2411336: MEJORAMIENTO SERVICIO INTEGRAL DE LA INSTITUCION EDUCATIVA SECUNDARIA INDUSTRIAL PERU BIRF DISTRITO DE SAN MIGUEL - PROVINCIA DE SAN ROMAN - DEPARTAMENTO DE PUNO | D88: =Base!H75 -> 21914154 | E88: =Base!I75 -> 21776068 | F88: =D88-E88 -> 138085.94 | G88: =Base!K75 -> 15564867 | H88: =D88-G88 -> 6349286.6 | I88: =IF(D88=0,0,G88/D88) -> 0.7102655 | J88: =Base!O75 -> Administración directa / Equipamiento / Contrata / Personal/bienes/servicios / Laudos arbitrales | K88: =Base!P75 -> Comprometido | L88: =Base!Q75 -> 11955231 | M88: =Base!R75 -> 2500000 | N88: =Base!S75 -> 3884089 | O88: =Base!T75 -> 0 | P88: =IF(Base!U75="","",Base!U75)
A89: =SUBTOTAL(103,$B$6:B89) -> 72 | B89: 25 | C89: =Base!G76 -> 2284935: MEJORAMIENTO DEL SERVICIO EDUCATIVO EN LA IES POLITECNICO REGIONAL LOS ANDES, DISTRITO DE JULIACA, PROVINCIA DE SAN ROMAN - PUNO | D89: =Base!H76 -> 22276780 | E89: =Base!I76 -> 17912911 | F89: =D89-E89 -> 4363868.8 | G89: =Base!K76 -> 15417466 | H89: =D89-G89 -> 6859314 | I89: =IF(D89=0,0,G89/D89) -> 0.69208683 | J89: =Base!O76 -> Administración directa / Contrata / Personal/bienes/servicios / Equipamiento | K89: =Base!P76 -> Comprometido | L89: =Base!Q76 -> 15800000 | M89: =Base!R76 -> 14789542 | N89: =Base!S76 -> 15918407 | O89: =Base!T76 -> 10295229 | P89: =IF(Base!U76="","",Base!U76)
A90: =SUBTOTAL(103,$B$6:B90) -> 73 | B90: 229 | C90: =Base!G77 -> 2357330: MEJORAMIENTO DEL SERVICIO EDUCATIVO DE LAS CARRERAS DE PRODUCCION AGROPECUARIA, MECANICA DE PRODUCCION, COMPUTACION E INFORMATICA, ENFERMERIA TECNICA EN EL INSTITUTO SUPERIOR TECNOLOGICO PUBLICO DE HUANCANE DISTRITO DE HUANCANE - PROVINCIA DE HUANCANE - DEPARTAMENTO DE PUNO | D90: =Base!H77 -> 17354707 | E90: =Base!I77 -> 17083718 | F90: =D90-E90 -> 270988.58 | G90: =Base!K77 -> 8610007.7 | H90: =D90-G90 -> 8744699.3 | I90: =IF(D90=0,0,G90/D90) -> 0.49611945 | J90: =Base!O77 -> Administración directa / Equipamiento / Contrata / Personal/bienes/servicios | K90: =Base!P77 -> Comprometido | L90: =Base!Q77 -> 12500000 | M90: =Base!R77 -> 4806839 | N90: =Base!S77 -> 753613 | O90: =Base!T77 -> 0 | P90: =IF(Base!U77="","",Base!U77)
A91: =SUBTOTAL(103,$B$6:B91) -> 74 | B91: 30 | C91: =Base!G78 -> 2357322: MEJORAMIENTO SERVICIO EDUCATIVO EN LA IES. 32 MARIANO H. CORNEJO DE LA LOCALIDAD DE JULIACA - DISTRITO DE JULIACA - PROVINCIA DE SAN ROMAN - REGION PUNO | D91: =Base!H78 -> 19795501 | E91: =Base!I78 -> 19793412 | F91: =D91-E91 -> 2089.28 | G91: =Base!K78 -> 14545766 | H91: =D91-G91 -> 5249734.8 | I91: =IF(D91=0,0,G91/D91) -> 0.73480162 | J91: =Base!O78 -> Administración directa / Equipamiento / Contrata / Personal/bienes/servicios | K91: =Base!P78 -> Comprometido | L91: =Base!Q78 -> 9609000 | M91: =Base!R78 -> 897867 | N91: =Base!S78 -> 6124874 | O91: =Base!T78 -> 0 | P91: =IF(Base!U78="","",Base!U78)
A92: =SUBTOTAL(103,$B$6:B92) -> 75 | B92: 33 | C92: =Base!G79 -> 2385673: MEJORAMIENTO DEL SERVICIO EDUCATIVO DE LA I.E.S. LAS MERCEDES DE LA CIUDAD DE JULIACA - DISTRITO DE JULIACA - PROVINCIA DE SAN ROMAN - DEPARTAMENTO DE PUNO | D92: =Base!H79 -> 17241964 | E92: =Base!I79 -> 17144705 | F92: =D92-E92 -> 97259.44 | G92: =Base!K79 -> 11639796 | H92: =D92-G92 -> 5602167.7 | I92: =IF(D92=0,0,G92/D92) -> 0.67508529 | J92: =Base!O79 -> Administración directa / Contrata / Personal/bienes/servicios / Equipamiento | K92: =Base!P79 -> Comprometido | L92: =Base!Q79 -> 8016014 | M92: =Base!R79 -> 10000000 | N92: =Base!S79 -> 1057112 | O92: =Base!T79 -> 2541629 | P92: =IF(Base!U79="","",Base!U79)
A93: =SUBTOTAL(103,$B$6:B93) -> 76 | B93: 161 | C93: =Base!G80 -> 2585543: MEJORAMIENTO Y AMPLIACION DEL SERVICIO DE EDUCACION SUPERIOR TECNOLOGICA EN EL INSTITUTO DE EDUCACION SUPERIOR TECNOLOGICO PUBLICO ACORA DEL DISTRITO DE ACORA DE LA PROVINCIA DE PUNO DEL DEPARTAMENTO DE PUNO | D93: =Base!H80 -> 15380884 | E93: =Base!I80 -> 14270657 | F93: =D93-E93 -> 1110226.8 | G93: =Base!K80 -> 9463521.5 | H93: =D93-G93 -> 5917362.5 | I93: =IF(D93=0,0,G93/D93) -> 0.61527812 | J93: =Base!O80 -> Administración directa / Equipamiento / Contrata / Personal/bienes/servicios | K93: =Base!P80 -> Comprometido | L93: =Base!Q80 -> 6000000 | M93: =Base!R80 -> 3456765 | N93: =Base!S80 -> 1108030 | O93: =Base!T80 -> 0 | P93: =IF(Base!U80="","",Base!U80)
A94: =SUBTOTAL(103,$B$6:B94) -> 77 | B94: 247 | C94: =Base!G81 -> 2535611: MEJORAMIENTO Y AMPLIACION DEL SERVICIO DE EDUCACION SUPERIOR TECNOLOGICO PUBLICO EN EL INSTITUTO ANDRES AVELINO CACERES DISTRITO DE PUTINA - PROVINCIA DE SAN ANTONIO DE PUTINA - DEPARTAMENTO DE PUNO | D94: =Base!H81 -> 9666000 | E94: =Base!I81 -> 9191703.8 | F94: =D94-E94 -> 474296.17 | G94: =Base!K81 -> 5594991.1 | H94: =D94-G94 -> 4071008.9 | I94: =IF(D94=0,0,G94/D94) -> 0.5788321 | J94: =Base!O81 -> Administración directa / Contrata / Personal/bienes/servicios | K94: =Base!P81 -> Comprometido | L94: =Base!Q81 -> 7546000 | M94: =Base!R81 -> 1410563 | N94: =Base!S81 -> 1509243 | O94: =Base!T81 -> 0 | P94: =IF(Base!U81="","",Base!U81)
A95: =SUBTOTAL(103,$B$6:B95) -> 78 | B95: 39 | C95: =Base!G82 -> 2538950: MEJORAMIENTO DEL SERVICIO EDUCATIVO DEL NIVEL PRIMARIO DE LA I.E. 71008 EN EL DISTRITO DE LAMPA - PROVINCIA DE LAMPA - DEPARTAMENTO DE PUNO | D95: =Base!H82 -> 6765264 | E95: =Base!I82 -> 6659441.2 | F95: =D95-E95 -> 105822.81 | G95: =Base!K82 -> 4177875.5 | H95: =D95-G95 -> 2587388.5 | I95: =IF(D95=0,0,G95/D95) -> 0.61754804 | J95: =Base!O82 -> Administración directa / Equipamiento / Contrata / Personal/bienes/servicios | K95: =Base!P82 -> Comprometido | L95: =Base!Q82 -> No registrado en cartera | M95: =Base!R82 -> No registrado en cartera | N95: =Base!S82 -> No registrado en cartera | O95: =Base!T82 -> No registrado en cartera | P95: =IF(Base!U82="","",Base!U82)
A96: =SUBTOTAL(103,$B$6:B96) -> 79 | B96: 26 | C96: =Base!G83 -> 2289661: MEJORAMIENTO DE LOS SERVICIOS EDUCATIVOS EN LA I.E.S. DOS DE MAYO DE CARACOTO, DISTRITO DE CARACOTO - SAN ROMAN - PUNO | D96: =Base!H83 -> 4291327 | E96: =Base!I83 -> 4093667 | F96: =D96-E96 -> 197659.95 | G96: =Base!K83 -> 3891386.8 | H96: =D96-G96 -> 399940.21 | I96: =IF(D96=0,0,G96/D96) -> 0.90680267 | J96: =Base!O83 -> Administración directa / Contrata / Equipamiento / Personal/bienes/servicios | K96: =Base!P83 -> Comprometido | L96: =Base!Q83 -> No registrado en cartera | M96: =Base!R83 -> No registrado en cartera | N96: =Base!S83 -> No registrado en cartera | O96: =Base!T83 -> No registrado en cartera | P96: =IF(Base!U83="","",Base!U83)
A97: =SUBTOTAL(103,$B$6:B97) -> 80 | B97: 41 | C97: =Base!G84 -> 2590087: MEJORAMIENTO DEL SERVICIO DE EDUCACION SECUNDARIA EN I.E. JOSE MARIA ARGUEDAS DISTRITO DE LLALLI DE LA PROVINCIA DE MELGAR DEL DEPARTAMENTO DE PUNO | D97: =Base!H84 -> 5799805 | E97: =Base!I84 -> 5459070.3 | F97: =D97-E97 -> 340734.7 | G97: =Base!K84 -> 3888315.9 | H97: =D97-G97 -> 1911489.1 | I97: =IF(D97=0,0,G97/D97) -> 0.67042183 | J97: =Base!O84 -> Administración directa / Contrata / Equipamiento / Personal/bienes/servicios | K97: =Base!P84 -> Comprometido | L97: =Base!Q84 -> No registrado en cartera | M97: =Base!R84 -> No registrado en cartera | N97: =Base!S84 -> No registrado en cartera | O97: =Base!T84 -> No registrado en cartera | P97: =IF(Base!U84="","",Base!U84)
A98: =SUBTOTAL(103,$B$6:B98) -> 81 | B98: 36 | C98: =Base!G85 -> 2417765: MEJORAMIENTO Y AMPLIACION DEL SERVICIOS DE EDUCACION BASICA EN EL NIVEL PRIMARIO DE LA IEP Nº 72169 TAMBILLO, IEP Nº 72175 TAYACCUCHO, IEP Nº 72188 QUETY, IEP Nº 72642 MALLCUAPO, IEP Nº 72749 CALASUCA DEL DISTRITO DE ITUATA - PROVINCIA DE CARABAYA - DEPARTAMENTO DE PUNO DISTRITO DE ITUATA - PROVINCIA DE CARABAYA - DEPARTAMENTO DE PUNO | D98: =Base!H85 -> 4802506 | E98: =Base!I85 -> 4376181.6 | F98: =D98-E98 -> 426324.38 | G98: =Base!K85 -> 3250907.8 | H98: =D98-G98 -> 1551598.2 | I98: =IF(D98=0,0,G98/D98) -> 0.67691905 | J98: =Base!O85 -> Administración directa / Contrata / Equipamiento / Personal/bienes/servicios | K98: =Base!P85 -> Comprometido | L98: =Base!Q85 -> 3770000 | M98: =Base!R85 -> 876556 | N98: =Base!S85 -> 4649244 | O98: =Base!T85 -> 7795363 | P98: =IF(Base!U85="","",Base!U85)
A99: =SUBTOTAL(103,$B$6:B99) -> 82 | B99: 311 | C99: =Base!G86 -> 2417765: MEJORAMIENTO Y AMPLIACION DEL SERVICIOS DE EDUCACION BASICA EN EL NIVEL PRIMARIO DE LA IEP Nº 72169 TAMBILLO, IEP Nº 72175 TAYACCUCHO, IEP Nº 72188 QUETY, IEP Nº 72642 MALLCUAPO, IEP Nº 72749 CALASUCA DEL DISTRITO DE ITUATA - PROVINCIA DE CARABAYA - DEPARTAMENTO DE PUNO DISTRITO DE ITUATA - PROVINCIA DE CARABAYA - DEPARTAMENTO DE PUNO | D99: =Base!H86 -> 4992699 | E99: =Base!I86 -> 4276945.2 | F99: =D99-E99 -> 715753.79 | G99: =Base!K86 -> 3252598.6 | H99: =D99-G99 -> 1740100.4 | I99: =IF(D99=0,0,G99/D99) -> 0.651471 | J99: =Base!O86 -> Administración directa / Contrata / Equipamiento / Personal/bienes/servicios | K99: =Base!P86 -> Comprometido | L99: =Base!Q86 -> 3770000 | M99: =Base!R86 -> 876556 | N99: =Base!S86 -> 4649244 | O99: =Base!T86 -> 7795363 | P99: =IF(Base!U86="","",Base!U86)
... A107: =SUBTOTAL(103,$B$6:B107) -> 90 | B107: 83 | C107: =Base!G94 -> 2627406: RENOVACION DE AMBIENTE COMPLEMENTARIO, AULA DE EDUCACION SUPERIOR PEDAGOGICA Y CERCO PERIMETRICO; ADQUISICION DE MOBILIARIO DE AULA DE EDUCACION SUPERIOR PEDAGOGICA; ADEMAS DE OTROS ACTIVOS EN EL(LA) INSTITUTO DE EDUCACION SUPERIOR PEDAGOGICA PUBLICO JULI DEL DISTRITO DE JULI, PROVINCIA CHUCUITO, DEPARTAMENTO PUNO | D107: =Base!H94 -> 61203 | E107: =Base!I94 -> 0 | F107: =D107-E107 -> 61203 | G107: =Base!K94 -> 0 | H107: =D107-G107 -> 61203 | I107: =IF(D107=0,0,G107/D107) -> 0 | J107: =Base!O94 -> Administración directa | K107: =Base!P94 -> Sin certificar | L107: =Base!Q94 -> 61203 | M107: =Base!R94 -> 0 | N107: =Base!S94 -> 0 | O107: =Base!T94 -> 0 | P107: =IF(Base!U94="","",Base!U94)
A108: 15. TRANSPORTE | D108: =SUM(D109:D118) -> 67673088 | E108: =SUM(E109:E118) -> 61457129 | F108: =SUM(F109:F118) -> 6215958.7 | G108: =SUM(G109:G118) -> 41195299 | H108: =SUM(H109:H118) -> 26477789 | I108: =IF(D108=0,0,G108/D108) -> 0.60873975
A109: =SUBTOTAL(103,$B$6:B109) -> 91 | B109: 110 | C109: =Base!G95 -> 2456529.MEJORAMIENTO DE LA CARRETERA PU 147, EMP. PE-34I JIPATA - EMP. PE-34I MOHO, DISTRITO DE MOHO - PROVINCIA DE MOHO - DEPARTAMENTO DE PUNO | D109: =Base!H95 -> 23143575 | E109: =Base!I95 -> 22275711 | F109: =D109-E109 -> 867864.16 | G109: =Base!K95 -> 12059018 | H109: =D109-G109 -> 11084557 | I109: =IF(D109=0,0,G109/D109) -> 0.52105253 | J109: =Base!O95 -> Administración directa / Contrata / Personal/bienes/servicios | K109: =Base!P95 -> Comprometido | L109: =Base!Q95 -> 15500800 | M109: =Base!R95 -> 4458489 | N109: =Base!S95 -> 450011 | O109: =Base!T95 -> 0 | P109: =IF(Base!U95="","",Base!U95)
A110: =SUBTOTAL(103,$B$6:B110) -> 92 | B110: 103 | C110: =Base!G96 -> 2343199: MEJORAMIENTO DE LA CARRETERA (EMP 34B) AZANGARO - (EMP PU-102) JILA PURINA DE LOS DISTRITO DE AZANGARO - DISTRITO DE TIRAPATA - PROVINCIA DE AZANGARO - REGION PUNO | D110: =Base!H96 -> 14991498 | E110: =Base!I96 -> 14685003 | F110: =D110-E110 -> 306495.03 | G110: =Base!K96 -> 11502167 | H110: =D110-G110 -> 3489331.3 | I110: =IF(D110=0,0,G110/D110) -> 0.76724599 | J110: =Base!O96 -> Administración directa / Contrata / Personal/bienes/servicios | K110: =Base!P96 -> Comprometido | L110: =Base!Q96 -> 12491498 | M110: =Base!R96 -> 632388 | N110: =Base!S96 -> 41870 | O110: =Base!T96 -> 0 | P110: =IF(Base!U96="","",Base!U96)
A111: =SUBTOTAL(103,$B$6:B111) -> 93 | B111: 106 | C111: =Base!G97 -> 2399543: MEJORAMIENTO DEL CAMINO VECINAL EMP. R01 (DV. LOANI) - CAMICACHI - EMP. R12 (ROSACANI) DISTRITO DE ILAVE - PROVINCIA DE EL COLLAO - REGION PUNO | D111: =Base!H97 -> 5270087 | E111: =Base!I97 -> 5222084.3 | F111: =D111-E111 -> 48002.71 | G111: =Base!K97 -> 5220159.3 | H111: =D111-G111 -> 49927.71 | I111: =IF(D111=0,0,G111/D111) -> 0.99052621 | J111: =Base!O97 -> Administración directa / Contrata / Personal/bienes/servicios | K111: =Base!P97 -> Comprometido | L111: =Base!Q97 -> No registrado en cartera | M111: =Base!R97 -> No registrado en cartera | N111: =Base!S97 -> No registrado en cartera | O111: =Base!T97 -> No registrado en cartera | P111: =IF(Base!U97="","",Base!U97)
A112: =SUBTOTAL(103,$B$6:B112) -> 94 | B112: 119 | C112: =Base!G98 -> 2591951: MEJORAMIENTO DEL SERVICIO DE TRANSITABILIDAD VIAL INTERURBANA EN EL CAMINO VECINAL DEL KM0+000 (DESVIO PUENTE OCRA CHUPA) AL KM 6+373 (C.P. PEDRO VILCAPAZA DE MORORCCO), DISTRITO DE MUÑANI DE LA PROVINCIA DE AZANGARO DEL DEPARTAMENTO DE PUNO | D112: =Base!H98 -> 6770858 | E112: =Base!I98 -> 6051014.3 | F112: =D112-E112 -> 719843.71 | G112: =Base!K98 -> 3961148.7 | H112: =D112-G112 -> 2809709.3 | I112: =IF(D112=0,0,G112/D112) -> 0.58502906 | J112: =Base!O98 -> Administración directa / Contrata / Personal/bienes/servicios / Equipamiento | K112: =Base!P98 -> Comprometido | L112: =Base!Q98 -> No registrado en cartera | M112: =Base!R98 -> No registrado en cartera | N112: =Base!S98 -> No registrado en cartera | O112: =Base!T98 -> No registrado en cartera | P112: =IF(Base!U98="","",Base!U98)
A113: =SUBTOTAL(103,$B$6:B113) -> 95 | B113: 121 | C113: =Base!G99 -> 2602163: MEJORAMIENTO DEL SERVICIO DE TRANSITABILIDAD VIAL INTERURBANA EN LA CARRETERA PU 866 (EMP PE 34 I) - EMP PU 110 (SULLCA), PU 870 (DV TOTORANI: EMP PU 866) - EMP PU 872 (OCCOPAMPA), PU 872: EMP. PU - 866 (HUAYRAPATA) - OCCOPAMPA - EMP. PU - 870 DISTRITOS DE MOHO, HUAYRAPATA DE LA PROVINCIA DE MOHO DEL DEPARTAMENTO DE PUNO | D113: =Base!H99 -> 2308286 | E113: =Base!I99 -> 0 | F113: =D113-E113 -> 2308286 | G113: =Base!K99 -> 0 | H113: =D113-G113 -> 2308286 | I113: =IF(D113=0,0,G113/D113) -> 0 | J113: =Base!O99 -> Administración directa / Contrata | K113: =Base!P99 -> Sin certificar | L113: =Base!Q99 -> 800000 | M113: =Base!R99 -> 10345657 | N113: =Base!S99 -> 0 | O113: =Base!T99 -> 10973904 | P113: =IF(Base!U99="","",Base!U99)
A114: =SUBTOTAL(103,$B$6:B114) -> 96 | B114: 463 | C114: =Base!G100 -> 2511009: MEJORAMIENTO DEL SERVICIO VIAL URBANO DE LA AVENIDA INDUSTRIAL DEL CENTRO POBLADO DE SALCEDO, DISTRITO DE PUNO - PROVINCIA DE PUNO - DEPARTAMENTO DE PUNO | D114: =Base!H100 -> 1827737 | E114: =Base!I100 -> 1014426 | F114: =D114-E114 -> 813311.02 | G114: =Base!K100 -> 13810.34 | H114: =D114-G114 -> 1813926.7 | I114: =IF(D114=0,0,G114/D114) -> 0.0075559777 | J114: =Base!O100 -> Administración directa / Contrata | K114: =Base!P100 -> Comprometido | L114: =Base!Q100 -> No registrado en cartera | M114: =Base!R100 -> No registrado en cartera | N114: =Base!S100 -> No registrado en cartera | O114: =Base!T100 -> No registrado en cartera | P114: =IF(Base!U100="","",Base!U100)
A115: =SUBTOTAL(103,$B$6:B115) -> 97 | B115: 128 | C115: =Base!G101 -> 2634040: MEJORAMIENTO DEL SERVICIO DE TRANSITABILIDAD VIAL INTERURBANA EN EL CAMINO VECINAL, TRAMO DESVIO PUCARA - POBLACION SALINAS - ASILLO SALINAS (KM 0+000 - 1+900) DEL DISTRITO DE SAN JUAN DE SALINAS DE LA PROVINCIA DE AZANGARO DEL DEPARTAMENTO DE PUNO | D115: =Base!H101 -> 4106961 | E115: =Base!I101 -> 3355560.2 | F115: =D115-E115 -> 751400.79 | G115: =Base!K101 -> 1831598.5 | H115: =D115-G115 -> 2275362.5 | I115: =IF(D115=0,0,G115/D115) -> 0.44597417 | J115: =Base!O101 -> Administración directa / Contrata / Personal/bienes/servicios | K115: =Base!P101 -> Comprometido | L115: =Base!Q101 -> No registrado en cartera | M115: =Base!R101 -> No registrado en cartera | N115: =Base!S101 -> No registrado en cartera | O115: =Base!T101 -> No registrado en cartera | P115: =IF(Base!U101="","",Base!U101)
A116: =SUBTOTAL(103,$B$6:B116) -> 98 | B116: 105 | C116: =Base!G102 -> 2387422: MEJORAMIENTO DE LA CARRETERA TRAMO II (PUENTE CULLCO) - PICHINCUTA - QUELCAHUECO - CORARACA DEL - DISTRITO DE ILAVE - PROVINCIA DE EL COLLAO - DEPARTAMENTO DE PUNO | D116: =Base!H102 -> 7751873 | E116: =Base!I102 -> 7482027.4 | F116: =D116-E116 -> 269845.63 | G116: =Base!K102 -> 5292812.8 | H116: =D116-G116 -> 2459060.2 | I116: =IF(D116=0,0,G116/D116) -> 0.68277857 | J116: =Base!O102 -> Administración directa / Contrata / Personal/bienes/servicios / Equipamiento | K116: =Base!P102 -> Comprometido | L116: =Base!Q102 -> No registrado en cartera | M116: =Base!R102 -> No registrado en cartera | N116: =Base!S102 -> No registrado en cartera | O116: =Base!T102 -> No registrado en cartera | P116: =IF(Base!U102="","",Base!U102)
A117: =SUBTOTAL(103,$B$6:B117) -> 99 | B117: 114 | C117: =Base!G103 -> 2527184: MEJORAMIENTO DEL SERVICIO DE TRANSITABILIDAD VIAL DEL CAMINO VECINAL TRAMO VILLA PAXA A VENTILLA (PU- 1065) DEL DISTRITO DE PUNO - PROVINCIA DE PUNO - DEPARTAMENTO DE PUNO | D117: =Base!H103 -> 936343 | E117: =Base!I103 -> 868354.77 | F117: =D117-E117 -> 67988.23 | G117: =Base!K103 -> 868354.72 | H117: =D117-G117 -> 67988.28 | I117: =IF(D117=0,0,G117/D117) -> 0.92738956 | J117: =Base!O103 -> Administración directa / Contrata / Personal/bienes/servicios | K117: =Base!P103 -> Comprometido | L117: =Base!Q103 -> No registrado en cartera | M117: =Base!R103 -> No registrado en cartera | N117: =Base!S103 -> No registrado en cartera | O117: =Base!T103 -> No registrado en cartera | P117: =IF(Base!U103="","",Base!U103)
A118: =SUBTOTAL(103,$B$6:B118) -> 100 | B118: 167 | C118: =Base!G104 -> 2519621: CREACION DEL SERVICIO DE TRANSITABILIDAD VEHICULAR Y PEATONAL EN EL JR. 7 DE JUNIO Y JR. BOLOGNESI CUADRA 10 DE LA LOCALIDAD DE YUNGUYO DEL DISTRITO DE YUNGUYO - PROVINCIA DE YUNGUYO - DEPARTAMENTO DE PUNO | D118: =Base!H104 -> 565870 | E118: =Base!I104 -> 502948.57 | F118: =D118-E118 -> 62921.43 | G118: =Base!K104 -> 446229.16 | H118: =D118-G118 -> 119640.84 | I118: =IF(D118=0,0,G118/D118) -> 0.78857186 | J118: =Base!O104 -> Administración directa / Contrata / Personal/bienes/servicios | K118: =Base!P104 -> Comprometido | L118: =Base!Q104 -> No registrado en cartera | M118: =Base!R104 -> No registrado en cartera | N118: =Base!S104 -> No registrado en cartera | O118: =Base!T104 -> No registrado en cartera | P118: =IF(Base!U104="","",Base!U104)
A119: 21. CULTURA Y DEPORTE | D119: =SUM(D120:D122) -> 6449080 | E119: =SUM(E120:E122) -> 6391544.6 | F119: =SUM(F120:F122) -> 57535.36 | G119: =SUM(G120:G122) -> 208464.85 | H119: =SUM(H120:H122) -> 6240615.2 | I119: =IF(D119=0,0,G119/D119) -> 0.032324742
A120: =SUBTOTAL(103,$B$6:B120) -> 101 | B120: 69 | C120: =Base!G105 -> 2645446: REPARACION DE TRIBUNA Y/O PALCO Y PISTA DE ATLETISMO (DEPORTE RECREATIVO); CONSTRUCCION DE CAMPO DEPORTIVO; EN EL(LA) ESTADIO DE LA GRAN UNIDAD SAN CARLOS DISTRITO DE PUNO, PROVINCIA PUNO, DEPARTAMENTO PUNO | D120: =Base!H105 -> 1075076 | E120: =Base!I105 -> 1062250 | F120: =D120-E120 -> 12826 | G120: =Base!K105 -> 20822.47 | H120: =D120-G120 -> 1054253.5 | I120: =IF(D120=0,0,G120/D120) -> 0.01936837 | J120: =Base!O105 -> Contrata / Expediente técnico | K120: =Base!P105 -> Comprometido | L120: =Base!Q105 -> 1062638 | M120: =Base!R105 -> 245874 | N120: =Base!S105 -> 0 | O120: =Base!T105 -> 0 | P120: =IF(Base!U105="","",Base!U105)
A121: =SUBTOTAL(103,$B$6:B121) -> 102 | B121: 73 | C121: =Base!G106 -> 2646109: REPARACION DE TRIBUNA Y/O PALCO; CONSTRUCCION DE CAMPO DEPORTIVO Y TRIBUNA Y/O PALCO; EN EL(LA) ESTADIO MUNICIPAL DE JULI DISTRITO DE JULI, PROVINCIA CHUCUITO, DEPARTAMENTO PUNO | D121: =Base!H106 -> 4474004 | E121: =Base!I106 -> 4473905 | F121: =D121-E121 -> 99 | G121: =Base!K106 -> 0 | H121: =D121-G121 -> 4474004 | I121: =IF(D121=0,0,G121/D121) -> 0 | J121: =Base!O106 -> Contrata / Expediente técnico | K121: =Base!P106 -> Solo certificado | L121: =Base!Q106 -> 1556258 | M121: =Base!R106 -> 2054256 | N121: =Base!S106 -> 0 | O121: =Base!T106 -> 994904 | P121: =IF(Base!U106="","",Base!U106)
A122: =SUBTOTAL(103,$B$6:B122) -> 103 | B122: 504 | C122: =Base!G107 -> 2630072.CREACION DEL SERVICIO DE PRACTICA DEPORTIVA Y/O RECREATIVA EN COLISEO CERRADO DE AYAPATA DISTRITO DE AYAPATA DE LA PROVINCIA DE CARABAYA DEL DEPARTAMENTO DE PUNO | D122: =Base!H107 -> 900000 | E122: =Base!I107 -> 855389.64 | F122: =D122-E122 -> 44610.36 | G122: =Base!K107 -> 187642.38 | H122: =D122-G122 -> 712357.62 | I122: =IF(D122=0,0,G122/D122) -> 0.20849153 | J122: =Base!O107 -> Administración directa / Contrata / Personal/bienes/servicios / Equipamiento | K122: =Base!P107 -> Comprometido | L122: =Base!Q107 -> No registrado en cartera | M122: =Base!R107 -> No registrado en cartera | N122: =Base!S107 -> No registrado en cartera | O122: =Base!T107 -> No registrado en cartera | P122: =IF(Base!U107="","",Base!U107)
A123: EJECUCIÓN POR ADMINISTRACIÓN INDIRECTA (CONTRATA) | D123: =D124+D134+D145+D147+D150 -> 209274718 | E123: =E124+E134+E145+E147+E150 -> 2.0185841e+08 | F123: =F124+F134+F145+F147+F150 -> 7416312.5 | G123: =G124+G134+G145+G147+G150 -> 1.0446792e+08 | H123: =H124+H134+H145+H147+H150 -> 1.048068e+08 | I123: =IF(D123=0,0,G123/D123) -> 0.49919035
A124: 22. EDUCACION | D124: =SUM(D125:D133) -> 41210021 | E124: =SUM(E125:E133) -> 38883859 | F124: =SUM(F125:F133) -> 2326161.9 | G124: =SUM(G125:G133) -> 14467550 | H124: =SUM(H125:H133) -> 26742471 | I124: =IF(D124=0,0,G124/D124) -> 0.35106875
A125: =SUBTOTAL(103,$B$6:B125) -> 104 | B125: 34 | C125: =Base!G108 -> 2393398: MEJORAMIENTO DEL SERVICIO EDUCATIVO DE NIVEL SECUNDARIO EN LA I.E. A - 28 PERU BIRF CENTRO POBLADO DE AZANGARO - DISTRITO DE AZANGARO - PROVINCIA DE AZANGARO - REGION PUNO | D125: =Base!H108 -> 18692228 | E125: =Base!I108 -> 18634477 | F125: =D125-E125 -> 57750.64 | G125: =Base!K108 -> 4987667.5 | H125: =D125-G125 -> 13704560 | I125: =IF(D125=0,0,G125/D125) -> 0.26683109 | J125: =Base!O108 -> Contrata / Personal/bienes/servicios / Equipamiento | K125: =Base!P108 -> Comprometido | L125: =Base!Q108 -> 12431185 | M125: =Base!R108 -> 4843790 | N125: =Base!S108 -> 2910115 | O125: =Base!T108 -> 0 | P125: =IF(Base!U108="","",Base!U108)
A126: =SUBTOTAL(103,$B$6:B126) -> 105 | B126: 460 | C126: =Base!G109 -> 2500458.MEJORAMIENTO DEL SERVICIO EDUCATIVO EN LA IEP N° 70477 SAGRADO CORAZON DE JESUS DEL DISTRITO DE AYAVIRI - PROVINCIA DE MELGAR - DEPARTAMENTO DE PUNO | D126: =Base!H109 -> 4437995 | E126: =Base!I109 -> 3573868.9 | F126: =D126-E126 -> 864126.14 | G126: =Base!K109 -> 2493396.7 | H126: =D126-G126 -> 1944598.3 | I126: =IF(D126=0,0,G126/D126) -> 0.56182954 | J126: =Base!O109 -> Administración directa / Contrata / Equipamiento / Personal/bienes/servicios | K126: =Base!P109 -> Comprometido | L126: =Base!Q109 -> No registrado en cartera | M126: =Base!R109 -> No registrado en cartera | N126: =Base!S109 -> No registrado en cartera | O126: =Base!T109 -> No registrado en cartera | P126: =IF(Base!U109="","",Base!U109)
A127: =SUBTOTAL(103,$B$6:B127) -> 106 | B127: 455 | C127: =Base!G110 -> 2453224.MEJORAMIENTO DE LOS SERVICIOS DE EDUCACION SECUNDARIA DE LA INSTITUCION EDUCATIVA LIBERTADOR JOSE DE SAN MARTIN DE HUARISANI DEL DISTRITO DE HUANCANE - PROVINCIA DE HUANCANE - DEPARTAMENTO DE PUNO | D127: =Base!H110 -> 4265759 | E127: =Base!I110 -> 3847052.9 | F127: =D127-E127 -> 418706.06 | G127: =Base!K110 -> 2741829.6 | H127: =D127-G127 -> 1523929.4 | I127: =IF(D127=0,0,G127/D127) -> 0.64275305 | J127: =Base!O110 -> Administración directa / Contrata / Equipamiento / Personal/bienes/servicios | K127: =Base!P110 -> Comprometido | L127: =Base!Q110 -> No registrado en cartera | M127: =Base!R110 -> No registrado en cartera | N127: =Base!S110 -> No registrado en cartera | O127: =Base!T110 -> No registrado en cartera | P127: =IF(Base!U110="","",Base!U110)
A128: =SUBTOTAL(103,$B$6:B128) -> 107 | B128: 172 | C128: =Base!G111 -> 2250382: INSTALACION DE LOS SERVICIOS DE EDUCACION INICIAL EN LA I.E.I. CHIA, DEL C.P. DE CHIA, DEL DISTRITO DE OLLACHEA - PROVINCIA CARABAYA - REGION PUNO | D128: =Base!H111 -> 2342684 | E128: =Base!I111 -> 2159343.3 | F128: =D128-E128 -> 183340.67 | G128: =Base!K111 -> 1123789.4 | H128: =D128-G128 -> 1218894.6 | I128: =IF(D128=0,0,G128/D128) -> 0.47970164 | J128: =Base!O111 -> Administración directa / Contrata / Personal/bienes/servicios | K128: =Base!P111 -> Comprometido | L128: =Base!Q111 -> 800000 | M128: =Base!R111 -> 26969 | N128: =Base!S111 -> 0 | O128: =Base!T111 -> 0 | P128: =IF(Base!U111="","",Base!U111)
A129: =SUBTOTAL(103,$B$6:B129) -> 108 | B129: 28 | C129: =Base!G112 -> 2344253: MEJORAMIENTO DEL SERVICIO EDUCATIVO EN LA I.E.S. JOSE ANTONIO ENCINAS FRANCO, CENTRO POBLADO DE LECHEMAYO DEL DISTRITO DE SAN GABAN - PROVINCIA DE CARABAYA - DEPARTAMENTO DE PUNO | D129: =Base!H112 -> 4026127 | E129: =Base!I112 -> 3933834.9 | F129: =D129-E129 -> 92292.06 | G129: =Base!K112 -> 1387806.2 | H129: =D129-G129 -> 2638320.8 | I129: =IF(D129=0,0,G129/D129) -> 0.34470007 | J129: =Base!O112 -> Contrata / Personal/bienes/servicios | K129: =Base!P112 -> Comprometido | L129: =Base!Q112 -> 2120577 | M129: =Base!R112 -> 5094106 | N129: =Base!S112 -> 4994536 | O129: =Base!T112 -> 0 | P129: =IF(Base!U112="","",Base!U112)
A130: =SUBTOTAL(103,$B$6:B130) -> 109 | B130: 32 | C130: =Base!G113 -> 2385051: MEJORAMIENTO DEL SERVICIO EDUCATIVO EN LA I.E.S. SAN JUAN BOSCO DE SALCEDO CON JORNADA ESCOLAR COMPLETA DISTRITO DE PUNO - PROVINCIA DE PUNO - REGION PUNO | D130: =Base!H113 -> 4927527 | E130: =Base!I113 -> 4223260.7 | F130: =D130-E130 -> 704266.31 | G130: =Base!K113 -> 1725644.1 | H130: =D130-G130 -> 3201882.9 | I130: =IF(D130=0,0,G130/D130) -> 0.35020491 | J130: =Base!O113 -> Administración directa / Contrata / Equipamiento / Personal/bienes/servicios | K130: =Base!P113 -> Comprometido | L130: =Base!Q113 -> 2000000 | M130: =Base!R113 -> 8000000 | N130: =Base!S113 -> 9133500 | O130: =Base!T113 -> 8629252 | P130: =IF(Base!U113="","",Base!U113)
A131: =SUBTOTAL(103,$B$6:B131) -> 110 | B131: 156 | C131: =Base!G114 -> 2566572: MEJORAMIENTO Y AMPLIACION DE LOS SERVICIOS DE EDUCACION SUPERIOR DEL INSTITUTO SUPERIOR TECNOLOGICO PUBLICO DE NUÑOA DEL DISTRITO DE NUÑOA - PROVINCIA DE MELGAR - DEPARTAMENTO DE PUNO | D131: =Base!H114 -> 1479604 | E131: =Base!I114 -> 1473924 | F131: =D131-E131 -> 5679.97 | G131: =Base!K114 -> 7416.86 | H131: =D131-G131 -> 1472187.1 | I131: =IF(D131=0,0,G131/D131) -> 0.0050127331 | J131: =Base!O114 -> Contrata / Expediente técnico | K131: =Base!P114 -> Comprometido | L131: =Base!Q114 -> 3000000 | M131: =Base!R114 -> 6984785 | N131: =Base!S114 -> 0 | O131: =Base!T114 -> 6681576 | P131: =IF(Base!U114="","",Base!U114)
A132: =SUBTOTAL(103,$B$6:B132) -> 111 | B132: 506 | C132: =Base!G115 -> 2501244.MEJORAMIENTO DEL SERVICIO EDUCATIVO DEL NIVEL SECUNDARIA DE LA I.E. AGROPECUARIO PAMPA YANAMAYO DEL DISTRITO DE ALTO INAMBARI - PROVINCIA DE SANDIA - DEPARTAMENTO DE PUNO | D132: =Base!H115 -> 1038097 | E132: =Base!I115 -> 1038097 | F132: =D132-E132 -> 0 | G132: =Base!K115 -> 0 | H132: =D132-G132 -> 1038097 | I132: =IF(D132=0,0,G132/D132) -> 0 | J132: =Base!O115 -> Contrata | K132: =Base!P115 -> Solo certificado | L132: =Base!Q115 -> No registrado en cartera | M132: =Base!R115 -> No registrado en cartera | N132: =Base!S115 -> No registrado en cartera | O132: =Base!T115 -> No registrado en cartera | P132: =IF(Base!U115="","",Base!U115)
A133: =SUBTOTAL(103,$B$6:B133) -> 112 | B133: 23 | C133: =Base!G116 -> 2194501: INSTALACION DEL SERVICIO EDUCATIVO DE LA INSTITUCION EDUCATIVA SECUNDARIA SANTA MONICA EN EL DISTRITO DE JULIACA, PROVINCIA DE SAN ROMAN - PUNO. | D133: =Base!H116 -> 0 | E133: =Base!I116 -> 0 | F133: =D133-E133 -> 0 | G133: =Base!K116 -> 0 | H133: =D133-G133 -> 0 | I133: =IF(D133=0,0,G133/D133) -> 0 | J133: =Base!O116 -> Personal/bienes/servicios | K133: =Base!P116 -> Sin PIM | L133: =Base!Q116 -> 144908 | M133: =Base!R116 -> 229001 | N133: =Base!S116 -> 0 | O133: =Base!T116 -> 0 | P133: =IF(Base!U116="","",Base!U116)
...

Sheet Gerencias y Oficinas
C1: ANEXO N° 02
B2: COMPORTAMIENTO DE EJECUCIÓN DE PROYECTOS DE INVERSION PUBLICA DEL AÑO FISCAL 2026 DE GERENCIAS REGIONALES Y UNIDADES EJECUTORAS · UE 001 · AL 06/10/2026
A4: N° | B4: META | C4: PROYECTO | D4: PIM 2026 (A) | E4: CERTIFICACIÓN (B) | F4: SALDO (A-B) | G4: DEVENGADO ( C ) | H4: SALDO (A-C) | I4: DEVEN % | J4: MODALIDAD DE EJECUCIÓN | K4: ESTADO SITUACIONAL PROYECTO | L4: Monto Año 2026 (S/) | M4: Monto Año 2027 (S/) | N4: Monto Año 2028 (S/) | O4: Monto Año 2029 (S/) | P4: BASE LEGAL
A6: GERENCIA REGIONAL DE DESARROLLO ECONOMICO | D6: =D7+D12+D15+D18+D83+D88 -> 15438088 | E6: =E7+E12+E15+E18+E83+E88 -> 13246424 | F6: =F7+F12+F15+F18+F83+F88 -> 2191664.1 | G6: =G7+G12+G15+G18+G83+G88 -> 6937956.8 | H6: =H7+H12+H15+H18+H83+H88 -> 8500131.2 | I6: =IF(D6=0,0,G6/D6) -> 0.44940518
A7: 09. TURISMO | D7: =SUM(D8:D11) -> 3137774 | E7: =SUM(E8:E11) -> 2421934 | F7: =SUM(F8:F11) -> 715839.98 | G7: =SUM(G8:G11) -> 1602346.4 | H7: =SUM(H8:H11) -> 1535427.6 | I7: =IF(D7=0,0,G7/D7) -> 0.51066342
A8: =SUBTOTAL(103,$B$6:B8) -> 1 | B8: 20 | C8: =Base!G286 -> 2526527: MEJORAMIENTO DE LAS CAPACIDADES PARA LA PRODUCTIVIDAD Y LA COMPETITIVIDAD DE ARTESANIAS EN 13 PROVINCIAS DEL DEPARTAMENTO DE PUNO | D8: =Base!H286 -> 2659376 | E8: =Base!I286 -> 1980094.5 | F8: =D8-E8 -> 679281.48 | G8: =Base!K286 -> 1386716.9 | H8: =D8-G8 -> 1272659.1 | I8: =IF(D8=0,0,G8/D8) -> 0.52144446 | J8: =Base!O286 -> Contrata / Personal/bienes/servicios / Equipamiento | K8: =Base!P286 -> Comprometido | L8: =Base!Q286 -> 3659376 | M8: =Base!R286 -> 55933 | N8: =Base!S286 -> 0 | O8: =Base!T286 -> 1953448 | P8: =IF(Base!U286="","",Base!U286)
A9: =SUBTOTAL(103,$B$6:B9) -> 2 | B9: 383 | C9: =Base!G287 -> 2717147.MEJORAMIENTO DE LOS SERVICIOS TURISTICOS DE AVENTURA Y ALOJAMIENTO RURAL EN LA ASOCIACION DE TURISMO VIVENCIAL COMUNITARIO LUQUINA CHICO, DISTRITO CHUCUITO, PROVINCIA PUNO, REGION PUNO. | D9: =Base!H287 -> 159946 | E9: =Base!I287 -> 154011 | F9: =D9-E9 -> 5935 | G9: =Base!K287 -> 60441 | H9: =D9-G9 -> 99505 | I9: =IF(D9=0,0,G9/D9) -> 0.37788379 | J9: =Base!O287 -> Equipamiento / Contrata | K9: =Base!P287 -> Comprometido | L9: =Base!Q287 -> No registrado en cartera | M9: =Base!R287 -> No registrado en cartera | N9: =Base!S287 -> No registrado en cartera | O9: =Base!T287 -> No registrado en cartera | P9: =IF(Base!U287="","",Base!U287)
A10: =SUBTOTAL(103,$B$6:B10) -> 3 | B10: 475 | C10: =Base!G288 -> 2723296.MEJORAMIENTO DE LA PRODUCCION Y COMERCIALIZACION DE ARTESANIA DE FIBRA DE ALPACA Y LANA DE OVINO EN LA ASOCIACION DE ARTESANOS EMPRENDEDORES EN TEXTILERIA SAN JUAN BAUTISTA DE NAPA ROSASPATA, DISTRITO DE ROSASPATA, PROVINCIA DE HUANCANE, REGION PU | D10: =Base!H288 -> 159560 | E10: =Base!I288 -> 141270 | F10: =D10-E10 -> 18290 | G10: =Base!K288 -> 57830 | H10: =D10-G10 -> 101730 | I10: =IF(D10=0,0,G10/D10) -> 0.36243419 | J10: =Base!O288 -> Equipamiento / Contrata | K10: =Base!P288 -> Comprometido | L10: =Base!Q288 -> No registrado en cartera | M10: =Base!R288 -> No registrado en cartera | N10: =Base!S288 -> No registrado en cartera | O10: =Base!T288 -> No registrado en cartera | P10: =IF(Base!U288="","",Base!U288)
A11: =SUBTOTAL(103,$B$6:B11) -> 4 | B11: 410 | C11: =Base!G289 -> 2717175.MEJORAMIENTO DE LOS SERVICIOS DE ALOJAMIENTO TURISTICO Y DEL TURISMO VIVENCIAL DE OBSERVACION ASTRONOMICA EN LA ASOCIACION DE TURISMO COMUNITARIO TIKA WASI LLACHON, DISTRITO DE CAPACHICA, PROVINCIA DE PUNO Y DEPARTAMENTO DE PUNO. | D11: =Base!H289 -> 158892 | E11: =Base!I289 -> 146558.5 | F11: =D11-E11 -> 12333.5 | G11: =Base!K289 -> 97358.5 | H11: =D11-G11 -> 61533.5 | I11: =IF(D11=0,0,G11/D11) -> 0.61273381 | J11: =Base!O289 -> Equipamiento / Contrata | K11: =Base!P289 -> Comprometido | L11: =Base!Q289 -> No registrado en cartera | M11: =Base!R289 -> No registrado en cartera | N11: =Base!S289 -> No registrado en cartera | O11: =Base!T289 -> No registrado en cartera | P11: =IF(Base!U289="","",Base!U289)
A12: 03. PLANEAMIENTO, GESTION Y RESERVA DE CONTINGENCIA | D12: =SUM(D13:D14) -> 243160 | E12: =SUM(E13:E14) -> 83160 | F12: =SUM(F13:F14) -> 160000 | G12: =SUM(G13:G14) -> 83100.4 | H12: =SUM(H13:H14) -> 160059.6 | I12: =IF(D12=0,0,G12/D12) -> 0.34175193
A13: =SUBTOTAL(103,$B$6:B13) -> 5 | B13: 399 | C13: =Base!G290 -> 2717164.MEJORAMIENTO DE LA CAPACIDAD PRODUCTIVA Y DE COMERCIALIZACION DE MIEL MEDIANTE EL FORTALECIMIENTO DE PROCESOS PRODUCTIVOS APICOLAS EN LA ASOCIACION DE PRODUCTORES AGROPECUARIOS MONTE SILOE KOLLA MISKI DISTRITO PLATERIA, PROVINCIA DE PUNO, REGION P | D13: =Base!H290 -> 160000 | E13: =Base!I290 -> 0 | F13: =D13-E13 -> 160000 | G13: =Base!K290 -> 0 | H13: =D13-G13 -> 160000 | I13: =IF(D13=0,0,G13/D13) -> 0 | J13: =Base!O290 -> Equipamiento / Contrata | K13: =Base!P290 -> Sin certificar | L13: =Base!Q290 -> No registrado en cartera | M13: =Base!R290 -> No registrado en cartera | N13: =Base!S290 -> No registrado en cartera | O13: =Base!T290 -> No registrado en cartera | P13: =IF(Base!U290="","",Base!U290)
A14: =SUBTOTAL(103,$B$6:B14) -> 6 | B14: 373 | C14: =Base!G291 -> 2676438: MEJORAMIENTO DE LA PRODUCCION DE MIEL DE ABEJA DE LA ASOCIACION DE APICULTORES Y PRODUCTORES AGROPECUARIOS DEL VALLE YANAHUAYA, DEL DISTRITO DE YANAHUARA PROVINCIA DE SANDIA DEPARTAMENTO DE PUNO | D14: =Base!H291 -> 83160 | E14: =Base!I291 -> 83160 | F14: =D14-E14 -> 0 | G14: =Base!K291 -> 83100.4 | H14: =D14-G14 -> 59.6 | I14: =IF(D14=0,0,G14/D14) -> 0.99928331 | J14: =Base!O291 -> Equipamiento | K14: =Base!P291 -> Comprometido | L14: =Base!Q291 -> No registrado en cartera | M14: =Base!R291 -> No registrado en cartera | N14: =Base!S291 -> No registrado en cartera | O14: =Base!T291 -> No registrado en cartera | P14: =IF(Base!U291="","",Base!U291)
A15: 08. COMERCIO | D15: =SUM(D16:D17) -> 1098209 | E15: =SUM(E16:E17) -> 995606.03 | F15: =SUM(F16:F17) -> 102602.97 | G15: =SUM(G16:G17) -> 677101.76 | H15: =SUM(H16:H17) -> 421107.24 | I15: =IF(D15=0,0,G15/D15) -> 0.61655091
A16: =SUBTOTAL(103,$B$6:B16) -> 7 | B16: 216 | C16: =Base!G292 -> 2016766: INICIATIVA A LA COMPETITIVIDAD | D16: =Base!H292 -> 928209 | E16: =Base!I292 -> 900951.03 | F16: =D16-E16 -> 27257.97 | G16: =Base!K292 -> 633092.52 | H16: =D16-G16 -> 295116.48 | I16: =IF(D16=0,0,G16/D16) -> 0.68205816 | J16: =Base!O292 -> Estudio de preinversión | K16: =Base!P292 -> Comprometido | L16: =Base!Q292 -> No registrado en cartera | M16: =Base!R292 -> No registrado en cartera | N16: =Base!S292 -> No registrado en cartera | O16: =Base!T292 -> No registrado en cartera | P16: =IF(Base!U292="","",Base!U292)
A17: =SUBTOTAL(103,$B$6:B17) -> 8 | B17: 493 | C17: =Base!G293 -> 2016766: INICIATIVA A LA COMPETITIVIDAD | D17: =Base!H293 -> 170000 | E17: =Base!I293 -> 94655 | F17: =D17-E17 -> 75345 | G17: =Base!K293 -> 44009.24 | H17: =D17-G17 -> 125990.76 | I17: =IF(D17=0,0,G17/D17) -> 0.25887788 | J17: =Base!O293 -> Estudio de preinversión | K17: =Base!P293 -> Comprometido | L17: =Base!Q293 -> No registrado en cartera | M17: =Base!R293 -> No registrado en cartera | N17: =Base!S293 -> No registrado en cartera | O17: =Base!T293 -> No registrado en cartera | P17: =IF(Base!U293="","",Base!U293)
A18: 10. AGROPECUARIA | D18: =SUM(D19:D82) -> 8596003 | E18: =SUM(E19:E82) -> 7643005.2 | F18: =SUM(F19:F82) -> 952997.85 | G18: =SUM(G19:G82) -> 4006476.2 | H18: =SUM(H19:H82) -> 4589526.8 | I18: =IF(D18=0,0,G18/D18) -> 0.46608595
A19: =SUBTOTAL(103,$B$6:B19) -> 9 | B19: 418 | C19: =Base!G294 -> 2717186.MEJORAMIENTO DE LA PLANTA DE TRANSFORMACION DE GRANOS ANDINOS DEL GRUPO TURISTICO GASTRONOMICO SAMKA S.A.C., DISTRITO PUNO, PROVINCIA PUNO, REGION PUNO. | D19: =Base!H294 -> 350000 | E19: =Base!I294 -> 334060 | F19: =D19-E19 -> 15940 | G19: =Base!K294 -> 65360 | H19: =D19-G19 -> 284640 | I19: =IF(D19=0,0,G19/D19) -> 0.18674286 | J19: =Base!O294 -> Equipamiento / Contrata | K19: =Base!P294 -> Comprometido | L19: =Base!Q294 -> No registrado en cartera | M19: =Base!R294 -> No registrado en cartera | N19: =Base!S294 -> No registrado en cartera | O19: =Base!T294 -> No registrado en cartera | P19: =IF(Base!U294="","",Base!U294)
A20: =SUBTOTAL(103,$B$6:B20) -> 10 | B20: 424 | C20: =Base!G295 -> 2717193.AMPLIACION DE LA CAPACIDAD PRODUCCION DE QUESO PARIA EN GRUPO NEBRASKA S.A.C. EN DISTRITO DE JULIACA PROVINCIA DE SAN ROMAN REGION PUNO | D20: =Base!H295 -> 349950 | E20: =Base!I295 -> 287705 | F20: =D20-E20 -> 62245 | G20: =Base!K295 -> 136062 | H20: =D20-G20 -> 213888 | I20: =IF(D20=0,0,G20/D20) -> 0.38880411 | J20: =Base!O295 -> Equipamiento / Contrata | K20: =Base!P295 -> Comprometido | L20: =Base!Q295 -> No registrado en cartera | M20: =Base!R295 -> No registrado en cartera | N20: =Base!S295 -> No registrado en cartera | O20: =Base!T295 -> No registrado en cartera | P20: =IF(Base!U295="","",Base!U295)
A21: =SUBTOTAL(103,$B$6:B21) -> 11 | B21: 413 | C21: =Base!G296 -> 2717178.MEJORAMIENTO DEL CULTIVO DE HABAS EN CORPORACION PECUARIO AGRICOLA EMMANUEL S.A.C., DISTRITO DE ZEPITA, PROVINCIA DE CHUCUITO Y DEPARTAMENTO DE PUNO | D21: =Base!H296 -> 349899 | E21: =Base!I296 -> 307070 | F21: =D21-E21 -> 42829 | G21: =Base!K296 -> 10500 | H21: =D21-G21 -> 339399 | I21: =IF(D21=0,0,G21/D21) -> 0.03000866 | J21: =Base!O296 -> Equipamiento / Contrata | K21: =Base!P296 -> Comprometido | L21: =Base!Q296 -> No registrado en cartera | M21: =Base!R296 -> No registrado en cartera | N21: =Base!S296 -> No registrado en cartera | O21: =Base!T296 -> No registrado en cartera | P21: =IF(Base!U296="","",Base!U296)
A22: =SUBTOTAL(103,$B$6:B22) -> 12 | B22: 394 | C22: =Base!G297 -> 2717158.MEJORAMIENTO DE LA PRODUCCION DE PACAS EN LA ASOCIACION DE PRODUCTORES AGROPECUARIOS Y FORESTALES SAN PEDRO DE FRAYLIMA, DISTRITO DE AZANGARO, PROVINCIA AZANGARO Y DEPARTAMENTO DE PUNO | D22: =Base!H297 -> 349792 | E22: =Base!I297 -> 321500 | F22: =D22-E22 -> 28292 | G22: =Base!K297 -> 0 | H22: =D22-G22 -> 349792 | I22: =IF(D22=0,0,G22/D22) -> 0 | J22: =Base!O297 -> Equipamiento / Contrata | K22: =Base!P297 -> Solo certificado | L22: =Base!Q297 -> No registrado en cartera | M22: =Base!R297 -> No registrado en cartera | N22: =Base!S297 -> No registrado en cartera | O22: =Base!T297 -> No registrado en cartera | P22: =IF(Base!U297="","",Base!U297)
A23: =SUBTOTAL(103,$B$6:B23) -> 13 | B23: 408 | C23: =Base!G298 -> 2717173.MEJORAMIENTO DE LA PRODUCCION DE DERIVADOS DE QUINUA EN HARINA EXTRUIDA Y POP EXTRUIDO DE LA EMPRESA CORPORACION DALSAR SOCIEDAD ANONIMA CERRADA DEL DISTRITO DE PUNO, PROVINCIA PUNO, DEPARTAMENTO PUNO. | D23: =Base!H298 -> 349792 | E23: =Base!I298 -> 329100 | F23: =D23-E23 -> 20692 | G23: =Base!K298 -> 0 | H23: =D23-G23 -> 349792 | I23: =IF(D23=0,0,G23/D23) -> 0 | J23: =Base!O298 -> Equipamiento / Contrata | K23: =Base!P298 -> Solo certificado | L23: =Base!Q298 -> No registrado en cartera | M23: =Base!R298 -> No registrado en cartera | N23: =Base!S298 -> No registrado en cartera | O23: =Base!T298 -> No registrado en cartera | P23: =IF(Base!U298="","",Base!U298)
A24: =SUBTOTAL(103,$B$6:B24) -> 14 | B24: 421 | C24: =Base!G299 -> 2717189.MEJORAMIENTO DE LA PRODUCCION DE YOGURT EN EL AEO AGROINDUSTRIA YOGULE S.A.C., DISTRITO DE CABANA, PROVINCIA SAN ROMAN, REGION PUNO | D24: =Base!H299 -> 346711 | E24: =Base!I299 -> 318955 | F24: =D24-E24 -> 27756 | G24: =Base!K299 -> 112190 | H24: =D24-G24 -> 234521 | I24: =IF(D24=0,0,G24/D24) -> 0.32358362 | J24: =Base!O299 -> Equipamiento / Contrata | K24: =Base!P299 -> Comprometido | L24: =Base!Q299 -> No registrado en cartera | M24: =Base!R299 -> No registrado en cartera | N24: =Base!S299 -> No registrado en cartera | O24: =Base!T299 -> No registrado en cartera | P24: =IF(Base!U299="","",Base!U299)
A25: =SUBTOTAL(103,$B$6:B25) -> 15 | B25: 387 | C25: =Base!G300 -> 2717151.MEJORAMIENTO DE LA PRODUCCION DE LECHE FRESCA EN LA ASOCIACION DE PRODUCTORES AGROPECUARIOS SUMAC KANCHAY DE LA LIBERTAD NUNOA MELGAR PUNO, DISTRITO DE NUNOA, PROVINCIA DE MELGAR Y REGION PUNO | D25: =Base!H300 -> 269980 | E25: =Base!I300 -> 259749 | F25: =D25-E25 -> 10231 | G25: =Base!K300 -> 255066 | H25: =D25-G25 -> 14914 | I25: =IF(D25=0,0,G25/D25) -> 0.94475887 | J25: =Base!O300 -> Equipamiento / Contrata | K25: =Base!P300 -> Comprometido | L25: =Base!Q300 -> No registrado en cartera | M25: =Base!R300 -> No registrado en cartera | N25: =Base!S300 -> No registrado en cartera | O25: =Base!T300 -> No registrado en cartera | P25: =IF(Base!U300="","",Base!U300)
A26: =SUBTOTAL(103,$B$6:B26) -> 16 | B26: 378 | C26: =Base!G301 -> 2676440: MEJORAMIENTO DE LA PRODUCCION Y LA PRODUCTIVIDAD DE QUESO TIPO PARIA PASTEURIZADO DE LA EMPRESA DE PRODUCCION AGROPECUARIA MICA ASUNCION SAC DEL, DISTRITO DE AZANGARO, PROVINCIA AZANGARO, DEPARTAMENTO PUNO. | D26: =Base!H301 -> 209400 | E26: =Base!I301 -> 176550 | F26: =D26-E26 -> 32850 | G26: =Base!K301 -> 136550 | H26: =D26-G26 -> 72850 | I26: =IF(D26=0,0,G26/D26) -> 0.65210124 | J26: =Base!O301 -> Equipamiento / Contrata | K26: =Base!P301 -> Comprometido | L26: =Base!Q301 -> No registrado en cartera | M26: =Base!R301 -> No registrado en cartera | N26: =Base!S301 -> No registrado en cartera | O26: =Base!T301 -> No registrado en cartera | P26: =IF(Base!U301="","",Base!U301)
A27: =SUBTOTAL(103,$B$6:B27) -> 17 | B27: 392 | C27: =Base!G302 -> 2717156.MEJORAMIENTO DE LA PRODUCCION Y LA COMERCIALIZACION DE LECHE FRESCA EN LA ORGANIZACION DE PRODUCTORES SAN JUAN DE FAON DEL DISTRITO DE HUATA, PROVINCIA DE PUNO, DEPARTAMENTO DE PUNO. | D27: =Base!H302 -> 160000 | E27: =Base!I302 -> 143401 | F27: =D27-E27 -> 16599 | G27: =Base!K302 -> 143401 | H27: =D27-G27 -> 16599 | I27: =IF(D27=0,0,G27/D27) -> 0.89625625 | J27: =Base!O302 -> Equipamiento / Contrata | K27: =Base!P302 -> Comprometido | L27: =Base!Q302 -> No registrado en cartera | M27: =Base!R302 -> No registrado en cartera | N27: =Base!S302 -> No registrado en cartera | O27: =Base!T302 -> No registrado en cartera | P27: =IF(Base!U302="","",Base!U302)
A28: =SUBTOTAL(103,$B$6:B28) -> 18 | B28: 393 | C28: =Base!G303 -> 2717157.MEJORAMIENTO DE LA PRODUCCION Y ENGORDE DE GANADO VACUNO A TRAVES DE LA OPTIMIZACION DE LA ALIMENTACION EN LA ASOCIACION DE PRODUCTORES AGROPECUARIOS EL TORITO BRAVO DEL DISTRITO DE QUILCAPUNCO, PROVINCIA DE SAN ANTONIO DE PUTINA, REGION PUNO. | D28: =Base!H303 -> 160000 | E28: =Base!I303 -> 149840 | F28: =D28-E28 -> 10160 | G28: =Base!K303 -> 18740 | H28: =D28-G28 -> 141260 | I28: =IF(D28=0,0,G28/D28) -> 0.117125 | J28: =Base!O303 -> Equipamiento / Contrata | K28: =Base!P303 -> Comprometido | L28: =Base!Q303 -> No registrado en cartera | M28: =Base!R303 -> No registrado en cartera | N28: =Base!S303 -> No registrado en cartera | O28: =Base!T303 -> No registrado en cartera | P28: =IF(Base!U303="","",Base!U303)
A29: =SUBTOTAL(103,$B$6:B29) -> 19 | B29: 397 | C29: =Base!G304 -> 2717161.MEJORAMIENTO DE LA CAPACIDAD DE TRANSFORMACION DE CHIPS DE PAPA NATIVA, EN LA AEO ASOCIACION DE PRODUCTORES MULTIPLES SAN ISIDRO DE TANTAMACO DEL DISTRITO DE MACUSANI, PROVINCIA DE CARABAYA, REGION DE PUNO | D29: =Base!H304 -> 160000 | E29: =Base!I304 -> 148990 | F29: =D29-E29 -> 11010 | G29: =Base!K304 -> 26000 | H29: =D29-G29 -> 134000 | I29: =IF(D29=0,0,G29/D29) -> 0.1625 | J29: =Base!O304 -> Equipamiento / Contrata | K29: =Base!P304 -> Comprometido | L29: =Base!Q304 -> No registrado en cartera | M29: =Base!R304 -> No registrado en cartera | N29: =Base!S304 -> No registrado en cartera | O29: =Base!T304 -> No registrado en cartera | P29: =IF(Base!U304="","",Base!U304)
A30: =SUBTOTAL(103,$B$6:B30) -> 20 | B30: 404 | C30: =Base!G305 -> 2717169.CREACION DE UNA PLANTA PROCESADORA DE QUINUA EN LA AEO ASOCIACION DE PRODUCTORES AGROPECUARIOS ROQUE APAZA PAMPA DEL DISTRITO DE PAUCARCOLLA, PROVINCIA DE PUNO, DEPARTAMENTO DE PUNO | D30: =Base!H305 -> 160000 | E30: =Base!I305 -> 150870 | F30: =D30-E30 -> 9130 | G30: =Base!K305 -> 45270 | H30: =D30-G30 -> 114730 | I30: =IF(D30=0,0,G30/D30) -> 0.2829375 | J30: =Base!O305 -> Equipamiento / Contrata | K30: =Base!P305 -> Comprometido | L30: =Base!Q305 -> No registrado en cartera | M30: =Base!R305 -> No registrado en cartera | N30: =Base!S305 -> No registrado en cartera | O30: =Base!T305 -> No registrado en cartera | P30: =IF(Base!U305="","",Base!U305)
... A82: =SUBTOTAL(103,$B$6:B82) -> 72 | B82: 526 | C82: =Base!G357 -> 2681133.MEJORAMIENTO DE LA PRODUCCION DE QUESOS TIPO PARIA PASTEURIZADO DE LA CENTRAL DE ASOCIACIONES GANADEROS LECHEROS Y AGRARIOS DEL DISTRITO DE VILQUE, DISTRITO DE VILQUE, PROVINCIA DE PUNO, REGION PUNO | D82: =Base!H357 -> 2795 | E82: =Base!I357 -> 2795 | F82: =D82-E82 -> 0 | G82: =Base!K357 -> 0 | H82: =D82-G82 -> 2795 | I82: =IF(D82=0,0,G82/D82) -> 0 | J82: =Base!O357 -> Contrata | K82: =Base!P357 -> Solo certificado | L82: =Base!Q357 -> No registrado en cartera | M82: =Base!R357 -> No registrado en cartera | N82: =Base!S357 -> No registrado en cartera | O82: =Base!T357 -> No registrado en cartera | P82: =IF(Base!U357="","",Base!U357)
A83: 11. PESCA | D83: =SUM(D84:D87) -> 1054126 | E83: =SUM(E84:E87) -> 893638.67 | F83: =SUM(F84:F87) -> 160487.33 | G83: =SUM(G84:G87) -> 30322 | H83: =SUM(H84:H87) -> 1023804 | I83: =IF(D83=0,0,G83/D83) -> 0.028765062
A84: =SUBTOTAL(103,$B$6:B84) -> 73 | B84: 368 | C84: =Base!G358 -> 2681278: MEJORAMIENTO DEL PROCESO DE PRODUCCION DE SELECCIONADOR DE TRUCHAS EN MAQUINARIAS ACUITROUT SOCIEDAD COMERCIAL DE RESPONSABILIDAD DE LA COMUNIDAD DE KOLLPAJAHUIRA, DISTRITO DE JULI, PROVINCIA DE CHUCUITO, DEPARTAMENTO DE PUNO | D84: =Base!H358 -> 179500 | E84: =Base!I358 -> 163750 | F84: =D84-E84 -> 15750 | G84: =Base!K358 -> 3750 | H84: =D84-G84 -> 175750 | I84: =IF(D84=0,0,G84/D84) -> 0.020891365 | J84: =Base!O358 -> Equipamiento / Contrata | K84: =Base!P358 -> Comprometido | L84: =Base!Q358 -> No registrado en cartera | M84: =Base!R358 -> No registrado en cartera | N84: =Base!S358 -> No registrado en cartera | O84: =Base!T358 -> No registrado en cartera | P84: =IF(Base!U358="","",Base!U358)
A85: =SUBTOTAL(103,$B$6:B85) -> 74 | B85: 375 | C85: =Base!G359 -> 2681123: MEJORAMIENTO EN EL PROCESO DE VALOR AGREGADO DE TRUCHAS EN LA EMPRESA AMERICAN TROUT FARO S.R.L. EN EL DISTRITO DE POMATA, PROVINCIA DE CHUCUITO Y DEPARTAMENTO DE PUNO. | D85: =Base!H359 -> 175166 | E85: =Base!I359 -> 166872 | F85: =D85-E85 -> 8294 | G85: =Base!K359 -> 5872 | H85: =D85-G85 -> 169294 | I85: =IF(D85=0,0,G85/D85) -> 0.033522487 | J85: =Base!O359 -> Equipamiento / Contrata | K85: =Base!P359 -> Comprometido | L85: =Base!Q359 -> No registrado en cartera | M85: =Base!R359 -> No registrado en cartera | N85: =Base!S359 -> No registrado en cartera | O85: =Base!T359 -> No registrado en cartera | P85: =IF(Base!U359="","",Base!U359)
A86: =SUBTOTAL(103,$B$6:B86) -> 75 | B86: 417 | C86: =Base!G360 -> 2717185.MEJORAMIENTO DE VALOR AGREGADO DE LA TRUCHA EN AQUA INDUSTRIAS EL FARO SOCIEDAD COMERCIAL DE RESPONSABILIDAD LIMITADA, DISTRITO DE POMATA, PROVINCIA DE CHUCUITO Y DEPARTAMENTO DE PUNO | D86: =Base!H360 -> 349792 | E86: =Base!I360 -> 325833.33 | F86: =D86-E86 -> 23958.67 | G86: =Base!K360 -> 0 | H86: =D86-G86 -> 349792 | I86: =IF(D86=0,0,G86/D86) -> 0 | J86: =Base!O360 -> Equipamiento / Contrata | K86: =Base!P360 -> Comprometido | L86: =Base!Q360 -> No registrado en cartera | M86: =Base!R360 -> No registrado en cartera | N86: =Base!S360 -> No registrado en cartera | O86: =Base!T360 -> No registrado en cartera | P86: =IF(Base!U360="","",Base!U360)
A87: =SUBTOTAL(103,$B$6:B87) -> 76 | B87: 474 | C87: =Base!G361 -> 2723300.MEJORAMIENTO DE LA PRODUCCION Y TRANSFORMACION DE FILETE DE TRUCHA DE LA EMPRESA TITIKAKA TROUT PERU SOCIEDAD COMERCIAL DE RESPONSABILIDAD LIMITADA DEL DISTRITO DE POMATA, PROVINCIA DE CHUCUITO, REGION PUNO | D87: =Base!H361 -> 349668 | E87: =Base!I361 -> 237183.34 | F87: =D87-E87 -> 112484.66 | G87: =Base!K361 -> 20700 | H87: =D87-G87 -> 328968 | I87: =IF(D87=0,0,G87/D87) -> 0.059199012 | J87: =Base!O361 -> Equipamiento / Contrata | K87: =Base!P361 -> Comprometido | L87: =Base!Q361 -> No registrado en cartera | M87: =Base!R361 -> No registrado en cartera | N87: =Base!S361 -> No registrado en cartera | O87: =Base!T361 -> No registrado en cartera | P87: =IF(Base!U361="","",Base!U361)
A88: 14. INDUSTRIA | D88: =SUM(D89:D95) -> 1308816 | E88: =SUM(E89:E95) -> 1209080 | F88: =SUM(F89:F95) -> 99736 | G88: =SUM(G89:G95) -> 538610 | H88: =SUM(H89:H95) -> 770206 | I88: =IF(D88=0,0,G88/D88) -> 0.41152461
A89: =SUBTOTAL(103,$B$6:B89) -> 77 | B89: 356 | C89: =Base!G362 -> 2676422: MEJORAMIENTO DE LA COMPETITIVIDAD PRODUCTIVA DE LA CERAMICA TRADICIONAL DE CHECCA PUPUJA EN LA ASOCIACION CERAMICA TRADICIONAL ANCESTRAL CHACCA PUPUJA, DISTRITO DE JOSE DOMINGO CHOQUEHUANCA, PROVINCIA DE AZANGARO, REGION PUNO. | D89: =Base!H362 -> 5365 | E89: =Base!I362 -> 5364 | F89: =D89-E89 -> 1 | G89: =Base!K362 -> 5364 | H89: =D89-G89 -> 1 | I89: =IF(D89=0,0,G89/D89) -> 0.99981361 | J89: =Base!O362 -> Contrata | K89: =Base!P362 -> Comprometido | L89: =Base!Q362 -> No registrado en cartera | M89: =Base!R362 -> No registrado en cartera | N89: =Base!S362 -> No registrado en cartera | O89: =Base!T362 -> No registrado en cartera | P89: =IF(Base!U362="","",Base!U362)
A90: =SUBTOTAL(103,$B$6:B90) -> 78 | B90: 374 | C90: =Base!G363 -> 2681274: MEJORAMIENTO DEL PROCESO DE PRODUCCION DE ARTICULOS MECANICOS EN LA CORPORACION MARSAD S.A.C. DEL DISTRITO DE PUNO, PROVINCIA DE PUNO, REGION DE PUNO | D90: =Base!H363 -> 335890 | E90: =Base!I363 -> 314900 | F90: =D90-E90 -> 20990 | G90: =Base!K363 -> 0 | H90: =D90-G90 -> 335890 | I90: =IF(D90=0,0,G90/D90) -> 0 | J90: =Base!O363 -> Equipamiento / Contrata | K90: =Base!P363 -> Comprometido | L90: =Base!Q363 -> No registrado en cartera | M90: =Base!R363 -> No registrado en cartera | N90: =Base!S363 -> No registrado en cartera | O90: =Base!T363 -> No registrado en cartera | P90: =IF(Base!U363="","",Base!U363)
A91: =SUBTOTAL(103,$B$6:B91) -> 79 | B91: 377 | C91: =Base!G364 -> 2681130: MEJORAMIENTO DE LA PRODUCCION DEL ENVASADO DE AGUA DE MESA DE LA EMPRESA GRUPO ANCCASI SOCIEDAD ANONIMA CERRADA DEL DISTRITO DE CORANI, PROVINCIA CARABAYA, DEPARTAMENTO PUNO | D91: =Base!H364 -> 157066 | E91: =Base!I364 -> 157066 | F91: =D91-E91 -> 0 | G91: =Base!K364 -> 157066 | H91: =D91-G91 -> 0 | I91: =IF(D91=0,0,G91/D91) -> 1 | J91: =Base!O364 -> Equipamiento / Contrata | K91: =Base!P364 -> Devengado total | L91: =Base!Q364 -> No registrado en cartera | M91: =Base!R364 -> No registrado en cartera | N91: =Base!S364 -> No registrado en cartera | O91: =Base!T364 -> No registrado en cartera | P91: =IF(Base!U364="","",Base!U364)
A92: =SUBTOTAL(103,$B$6:B92) -> 80 | B92: 386 | C92: =Base!G365 -> 2717150.MEJORAMIENTO DEL PROCESO PRODUCTIVO Y EL VALOR CULTURAL DE LAS CERAMICAS DE LA ASOCIACION DE ARTESANOS PRODUCTORES MUSUQ PAQARIY PUKARA, DEL DISTRITO DE PUCARA, PROVINCIA DE LAMPA, DEPARTAMENTO DE PUNO | D92: =Base!H365 -> 159345 | E92: =Base!I365 -> 150543 | F92: =D92-E92 -> 8802 | G92: =Base!K365 -> 150263 | H92: =D92-G92 -> 9082 | I92: =IF(D92=0,0,G92/D92) -> 0.94300417 | J92: =Base!O365 -> Equipamiento / Contrata | K92: =Base!P365 -> Comprometido | L92: =Base!Q365 -> No registrado en cartera | M92: =Base!R365 -> No registrado en cartera | N92: =Base!S365 -> No registrado en cartera | O92: =Base!T365 -> No registrado en cartera | P92: =IF(Base!U365="","",Base!U365)
A93: =SUBTOTAL(103,$B$6:B93) -> 81 | B93: 473 | C93: =Base!G366 -> 2723295.MEJORAMIENTO DE LA PRODUCCION Y COMERCIALIZACION DE QUESOS TIPO PARIA DE LA ASOCIACION AGROINDUSTRIAL YURAQ WASI DE LA COMUNIDAD CAMPESINA PRIMER JILAHUATA, DISTRITO DE AZANGARO, PROVINCIA DE AZANGARO, REGION PUNO | D93: =Base!H366 -> 160000 | E93: =Base!I366 -> 145797 | F93: =D93-E93 -> 14203 | G93: =Base!K366 -> 139797 | H93: =D93-G93 -> 20203 | I93: =IF(D93=0,0,G93/D93) -> 0.87373125 | J93: =Base!O366 -> Equipamiento / Contrata | K93: =Base!P366 -> Comprometido | L93: =Base!Q366 -> No registrado en cartera | M93: =Base!R366 -> No registrado en cartera | N93: =Base!S366 -> No registrado en cartera | O93: =Base!T366 -> No registrado en cartera | P93: =IF(Base!U366="","",Base!U366)
A94: =SUBTOTAL(103,$B$6:B94) -> 82 | B94: 476 | C94: =Base!G367 -> 2723301.MEJORAMIENTO DE LA TRANSFORMACION Y COMERCIALIZACION DE HILOS Y PRENDAS DE TONOS Y TENIDOS NATURALES DE FIBRA DE ALPACA EN LA ASOCIACION DE ARTESANAS KISWAR TIKA, DISTRITO DE OCUVIRI, PROVINCIA LAMPA, REGION PUNO | D94: =Base!H367 -> 141150 | E94: =Base!I367 -> 115290 | F94: =D94-E94 -> 25860 | G94: =Base!K367 -> 0 | H94: =D94-G94 -> 141150 | I94: =IF(D94=0,0,G94/D94) -> 0 | J94: =Base!O367 -> Equipamiento / Contrata | K94: =Base!P367 -> Comprometido | L94: =Base!Q367 -> No registrado en cartera | M94: =Base!R367 -> No registrado en cartera | N94: =Base!S367 -> No registrado en cartera | O94: =Base!T367 -> No registrado en cartera | P94: =IF(Base!U367="","",Base!U367)
A95: =SUBTOTAL(103,$B$6:B95) -> 83 | B95: 477 | C95: =Base!G368 -> 2723299.MEJORAMIENTO DE LA CAPACIDAD PRODUCTIVA DE HELADOS ARTESANALES A BASE DE GRANOS ANDINOS DEL GRUPO DE PRODUCTORES, COMERCIALIZACION Y TRANSFORMACION DE CEREALES ANDINOS SAN SANTIAGO S.A.C., DEL DISTRITO DE PUNO, PROVINCIA DE PUNO, REGION DE PUNO. | D95: =Base!H368 -> 350000 | E95: =Base!I368 -> 320120 | F95: =D95-E95 -> 29880 | G95: =Base!K368 -> 86120 | H95: =D95-G95 -> 263880 | I95: =IF(D95=0,0,G95/D95) -> 0.24605714 | J95: =Base!O368 -> Equipamiento / Contrata | K95: =Base!P368 -> Comprometido | L95: =Base!Q368 -> No registrado en cartera | M95: =Base!R368 -> No registrado en cartera | N95: =Base!S368 -> No registrado en cartera | O95: =Base!T368 -> No registrado en cartera | P95: =IF(Base!U368="","",Base!U368)
A96: GERENCIA REGIONAL DE RECURSOS NATURALES Y GESTION AMBIENTAL | D96: =D97+D101+D103 -> 18155027 | E96: =E97+E101+E103 -> 15578094 | F96: =F97+F101+F103 -> 2576932.7 | G96: =G97+G101+G103 -> 8757642.5 | H96: =H97+H101+H103 -> 9397384.5 | I96: =IF(D96=0,0,G96/D96) -> 0.48238113
A97: 05. ORDEN PUBLICO Y SEGURIDAD | D97: =SUM(D98:D100) -> 16120710 | E97: =SUM(E98:E100) -> 15413788 | F97: =SUM(F98:F100) -> 706921.89 | G97: =SUM(G98:G100) -> 8626797.8 | H97: =SUM(H98:H100) -> 7493912.2 | I97: =IF(D97=0,0,G97/D97) -> 0.53513759
A98: =SUBTOTAL(103,$B$6:B98) -> 84 | B98: 4 | C98: =Base!G369 -> 2183634: MEJORAMIENTO DE LA DEFENSA RIBEREÑA EN LAS MARGENES DERECHA E IZQUIERDA DEL RIO RAMIS EN LOS TRAMOS DE SACASCO, COLLANA, CHACAMARCA, PATASCACHI, YANAOCO, TUNI GRANDE, RAMIS Y BALSAPATA DE LAS PROVINCIAS DE HUANCANE Y AZANGARO - REGION PUNO | D98: =Base!H369 -> 10918999 | E98: =Base!I369 -> 10451686 | F98: =D98-E98 -> 467312.78 | G98: =Base!K369 -> 5853517.8 | H98: =D98-G98 -> 5065481.2 | I98: =IF(D98=0,0,G98/D98) -> 0.53608557 | J98: =Base!O369 -> Administración directa / Contrata / Personal/bienes/servicios | K98: =Base!P369 -> Comprometido | L98: =Base!Q369 -> 10517000 | M98: =Base!R369 -> 7783178 | N98: =Base!S369 -> 1598000 | O98: =Base!T369 -> 2000000 | P98: =IF(Base!U369="","",Base!U369)
A99: =SUBTOTAL(103,$B$6:B99) -> 85 | B99: 6 | C99: =Base!G370 -> 2532916: CREACION DEL SERVICIO DE PROTECCION EN RIBERAS DEL RIO LORIPONGO Y MOLLA AMBOS MARGENES VULNERABLES ANTE EL PELIGRO DE INUNDACION EN LA LOCALIDAD DE LARAQUERI Y CENTRO POBLADO DE HUARIJUYO DEL DISTRITO DE PICHACANI - PROVINCIA DE PUNO - DEPARTAMENTO DE PUNO | D99: =Base!H370 -> 19658 | E99: =Base!I370 -> 3612 | F99: =D99-E99 -> 16046 | G99: =Base!K370 -> 0 | H99: =D99-G99 -> 19658 | I99: =IF(D99=0,0,G99/D99) -> 0 | J99: =Base!O370 -> Expediente técnico | K99: =Base!P370 -> Solo certificado | L99: =Base!Q370 -> 200000 | M99: =Base!R370 -> 2915452 | N99: =Base!S370 -> 2124684 | O99: =Base!T370 -> 2000000 | P99: =IF(Base!U370="","",Base!U370)
A100: =SUBTOTAL(103,$B$6:B100) -> 86 | B100: 303 | C100: =Base!G371 -> 2520451: CREACION DEL SERVICIO DE PROTECCION EN RIBERAS DEL RIO QUELLOMAYO MARGEN DERECHO VULNERABLES ANTE EL PELIGRO DE INUNDACION EN LA LOCALIDAD DE SAN GABAN, DEL DISTRITO DE SAN GABAN - PROVINCIA DE CARABAYA - DEPARTAMENTO DE PUNO | D100: =Base!H371 -> 5182053 | E100: =Base!I371 -> 4958489.9 | F100: =D100-E100 -> 223563.11 | G100: =Base!K371 -> 2773280 | H100: =D100-G100 -> 2408773 | I100: =IF(D100=0,0,G100/D100) -> 0.53517013 | J100: =Base!O371 -> Administración directa / Contrata / Personal/bienes/servicios | K100: =Base!P371 -> Comprometido | L100: =Base!Q371 -> 409040 | M100: =Base!R371 -> 29865 | N100: =Base!S371 -> 0 | O100: =Base!T371 -> 0 | P100: =IF(Base!U371="","",Base!U371)
A101: 10. AGROPECUARIA | D101: =SUM(D102) -> 1800000 | E101: =SUM(E102) -> 26893 | F101: =SUM(F102) -> 1773107 | G101: =SUM(G102) -> 26892.69 | H101: =SUM(H102) -> 1773107.3 | I101: =IF(D101=0,0,G101/D101) -> 0.014940383
A102: =SUBTOTAL(103,$B$6:B102) -> 87 | B102: 5 | C102: =Base!G372 -> 2474102: MEJORAMIENTO DEL SERVICIO DE PROTECCION FRENTE A TORMENTAS ELECTRICAS EN 4 PROVINCIAS DEL DEPARTAMENTO DE PUNO | D102: =Base!H372 -> 1800000 | E102: =Base!I372 -> 26893 | F102: =D102-E102 -> 1773107 | G102: =Base!K372 -> 26892.69 | H102: =D102-G102 -> 1773107.3 | I102: =IF(D102=0,0,G102/D102) -> 0.014940383 | J102: =Base!O372 -> Personal/bienes/servicios / Contrata / Equipamiento / Expediente técnico | K102: =Base!P372 -> Comprometido | L102: =Base!Q372 -> 300000 | M102: =Base!R372 -> 4508196 | N102: =Base!S372 -> 5000000 | O102: =Base!T372 -> 1000000 | P102: =IF(Base!U372="","",Base!U372)
A103: 17. AMBIENTE | D103: =SUM(D104:D110) -> 234317 | E103: =SUM(E104:E110) -> 137413.2 | F103: =SUM(F104:F110) -> 96903.8 | G103: =SUM(G104:G110) -> 103951.95 | H103: =SUM(H104:H110) -> 130365.05 | I103: =IF(D103=0,0,G103/D103) -> 0.44363811
A104: =SUBTOTAL(103,$B$6:B104) -> 88 | B104: 7 | C104: =Base!G373 -> 2533866: RECUPERACION DE ECOSISTEMAS DEGRADADOS POR VERTIMIENTO DE AGUAS RESIDUALES Y RESIDUOS SOLIDOS EN LA DESEMBOCADURA DEL RIO COATA, EN LOS DISTRITOS DE HUATA, COATA, CAPACHICA, JULIACA Y SAN MIGUEL EN LAS PROVINCIAS DE PUNO Y SAN ROMAN DEL DEPARTAMENTO DE PUNO | D104: =Base!H373 -> 32099 | E104: =Base!I373 -> 0 | F104: =D104-E104 -> 32099 | G104: =Base!K373 -> 0 | H104: =D104-G104 -> 32099 | I104: =IF(D104=0,0,G104/D104) -> 0 | J104: =Base!O373 -> Contrata | K104: =Base!P373 -> Sin certificar | L104: =Base!Q373 -> 500000 | M104: =Base!R373 -> 0 | N104: =Base!S373 -> 0 | O104: =Base!T373 -> 0 | P104: =IF(Base!U373="","",Base!U373)
A105: =SUBTOTAL(103,$B$6:B105) -> 89 | B105: 152 | C105: =Base!G374 -> 2250970: MEJORAMIENTO DEL SERVICIO DE CONSERVACION DE LA DIVERSIDAD BIOLOGICA EN SELVA VERDE, SAN GABAN, PUNTA PERDIDA, COTACUCHO, PUNO, JUCUMARINI, CUSHINI, RIO CONDOR, RIO TAVARA, Y PACO PACUNI, DISTRITOS DE AYAPATA, SAN GABAN, SANTA ROSA, VILQUE CHICO-PUNO | D105: =Base!H374 -> 30000 | E105: =Base!I374 -> 23434 | F105: =D105-E105 -> 6566 | G105: =Base!K374 -> 13106.35 | H105: =D105-G105 -> 16893.65 | I105: =IF(D105=0,0,G105/D105) -> 0.43687833 | J105: =Base!O374 -> Contrata / Personal/bienes/servicios | K105: =Base!P374 -> Comprometido | L105: =Base!Q374 -> 2080646 | M105: =Base!R374 -> 70728 | N105: =Base!S374 -> 300000 | O105: =Base!T374 -> 300000 | P105: =IF(Base!U374="","",Base!U374)
A106: =SUBTOTAL(103,$B$6:B106) -> 90 | B106: 154 | C106: =Base!G375 -> 2631070: RECUPERACION DE LOS SERVICIOS ECOSISTEMICOS EN 19 UNIDADES PRODUCTORAS 19 DISTRITOS DE 13 PROVINCIAS DEL DEPARTAMENTO DE PUNO | D106: =Base!H375 -> 90586 | E106: =Base!I375 -> 90435.2 | F106: =D106-E106 -> 150.8 | G106: =Base!K375 -> 78301.6 | H106: =D106-G106 -> 12284.4 | I106: =IF(D106=0,0,G106/D106) -> 0.86438964 | J106: =Base!O375 -> Expediente técnico | K106: =Base!P375 -> Comprometido | L106: =Base!Q375 -> 100000 | M106: =Base!R375 -> 0 | N106: =Base!S375 -> 2000000 | O106: =Base!T375 -> 2000000 | P106: =IF(Base!U375="","",Base!U375)
A107: =SUBTOTAL(103,$B$6:B107) -> 91 | B107: 250 | C107: =Base!G376 -> 2549395: RECUPERACION DE ECOSISTEMAS DEGRADADOS EN LAS UNIDADES HIDROGRAFICAS: LLALLIMAYO DE LA UH 018 PUCARA Y UH 019 AZANGARO, DE LA CUENCA RAMIS DEL DEPARTAMENTO DE PUNO, REGION PUNO 5 PROVINCIAS DEL DEPARTAMENTO DE PUNO | D107: =Base!H376 -> 0 | E107: =Base!I376 -> 0 | F107: =D107-E107 -> 0 | G107: =Base!K376 -> 0 | H107: =D107-G107 -> 0 | I107: =IF(D107=0,0,G107/D107) -> 0 | J107: =Base!O376 -> Contrata | K107: =Base!P376 -> Sin PIM | L107: =Base!Q376 -> 800000 | M107: =Base!R376 -> 0 | N107: =Base!S376 -> 0 | O107: =Base!T376 -> 0 | P107: =IF(Base!U376="","",Base!U376)
A108: =SUBTOTAL(103,$B$6:B108) -> 92 | B108: 253 | C108: =Base!G377 -> 2566295: RECUPERACION DE ECOSISTEMAS DEGRADADOS EN ZONAS ALTO ANDINAS EN CABECERA DE CUENCA DE LAS UH0172, UH0178 Y UH0171 CUENCA SUCHES EN 4 PROVINCIAS DEL DEPARTAMENTO DE PUNO | D108: =Base!H377 -> 0 | E108: =Base!I377 -> 0 | F108: =D108-E108 -> 0 | G108: =Base!K377 -> 0 | H108: =D108-G108 -> 0 | I108: =IF(D108=0,0,G108/D108) -> 0 | J108: =Base!O377 -> Personal/bienes/servicios | K108: =Base!P377 -> Sin PIM | L108: =Base!Q377 -> 200000 | M108: =Base!R377 -> 0 | N108: =Base!S377 -> 0 | O108: =Base!T377 -> 0 | P108: =IF(Base!U377="","",Base!U377)
A109: =SUBTOTAL(103,$B$6:B109) -> 93 | B109: 465 | C109: =Base!G378 -> 2260735: MEJORAMIENTO DE LA GESTION INTEGRADA DE LOS RECURSOS HIDRICOS EN CUENCAS DE LA REGION PUNO | D109: =Base!H378 -> 70632 | E109: =Base!I378 -> 12544 | F109: =D109-E109 -> 58088 | G109: =Base!K378 -> 12544 | H109: =D109-G109 -> 58088 | I109: =IF(D109=0,0,G109/D109) -> 0.17759656 | J109: =Base!O378 -> Contrata / Personal/bienes/servicios | K109: =Base!P378 -> Comprometido | L109: =Base!Q378 -> 70632 | M109: =Base!R378 -> 0 | N109: =Base!S378 -> 0 | O109: =Base!T378 -> 0 | P109: =IF(Base!U378="","",Base!U378)
A110: =SUBTOTAL(103,$B$6:B110) -> 94 | B110: 471 | C110: =Base!G379 -> 2684838.MEJORAMIENTO Y AMPLIACION DEL SERVICIO DE LIMPIEZA PUBLICA EN 7 UNIDADES PRODUCTORAS 7 DISTRITOS DE LA PROVINCIA DE MELGAR DEL DEPARTAMENTO DE PUNO | D110: =Base!H379 -> 11000 | E110: =Base!I379 -> 11000 | F110: =D110-E110 -> 0 | G110: =Base!K379 -> 0 | H110: =D110-G110 -> 11000 | I110: =IF(D110=0,0,G110/D110) -> 0 | J110: =Base!O379 -> Contrata / Administración directa | K110: =Base!P379 -> Solo certificado | L110: =Base!Q379 -> 11000 | M110: =Base!R379 -> 164792 | N110: =Base!S379 -> 9322563 | O110: =Base!T379 -> 9322563 | P110: =IF(Base!U379="","",Base!U379)
A111: PROYECTO ESPECIAL TRUCHAS TITICACA - PETT | D111: =D112 -> 13183082 | E111: =E112 -> 12706541 | F111: =F112 -> 476541.15 | G111: =G112 -> 3714211.5 | H111: =H112 -> 9468870.5 | I111: =IF(D111=0,0,G111/D111) -> 0.28174076
A112: 03. PLANEAMIENTO, GESTION Y RESERVA DE CONTINGENCIA | D112: =SUM(D113:D115) -> 13183082 | E112: =SUM(E113:E115) -> 12706541 | F112: =SUM(F113:F115) -> 476541.15 | G112: =SUM(G113:G115) -> 3714211.5 | H112: =SUM(H113:H115) -> 9468870.5 | I112: =IF(D112=0,0,G112/D112) -> 0.28174076
A113: =SUBTOTAL(103,$B$6:B113) -> 95 | B113: 59 | C113: =Base!G380 -> 2324613: MEJORAMIENTO DE LAS CAPACIDADES TECNOLOGICAS EN EL MANEJO DE CADENA PRODUCTIVA DE TRUCHA EN LA REGION PUNO | D113: =Base!H380 -> 550560 | E113: =Base!I380 -> 519500 | F113: =D113-E113 -> 31060 | G113: =Base!K380 -> 517920.09 | H113: =D113-G113 -> 32639.91 | I113: =IF(D113=0,0,G113/D113) -> 0.94071507 | J113: =Base!O380 -> Personal/bienes/servicios / Contrata | K113: =Base!P380 -> Comprometido | L113: =Base!Q380 -> 100560 | M113: =Base!R380 -> 93700 | N113: =Base!S380 -> 0 | O113: =Base!T380 -> 0 | P113: =IF(Base!U380="","",Base!U380)
A114: =SUBTOTAL(103,$B$6:B114) -> 96 | B114: 60 | C114: =Base!G381 -> 2603148: MEJORAMIENTO DE LOS SERVICIOS DE APOYO AL DESARROLLO PRODUCTIVO EN 19 UNIDADES PRODUCTORAS 19 DISTRITOS DE 7 PROVINCIAS DEL DEPARTAMENTO DE PUNO | D114: =Base!H381 -> 12532522 | E114: =Base!I381 -> 12187041 | F114: =D114-E114 -> 345481.15 | G114: =Base!K381 -> 3196291.4 | H114: =D114-G114 -> 9336230.6 | I114: =IF(D114=0,0,G114/D114) -> 0.25503976 | J114: =Base!O381 -> Administración directa / Personal/bienes/servicios / Contrata / Equipamiento | K114: =Base!P381 -> Comprometido | L114: =Base!Q381 -> 1000000 | M114: =Base!R381 -> 4832260 | N114: =Base!S381 -> 1000000 | O114: =Base!T381 -> 1000000 | P114: =IF(Base!U381="","",Base!U381)
A115: =SUBTOTAL(103,$B$6:B115) -> 97 | B115: 61 | C115: =Base!G382 -> 2603160: MEJORAMIENTO DE LOS SERVICIOS DE APOYO AL DESARROLLO PRODUCTIVO EN 4 UNIDADES PRODUCTORAS 4 DISTRITOS DE LAS PROVINCIAS DE SANDIA, CARABAYA DEL DEPARTAMENTO DE PUNO | D115: =Base!H382 -> 100000 | E115: =Base!I382 -> 0 | F115: =D115-E115 -> 100000 | G115: =Base!K382 -> 0 | H115: =D115-G115 -> 100000 | I115: =IF(D115=0,0,G115/D115) -> 0 | J115: =Base!O382 -> Personal/bienes/servicios | K115: =Base!P382 -> Sin certificar | L115: =Base!Q382 -> 100000 | M115: =Base!R382 -> 0 | N115: =Base!S382 -> 0 | O115: =Base!T382 -> 0 | P115: =IF(Base!U382="","",Base!U382)
A116: PROYECTO ESPECIAL CAMELIDOS SUDAMERICANOS | D116: =D117+D119 -> 5603985 | E116: =E117+E119 -> 5402770 | F116: =F117+F119 -> 201215.05 | G116: =G117+G119 -> 3499541.4 | H116: =H117+H119 -> 2104443.6 | I116: =IF(D116=0,0,G116/D116) -> 0.62447372
A117: 03. PLANEAMIENTO, GESTION Y RESERVA DE CONTINGENCIA | D117: =SUM(D118) -> 1332387 | E117: =SUM(E118) -> 1332216.6 | F117: =SUM(F118) -> 170.39 | G117: =SUM(G118) -> 1212326 | H117: =SUM(H118) -> 120061 | I117: =IF(D117=0,0,G117/D117) -> 0.90989029
A118: =SUBTOTAL(103,$B$6:B118) -> 98 | B118: 218 | C118: =Base!G383 -> 2187217: MEJORAMIENTO DE LA CADENA DE VALOR DE LA FIBRA DE ALPACA EN LA REGION PUNO | D118: =Base!H383 -> 1332387 | E118: =Base!I383 -> 1332216.6 | F118: =D118-E118 -> 170.39 | G118: =Base!K383 -> 1212326 | H118: =D118-G118 -> 120061 | I118: =IF(D118=0,0,G118/D118) -> 0.90989029 | J118: =Base!O383 -> Contrata / Personal/bienes/servicios | K118: =Base!P383 -> Comprometido | L118: =Base!Q383 -> 630478 | M118: =Base!R383 -> 188781 | N118: =Base!S383 -> 2845395 | O118: =Base!T383 -> 2772809 | P118: =IF(Base!U383="","",Base!U383)
A119: 10. AGROPECUARIA | D119: =SUM(D120) -> 4271598 | E119: =SUM(E120) -> 4070553.3 | F119: =SUM(F120) -> 201044.66 | G119: =SUM(G120) -> 2287215.4 | H119: =SUM(H120) -> 1984382.6 | I119: =IF(D119=0,0,G119/D119) -> 0.53544724
A120: =SUBTOTAL(103,$B$6:B120) -> 99 | B120: 264 | C120: =Base!G384 -> 2603155: MEJORAMIENTO DE LOS SERVICIOS DE APOYO AL DESARROLLO PRODUCTIVO EN 37 UNIDADES PRODUCTORAS 37 DISTRITOS DE 11 PROVINCIAS DEL DEPARTAMENTO DE PUNO | D120: =Base!H384 -> 4271598 | E120: =Base!I384 -> 4070553.3 | F120: =D120-E120 -> 201044.66 | G120: =Base!K384 -> 2287215.4 | H120: =D120-G120 -> 1984382.6 | I120: =IF(D120=0,0,G120/D120) -> 0.53544724 | J120: =Base!O384 -> Personal/bienes/servicios / Contrata / Equipamiento | K120: =Base!P384 -> Comprometido | L120: =Base!Q384 -> 1500000 | M120: =Base!R384 -> 4950944 | N120: =Base!S384 -> 5144103 | O120: =Base!T384 -> 4718085 | P120: =IF(Base!U384="","",Base!U384)
A121: GERENCIA REGIONAL DE DESARROLLO SOCIAL | D121: =D122+D150+D162+D165 -> 74397967 | E121: =E122+E150+E162+E165 -> 67208622 | F121: =F122+F150+F162+F165 -> 7189345.4 | G121: =G122+G150+G162+G165 -> 23249590 | H121: =H122+H150+H162+H165 -> 51148377 | I121: =IF(D121=0,0,G121/D121) -> 0.31250303
A122: 20. SALUD | D122: =SUM(D123:D149) -> 52935028 | E122: =SUM(E123:E149) -> 48878434 | F122: =SUM(F123:F149) -> 4056593.9 | G122: =SUM(G123:G149) -> 17052641 | H122: =SUM(H123:H149) -> 35882387 | I122: =IF(D122=0,0,G122/D122) -> 0.32214286
A123: =SUBTOTAL(103,$B$6:B123) -> 100 | B123: 195 | C123: =Base!G385 -> 2154443: MEJORAMIENTO DEL ESTADO NUTRICIONAL DEL NIÑO MENOR DE TRES AÑOS Y LA MADRE GESTANTE EN LAS PROVINCIAS DE AZANGARO, LAMPA Y SAN ROMAN DE LA REGION PUNO | D123: =Base!H385 -> 0 | E123: =Base!I385 -> 0 | F123: =D123-E123 -> 0 | G123: =Base!K385 -> 0 | H123: =D123-G123 -> 0 | I123: =IF(D123=0,0,G123/D123) -> 0 | J123: =Base!O385 -> Personal/bienes/servicios | K123: =Base!P385 -> Sin PIM | L123: =Base!Q385 -> 4098 | M123: =Base!R385 -> 0 | N123: =Base!S385 -> 0 | O123: =Base!T385 -> 0 | P123: =IF(Base!U385="","",Base!U385)
A124: =SUBTOTAL(103,$B$6:B124) -> 101 | B124: 196 | C124: =Base!G386 -> 2159149: MEJORAMIENTO DE LAS CAPACIDADES PARA PREVENIR LA DESNUTRICION CRONICA, EN MENORES DE 3 AÑOS EN LAS PROVINCIAS DE CARABAYA, MELGAR Y SANDIA DE LA REGION PUNO | D124: =Base!H386 -> 0 | E124: =Base!I386 -> 0 | F124: =D124-E124 -> 0 | G124: =Base!K386 -> 0 | H124: =D124-G124 -> 0 | I124: =IF(D124=0,0,G124/D124) -> 0 | J124: =Base!O386 -> Personal/bienes/servicios | K124: =Base!P386 -> Sin PIM | L124: =Base!Q386 -> 87917 | M124: =Base!R386 -> 0 | N124: =Base!S386 -> 0 | O124: =Base!T386 -> 0 | P124: =IF(Base!U386="","",Base!U386)
A125: =SUBTOTAL(103,$B$6:B125) -> 102 | B125: 239 | C125: =Base!G387 -> 2488048: CREACION DEL SERVICIO DE ANALISIS DE BIOLOGIA MOLECULAR DE DIAGNOSTICO COVID-19 EN EL LABORATORIO DE REFERENCIA REGIONAL DE LA DIRESA PUNO, DISTRITO DE PUNO - PROVINCIA DE PUNO - DEPARTAMENTO DE PUNO | D125: =Base!H387 -> 0 | E125: =Base!I387 -> 0 | F125: =D125-E125 -> 0 | G125: =Base!K387 -> 0 | H125: =D125-G125 -> 0 | I125: =IF(D125=0,0,G125/D125) -> 0 | J125: =Base!O387 -> Administración directa | K125: =Base!P387 -> Sin PIM | L125: =Base!Q387 -> 276105 | M125: =Base!R387 -> 0 | N125: =Base!S387 -> 0 | O125: =Base!T387 -> 0 | P125: =IF(Base!U387="","",Base!U387)
A126: =SUBTOTAL(103,$B$6:B126) -> 103 | B126: 249 | C126: =Base!G388 -> 2544369: ADQUISICION DE AMBULANCIA RURAL Y AMBULANCIA RURAL; EN CINCUENTA Y CINCO ESTABLECIMIENTOS DE SALUD I.4, ESTABLECIMIENTOS DE SALUD I.2, ESTABLECIMIENTOS DE SALUD I.3 A NIVEL DEPARTAMENTAL (PUNO) | D126: =Base!H388 -> 0 | E126: =Base!I388 -> 0 | F126: =D126-E126 -> 0 | G126: =Base!K388 -> 0 | H126: =D126-G126 -> 0 | I126: =IF(D126=0,0,G126/D126) -> 0 | J126: =Base!O388 -> Personal/bienes/servicios | K126: =Base!P388 -> Sin PIM | L126: =Base!Q388 -> 89896 | M126: =Base!R388 -> 0 | N126: =Base!S388 -> 0 | O126: =Base!T388 -> 0 | P126: =IF(Base!U388="","",Base!U388)
A127: =SUBTOTAL(103,$B$6:B127) -> 104 | B127: 254 | C127: =Base!G389 -> 2567368: ADQUISICION DE MAMOGRAFO; EN EL(LA) EESS SAN MARTIN DE P. (MACUSANI) - MACUSANI DISTRITO DE MACUSANI, PROVINCIA CARABAYA, DEPARTAMENTO PUNO | D127: =Base!H389 -> 2390440 | E127: =Base!I389 -> 2386020 | F127: =D127-E127 -> 4420 | G127: =Base!K389 -> 824976.09 | H127: =D127-G127 -> 1565463.9 | I127: =IF(D127=0,0,G127/D127) -> 0.34511474 | J127: =Base!O389 -> Equipamiento / Contrata / Personal/bienes/servicios | K127: =Base!P389 -> Comprometido | L127: =Base!Q389 -> 21175 | M127: =Base!R389 -> 2971 | N127: =Base!S389 -> 1 | O127: =Base!T389 -> 0 | P127: =IF(Base!U389="","",Base!U389)
A128: =SUBTOTAL(103,$B$6:B128) -> 105 | B128: 255 | C128: =Base!G390 -> 2567375: ADQUISICION DE TOMOGRAFO COMPUTARIZADO MULTICORTE; EN EL(LA) EESS SAN MARTIN DE P. (MACUSANI) - MACUSANI DISTRITO DE MACUSANI, PROVINCIA CARABAYA, DEPARTAMENTO PUNO | D128: =Base!H390 -> 20600 | E128: =Base!I390 -> 20600 | F128: =D128-E128 -> 0 | G128: =Base!K390 -> 17783.6 | H128: =D128-G128 -> 2816.4 | I128: =IF(D128=0,0,G128/D128) -> 0.86328155 | J128: =Base!O390 -> Contrata | K128: =Base!P390 -> Comprometido | L128: =Base!Q390 -> 40062 | M128: =Base!R390 -> 0 | N128: =Base!S390 -> 0 | O128: =Base!T390 -> 0 | P128: =IF(Base!U390="","",Base!U390)
A129: =SUBTOTAL(103,$B$6:B129) -> 106 | B129: 263 | C129: =Base!G391 -> 2600443: ADQUISICION DE SISTEMA DE CIRUGIA LAPAROSCOPICA, TOMOGRAFO, MESA DE OPERACIONES HIDRAULICA/ELECTRICA Y LAMPARA QUIRURGICA DE TECHO; ADEMAS DE OTROS ACTIVOS EN EL(LA) YUNGUYO DISTRITO DE YUNGUYO, PROVINCIA YUNGUYO, DEPARTAMENTO PUNO | D129: =Base!H391 -> 3517960 | E129: =Base!I391 -> 3461030.1 | F129: =D129-E129 -> 56929.9 | G129: =Base!K391 -> 2179648.5 | H129: =D129-G129 -> 1338311.5 | I129: =IF(D129=0,0,G129/D129) -> 0.6195774 | J129: =Base!O391 -> Equipamiento / Contrata / Personal/bienes/servicios | K129: =Base!P391 -> Comprometido | L129: =Base!Q391 -> 2000000 | M129: =Base!R391 -> 64020 | N129: =Base!S391 -> 1401972 | O129: =Base!T391 -> 495265 | P129: =IF(Base!U391="","",Base!U391)
A130: =SUBTOTAL(103,$B$6:B130) -> 107 | B130: 281 | C130: =Base!G392 -> 2650340: ADQUISICION DE MESA DE OPERACIONES HIDRAULICA/ELECTRICA, ESTERILIZADOR CON GENERADOR ELECTRICO DE VAPOR (INS), EQUIPOS BIOMEDICOS Y COCHE DE PARO; ADEMAS DE OTROS ACTIVOS EN EL(LA) PUTINA DISTRITO DE PUTINA, PROVINCIA SAN ANTONIO DE PUTINA, DEPARTAMENTO PUNO | D130: =Base!H392 -> 2170829 | E130: =Base!I392 -> 2170829 | F130: =D130-E130 -> 0 | G130: =Base!K392 -> 147448.3 | H130: =D130-G130 -> 2023380.7 | I130: =IF(D130=0,0,G130/D130) -> 0.067922577 | J130: =Base!O392 -> Equipamiento / Contrata | K130: =Base!P392 -> Comprometido | L130: =Base!Q392 -> 2421000 | M130: =Base!R392 -> 2508625 | N130: =Base!S392 -> 546908 | O130: =Base!T392 -> 170650 | P130: =IF(Base!U392="","",Base!U392)
A131: =SUBTOTAL(103,$B$6:B131) -> 108 | B131: 285 | C131: =Base!G393 -> 2684028: ADQUISICION DE AMBULANCIA URBANA; EN ONCE ESTABLECIMIENTOS DE SALUD II.1, ESTABLECIMIENTOS DE SALUD II.2 A NIVEL DEPARTAMENTAL (PUNO) | D131: =Base!H393 -> 31336 | E131: =Base!I393 -> 0 | F131: =D131-E131 -> 31336 | G131: =Base!K393 -> 0 | H131: =D131-G131 -> 31336 | I131: =IF(D131=0,0,G131/D131) -> 0 | J131: =Base!O393 -> Contrata | K131: =Base!P393 -> Sin certificar | L131: =Base!Q393 -> 513444 | M131: =Base!R393 -> 0 | N131: =Base!S393 -> 0 | O131: =Base!T393 -> 0 | P131: =IF(Base!U393="","",Base!U393)
A132: =SUBTOTAL(103,$B$6:B132) -> 109 | B132: 287 | C132: =Base!G394 -> 2685776: ADQUISICION DE ANALIZADOR DE GASES Y ELECTROLITOS, ESPECTROFOTOMETRO, EQUIPO DE RAYOS X DENTAL Y BIDESTILADOR DE AGUA; ADEMAS DE OTROS ACTIVOS EN EL(LA) MOHO DISTRITO DE MOHO, PROVINCIA MOHO, DEPARTAMENTO PUNO | D132: =Base!H394 -> 1263865 | E132: =Base!I394 -> 1181167.9 | F132: =D132-E132 -> 82697.06 | G132: =Base!K394 -> 146441.28 | H132: =D132-G132 -> 1117423.7 | I132: =IF(D132=0,0,G132/D132) -> 0.11586782 | J132: =Base!O394 -> Equipamiento / Contrata / Personal/bienes/servicios | K132: =Base!P394 -> Comprometido | L132: =Base!Q394 -> 894000 | M132: =Base!R394 -> 0 | N132: =Base!S394 -> 825648 | O132: =Base!T394 -> 825648 | P132: =IF(Base!U394="","",Base!U394)
A133: =SUBTOTAL(103,$B$6:B133) -> 110 | B133: 313 | C133: =Base!G395 -> 2694246: ADQUISICION DE MAMOGRAFO, COLONOVIDEOENDOSCOPIO, MESA DE OPERACIONES HIDRAULICA/ELECTRICA Y CALDERO; ADEMAS DE OTROS ACTIVOS EN EL(LA) HOSPITAL REGIONAL MANUEL NUÑEZ BUTRON HOSPITAL REGIONAL MANUEL NUÑEZ BUTRON DISTRITO DE PUNO, PROVINCIA PUNO, DEPARTAMENTO PUNO | D133: =Base!H395 -> 8483998 | E133: =Base!I395 -> 8474782.3 | F133: =D133-E133 -> 9215.69 | G133: =Base!K395 -> 5322446.1 | H133: =D133-G133 -> 3161551.9 | I133: =IF(D133=0,0,G133/D133) -> 0.62735117 | J133: =Base!O395 -> Equipamiento / Contrata / Personal/bienes/servicios | K133: =Base!P395 -> Comprometido | L133: =Base!Q395 -> 2578971 | M133: =Base!R395 -> 22487 | N133: =Base!S395 -> 500000 | O133: =Base!T395 -> 500000 | P133: =IF(Base!U395="","",Base!U395)
A134: =SUBTOTAL(103,$B$6:B134) -> 111 | B134: 314 | C134: =Base!G396 -> 2611144: ADQUISICION DE ANALIZADOR DE GASES Y ELECTROLITOS, ASPIRADOR DE SECRECIONES, BOMBA DE INFUSION Y COCHE DE PARO EQUIPADO; ADEMAS DE OTROS ACTIVOS EN EL(LA) CARLOS MONJE MEDRANO DISTRITO DE JULIACA, PROVINCIA SAN ROMAN, DEPARTAMENTO PUNO | D134: =Base!H396 -> 4219373 | E134: =Base!I396 -> 4183621 | F134: =D134-E134 -> 35751.97 | G134: =Base!K396 -> 3829328.1 | H134: =D134-G134 -> 390044.92 | I134: =IF(D134=0,0,G134/D134) -> 0.90755856 | J134: =Base!O396 -> Equipamiento / Contrata | K134: =Base!P396 -> Comprometido | L134: =Base!Q396 -> 3305500 | M134: =Base!R396 -> 177809 | N134: =Base!S396 -> 150483 | O134: =Base!T396 -> 0 | P134: =IF(Base!U396="","",Base!U396)
... A149: =SUBTOTAL(103,$B$6:B149) -> 126 | B149: 524 | C149: =Base!G411 -> 2733644.ADQUISICION DE PATRULLEROS Y PATRULLEROS; EN EL(LA) FRENTE POLICIAL PUNO - COMISARIAS EN LAS 13 PROVINCIAS DE LA REGION PUNO, DISTRITO DE PUNO, PROVINCIA PUNO, DEPARTAMENTO PUNO | D149: =Base!H411 -> 25610 | E149: =Base!I411 -> 0 | F149: =D149-E149 -> 25610 | G149: =Base!K411 -> 0 | H149: =D149-G149 -> 25610 | I149: =IF(D149=0,0,G149/D149) -> 0 | J149: =Base!O411 -> Expediente técnico | K149: =Base!P411 -> Sin certificar | L149: =Base!Q411 -> No registrado en cartera | M149: =Base!R411 -> No registrado en cartera | N149: =Base!S411 -> No registrado en cartera | O149: =Base!T411 -> No registrado en cartera | P149: =IF(Base!U411="","",Base!U411)
A150: 22. EDUCACION | D150: =SUM(D151:D161) -> 9526686 | E150: =SUM(E151:E161) -> 7349693.7 | F150: =SUM(F151:F161) -> 2176992.3 | G150: =SUM(G151:G161) -> 335809.26 | H150: =SUM(H151:H161) -> 9190876.7 | I150: =IF(D150=0,0,G150/D150) -> 0.035249326
A151: =SUBTOTAL(103,$B$6:B151) -> 127 | B151: 512 | C151: =Base!G412 -> 2721991.RENOVACION DE AULA DE EDUCACION PRIMARIA, AMBIENTE ADMINISTRATIVO, SERVICIOS HIGIENICOS Y/O VESTIDORES Y AMBIENTE DE USOS MULTIPLES; ADEMAS DE OTROS ACTIVOS EN CUATRO II.EE. PRIMARIA A NIVEL DISTRITAL (PUNO - SANDIA - SAN PEDRO DE PUTINA PUNCO) | D151: =Base!H412 -> 3254770 | E151: =Base!I412 -> 2925559.5 | F151: =D151-E151 -> 329210.45 | G151: =Base!K412 -> 0 | H151: =D151-G151 -> 3254770 | I151: =IF(D151=0,0,G151/D151) -> 0 | J151: =Base!O412 -> Contrata / Expediente técnico / Personal/bienes/servicios | K151: =Base!P412 -> Solo certificado | L151: =Base!Q412 -> No registrado en cartera | M151: =Base!R412 -> No registrado en cartera | N151: =Base!S412 -> No registrado en cartera | O151: =Base!T412 -> No registrado en cartera | P151: =IF(Base!U412="","",Base!U412)
A152: =SUBTOTAL(103,$B$6:B152) -> 128 | B152: 513 | C152: =Base!G413 -> 2721892.CONSTRUCCION DE AULA DE EDUCACION SECUNDARIA, AMBIENTE ADMINISTRATIVO Y SERVICIOS HIGIENICOS Y/O VESTIDORES; ADQUISICION DE MOBILIARIO DE AULA; EN EL(LA) IE PUERTO DE EDEN DISTRITO DE SAN PEDRO DE PUTINA PUNCO, PROVINCIA SANDIA, DEPARTAMENTO PUNO | D152: =Base!H413 -> 1007572 | E152: =Base!I413 -> 838299.38 | F152: =D152-E152 -> 169272.62 | G152: =Base!K413 -> 0 | H152: =D152-G152 -> 1007572 | I152: =IF(D152=0,0,G152/D152) -> 0 | J152: =Base!O413 -> Contrata / Expediente técnico / Personal/bienes/servicios | K152: =Base!P413 -> Solo certificado | L152: =Base!Q413 -> No registrado en cartera | M152: =Base!R413 -> No registrado en cartera | N152: =Base!S413 -> No registrado en cartera | O152: =Base!T413 -> No registrado en cartera | P152: =IF(Base!U413="","",Base!U413)
A153: =SUBTOTAL(103,$B$6:B153) -> 129 | B153: 515 | C153: =Base!G414 -> 2719529.RENOVACION DE AULA DE EDUCACION PRIMARIA, SERVICIOS HIGIENICOS Y/O VESTIDORES Y AMBIENTE DE USOS MULTIPLES; ADQUISICION DE MOBILIARIO DE AULA; EN TRES II.EE. PRIMARIA A NIVEL DISTRITAL (PUNO - SANDIA - ALTO INAMBARI) | D153: =Base!H414 -> 1688098 | E153: =Base!I414 -> 1486603.2 | F153: =D153-E153 -> 201494.77 | G153: =Base!K414 -> 0 | H153: =D153-G153 -> 1688098 | I153: =IF(D153=0,0,G153/D153) -> 0 | J153: =Base!O414 -> Contrata / Expediente técnico / Personal/bienes/servicios | K153: =Base!P414 -> Solo certificado | L153: =Base!Q414 -> No registrado en cartera | M153: =Base!R414 -> No registrado en cartera | N153: =Base!S414 -> No registrado en cartera | O153: =Base!T414 -> No registrado en cartera | P153: =IF(Base!U414="","",Base!U414)
A154: =SUBTOTAL(103,$B$6:B154) -> 130 | B154: 509 | C154: =Base!G415 -> 2723359.CONSTRUCCION DE AULA DE EDUCACION SECUNDARIA; ADQUISICION DE MOBILIARIO DE AULA; EN EL(LA) IE SECUNDARIA SANTA ROSA DISTRITO DE ALTO INAMBARI, PROVINCIA SANDIA, DEPARTAMENTO PUNO | D154: =Base!H415 -> 680748 | E154: =Base!I415 -> 538302.92 | F154: =D154-E154 -> 142445.08 | G154: =Base!K415 -> 0 | H154: =D154-G154 -> 680748 | I154: =IF(D154=0,0,G154/D154) -> 0 | J154: =Base!O415 -> Contrata / Expediente técnico / Personal/bienes/servicios | K154: =Base!P415 -> Solo certificado | L154: =Base!Q415 -> No registrado en cartera | M154: =Base!R415 -> No registrado en cartera | N154: =Base!S415 -> No registrado en cartera | O154: =Base!T415 -> No registrado en cartera | P154: =IF(Base!U415="","",Base!U415)
A155: =SUBTOTAL(103,$B$6:B155) -> 131 | B155: 510 | C155: =Base!G416 -> 2721888.CONSTRUCCION DE AULA DE EDUCACION SECUNDARIA; ADQUISICION DE MOBILIARIO DE AULA; EN EL(LA) IE I.E. SECUNDARIA JOSE MARIA ARGUEDAS EN LA LOCALIDAD CCAPUNA, DISTRITO DE SANDIA, PROVINCIA SANDIA, DEPARTAMENTO PUNO | D155: =Base!H416 -> 670100 | E155: =Base!I416 -> 532791.97 | F155: =D155-E155 -> 137308.03 | G155: =Base!K416 -> 0 | H155: =D155-G155 -> 670100 | I155: =IF(D155=0,0,G155/D155) -> 0 | J155: =Base!O416 -> Contrata / Expediente técnico / Personal/bienes/servicios | K155: =Base!P416 -> Solo certificado | L155: =Base!Q416 -> No registrado en cartera | M155: =Base!R416 -> No registrado en cartera | N155: =Base!S416 -> No registrado en cartera | O155: =Base!T416 -> No registrado en cartera | P155: =IF(Base!U416="","",Base!U416)
A156: =SUBTOTAL(103,$B$6:B156) -> 132 | B156: 511 | C156: =Base!G417 -> 2721886.CONSTRUCCION DE AULA DE EDUCACION INICIAL; ADQUISICION DE MOBILIARIO DE AULA; EN EL(LA) IE INICIAL N° 1048 DE HUENCALLA DISTRITO DE SANDIA, PROVINCIA SANDIA, DEPARTAMENTO PUNO | D156: =Base!H417 -> 388514 | E156: =Base!I417 -> 269223.84 | F156: =D156-E156 -> 119290.16 | G156: =Base!K417 -> 0 | H156: =D156-G156 -> 388514 | I156: =IF(D156=0,0,G156/D156) -> 0 | J156: =Base!O417 -> Contrata / Expediente técnico / Personal/bienes/servicios | K156: =Base!P417 -> Solo certificado | L156: =Base!Q417 -> No registrado en cartera | M156: =Base!R417 -> No registrado en cartera | N156: =Base!S417 -> No registrado en cartera | O156: =Base!T417 -> No registrado en cartera | P156: =IF(Base!U417="","",Base!U417)
A157: =SUBTOTAL(103,$B$6:B157) -> 133 | B157: 514 | C157: =Base!G418 -> 2721889.CONSTRUCCION DE AULA DE EDUCACION INICIAL Y AMBIENTE ADMINISTRATIVO; ADQUISICION DE MOBILIARIO DE AULA Y EQUIPAMIENTO DE AULA; EN EL(LA) IE 1027 EN LA LOCALIDAD ISILLUMA, DISTRITO DE ALTO INAMBARI, PROVINCIA SANDIA, DEPARTAMENTO PUNO | D157: =Base!H418 -> 542416 | E157: =Base!I418 -> 401911.51 | F157: =D157-E157 -> 140504.49 | G157: =Base!K418 -> 0 | H157: =D157-G157 -> 542416 | I157: =IF(D157=0,0,G157/D157) -> 0 | J157: =Base!O418 -> Contrata / Expediente técnico / Personal/bienes/servicios | K157: =Base!P418 -> Solo certificado | L157: =Base!Q418 -> No registrado en cartera | M157: =Base!R418 -> No registrado en cartera | N157: =Base!S418 -> No registrado en cartera | O157: =Base!T418 -> No registrado en cartera | P157: =IF(Base!U418="","",Base!U418)
A158: =SUBTOTAL(103,$B$6:B158) -> 134 | B158: 516 | C158: =Base!G419 -> 2729834.CONSTRUCCION DE AULA DE EDUCACION PRIMARIA, SERVICIOS HIGIENICOS Y/O VESTIDORES PARA ESTUDIANTES Y AMBIENTE DE GESTION ADMINISTRATIVA Y DIRECCION; ADQUISICION DE MOBILIARIO DE AULA; EN EL(LA) I.E. 72544 DISTRITO DE ALTO INAMBARI, PROVINCIA SANDIA, | D158: =Base!H419 -> 928545 | E158: =Base!I419 -> 0 | F158: =D158-E158 -> 928545 | G158: =Base!K419 -> 0 | H158: =D158-G158 -> 928545 | I158: =IF(D158=0,0,G158/D158) -> 0 | J158: =Base!O419 -> Contrata / Expediente técnico | K158: =Base!P419 -> Sin certificar | L158: =Base!Q419 -> No registrado en cartera | M158: =Base!R419 -> No registrado en cartera | N158: =Base!S419 -> No registrado en cartera | O158: =Base!T419 -> No registrado en cartera | P158: =IF(Base!U419="","",Base!U419)
A159: =SUBTOTAL(103,$B$6:B159) -> 135 | B159: 348 | C159: =Base!G420 -> 2693441: ADQUISICION DE EQUIPO DE AULA DE EDUCACION SECUNDARIA; EN EL(LA) I.E. GLORIOSO SAN CARLOS DISTRITO DE PUNO, PROVINCIA PUNO, DEPARTAMENTO PUNO | D159: =Base!H420 -> 70059 | E159: =Base!I420 -> 70057.9 | F159: =D159-E159 -> 1.1 | G159: =Base!K420 -> 70029.94 | H159: =D159-G159 -> 29.06 | I159: =IF(D159=0,0,G159/D159) -> 0.99958521 | J159: =Base!O420 -> Otro (SOFTWARES) / Contrata / Personal/bienes/servicios | K159: =Base!P420 -> Comprometido | L159: =Base!Q420 -> 105988 | M159: =Base!R420 -> 0 | N159: =Base!S420 -> 35929 | O159: =Base!T420 -> 0 | P159: =IF(Base!U420="","",Base!U420)
A160: =SUBTOTAL(103,$B$6:B160) -> 136 | B160: 349 | C160: =Base!G421 -> 2692840: ADQUISICION DE EQUIPO DE AULA DE EDUCACION PRIMARIA; EN EL(LA) I.E. GLORIOSO SAN CARLOS DISTRITO DE PUNO, PROVINCIA PUNO, DEPARTAMENTO PUNO | D160: =Base!H421 -> 100785 | E160: =Base!I421 -> 100589.42 | F160: =D160-E160 -> 195.58 | G160: =Base!K421 -> 88974.89 | H160: =D160-G160 -> 11810.11 | I160: =IF(D160=0,0,G160/D160) -> 0.88281877 | J160: =Base!O421 -> Contrata / Otro (SOFTWARES) / Personal/bienes/servicios | K160: =Base!P421 -> Comprometido | L160: =Base!Q421 -> 155899 | M160: =Base!R421 -> 0 | N160: =Base!S421 -> 55114 | O160: =Base!T421 -> 0 | P160: =IF(Base!U421="","",Base!U421)
A161: =SUBTOTAL(103,$B$6:B161) -> 137 | B161: 461 | C161: =Base!G422 -> 2699544: ADQUISICION DE EQUIPAMIENTO DE AULA; EN SIETE II.EE. INICIAL DISTRITO DE SAN JUAN DE SALINAS, PROVINCIA AZANGARO, DEPARTAMENTO PUNO | D161: =Base!H422 -> 195079 | E161: =Base!I422 -> 186354 | F161: =D161-E161 -> 8725 | G161: =Base!K422 -> 176804.43 | H161: =D161-G161 -> 18274.57 | I161: =IF(D161=0,0,G161/D161) -> 0.90632221 | J161: =Base!O422 -> Administración directa / Equipamiento / Contrata / Personal/bienes/servicios | K161: =Base!P422 -> Comprometido | L161: =Base!Q422 -> 195079 | M161: =Base!R422 -> 23547 | N161: =Base!S422 -> 1 | O161: =Base!T422 -> 0 | P161: =IF(Base!U422="","",Base!U422)
A162: 05. ORDEN PUBLICO Y SEGURIDAD | D162: =SUM(D163:D164) -> 11936253 | E162: =SUM(E163:E164) -> 10980494 | F162: =SUM(F163:F164) -> 955759.22 | G162: =SUM(G163:G164) -> 5861139.6 | H162: =SUM(H163:H164) -> 6075113.4 | I162: =IF(D162=0,0,G162/D162) -> 0.49103681
A163: =SUBTOTAL(103,$B$6:B163) -> 138 | B163: 3 | C163: =Base!G423 -> 2683535: MEJORAMIENTO DEL SERVICIO DE SEGURIDAD CIUDADANA LOCAL EN 73 UNIDADES PRODUCTORAS 73 DISTRITOS DE 11 PROVINCIAS DEL DEPARTAMENTO DE PUNO 11 PROVINCIAS DEL DEPARTAMENTO DE PUNO | D163: =Base!H423 -> 6654893 | E163: =Base!I423 -> 6543805.7 | F163: =D163-E163 -> 111087.31 | G163: =Base!K423 -> 5720623 | H163: =D163-G163 -> 934270.03 | I163: =IF(D163=0,0,G163/D163) -> 0.85961156 | J163: =Base!O423 -> Equipamiento / Contrata / Personal/bienes/servicios | K163: =Base!P423 -> Comprometido | L163: =Base!Q423 -> 100000 | M163: =Base!R423 -> 218816 | N163: =Base!S423 -> 309853 | O163: =Base!T423 -> 0 | P163: =IF(Base!U423="","",Base!U423)
A164: =SUBTOTAL(103,$B$6:B164) -> 139 | B164: 286 | C164: =Base!G424 -> 2685431: ADQUISICION DE AMBULANCIA URBANA, CAMIONETA, CAMION PLATAFORMA Y CAMION CISTERNA; ADEMAS DE OTROS ACTIVOS EN CINCO COMPAÑIA DE BOMBEROS | D164: =Base!H424 -> 5281360 | E164: =Base!I424 -> 4436688.1 | F164: =D164-E164 -> 844671.91 | G164: =Base!K424 -> 140516.63 | H164: =D164-G164 -> 5140843.4 | I164: =IF(D164=0,0,G164/D164) -> 0.026606145 | J164: =Base!O424 -> Equipamiento / Contrata / Personal/bienes/servicios | K164: =Base!P424 -> Comprometido | L164: =Base!Q424 -> 5358341 | M164: =Base!R424 -> 6902686 | N164: =Base!S424 -> 800000 | O164: =Base!T424 -> 800000 | P164: =IF(Base!U424="","",Base!U424)
A165: 23. PROTECCION SOCIAL | D165: =SUM(D166) -> 0 | E165: =SUM(E166) -> 0 | F165: =SUM(F166) -> 0 | G165: =SUM(G166) -> 0 | H165: =SUM(H166) -> 0 | I165: =IF(D165=0,0,G165/D165) -> 0
A166: =SUBTOTAL(103,$B$6:B166) -> 140 | B166: 266 | C166: =Base!G425 -> 2608728: REPARACION DE AMBIENTE DE RESIDENCIA; ADQUISICION DE EQUIPAMIENTO DE AMBIENTES DE BIENESTAR Y SERVICIOS GENERALES Y MOBILIARIO DE AMBIENTES DE BIENESTAR Y SERVICIOS GENERALES; EN EL(LA) ALDEA INFANTIL NIÑO SAN SALVADOR DEL DISTRITO DE CAPACHICA, PROVINCIA PUNO, DEPARTAMENTO PUNO | D166: =Base!H425 -> 0 | E166: =Base!I425 -> 0 | F166: =D166-E166 -> 0 | G166: =Base!K425 -> 0 | H166: =D166-G166 -> 0 | I166: =IF(D166=0,0,G166/D166) -> 0 | J166: =Base!O425 -> Contrata | K166: =Base!P425 -> Sin PIM | L166: =Base!Q425 -> 200000 | M166: =Base!R425 -> 0 | N166: =Base!S425 -> 0 | O166: =Base!T425 -> 0 | P166: =IF(Base!U425="","",Base!U425)
A167: DIRECCIÓN DE ESTUDIOS DE PREINVERSIÓN | D167: =SUM(D168:D177) -> 7151039 | E167: =SUM(E168:E177) -> 5777501 | F167: =SUM(F168:F177) -> 1373538 | G167: =SUM(G168:G177) -> 5400403.3 | H167: =SUM(H168:H177) -> 1750635.7 | I167: =IF(D167=0,0,G167/D167) -> 0.75519142
...

Sheet Sin clasificar
C1: ANEXO N° 03 · PROYECTOS SIN GERENCIA ASIGNADA
B2: COMPORTAMIENTO DE EJECUCIÓN DE PROYECTOS DE INVERSION PUBLICA DEL AÑO FISCAL 2026 DE GERENCIAS REGIONALES Y UNIDADES EJECUTORAS · UE 001 · AL 06/10/2026
A4: N° | B4: META | C4: PROYECTO | D4: PIM 2026 (A) | E4: CERTIFICACIÓN (B) | F4: SALDO (A-B) | G4: DEVENGADO ( C ) | H4: SALDO (A-C) | I4: DEVEN % | J4: MODALIDAD DE EJECUCIÓN | K4: ESTADO SITUACIONAL PROYECTO | L4: Monto Año 2026 (S/) | M4: Monto Año 2027 (S/) | N4: Monto Año 2028 (S/) | O4: Monto Año 2029 (S/) | P4: BASE LEGAL
A6: SIN CLASIFICAR (pendiente de asignar gerencia) | D6: =D7+D10 -> 892982 | E6: =E7+E10 -> 573620.69 | F6: =F7+F10 -> 319361.31 | G6: =G7+G10 -> 288990.91 | H6: =H7+H10 -> 603991.09 | I6: =IF(D6=0,0,G6/D6) -> 0.32362456
A7: 20. SALUD | D7: =SUM(D8:D9) -> 382553 | E7: =SUM(E8:E9) -> 282553 | F7: =SUM(F8:F9) -> 100000 | G7: =SUM(G8:G9) -> 0 | H7: =SUM(H8:H9) -> 382553 | I7: =IF(D7=0,0,G7/D7) -> 0
A8: =SUBTOTAL(103,$B$6:B8) -> 1 | B8: 284 | C8: =Base!G436 -> 2662519: MEJORAMIENTO DEL SERVICIO DE ATENCIÓN DE SALUD BÁSICOS EN C.S. CLAS PUSI DISTRITO DE PUSI DE LA PROVINCIA DE HUANCANE DEL DEPARTAMENTO DE PUNO | D8: =Base!H436 -> 282553 | E8: =Base!I436 -> 282553 | F8: =D8-E8 -> 0 | G8: =Base!K436 -> 0 | H8: =D8-G8 -> 282553 | I8: =IF(D8=0,0,G8/D8) -> 0 | J8: =Base!O436 -> Expediente técnico | K8: =Base!P436 -> Comprometido | L8: =Base!Q436 -> 50000 | M8: =Base!R436 -> 0 | N8: =Base!S436 -> 0 | O8: =Base!T436 -> 1000000 | P8: =IF(Base!U436="","",Base!U436)
A9: =SUBTOTAL(103,$B$6:B9) -> 2 | B9: 533 | C9: =Base!G439 -> 2681141: MEJORAMIENTO DEL SERVICIO DE ATENCIÓN DE SALUD BÁSICOS EN HUACULLANI DISTRITO DE HUACULLANI DE LA PROVINCIA DE CHUCUITO DEL DEPARTAMENTO DE PUNO | D9: =Base!H439 -> 100000 | E9: =Base!I439 -> 0 | F9: =D9-E9 -> 100000 | G9: =Base!K439 -> 0 | H9: =D9-G9 -> 100000 | I9: =IF(D9=0,0,G9/D9) -> 0 | J9: =Base!O439 -> Expediente técnico | K9: =Base!P439 -> Sin certificar | L9: =Base!Q439 -> 100000 | M9: =Base!R439 -> 0 | N9: =Base!S439 -> 3681052 | O9: =Base!T439 -> 4156140 | P9: =IF(Base!U439="","",Base!U439)
A10: 22. EDUCACION | D10: =SUM(D11:D13) -> 510429 | E10: =SUM(E11:E13) -> 291067.69 | F10: =SUM(F11:F13) -> 219361.31 | G10: =SUM(G11:G13) -> 288990.91 | H10: =SUM(H11:H13) -> 221438.09 | I10: =IF(D10=0,0,G10/D10) -> 0.56617259
A11: =SUBTOTAL(103,$B$6:B11) -> 3 | B11: 345 | C11: =Base!G437 -> 2699546: ADQUISICION DE EQUIPAMIENTO DE AULA DE INNOVACION PEDAGOGICA; EN OCHO II.EE. PRIMARIA DISTRITO DE SAN JUAN DE SALINAS, PROVINCIA AZANGARO, DEPARTAMENTO PUNO | D11: =Base!H437 -> 271707 | E11: =Base!I437 -> 271705.69 | F11: =D11-E11 -> 1.31 | G11: =Base!K437 -> 270842.66 | H11: =D11-G11 -> 864.34 | I11: =IF(D11=0,0,G11/D11) -> 0.99681885 | J11: =Base!O437 -> Equipamiento / Administración directa / Contrata / Personal/bienes/servicios | K11: =Base!P437 -> Comprometido | L11: =Base!Q437 -> 267733 | M11: =Base!R437 -> 20886 | N11: =Base!S437 -> 0 | O11: =Base!T437 -> 0 | P11: =IF(Base!U437="","",Base!U437)
A12: =SUBTOTAL(103,$B$6:B12) -> 4 | B12: 532 | C12: =Base!G438 -> 2617364: (MEJORAMIENTO DE INFRAESTRUCTURA DE EDUCACION BASICA REGULAR - nombre no disponible en fuentes) | D12: =Base!H438 -> 218556 | E12: =Base!I438 -> 0 | F12: =D12-E12 -> 218556 | G12: =Base!K438 -> 0 | H12: =D12-G12 -> 218556 | I12: =IF(D12=0,0,G12/D12) -> 0 | J12: =Base!O438 -> Contrata | K12: =Base!P438 -> Sin certificar | L12: =Base!Q438 -> No registrado en cartera | M12: =Base!R438 -> No registrado en cartera | N12: =Base!S438 -> No registrado en cartera | O12: =Base!T438 -> No registrado en cartera | P12: =IF(Base!U438="","",Base!U438)
A13: =SUBTOTAL(103,$B$6:B13) -> 5 | B13: 499 | C13: =Base!G440 -> 2231037: MEJORAMIENTO DE LOS SERVICIOS EDUCATIVOS EN LA I.E.I. N 596 MUNAYPATA DEL CENTRO POBLADO DE MUNAYPATA, DISTRITO DE OLLACHEA PROVINCIA DE CARABAYA PUNO | D13: =Base!H440 -> 20166 | E13: =Base!I440 -> 19362 | F13: =D13-E13 -> 804 | G13: =Base!K440 -> 18148.25 | H13: =D13-G13 -> 2017.75 | I13: =IF(D13=0,0,G13/D13) -> 0.89994297 | J13: =Base!O440 -> Contrata / Personal/bienes/servicios | K13: =Base!P440 -> Comprometido | L13: =Base!Q440 -> 20166 | M13: =Base!R440 -> 0 | N13: =Base!S440 -> 0 | O13: =Base!T440 -> 0 | P13: =IF(Base!U440="","",Base!U440)
A15: TOTAL SIN CLASIFICAR | D15: =D6 -> 892982 | E15: =E6 -> 573620.69 | F15: =F6 -> 319361.31 | G15: =G6 -> 288990.91 | H15: =H6 -> 603991.09 | I15: =IF(D15=0,0,G15/D15) -> 0.32362456

Sheet Base
A1: Base de datos por CUI-meta · UE 001 REGION PUNO-SEDE CENTRAL · al 06/10/2026
A2: Fuentes: SIAF reporte20261006085201.xls (cifras y modalidad), Cartera PMI 06/10/2026 (montos 2026-2029), Excel de Alex 16/09 (agrupación). Las hojas de anexo leen de aquí.
A4: Hoja | B4: Gerencia / Oficina | C4: Grupo (Alex) | D4: Función | E4: CUI | F4: Meta | G4: Proyecto | H4: PIM 2026 | I4: Certificación | J4: Compromiso anual | K4: Devengado | L4: Saldo sin certificar (A-B) | M4: Saldo sin comprometer (A-comp) | N4: Saldo sin devengar (A-C) | O4: Modalidad de ejecución | P4: Estado situacional | Q4: Monto Año 2026 (S/) | R4: Monto Año 2027 (S/) | S4: Monto Año 2028 (S/) | T4: Monto Año 2029 (S/) | U4: Base legal | V4: Observación de clasificación
A5: Gerencia de Infraestructura | B5: GERENCIA DE INFRAESTRUCTURA | C5: EJECUCIÓN POR ADMINISTRACIÓN DIRECTA > EJECUCIÓN POR ADMINISTRACIÓN DIRECTA - DIRECTIVA 10 | D5: 20. SALUD | E5: 2108576 | F5: 1 | G5: 2108576: CONSTRUCCION DEL HOSPITAL MATERNO INFANTIL DEL CONO SUR JULIACA | H5: 167354 | I5: 149951.3 | J5: 149951.3 | K5: 102781.21 | L5: =H5-I5 -> 17402.7 | M5: =H5-J5 -> 17402.7 | N5: =H5-K5 -> 64572.79 | O5: Administración directa / Laudos arbitrales | P5: =IF(H5=0,"Sin PIM",IF(ROUND(K5-H5,2)>=0,"Devengado total",IF(J5>0.005,"Comprometido",IF(I5>0.005,"Solo certificado","Sin certificar")))) -> Comprometido | Q5: 12460540 | R5: 5731000 | S5: 5000000 | T5: 5000000
A6: Gerencia de Infraestructura | B6: GERENCIA DE INFRAESTRUCTURA | C6: EJECUCIÓN POR ADMINISTRACIÓN DIRECTA > EJECUCIÓN POR ADMINISTRACIÓN DIRECTA - DIRECTIVA 10 | D6: 20. SALUD | E6: 2279375 | F6: 220 | G6: 2279375: MEJORAMIENTO DE LOS SERVICIOS DE SALUD DEL HOSPITAL DE APOYO ILAVE, PROVINCIA DE EL COLLAO - REGION PUNO | H6: 53759397 | I6: 53759397 | J6: 262914.25 | K6: 261343.05 | L6: =H6-I6 -> 0.1 | M6: =H6-J6 -> 53496483 | N6: =H6-K6 -> 53498054 | O6: Contrata / Expediente técnico / Administración directa / Laudos arbitrales | P6: =IF(H6=0,"Sin PIM",IF(ROUND(K6-H6,2)>=0,"Devengado total",IF(J6>0.005,"Comprometido",IF(I6>0.005,"Solo certificado","Sin certificar")))) -> Comprometido | Q6: No registrado en cartera | R6: No registrado en cartera | S6: No registrado en cartera | T6: No registrado en cartera
A7: Gerencia de Infraestructura | B7: GERENCIA DE INFRAESTRUCTURA | C7: EJECUCIÓN POR ADMINISTRACIÓN DIRECTA > EJECUCIÓN POR ADMINISTRACIÓN DIRECTA - DIRECTIVA 10 | D7: 22. EDUCACION | E7: 2323700 | F7: 223 | G7: 2323700: MEJORAMIENTO DEL SERVICIO EDUCATIVO DE LAS CARRERAS DE PRODUCCION, AUTOMOTRIZ, MINERIA, CONTABILIDAD, COMPUTACION, SECRETARIADO, ENFERMERIA, LABORATORIO CLINICO Y PROTESIS DENTAL DEL IST MANUEL NUÑEZ BUTRON, JULIACA, SAN ROMAN - PUNO | H7: 10519577 | I7: 10386241 | J7: 8483089.2 | K7: 7596372.7 | L7: =H7-I7 -> 133335.78 | M7: =H7-J7 -> 2036487.8 | N7: =H7-K7 -> 2923204.3 | O7: Administración directa / Contrata / Personal/bienes/servicios | P7: =IF(H7=0,"Sin PIM",IF(ROUND(K7-H7,2)>=0,"Devengado total",IF(J7>0.005,"Comprometido",IF(I7>0.005,"Solo certificado","Sin certificar")))) -> Comprometido | Q7: 2546207 | R7: 638376 | S7: 2568939 | T7: 0
A8: Gerencia de Infraestructura | B8: GERENCIA DE INFRAESTRUCTURA | C8: EJECUCIÓN POR ADMINISTRACIÓN DIRECTA > EJECUCIÓN POR ADMINISTRACIÓN DIRECTA - DIRECTIVA 10 | D8: 22. EDUCACION | E8: 2335880 | F8: 224 | G8: 2335880: MEJORAMIENTO DEL SERVICIO EDUCATIVO DE LAS CARRERAS DE CONTABILIDAD, ENFERMERIA TECNICA, COMPUTACION E INFORMATICA, INDUSTRIA ALIMENTARIA Y PRODUCCION AGROPECUARIA DEL ISEPA, PROVINCIA DE MELGAR - PUNO | H8: 10208307 | I8: 9968469.6 | J8: 9951805 | K8: 6440724.5 | L8: =H8-I8 -> 239837.38 | M8: =H8-J8 -> 256501.96 | N8: =H8-K8 -> 3767582.5 | O8: Administración directa / Equipamiento / Contrata / Personal/bienes/servicios | P8: =IF(H8=0,"Sin PIM",IF(ROUND(K8-H8,2)>=0,"Devengado total",IF(J8>0.005,"Comprometido",IF(I8>0.005,"Solo certificado","Sin certificar")))) -> Comprometido | Q8: 5597990 | R8: 1254673 | S8: 2493351 | T8: 0
A9: Gerencia de Infraestructura | B9: GERENCIA DE INFRAESTRUCTURA | C9: EJECUCIÓN POR ADMINISTRACIÓN DIRECTA > EJECUCIÓN POR ADMINISTRACIÓN DIRECTA - DIRECTIVA 10 | D9: 22. EDUCACION | E9: 2521936 | F9: 245 | G9: 2521936: MEJORAMIENTO Y AMPLIACION DEL SERVICIO DE EDUCACION SUPERIOR TECNOLOGICA EN EL INSTITUTO SUPERIOR TECNOLOGICO PUBLICO DE MACUSANI DISTRITO DE MACUSANI - PROVINCIA DE CARABAYA - DEPARTAMENTO DE PUNO | H9: 11203165 | I9: 10889669 | J9: 8942137.9 | K9: 6395813.3 | L9: =H9-I9 -> 313496.41 | M9: =H9-J9 -> 2261027.1 | N9: =H9-K9 -> 4807351.7 | O9: Administración directa / Equipamiento / Contrata / Personal/bienes/servicios | P9: =IF(H9=0,"Sin PIM",IF(ROUND(K9-H9,2)>=0,"Devengado total",IF(J9>0.005,"Comprometido",IF(I9>0.005,"Solo certificado","Sin certificar")))) -> Comprometido | Q9: 4902849 | R9: 60001 | S9: 2722594 | T9: 0
A10: Gerencia de Infraestructura | B10: GERENCIA DE INFRAESTRUCTURA | C10: EJECUCIÓN POR ADMINISTRACIÓN DIRECTA > EJECUCIÓN POR ADMINISTRACIÓN DIRECTA - DIRECTIVA 10 | D10: 22. EDUCACION | E10: 2344324 | F10: 29 | G10: 2344324: MEJORAMIENTO DE LOS SERVICIOS EDUCATIVOS DE LA I.E.S. MANUEL GONZALES PRADA, CENTRO POBLADO DE ISANI - DISTRITO DE ZEPITA - PROVINCIA DE CHUCUITO - REGION PUNO | H10: 2079431 | I10: 1994037.5 | J10: 1986740.5 | K10: 1946470.9 | L10: =H10-I10 -> 85393.54 | M10: =H10-J10 -> 92690.54 | N10: =H10-K10 -> 132960.06 | O10: Administración directa / Equipamiento / Contrata / Personal/bienes/servicios | P10: =IF(H10=0,"Sin PIM",IF(ROUND(K10-H10,2)>=0,"Devengado total",IF(J10>0.005,"Comprometido",IF(I10>0.005,"Solo certificado","Sin certificar")))) -> Comprometido | Q10: 298669 | R10: 349669 | S10: 84977 | T10: 0
A11: Gerencia de Infraestructura | B11: GERENCIA DE INFRAESTRUCTURA | C11: EJECUCIÓN POR ADMINISTRACIÓN DIRECTA > EJECUCIÓN POR ADMINISTRACIÓN DIRECTA - DIRECTIVA 10 | D11: 22. EDUCACION | E11: 2490075 | F11: 315 | G11: 2490075: MEJORAMIENTO DEL SERVICIO EDUCATIVO DEL NIVEL SECUNDARIA DE LA I.E. AGROPECUARIO SAN JUAN DEL ORO EN EL DISTRITO DE SAN JUAN DEL ORO - PROVINCIA DE SANDIA - DEPARTAMENTO DE PUNO | H11: 1425006 | I11: 1239788.9 | J11: 1239288.9 | K11: 1170437 | L11: =H11-I11 -> 185217.1 | M11: =H11-J11 -> 185717.1 | N11: =H11-K11 -> 254569.02 | O11: Administración directa / Equipamiento / Contrata / Personal/bienes/servicios | P11: =IF(H11=0,"Sin PIM",IF(ROUND(K11-H11,2)>=0,"Devengado total",IF(J11>0.005,"Comprometido",IF(I11>0.005,"Solo certificado","Sin certificar")))) -> Comprometido | Q11: 1122019 | R11: 0 | S11: 32869 | T11: 0
A12: Gerencia de Infraestructura | B12: GERENCIA DE INFRAESTRUCTURA | C12: EJECUCIÓN POR ADMINISTRACIÓN DIRECTA > EJECUCIÓN POR ADMINISTRACIÓN DIRECTA - DIRECTIVA 10 | D12: 22. EDUCACION | E12: 2570978 | F12: 160 | G12: 2570978: MEJORAMIENTO DE LOS SERVICIOS DE EDUCACION SUPERIOR DEL INSTITUTO SUPERIOR TECNOLOGICO PUBLICA DE CABANILLAS DEL DISTRITO DE CABANILLAS - PROVINCIA DE SAN ROMAN - DEPARTAMENTO DE PUNO | H12: 9222405 | I12: 9003232.5 | J12: 6544074.6 | K12: 5421356.6 | L12: =H12-I12 -> 219172.47 | M12: =H12-J12 -> 2678330.4 | N12: =H12-K12 -> 3801048.4 | O12: Administración directa / Equipamiento / Contrata / Personal/bienes/servicios | P12: =IF(H12=0,"Sin PIM",IF(ROUND(K12-H12,2)>=0,"Devengado total",IF(J12>0.005,"Comprometido",IF(I12>0.005,"Solo certificado","Sin certificar")))) -> Comprometido | Q12: 2595053 | R12: 255676 | S12: 1817178 | T12: 0
A13: Gerencia de Infraestructura | B13: GERENCIA DE INFRAESTRUCTURA | C13: EJECUCIÓN POR ADMINISTRACIÓN DIRECTA > EJECUCIÓN POR ADMINISTRACIÓN DIRECTA - DIRECTIVA 10 | D13: 22. EDUCACION | E13: 2591926 | F13: 162 | G13: 2591926: MEJORAMIENTO SERVICIO DE EDUCACION SUPERIOR TECNOLOGICA EN EL INSTITUTO SUPERIOR TECNOLOGICO PUBLICO JOSE DOMINGO CHOQUEHUANCA DEL DISTRITO DE JOSE DOMINGO CHOQUEHUANCA DE LA PROVINCIA DE AZANGARO DEL DEPARTAMENTO DE PUNO | H13: 5194033 | I13: 5106124.8 | J13: 4283978.6 | K13: 1941765.3 | L13: =H13-I13 -> 87908.23 | M13: =H13-J13 -> 910054.36 | N13: =H13-K13 -> 3252267.7 | O13: Contrata / Personal/bienes/servicios | P13: =IF(H13=0,"Sin PIM",IF(ROUND(K13-H13,2)>=0,"Devengado total",IF(J13>0.005,"Comprometido",IF(I13>0.005,"Solo certificado","Sin certificar")))) -> Comprometido | Q13: 5194033 | R13: 6569076 | S13: 1 | T13: 0
A14: Gerencia de Infraestructura | B14: GERENCIA DE INFRAESTRUCTURA | C14: EJECUCIÓN POR ADMINISTRACIÓN DIRECTA > EJECUCIÓN POR ADMINISTRACIÓN DIRECTA - DIRECTIVA 10 | D14: 22. EDUCACION | E14: 2629119 | F14: 44 | G14: 2629119.MEJORAMIENTO DEL SERVICIO DE EDUCACION SECUNDARIA EN I.E. ROSASPATA DE CENTRO POBLADO ROSASPATA DISTRITO DE ROSASPATA DE LA PROVINCIA DE HUANCANE DEL DEPARTAMENTO DE PUNO | H14: 3656326 | I14: 3383177.1 | J14: 3097239.5 | K14: 2126125.4 | L14: =H14-I14 -> 273148.9 | M14: =H14-J14 -> 559086.53 | N14: =H14-K14 -> 1530200.6 | O14: Administración directa / Contrata / Personal/bienes/servicios / Equipamiento | P14: =IF(H14=0,"Sin PIM",IF(ROUND(K14-H14,2)>=0,"Devengado total",IF(J14>0.005,"Comprometido",IF(I14>0.005,"Solo certificado","Sin certificar")))) -> Comprometido | Q14: 2278000 | R14: 1683936 | S14: 1459275 | T14: 0
A15: Gerencia de Infraestructura | B15: GERENCIA DE INFRAESTRUCTURA | C15: EJECUCIÓN POR ADMINISTRACIÓN DIRECTA > EJECUCIÓN POR ADMINISTRACIÓN DIRECTA - DIRECTIVA 10 | D15: 22. EDUCACION | E15: 2539673 | F15: 248 | G15: 2539673: MEJORAMIENTO Y AMPLIACION DEL SERVICIO DE EDUCACION SUPERIOR TECNOLOGICA EN EL INSTITUTO SUPERIOR TECNOLOGICO PUBLICO DE JULI, DISTRITO DE JULI - PROVINCIA DE CHUCUITO - DEPARTAMENTO DE PUNO | H15: 2000000 | I15: 2000000 | J15: 0 | K15: 0 | L15: =H15-I15 -> 0 | M15: =H15-J15 -> 2000000 | N15: =H15-K15 -> 2000000 | O15: Contrata | P15: =IF(H15=0,"Sin PIM",IF(ROUND(K15-H15,2)>=0,"Devengado total",IF(J15>0.005,"Comprometido",IF(I15>0.005,"Solo certificado","Sin certificar")))) -> Solo certificado | Q15: 12000000 | R15: 14558623 | S15: 14894208 | T15: 10928387
A16: Gerencia de Infraestructura | B16: GERENCIA DE INFRAESTRUCTURA | C16: EJECUCIÓN POR ADMINISTRACIÓN DIRECTA > EJECUCIÓN POR ADMINISTRACIÓN DIRECTA - DIRECTIVA 10 | D16: 22. EDUCACION | E16: 2637985 | F16: 45 | G16: 2637985: MEJORAMIENTO DEL SERVICIO DE EDUCACION SECUNDARIA EN I.E. LLAULLI DE CENTRO POBLADO LLAULLI DISTRITO DE MOHO DE LA PROVINCIA DE MOHO DEL DEPARTAMENTO DE PUNO | H16: 0 | I16: 0 | J16: 0 | K16: 0 | L16: =H16-I16 -> 0 | M16: =H16-J16 -> 0 | N16: =H16-K16 -> 0 | O16: Contrata | P16: =IF(H16=0,"Sin PIM",IF(ROUND(K16-H16,2)>=0,"Devengado total",IF(J16>0.005,"Comprometido",IF(I16>0.005,"Solo certificado","Sin certificar")))) -> Sin PIM | Q16: 100000 | R16: 1234564 | S16: 0 | T16: 3335545
A17: Gerencia de Infraestructura | B17: GERENCIA DE INFRAESTRUCTURA | C17: EJECUCIÓN POR ADMINISTRACIÓN DIRECTA > EJECUCIÓN POR ADMINISTRACIÓN DIRECTA - DIRECTIVA 10 | D17: 22. EDUCACION | E17: 2664940 | F17: 193 | G17: 2664940: MEJORAMIENTO DEL SERVICIO DE EDUCACION INICIAL EN I.E. 1099 INMACULADA DISTRITO DE PUTINA DE LA PROVINCIA DE SAN ANTONIO DE PUTINA DEL DEPARTAMENTO DE PUNO | H17: 1861270 | I17: 1466941.4 | J17: 1458946.4 | K17: 1164545.4 | L17: =H17-I17 -> 394328.59 | M17: =H17-J17 -> 402323.59 | N17: =H17-K17 -> 696724.63 | O17: Administración directa / Contrata / Expediente técnico / Equipamiento / Personal/bienes/servicios | P17: =IF(H17=0,"Sin PIM",IF(ROUND(K17-H17,2)>=0,"Devengado total",IF(J17>0.005,"Comprometido",IF(I17>0.005,"Solo certificado","Sin certificar")))) -> Comprometido | Q17: 1410000 | R17: 833474 | S17: 0 | T17: 0
A18: Gerencia de Infraestructura | B18: GERENCIA DE INFRAESTRUCTURA | C18: EJECUCIÓN POR ADMINISTRACIÓN DIRECTA > EJECUCIÓN POR ADMINISTRACIÓN DIRECTA - DIRECTIVA 10 | D18: 22. EDUCACION | E18: 2637997 | F18: 46 | G18: 2637997: MEJORAMIENTO DEL SERVICIO DE EDUCACION SECUNDARIA EN I.E. UMUCHI DISTRITO DE MOHO DE LA PROVINCIA DE MOHO DEL DEPARTAMENTO DE PUNO | H18: 304829 | I18: 0 | J18: 0 | K18: 0 | L18: =H18-I18 -> 304829 | M18: =H18-J18 -> 304829 | N18: =H18-K18 -> 304829 | O18: Contrata | P18: =IF(H18=0,"Sin PIM",IF(ROUND(K18-H18,2)>=0,"Devengado total",IF(J18>0.005,"Comprometido",IF(I18>0.005,"Solo certificado","Sin certificar")))) -> Sin certificar | Q18: 100000 | R18: 0 | S18: 0 | T18: 4317457
A19: Gerencia de Infraestructura | B19: GERENCIA DE INFRAESTRUCTURA | C19: EJECUCIÓN POR ADMINISTRACIÓN DIRECTA > EJECUCIÓN POR ADMINISTRACIÓN DIRECTA - DIRECTIVA 10 | D19: 22. EDUCACION | E19: 2650476 | F19: 480 | G19: 2650476.ADQUISICION DE EQUIPAMIENTO DE AMBIENTES COMPLEMENTARIOS Y MOBILIARIO DE AULA; EN EL(LA) I.E. EL CENTENARIO DISTRITO DE PUTINA, PROVINCIA SAN ANTONIO DE PUTINA, DEPARTAMENTO PUNO | H19: 677644 | I19: 607692.88 | J19: 331244.1 | K19: 131223.38 | L19: =H19-I19 -> 69951.12 | M19: =H19-J19 -> 346399.9 | N19: =H19-K19 -> 546420.62 | O19: Equipamiento / Contrata / Administración directa / Personal/bienes/servicios | P19: =IF(H19=0,"Sin PIM",IF(ROUND(K19-H19,2)>=0,"Devengado total",IF(J19>0.005,"Comprometido",IF(I19>0.005,"Solo certificado","Sin certificar")))) -> Comprometido | Q19: No registrado en cartera | R19: No registrado en cartera | S19: No registrado en cartera | T19: No registrado en cartera
A20: Gerencia de Infraestructura | B20: GERENCIA DE INFRAESTRUCTURA | C20: EJECUCIÓN POR ADMINISTRACIÓN DIRECTA > EJECUCIÓN POR ADMINISTRACIÓN DIRECTA - DIRECTIVA 10 | D20: 22. EDUCACION | E20: 2695845 | F20: 479 | G20: 2695845.MEJORAMIENTO DEL SERVICIO DE EDUCACION SECUNDARIA EN I.E. SAN FRANCISCO DE BORJA DISTRITO DE TARACO DE LA PROVINCIA DE HUANCANE DEL DEPARTAMENTO DE PUNO | H20: 492669 | I20: 464894 | J20: 413671.98 | K20: 211662.5 | L20: =H20-I20 -> 27775 | M20: =H20-J20 -> 78997.02 | N20: =H20-K20 -> 281006.5 | O20: Expediente técnico | P20: =IF(H20=0,"Sin PIM",IF(ROUND(K20-H20,2)>=0,"Devengado total",IF(J20>0.005,"Comprometido",IF(I20>0.005,"Solo certificado","Sin certificar")))) -> Comprometido | Q20: No registrado en cartera | R20: No registrado en cartera | S20: No registrado en cartera | T20: No registrado en cartera
A21: Gerencia de Infraestructura | B21: GERENCIA DE INFRAESTRUCTURA | C21: EJECUCIÓN POR ADMINISTRACIÓN DIRECTA > EJECUCIÓN POR ADMINISTRACIÓN DIRECTA - DIRECTIVA 10 | D21: 22. EDUCACION | E21: 2196865 | F21: 170 | G21: 2196865: MEJORAMIENTO DEL SERVICIO EDUCATIVO DE NIVEL INICIAL ESCOLARIZADO EN LA I.E.I. LLUNGO, DISTRITO DE ATUNCOLLA, PROVINCIA DE PUNO - PUNO. | H21: 118539 | I21: 70562.13 | J21: 70562.13 | K21: 70562.13 | L21: =H21-I21 -> 47976.87 | M21: =H21-J21 -> 47976.87 | N21: =H21-K21 -> 47976.87 | O21: Contrata / Personal/bienes/servicios / Administración directa | P21: =IF(H21=0,"Sin PIM",IF(ROUND(K21-H21,2)>=0,"Devengado total",IF(J21>0.005,"Comprometido",IF(I21>0.005,"Solo certificado","Sin certificar")))) -> Comprometido | Q21: 159740 | R21: 0 | S21: 0 | T21: 0
A22: Gerencia de Infraestructura | B22: GERENCIA DE INFRAESTRUCTURA | C22: EJECUCIÓN POR ADMINISTRACIÓN DIRECTA > EJECUCIÓN POR ADMINISTRACIÓN DIRECTA - DIRECTIVA 10 | D22: 22. EDUCACION | E22: 2301117 | F22: 490 | G22: 2301117: MEJORAMIENTO DEL SERVICIO EDUCATIVO EN LAS INSTITUCIONES EDUCATIVAS PRIMARIAS N 70511, N 70815 Y N 72637, DISTRITO DE ORURILLO - MELGAR - PUNO | H22: 28700 | I22: 0 | J22: 0 | K22: 0 | L22: =H22-I22 -> 28700 | M22: =H22-J22 -> 28700 | N22: =H22-K22 -> 28700 | O22: Administración directa | P22: =IF(H22=0,"Sin PIM",IF(ROUND(K22-H22,2)>=0,"Devengado total",IF(J22>0.005,"Comprometido",IF(I22>0.005,"Solo certificado","Sin certificar")))) -> Sin certificar | Q22: 539829 | R22: 504509 | S22: 0 | T22: 0
A23: Gerencia de Infraestructura | B23: GERENCIA DE INFRAESTRUCTURA | C23: EJECUCIÓN POR ADMINISTRACIÓN DIRECTA > EJECUCIÓN POR ADMINISTRACIÓN DIRECTA - DIRECTIVA 10 | D23: 22. EDUCACION | E23: 2301117 | F23: 489 | G23: 2301117: MEJORAMIENTO DEL SERVICIO EDUCATIVO EN LAS INSTITUCIONES EDUCATIVAS PRIMARIAS N 70511, N 70815 Y N 72637, DISTRITO DE ORURILLO - MELGAR - PUNO | H23: 25000 | I23: 0 | J23: 0 | K23: 0 | L23: =H23-I23 -> 25000 | M23: =H23-J23 -> 25000 | N23: =H23-K23 -> 25000 | O23: Administración directa | P23: =IF(H23=0,"Sin PIM",IF(ROUND(K23-H23,2)>=0,"Devengado total",IF(J23>0.005,"Comprometido",IF(I23>0.005,"Solo certificado","Sin certificar")))) -> Sin certificar | Q23: 539829 | R23: 504509 | S23: 0 | T23: 0
A24: Gerencia de Infraestructura | B24: GERENCIA DE INFRAESTRUCTURA | C24: EJECUCIÓN POR ADMINISTRACIÓN DIRECTA > EJECUCIÓN POR ADMINISTRACIÓN DIRECTA - DIRECTIVA 10 | D24: 22. EDUCACION | E24: 2623682 | F24: 484 | G24: 2623682: RENOVACION DE AULA DE EDUCACION SUPERIOR PEDAGOGICA, LABORATORIO Y/O TALLER Y AMBIENTE COMPLEMENTARIO; REPARACION DE CERCO Y/O PORTADA; ADEMAS DE OTROS ACTIVOS EN EL(LA) INSTITUTO DE EDUCACION SUPERIOR PEDAGOGICO HUANCANE DEL DISTRITO DE HUANCANE, PROVINCIA HUANCANE, DEPARTAMENTO PUNO | H24: 23560 | I24: 22650 | J24: 22650 | K24: 14282.09 | L24: =H24-I24 -> 910 | M24: =H24-J24 -> 910 | N24: =H24-K24 -> 9277.91 | O24: Contrata / Personal/bienes/servicios | P24: =IF(H24=0,"Sin PIM",IF(ROUND(K24-H24,2)>=0,"Devengado total",IF(J24>0.005,"Comprometido",IF(I24>0.005,"Solo certificado","Sin certificar")))) -> Comprometido | Q24: 23560 | R24: 27080 | S24: 0 | T24: 0
A25: Gerencia de Infraestructura | B25: GERENCIA DE INFRAESTRUCTURA | C25: EJECUCIÓN POR ADMINISTRACIÓN DIRECTA > EJECUCIÓN POR ADMINISTRACIÓN DIRECTA - DIRECTIVA 10 | D25: 22. EDUCACION | E25: 2196822 | F25: 453 | G25: 2196822: INSTALACION DEL SERVICIO DE EDUCACION INICIAL DE LA I.E.I. NRO. 94 DEL CENTRO POBLADO DE UMUCHI, DISTRITO DE MOHO, PROVINCIA DE MOHO, DEPARTAMENTO DE PUNO. | H25: 17714 | I25: 14228.68 | J25: 14228.68 | K25: 9749.8 | L25: =H25-I25 -> 3485.32 | M25: =H25-J25 -> 3485.32 | N25: =H25-K25 -> 7964.2 | O25: Contrata / Administración directa / Personal/bienes/servicios | P25: =IF(H25=0,"Sin PIM",IF(ROUND(K25-H25,2)>=0,"Devengado total",IF(J25>0.005,"Comprometido",IF(I25>0.005,"Solo certificado","Sin certificar")))) -> Comprometido | Q25: 13915 | R25: 0 | S25: 0 | T25: 0
A26: Gerencia de Infraestructura | B26: GERENCIA DE INFRAESTRUCTURA | C26: EJECUCIÓN POR ADMINISTRACIÓN DIRECTA > EJECUCIÓN POR ADMINISTRACIÓN DIRECTA - DIRECTIVA 10 | D26: 22. EDUCACION | E26: 2194504 | F26: 24 | G26: 2194504: INSTALACION DEL SERVICIO EDUCATIVO DEL NIVEL SECUNDARIO EN LA I.E.S. RODOLFO DIESEL, DISTRITO DE JULIACA, PROVINCIA SAN ROMAN - PUNO. | H26: 0 | I26: 0 | J26: 0 | K26: 0 | L26: =H26-I26 -> 0 | M26: =H26-J26 -> 0 | N26: =H26-K26 -> 0 | O26: Contrata | P26: =IF(H26=0,"Sin PIM",IF(ROUND(K26-H26,2)>=0,"Devengado total",IF(J26>0.005,"Comprometido",IF(I26>0.005,"Solo certificado","Sin certificar")))) -> Sin PIM | Q26: No registrado en cartera | R26: No registrado en cartera | S26: No registrado en cartera | T26: No registrado en cartera
A27: Gerencia de Infraestructura | B27: GERENCIA DE INFRAESTRUCTURA | C27: EJECUCIÓN POR ADMINISTRACIÓN DIRECTA > EJECUCIÓN POR ADMINISTRACIÓN DIRECTA - DIRECTIVA 10 | D27: 22. EDUCACION | E27: 2196834 | F27: 168 | G27: 2196834: MEJORAMIENTO DE LOS SERVICIOS DE EDUCACION INICIAL EN LA I.E.I. CUCURAYA DE LA COMUNIDAD DE CUCURAYA, DISTRITO DE TILALI, PROVINCIA DE MOHO - PUNO. | H27: 728529 | I27: 0 | J27: 0 | K27: 0 | L27: =H27-I27 -> 728529 | M27: =H27-J27 -> 728529 | N27: =H27-K27 -> 728529 | O27: Administración directa / Contrata / Equipamiento / Personal/bienes/servicios | P27: =IF(H27=0,"Sin PIM",IF(ROUND(K27-H27,2)>=0,"Devengado total",IF(J27>0.005,"Comprometido",IF(I27>0.005,"Solo certificado","Sin certificar")))) -> Sin certificar | Q27: 699403 | R27: 0 | S27: 0 | T27: 0
A28: Gerencia de Infraestructura | B28: GERENCIA DE INFRAESTRUCTURA | C28: EJECUCIÓN POR ADMINISTRACIÓN DIRECTA > EJECUCIÓN POR ADMINISTRACIÓN DIRECTA - DIRECTIVA 10 | D28: 22. EDUCACION | E28: 2490131 | F28: 464 | G28: 2490131: MEJORAMIENTO DEL SERVICIO DE EDUCACION SECUNDARIA DE LA IES CABANILLAS, DISTRITO DE CABANILLAS - PROVINCIA DE SAN ROMAN - DEPARTAMENTO DE PUNO | H28: 40621 | I28: 28914.4 | J28: 28914.4 | K28: 27953.93 | L28: =H28-I28 -> 11706.6 | M28: =H28-J28 -> 11706.6 | N28: =H28-K28 -> 12667.07 | O28: Contrata / Personal/bienes/servicios / Laudos arbitrales | P28: =IF(H28=0,"Sin PIM",IF(ROUND(K28-H28,2)>=0,"Devengado total",IF(J28>0.005,"Comprometido",IF(I28>0.005,"Solo certificado","Sin certificar")))) -> Comprometido | Q28: 2455 | R28: 0 | S28: 0 | T28: 0
A29: Gerencia de Infraestructura | B29: GERENCIA DE INFRAESTRUCTURA | C29: EJECUCIÓN POR ADMINISTRACIÓN DIRECTA > EJECUCIÓN POR ADMINISTRACIÓN DIRECTA - DIRECTIVA 10 | D29: 22. EDUCACION | E29: 2196857 | F29: 169 | G29: 2196857: INSTALACION DEL SERVICIO EDUCATIVO EN LA INSTITUCION EDUCATIVA INICIAL N 986 SAN JUAN BAUTISTA DEL DISTRITO DE JULIACA, PROVINCIA DE SAN ROMAN - PUNO | H29: 0 | I29: 0 | J29: 0 | K29: 0 | L29: =H29-I29 -> 0 | M29: =H29-J29 -> 0 | N29: =H29-K29 -> 0 | O29: Contrata | P29: =IF(H29=0,"Sin PIM",IF(ROUND(K29-H29,2)>=0,"Devengado total",IF(J29>0.005,"Comprometido",IF(I29>0.005,"Solo certificado","Sin certificar")))) -> Sin PIM | Q29: 2878733 | R29: 0 | S29: 0 | T29: 0
A30: Gerencia de Infraestructura | B30: GERENCIA DE INFRAESTRUCTURA | C30: EJECUCIÓN POR ADMINISTRACIÓN DIRECTA > EJECUCIÓN POR ADMINISTRACIÓN DIRECTA - DIRECTIVA 10 | D30: 22. EDUCACION | E30: 2301117 | F30: 27 | G30: 2301117: MEJORAMIENTO DEL SERVICIO EDUCATIVO EN LAS INSTITUCIONES EDUCATIVAS PRIMARIAS N 70511, N 70815 Y N 72637, DISTRITO DE ORURILLO - MELGAR - PUNO | H30: 855386 | I30: 725859.11 | J30: 718409.61 | K30: 715665.61 | L30: =H30-I30 -> 129526.89 | M30: =H30-J30 -> 136976.39 | N30: =H30-K30 -> 139720.39 | O30: Administración directa / Contrata / Expediente técnico / Equipamiento / Personal/bienes/servicios | P30: =IF(H30=0,"Sin PIM",IF(ROUND(K30-H30,2)>=0,"Devengado total",IF(J30>0.005,"Comprometido",IF(I30>0.005,"Solo certificado","Sin certificar")))) -> Comprometido | Q30: 539829 | R30: 504509 | S30: 0 | T30: 0
A31: Gerencia de Infraestructura | B31: GERENCIA DE INFRAESTRUCTURA | C31: EJECUCIÓN POR ADMINISTRACIÓN DIRECTA > EJECUCIÓN POR ADMINISTRACIÓN DIRECTA - DIRECTIVA 10 | D31: 22. EDUCACION | E31: 2194462 | F31: 22 | G31: 2194462: INSTALACION DEL SERVICIO DE EDUCACION SECUNDARIA THOMAS ALVA EDISON EN LA URBANIZACION CHILLA - LOS ROSALES EN EL DISTRITO DE JULIACA, PROVINCIA DE SAN ROMAN. | H31: 77590 | I31: 76159.18 | J31: 76159.18 | K31: 76159.18 | L31: =H31-I31 -> 1430.82 | M31: =H31-J31 -> 1430.82 | N31: =H31-K31 -> 1430.82 | O31: Contrata / Personal/bienes/servicios | P31: =IF(H31=0,"Sin PIM",IF(ROUND(K31-H31,2)>=0,"Devengado total",IF(J31>0.005,"Comprometido",IF(I31>0.005,"Solo certificado","Sin certificar")))) -> Comprometido | Q31: 357505 | R31: 0 | S31: 0 | T31: 344884
A32: Gerencia de Infraestructura | B32: GERENCIA DE INFRAESTRUCTURA | C32: EJECUCIÓN POR ADMINISTRACIÓN DIRECTA > EJECUCIÓN POR ADMINISTRACIÓN DIRECTA - DIRECTIVA 10 | D32: 22. EDUCACION | E32: 2467893 | F32: 37 | G32: 2467893: MEJORAMIENTO DEL SERVICIO EDUCATIVO DEL NIVEL SECUNDARIA DE LA I.E.S. TARACO DEL DISTRITO DE TARACO - PROVINCIA DE HUANCANE - DEPARTAMENTO DE PUNO | H32: 50132 | I32: 47450.05 | J32: 47450.05 | K32: 47450.05 | L32: =H32-I32 -> 2681.95 | M32: =H32-J32 -> 2681.95 | N32: =H32-K32 -> 2681.95 | O32: Contrata | P32: =IF(H32=0,"Sin PIM",IF(ROUND(K32-H32,2)>=0,"Devengado total",IF(J32>0.005,"Comprometido",IF(I32>0.005,"Solo certificado","Sin certificar")))) -> Comprometido | Q32: 175369 | R32: 79091 | S32: 583672 | T32: 0
A33: Gerencia de Infraestructura | B33: GERENCIA DE INFRAESTRUCTURA | C33: EJECUCIÓN POR ADMINISTRACIÓN DIRECTA > EJECUCIÓN POR ADMINISTRACIÓN DIRECTA - DIRECTIVA 10 | D33: 15. TRANSPORTE | E33: 2194702 | F33: 95 | G33: 2194702: MEJORAMIENTO DE LA CARRETERA (PU 675) POMATA - YOROHOCO, PROVINCIA DE CHUCUITO - PUNO | H33: 18401182 | I33: 17764558 | J33: 17200007 | K33: 15484260 | L33: =H33-I33 -> 636624.07 | M33: =H33-J33 -> 1201175.5 | N33: =H33-K33 -> 2916922.1 | O33: Administración directa / Contrata / Personal/bienes/servicios | P33: =IF(H33=0,"Sin PIM",IF(ROUND(K33-H33,2)>=0,"Devengado total",IF(J33>0.005,"Comprometido",IF(I33>0.005,"Solo certificado","Sin certificar")))) -> Comprometido | Q33: 9922902 | R33: 180000 | S33: 0 | T33: 0
A34: Gerencia de Infraestructura | B34: GERENCIA DE INFRAESTRUCTURA | C34: EJECUCIÓN POR ADMINISTRACIÓN DIRECTA > EJECUCIÓN POR ADMINISTRACIÓN DIRECTA - DIRECTIVA 10 | D34: 15. TRANSPORTE | E34: 2287700 | F34: 98 | G34: 2287700: MEJORAMIENTO DE LA CARRETERA PU N-110: EMP. PE-34I ASIRUNI - ROSASPATA - HUAYRAPATA - EMP. PE-34I NINANTAYA, DISTRITOS DE VILQUECHICO-ROSASPATA-MOHO-HUAYRAPATA, PROVINCIA DE HUANCANE Y MOHO - PUNO | H34: 10002053 | I34: 9636351.5 | J34: 9595158.3 | K34: 5473965.1 | L34: =H34-I34 -> 365701.52 | M34: =H34-J34 -> 406894.73 | N34: =H34-K34 -> 4528087.9 | O34: Administración directa / Contrata / Personal/bienes/servicios | P34: =IF(H34=0,"Sin PIM",IF(ROUND(K34-H34,2)>=0,"Devengado total",IF(J34>0.005,"Comprometido",IF(I34>0.005,"Solo certificado","Sin certificar")))) -> Comprometido | Q34: 4289351 | R34: 500000 | S34: 109570 | T34: 0
A35: Gerencia de Infraestructura | B35: GERENCIA DE INFRAESTRUCTURA | C35: EJECUCIÓN POR ADMINISTRACIÓN DIRECTA > EJECUCIÓN POR ADMINISTRACIÓN DIRECTA - DIRECTIVA 10 | D35: 15. TRANSPORTE | E35: 2480499 | F35: 112 | G35: 2480499: MEJORAMIENTO DE LA CARRETERA PU 146; EMP PE - 34 I (HUANCANE) - HUERTAPATA - VISCACHANI - QUELLAHUYO - EMP PE - 34 (CACUÑA), DISTRITO DE HUANCANE - PROVINCIA DE HUANCANE - DEPARTAMENTO DE PUNO | H35: 3297813 | I35: 3286650.5 | J35: 3286650.5 | K35: 3269277.3 | L35: =H35-I35 -> 11162.55 | M35: =H35-J35 -> 11162.55 | N35: =H35-K35 -> 28535.72 | O35: Administración directa / Contrata | P35: =IF(H35=0,"Sin PIM",IF(ROUND(K35-H35,2)>=0,"Devengado total",IF(J35>0.005,"Comprometido",IF(I35>0.005,"Solo certificado","Sin certificar")))) -> Comprometido | Q35: 5406629 | R35: 0 | S35: 304959 | T35: 0
A36: Gerencia de Infraestructura | B36: GERENCIA DE INFRAESTRUCTURA | C36: EJECUCIÓN POR ADMINISTRACIÓN DIRECTA > EJECUCIÓN POR ADMINISTRACIÓN DIRECTA - DIRECTIVA 10 | D36: 15. TRANSPORTE | E36: 2300575 | F36: 99 | G36: 2300575: MEJORAMIENTO DE LA AVENIDA CIRCUNVALACION II (EMP. PE- 3S-AV. HUANCANE-CIRCUNVALACION ESTE-EMP PE-3S) DE LA CIUDAD DE JULIACA- EMPALME PU-3S INICIO CON CIRCUNVALACION II - DISTRITO DE SAN MIGUEL - EMPALME PU-3S FINAL CON CIRCUNVALACION II - DISTRITO DE CARACOTO - PROVINCIA DE SAN ROMAN - REGION PUNO | H36: 2394023 | I36: 2316938.8 | J36: 2310743.8 | K36: 1138698.8 | L36: =H36-I36 -> 77084.21 | M36: =H36-J36 -> 83279.21 | N36: =H36-K36 -> 1255324.2 | O36: Administración directa / Contrata / Personal/bienes/servicios | P36: =IF(H36=0,"Sin PIM",IF(ROUND(K36-H36,2)>=0,"Devengado total",IF(J36>0.005,"Comprometido",IF(I36>0.005,"Solo certificado","Sin certificar")))) -> Comprometido | Q36: 3545977 | R36: 1000000 | S36: 3651450 | T36: 1489826
A37: Gerencia de Infraestructura | B37: GERENCIA DE INFRAESTRUCTURA | C37: EJECUCIÓN POR ADMINISTRACIÓN DIRECTA > EJECUCIÓN POR ADMINISTRACIÓN DIRECTA - DIRECTIVA 10 | D37: 15. TRANSPORTE | E37: 2031310 | F37: 87 | G37: 2031310: CONSTRUCCION Y MEJORAMIENTO DE LA CARRETERA SAN JOSE (EMP. R 100) VALLE GRANDE -ISILLUMA DEL DISTRITO DE ALTO INAMBARI | H37: 1122559 | I37: 1117871.1 | J37: 1117871.1 | K37: 1042098.6 | L37: =H37-I37 -> 4687.95 | M37: =H37-J37 -> 4687.95 | N37: =H37-K37 -> 80460.44 | O37: Administración directa / Contrata / Personal/bienes/servicios | P37: =IF(H37=0,"Sin PIM",IF(ROUND(K37-H37,2)>=0,"Devengado total",IF(J37>0.005,"Comprometido",IF(I37>0.005,"Solo certificado","Sin certificar")))) -> Comprometido | Q37: 1404195 | R37: 324567 | S37: 0 | T37: 936265
A38: Gerencia de Infraestructura | B38: GERENCIA DE INFRAESTRUCTURA | C38: EJECUCIÓN POR ADMINISTRACIÓN DIRECTA > EJECUCIÓN POR ADMINISTRACIÓN DIRECTA - DIRECTIVA 10 | D38: 15. TRANSPORTE | E38: 2163760 | F38: 92 | G38: 2163760: MEJORAMIENTO DE LA INFRAESTRUCTURA VIAL TURISTICO, TRAMO PHUTINI - JAYU JAYU, DISTRITO DE ACORA - PUNO - PUNO | H38: 1202934 | I38: 1151623.8 | J38: 1151623.8 | K38: 1105100.4 | L38: =H38-I38 -> 51310.21 | M38: =H38-J38 -> 51310.21 | N38: =H38-K38 -> 97833.58 | O38: Administración directa / Contrata / Personal/bienes/servicios | P38: =IF(H38=0,"Sin PIM",IF(ROUND(K38-H38,2)>=0,"Devengado total",IF(J38>0.005,"Comprometido",IF(I38>0.005,"Solo certificado","Sin certificar")))) -> Comprometido | Q38: 2596051 | R38: 120000 | S38: 2215461 | T38: 3675255
... A44: Gerencia de Infraestructura | B44: GERENCIA DE INFRAESTRUCTURA | C44: EJECUCIÓN POR ADMINISTRACIÓN DIRECTA > EJECUCIÓN POR ADMINISTRACIÓN DIRECTA - DIRECTIVA 10 | D44: 15. TRANSPORTE | E44: 2514428 | F44: 113 | G44: 2514428: CREACION DEL SERVICIO DE INTERCONEXION DE MOVILIDAD URBANA EN LA VIA TRONCAL DEL PUENTE YARAJA DISTRITO DE AZANGARO - PROVINCIA DE AZANGARO - DEPARTAMENTO DE PUNO | H44: 104124 | I44: 48234.88 | J44: 48234.88 | K44: 48234.88 | L44: =H44-I44 -> 55889.12 | M44: =H44-J44 -> 55889.12 | N44: =H44-K44 -> 55889.12 | O44: Administración directa / Contrata / Personal/bienes/servicios | P44: =IF(H44=0,"Sin PIM",IF(ROUND(K44-H44,2)>=0,"Devengado total",IF(J44>0.005,"Comprometido",IF(I44>0.005,"Solo certificado","Sin certificar")))) -> Comprometido | Q44: 228677 | R44: 0 | S44: 0 | T44: 865181
A45: Gerencia de Infraestructura | B45: GERENCIA DE INFRAESTRUCTURA | C45: EJECUCIÓN POR ADMINISTRACIÓN DIRECTA > EJECUCIÓN POR ADMINISTRACIÓN DIRECTA - DIRECTIVA 10 | D45: 15. TRANSPORTE | E45: 2436247 | F45: 107 | G45: 2436247.MEJORAMIENTO DEL CAMINO VECINAL RUTA PU-713, EMP. PE 3S (AYAVIRI - DESV. CALUYO - TINAJANI - L. PROV. LAMPA), DISTRITO DE AYAVIRI - PROVINCIA DE MELGAR - DEPARTAMENTO DE PUNO | H45: 22224878 | I45: 21946068 | J45: 18817053 | K45: 7073509.6 | L45: =H45-I45 -> 278809.8 | M45: =H45-J45 -> 3407824.7 | N45: =H45-K45 -> 15151368 | O45: Contrata / Personal/bienes/servicios / Expediente técnico | P45: =IF(H45=0,"Sin PIM",IF(ROUND(K45-H45,2)>=0,"Devengado total",IF(J45>0.005,"Comprometido",IF(I45>0.005,"Solo certificado","Sin certificar")))) -> Comprometido | Q45: No registrado en cartera | R45: No registrado en cartera | S45: No registrado en cartera | T45: No registrado en cartera
A46: Gerencia de Infraestructura | B46: GERENCIA DE INFRAESTRUCTURA | C46: EJECUCIÓN POR ADMINISTRACIÓN DIRECTA > EJECUCIÓN POR ADMINISTRACIÓN DIRECTA - DIRECTIVA 10 | D46: 15. TRANSPORTE | E46: 2603167 | F46: 124 | G46: 2603167.MEJORAMIENTO DEL SERVICIO DE TRANSITABILIDAD VIAL INTERURBANA EN LA CARRETERA PU - 1233 (ILAVE) - ANOKARIRI (EMP. - 1234), ANOKARIRI - SACUYO - SECTOR NUEVA ALIANZA, PU 1103 (SECTOR NUEVA ALIANZA) - EMP. PE 36P (LARAQUERI PICHACANI) DISTRITOS DE I | H46: 11412366 | I46: 10878205 | J46: 8794639.2 | K46: 6860678.4 | L46: =H46-I46 -> 534160.77 | M46: =H46-J46 -> 2617726.8 | N46: =H46-K46 -> 4551687.6 | O46: Administración directa / Contrata / Expediente técnico / Personal/bienes/servicios / Equipamiento | P46: =IF(H46=0,"Sin PIM",IF(ROUND(K46-H46,2)>=0,"Devengado total",IF(J46>0.005,"Comprometido",IF(I46>0.005,"Solo certificado","Sin certificar")))) -> Comprometido | Q46: 2800000 | R46: 10234564 | S46: 6182303 | T46: 9563936
A47: Gerencia de Infraestructura | B47: GERENCIA DE INFRAESTRUCTURA | C47: EJECUCIÓN POR ADMINISTRACIÓN DIRECTA > EJECUCIÓN POR ADMINISTRACIÓN DIRECTA - DIRECTIVA 10 | D47: 15. TRANSPORTE | E47: 2585540 | F47: 116 | G47: 2585540: MEJORAMIENTO DEL SERVICIO DE TRANSITABILIDAD VIAL INTERURBANA EN LA CARRETERA PU-139 (HDA. POTONI) - SAN JOSE, - COLLANA - EMP. PU-111 - PUENTE YARAJA (AZANGARO) DISTRITOS DE POTONI, SAN JOSE DE LA PROVINCIA DE AZANGARO DEL DEPARTAMENTO DE PUNO | H47: 6736048 | I47: 6652871.2 | J47: 5551874.7 | K47: 3336854.4 | L47: =H47-I47 -> 83176.79 | M47: =H47-J47 -> 1184173.3 | N47: =H47-K47 -> 3399193.6 | O47: Administración directa / Contrata / Expediente técnico / Personal/bienes/servicios | P47: =IF(H47=0,"Sin PIM",IF(ROUND(K47-H47,2)>=0,"Devengado total",IF(J47>0.005,"Comprometido",IF(I47>0.005,"Solo certificado","Sin certificar")))) -> Comprometido | Q47: 800000 | R47: 12057170 | S47: 6000000 | T47: 7375100
A48: Gerencia de Infraestructura | B48: GERENCIA DE INFRAESTRUCTURA | C48: EJECUCIÓN POR ADMINISTRACIÓN DIRECTA > EJECUCIÓN POR ADMINISTRACIÓN DIRECTA - DIRECTIVA 10 | D48: 15. TRANSPORTE | E48: 2603165 | F48: 123 | G48: 2603165: MEJORAMIENTO DEL SERVICIO DE TRANSITABILIDAD VIAL INTERURBANA EN LA CARRETERA TRAMO ACHAYA - EMP. PU 113(ARAPA), DE LOS DISTRITOS DE ACHAYA, ARAPA DE LA PROVINCIA DE AZANGARO DEL DEPARTAMENTO DE PUNO | H48: 9037622 | I48: 8236997.1 | J48: 7212897.1 | K48: 5290297.7 | L48: =H48-I48 -> 800624.91 | M48: =H48-J48 -> 1824724.9 | N48: =H48-K48 -> 3747324.3 | O48: Administración directa / Contrata / Equipamiento / Personal/bienes/servicios / Expediente técnico | P48: =IF(H48=0,"Sin PIM",IF(ROUND(K48-H48,2)>=0,"Devengado total",IF(J48>0.005,"Comprometido",IF(I48>0.005,"Solo certificado","Sin certificar")))) -> Comprometido | Q48: 2500000 | R48: 6578987 | S48: 6552040 | T48: 2921013
A49: Gerencia de Infraestructura | B49: GERENCIA DE INFRAESTRUCTURA | C49: EJECUCIÓN POR ADMINISTRACIÓN DIRECTA > EJECUCIÓN POR ADMINISTRACIÓN DIRECTA - DIRECTIVA 10 | D49: 15. TRANSPORTE | E49: 2185578 | F49: 94 | G49: 2185578: MEJORAMIENTO DE LA CARRETERA DV. DESAGUADERO (EMP PE 36A) - KELLUYO - PISACOMA, PROVINCIA DE CHUCUITO - PUNO | H49: 67139 | I49: 0 | J49: 0 | K49: 0 | L49: =H49-I49 -> 67139 | M49: =H49-J49 -> 67139 | N49: =H49-K49 -> 67139 | O49: Contrata | P49: =IF(H49=0,"Sin PIM",IF(ROUND(K49-H49,2)>=0,"Devengado total",IF(J49>0.005,"Comprometido",IF(I49>0.005,"Solo certificado","Sin certificar")))) -> Sin certificar | Q49: 1732548 | R49: 0 | S49: 2325267 | T49: 0
A50: Gerencia de Infraestructura | B50: GERENCIA DE INFRAESTRUCTURA | C50: EJECUCIÓN POR ADMINISTRACIÓN DIRECTA > EJECUCIÓN POR ADMINISTRACIÓN DIRECTA - DIRECTIVA 10 | D50: 15. TRANSPORTE | E50: 2515272 | F50: 433 | G50: 2515272: RECUPERACION DEL PUENTE COLGANTE PEATONAL SOBRE EL RIO INAMBARI EN LA LOCALIDAD SANTA ROSA YANAMAYO DEL DISTRITO DE ALTO INAMBARI - PROVINCIA DE SANDIA - DEPARTAMENTO DE PUNO | H50: 105000 | I50: 44312.3 | J50: 44312.3 | K50: 39935.87 | L50: =H50-I50 -> 60687.7 | M50: =H50-J50 -> 60687.7 | N50: =H50-K50 -> 65064.13 | O50: Administración directa / Contrata / Personal/bienes/servicios | P50: =IF(H50=0,"Sin PIM",IF(ROUND(K50-H50,2)>=0,"Devengado total",IF(J50>0.005,"Comprometido",IF(I50>0.005,"Solo certificado","Sin certificar")))) -> Comprometido | Q50: 105000 | R50: 0 | S50: 0 | T50: 0
A51: Gerencia de Infraestructura | B51: GERENCIA DE INFRAESTRUCTURA | C51: EJECUCIÓN POR ADMINISTRACIÓN DIRECTA > EJECUCIÓN POR ADMINISTRACIÓN DIRECTA - DIRECTIVA 10 | D51: 15. TRANSPORTE | E51: 2585540 | F51: 508 | G51: 2585540.MEJORAMIENTO DEL SERVICIO DE TRANSITABILIDAD VIAL INTERURBANA EN LA CARRETERA PU-139 (HDA. POTONI) - SAN JOSE, - COLLANA - EMP. PU-111 - PUENTE YARAJA (AZANGARO) DISTRITOS DE POTONI, SAN JOSE DE LA PROVINCIA DE AZANGARO DEL DEPARTAMENTO DE PUNO | H51: 94054 | I51: 94054 | J51: 94054 | K51: 60075.86 | L51: =H51-I51 -> 0 | M51: =H51-J51 -> 0 | N51: =H51-K51 -> 33978.14 | O51: Expediente técnico | P51: =IF(H51=0,"Sin PIM",IF(ROUND(K51-H51,2)>=0,"Devengado total",IF(J51>0.005,"Comprometido",IF(I51>0.005,"Solo certificado","Sin certificar")))) -> Comprometido | Q51: 800000 | R51: 12057170 | S51: 6000000 | T51: 7375100
A52: Gerencia de Infraestructura | B52: GERENCIA DE INFRAESTRUCTURA | C52: EJECUCIÓN POR ADMINISTRACIÓN DIRECTA > EJECUCIÓN POR ADMINISTRACIÓN DIRECTA - DIRECTIVA 10 | D52: 15. TRANSPORTE | E52: 2440946 | F52: 457 | G52: 2440946.MEJORAMIENTO DEL SERVICIO DE TRANSITABILIDAD VEHICULAR DE LA CARRETERA TRAMO ACHAYA (PU-140) - ESTRELLA (EMP. PE- 3S) DEL DISTRITO DE ACHAYA - PROVINCIA DE AZANGARO - DEPARTAMENTO DE PUNO | H52: 28752 | I52: 28751.6 | J52: 28751.6 | K52: 28751.6 | L52: =H52-I52 -> 0.4 | M52: =H52-J52 -> 0.4 | N52: =H52-K52 -> 0.4 | O52: Administración directa | P52: =IF(H52=0,"Sin PIM",IF(ROUND(K52-H52,2)>=0,"Devengado total",IF(J52>0.005,"Comprometido",IF(I52>0.005,"Solo certificado","Sin certificar")))) -> Comprometido | Q52: 28752 | R52: 50000 | S52: 0 | T52: 0
A53: Gerencia de Infraestructura | B53: GERENCIA DE INFRAESTRUCTURA | C53: EJECUCIÓN POR ADMINISTRACIÓN DIRECTA > EJECUCIÓN POR ADMINISTRACIÓN DIRECTA - DIRECTIVA 10 | D53: 15. TRANSPORTE | E53: 2055915 | F53: 88 | G53: 2055915: MEJORAMIENTO DE LA CARRETERA AZANGARO - SAYTOCOCHA - SANDIA - SAN JUAN DEL ORO | H53: 0 | I53: 0 | J53: 0 | K53: 0 | L53: =H53-I53 -> 0 | M53: =H53-J53 -> 0 | N53: =H53-K53 -> 0 | O53: Personal/bienes/servicios | P53: =IF(H53=0,"Sin PIM",IF(ROUND(K53-H53,2)>=0,"Devengado total",IF(J53>0.005,"Comprometido",IF(I53>0.005,"Solo certificado","Sin certificar")))) -> Sin PIM | Q53: 7600000 | R53: 413080 | S53: 1413086 | T53: 5797708
A54: Gerencia de Infraestructura | B54: GERENCIA DE INFRAESTRUCTURA | C54: EJECUCIÓN POR ADMINISTRACIÓN DIRECTA > EJECUCIÓN POR ADMINISTRACIÓN DIRECTA - DIRECTIVA 10 | D54: 15. TRANSPORTE | E54: 2131389 | F54: 89 | G54: 2131389: MEJORAMIENTO DE LA INFRAESTRUCTURA VIAL DEL CIRCUITO TURISTICO LAGO SAGRADO DE LOS INCAS - DISTRITOS CAPACHICA, CHUCUITO, PLATERIA, ACORA, ILAVE | H54: 0 | I54: 0 | J54: 0 | K54: 0 | L54: =H54-I54 -> 0 | M54: =H54-J54 -> 0 | N54: =H54-K54 -> 0 | O54: Contrata | P54: =IF(H54=0,"Sin PIM",IF(ROUND(K54-H54,2)>=0,"Devengado total",IF(J54>0.005,"Comprometido",IF(I54>0.005,"Solo certificado","Sin certificar")))) -> Sin PIM | Q54: 3778561 | R54: 0 | S54: 0 | T54: 1047863
A55: Gerencia de Infraestructura | B55: GERENCIA DE INFRAESTRUCTURA | C55: EJECUCIÓN POR ADMINISTRACIÓN DIRECTA > EJECUCIÓN POR ADMINISTRACIÓN DIRECTA - DIRECTIVA 10 | D55: 15. TRANSPORTE | E55: 2232371 | F55: 97 | G55: 2232371: MEJORAMIENTO Y CONSTRUCCION DE LA CARRETERA PICHACANI - YURACMAYO DISTRITO DE PICHACANI Y SAN ANTONIO, PROVINCIA DE PUNO - PUNO | H55: 0 | I55: 0 | J55: 0 | K55: 0 | L55: =H55-I55 -> 0 | M55: =H55-J55 -> 0 | N55: =H55-K55 -> 0 | O55: Contrata | P55: =IF(H55=0,"Sin PIM",IF(ROUND(K55-H55,2)>=0,"Devengado total",IF(J55>0.005,"Comprometido",IF(I55>0.005,"Solo certificado","Sin certificar")))) -> Sin PIM | Q55: 1023926 | R55: 0 | S55: 0 | T55: 0
A56: Gerencia de Infraestructura | B56: GERENCIA DE INFRAESTRUCTURA | C56: EJECUCIÓN POR ADMINISTRACIÓN DIRECTA > EJECUCIÓN POR ADMINISTRACIÓN DIRECTA - DIRECTIVA 10 | D56: 15. TRANSPORTE | E56: 2443679 | F56: 108 | G56: 2443679: MEJORAMIENTO DEL SERVICIO DE TRANSITABILIDAD VEHICULAR DE LA CARRETERA TRAMO I: EMP- 34L (COJATA) - HUANCASAYA, TRAMO II: HUANCASAYA - TARUCANI-EMP-PU-115 (INCHUPALLA), DEL DISTRITO DE COJATA - PROVINCIA DE HUANCANE - DEPARTAMENTO DE PUNO | H56: 0 | I56: 0 | J56: 0 | K56: 0 | L56: =H56-I56 -> 0 | M56: =H56-J56 -> 0 | N56: =H56-K56 -> 0 | O56: Contrata | P56: =IF(H56=0,"Sin PIM",IF(ROUND(K56-H56,2)>=0,"Devengado total",IF(J56>0.005,"Comprometido",IF(I56>0.005,"Solo certificado","Sin certificar")))) -> Sin PIM | Q56: 800000 | R56: 2345478 | S56: 9005306 | T56: 19493721
A57: Gerencia de Infraestructura | B57: GERENCIA DE INFRAESTRUCTURA | C57: EJECUCIÓN POR ADMINISTRACIÓN DIRECTA > EJECUCIÓN POR ADMINISTRACIÓN DIRECTA - DIRECTIVA 10 | D57: 21. CULTURA Y DEPORTE | E57: 2163853 | F57: 217 | G57: 2163853: MEJORAMIENTO DEL ESTADIO MUNICIPAL CESAR RAUL CARRERA DEL DISTRITO DE AZANGARO, PROVINCIA DE AZANGARO - PUNO | H57: 5810277 | I57: 5204423.6 | J57: 3160250 | K57: 1157372.6 | L57: =H57-I57 -> 605853.4 | M57: =H57-J57 -> 2650027 | N57: =H57-K57 -> 4652904.4 | O57: Administración directa / Contrata / Personal/bienes/servicios | P57: =IF(H57=0,"Sin PIM",IF(ROUND(K57-H57,2)>=0,"Devengado total",IF(J57>0.005,"Comprometido",IF(I57>0.005,"Solo certificado","Sin certificar")))) -> Comprometido | Q57: 6269000 | R57: 1345765 | S57: 5566267 | T57: 0
... A67: Gerencia de Infraestructura | B67: GERENCIA DE INFRAESTRUCTURA | C67: EJECUCIÓN POR ADMINISTRACIÓN DIRECTA > EJECUCIÓN POR ADMINISTRACIÓN DIRECTA - DIRECTIVA 10 | D67: 23. PROTECCION SOCIAL | E67: 2230752 | F67: 456 | G67: 2230752: MEJORAMIENTO DE LOS SERVICIOS ASISTENCIALES DE LA ALDEA INFANTIL VIRGEN DE LA CANDELARIA EN EL BARRIO LA RINCONADA DEL CENTRO POBLADO DE SALCEDO, DISTRITO DE PUNO, PROVINCIA DE PUNO, REGION DE PUNO | H67: 99230 | I67: 99007.59 | J67: 96667.59 | K67: 96198.77 | L67: =H67-I67 -> 222.41 | M67: =H67-J67 -> 2562.41 | N67: =H67-K67 -> 3031.23 | O67: Administración directa / Contrata / Personal/bienes/servicios | P67: =IF(H67=0,"Sin PIM",IF(ROUND(K67-H67,2)>=0,"Devengado total",IF(J67>0.005,"Comprometido",IF(I67>0.005,"Solo certificado","Sin certificar")))) -> Comprometido | Q67: 99230 | R67: 0 | S67: 0 | T67: 0
A68: Gerencia de Infraestructura | B68: GERENCIA DE INFRAESTRUCTURA | C68: EJECUCIÓN POR ADMINISTRACIÓN DIRECTA > EJECUCIÓN POR ADMINISTRACIÓN DIRECTA - DIRECTIVA 10 | D68: 23. PROTECCION SOCIAL | E68: 2194989 | F68: 458 | G68: 2194989: MEJORAMIENTO DE LOS SERVICIOS EDUCATIVOS EN LA INSTITUCION EDUCATIVA SECUNDARIA DANTE NAVA DEL CENTRO POBLADO SANTA CRUZ DE PUNA AYLLU, DISTRITO DE PATAMBUCO, PROVINCIA DE SANDIA, REGION PUNO | H68: 133512 | I68: 0 | J68: 0 | K68: 0 | L68: =H68-I68 -> 133512 | M68: =H68-J68 -> 133512 | N68: =H68-K68 -> 133512 | O68: Administración directa | P68: =IF(H68=0,"Sin PIM",IF(ROUND(K68-H68,2)>=0,"Devengado total",IF(J68>0.005,"Comprometido",IF(I68>0.005,"Solo certificado","Sin certificar")))) -> Sin certificar | Q68: No registrado en cartera | R68: No registrado en cartera | S68: No registrado en cartera | T68: No registrado en cartera | V68: Meta sin número en Alex; asignado por CUI
A69: Gerencia de Infraestructura | B69: GERENCIA DE INFRAESTRUCTURA | C69: EJECUCIÓN POR ADMINISTRACIÓN DIRECTA > EJECUCIÓN POR ADMINISTRACIÓN DIRECTA - DIRECTIVA 17 | D69: 20. SALUD | E69: 2504553 | F69: 242 | G69: 2504553: MEJORAMIENTO DEL SERVICIO DE SALUD EN EL CENTRO DE SALUD YANAPATA DE LA MICRO RED COPANI, RED DE SALUD YUNGUYO, DISTRITO DE YUNGUYO - PROVINCIA DE YUNGUYO - DEPARTAMENTO DE PUNO | H69: 8256172 | I69: 7527846.9 | J69: 5727178.4 | K69: 4485721.8 | L69: =H69-I69 -> 728325.09 | M69: =H69-J69 -> 2528993.6 | N69: =H69-K69 -> 3770450.2 | O69: Administración directa / Equipamiento / Contrata / Personal/bienes/servicios | P69: =IF(H69=0,"Sin PIM",IF(ROUND(K69-H69,2)>=0,"Devengado total",IF(J69>0.005,"Comprometido",IF(I69>0.005,"Solo certificado","Sin certificar")))) -> Comprometido | Q69: 9468125 | R69: 933429 | S69: 6042788 | T69: 2500000
A70: Gerencia de Infraestructura | B70: GERENCIA DE INFRAESTRUCTURA | C70: EJECUCIÓN POR ADMINISTRACIÓN DIRECTA > EJECUCIÓN POR ADMINISTRACIÓN DIRECTA - DIRECTIVA 17 | D70: 20. SALUD | E70: 2470517 | F70: 237 | G70: 2470517: MEJORAMIENTO DE LOS SERVICIOS DE SALUD DEL CENTRO DE SALUD COPANI DE LA MICRO RED COPANI, RED DE SALUD YUNGUYO, DISTRITO DE COPANI - PROVINCIA DE YUNGUYO - DEPARTAMENTO DE PUNO | H70: 7374992 | I70: 7374802 | J70: 0 | K70: 0 | L70: =H70-I70 -> 190 | M70: =H70-J70 -> 7374992 | N70: =H70-K70 -> 7374992 | O70: Contrata | P70: =IF(H70=0,"Sin PIM",IF(ROUND(K70-H70,2)>=0,"Devengado total",IF(J70>0.005,"Comprometido",IF(I70>0.005,"Solo certificado","Sin certificar")))) -> Solo certificado | Q70: 8000000 | R70: 8258658 | S70: 10741348 | T70: 1075057
A71: Gerencia de Infraestructura | B71: GERENCIA DE INFRAESTRUCTURA | C71: EJECUCIÓN POR ADMINISTRACIÓN DIRECTA > EJECUCIÓN POR ADMINISTRACIÓN DIRECTA - DIRECTIVA 17 | D71: 20. SALUD | E71: 2357092 | F71: 228 | G71: 2357092: MEJORAMIENTO DE LA CAPACIDAD RESOLUTIVA DEL CENTRO DE SALUD COJATA I-4, DE LA MICRO RED COJATA, RED DE SALUD HUANCANE, DIRESA PUNO, DISTRITO DE COJATA - PROVINCIA DE HUANCANE - DEPARTAMENTO DE PUNO | H71: 6997430 | I71: 6787158.8 | J71: 5340502.4 | K71: 2630352.4 | L71: =H71-I71 -> 210271.19 | M71: =H71-J71 -> 1656927.6 | N71: =H71-K71 -> 4367077.6 | O71: Administración directa / Contrata / Personal/bienes/servicios / Equipamiento | P71: =IF(H71=0,"Sin PIM",IF(ROUND(K71-H71,2)>=0,"Devengado total",IF(J71>0.005,"Comprometido",IF(I71>0.005,"Solo certificado","Sin certificar")))) -> Comprometido | Q71: 8000000 | R71: 10256256 | S71: 15069544 | T71: 4478827
A72: Gerencia de Infraestructura | B72: GERENCIA DE INFRAESTRUCTURA | C72: EJECUCIÓN POR ADMINISTRACIÓN DIRECTA > EJECUCIÓN POR ADMINISTRACIÓN DIRECTA - DIRECTIVA 17 | D72: 20. SALUD | E72: 2494039 | F72: 241 | G72: 2494039: MEJORAMIENTO Y AMPLIACION DE LOS SERVICIOS DE SALUD EN EL ESTABLECIMIENTO DE SALUD UMACHIRI CATEGORIA I-2 DEL DISTRITO DE UMACHIRI - PROVINCIA DE MELGAR - DEPARTAMENTO DE PUNO | H72: 6688287 | I72: 6156914.2 | J72: 4915105.7 | K72: 3692512.7 | L72: =H72-I72 -> 531372.77 | M72: =H72-J72 -> 1773181.3 | N72: =H72-K72 -> 2995774.3 | O72: Administración directa / Equipamiento / Contrata / Personal/bienes/servicios | P72: =IF(H72=0,"Sin PIM",IF(ROUND(K72-H72,2)>=0,"Devengado total",IF(J72>0.005,"Comprometido",IF(I72>0.005,"Solo certificado","Sin certificar")))) -> Comprometido | Q72: 2822702 | R72: 65844 | S72: 0 | T72: 0
A73: Gerencia de Infraestructura | B73: GERENCIA DE INFRAESTRUCTURA | C73: EJECUCIÓN POR ADMINISTRACIÓN DIRECTA > EJECUCIÓN POR ADMINISTRACIÓN DIRECTA - DIRECTIVA 17 | D73: 20. SALUD | E73: 2290342 | F73: 221 | G73: 2290342: MEJORAMIENTO DE LA CAPACIDAD RESOLUTIVA DE LOS SERVICIOS DEL PUESTO DE SALUD I - 1 DEL CENTRO POBLADO DE CARI CARI DEL DISTRITO DE MAÑAZO - PROVINCIA DE PUNO - DEPARTAMENTO DE PUNO | H73: 3318026 | I73: 3154441.6 | J73: 2893837.6 | K73: 2243366.7 | L73: =H73-I73 -> 163584.43 | M73: =H73-J73 -> 424188.43 | N73: =H73-K73 -> 1074659.3 | O73: Administración directa / Equipamiento / Contrata / Expediente técnico / Personal/bienes/servicios | P73: =IF(H73=0,"Sin PIM",IF(ROUND(K73-H73,2)>=0,"Devengado total",IF(J73>0.005,"Comprometido",IF(I73>0.005,"Solo certificado","Sin certificar")))) -> Comprometido | Q73: 821892 | R73: 47336 | S73: 0 | T73: 0
A74: Gerencia de Infraestructura | B74: GERENCIA DE INFRAESTRUCTURA | C74: EJECUCIÓN POR ADMINISTRACIÓN DIRECTA > EJECUCIÓN POR ADMINISTRACIÓN DIRECTA - DIRECTIVA 17 | D74: 20. SALUD | E74: 2451529 | F74: 235 | G74: 2451529: MEJORAMIENTO DEL SERVICIO DE SALUD EN EL CENTRO DE SALUD PILCUYO DE LA MICRORED PILCUYO, RED DE SALUD EL COLLAO, DEL DISTRITO DE PILCUYO - PROVINCIA DE EL COLLAO - DEPARTAMENTO DE PUNO | H74: 0 | I74: 0 | J74: 0 | K74: 0 | L74: =H74-I74 -> 0 | M74: =H74-J74 -> 0 | N74: =H74-K74 -> 0 | O74: Contrata | P74: =IF(H74=0,"Sin PIM",IF(ROUND(K74-H74,2)>=0,"Devengado total",IF(J74>0.005,"Comprometido",IF(I74>0.005,"Solo certificado","Sin certificar")))) -> Sin PIM | Q74: 12571000 | R74: 5987564 | S74: 16094501 | T74: 22576094
A75: Gerencia de Infraestructura | B75: GERENCIA DE INFRAESTRUCTURA | C75: EJECUCIÓN POR ADMINISTRACIÓN DIRECTA > EJECUCIÓN POR ADMINISTRACIÓN DIRECTA - DIRECTIVA 17 | D75: 22. EDUCACION | E75: 2411336 | F75: 35 | G75: 2411336: MEJORAMIENTO SERVICIO INTEGRAL DE LA INSTITUCION EDUCATIVA SECUNDARIA INDUSTRIAL PERU BIRF DISTRITO DE SAN MIGUEL - PROVINCIA DE SAN ROMAN - DEPARTAMENTO DE PUNO | H75: 21914154 | I75: 21776068 | J75: 20527324 | K75: 15564867 | L75: =H75-I75 -> 138085.94 | M75: =H75-J75 -> 1386829.9 | N75: =H75-K75 -> 6349286.6 | O75: Administración directa / Equipamiento / Contrata / Personal/bienes/servicios / Laudos arbitrales | P75: =IF(H75=0,"Sin PIM",IF(ROUND(K75-H75,2)>=0,"Devengado total",IF(J75>0.005,"Comprometido",IF(I75>0.005,"Solo certificado","Sin certificar")))) -> Comprometido | Q75: 11955231 | R75: 2500000 | S75: 3884089 | T75: 0
A76: Gerencia de Infraestructura | B76: GERENCIA DE INFRAESTRUCTURA | C76: EJECUCIÓN POR ADMINISTRACIÓN DIRECTA > EJECUCIÓN POR ADMINISTRACIÓN DIRECTA - DIRECTIVA 17 | D76: 22. EDUCACION | E76: 2284935 | F76: 25 | G76: 2284935: MEJORAMIENTO DEL SERVICIO EDUCATIVO EN LA IES POLITECNICO REGIONAL LOS ANDES, DISTRITO DE JULIACA, PROVINCIA DE SAN ROMAN - PUNO | H76: 22276780 | I76: 17912911 | J76: 17718757 | K76: 15417466 | L76: =H76-I76 -> 4363868.8 | M76: =H76-J76 -> 4558023.3 | N76: =H76-K76 -> 6859314 | O76: Administración directa / Contrata / Personal/bienes/servicios / Equipamiento | P76: =IF(H76=0,"Sin PIM",IF(ROUND(K76-H76,2)>=0,"Devengado total",IF(J76>0.005,"Comprometido",IF(I76>0.005,"Solo certificado","Sin certificar")))) -> Comprometido | Q76: 15800000 | R76: 14789542 | S76: 15918407 | T76: 10295229
A77: Gerencia de Infraestructura | B77: GERENCIA DE INFRAESTRUCTURA | C77: EJECUCIÓN POR ADMINISTRACIÓN DIRECTA > EJECUCIÓN POR ADMINISTRACIÓN DIRECTA - DIRECTIVA 17 | D77: 22. EDUCACION | E77: 2357330 | F77: 229 | G77: 2357330: MEJORAMIENTO DEL SERVICIO EDUCATIVO DE LAS CARRERAS DE PRODUCCION AGROPECUARIA, MECANICA DE PRODUCCION, COMPUTACION E INFORMATICA, ENFERMERIA TECNICA EN EL INSTITUTO SUPERIOR TECNOLOGICO PUBLICO DE HUANCANE DISTRITO DE HUANCANE - PROVINCIA DE HUANCANE - DEPARTAMENTO DE PUNO | H77: 17354707 | I77: 17083718 | J77: 13323232 | K77: 8610007.7 | L77: =H77-I77 -> 270988.58 | M77: =H77-J77 -> 4031474.9 | N77: =H77-K77 -> 8744699.3 | O77: Administración directa / Equipamiento / Contrata / Personal/bienes/servicios | P77: =IF(H77=0,"Sin PIM",IF(ROUND(K77-H77,2)>=0,"Devengado total",IF(J77>0.005,"Comprometido",IF(I77>0.005,"Solo certificado","Sin certificar")))) -> Comprometido | Q77: 12500000 | R77: 4806839 | S77: 753613 | T77: 0
A78: Gerencia de Infraestructura | B78: GERENCIA DE INFRAESTRUCTURA | C78: EJECUCIÓN POR ADMINISTRACIÓN DIRECTA > EJECUCIÓN POR ADMINISTRACIÓN DIRECTA - DIRECTIVA 17 | D78: 22. EDUCACION | E78: 2357322 | F78: 30 | G78: 2357322: MEJORAMIENTO SERVICIO EDUCATIVO EN LA IES. 32 MARIANO H. CORNEJO DE LA LOCALIDAD DE JULIACA - DISTRITO DE JULIACA - PROVINCIA DE SAN ROMAN - REGION PUNO | H78: 19795501 | I78: 19793412 | J78: 18134195 | K78: 14545766 | L78: =H78-I78 -> 2089.28 | M78: =H78-J78 -> 1661306.3 | N78: =H78-K78 -> 5249734.8 | O78: Administración directa / Equipamiento / Contrata / Personal/bienes/servicios | P78: =IF(H78=0,"Sin PIM",IF(ROUND(K78-H78,2)>=0,"Devengado total",IF(J78>0.005,"Comprometido",IF(I78>0.005,"Solo certificado","Sin certificar")))) -> Comprometido | Q78: 9609000 | R78: 897867 | S78: 6124874 | T78: 0
A79: Gerencia de Infraestructura | B79: GERENCIA DE INFRAESTRUCTURA | C79: EJECUCIÓN POR ADMINISTRACIÓN DIRECTA > EJECUCIÓN POR ADMINISTRACIÓN DIRECTA - DIRECTIVA 17 | D79: 22. EDUCACION | E79: 2385673 | F79: 33 | G79: 2385673: MEJORAMIENTO DEL SERVICIO EDUCATIVO DE LA I.E.S. LAS MERCEDES DE LA CIUDAD DE JULIACA - DISTRITO DE JULIACA - PROVINCIA DE SAN ROMAN - DEPARTAMENTO DE PUNO | H79: 17241964 | I79: 17144705 | J79: 14900492 | K79: 11639796 | L79: =H79-I79 -> 97259.44 | M79: =H79-J79 -> 2341471.6 | N79: =H79-K79 -> 5602167.7 | O79: Administración directa / Contrata / Personal/bienes/servicios / Equipamiento | P79: =IF(H79=0,"Sin PIM",IF(ROUND(K79-H79,2)>=0,"Devengado total",IF(J79>0.005,"Comprometido",IF(I79>0.005,"Solo certificado","Sin certificar")))) -> Comprometido | Q79: 8016014 | R79: 10000000 | S79: 1057112 | T79: 2541629
A80: Gerencia de Infraestructura | B80: GERENCIA DE INFRAESTRUCTURA | C80: EJECUCIÓN POR ADMINISTRACIÓN DIRECTA > EJECUCIÓN POR ADMINISTRACIÓN DIRECTA - DIRECTIVA 17 | D80: 22. EDUCACION | E80: 2585543 | F80: 161 | G80: 2585543: MEJORAMIENTO Y AMPLIACION DEL SERVICIO DE EDUCACION SUPERIOR TECNOLOGICA EN EL INSTITUTO DE EDUCACION SUPERIOR TECNOLOGICO PUBLICO ACORA DEL DISTRITO DE ACORA DE LA PROVINCIA DE PUNO DEL DEPARTAMENTO DE PUNO | H80: 15380884 | I80: 14270657 | J80: 11275907 | K80: 9463521.5 | L80: =H80-I80 -> 1110226.8 | M80: =H80-J80 -> 4104977.3 | N80: =H80-K80 -> 5917362.5 | O80: Administración directa / Equipamiento / Contrata / Personal/bienes/servicios | P80: =IF(H80=0,"Sin PIM",IF(ROUND(K80-H80,2)>=0,"Devengado total",IF(J80>0.005,"Comprometido",IF(I80>0.005,"Solo certificado","Sin certificar")))) -> Comprometido | Q80: 6000000 | R80: 3456765 | S80: 1108030 | T80: 0
A81: Gerencia de Infraestructura | B81: GERENCIA DE INFRAESTRUCTURA | C81: EJECUCIÓN POR ADMINISTRACIÓN DIRECTA > EJECUCIÓN POR ADMINISTRACIÓN DIRECTA - DIRECTIVA 17 | D81: 22. EDUCACION | E81: 2535611 | F81: 247 | G81: 2535611: MEJORAMIENTO Y AMPLIACION DEL SERVICIO DE EDUCACION SUPERIOR TECNOLOGICO PUBLICO EN EL INSTITUTO ANDRES AVELINO CACERES DISTRITO DE PUTINA - PROVINCIA DE SAN ANTONIO DE PUTINA - DEPARTAMENTO DE PUNO | H81: 9666000 | I81: 9191703.8 | J81: 6884607.5 | K81: 5594991.1 | L81: =H81-I81 -> 474296.17 | M81: =H81-J81 -> 2781392.5 | N81: =H81-K81 -> 4071008.9 | O81: Administración directa / Contrata / Personal/bienes/servicios | P81: =IF(H81=0,"Sin PIM",IF(ROUND(K81-H81,2)>=0,"Devengado total",IF(J81>0.005,"Comprometido",IF(I81>0.005,"Solo certificado","Sin certificar")))) -> Comprometido | Q81: 7546000 | R81: 1410563 | S81: 1509243 | T81: 0
A82: Gerencia de Infraestructura | B82: GERENCIA DE INFRAESTRUCTURA | C82: EJECUCIÓN POR ADMINISTRACIÓN DIRECTA > EJECUCIÓN POR ADMINISTRACIÓN DIRECTA - DIRECTIVA 17 | D82: 22. EDUCACION | E82: 2538950 | F82: 39 | G82: 2538950: MEJORAMIENTO DEL SERVICIO EDUCATIVO DEL NIVEL PRIMARIO DE LA I.E. 71008 EN EL DISTRITO DE LAMPA - PROVINCIA DE LAMPA - DEPARTAMENTO DE PUNO | H82: 6765264 | I82: 6659441.2 | J82: 5339669.8 | K82: 4177875.5 | L82: =H82-I82 -> 105822.81 | M82: =H82-J82 -> 1425594.2 | N82: =H82-K82 -> 2587388.5 | O82: Administración directa / Equipamiento / Contrata / Personal/bienes/servicios | P82: =IF(H82=0,"Sin PIM",IF(ROUND(K82-H82,2)>=0,"Devengado total",IF(J82>0.005,"Comprometido",IF(I82>0.005,"Solo certificado","Sin certificar")))) -> Comprometido | Q82: No registrado en cartera | R82: No registrado en cartera | S82: No registrado en cartera | T82: No registrado en cartera
A83: Gerencia de Infraestructura | B83: GERENCIA DE INFRAESTRUCTURA | C83: EJECUCIÓN POR ADMINISTRACIÓN DIRECTA > EJECUCIÓN POR ADMINISTRACIÓN DIRECTA - DIRECTIVA 17 | D83: 22. EDUCACION | E83: 2289661 | F83: 26 | G83: 2289661: MEJORAMIENTO DE LOS SERVICIOS EDUCATIVOS EN LA I.E.S. DOS DE MAYO DE CARACOTO, DISTRITO DE CARACOTO - SAN ROMAN - PUNO | H83: 4291327 | I83: 4093667 | J83: 4092925.7 | K83: 3891386.8 | L83: =H83-I83 -> 197659.95 | M83: =H83-J83 -> 198401.33 | N83: =H83-K83 -> 399940.21 | O83: Administración directa / Contrata / Equipamiento / Personal/bienes/servicios | P83: =IF(H83=0,"Sin PIM",IF(ROUND(K83-H83,2)>=0,"Devengado total",IF(J83>0.005,"Comprometido",IF(I83>0.005,"Solo certificado","Sin certificar")))) -> Comprometido | Q83: No registrado en cartera | R83: No registrado en cartera | S83: No registrado en cartera | T83: No registrado en cartera
A84: Gerencia de Infraestructura | B84: GERENCIA DE INFRAESTRUCTURA | C84: EJECUCIÓN POR ADMINISTRACIÓN DIRECTA > EJECUCIÓN POR ADMINISTRACIÓN DIRECTA - DIRECTIVA 17 | D84: 22. EDUCACION | E84: 2590087 | F84: 41 | G84: 2590087: MEJORAMIENTO DEL SERVICIO DE EDUCACION SECUNDARIA EN I.E. JOSE MARIA ARGUEDAS DISTRITO DE LLALLI DE LA PROVINCIA DE MELGAR DEL DEPARTAMENTO DE PUNO | H84: 5799805 | I84: 5459070.3 | J84: 4960247.3 | K84: 3888315.9 | L84: =H84-I84 -> 340734.7 | M84: =H84-J84 -> 839557.73 | N84: =H84-K84 -> 1911489.1 | O84: Administración directa / Contrata / Equipamiento / Personal/bienes/servicios | P84: =IF(H84=0,"Sin PIM",IF(ROUND(K84-H84,2)>=0,"Devengado total",IF(J84>0.005,"Comprometido",IF(I84>0.005,"Solo certificado","Sin certificar")))) -> Comprometido | Q84: No registrado en cartera | R84: No registrado en cartera | S84: No registrado en cartera | T84: No registrado en cartera
A85: Gerencia de Infraestructura | B85: GERENCIA DE INFRAESTRUCTURA | C85: EJECUCIÓN POR ADMINISTRACIÓN DIRECTA > EJECUCIÓN POR ADMINISTRACIÓN DIRECTA - DIRECTIVA 17 | D85: 22. EDUCACION | E85: 2417765 | F85: 36 | G85: 2417765: MEJORAMIENTO Y AMPLIACION DEL SERVICIOS DE EDUCACION BASICA EN EL NIVEL PRIMARIO DE LA IEP Nº 72169 TAMBILLO, IEP Nº 72175 TAYACCUCHO, IEP Nº 72188 QUETY, IEP Nº 72642 MALLCUAPO, IEP Nº 72749 CALASUCA DEL DISTRITO DE ITUATA - PROVINCIA DE CARABAYA - DEPARTAMENTO DE PUNO DISTRITO DE ITUATA - PROVINCIA DE CARABAYA - DEPARTAMENTO DE PUNO | H85: 4802506 | I85: 4376181.6 | J85: 4092158.6 | K85: 3250907.8 | L85: =H85-I85 -> 426324.38 | M85: =H85-J85 -> 710347.38 | N85: =H85-K85 -> 1551598.2 | O85: Administración directa / Contrata / Equipamiento / Personal/bienes/servicios | P85: =IF(H85=0,"Sin PIM",IF(ROUND(K85-H85,2)>=0,"Devengado total",IF(J85>0.005,"Comprometido",IF(I85>0.005,"Solo certificado","Sin certificar")))) -> Comprometido | Q85: 3770000 | R85: 876556 | S85: 4649244 | T85: 7795363
A86: Gerencia de Infraestructura | B86: GERENCIA DE INFRAESTRUCTURA | C86: EJECUCIÓN POR ADMINISTRACIÓN DIRECTA > EJECUCIÓN POR ADMINISTRACIÓN DIRECTA - DIRECTIVA 17 | D86: 22. EDUCACION | E86: 2417765 | F86: 311 | G86: 2417765: MEJORAMIENTO Y AMPLIACION DEL SERVICIOS DE EDUCACION BASICA EN EL NIVEL PRIMARIO DE LA IEP Nº 72169 TAMBILLO, IEP Nº 72175 TAYACCUCHO, IEP Nº 72188 QUETY, IEP Nº 72642 MALLCUAPO, IEP Nº 72749 CALASUCA DEL DISTRITO DE ITUATA - PROVINCIA DE CARABAYA - DEPARTAMENTO DE PUNO DISTRITO DE ITUATA - PROVINCIA DE CARABAYA - DEPARTAMENTO DE PUNO | H86: 4992699 | I86: 4276945.2 | J86: 4118772 | K86: 3252598.6 | L86: =H86-I86 -> 715753.79 | M86: =H86-J86 -> 873927.04 | N86: =H86-K86 -> 1740100.4 | O86: Administración directa / Contrata / Equipamiento / Personal/bienes/servicios | P86: =IF(H86=0,"Sin PIM",IF(ROUND(K86-H86,2)>=0,"Devengado total",IF(J86>0.005,"Comprometido",IF(I86>0.005,"Solo certificado","Sin certificar")))) -> Comprometido | Q86: 3770000 | R86: 876556 | S86: 4649244 | T86: 7795363
A87: Gerencia de Infraestructura | B87: GERENCIA DE INFRAESTRUCTURA | C87: EJECUCIÓN POR ADMINISTRACIÓN DIRECTA > EJECUCIÓN POR ADMINISTRACIÓN DIRECTA - DIRECTIVA 17 | D87: 22. EDUCACION | E87: 2606991 | F87: 306 | G87: 2606991: MEJORAMIENTO DEL SERVICIO DE EDUCACION INICIAL EN I.E. 69 DISTRITO DE ANTAUTA DE LA PROVINCIA DE MELGAR DEL DEPARTAMENTO DE PUNO | H87: 3853164 | I87: 3701445.6 | J87: 3685448.8 | K87: 3036070 | L87: =H87-I87 -> 151718.37 | M87: =H87-J87 -> 167715.24 | N87: =H87-K87 -> 817093.95 | O87: Administración directa / Contrata / Equipamiento / Personal/bienes/servicios | P87: =IF(H87=0,"Sin PIM",IF(ROUND(K87-H87,2)>=0,"Devengado total",IF(J87>0.005,"Comprometido",IF(I87>0.005,"Solo certificado","Sin certificar")))) -> Comprometido | Q87: No registrado en cartera | R87: No registrado en cartera | S87: No registrado en cartera | T87: No registrado en cartera
A88: Gerencia de Infraestructura | B88: GERENCIA DE INFRAESTRUCTURA | C88: EJECUCIÓN POR ADMINISTRACIÓN DIRECTA > EJECUCIÓN POR ADMINISTRACIÓN DIRECTA - DIRECTIVA 17 | D88: 22. EDUCACION | E88: 2649852 | F88: 181 | G88: 2649852: MEJORAMIENTO DEL SERVICIO DE EDUCACION INICIAL EN I.E. 325 DISTRITO DE PUNO DE LA PROVINCIA DE PUNO DEL DEPARTAMENTO DE PUNO | H88: 1142346 | I88: 911210.56 | J88: 703126.63 | K88: 18478.9 | L88: =H88-I88 -> 231135.44 | M88: =H88-J88 -> 439219.37 | N88: =H88-K88 -> 1123867.1 | O88: Administración directa / Contrata / Personal/bienes/servicios / Equipamiento | P88: =IF(H88=0,"Sin PIM",IF(ROUND(K88-H88,2)>=0,"Devengado total",IF(J88>0.005,"Comprometido",IF(I88>0.005,"Solo certificado","Sin certificar")))) -> Comprometido | Q88: 100000 | R88: 0 | S88: 959009 | T88: 0
A89: Gerencia de Infraestructura | B89: GERENCIA DE INFRAESTRUCTURA | C89: EJECUCIÓN POR ADMINISTRACIÓN DIRECTA > EJECUCIÓN POR ADMINISTRACIÓN DIRECTA - DIRECTIVA 17 | D89: 22. EDUCACION | E89: 2649858 | F89: 187 | G89: 2649858: MEJORAMIENTO DEL SERVICIO DE EDUCACION INICIAL EN I.E. EDUARDITOS DISTRITO DE PICHACANI DE LA PROVINCIA DE PUNO DEL DEPARTAMENTO DE PUNO | H89: 2361641 | I89: 1509241.4 | J89: 1501265.7 | K89: 1059463.8 | L89: =H89-I89 -> 852399.64 | M89: =H89-J89 -> 860375.28 | N89: =H89-K89 -> 1302177.2 | O89: Administración directa / Contrata / Equipamiento / Personal/bienes/servicios | P89: =IF(H89=0,"Sin PIM",IF(ROUND(K89-H89,2)>=0,"Devengado total",IF(J89>0.005,"Comprometido",IF(I89>0.005,"Solo certificado","Sin certificar")))) -> Comprometido | Q89: 100000 | R89: 45539 | S89: 0 | T89: 0
A90: Gerencia de Infraestructura | B90: GERENCIA DE INFRAESTRUCTURA | C90: EJECUCIÓN POR ADMINISTRACIÓN DIRECTA > EJECUCIÓN POR ADMINISTRACIÓN DIRECTA - DIRECTIVA 17 | D90: 22. EDUCACION | E90: 2411335 | F90: 307 | G90: 2411335: MEJORAMIENTO DEL SERVICIO EDUCATIVO EN LA I.E.S. SAN SALVADOR, - DISTRITO DE PUNO - PROVINCIA DE PUNO - DEPARTAMENTO DE PUNO | H90: 1272735 | I90: 1253656.9 | J90: 1253656.9 | K90: 1181486.1 | L90: =H90-I90 -> 19078.14 | M90: =H90-J90 -> 19078.14 | N90: =H90-K90 -> 91248.85 | O90: Administración directa / Contrata / Personal/bienes/servicios / Equipamiento | P90: =IF(H90=0,"Sin PIM",IF(ROUND(K90-H90,2)>=0,"Devengado total",IF(J90>0.005,"Comprometido",IF(I90>0.005,"Solo certificado","Sin certificar")))) -> Comprometido | Q90: 1216856 | R90: 370264 | S90: 0 | T90: 0
A91: Gerencia de Infraestructura | B91: GERENCIA DE INFRAESTRUCTURA | C91: EJECUCIÓN POR ADMINISTRACIÓN DIRECTA > EJECUCIÓN POR ADMINISTRACIÓN DIRECTA - DIRECTIVA 17 | D91: 22. EDUCACION | E91: 2651383 | F91: 333 | G91: 2651383.MEJORAMIENTO DEL SERVICIO DE EDUCACION INICIAL EN I.E. 941 DISTRITO DE CABANILLAS DE LA PROVINCIA DE SAN ROMAN DEL DEPARTAMENTO DE PUNO | H91: 919876 | I91: 340967.6 | J91: 242000 | K91: 7840.91 | L91: =H91-I91 -> 578908.4 | M91: =H91-J91 -> 677876 | N91: =H91-K91 -> 912035.09 | O91: Administración directa / Contrata / Personal/bienes/servicios / Equipamiento | P91: =IF(H91=0,"Sin PIM",IF(ROUND(K91-H91,2)>=0,"Devengado total",IF(J91>0.005,"Comprometido",IF(I91>0.005,"Solo certificado","Sin certificar")))) -> Comprometido | Q91: 903516 | R91: 919620 | S91: 268263 | T91: 0
A92: Gerencia de Infraestructura | B92: GERENCIA DE INFRAESTRUCTURA | C92: EJECUCIÓN POR ADMINISTRACIÓN DIRECTA > EJECUCIÓN POR ADMINISTRACIÓN DIRECTA - DIRECTIVA 17 | D92: 22. EDUCACION | E92: 2250396 | F92: 173 | G92: 2250396: INSTALACION DEL SERVICIO EDUCATIVO DEL NIVEL INICIAL ESCOLARIZADO CICLO II EN LA I.E.I N 707 DEL CENTRO POBLADO DE JACHOCCO HUARACO, DISTRITO ILAVE, PROVINCIA DE EL COLLAO - DEPARTAMENTO PUNO. | H92: 41720 | I92: 31883.37 | J92: 31883.37 | K92: 31883.37 | L92: =H92-I92 -> 9836.63 | M92: =H92-J92 -> 9836.63 | N92: =H92-K92 -> 9836.63 | O92: Contrata / Personal/bienes/servicios | P92: =IF(H92=0,"Sin PIM",IF(ROUND(K92-H92,2)>=0,"Devengado total",IF(J92>0.005,"Comprometido",IF(I92>0.005,"Solo certificado","Sin certificar")))) -> Comprometido | Q92: 120201 | R92: 0 | S92: 0 | T92: 0
A93: Gerencia de Infraestructura | B93: GERENCIA DE INFRAESTRUCTURA | C93: EJECUCIÓN POR ADMINISTRACIÓN DIRECTA > EJECUCIÓN POR ADMINISTRACIÓN DIRECTA - DIRECTIVA 17 | D93: 22. EDUCACION | E93: 2649805 | F93: 180 | G93: 2649805: MEJORAMIENTO DEL SERVICIO DE EDUCACION INICIAL EN I.E. 881 DISTRITO DE CABANILLA DE LA PROVINCIA DE LAMPA DEL DEPARTAMENTO DE PUNO | H93: 704972 | I93: 309066 | J93: 255972 | K93: 15770.09 | L93: =H93-I93 -> 395906 | M93: =H93-J93 -> 449000 | N93: =H93-K93 -> 689201.91 | O93: Administración directa / Contrata / Expediente técnico / Personal/bienes/servicios | P93: =IF(H93=0,"Sin PIM",IF(ROUND(K93-H93,2)>=0,"Devengado total",IF(J93>0.005,"Comprometido",IF(I93>0.005,"Solo certificado","Sin certificar")))) -> Comprometido | Q93: 100000 | R93: 0 | S93: 921923 | T93: 0
A94: Gerencia de Infraestructura | B94: GERENCIA DE INFRAESTRUCTURA | C94: EJECUCIÓN POR ADMINISTRACIÓN DIRECTA > EJECUCIÓN POR ADMINISTRACIÓN DIRECTA - DIRECTIVA 17 | D94: 22. EDUCACION | E94: 2627406 | F94: 83 | G94: 2627406: RENOVACION DE AMBIENTE COMPLEMENTARIO, AULA DE EDUCACION SUPERIOR PEDAGOGICA Y CERCO PERIMETRICO; ADQUISICION DE MOBILIARIO DE AULA DE EDUCACION SUPERIOR PEDAGOGICA; ADEMAS DE OTROS ACTIVOS EN EL(LA) INSTITUTO DE EDUCACION SUPERIOR PEDAGOGICA PUBLICO JULI DEL DISTRITO DE JULI, PROVINCIA CHUCUITO, DEPARTAMENTO PUNO | H94: 61203 | I94: 0 | J94: 0 | K94: 0 | L94: =H94-I94 -> 61203 | M94: =H94-J94 -> 61203 | N94: =H94-K94 -> 61203 | O94: Administración directa | P94: =IF(H94=0,"Sin PIM",IF(ROUND(K94-H94,2)>=0,"Devengado total",IF(J94>0.005,"Comprometido",IF(I94>0.005,"Solo certificado","Sin certificar")))) -> Sin certificar | Q94: 61203 | R94: 0 | S94: 0 | T94: 0
A95: Gerencia de Infraestructura | B95: GERENCIA DE INFRAESTRUCTURA | C95: EJECUCIÓN POR ADMINISTRACIÓN DIRECTA > EJECUCIÓN POR ADMINISTRACIÓN DIRECTA - DIRECTIVA 17 | D95: 15. TRANSPORTE | E95: 2456529 | F95: 110 | G95: 2456529.MEJORAMIENTO DE LA CARRETERA PU 147, EMP. PE-34I JIPATA - EMP. PE-34I MOHO, DISTRITO DE MOHO - PROVINCIA DE MOHO - DEPARTAMENTO DE PUNO | H95: 23143575 | I95: 22275711 | J95: 19031849 | K95: 12059018 | L95: =H95-I95 -> 867864.16 | M95: =H95-J95 -> 4111726.2 | N95: =H95-K95 -> 11084557 | O95: Administración directa / Contrata / Personal/bienes/servicios | P95: =IF(H95=0,"Sin PIM",IF(ROUND(K95-H95,2)>=0,"Devengado total",IF(J95>0.005,"Comprometido",IF(I95>0.005,"Solo certificado","Sin certificar")))) -> Comprometido | Q95: 15500800 | R95: 4458489 | S95: 450011 | T95: 0
A96: Gerencia de Infraestructura | B96: GERENCIA DE INFRAESTRUCTURA | C96: EJECUCIÓN POR ADMINISTRACIÓN DIRECTA > EJECUCIÓN POR ADMINISTRACIÓN DIRECTA - DIRECTIVA 17 | D96: 15. TRANSPORTE | E96: 2343199 | F96: 103 | G96: 2343199: MEJORAMIENTO DE LA CARRETERA (EMP 34B) AZANGARO - (EMP PU-102) JILA PURINA DE LOS DISTRITO DE AZANGARO - DISTRITO DE TIRAPATA - PROVINCIA DE AZANGARO - REGION PUNO | H96: 14991498 | I96: 14685003 | J96: 13584705 | K96: 11502167 | L96: =H96-I96 -> 306495.03 | M96: =H96-J96 -> 1406792.9 | N96: =H96-K96 -> 3489331.3 | O96: Administración directa / Contrata / Personal/bienes/servicios | P96: =IF(H96=0,"Sin PIM",IF(ROUND(K96-H96,2)>=0,"Devengado total",IF(J96>0.005,"Comprometido",IF(I96>0.005,"Solo certificado","Sin certificar")))) -> Comprometido | Q96: 12491498 | R96: 632388 | S96: 41870 | T96: 0
